Workbook
Name \A: [1]A!$D$9:$D$53
Name \p: #REF!
Name _: '[2]#¡REF'!#REF!
Name __?EL: '[3]#¡REF'!#REF!
Name __?EL_1: '[3]#¡REF'!#REF!
Name __?ELCEN: '[3]#¡REF'!#REF!
Name __?ELCEN_1: '[3]#¡REF'!#REF!
Name __?ELECSURE: '[3]#¡REF'!#REF!
Name __?ELECSURE_1: '[3]#¡REF'!#REF!
Name __?ELECSURME: '[3]#¡REF'!#REF!
Name __?ELECSURME_1: '[3]#¡REF'!#REF!
Name __?ELECT: '[3]#¡REF'!#REF!
Name __?ELECT_1: '[3]#¡REF'!#REF!
Name __?ELECTROL: '[3]#¡REF'!#REF!
Name __?ELECTROL_1: '[3]#¡REF'!#REF!
Name __?ELEORIE: '[3]#¡REF'!#REF!
Name __?ELEORIE_1: '[3]#¡REF'!#REF!
Name __?ELNO: '[3]#¡REF'!#REF!
Name __?ELNO_1: '[3]#¡REF'!#REF!
Name __?ELSURE: '[3]#¡REF'!#REF!
Name __?ELSURE_1: '[3]#¡REF'!#REF!
Name __?HIDRAND: '[3]#¡REF'!#REF!
Name __?HIDRAND_1: '[3]#¡REF'!#REF!
Name __?S: '[3]#¡REF'!#REF!
Name __?S_1: '[3]#¡REF'!#REF!
Name ______________REV3: [4]DATOS!$A$3:$E$22
Name ______________SOL1: #REF!
Name _____________REV3: [4]DATOS!$A$3:$E$22
Name _____________SOL1: #REF!
Name ____________PPA1: #REF!
Name ____________REV3: [4]DATOS!$A$3:$E$22
Name ____________Rp12: [5]Datos!$G$17
Name ____________Sec13: [5]Datos!$G$12
Name ____________Sec77: [5]Datos!$G$8
Name ____________SOL1: #REF!
Name ___________Pbs1: [5]Datos!$E$6
Name ___________PPA1: #REF!
Name ___________REV3: [4]DATOS!$A$3:$E$22
Name ___________Rp12: [5]Datos!$G$17
Name ___________Sec13: [5]Datos!$G$12
Name ___________Sec77: [5]Datos!$G$8
Name ___________SOL1: #REF!
Name __________HED2: #REF!
Name __________Pbs1: [5]Datos!$E$6
Name __________PPA1: #REF!
Name __________REV3: [6]DATOS!$A$3:$E$22
Name __________Rp12: [5]Datos!$G$17
Name __________Sec01: [5]Datos!$G$4
Name __________sec02: [7]Datos!$D$27
Name __________sec03: [8]Datos!$D$28
Name __________sec04: [7]Datos!$D$29
Name __________sec05: [7]Datos!$D$30
Name __________Sec13: [5]Datos!$G$12
Name __________Sec77: [5]Datos!$G$8
Name __________SOL1: #REF!
Name _________HED2: #REF!
Name _________Pbs1: [5]Datos!$E$6
Name _________PPA1: #REF!
Name _________REV3: [6]DATOS!$A$3:$E$22
Name _________Rp12: [5]Datos!$G$17

Sheet RESUMEN TOTAL
B2: RESUMEN GENERAL DEL PRESUPUESTO (OBRA Y EXPEDIENTE TÉCNICO)
B4: PROYECTO | C4: : | D4: AMPLIACIÓN DEL SERVICIO DE ENERGÍA ELÉCTRICA EN LA PROVINCIA DEL SANTA Y EN EL DISTRITO DE PAMPAROMAS – DEPARTAMENTO DE ANCASH
B5: DEPARTAMENTO | C5: : | D5: ANCASH
J6: Fecha: 30-May-2022
J7: T.C. (S/ /US$): 3,683
E9: CONTRACTUAL | H9: ESTUDIO DEFINITIVO
B10: ITEM | D10: Descripcion | E10: Total Sin I.G.V. (S/.) | F10: I.G.V. | G10: TOTAL S/. | H10: Total Sin I.G.V. (S/.) | I10: I.G.V. | J10: TOTAL S/.
B12: A | D12: COSTO DE OBRA | E12: =+'RES-GRAL OBRA'!G15 -> 2658762.1 | F12: =+'RES-GRAL OBRA'!G16 -> 478577.18 | G12: =+SUM(E12:F12) -> 3137339.3 | H12: =+'RES-GRAL OBRA'!H15 -> 3055209.1 | I12: =+'RES-GRAL OBRA'!H16 -> 549937.63 | J12: =+SUM(H12:I12) -> 3605146.7
B14: B | D14: COSTO DE EXPEDIENTE TÉCNICO | E14: 200121.88 | F14: 36021.94 | G14: =+SUM(E14:F14) -> 236143.82 | H14: =+E14 -> 200121.88 | I14: =+F14 -> 36021.94 | J14: =+SUM(H14:I14) -> 236143.82
G15: =+SUM(E15:F15) -> 0
D16: TOTAL | E16: =E12+E14 -> 2858884 | F16: =F12+F14 -> 514599.12 | G16: =G12+G14 -> 3373483.1 | H16: =H12+H14 -> 3255330.9 | I16: =I12+I14 -> 585959.57 | J16: =J12+J14 -> 3841290.5
G18: % DE INCIDENCIA SOBRE EL CONTRACTUAL | J18: =ROUND((J16/G16),4) -> 1.1387
J21: =+J12/G12 -> 1.1491096

Sheet RES-GRAL OBRA
B2: RESUMEN GENERAL PRESUPUESTO DE OBRA
B4: PROYECTO | E4: : | F4: AMPLIACIÓN DEL SERVICIO DE ENERGÍA ELÉCTRICA EN LA PROVINCIA DEL SANTA Y EN EL DISTRITO DE PAMPAROMAS – DEPARTAMENTO DE ANCASH
B5: DEPARTAMENTO | E5: : | F5: ANCASH | H5: Fecha: 30-May-2022
H6: T.C. (S/ /US$): 3,683
B7: ITEM | C7: DESCRIPCION | G7: PRESUPUESTO CONTRATO | H7: PRESUPUESTO ESTUDIO DEFINITIVO | I7: ADICIONALES | K7: DEDUCTIVOS
I8: MAYORES METRADOS | J8: PARTIDAS NUEVAS | K8: MENOR METRADO | L8: DEDUCTIVO VINCULANTE
B9: A | D9: SUMINISTROS DE MATERIALES | G9: =+'RES-LP'!G12+'RES-RP'!G12+'RES-RS'!G12+'RES- SFV'!G12 -> 1356698.6 | H9: =+'RES-LP'!H12+'RES-RP'!H12+'RES-RS'!H12+'RES- SFV'!H12 -> 1559314.8 | I9: =+'RES-LP'!I12+'RES-RP'!I12+'RES-RS'!I12+'RES- SFV'!I12 -> 165194.76 | J9: =+'RES-LP'!J12+'RES-RP'!J12+'RES-RS'!J12+'RES- SFV'!J12 -> 387288.28 | K9: =+'RES-LP'!K12+'RES-RP'!K12+'RES-RS'!K12+'RES- SFV'!K12 -> 349866.84 | L9: =+'RES-LP'!L12+'RES-RP'!L12+'RES-RS'!L12+'RES- SFV'!L12 -> 196109.06
B10: B | D10: MONTAJE ELECTROMECANICO | G10: =+'RES-LP'!G13+'RES-RP'!G13+'RES-RS'!G13+'RES- SFV'!G13 -> 872009.12 | H10: =+'RES-LP'!H13+'RES-RP'!H13+'RES-RS'!H13+'RES- SFV'!H13 -> 1009873.9 | I10: =+'RES-LP'!I13+'RES-RP'!I13+'RES-RS'!I13+'RES- SFV'!I13 -> 124806.45 | J10: =+'RES-LP'!J13+'RES-RP'!J13+'RES-RS'!J13+'RES- SFV'!J13 -> 116126.84 | K10: =+'RES-LP'!K13+'RES-RP'!K13+'RES-RS'!K13+'RES- SFV'!K13 -> 103068.48 | L10: =+'RES-LP'!L13+'RES-RP'!L13+'RES-RS'!L13+'RES- SFV'!L13 -> 81998.26
B11: C | D11: TRANSPORTE DE MATERIALES | G11: =+'RES-LP'!G14+'RES-RP'!G14+'RES-RS'!G14+'RES- SFV'!G14 -> 121683.17 | H11: =+'RES-LP'!H14+'RES-RP'!H14+'RES-RS'!H14+'RES- SFV'!H14 -> 131667.96 | I11: =+'RES-LP'!I14+'RES-RP'!I14+'RES-RS'!I14+'RES- SFV'!I14 -> 16270.73 | J11: =+'RES-LP'!J14+'RES-RP'!J14+'RES-RS'!J14+'RES- SFV'!J14 -> 19445.26 | K11: =+'RES-LP'!K14+'RES-RP'!K14+'RES-RS'!K14+'RES- SFV'!K14 -> 25731.2 | L11: =+'RES-LP'!L14+'RES-RP'!L14+'RES-RS'!L14+'RES- SFV'!L14 -> 16682.92
B12: D | D12: COSTO DIRECTO ( C.D. ) | G12: =ROUND(SUM(G9:G11),2) -> 2350390.9 | H12: =ROUND(SUM(H9:H11),2) -> 2700856.7 | I12: =ROUND(SUM(I9:I11),2) -> 306271.94 | J12: =ROUND(SUM(J9:J11),2) -> 522860.38 | K12: =ROUND(SUM(K9:K11),2) -> 478666.52 | L12: =ROUND(SUM(L9:L11),2) -> 294790.24
B13: E | D13: GASTOS GENERALES (10.12%) | G13: =ROUND(G12*10.12%,2) -> 237859.55 | H13: =ROUND(H12*10.12%,2) -> 273326.69 | I13: =ROUND(I12*10.12%,2) -> 30994.72 | J13: =ROUND(J12*10.12%,2) -> 52913.47 | K13: =ROUND(K12*10.12%,2) -> 48441.05 | L13: =ROUND(L12*10.12%,2) -> 29832.77 | M13: =+H13-G13 -> 35467.14
B14: F | D14: UTILIDADES (3%) | G14: =ROUND(G12*3%,2) -> 70511.73 | H14: =ROUND(H12*3%,2) -> 81025.7 | I14: =ROUND(I12*3%,2) -> 9188.16 | J14: =ROUND(J12*3%,2) -> 15685.81 | K14: =ROUND(K12*3%,2) -> 14360 | L14: =ROUND(L12*3%,2) -> 8843.71 | M14: =+H14-G14 -> 10513.97
D15: SUB-TOTAL SIN I.G.V. (S/.) | G15: =G14+G13+G12 -> 2658762.1 | H15: =H14+H13+H12 -> 3055209.1 | I15: =I14+I13+I12 -> 346454.82 | J15: =J14+J13+J12 -> 591459.66 | K15: =K14+K13+K12 -> 541467.57 | L15: =L14+L13+L12 -> 333466.72 | M15: =+H15-G15 -> 396446.92
D16: IMPUESTO GENERAL A LAS VENTAS IGV (18%) | G16: =ROUND(G15*0.18,2) -> 478577.18 | H16: =ROUND(H15*0.18,2) -> 549937.63 | I16: =ROUND(I15*0.18,2) -> 62361.87 | J16: =ROUND(J15*0.18,2) -> 106462.74 | K16: =ROUND(K15*0.18,2) -> 97464.16 | L16: =ROUND(L15*0.18,2) -> 60024.01
D17: COSTO TOTAL (Incluye I.G.V.) S/. | G17: =G15+G16 -> 3137339.3 | H17: =H15+H16 -> 3605146.7 | I17: =I15+I16 -> 408816.69 | J17: =J15+J16 -> 697922.4 | K17: =K15+K16 -> 638931.73 | L17: =L15+L16 -> 393490.73
D19: INCIDENCIA RESPECTO AL CONTRACTUAL % | H19: =+ROUND(H17/$G$17,4) -> 1.1491 | I19: =+ROUND(I17/$G$17,4) -> 0.1303 | J19: =+ROUND(J17/$G$17,4) -> 0.2225 | K19: =+ROUND(K17/$G$17,4) -> 0.2037 | L19: =+ROUND(L17/$G$17,4) -> 0.1254
H23: =+G17+I17+J17-K17 -> 3605146.7 | I23: =+H17-G17 -> 467807.37 | J23: =+I17+J17-K17 -> 467807.36
H24: =+H17-H23 -> 0.0099999998 | J24: =+I23-J23 -> 0.01

Sheet RG
B2: RESUMEN DE PRESUPUESTO CONTRATCUAL REPLANTEO
B4: PROYECTO | E4: : | F4: CREACIÓN INSTALACIÓN DEL SUBSISTEMA DE DISTRIBUCIÓN PRIMARIA 10-22,9 KV Y SUBSISTEMA DE DISTRIBUCIÓN SECUNDARIA 380/220 V E INSTALACIÓN DE ALUMBRADO PÚBLICO LUCAS CUTIVALU DEL DISTRITO DE MIGUEL CHECA - PROVINCIA DE SULLANA - DEPARTAMENTO DE PIURA
B5: DEPARTAMENTOS | E5: : | F5: PIURA
B6: ITEM | C6: DESCRIPCION | G6: LINEAS PRIMARIAS | I6: REDES PRIMARIAS | K6: REDES SECUNDARIAS | M6: TOTAL
G7: PRESUPUESTO CONTRATO | H7: PRESUPUESTO REPLANTEO | I7: PRESUPUESTO CONTRATO | J7: PRESUPUESTO REPLANTEO | K7: PRESUPUESTO CONTRATO | L7: PRESUPUESTO REPLANTEO | M7: PRESUPUESTO CONTRATO | N7: PRESUPUESTO REPLANTEO
B9: A | D9: SUMINISTROS DE MATERIALES | G9: =+#REF! -> #REF! | H9: =+#REF! -> #REF! | I9: =+#REF! -> #REF! | J9: =+#REF! -> #REF! | K9: =+'RES-RS'!G12 -> 301377.1 | L9: =+'RES-RS'!H12 -> 420410.61 | M9: =+G9+I9+K9 -> #REF! | N9: =+H9+J9+L9 -> #REF!
B10: B | D10: MONTAJE ELECTROMECANICO | G10: =+#REF! -> #REF! | H10: =+#REF! -> #REF! | I10: =+#REF! -> #REF! | J10: =+#REF! -> #REF! | K10: =+'RES-RS'!G13 -> 273560.14 | L10: =+'RES-RS'!H13 -> 323016.92 | M10: =+G10+I10+K10 -> #REF! | N10: =+H10+J10+L10 -> #REF!
B11: C | D11: TRANSPORTE DE MATERIALES | G11: =+#REF! -> #REF! | H11: =+#REF! -> #REF! | I11: =+#REF! -> #REF! | J11: =+#REF! -> #REF! | K11: =+'RES-RS'!G14 -> 39859.51 | L11: =+'RES-RS'!H14 -> 46723.13 | M11: =+G11+I11+K11 -> #REF! | N11: =+H11+J11+L11 -> #REF!
B13: D | D13: COSTO DIRECTO ( C.D. ) | G13: =SUM(G9:G12) -> #REF! | H13: =SUM(H9:H12) -> #REF! | I13: =SUM(I9:I12) -> #REF! | J13: =SUM(J9:J12) -> #REF! | K13: =SUM(K9:K12) -> 614796.75 | L13: =SUM(L9:L12) -> 790150.66 | M13: =SUM(M9:M12) -> #REF! | N13: =SUM(N9:N12) -> #REF!
B15: E | D15: GASTOS GENERALES (30.52%) | G15: =ROUND(G13*30.52%,2) -> #REF! | H15: =ROUND(H13*30.52%,2) -> #REF! | I15: =ROUND(I13*30.52%,2) -> #REF! | J15: =ROUND(J13*30.52%,2) -> #REF! | K15: =ROUND(K13*30.52%,2) -> 187635.97 | L15: =ROUND(L13*30.52%,2) -> 241153.98 | M15: =ROUND(M13*30.52%,2) -> #REF! | N15: =ROUND(N13*30.52%,2) -> #REF!
B16: F | D16: UTILIDADES (4.01%) | G16: =ROUND(G13*4.01%,2) -> #REF! | H16: =ROUND(H13*4.01%,2) -> #REF! | I16: =ROUND(I13*4.01%,2) -> #REF! | J16: =ROUND(J13*4.01%,2) -> #REF! | K16: =ROUND(K13*4.01%,2) -> 24653.35 | L16: =ROUND(L13*4.01%,2) -> 31685.04 | M16: =ROUND(M13*4.01%,2) -> #REF! | N16: =ROUND(N13*4.01%,2) -> #REF!
D19: SUB-TOTAL SIN I.G.V. (S/.) | G19: =G16+G15+G13 -> #REF! | H19: =H16+H15+H13 -> #REF! | I19: =I16+I15+I13 -> #REF! | J19: =J16+J15+J13 -> #REF! | K19: =K16+K15+K13 -> 827086.07 | L19: =L16+L15+L13 -> 1062989.7 | M19: =M16+M15+M13 -> #REF! | N19: =N16+N15+N13 -> #REF!
D21: IMPUESTO GENERAL A LAS VENTAS IGV (18%) | G21: =ROUND(G19*0.18,2) -> #REF! | H21: =ROUND(H19*0.18,2) -> #REF! | I21: =ROUND(I19*0.18,2) -> #REF! | J21: =ROUND(J19*0.18,2) -> #REF! | K21: =ROUND(K19*0.18,2) -> 148875.49 | L21: =ROUND(L19*0.18,2) -> 191338.14 | M21: =ROUND(M19*0.18,2) -> #REF! | N21: =ROUND(N19*0.18,2) -> #REF!
D22: COSTO TOTAL (Incluye I.G.V.) S/. | G22: =G19+G21 -> #REF! | H22: =H19+H21 -> #REF! | I22: =I19+I21 -> #REF! | J22: =J19+J21 -> #REF! | K22: =K19+K21 -> 975961.56 | L22: =L19+L21 -> 1254327.8 | M22: =M19+M21 -> #REF! | N22: =N19+N21 -> #REF!
D23: INCIDENCIA RESPECTO AL CONTRACTUAL % | H23: =+H22/$G$22 -> #REF! | J23: =+J22/$I$22 -> #REF! | L23: =+L22/$L$22 -> 1 | N23: =+N22/$M$22 -> #REF!
D24: INCIDENCIA DEL ADICIONAL % | G24: =+(I22+J22-L22)/G22 -> #REF!
D25: INCIDENCIA DEL MAYOR METRADO % | G25: =+K22/G22 -> #REF!
D26: INCIDENCIA DEL ADICONAL + MAYOR METRADO % | G26: =+(I22+J22+K22-L22)/G22 -> #REF!
H29: =+H22-K22+M22 -> #REF! | M29: 1495463.1 | N29: 1557304.6
H30: =+H29-G22 -> #REF!

Sheet GG Contr.
B1: CREACIÓN INSTALACIÓN DEL SUBSISTEMA DE DISTRIBUCIÓN PRIMARIA 10-22,9 KV Y SUBSISTEMA DE DISTRIBUCIÓN SECUNDARIA 380/220 V E INSTALACIÓN DE ALUMBRADO PÚBLICO LUCAS CUTIVALU DEL DISTRITO DE MIGUEL CHECA - PROVINCIA DE SULLANA - DEPARTAMENTO DE PIURA
B3: CALCULO DE LOS GASTOS GENERALES DIRECTOS E INDIRECTOS
C5: Sección : | D5: LINEAS PRIMARIAS, REDES PRIMARIAS Y REDES SECUNDARIAS
C6: Departamento : | D6: PIURA | K6: =I190/E69 -> 0.30530483
C7: Plazo de Obra : | D7: 5 | E7: meses
B9: 1.0 | C9: GASTOS GENERALES VARIABLES-GG DIRECTOS | I9: 942051.3
B11: 1.1 | C11: Personal Profesional Principal
C12: Descripción | D12: Unidad | E12: Cant. | F12: Particip. | G12: Tiempo | H12: Sueldo | I12: Parcial
F13: % | G13: (meses) | H13: (S/.) | I13: (S/.)
C14: Gerente de Obra | D14: Und. | E14: 0 | F14: 0.5 | G14: 2.5 | H14: 10000 | I14: 0
C15: Ingeniero Residente de la Obra | D15: Und. | E15: 1 | F15: 1 | G15: 5 | H15: 6000 | I15: =ROUND(E15*F15*G15*H15,2) -> 30000
C16: Ingeniero Asistente de Obra | D16: Und. | E16: 0 | F16: 0.82 | G16: 4.1 | H16: 6500 | I16: 0
C17: Gestor de Servidumbre | D17: Und. | E17: 0 | F17: 0.5 | G17: 2.5 | H17: 4500 | I17: 0
C18: Ingeniero de Seguridad e Higiene Ocupacional | D18: Und. | E18: 1 | F18: 1 | G18: 5 | H18: 4500 | I18: =ROUND(E18*F18*G18*H18,2) -> 22500
C19: Ingeniero Asistente de Residente de Obra | D19: Und. | E19: 1 | F19: 1 | G19: 5 | H19: 4000 | I19: =ROUND(E19*F19*G19*H19,2) -> 20000
C21: PARCIAL 1,1 | I21: =SUM(I14:I20) -> 72500
C22: Nota: El sueldo considerado por cada profesional incluye impuestos y leyes sociales
B24: 1.2 | C24: Personal de Auxiliar y Apoyo
C25: Descripción | D25: Und. | E25: Cant. | F25: Particip. | G25: Tiempo | H25: Sueldo | I25: Parcial
F26: % | G26: (meses) | H26: (S/.) | I26: (S/.)
C27: Administrador | D27: Und. | E27: 1 | F27: 1 | G27: 5 | H27: 3500 | I27: =ROUND(E27*F27*G27*H27,2) -> 17500
C28: Asistente de administrador | D28: Und. | E28: 0 | F28: 0.8 | G28: 4 | H28: 1500 | I28: =ROUND(E28*F28*G28*H28,2) -> 0
C29: Dibujante en Autocad y otros programas | D29: Und. | E29: 1 | F29: 1 | G29: 5 | H29: 1500 | I29: =ROUND(E29*F29*G29*H29,2) -> 7500
C30: Almacenero | D30: Und. | E30: 1 | F30: 1 | G30: 5 | H30: 1800 | I30: =ROUND(E30*F30*G30*H30,2) -> 9000
C31: Asistente de almacen | D31: Und. | E31: 0 | F31: 1 | G31: 5 | H31: 1050 | I31: =ROUND(E31*F31*G31*H31,2) -> 0
C32: Técnico mecánico | D32: Und. | E32: 0 | F32: 1 | G32: 5 | H32: 1200 | I32: =ROUND(E32*F32*G32*H32,2) -> 0
C33: Chofer | D33: Und. | E33: 1 | F33: 1 | G33: 5 | H33: 1500 | I33: =ROUND(E33*F33*G33*H33,2) -> 7500
C34: Seguridad en obra (Guardian) | D34: Und. | E34: 1 | F34: 1 | G34: 5 | H34: 1047 | I34: =ROUND(E34*F34*G34*H34,2) -> 5235
C36: PARCIAL 1,2 | I36: =SUM(I27:I35) -> 46735 | K36: 46735
C37: Nota: El sueldo considerado por trabajador incluye impuestos y leyes sociales
B39: 1.3 | C39: Hospedajes, Oficina, Campamentos, alimentación y movilidad del personal principal, auxiliar y apoyo
C40: Descripción | D40: Und. | E40: Cant. | F40: Particip. | G40: Tiempo | H40: Gasto/ Und. | I40: Parcial
F41: % | G41: (meses) | H41: (S/.) | I41: (S/.)
C42: Hospedajes | D42: Glb/mes | E42: 1 | F42: 1 | G42: 5 | H42: 1500 | I42: =ROUND(E42*F42*G42*H42,2) -> 7500
C43: Alquiler de Oficina - Almacen en Obra (Incluye agua y luz) | D43: Glb/mes | E43: 1 | F43: 1 | G43: 5 | H43: 849.88 | I43: =ROUND(E43*F43*G43*H43,2) -> 4249.4
C44: Alquiler de casa almacén (incluye agua y luz) | D44: Glb/mes | E44: 0 | F44: 1 | G44: 5 | H44: 450 | I44: =ROUND(E44*F44*G44*H44,2) -> 0
C45: Comunicaciones: telefono, fax, internet, radio, etc. | D45: Glb/mes | E45: 1 | F45: 1 | G45: 5 | H45: 550 | I45: =ROUND(E45*F45*G45*H45,2) -> 2750
C46: Alimentación | D46: Glb/mes | E46: 1 | F46: 1 | G46: 5 | H46: 2000 | I46: =ROUND(E46*F46*G46*H46,2) -> 10000
C47: Pasajes | D47: Glb/mes | E47: 1 | F47: 1 | G47: 5 | H47: 650 | I47: =ROUND(E47*F47*G47*H47,2) -> 3250
C49: PARCIAL 1,3 | I49: =SUM(I42:I48) -> 27749.4
B51: 1.4 | C51: Mobiliario, equipo, material de oficina y otros
C52: Descripción | D52: Und. | E52: Cant. | F52: Desgaste | G52: Tiempo | H52: Gasto/ Und.xmes | I52: Parcial
F53: % | G53: (meses) | H53: (S/.) | I53: (S/.)
C54: Mobiliario de oficina | D54: Glb/mes | E54: 3 | F54: 0.020833333 | G54: 5 | H54: 2500 | I54: =ROUND(E54*F54*G54*H54,2) -> 781.25
C55: Computadora | D55: Glb/mes | E55: 3 | F55: 0.020833333 | G55: 5 | H55: 3500 | I55: =ROUND(E55*F55*G55*H55,2) -> 1093.75
C56: Impresora | D56: Glb/mes | E56: 2 | F56: 0.020833333 | G56: 5 | H56: 1000 | I56: =ROUND(E56*F56*G56*H56,2) -> 208.33
C57: Útiles de Oficina | D57: Glb/mes | E57: 1 | F57: 0.020833333 | G57: 5 | H57: 1200 | I57: =ROUND(E57*F57*G57*H57,2) -> 125
C58: Camioneta pick up | D58: Glb/mes | E58: 1 | F58: 0.0631315 | G58: 5 | H58: 118800 | I58: =ROUND(E58*F58*G58*H58,2) -> 37500.11
C59: Combustible | D59: Glb/mes | E59: 1 | F59: 1 | G59: 5 | H59: 3000 | I59: =ROUND(E59*F59*G59*H59,2) -> 15000
C60: Mantenimiento | D60: Glb/mes | E60: 1 | F60: 0.7 | G60: 5 | H60: 1500 | I60: =ROUND(E60*F60*G60*H60,2) -> 5250
C62: PARCIAL 1,4 | I62: =SUM(I54:I61) -> 59958.44 | K62: 59958.44
C63: Nota: El desgaste de los equipos ha sido calculado considerando una depreciación líneal en 36 meses de vida útil.
C64: El desgaste de las camionetas ha sido calculado considerando una depreciación líneal en 120 meses de vida útil.
B66: 1.5 | C66: Gastos financieros y otros gastos
C67: Descripción | D67: Und. | E67: Costo Directo | F67: % de CD | G67: Costo/mes | H67: Tiempo | I67: Parcial
E68: Obra (s/.) | F68: al mes | G68: S/. | H68: (meses) | I68: S/.
C69: Cartas fianza | D69: mes | E69: 942051.3 | F69: 0.0005 | G69: 495.26 | H69: 7 | I69: =ROUND(G69*H69,2) -> 3466.82 | K69: =+G69*H69 -> 3466.82
C70: Seguros | D70: Gbl | E70: 942051.3 | F70: 0.0002 | G70: 198.1 | H70: 6 | I70: =ROUND(G70*H70,2) -> 1188.6
C72: PARCIAL 1,6 | I72: =SUM(I69:I71) -> 4655.42 | K72: 4655.42
C74: PARCIAL GASTOS GENERALES VARIABLES (1) | I74: =+I72+I62+I49+I36+I21 -> 211598.26 | K74: 256598.26
B77: 1.6 | C77: Plan para la vigilancia, prevención y control de COVID-19 - ( R.M. N° 448-2020-MINSA)
C78: Descripción | D78: Und. | E78: Cant. | F78: Particip. | G78: Tiempo | H78: Costo/mes | I78: Parcial
F79: % | G79: (meses) | H79: (S/.) | I79: (S/.)
C80: A.1 Personal Profesional Principal
C81: - Profesional Técnico de la Salud | D81: Global | E81: 1 | H81: 3000 | I81: =ROUND(E81*H81,2) -> 3000
C82: A.2 Personal Auxiliar y de Apoyo
C83: - Operario de Limpieza y Desinfección (COVID-19) | D83: Global | E83: 1 | H83: 1800 | I83: =ROUND(E83*H83,2) -> 1800
C84: SUB-TOTAL A | I84: =SUM(I80:I83) -> 4800 | K84: 8550
C86: Descripción | D86: Und. | E86: Cant. | F86: Particip. | G86: Tiempo | H86: Gasto/ Und. | I86: Parcial
F87: % | G87: (meses) | H87: (S/.) | I87: (S/.)
C88: B.1 Plan para la Vigilancia, Prevención, y Control de la COVID-19 en el Trabajo
C89: - Elaboración, Aprobación, y Registro en el MINSA | D89: Global | E89: 1 | H89: 1200 | I89: =ROUND(E89*H89,2) -> 1200
C90: B.2 Evaluación Médico Ocupacionales
C91: - Termómetro Digital Infrarrojo (4) | D91: Und. | E91: 1 | F91: 0.083333333 | G91: 5 | H91: 590 | I91: =ROUND(E91*F91*G91*H91,2) -> 245.83
C92: - Pruebas de descarte de la COVID-19 | D92: Global | E92: 1 | H92: 4993.2 | I92: =ROUND(E92*H92,2) -> 4993.2
C93: B.3 Equipos de Proteccion Personal (EPPs)
C94: - Mascarilla Quirúrgica descartable | D94: Und. | E94: 60 | F94: 1 | G94: 5 | H94: 0.8 | I94: =ROUND(E94*F94*G94*H94,2) -> 240
C95: - Mascarilla Facial Textil comunitaria | D95: Global | E95: 1 | H95: 558.7 | I95: =ROUND(E95*H95,2) -> 558.7
C96: - Careta Facial | D96: Global | E96: 1 | H96: 2567 | I96: =ROUND(E96*H96,2) -> 2567
C97: - Guante Quirúrgico descartable | D97: Und. | E97: 60 | F97: 1 | G97: 5 | H97: 0.75 | I97: =ROUND(E97*G97*H97,2) -> 225 | K97: =+E97*G97*H97 -> 225
C98: - Gafas de Protección | D98: Und. | E98: 1 | F98: 1 | G98: 5 | H98: 12 | I98: =ROUND(E98*G98*H98,2) -> 60
C99: B.4 Lavado y Desinfección de Manos y de Planta de Calzado
C100: - Jabón líquido, Papel Toalla, Alcohol Gel Antibacterial, Solución de Alcohol al 96%, Lejia, Bandeja de Limpieza | D100: Glb/mes | E100: 1 | F100: 1 | G100: 5 | H100: 726.85 | I100: =ROUND(G100*H100,2) -> 3634.25 | K100: 3634.25
C101: B.5 Lavado, Desinfección y Fumigación del Centro Laboral (ambientes, mobiliario, herramientas, equipos, unidades de transporte en obra, etc
C102: - Lejia, Detergente | D102: Glb/mes | E102: 1 | F102: 1 | G102: 5 | H102: 564.2 | I102: =ROUND(G102*H102,2) -> 2821 | K102: 2821
C103: B.6 Actividades Varias
C104: - Charlas de Capacitación y de Sensibilizacion (Medidas Preventivas, Uso de EPPs, lavado correcto, información sobre el COVID-19) (3) | D104: Glb/mes | E104: 1 | F104: 1 | G104: 5 | H104: 250 | I104: =ROUND(G104*H104,2) -> 1250 | K104: 1250
C105: - Señaléticas de Prevención: Carteles de Prevencion, Infografias (Uso de Mascarillas, Distanciamiento, Lavado de manos, Uso obligatorio de EPPs). | D105: Global | E105: 1 | H105: 350 | I105: =ROUND(E105*H105,2) -> 350 | K105: 350
C106: - Cilindros para acopio de material deshechable | D106: Und. | E106: 2 | F106: 1 | G106: 1 | H106: 350 | I106: =ROUND(E106*F106*G106*H106,2) -> 700 | K106: 700
C107: B.7 Hospedaje, oficina, alimentación y movilidad del personal principal, auxiliar y de apoyo
C108: - Hospedaje. | D108: Glb/mes | E108: 1 | F108: 1 | G108: 5 | H108: 200 | I108: =ROUND(E108*F108*G108*H108,2) -> 1000 | K108: 1000
C109: - Alquiler de Oficina en Obra para Evaluación Médico Ocupacional (Incluye agua y luz). | D109: Glb/mes | E109: 1 | F109: 1 | G109: 5 | H109: 250 | I109: =ROUND(E109*F109*G109*H109,2) -> 1250 | K109: 1250
C110: - Comunicaciones: telefono, fax, internet, radio, etc. | D110: Glb/mes | E110: 1 | F110: 1 | G110: 5 | H110: 110 | I110: =ROUND(E110*F110*G110*H110,2) -> 550 | K110: 550
C111: - Alimentación | D111: Glb/mes | E111: 1 | F111: 1 | G111: 5 | H111: 610 | I111: =ROUND(E111*F111*G111*H111,2) -> 3050 | K111: 3050
C112: - Pasajes | D112: Glb/mes | E112: 1 | F112: 1 | G112: 5 | H112: 125 | I112: =ROUND(E112*F112*G112*H112,2) -> 625 | K112: 625
C113: B.8 Transporte de Personal en Obra
C114: - Traslado desde campamento a punto de instalación (incluye unidad móvil tipo Minivan con capacidad mínima de 11 pasajeros, chofer, combustible, mantenimiento) | D114: Global | E114: 1 | H114: 2479.5 | I114: =ROUND(E114*H114,2) -> 2479.5
C115: B.9 Mobiliario, equipo, material de oficina y otros (4)
C116: - Equipamiento Médico para Evaluación Médico Ocupacional (camilla, estetoscopio, mobiliario médico, etc) | D116: Glb/mes | E116: 1 | F116: 0.05 | G116: 5 | H116: 1800 | I116: =ROUND(E116*F116*G116*H116,2) -> 450
C117: - Mobiliario de oficina | D117: Glb/mes | E117: 1 | F117: 0.05 | G117: 5 | H117: 1200 | I117: =ROUND(E117*F117*G117*H117,2) -> 300
...

Sheet RES-LP
B2: RESUMEN PRESUPUESTO DE OBRA
B4: AMPLIACIÓN DEL SERVICIO DE ENERGÍA ELÉCTRICA EN LA PROVINCIA DEL SANTA Y EN EL DISTRITO DE PAMPAROMAS – DEPARTAMENTO DE ANCASH
B6: UBICACIÓN | C6: : | D6: ANCASH
B7: SECCIÓN I | C7: : | D7: LINEAS PRIMARIAS | H7: Fecha: 30-May-2022
H8: T.C. (S/ /US$): 3,683
B9: ITEM | C9: DESCRIPCION | G9: PRESUPUESTO CONTRATO | H9: PRESUPUESTO ESTUDIO DEFINIVO | I9: ADICIONALES | K9: DEDUCTIVOS
I10: MAYORES METRADOS | J10: PARTIDAS NUEVAS | K10: MENOR METRADO | L10: DEDUCTIVO VINCULANTE
B12: A | D12: SUMINISTRO DE MATERIALES | G12: =+'Mtdo-Ppto LP'!K154 -> 628325.26 | H12: =+'Mtdo-Ppto LP'!M154 -> 683730.19 | I12: =+'Mtdo-Ppto LP'!O154 -> 91503.47 | J12: =+'Mtdo-Ppto LP'!Q154 -> 85371.61 | K12: =+'Mtdo-Ppto LP'!S154 -> 121470.16 | L12: =+'Mtdo-Ppto LP'!U154 -> 94577.96
B13: B | D13: MONTAJE ELECTROMECANICO | G13: =+'Mtdo-Ppto LP'!K307 -> 461491.17 | H13: =+'Mtdo-Ppto LP'!M307 -> 552762.73 | I13: =+'Mtdo-Ppto LP'!O307 -> 54136.69 | J13: =+'Mtdo-Ppto LP'!Q307 -> 91265.2 | K13: =+'Mtdo-Ppto LP'!S307 -> 54130.28 | L13: =+'Mtdo-Ppto LP'!U307 -> 47888.05
B14: C | D14: TRANSPORTE DE MATERIALES | G14: =+'Mtdo-Ppto LP'!K446 -> 60052.8 | H14: =+'Mtdo-Ppto LP'!M446 -> 59272.43 | I14: =+'Mtdo-Ppto LP'!O446 -> 9755.13 | J14: =+'Mtdo-Ppto LP'!Q446 -> 6567.64 | K14: =+'Mtdo-Ppto LP'!S446 -> 17103.14 | L14: =+'Mtdo-Ppto LP'!U446 -> 11389.32
B15: D | D15: TOTAL COSTO DIRECTO | G15: =+SUM(G12:G14) -> 1149869.2 | H15: =+SUM(H12:H14) -> 1295765.3 | I15: =+SUM(I12:I14) -> 155395.29 | J15: =+SUM(J12:J14) -> 183204.45 | K15: =+SUM(K12:K14) -> 192703.58 | L15: =+SUM(L12:L14) -> 153855.33
B16: E | D16: GASTOS GENERALES (10.12%) | G16: =ROUND(G15*10.12%,2) -> 116366.77 | H16: =ROUND(H15*10.12%,2) -> 131131.45 | I16: =ROUND(I15*10.12%,2) -> 15726 | J16: =ROUND(J15*10.12%,2) -> 18540.29 | K16: =ROUND(K15*10.12%,2) -> 19501.6 | L16: =ROUND(L15*10.12%,2) -> 15570.16
B17: F | D17: UTILIDADES (3%) | G17: =ROUND(G15*3%,2) -> 34496.08 | H17: =ROUND(H15*3%,2) -> 38872.96 | I17: =ROUND(I15*3%,2) -> 4661.86 | J17: =ROUND(J15*3%,2) -> 5496.13 | K17: =ROUND(K15*3%,2) -> 5781.11 | L17: =ROUND(L15*3%,2) -> 4615.66
B18: G | D18: COSTO TOTAL S/. (No incluye I.G.V.) | G18: =G17+G16+G15 -> 1300732.1 | H18: =H17+H16+H15 -> 1465769.8 | I18: =I17+I16+I15 -> 175783.15 | J18: =J17+J16+J15 -> 207240.87 | K18: =K17+K16+K15 -> 217986.29 | L18: =L17+L16+L15 -> 174041.15 | M18: =+H18-G18 -> 165037.68
D20: INCIDENCIA % | G20: =+G18/G18 -> 1 | H20: =+H18/$G$18 -> 1.1268806 | I20: =+I18/$G$18 -> 0.1351417 | J20: =+J18/$G$18 -> 0.15932633 | K20: =+K18/$G$18 -> 0.16758739 | L20: =+L18/$G$18 -> 0.13380246
H22: =+H18-I18+K18-J18 -> 1300732 | K22: =+G12-H12+I12+J12-K12 -> -0.01
H23: =+G18-H22 -> 0.050000001 | K23: =+G13-H13+I13+J13-K13 -> 0.05
K24: =+G14-H14+I14+J14-K14 -> 0
K25: =+G15-H15+I15+J15-K15 -> 0.04

Sheet Mtdo-Ppto LP
B6: PRESUPUESTO DE OBRA
B8: OBRA | E8: : | F8: AMPLIACIÓN DEL SERVICIO DE ENERGÍA ELÉCTRICA EN LA PROVINCIA DEL SANTA Y EN EL DISTRITO DE PAMPAROMAS – DEPARTAMENTO DE ANCASH
B9: DEPARTAMENTO | E9: : | F9: ANCASH
B10: SECCIÓN I | E10: : | F10: LINEAS PRIMARIAS
B12: ITEM | C12: DESCRIPCIÓN DE PARTIDAS | G12: UNID. | H12: Precio de Contrato | I12: Precio Pactado | J12: CONTRACTUAL | L12: ESTUDIO DEFINITIVO | N12: ADICIONALES | R12: DEDUCTIVOS | V12: OBSERVACIÓN
J13: Metrado | K13: TOTAL | L13: Metrado | M13: TOTAL | N13: MAYORES METRADOS | P13: PARTIDAS NUEVAS | R13: MENORES METRADOS | T13: DEDUCTIVO VINCULANTE
N14: Metrado | O14: TOTAL | P14: Metrado | Q14: TOTAL | R14: Metrado | S14: TOTAL | T14: Metrado | U14: TOTAL
H15: Unitario | I15: Unitario | J15: Cantidad | K15: S/. | L15: Cantidad | M15: S/. | N15: Cantidad | O15: S/. | P15: Cantidad | Q15: S/. | R15: Cantidad | S15: S/. | T15: Cantidad | U15: S/.
B16: A | D16: SUMINISTRO DE MATERIALES
B17: 1 | C17: 3 | D17: CRUCETAS DE MADERA DE PROCEDENCIA NACIONAL | Y17: 1
B18: 1.01 | C18: =+C17+1 -> 4 | D18: Cruceta de madera tratada de 90 mm x 115 mm x 1,20 m | G18: u | H18: 105 | J18: 11 | K18: =+ROUND($H18*J18,2) -> 1155 | L18: =+[191]Metrados!E19 -> 7 | M18: =+ROUND($H18*L18,2) -> 735 | N18: =+IF($L18-$J18>=0,$L18-$J18,0) -> 0 | O18: =+ROUND($H18*N18,2) -> 0 | Q18: =+ROUND($H18*P18,2) -> 0 | R18: =+IF($L18-$J18<=0,-$L18+$J18,0) -> 4 | S18: =+ROUND($H18*R18,2) -> 420 | T18: =+R18 -> 4 | U18: =+ROUND($H18*T18,2) -> 420 | V18: Se vincula con el mayor metrado de la partida 4.01 | Z18: 0
B19: 1.02 | C19: =+C18+1 -> 5 | D19: Cruceta de madera tratada de 90 mm x 115 mm x 2,00 m | G19: u | H19: 178 | J19: 2 | K19: =+ROUND($H19*J19,2) -> 356 | L19: =+[191]Metrados!E20 -> 1 | M19: =+ROUND($H19*L19,2) -> 178 | N19: =+IF($L19-$J19>=0,$L19-$J19,0) -> 0 | O19: =+ROUND($H19*N19,2) -> 0 | Q19: =+ROUND($H19*P19,2) -> 0 | R19: =+IF($L19-$J19<=0,-$L19+$J19,0) -> 1 | S19: =+ROUND($H19*R19,2) -> 178 | T19: =+R19 -> 1 | U19: =+ROUND($H19*T19,2) -> 178 | V19: Se vincula con el mayor metrado de la partida 4.01 | Z19: 0
B20: 1.03 | C20: =+C19+1 -> 6 | D20: Cruceta de madera tratada de 90 mm x 115 mm x 2,40 m | G20: u | H20: 205 | J20: 1 | K20: =+ROUND($H20*J20,2) -> 205 | L20: =+[191]Metrados!E21 -> 13 | M20: =+ROUND($H20*L20,2) -> 2665 | N20: =+IF($L20-$J20>=0,$L20-$J20,0) -> 12 | O20: =+ROUND($H20*N20,2) -> 2460 | Q20: =+ROUND($H20*P20,2) -> 0 | R20: =+IF($L20-$J20<=0,-$L20+$J20,0) -> 0 | S20: =+ROUND($H20*R20,2) -> 0 | T20: =+R20 -> 0 | U20: =+ROUND($H20*T20,2) -> 0 | V20: Se vincula con el mayor metrado de la partida 4.01 | Z20: 13
B21: 1.04 | C21: =+C20+1 -> 7 | D21: Listón de madera tratada 50 x 19 mm sección, 2,7 m longitud (incluye clavos de fijación) | G21: u | H21: 27.35 | J21: 9 | K21: =+ROUND($H21*J21,2) -> 246.15 | L21: =+[191]Metrados!E22 -> 0 | M21: =+ROUND($H21*L21,2) -> 0 | N21: =+IF($L21-$J21>=0,$L21-$J21,0) -> 0 | O21: =+ROUND($H21*N21,2) -> 0 | Q21: =+ROUND($H21*P21,2) -> 0 | R21: =+IF($L21-$J21<=0,-$L21+$J21,0) -> 9 | S21: =+ROUND($H21*R21,2) -> 246.15 | U21: =+ROUND($H21*T21,2) -> 0 | Z21: 0
C22: =+#REF!+1 -> #REF! | F22: =+"SUB-TOTAL "&B17&": " -> SUB-TOTAL 1: | K22: =+SUM(K18:K21) -> 1962.15 | M22: =+SUM(M18:M21) -> 3578 | O22: =+SUM(O18:O21) -> 2460 | Q22: =+SUM(Q18:Q21) -> 0 | S22: =+SUM(S18:S21) -> 844.15 | U22: =+SUM(U18:U21) -> 598 | W22: =+K22-M22+O22+Q22-S22 -> 0 | Z22: 0
B23: 2 | C23: =+C22+1 -> #REF! | D23: POSTES DE CONCRETO ARMADO CENTRIFUGADO | Z23: 0
B24: 2.01 | C24: =+C21+1 -> 8 | D24: Poste de C.A.C. de 12 m/200 daN (Incluye perilla) | G24: u | H24: 837.45 | J24: 15 | K24: =+ROUND($H24*J24,2) -> 12561.75 | L24: =+[191]Metrados!E25 -> 3 | M24: =+ROUND($H24*L24,2) -> 2512.35 | N24: =+IF($L24-$J24>=0,$L24-$J24,0) -> 0 | O24: =+ROUND($H24*N24,2) -> 0 | Q24: =+ROUND($H24*P24,2) -> 0 | R24: =+IF($L24-$J24<=0,-$L24+$J24,0) -> 12 | S24: =+ROUND($H24*R24,2) -> 10049.4 | T24: =+R24 -> 12 | U24: =+ROUND($H24*T24,2) -> 10049.4 | V24: Se vincula con la partida nueva 3.02 y 3.03 | Z24: 0
B25: 2.02 | C25: =+#REF!+1 -> #REF! | D25: Poste de C.A.C. de 12 m/300 daN (Incluye perilla) | G25: u | H25: 923.47 | J25: 6 | K25: =+ROUND($H25*J25,2) -> 5540.82 | L25: =+[191]Metrados!E26 -> 6 | M25: =+ROUND($H25*L25,2) -> 5540.82 | N25: =+IF($L25-$J25>=0,$L25-$J25,0) -> 0 | O25: =+ROUND($H25*N25,2) -> 0 | Q25: =+ROUND($H25*P25,2) -> 0 | R25: =+IF($L25-$J25<=0,-$L25+$J25,0) -> 0 | S25: =+ROUND($H25*R25,2) -> 0 | U25: =+ROUND($H25*T25,2) -> 0 | Z25: 0
B26: 2.03 | C26: =+#REF!+1 -> #REF! | D26: Poste de C.A.C. de 13 m/300 daN (Incluye perilla) | G26: u | H26: 1085.14 | J26: 118 | K26: =+ROUND($H26*J26,2) -> 128046.52 | L26: =+[191]Metrados!E27 -> 96 | M26: =+ROUND($H26*L26,2) -> 104173.44 | N26: =+IF($L26-$J26>=0,$L26-$J26,0) -> 0 | O26: =+ROUND($H26*N26,2) -> 0 | Q26: =+ROUND($H26*P26,2) -> 0 | R26: =+IF($L26-$J26<=0,-$L26+$J26,0) -> 22 | S26: =+ROUND($H26*R26,2) -> 23873.08 | T26: =+R26 -> 22 | U26: =+ROUND($H26*T26,2) -> 23873.08 | V26: Se vincula con el mayor metrado de la partida 2.04 | Z26: 0
B27: 2.04 | C27: =+C22+1 -> #REF! | D27: Poste de C.A.C. de 13 m/400 daN (Incluye perilla) | G27: u | H27: 1207.94 | J27: 32 | K27: =+ROUND($H27*J27,2) -> 38654.08 | L27: =+[191]Metrados!E28 -> 60 | M27: =+ROUND($H27*L27,2) -> 72476.4 | N27: =+IF($L27-$J27>=0,$L27-$J27,0) -> 28 | O27: =+ROUND($H27*N27,2) -> 33822.32 | Q27: =+ROUND($H27*P27,2) -> 0 | R27: =+IF($L27-$J27<=0,-$L27+$J27,0) -> 0 | S27: =+ROUND($H27*R27,2) -> 0 | U27: =+ROUND($H27*T27,2) -> 0 | Z27: 0
B28: =+B27+0.01 -> 2.05 | C28: =+C27+1 -> #REF! | D28: Poste de C.A.C. de 15 m/400 daN (Incluye perilla) | G28: u | I28: 0 | K28: =+ROUND($H28*J28,2) -> 0 | L28: =+[191]Metrados!E29 -> 0 | M28: =+ROUND($I28*L28,2) -> 0 | O28: =+ROUND($H28*N28,2) -> 0 | P28: =+L28 -> 0 | Q28: =+ROUND($I28*P28,2) -> 0 | S28: =+ROUND($H28*R28,2) -> 0 | U28: =+ROUND($H28*T28,2) -> 0 | Z28: 0
C29: =+#REF!+1 -> #REF! | F29: =+"SUB-TOTAL "&B23&": " -> SUB-TOTAL 2: | K29: =+SUM(K24:K28) -> 184803.17 | M29: =+SUM(M24:M28) -> 184703.01 | O29: =+SUM(O24:O28) -> 33822.32 | Q29: =+SUM(Q24:Q28) -> 0 | S29: =+SUM(S24:S28) -> 33922.48 | U29: =+SUM(U24:U28) -> 33922.48 | W29: =+K29-M29+O29+Q29-S29 -> 0 | Z29: 0
B30: 3 | C30: =+#REF!+1 -> #REF! | D30: POSTES DE MADERA IMPORTADA | Z30: 0
B31: 3.01 | C31: =+C30+1 -> #REF! | D31: Poste de madera importada (Pino Amarillo del Sur) de 12 m, Clase 6 | G31: u | H31: 1703.39 | J31: 9 | K31: =+ROUND($H31*J31,2) -> 15330.51 | L31: =+[191]Metrados!E32 -> 0 | M31: =+ROUND($H31*L31,2) -> 0 | N31: =+IF($L31-$J31>=0,$L31-$J31,0) -> 0 | O31: =+ROUND($H31*N31,2) -> 0 | Q31: =+ROUND($H31*P31,2) -> 0 | R31: =+IF($L31-$J31<=0,-$L31+$J31,0) -> 9 | S31: =+ROUND($H31*R31,2) -> 15330.51 | T31: =+R31 -> 9 | U31: =+ROUND($H31*T31,2) -> 15330.51 | V31: Se vincula con la partida nueva 3.02 y 3.03 | Z31: 0
C32: =+#REF!+1 -> #REF! | F32: =+"SUB-TOTAL "&B30&": " -> SUB-TOTAL 3: | K32: =+SUM(K31:K31) -> 15330.51 | M32: =+SUM(M31:M31) -> 0 | O32: =+SUM(O31:O31) -> 0 | Q32: =+SUM(Q31:Q31) -> 0 | S32: =+SUM(S31:S31) -> 15330.51 | U32: =+SUM(U31:U31) -> 15330.51 | W32: =+K32-M32+O32+Q32-S32 -> 0 | Z32: 0
B33: 3.00A | C33: =+C32+1 -> #REF! | D33: POSTES DE FIBRA DE VIDRIO | Z33: 0
B34: 3.01A | C34: =+#REF!+1 -> #REF! | D34: Poste de PRFV de 12 m/200 daN | G34: u | I34: 1958.01 | K34: =+ROUND($H34*J34,2) -> 0 | L34: =+[191]Metrados!E35 -> 4 | M34: =+ROUND($I34*L34,2) -> 7832.04 | O34: =+ROUND($H34*N34,2) -> 0 | P34: =+L34 -> 4 | Q34: =+ROUND($I34*P34,2) -> 7832.04 | R34: =+IF($L34-$J34<=0,-$L34+$J34,0) -> 0 | S34: =+ROUND($H34*R34,2) -> 0 | U34: =+ROUND($H34*T34,2) -> 0 | Z34: 0
B35: 3.02A | C35: =+C34+1 -> #REF! | D35: Poste de PRFV de 12 m/300 daN | G35: u | I35: 2336.29 | K35: =+ROUND($H35*J35,2) -> 0 | L35: =+[191]Metrados!E36 -> 11 | M35: =+ROUND($I35*L35,2) -> 25699.19 | O35: =+ROUND($H35*N35,2) -> 0 | P35: =+L35 -> 11 | Q35: =+ROUND($I35*P35,2) -> 25699.19 | R35: =+IF($L35-$J35<=0,-$L35+$J35,0) -> 0 | S35: =+ROUND($H35*R35,2) -> 0 | U35: =+ROUND($H35*T35,2) -> 0 | Z35: 0
C36: =+#REF!+1 -> #REF! | F36: =+"SUB-TOTAL "&B33&": " -> SUB-TOTAL 3.00A: | M36: =+SUM(M34:M35) -> 33531.23 | O36: =+SUM(O34:O35) -> 0 | Q36: =+SUM(Q34:Q35) -> 33531.23 | S36: =+SUM(S34:S35) -> 0 | U36: =+SUM(U34:U35) -> 0 | W36: =+K36-M36+O36+Q36-S36 -> 0 | Z36: 0
B37: 4 | C37: =+C32+1 -> #REF! | D37: OTROS MATERIALES DE CONCRETO ARMADO | Z37: 0
B38: 4.01 | C38: =+C37+1 -> #REF! | D38: Cruceta Asimétrica de C.A.V. Za / 1,5 / 0,9 / 250 / 200 / 100 daN (Za / L / L1/ T / F / V) | G38: u | H38: 120.3 | J38: 2 | K38: =+ROUND($H38*J38,2) -> 240.6 | L38: =+[191]Metrados!E39 -> 0 | M38: =+ROUND($H38*L38,2) -> 0 | N38: =+IF($L38-$J38>=0,$L38-$J38,0) -> 0 | O38: =+ROUND($H38*N38,2) -> 0 | Q38: =+ROUND($H38*P38,2) -> 0 | R38: =+IF($L38-$J38<=0,-$L38+$J38,0) -> 2 | S38: =+ROUND($H38*R38,2) -> 240.6 | U38: =+ROUND($H38*T38,2) -> 0 | Z38: -12
B39: 4.02 | C39: =+C38+1 -> #REF! | D39: Ménsula de C.A.V. M / 1,2 / 250 / 150 / 150 daN (M / L / T / F / V) | G39: u | H39: 88.8 | J39: 393 | K39: =+ROUND($H39*J39,2) -> 34898.4 | L39: =+[191]Metrados!E40 -> 84 | M39: =+ROUND($H39*L39,2) -> 7459.2 | N39: =+IF($L39-$J39>=0,$L39-$J39,0) -> 0 | O39: =+ROUND($H39*N39,2) -> 0 | Q39: =+ROUND($H39*P39,2) -> 0 | R39: =+IF($L39-$J39<=0,-$L39+$J39,0) -> 309 | S39: =+ROUND($H39*R39,2) -> 27439.2 | T39: =+N38+P41 -> 122 | U39: =+ROUND($H39*T39,2) -> 10833.6 | V39: Se vincula con el mayor metrado de la partida 4.01 y la partida nueva 4.05 | Z39: 0
B40: 4.03 | C40: =+C39+1 -> #REF! | D40: Ménsula de C.A.V. M / 0,8 / 250 / 150 / 150 daN (M / L / T / F / V) | G40: u | H40: 92.26 | J40: 1 | K40: =+ROUND($H40*J40,2) -> 92.26 | L40: =+[191]Metrados!E41 -> 0 | M40: =+ROUND($H40*L40,2) -> 0 | N40: =+IF($L40-$J40>=0,$L40-$J40,0) -> 0 | O40: =+ROUND($H40*N40,2) -> 0 | Q40: =+ROUND($H40*P40,2) -> 0 | R40: =+IF($L40-$J40<=0,-$L40+$J40,0) -> 1 | S40: =+ROUND($H40*R40,2) -> 92.26 | U40: =+ROUND($H40*T40,2) -> 0 | Z40: 0
B41: 4.05 | C41: =+C40+1 -> #REF! | D41: Cruceta Simétrica de C.A.V. Z / 2,4 / 300 / 300 / 150 daN (Z/ L / T / F / V) | G41: u | I41: 230 | K41: =+ROUND($H41*J41,2) -> 0 | L41: =+[191]Metrados!E42 -> 122 | M41: =+ROUND($I41*L41,2) -> 28060 | O41: =+ROUND($H41*N41,2) -> 0 | P41: =+L41 -> 122 | Q41: =+ROUND($I41*P41,2) -> 28060 | R41: =+IF($L41-$J41<=0,-$L41+$J41,0) -> 0 | S41: =+ROUND($H41*R41,2) -> 0 | U41: =+ROUND($H41*T41,2) -> 0 | Z41: -1
C42: =+#REF!+1 -> #REF! | F42: =+"SUB-TOTAL "&B37&": " -> SUB-TOTAL 4: | K42: =+SUM(K38:K41) -> 35231.26 | M42: =+SUM(M38:M41) -> 35519.2 | O42: =+SUM(O38:O41) -> 0 | Q42: =+SUM(Q38:Q41) -> 28060 | S42: =+SUM(S38:S41) -> 27772.06 | U42: =+SUM(U38:U40) -> 10833.6 | Z42: 0
B43: 5 | C43: =+C42+1 -> #REF! | D43: AISLADORES Y ACCESORIOS | Z43: 0
B44: 5.01 | C44: =+C43+1 -> #REF! | D44: Aislador de Porcelana Tipo Pin, Clase ANSI 56-3 | G44: u | H44: 76.45 | J44: 29 | K44: =+ROUND($H44*J44,2) -> 2217.05 | L44: =+[191]Metrados!E45 -> 24 | M44: =+ROUND($H44*L44,2) -> 1834.8 | N44: =+IF($L44-$J44>=0,$L44-$J44,0) -> 0 | O44: =+ROUND($H44*N44,2) -> 0 | Q44: =+ROUND($H44*P44,2) -> 0 | R44: =+IF($L44-$J44<=0,-$L44+$J44,0) -> 5 | S44: =+ROUND($H44*R44,2) -> 382.25 | T44: =+R44 -> 5 | U44: =+ROUND($H44*T44,2) -> 382.25 | V44: Se vincula con el mayor metrado de la partida 6.01 y 6.02 | Z44: 0
B45: 5.02 | C45: =+C44+1 -> #REF! | D45: Espiga de AºGº de 609 mm longitud, para Cabeza de Poste y Aislador ANSI 56-3 | G45: u | H45: 35.96 | J45: 29 | K45: =+ROUND($H45*J45,2) -> 1042.84 | L45: =+[191]Metrados!E46 -> 24 | M45: =+ROUND($H45*L45,2) -> 863.04 | N45: =+IF($L45-$J45>=0,$L45-$J45,0) -> 0 | O45: =+ROUND($H45*N45,2) -> 0 | Q45: =+ROUND($H45*P45,2) -> 0 | R45: =+IF($L45-$J45<=0,-$L45+$J45,0) -> 5 | S45: =+ROUND($H45*R45,2) -> 179.8 | T45: =+R45 -> 5 | U45: =+ROUND($H45*T45,2) -> 179.8 | V45: Se vincula con el mayor metrado de la partida 6.01 y 6.02 | Z45: 0
B46: 5.03 | C46: =+C44+1 -> #REF! | D46: Conjunto Aislador Line Post Polimérico en Mesula y Cruceta: | G46: u | H46: 209.65 | J46: 369 | K46: =+ROUND($H46*J46,2) -> 77360.85 | L46: =+[191]Metrados!E48 -> 307 | M46: =+ROUND($H46*L46,2) -> 64362.55 | Z46: 0
C47: =+C45+1 -> #REF! | D47: .- Aislador Polimérico de 36 kV, Tipo Line Post con Espárrago de 19 mm Ø, 200 mm longitud (Alternativa a Conjunto Aislador-Espiga en Cruceta) | N47: =+IF($L46-$J46>=0,$L46-$J46,0) -> 0 | O47: =+ROUND($H46*N47,2) -> 0 | Q47: =+ROUND($H46*P47,2) -> 0 | R47: =+IF($L46-$J46<=0,-$L46+$J46,0) -> 62 | S47: =+ROUND($H46*R47,2) -> 12998.3 | T47: =+R47 -> 62 | U47: =+ROUND($H46*T47,2) -> 12998.3 | V47: Se vincula con el mayor metrado de la partida 6.01 y 6.02 | Z47: 0
C48: =+#REF!+1 -> #REF! | F48: =+"SUB-TOTAL "&B43&": " -> SUB-TOTAL 5: | K48: =+SUM(K44:K47) -> 80620.74 | M48: =+SUM(M44:M47) -> 67060.39 | O48: =+SUM(O44:O47) -> 0 | Q48: =+SUM(Q44:Q47) -> 0 | S48: =+SUM(S44:S47) -> 13560.35 | U48: =+SUM(U44:U47) -> 13560.35 | Z48: 0
B49: 6 | C49: =+C48+1 -> #REF! | D49: AISLADORES DE SUSPENSION Y ACCESORIOS | Z49: 0
B50: 6.01 | C50: =+C49+1 -> #REF! | D50: Grillete Recto | G50: u | H50: 17.76 | J50: 155 | K50: =+ROUND($H50*J50,2) -> 2752.8 | L50: =+[191]Metrados!E51 -> 283 | M50: =+ROUND($H50*L50,2) -> 5026.08 | N50: =+IF($L50-$J50>=0,$L50-$J50,0) -> 128 | O50: =+ROUND($H50*N50,2) -> 2273.28 | Q50: =+ROUND($H50*P50,2) -> 0 | R50: =+IF($L50-$J50<=0,-$L50+$J50,0) -> 0 | S50: =+ROUND($H50*R50,2) -> 0 | U50: =+ROUND($H50*T50,2) -> 0 | Z50: 0
B51: 6.02 | C51: =+C50+1 -> #REF! | D51: Aislador Polimerico con Conexión Horquilla (Estructura) y Lengüeta (Linea) de 36 kV, según Especificacion Técnica. | G51: u | H51: 76.66 | J51: 155 | K51: =+ROUND($H51*J51,2) -> 11882.3 | L51: =+[191]Metrados!E52 -> 283 | M51: =+ROUND($H51*L51,2) -> 21694.78 | N51: =+IF($L51-$J51>=0,$L51-$J51,0) -> 128 | O51: =+ROUND($H51*N51,2) -> 9812.48 | Q51: =+ROUND($H51*P51,2) -> 0 | R51: =+IF($L51-$J51<=0,-$L51+$J51,0) -> 0 | S51: =+ROUND($H51*R51,2) -> 0 | U51: =+ROUND($H51*T51,2) -> 0 | Z51: 0
C52: =+#REF!+1 -> #REF! | F52: =+"SUB-TOTAL "&B49&": " -> SUB-TOTAL 6: | K52: =+SUM(K50:K51) -> 14635.1 | M52: =+SUM(M50:M51) -> 26720.86 | O52: =+SUM(O50:O51) -> 12085.76 | Q52: =+SUM(Q50:Q51) -> 0 | S52: =+SUM(S50:S51) -> 0 | U52: =+SUM(U50:U51) -> 0 | Z52: 0
B53: 7 | C53: =+C52+1 -> #REF! | D53: CONDUCTOR DE ALEACIÓN DE ALUMINIO | Z53: 0
B54: 7.01 | C54: =+C53+1 -> #REF! | D54: Conductor de Aleacion de Aluminio de 35 mm² | G54: km | H54: 2249.62 | J54: 53.4 | K54: =+ROUND($H54*J54,2) -> 120129.71 | L54: =+[191]Metrados!E55 -> 51.19 | M54: =+ROUND($H54*L54,2) -> 115158.05 | N54: =+IF($L54-$J54>=0,$L54-$J54,0) -> 0 | O54: =+ROUND($H54*N54,2) -> 0 | Q54: =+ROUND($H54*P54,2) -> 0 | R54: =+IF($L54-$J54<=0,-$L54+$J54,0) -> 2.21 | S54: =+ROUND($H54*R54,2) -> 4971.66 | T54: =+R54 -> 2.21 | U54: =+ROUND($H54*T54,2) -> 4971.66 | V54: Se vincula con el mayor metrado de la partida 14.03 | Z54: 0
B55: 7.02 | C55: =+C54+1 -> #REF! | D55: Conductor de Aleacion de Aluminio de 70 mm² | G55: km | H55: 4157 | J55: 1.91 | K55: =+ROUND($H55*J55,2) -> 7939.87 | L55: =+[191]Metrados!E56 -> 1.17 | M55: =+ROUND($H55*L55,2) -> 4863.69 | N55: =+IF($L55-$J55>=0,$L55-$J55,0) -> 0 | O55: =+ROUND($H55*N55,2) -> 0 | Q55: =+ROUND($H55*P55,2) -> 0 | R55: =+IF($L55-$J55<=0,-$L55+$J55,0) -> 0.74 | S55: =+ROUND($H55*R55,2) -> 3076.18 | T55: =+R55 -> 0.74 | U55: =+ROUND($H55*T55,2) -> 3076.18 | V55: Se vincula con el mayor metrado de la partida 14.03 | Z55: 0
C56: =+#REF!+1 -> #REF! | F56: =+"SUB-TOTAL "&B53&": " -> SUB-TOTAL 7: | K56: =+SUM(K54:K55) -> 128069.58 | M56: =+SUM(M54:M55) -> 120021.74 | O56: =+SUM(O54:O55) -> 0 | Q56: =+SUM(Q54:Q55) -> 0 | S56: =+SUM(S54:S55) -> 8047.84 | U56: =+SUM(U54:U55) -> 8047.84 | Z56: 0
B57: 8 | C57: =+C56+1 -> #REF! | D57: ACCESORIOS PARA CONDUCTOR DE ALEACION DE ALUMINIO | Z57: 0
B58: 8.01 | C58: =+C57+1 -> #REF! | D58: Varilla de Armar preformada Simple para Conductor de 35 mm² | G58: u | H58: 10.19 | J58: 326 | K58: =+ROUND($H58*J58,2) -> 3321.94 | L58: =+[191]Metrados!E59 -> 275 | M58: =+ROUND($H58*L58,2) -> 2802.25 | N58: =+IF($L58-$J58>=0,$L58-$J58,0) -> 0 | O58: =+ROUND($H58*N58,2) -> 0 | Q58: =+ROUND($H58*P58,2) -> 0 | R58: =+IF($L58-$J58<=0,-$L58+$J58,0) -> 51 | S58: =+ROUND($H58*R58,2) -> 519.69 | T58: =+P72 -> 2 | U58: =+ROUND($H58*T58,2) -> 20.38 | V58: Se vincula con la partida nueva 8.15 | Z58: 0
B59: 8.02 | C59: =+C58+1 -> #REF! | D59: Varilla de Armar preformada Simple para Conductor de 70 mm² | G59: u | H59: 17.38 | J59: 2 | K59: =+ROUND($H59*J59,2) -> 34.76 | L59: =+[191]Metrados!E60 -> 2 | M59: =+ROUND($H59*L59,2) -> 34.76 | N59: =+IF($L59-$J59>=0,$L59-$J59,0) -> 0 | O59: =+ROUND($H59*N59,2) -> 0 | Q59: =+ROUND($H59*P59,2) -> 0 | R59: =+IF($L59-$J59<=0,-$L59+$J59,0) -> 0 | S59: =+ROUND($H59*R59,2) -> 0 | U59: =+ROUND($H59*T59,2) -> 0 | Z59: 0
B60: 8.03 | C60: =+C59+1 -> #REF! | D60: Manguito de Empalme para Conductor de 35 mm² | G60: u | H60: 12.11 | J60: 17 | K60: =+ROUND($H60*J60,2) -> 205.87 | L60: =+[191]Metrados!E61 -> 0 | M60: =+ROUND($H60*L60,2) -> 0 | N60: =+IF($L60-$J60>=0,$L60-$J60,0) -> 0 | O60: =+ROUND($H60*N60,2) -> 0 | Q60: =+ROUND($H60*P60,2) -> 0 | R60: =+IF($L60-$J60<=0,-$L60+$J60,0) -> 17 | S60: =+ROUND($H60*R60,2) -> 205.87 | U60: =+ROUND($H60*T60,2) -> 0 | Z60: 0
B61: 8.04 | C61: =+C60+1 -> #REF! | D61: Manguito de Reparacion para Conductor de 35 mm² | G61: u | H61: 11.59 | J61: 7 | K61: =+ROUND($H61*J61,2) -> 81.13 | L61: =+[191]Metrados!E62 -> 0 | M61: =+ROUND($H61*L61,2) -> 0 | N61: =+IF($L61-$J61>=0,$L61-$J61,0) -> 0 | O61: =+ROUND($H61*N61,2) -> 0 | Q61: =+ROUND($H61*P61,2) -> 0 | R61: =+IF($L61-$J61<=0,-$L61+$J61,0) -> 7 | S61: =+ROUND($H61*R61,2) -> 81.13 | U61: =+ROUND($H61*T61,2) -> 0 | Z61: 0
B62: 8.05 | C62: =+C61+1 -> #REF! | D62: Grapa de Doble Via de Aluminio para Conductor de 35 mm² | G62: u | H62: 7.77 | J62: 84 | K62: =+ROUND($H62*J62,2) -> 652.68 | L62: =+[191]Metrados!E63 -> 190 | M62: =+ROUND($H62*L62,2) -> 1476.3 | N62: =+IF($L62-$J62>=0,$L62-$J62,0) -> 106 | O62: =+ROUND($H62*N62,2) -> 823.62 | Q62: =+ROUND($H62*P62,2) -> 0 | R62: =+IF($L62-$J62<=0,-$L62+$J62,0) -> 0 | S62: =+ROUND($H62*R62,2) -> 0 | U62: =+ROUND($H62*T62,2) -> 0 | Z62: 0
B63: 8.06 | C63: =+C62+1 -> #REF! | D63: Grapa de Doble Via de Aluminio para Conductor de 70 mm² | G63: u | H63: 10.36 | J63: 2 | K63: =+ROUND($H63*J63,2) -> 20.72 | L63: =+[191]Metrados!E64 -> 6 | M63: =+ROUND($H63*L63,2) -> 62.16 | N63: =+IF($L63-$J63>=0,$L63-$J63,0) -> 4 | O63: =+ROUND($H63*N63,2) -> 41.44 | Q63: =+ROUND($H63*P63,2) -> 0 | R63: =+IF($L63-$J63<=0,-$L63+$J63,0) -> 0 | S63: =+ROUND($H63*R63,2) -> 0 | U63: =+ROUND($H63*T63,2) -> 0 | Z63: 0
B64: 8.07 | C64: =+C63+1 -> #REF! | D64: Alambre de Amarre Aluminio Recocido de 16 mm² | G64: m | H64: 1.41 | J64: 1052.3 | K64: =+ROUND($H64*J64,2) -> 1483.74 | L64: =+[191]Metrados!E65 -> 905 | M64: =+ROUND($H64*L64,2) -> 1276.05 | N64: =+IF($L64-$J64>=0,$L64-$J64,0) -> 0 | O64: =+ROUND($H64*N64,2) -> 0 | Q64: =+ROUND($H64*P64,2) -> 0 | R64: =+IF($L64-$J64<=0,-$L64+$J64,0) -> 147.3 | S64: =+ROUND($H64*R64,2) -> 207.69 | U64: =+ROUND($H64*T64,2) -> 0 | Z64: 0
B65: 8.08 | C65: =+C64+1 -> #REF! | D65: Amortiguador de Vibracion Tipo Stockbridge para Conductor de 35 mm² | G65: u | H65: 36.01 | J65: 4 | K65: =+ROUND($H65*J65,2) -> 144.04 | L65: =+[191]Metrados!E66 -> 2 | M65: =+ROUND($H65*L65,2) -> 72.02 | N65: =+IF($L65-$J65>=0,$L65-$J65,0) -> 0 | O65: =+ROUND($H65*N65,2) -> 0 | Q65: =+ROUND($H65*P65,2) -> 0 | R65: =+IF($L65-$J65<=0,-$L65+$J65,0) -> 2 | S65: =+ROUND($H65*R65,2) -> 72.02 | U65: =+ROUND($H65*T65,2) -> 0 | Z65: 0
B66: 8.09 | C66: =+C65+1 -> #REF! | D66: Amortiguador de Vibracion Tipo Stockbridge para Conductor de 70 mm² | G66: u | H66: 44.34 | J66: 8 | K66: =+ROUND($H66*J66,2) -> 354.72 | L66: =+[191]Metrados!E67 -> 6 | M66: =+ROUND($H66*L66,2) -> 266.04 | N66: =+IF($L66-$J66>=0,$L66-$J66,0) -> 0 | O66: =+ROUND($H66*N66,2) -> 0 | Q66: =+ROUND($H66*P66,2) -> 0 | R66: =+IF($L66-$J66<=0,-$L66+$J66,0) -> 2 | S66: =+ROUND($H66*R66,2) -> 88.68 | U66: =+ROUND($H66*T66,2) -> 0 | Z66: 0
B67: 8.1 | C67: =+C66+1 -> #REF! | D67: Grapa de Angulo para Conductor de 35 mm² | G67: u | H67: 29.37 | J67: 14 | K67: =+ROUND($H67*J67,2) -> 411.18 | L67: =+[191]Metrados!E68 -> 2 | M67: =+ROUND($H67*L67,2) -> 58.74 | N67: =+IF($L67-$J67>=0,$L67-$J67,0) -> 0 | O67: =+ROUND($H67*N67,2) -> 0 | Q67: =+ROUND($H67*P67,2) -> 0 | R67: =+IF($L67-$J67<=0,-$L67+$J67,0) -> 12 | S67: =+ROUND($H67*R67,2) -> 352.44 | T67: =+R67 -> 12 | U67: =+ROUND($H67*T67,2) -> 352.44 | V67: Se vincula con el mayor metrado de la partida 8.12 | Z67: 0
B68: 8.11 | C68: =+C67+1 -> #REF! | D68: Grapa de Angulo para Conductor de 70 mm² | G68: u | H68: 47.48 | J68: 4 | K68: =+ROUND($H68*J68,2) -> 189.92 | L68: =+[191]Metrados!E69 -> 0 | M68: =+ROUND($H68*L68,2) -> 0 | N68: =+IF($L68-$J68>=0,$L68-$J68,0) -> 0 | O68: =+ROUND($H68*N68,2) -> 0 | Q68: =+ROUND($H68*P68,2) -> 0 | R68: =+IF($L68-$J68<=0,-$L68+$J68,0) -> 4 | S68: =+ROUND($H68*R68,2) -> 189.92 | U68: =+ROUND($H68*T68,2) -> 0 | Z68: 0
B69: 8.12 | C69: =+C63+1 -> #REF! | D69: Grapa de Anclaje para Conductor de 35 mm² | G69: u | H69: 25.34 | J69: 129 | K69: =+ROUND($H69*J69,2) -> 3268.86 | L69: =+[191]Metrados!E70 -> 273 | M69: =+ROUND($H69*L69,2) -> 6917.82 | N69: =+IF($L69-$J69>=0,$L69-$J69,0) -> 144 | O69: =+ROUND($H69*N69,2) -> 3648.96 | Q69: =+ROUND($H69*P69,2) -> 0 | R69: =+IF($L69-$J69<=0,-$L69+$J69,0) -> 0 | S69: =+ROUND($H69*R69,2) -> 0 | U69: =+ROUND($H69*T69,2) -> 0 | Z69: 0
B70: 8.13 | C70: =+C59+1 -> #REF! | D70: Grapa de Anclaje para Conductor de 70 mm² | G70: u | H70: 49.03 | J70: 8 | K70: =+ROUND($H70*J70,2) -> 392.24 | L70: =+[191]Metrados!E71 -> 8 | M70: =+ROUND($H70*L70,2) -> 392.24 | N70: =+IF($L70-$J70>=0,$L70-$J70,0) -> 0 | O70: =+ROUND($H70*N70,2) -> 0 | Q70: =+ROUND($H70*P70,2) -> 0 | R70: =+IF($L70-$J70<=0,-$L70+$J70,0) -> 0 | S70: =+ROUND($H70*R70,2) -> 0 | U70: =+ROUND($H70*T70,2) -> 0 | Z70: 0
B71: 8.14 | C71: =+#REF!+1 -> #REF! | D71: Cinta plana de armar de aluminio | G71: m | I71: 1 | K71: =+ROUND($H71*J71,2) -> 0 | L71: =+[191]Metrados!E72 -> 281 | M71: =+ROUND($I71*L71,2) -> 281 | O71: =+ROUND($H71*N71,2) -> 0 | P71: =+L71 -> 281 | Q71: =+ROUND($I71*P71,2) -> 281 | S71: =+ROUND($H71*R71,2) -> 0 | U71: =+ROUND($H71*T71,2) -> 0 | Z71: 0
B72: 8.15 | C72: =+#REF!+1 -> #REF! | D72: Varilla de Armar preformada Doble para Conductor de 35 mm² | G72: u | I72: 15.8 | K72: =+ROUND($H72*J72,2) -> 0 | L72: =+[191]Metrados!E73 -> 2 | M72: =+ROUND($I72*L72,2) -> 31.6 | O72: =+ROUND($H72*N72,2) -> 0 | P72: =+L72 -> 2 | Q72: =+ROUND($I72*P72,2) -> 31.6 | S72: =+ROUND($H72*R72,2) -> 0 | U72: =+ROUND($H72*T72,2) -> 0 | Z72: 0
C73: =+C71+1 -> #REF! | F73: =+"SUB-TOTAL "&B57&": " -> SUB-TOTAL 8: | K73: =+SUM(K58:K72) -> 10561.8 | M73: =+SUM(M58:M72) -> 13670.98 | O73: =+SUM(O58:O72) -> 4514.02 | Q73: =+SUM(Q58:Q72) -> 312.6 | S73: =+SUM(S58:S72) -> 1717.44 | U73: =+SUM(U58:U72) -> 372.82 | Z73: 0
B74: 9 | C74: =+C73+1 -> #REF! | D74: CONDUCTOR DE COBRE | Z74: 0
B75: 9.01 | C75: =+C74+1 -> #REF! | D75: Cable de Acero con Recubrimiento Metalúrgico de Cu de 4 AWG (21,15 mm²), para Puesta a Tierra | G75: m | H75: 12.8 | J75: 2936.1 | K75: =+ROUND($H75*J75,2) -> 37582.08 | L75: =+[191]Metrados!E76 -> 3162.9 | M75: =+ROUND($H75*L75,2) -> 40485.12 | N75: =+IF($L75-$J75>=0,$L75-$J75,0) -> 226.8 | O75: =+ROUND($H75*N75,2) -> 2903.04 | Q75: =+ROUND($H75*P75,2) -> 0 | R75: =+IF($L75-$J75<=0,-$L75+$J75,0) -> 0 | S75: =+ROUND($H75*R75,2) -> 0 | U75: =+ROUND($H75*T75,2) -> 0 | Z75: 0
C76: =+#REF!+1 -> #REF! | F76: =+"SUB-TOTAL "&B74&": " -> SUB-TOTAL 9: | K76: =+SUM(K75:K75) -> 37582.08 | M76: =+SUM(M75:M75) -> 40485.12 | O76: =+SUM(O75:O75) -> 2903.04 | Q76: =+SUM(Q75:Q75) -> 0 | S76: =+SUM(S75:S75) -> 0 | U76: =+SUM(U75:U75) -> 0 | Z76: 0
B77: 10 | C77: =+C76+1 -> #REF! | D77: MATERIAL DE FERRETERIA PARA POSTES Y CRUCETAS | Z77: 0
B78: 10.01 | C78: =+C77+1 -> #REF! | D78: Perno Cabeza Coche de AºGº de 13 mm Ø x 152 mm longitud, 76 mm maquinado, con Arandela, Tuerca y Contratuerca | G78: u | H78: 3.86 | J78: 9 | K78: =+ROUND($H78*J78,2) -> 34.74 | L78: =+[191]Metrados!E79 -> 33 | M78: =+ROUND($H78*L78,2) -> 127.38 | N78: =+IF($L78-$J78>=0,$L78-$J78,0) -> 24 | O78: =+ROUND($H78*N78,2) -> 92.64 | Q78: =+ROUND($H78*P78,2) -> 0 | R78: =+IF($L78-$J78<=0,-$L78+$J78,0) -> 0 | S78: =+ROUND($H78*R78,2) -> 0 | U78: =+ROUND($H78*T78,2) -> 0 | Z78: 26
B79: 10.02 | C79: =+C78+1 -> #REF! | D79: Perno de A°G° de 13 mm Ø x 254 mm, provisto de Tuerca y Contratuerca | G79: u | H79: 5.57 | J79: 26 | K79: =+ROUND($H79*J79,2) -> 144.82 | L79: =+[191]Metrados!E80 -> 0 | M79: =+ROUND($H79*L79,2) -> 0 | N79: =+IF($L79-$J79>=0,$L79-$J79,0) -> 0 | O79: =+ROUND($H79*N79,2) -> 0 | Q79: =+ROUND($H79*P79,2) -> 0 | R79: =+IF($L79-$J79<=0,-$L79+$J79,0) -> 26 | S79: =+ROUND($H79*R79,2) -> 144.82 | T79: =+R79 -> 26 | U79: =+ROUND($H79*T79,2) -> 144.82 | V79: Se vincula con el mayor metrado de la partida 10.04 | Z79: 0
B80: 10.03 | C80: =+C79+1 -> #REF! | D80: Perno de A°G° de 13 mm Ø x 305 mm, provisto de Tuerca y Contratuerca | G80: u | H80: 6.25 | J80: 7 | K80: =+ROUND($H80*J80,2) -> 43.75 | L80: =+[191]Metrados!E81 -> 21 | M80: =+ROUND($H80*L80,2) -> 131.25 | N80: =+IF($L80-$J80>=0,$L80-$J80,0) -> 14 | O80: =+ROUND($H80*N80,2) -> 87.5 | Q80: =+ROUND($H80*P80,2) -> 0 | R80: =+IF($L80-$J80<=0,-$L80+$J80,0) -> 0 | S80: =+ROUND($H80*R80,2) -> 0 | U80: =+ROUND($H80*T80,2) -> 0 | Z80: 13
B81: 10.04 | C81: =+C80+1 -> #REF! | D81: Perno de A°G° de 16 mm Ø x 254 mm, provisto de Tuerca y Contratuerca | G81: u | H81: 8.61 | J81: 18 | K81: =+ROUND($H81*J81,2) -> 154.98 | L81: =+[191]Metrados!E82 -> 172 | M81: =+ROUND($H81*L81,2) -> 1480.92 | N81: =+IF($L81-$J81>=0,$L81-$J81,0) -> 154 | O81: =+ROUND($H81*N81,2) -> 1325.94 | Q81: =+ROUND($H81*P81,2) -> 0 | R81: =+IF($L81-$J81<=0,-$L81+$J81,0) -> 0 | S81: =+ROUND($H81*R81,2) -> 0 | U81: =+ROUND($H81*T81,2) -> 0 | Z81: 0
B82: 10.05 | C82: =+C81+1 -> #REF! | D82: Perno de A°G° de 16 mm Ø x 305 mm, provisto de Tuerca y Contratuerca | G82: u | H82: 9.14 | J82: 18 | K82: =+ROUND($H82*J82,2) -> 164.52 | L82: =+[191]Metrados!E83 -> 14 | M82: =+ROUND($H82*L82,2) -> 127.96 | N82: =+IF($L82-$J82>=0,$L82-$J82,0) -> 0 | O82: =+ROUND($H82*N82,2) -> 0 | Q82: =+ROUND($H82*P82,2) -> 0 | R82: =+IF($L82-$J82<=0,-$L82+$J82,0) -> 4 | S82: =+ROUND($H82*R82,2) -> 36.56 | T82: =+R82 -> 4 | U82: =+ROUND($H82*T82,2) -> 36.56 | V82: Se vincula con el mayor metrado de la partida 10.04 | Z82: 0
B83: 10.06 | C83: =+C82+1 -> #REF! | D83: Perno de A°G° de 16 mm Ø x 356 mm, provisto de Tuerca y Contratuerca | G83: u | H83: 9.82 | J83: 8 | K83: =+ROUND($H83*J83,2) -> 78.56 | L83: =+[191]Metrados!E84 -> 5 | M83: =+ROUND($H83*L83,2) -> 49.1 | N83: =+IF($L83-$J83>=0,$L83-$J83,0) -> 0 | O83: =+ROUND($H83*N83,2) -> 0 | Q83: =+ROUND($H83*P83,2) -> 0 | R83: =+IF($L83-$J83<=0,-$L83+$J83,0) -> 3 | S83: =+ROUND($H83*R83,2) -> 29.46 | T83: =+R83 -> 3 | U83: =+ROUND($H83*T83,2) -> 29.46 | V83: Se vincula con el mayor metrado de la partida 10.04 | Z83: 0
B84: 10.07 | C84: =+C83+1 -> #REF! | D84: Perno de A°G° de 16 mm Ø x 508 mm, provisto de Tuerca y Contratuerca | G84: u | H84: 12.54 | J84: 3 | K84: =+ROUND($H84*J84,2) -> 37.62 | L84: =+[191]Metrados!E85 -> 104 | M84: =+ROUND($H84*L84,2) -> 1304.16 | N84: =+IF($L84-$J84>=0,$L84-$J84,0) -> 101 | O84: =+ROUND($H84*N84,2) -> 1266.54 | Q84: =+ROUND($H84*P84,2) -> 0 | R84: =+IF($L84-$J84<=0,-$L84+$J84,0) -> 0 | S84: =+ROUND($H84*R84,2) -> 0 | U84: =+ROUND($H84*T84,2) -> 0 | Z84: 1
B85: 10.08 | C85: =+C84+1 -> #REF! | D85: Perno Doble Armado de A°G° de 16 mm Ø x 508 mm, provisto de 4 Tuercas y 4 Contratuercas | G85: u | H85: 18.18 | J85: 380 | K85: =+ROUND($H85*J85,2) -> 6908.4 | L85: =+[191]Metrados!E86 -> 107 | M85: =+ROUND($H85*L85,2) -> 1945.26 | N85: =+IF($L85-$J85>=0,$L85-$J85,0) -> 0 | O85: =+ROUND($H85*N85,2) -> 0 | Q85: =+ROUND($H85*P85,2) -> 0 | R85: =+IF($L85-$J85<=0,-$L85+$J85,0) -> 273 | S85: =+ROUND($H85*R85,2) -> 4963.14 | T85: =+N84 -> 101 | U85: =+ROUND($H85*T85,2) -> 1836.18 | V85: Se vincula con el mayor metrado de la partida 10.07 | Z85: -1
B86: 10.09 | C86: =+C85+1 -> #REF! | D86: Perno Ojo de A°G° de 16 mm Ø x 254 mm, provisto de Tuerca y Contratuerca | G86: u | H86: 13.11 | J86: 61 | K86: =+ROUND($H86*J86,2) -> 799.71 | L86: =+[191]Metrados!E87 -> 70 | M86: =+ROUND($H86*L86,2) -> 917.7 | N86: =+IF($L86-$J86>=0,$L86-$J86,0) -> 9 | O86: =+ROUND($H86*N86,2) -> 117.99 | Q86: =+ROUND($H86*P86,2) -> 0 | R86: =+IF($L86-$J86<=0,-$L86+$J86,0) -> 0 | S86: =+ROUND($H86*R86,2) -> 0 | U86: =+ROUND($H86*T86,2) -> 0 | Z86: 0
B87: 10.1 | C87: =+C86+1 -> #REF! | D87: Perno Ojo de A°G° de 16 mm Ø x 305 mm, provisto de Tuerca y Contratuerca | G87: u | H87: 14.35 | J87: 47 | K87: =+ROUND($H87*J87,2) -> 674.45 | L87: =+[191]Metrados!E88 -> 21 | M87: =+ROUND($H87*L87,2) -> 301.35 | N87: =+IF($L87-$J87>=0,$L87-$J87,0) -> 0 | O87: =+ROUND($H87*N87,2) -> 0 | Q87: =+ROUND($H87*P87,2) -> 0 | R87: =+IF($L87-$J87<=0,-$L87+$J87,0) -> 26 | S87: =+ROUND($H87*R87,2) -> 373.1 | T87: =+P98 -> 24 | U87: =+ROUND($H87*T87,2) -> 344.4 | V87: Se vincula con la partida nueva 10.21 | Z87: 0
B88: 10.11 | C88: =+C87+1 -> #REF! | D88: Perno Ojo de A°G° de 16 mm Ø x 356 mm, provisto de Tuerca y Contratuerca | G88: u | H88: 14.6 | J88: 9 | K88: =+ROUND($H88*J88,2) -> 131.4 | L88: =+[191]Metrados!E89 -> 0 | M88: =+ROUND($H88*L88,2) -> 0 | N88: =+IF($L88-$J88>=0,$L88-$J88,0) -> 0 | O88: =+ROUND($H88*N88,2) -> 0 | Q88: =+ROUND($H88*P88,2) -> 0 | R88: =+IF($L88-$J88<=0,-$L88+$J88,0) -> 9 | S88: =+ROUND($H88*R88,2) -> 131.4 | T88: =+R88 -> 9 | U88: =+ROUND($H88*T88,2) -> 131.4 | V88: Se vincula con el mayor metrado de la partida 10.09 | Z88: 0
B89: 10.12 | C89: =+C83+1 -> #REF! | D89: Tuerca-Ojo para Perno de 16 mm Ø | G89: u | H89: 11.17 | J89: 38 | K89: =+ROUND($H89*J89,2) -> 424.46 | L89: =+[191]Metrados!E90 -> 112 | M89: =+ROUND($H89*L89,2) -> 1251.04 | N89: =+IF($L89-$J89>=0,$L89-$J89,0) -> 74 | O89: =+ROUND($H89*N89,2) -> 826.58 | Q89: =+ROUND($H89*P89,2) -> 0 | R89: =+IF($L89-$J89<=0,-$L89+$J89,0) -> 0 | S89: =+ROUND($H89*R89,2) -> 0 | U89: =+ROUND($H89*T89,2) -> 0 | Z89: 0
B90: 10.13 | C90: =+C89+1 -> #REF! | D90: Tirafondo de A°G° de 13 mm ø x 102 mm de longitud | G90: u | H90: 2.74 | J90: 4 | K90: =+ROUND($H90*J90,2) -> 10.96 | L90: =+[191]Metrados!E91 -> 0 | M90: =+ROUND($H90*L90,2) -> 0 | N90: =+IF($L90-$J90>=0,$L90-$J90,0) -> 0 | O90: =+ROUND($H90*N90,2) -> 0 | Q90: =+ROUND($H90*P90,2) -> 0 | R90: =+IF($L90-$J90<=0,-$L90+$J90,0) -> 4 | S90: =+ROUND($H90*R90,2) -> 10.96 | T90: =+N80 -> 14 | U90: =+ROUND($H90*T90,2) -> 38.36 | V90: Se vincula con el mayor metrado de la partida 10.03 | Z90: 0
B91: 10.14 | C91: =+C90+1 -> #REF! | D91: Brazo-Soporte (Riostra) de Perfil Angular de A°G° de 38 x 38 x 5 mm y 710 mm longitud | G91: u | H91: 22.46 | J91: 13 | K91: =+ROUND($H91*J91,2) -> 291.98 | L91: =+[191]Metrados!E92 -> 33 | M91: =+ROUND($H91*L91,2) -> 741.18 | N91: =+IF($L91-$J91>=0,$L91-$J91,0) -> 20 | O91: =+ROUND($H91*N91,2) -> 449.2 | Q91: =+ROUND($H91*P91,2) -> 0 | R91: =+IF($L91-$J91<=0,-$L91+$J91,0) -> 0 | S91: =+ROUND($H91*R91,2) -> 0 | U91: =+ROUND($H91*T91,2) -> 0 | Z91: 26
B92: 10.15 | C92: =+C91+1 -> #REF! | D92: Arandela Cuadrada Plana de A° G°, 57 x 57 x 5 mm, Agujero de 18 mm Ø | G92: u | H92: 1.67 | J92: 618 | K92: =+ROUND($H92*J92,2) -> 1032.06 | L92: =+[191]Metrados!E93 -> 518 | M92: =+ROUND($H92*L92,2) -> 865.06 | N92: =+IF($L92-$J92>=0,$L92-$J92,0) -> 0 | O92: =+ROUND($H92*N92,2) -> 0 | Q92: =+ROUND($H92*P92,2) -> 0 | R92: =+IF($L92-$J92<=0,-$L92+$J92,0) -> 100 | S92: =+ROUND($H92*R92,2) -> 167 | U92: =+ROUND($H92*T92,2) -> 0 | Z92: 12
B93: 10.16 | C93: =+C92+1 -> #REF! | D93: Arandela Cuadrada curva de A° G°, 57 x 57 x 5 mm, Agujero de 18 mm Ø | G93: u | H93: 1.67 | J93: 979 | K93: =+ROUND($H93*J93,2) -> 1634.93 | L93: =+[191]Metrados!E94 -> 772 | M93: =+ROUND($H93*L93,2) -> 1289.24 | N93: =+IF($L93-$J93>=0,$L93-$J93,0) -> 0 | O93: =+ROUND($H93*N93,2) -> 0 | Q93: =+ROUND($H93*P93,2) -> 0 | R93: =+IF($L93-$J93<=0,-$L93+$J93,0) -> 207 | S93: =+ROUND($H93*R93,2) -> 345.69 | U93: =+ROUND($H93*T93,2) -> 0 | Z93: 10
B94: 10.17 | C94: =+C93+1 -> #REF! | D94: Plantillas para Identificación y/o codificación de Postes (Peligro, Identificación y/o codificación y Fases) | G94: Jgo. | H94: 23.08 | J94: 21 | K94: =+ROUND($H94*J94,2) -> 484.68 | L94: =+[191]Metrados!E95 -> 22 | M94: =+ROUND($H94*L94,2) -> 507.76 | N94: =+IF($L94-$J94>=0,$L94-$J94,0) -> 1 | O94: =+ROUND($H94*N94,2) -> 23.08 | Q94: =+ROUND($H94*P94,2) -> 0 | R94: =+IF($L94-$J94<=0,-$L94+$J94,0) -> 0 | S94: =+ROUND($H94*R94,2) -> 0 | U94: =+ROUND($H94*T94,2) -> 0 | Z94: 0
B95: 10.18 | C95: =+C94+1 -> #REF! | D95: Placa de Señal de Peligro y accesorios de fijación | G95: u | H95: 18.24 | J95: 9 | K95: =+ROUND($H95*J95,2) -> 164.16 | L95: =+[191]Metrados!E96 -> 0 | M95: =+ROUND($H95*L95,2) -> 0 | N95: =+IF($L95-$J95>=0,$L95-$J95,0) -> 0 | O95: =+ROUND($H95*N95,2) -> 0 | Q95: =+ROUND($H95*P95,2) -> 0 | R95: =+IF($L95-$J95<=0,-$L95+$J95,0) -> 9 | S95: =+ROUND($H95*R95,2) -> 164.16 | T95: =+N94 -> 1 | U95: =+ROUND($H95*T95,2) -> 18.24 | V95: Se vincula con el mayor metrado de la partida 10.17 | Z95: 0
B96: 10.19 | C96: =+C95+1 -> #REF! | D96: Placa de Identificación y/o codificación de Estructura y accesorios de fijación | G96: u | H96: 16.84 | J96: 9 | K96: =+ROUND($H96*J96,2) -> 151.56 | L96: =+[191]Metrados!E97 -> 0 | M96: =+ROUND($H96*L96,2) -> 0 | N96: =+IF($L96-$J96>=0,$L96-$J96,0) -> 0 | O96: =+ROUND($H96*N96,2) -> 0 | Q96: =+ROUND($H96*P96,2) -> 0 | R96: =+IF($L96-$J96<=0,-$L96+$J96,0) -> 9 | S96: =+ROUND($H96*R96,2) -> 151.56 | T96: =+N94 -> 1 | U96: =+ROUND($H96*T96,2) -> 16.84 | V96: Se vincula con el mayor metrado de la partida 10.17 | Z96: 0
B97: 10.2 | C97: =+C79+1 -> #REF! | D97: Placa de Secuencia de Fases y accesorios de fijación | G97: u | H97: 18.78 | J97: 9 | K97: =+ROUND($H97*J97,2) -> 169.02 | L97: =+[191]Metrados!E98 -> 0 | M97: =+ROUND($H97*L97,2) -> 0 | N97: =+IF($L97-$J97>=0,$L97-$J97,0) -> 0 | O97: =+ROUND($H97*N97,2) -> 0 | Q97: =+ROUND($H97*P97,2) -> 0 | R97: =+IF($L97-$J97<=0,-$L97+$J97,0) -> 9 | S97: =+ROUND($H97*R97,2) -> 169.02 | T97: =+N94 -> 1 | U97: =+ROUND($H97*T97,2) -> 18.78 | V97: Se vincula con el mayor metrado de la partida 10.17 | Z97: 0
B98: 10.21 | C98: =+#REF!+1 -> #REF! | D98: Perno Ojo de A°G° de 16 mm Ø x 203 mm, provisto de Tuerca y Contratuerca | G98: u | I98: =+H86*0.9 -> 11.799 | K98: =+ROUND($H98*J98,2) -> 0 | L98: =+[191]Metrados!E99 -> 24 | M98: =+ROUND($I98*L98,2) -> 283.18 | O98: =+ROUND($H98*N98,2) -> 0 | P98: =+L98 -> 24 | Q98: =+ROUND($I98*P98,2) -> 283.18 | S98: =+ROUND($H98*R98,2) -> 0 | U98: =+ROUND($H98*T98,2) -> 0 | Z98: 0
B99: 10.22 | C99: =+#REF!+1 -> #REF! | D99: Soporte separador de vertice de postes de A°G° fabricado con platina de 76 X 6,4 mm | G99: u | I99: 38 | K99: =+ROUND($H99*J99,2) -> 0 | L99: =+[191]Metrados!E100 -> 2 | M99: =+ROUND($I99*L99,2) -> 76 | O99: =+ROUND($H99*N99,2) -> 0 | P99: =+L99 -> 2 | Q99: =+ROUND($I99*P99,2) -> 76 | S99: =+ROUND($H99*R99,2) -> 0 | U99: =+ROUND($H99*T99,2) -> 0 | Z99: 0
B100: 10.23 | C100: =+#REF!+1 -> #REF! | D100: Braquete de A°G° para soporte de aislador tipo Line Post en cabea de poste | G100: u | I100: 50 | K100: =+ROUND($H100*J100,2) -> 0 | L100: =+[191]Metrados!E101 -> 75 | M100: =+ROUND($I100*L100,2) -> 3750 | O100: =+ROUND($H100*N100,2) -> 0 | P100: =+L100 -> 75 | Q100: =+ROUND($I100*P100,2) -> 3750 | S100: =+ROUND($H100*R100,2) -> 0 | U100: =+ROUND($H100*T100,2) -> 0 | Z100: 0
C101: =+C98+1 -> #REF! | F101: =+"SUB-TOTAL "&B77&": " -> SUB-TOTAL 10: | K101: =+SUM(K78:K100) -> 13536.76 | M101: =+SUM(M78:M100) -> 15148.54 | O101: =+SUM(O78:O100) -> 4189.47 | Q101: =+SUM(Q78:Q100) -> 4109.18 | S101: =+SUM(S78:S100) -> 6686.87 | U101: =+SUM(U78:U100) -> 2615.04 | Z101: 0
B102: 11 | C102: =+C101+1 -> #REF! | D102: RETENIDAS Y ANCLAJES | Z102: 0
B103: 11.01 | C103: =+C102+1 -> #REF! | D103: Cable de Acero Grado Siemens Martin, de 10 mm Ø, 7 hilos | G103: m | H103: 4.31 | J103: 881 | K103: =+ROUND($H103*J103,2) -> 3797.11 | L103: =+[191]Metrados!E104 -> 0 | M103: =+ROUND($H103*L103,2) -> 0 | N103: =+IF($L103-$J103>=0,$L103-$J103,0) -> 0 | O103: =+ROUND($H103*N103,2) -> 0 | Q103: =+ROUND($H103*P103,2) -> 0 | R103: =+IF($L103-$J103<=0,-$L103+$J103,0) -> 881 | S103: =+ROUND($H103*R103,2) -> 3797.11 | U103: =+ROUND($H103*T103,2) -> 0 | Z103: 0
B104: 11.02 | C104: =+C103+1 -> #REF! | D104: Varilla de Anclaje de A°G° de 16 mm Ø x 2,40 m, provisto de Ojal Guardacabo en un extremo; Tuerca y Contratuerca en el otro | G104: u | H104: 46.85 | J104: 66 | K104: =+ROUND($H104*J104,2) -> 3092.1 | L104: =+[191]Metrados!E105 -> 83 | M104: =+ROUND($H104*L104,2) -> 3888.55 | N104: =+IF($L104-$J104>=0,$L104-$J104,0) -> 17 | O104: =+ROUND($H104*N104,2) -> 796.45 | Q104: =+ROUND($H104*P104,2) -> 0 | R104: =+IF($L104-$J104<=0,-$L104+$J104,0) -> 0 | S104: =+ROUND($H104*R104,2) -> 0 | U104: =+ROUND($H104*T104,2) -> 0 | Z104: 0
B105: 11.03 | C105: =+C104+1 -> #REF! | D105: Mordaza Preformada de A°G° para Cable de 10 mm Ø | G105: u | H105: 11.69 | J105: 208 | K105: =+ROUND($H105*J105,2) -> 2431.52 | L105: =+[191]Metrados!E106 -> 166 | M105: =+ROUND($H105*L105,2) -> 1940.54 | N105: =+IF($L105-$J105>=0,$L105-$J105,0) -> 0 | O105: =+ROUND($H105*N105,2) -> 0 | Q105: =+ROUND($H105*P105,2) -> 0 | R105: =+IF($L105-$J105<=0,-$L105+$J105,0) -> 42 | S105: =+ROUND($H105*R105,2) -> 490.98 | U105: =+ROUND($H105*T105,2) -> 0 | Z105: 0
B106: 11.04 | C106: =+C105+1 -> #REF! | D106: Alambre de Acero N° 14 para Entorchado | G106: m | H106: 0.71 | J106: 312 | K106: =+ROUND($H106*J106,2) -> 221.52 | L106: =+[191]Metrados!E107 -> 124.5 | M106: =+ROUND($H106*L106,2) -> 88.4 | N106: =+IF($L106-$J106>=0,$L106-$J106,0) -> 0 | O106: =+ROUND($H106*N106,2) -> 0 | Q106: =+ROUND($H106*P106,2) -> 0 | R106: =+IF($L106-$J106<=0,-$L106+$J106,0) -> 187.5 | S106: =+ROUND($H106*R106,2) -> 133.13 | U106: =+ROUND($H106*T106,2) -> 0 | Z106: 0
B107: 11.05 | C107: =+C106+1 -> #REF! | D107: Arandela de Anclaje de A°G°, 102 x 102 x 6,35 mm, Agujero de 18 mmø | G107: u | H107: 5.46 | J107: 66 | K107: =+ROUND($H107*J107,2) -> 360.36 | L107: =+[191]Metrados!E108 -> 83 | M107: =+ROUND($H107*L107,2) -> 453.18 | N107: =+IF($L107-$J107>=0,$L107-$J107,0) -> 17 | O107: =+ROUND($H107*N107,2) -> 92.82 | Q107: =+ROUND($H107*P107,2) -> 0 | R107: =+IF($L107-$J107<=0,-$L107+$J107,0) -> 0 | S107: =+ROUND($H107*R107,2) -> 0 | U107: =+ROUND($H107*T107,2) -> 0 | Z107: 0
...

Sheet FP LP
B3: FORMULA POLINÓMICA
C6: PROYECTO :
C7: AMPLIACIÓN DEL SERVICIO DE ENERGÍA ELÉCTRICA EN LA PROVINCIA DEL SANTA Y EN EL DISTRITO DE PAMPAROMAS – DEPARTAMENTO DE ANCASH”
C9: LINEAS PRIMARIAS
C10: PRESUPUESTO BASE S/ | D10: =+'RES-LP'!H18 -> 1465769.8 | K10: =D10=SUM(G13:G27) -> TRUE
B12: Nº | C12: ELEMENTO REPRESENTATIVO | D12: INDICE | E12: SIMBOLO | F12: SIMBOLO MONOMIO | G12: MONTO | H12: INCIDENCIA | I12: % PARCIAL | J12: COEFICIENTE
B13: 1 | C13: POSTES DE MADERA IMPORTADA | D13: 042 | E13: PM | F13: PC | G13: =+'Mtdo-Ppto LP'!M32 -> 0 | H13: =ROUND(G13/$D$10,3) -> 0 | I13: =ROUND(G13/SUM($G$13:$G$16),4) -> 0 | J13: =ROUND(SUM(H13:H16),3) -> 0.176
C14: CRUCETAS DE MADERA | D14: 043 | E14: CM | G14: =+'Mtdo-Ppto LP'!M22 -> 3578 | H14: =ROUND(G14/$D$10,3) -> 0.002 | I14: =ROUND(G14/SUM($G$13:$G$16),4) -> 0.0139
C15: POSTES DE CONCRETO | D15: 062 | E15: PC | G15: =+'Mtdo-Ppto LP'!M29+'Mtdo-Ppto LP'!M36 -> 218234.24 | H15: =ROUND(G15/$D$10,3-0.1) -> 0.15 | I15: =ROUND(G15/SUM($G$13:$G$16),4) -> 0.8481
C16: OTROS MATERIALES DE CONCRETO ARMADO | D16: 062 | E16: CC | G16: =+'Mtdo-Ppto LP'!M42 -> 35519.2 | H16: =ROUND(G16/$D$10,3) -> 0.024 | I16: =ROUND(G16/SUM($G$13:$G$16),4) -> 0.138
B17: 2 | C17: CONDUCTORES DE AAAC Y ACCESORIOS | D17: 030 | E17: DI | F17: DI | G17: =+'Mtdo-Ppto LP'!M56+'Mtdo-Ppto LP'!M73 -> 133692.72 | H17: =ROUND(G17/$D$10,3) -> 0.091 | I17: =ROUND(G17/SUM($G$17:$G$18),4) -> 0.9068 | J17: =ROUND(SUM(H17:H18),3) -> 0.1
C18: EQUIPOS DE PROTECCIÓN | D18: 011 | E18: AE1 | G18: =+'Mtdo-Ppto LP'!M136 -> 13745.66 | H18: =ROUND(G18/$D$10,3) -> 0.009 | I18: =ROUND(G18/SUM($G$17:$G$18),4) -> 0.0932
B19: 3 | C19: AISLADORES Y ACCESORIOS | D19: 011 | E19: AE2 | F19: AE2 | G19: =+'Mtdo-Ppto LP'!M48+'Mtdo-Ppto LP'!M52 -> 93781.25 | H19: =ROUND(G19/$D$10,3) -> 0.064 | I19: =ROUND(G19/SUM($G$19:$G$24),4) -> 0.3362 | J19: =ROUND(SUM(H19:H24),3) -> 0.191
C20: RETENIDAS Y ANCLAJES | D20: 002 | E20: FE | G20: =+'Mtdo-Ppto LP'!M117 -> 31585.24 | H20: =ROUND(G20/$D$10,3) -> 0.022 | I20: =ROUND(G20/SUM($G$19:$G$24),4) -> 0.1132
C21: FERRETERIA PARA POSTES Y CRUCETAS | D21: 002 | E21: FP | G21: =+'Mtdo-Ppto LP'!M101 -> 15148.54 | H21: =ROUND(G21/$D$10,3) -> 0.01 | I21: =ROUND(G21/SUM($G$19:$G$24),4) -> 0.0543
C22: CONDUCTOR DE COBRE | D22: 006 | E22: CU | G22: =+'Mtdo-Ppto LP'!M76 -> 40485.12 | H22: =ROUND(G22/$D$10,3) -> 0.028 | I22: =ROUND(G22/SUM($G$19:$G$24),4) -> 0.1451
C23: MATERIAL PARA PUESTA A TIERRA | D23: 006 | E23: PT | G23: =+'Mtdo-Ppto LP'!M129 -> 11437.24 | H23: =ROUND(G23/$D$10,3) -> 0.008 | I23: =ROUND(G23/SUM($G$19:$G$24),4) -> 0.041
C24: TRAMO SUBTERRANEO | D24: 006 | E24: TS | G24: =+'Mtdo-Ppto LP'!M153 -> 86522.98 | H24: =ROUND(G24/$D$10,3) -> 0.059 | I24: =ROUND(G24/SUM($G$19:$G$24),4) -> 0.3102
B25: 4 | C25: MONTAJE ELECTROMECANICO | D25: 047 | E25: J | F25: J | G25: =+'Mtdo-Ppto LP'!M307 -> 552762.73 | H25: =ROUND(G25/$D$10,3) -> 0.377 | I25: =ROUND(G25/($G$25+$G$26),4) -> 0.9032 | J25: =ROUND(SUM(H25:H26),3) -> 0.417
C26: TRANSPORTE | D26: 032 | E26: FT | G26: =+'Mtdo-Ppto LP'!M446 -> 59272.43 | H26: =ROUND(G26/$D$10,3) -> 0.04 | I26: =ROUND(G26/($G$25+$G$26),4) -> 0.0968
B27: 5 | C27: GASTOS GENERALES Y UTILIDADES | D27: 039 | E27: GG | F27: GU | G27: =+'RES-LP'!H16+'RES-LP'!H17 -> 170004.41 | H27: =ROUND(G27/$D$10,3) -> 0.116 | I27: =+G27/G27 -> 1 | J27: =ROUND(SUM(H27),3) -> 0.116
B29: K= | C29: =J13&" PCr/PCo + "&J17&" DIr/DIo + "&J19&" AE2r/AE2o+ "&J25&" Jr/Jo + "&J27&" GUr/GUo" -> 0.176 PCr/PCo + 0.1 DIr/DIo + 0.191 AE2r/AE2o+ 0.417 Jr/Jo + 0.116 GUr/GUo
B32: NOTAS:
B34: 1.- | C34: En la fórmula los sub-indices "o" de cada símbolo corresponden al indice de precios según (CREPCO) a la
C35: fecha de Elaboración del Presupuesto (Presupuesto Base) y los sub-indices "r" al indice de precios al
C36: momento de reajuste o fecha de valorización
B37: 2.- | C37: En el caso de los monomios compuestos por varios indices se ha considerado para efecto de denominación
C38: el símbolo que tiene mayor porcentaje de incidencia
B39: 3.- | C39: En caso de cambios en el suministro se deberá actualizar la formula polinómica.
H46: =+IF(SUM(H13:H27)=1,"OK","X") -> OK | I46: =+IF(SUM(I13:I27)=5,"OK","X") -> OK | J46: =+IF(SUM(J13:J27)=1,"OK","X") -> OK

Sheet RES-RP
B2: RESUMEN PRESUPUESTO DE OBRA
B4: AMPLIACIÓN DEL SERVICIO DE ENERGÍA ELÉCTRICA EN LA PROVINCIA DEL SANTA Y EN EL DISTRITO DE PAMPAROMAS – DEPARTAMENTO DE ANCASH
B6: UBICACIÓN | C6: : | D6: ANCASH
B7: SECCIÓN II | C7: : | D7: REDES PRIMARIAS | H7: Fecha: 30-May-2022
H8: T.C. (S/./US$): 3,642
B9: ITEM | C9: DESCRIPCION | G9: PRESUPUESTO CONTRATO | H9: PRESUPUESTO ESTUDIO DEFINIVO | I9: ADICIONALES | K9: DEDUCTIVOS
I10: MAYORES METRADOS | J10: PARTIDAS NUEVAS | K10: MENOR METRADO | L10: DEDUCTIVO VINCULANTE
B12: A | D12: SUMINISTRO DE MATERIALES | G12: =+'Mtdo-Ppto RP'!K136 -> 202256.75 | H12: =+'Mtdo-Ppto RP'!M136 -> 223205.59 | I12: =+'Mtdo-Ppto RP'!O136 -> 17268.84 | J12: =+'Mtdo-Ppto RP'!Q136 -> 55879.66 | K12: =+'Mtdo-Ppto RP'!S136 -> 52199.66 | L12: =+'Mtdo-Ppto RP'!U136 -> 29858.15
B13: B | D13: MONTAJE ELECTROMECANICO | G13: =+'Mtdo-Ppto RP'!K235 -> 85459.52 | H13: =+'Mtdo-Ppto RP'!M235 -> 84855.49 | I13: =+'Mtdo-Ppto RP'!O235 -> 13835.11 | J13: =+'Mtdo-Ppto RP'!Q235 -> 4104.22 | K13: =+'Mtdo-Ppto RP'!S235 -> 18543.39 | L13: =+'Mtdo-Ppto RP'!U235 -> 8920.98
B14: C | D14: TRANSPORTE DE MATERIALES | G14: =+'Mtdo-Ppto RP'!K356 -> 16212.19 | H14: =+'Mtdo-Ppto RP'!M356 -> 19115.26 | I14: =+'Mtdo-Ppto RP'!O356 -> 2169.3 | J14: =+'Mtdo-Ppto RP'!Q356 -> 4146.01 | K14: =+'Mtdo-Ppto RP'!S356 -> 3412.24 | L14: =+'Mtdo-Ppto RP'!U356 -> 2082.23
B15: D | D15: TOTAL COSTO DIRECTO | G15: =+SUM(G12:G14) -> 303928.46 | H15: =+SUM(H12:H14) -> 327176.34 | I15: =+SUM(I12:I14) -> 33273.25 | J15: =+SUM(J12:J14) -> 64129.89 | K15: =+SUM(K12:K14) -> 74155.29 | L15: =+SUM(L12:L14) -> 40861.36
B16: E | D16: GASTOS GENERALES (10.12%) | G16: =ROUND(G15*10.12%,2) -> 30757.56 | H16: =ROUND(H15*10.12%,2) -> 33110.25 | I16: =ROUND(I15*10.12%,2) -> 3367.25 | J16: =ROUND(J15*10.12%,2) -> 6489.94 | K16: =ROUND(K15*10.12%,2) -> 7504.52 | L16: =ROUND(L15*10.12%,2) -> 4135.17
B17: F | D17: UTILIDADES (3%) | G17: =ROUND(G15*3%,2) -> 9117.85 | H17: =ROUND(H15*3%,2) -> 9815.29 | I17: =ROUND(I15*3%,2) -> 998.2 | J17: =ROUND(J15*3%,2) -> 1923.9 | K17: =ROUND(K15*3%,2) -> 2224.66 | L17: =ROUND(L15*3%,2) -> 1225.84
B18: G | D18: COSTO TOTAL S/. (No incluye I.G.V.) | G18: =G17+G16+G15 -> 343803.87 | H18: =H17+H16+H15 -> 370101.88 | I18: =I17+I16+I15 -> 37638.7 | J18: =J17+J16+J15 -> 72543.73 | K18: =K17+K16+K15 -> 83884.47 | L18: =L17+L16+L15 -> 46222.37 | M18: =+H18-G18 -> 26298.01
D20: INCIDENCIA % | G20: =+G18/G18 -> 1 | H20: =+H18/$G$18 -> 1.0764913 | I20: =+I18/$G$18 -> 0.10947724 | J20: =+J18/$G$18 -> 0.21100324 | K20: =+K18/$G$18 -> 0.24398931 | L20: =+L18/$G$18 -> 0.13444401
H22: =+H18-I18+K18-J18 -> 343803.92 | K22: =+G12-H12+I12+J12-K12 -> 0
H23: =+G18-H22 -> -0.05 | K23: =+G13-H13+I13+J13-K13 -> -0.03
K24: =+G14-H14+I14+J14-K14 -> 0
K25: =+G15-H15+I15+J15-K15 -> -0.03

Sheet Mtdo-Ppto RP
B6: PRESUPUESTO DE OBRA
B8: OBRA | E8: : | F8: AMPLIACIÓN DEL SERVICIO DE ENERGÍA ELÉCTRICA EN LA PROVINCIA DEL SANTA Y EN EL DISTRITO DE PAMPAROMAS – DEPARTAMENTO DE ANCASH
B9: DEPARTAMENTO | E9: : | F9: ANCASH
B10: SECCIÓN II | E10: : | F10: REDES PRIMARIAS
B12: ITEM | C12: DESCRIPCIÓN DE PARTIDAS | G12: UNID. | H12: Precio de Contrato | I12: Precio Pactado | J12: CONTRACTUAL | L12: ESTUDIO DEFINITIVO | N12: ADICIONALES | R12: DEDUCTIVOS | V12: OBSERVACIÓN
J13: Metrado | K13: TOTAL | L13: Metrado | M13: TOTAL | N13: MAYORES METRADOS | P13: PARTIDAS NUEVAS | R13: MENORES METRADOS | T13: DEDUCTIVO VINCULANTE
N14: Metrado | O14: TOTAL | P14: Metrado | Q14: TOTAL | R14: Metrado | S14: TOTAL | T14: Metrado | U14: TOTAL
H15: Unitario | I15: Unitario | J15: Cantidad | K15: S/. | L15: Cantidad | M15: S/. | N15: Cantidad | O15: S/. | P15: Cantidad | Q15: S/. | R15: Cantidad | S15: S/. | T15: Cantidad | U15: S/.
B16: A | D16: SUMINISTRO DE MATERIALES
B17: 1 | C17: 3 | D17: CRUCETAS DE MADERA DE PROCEDENCIA NACIONAL
B18: =+B17+0.01 -> 1.01 | C18: =+C17+1 -> 4 | D18: Cruceta de madera tratada de 90 mm x 115 mm x 1,20 m | G18: u | H18: 105 | J18: 13 | K18: =+ROUND($H18*J18,2) -> 1365 | L18: =+[192]Metrado!E13 -> 10 | M18: =+ROUND($H18*L18,2) -> 1050 | N18: =+IF($L18-$J18>=0,$L18-$J18,0) -> 0 | O18: =+ROUND($H18*N18,2) -> 0 | Q18: =+ROUND($H18*P18,2) -> 0 | R18: =+IF($L18-$J18<=0,-$L18+$J18,0) -> 3 | S18: =+ROUND($H18*R18,2) -> 315 | T18: =+R18 -> 3 | U18: =+ROUND($H18*T18,2) -> 315 | V18: Se vincula con la partida nueva 1.03 | Y18: 0
B19: =+B18+0.01 -> 1.02 | C19: =+C18+1 -> 5 | D19: Listón de madera tratada 50 x 19 mm sección, 2,7 m longitud (incluye clavos de fijación) | G19: u | H19: 27.35 | J19: 2 | K19: =+ROUND($H19*J19,2) -> 54.7 | L19: =+[192]Metrado!E14 -> 0 | M19: =+ROUND($H19*L19,2) -> 0 | N19: =+IF($L19-$J19>=0,$L19-$J19,0) -> 0 | O19: =+ROUND($H19*N19,2) -> 0 | Q19: =+ROUND($H19*P19,2) -> 0 | R19: =+IF($L19-$J19<=0,-$L19+$J19,0) -> 2 | S19: =+ROUND($H19*R19,2) -> 54.7 | U19: =+ROUND($H19*T19,2) -> 0 | Y19: 0
B20: 1.03 | C20: =+C19+1 -> 6 | D20: Cruceta de madera tratada de 90 mm x 115 mm x 2,00 m | G20: u | I20: =+'Mtdo-Ppto LP'!H19 -> 178 | K20: =+ROUND($H20*J20,2) -> 0 | L20: =+[192]Metrado!E15 -> 2 | M20: =+ROUND($I20*L20,2) -> 356 | O20: =+ROUND($H20*N20,2) -> 0 | P20: =+L20 -> 2 | Q20: =+ROUND($I20*P20,2) -> 356 | S20: =+ROUND($H20*R20,2) -> 0 | U20: =+ROUND($H20*T20,2) -> 0 | Y20: 0
B21: 1.04 | C21: =+C20+1 -> 7 | D21: Cruceta de madera tratada de 90 mm x 115 mm x 2,40 m | G21: u | I21: =+'Mtdo-Ppto LP'!H20 -> 205 | K21: =+ROUND($H21*J21,2) -> 0 | L21: =+[192]Metrado!E16 -> 3 | M21: =+ROUND($I21*L21,2) -> 615 | O21: =+ROUND($H21*N21,2) -> 0 | P21: =+L21 -> 3 | Q21: =+ROUND($I21*P21,2) -> 615 | S21: =+ROUND($H21*R21,2) -> 0 | U21: =+ROUND($H21*T21,2) -> 0 | Y21: 0
C22: =+C19+1 -> 6 | F22: =+"SUB-TOTAL "&B17&": " -> SUB-TOTAL 1: | K22: =+SUM(K18:K21) -> 1419.7 | M22: =+SUM(M18:M21) -> 2021 | O22: =+SUM(O18:O21) -> 0 | Q22: =+SUM(Q18:Q21) -> 971 | S22: =+SUM(S18:S21) -> 369.7 | U22: =+SUM(U18:U21) -> 315 | W22: =+K22-M22+O22+Q22-S22 -> 0 | Y22: 0
B23: =1+B17 -> 2 | C23: =+C22+1 -> 7 | D23: POSTES DE CONCRETO ARMADO CENTRIFUGADO | Y23: 0
B24: 2.01 | C24: =+C20+1 -> 7 | D24: Poste de C.A.C. de 12 m/200 daN (Incluye perilla) | G24: u | H24: 837.45 | J24: 3 | K24: =+ROUND($H24*J24,2) -> 2512.35 | L24: =+[192]Metrado!E19 -> 1 | M24: =+ROUND($H24*L24,2) -> 837.45 | N24: =+IF($L24-$J24>=0,$L24-$J24,0) -> 0 | O24: =+ROUND($H24*N24,2) -> 0 | Q24: =+ROUND($H24*P24,2) -> 0 | R24: =+IF($L24-$J24<=0,-$L24+$J24,0) -> 2 | S24: =+ROUND($H24*R24,2) -> 1674.9 | T24: =+R24 -> 2 | U24: =+ROUND($H24*T24,2) -> 1674.9 | V24: Se vincula con la partida nueva 3.02 | Y24: 0
B25: 2.02 | C25: =+C21+1 -> 8 | D25: Poste de C.A.C. de 12 m/300 daN (Incluye perilla) | G25: u | H25: 923.47 | J25: 11 | K25: =+ROUND($H25*J25,2) -> 10158.17 | L25: =+[192]Metrado!E20 -> 13 | M25: =+ROUND($H25*L25,2) -> 12005.11 | N25: =+IF($L25-$J25>=0,$L25-$J25,0) -> 2 | O25: =+ROUND($H25*N25,2) -> 1846.94 | Q25: =+ROUND($H25*P25,2) -> 0 | R25: =+IF($L25-$J25<=0,-$L25+$J25,0) -> 0 | S25: =+ROUND($H25*R25,2) -> 0 | U25: =+ROUND($H25*T25,2) -> 0 | Y25: 0
B26: 2.03 | C26: =+C22+1 -> 7 | D26: Poste de C.A.C. de 13 m/300 daN (Incluye perilla) | G26: u | H26: 1085.14 | J26: 10 | K26: =+ROUND($H26*J26,2) -> 10851.4 | L26: =+[192]Metrado!E21 -> 11 | M26: =+ROUND($H26*L26,2) -> 11936.54 | N26: =+IF($L26-$J26>=0,$L26-$J26,0) -> 1 | O26: =+ROUND($H26*N26,2) -> 1085.14 | Q26: =+ROUND($H26*P26,2) -> 0 | R26: =+IF($L26-$J26<=0,-$L26+$J26,0) -> 0 | S26: =+ROUND($H26*R26,2) -> 0 | U26: =+ROUND($H26*T26,2) -> 0 | Y26: 0
B27: 2.04 | C27: =+C23+1 -> 8 | D27: Poste de C.A.C. de 13 m/400 daN (Incluye perilla) | G27: u | H27: 1207.94 | J27: 10 | K27: =+ROUND($H27*J27,2) -> 12079.4 | L27: =+[192]Metrado!E22 -> 14 | M27: =+ROUND($H27*L27,2) -> 16911.16 | N27: =+IF($L27-$J27>=0,$L27-$J27,0) -> 4 | O27: =+ROUND($H27*N27,2) -> 4831.76 | Q27: =+ROUND($H27*P27,2) -> 0 | R27: =+IF($L27-$J27<=0,-$L27+$J27,0) -> 0 | S27: =+ROUND($H27*R27,2) -> 0 | U27: =+ROUND($H27*T27,2) -> 0 | Y27: 0
C28: =+C27+1 -> 9 | F28: =+"SUB-TOTAL "&B23&": " -> SUB-TOTAL 2: | K28: =+SUM(K24:K27) -> 35601.32 | M28: =+SUM(M24:M27) -> 41690.26 | O28: =+SUM(O24:O27) -> 7763.84 | Q28: =+SUM(Q24:Q27) -> 0 | S28: =+SUM(S24:S27) -> 1674.9 | U28: =+SUM(U24:U27) -> 1674.9 | W28: =+K28-M28+O28+Q28-S28 -> -2.2737368e-12 | Y28: 0
B29: 3 | C29: =+C28+1 -> 10 | D29: POSTES DE MADERA IMPORTADA | Y29: 0
B30: 3.01 | C30: =+#REF!+1 -> #REF! | D30: Poste de madera importada (Pino Amarillo del Sur) de 12 m, Clase 5 | G30: u | H30: 1864.52 | J30: 2 | K30: =+ROUND($H30*J30,2) -> 3729.04 | L30: =+[192]Metrado!E25 -> 0 | M30: =+ROUND($H30*L30,2) -> 0 | N30: =+IF($L30-$J30>=0,$L30-$J30,0) -> 0 | O30: =+ROUND($H30*N30,2) -> 0 | Q30: =+ROUND($H30*P30,2) -> 0 | R30: =+IF($L30-$J30<=0,-$L30+$J30,0) -> 2 | S30: =+ROUND($H30*R30,2) -> 3729.04 | T30: =+R30 -> 2 | U30: =+ROUND($H30*T30,2) -> 3729.04 | V30: Se vincula con la partida nueva 3.02 | Y30: 0
C31: =+#REF!+1 -> #REF! | F31: =+"SUB-TOTAL "&B29&": " -> SUB-TOTAL 3: | K31: =+SUM(K30:K30) -> 3729.04 | M31: =+SUM(M30:M30) -> 0 | O31: =+SUM(O30:O30) -> 0 | Q31: =+SUM(Q30:Q30) -> 0 | S31: =+SUM(S30:S30) -> 3729.04 | U31: =+SUM(U30:U30) -> 3729.04 | Y31: 0
B32: 3.00A | C32: =+C31+1 -> #REF! | D32: POSTES DE FIBRA DE VIDRIO | Y32: 0
B33: 3.01A | C33: =+C32+1 -> #REF! | D33: Poste de PRFV de 12 m/200 daN | I33: 1958.01 | K33: =+ROUND($H33*J33,2) -> 0 | L33: =+[192]Metrado!E28 -> 0 | M33: =+ROUND($I33*L33,2) -> 0 | O33: =+ROUND($H33*N33,2) -> 0 | P33: =+L33 -> 0 | Q33: =+ROUND($I33*P33,2) -> 0 | S33: =+ROUND($H33*R33,2) -> 0 | U33: =+ROUND($H33*T33,2) -> 0 | Y33: 0
B34: 3.02A | C34: =+C33+1 -> #REF! | D34: Poste de PRFV de 12 m/300 daN | I34: 2336.29 | K34: =+ROUND($H34*J34,2) -> 0 | L34: =+[192]Metrado!E29 -> 5 | M34: =+ROUND($I34*L34,2) -> 11681.45 | O34: =+ROUND($H34*N34,2) -> 0 | P34: =+L34 -> 5 | Q34: =+ROUND($I34*P34,2) -> 11681.45 | S34: =+ROUND($H34*R34,2) -> 0 | U34: =+ROUND($H34*T34,2) -> 0 | Y34: 0
C35: =+C34+1 -> #REF! | F35: =+"SUB-TOTAL "&B32&": " -> SUB-TOTAL 3.00A: | M35: =+SUM(M33:M34) -> 11681.45 | O35: =+SUM(O33:O34) -> 0 | Q35: =+SUM(Q33:Q34) -> 11681.45 | S35: =+SUM(S33:S34) -> 0 | U35: =+SUM(U33:U34) -> 0 | Y35: 0
B36: =+B29+1 -> 4 | C36: =+C31+1 -> #REF! | D36: OTROS MATERIALES DE CONCRETO ARMADO | Y36: 0
B37: 4.01 | C37: =+C36+1 -> #REF! | D37: Cruceta Asimétrica de C.A.V. Za / 1,5 / 0,9 / 250 / 200 / 100 daN (Za / L / L1/ T / F / V) | G37: u | H37: 120.3 | J37: 5 | K37: =+ROUND($H37*J37,2) -> 601.5 | L37: =+[192]Metrado!E32 -> 5 | M37: =+ROUND($H37*L37,2) -> 601.5 | N37: =+IF($L37-$J37>=0,$L37-$J37,0) -> 0 | O37: =+ROUND($H37*N37,2) -> 0 | Q37: =+ROUND($H37*P37,2) -> 0 | R37: =+IF($L37-$J37<=0,-$L37+$J37,0) -> 0 | S37: =+ROUND($H37*R37,2) -> 0 | U37: =+ROUND($H37*T37,2) -> 0 | Y37: 0
B38: 4.02 | C38: =+C37+1 -> #REF! | D38: Ménsula de C.A.V. M / 1,2 / 250 / 150 / 150 daN (M / L / T / F / V) | G38: u | H38: 88.8 | J38: 40 | K38: =+ROUND($H38*J38,2) -> 3552 | L38: =+[192]Metrado!E33 -> 60 | M38: =+ROUND($H38*L38,2) -> 5328 | N38: =+IF($L38-$J38>=0,$L38-$J38,0) -> 20 | O38: =+ROUND($H38*N38,2) -> 1776 | Q38: =+ROUND($H38*P38,2) -> 0 | R38: =+IF($L38-$J38<=0,-$L38+$J38,0) -> 0 | S38: =+ROUND($H38*R38,2) -> 0 | U38: =+ROUND($H38*T38,2) -> 0 | Y38: 0
B39: 4.03 | C39: =+C38+1 -> #REF! | D39: Plataforma de Concreto Soporte de Transformador de 2,20 m, carga de trabajo de 500 daN | G39: u | H39: 620 | J39: 5 | K39: =+ROUND($H39*J39,2) -> 3100 | L39: =+[192]Metrado!E34 -> 5 | M39: =+ROUND($H39*L39,2) -> 3100 | N39: =+IF($L39-$J39>=0,$L39-$J39,0) -> 0 | O39: =+ROUND($H39*N39,2) -> 0 | Q39: =+ROUND($H39*P39,2) -> 0 | R39: =+IF($L39-$J39<=0,-$L39+$J39,0) -> 0 | S39: =+ROUND($H39*R39,2) -> 0 | U39: =+ROUND($H39*T39,2) -> 0 | Y39: 0
C40: =+#REF!+1 -> #REF! | F40: =+"SUB-TOTAL "&B36&": " -> SUB-TOTAL 4: | K40: =+SUM(K37:K39) -> 7253.5 | M40: =+SUM(M37:M39) -> 9029.5 | O40: =+SUM(O37:O39) -> 1776 | Q40: =+SUM(Q37:Q39) -> 0 | S40: =+SUM(S37:S39) -> 0 | U40: =+SUM(U37:U39) -> 0 | Y40: 0
B41: =+B36+1 -> 5 | C41: =+C40+1 -> #REF! | D41: AISLADORES Y ACCESORIOS | Y41: 0
B42: 5.01 | C42: =+C41+1 -> #REF! | D42: Aislador de Porcelana Tipo Pin, Clase ANSI 56-3 | G42: u | H42: 76.45 | J42: 16 | K42: =+ROUND($H42*J42,2) -> 1223.2 | L42: =+[192]Metrado!E37 -> 25 | M42: =+ROUND($H42*L42,2) -> 1911.25 | N42: =+IF($L42-$J42>=0,$L42-$J42,0) -> 9 | O42: =+ROUND($H42*N42,2) -> 688.05 | Q42: =+ROUND($H42*P42,2) -> 0 | R42: =+IF($L42-$J42<=0,-$L42+$J42,0) -> 0 | S42: =+ROUND($H42*R42,2) -> 0 | U42: =+ROUND($H42*T42,2) -> 0 | Y42: 0
B43: 5.02 | C43: =+C42+1 -> #REF! | D43: Espiga de AºGº de 609 mm longitud, para Cabeza de Poste y Aislador ANSI 56-3 | G43: u | H43: 35.96 | J43: 16 | K43: =+ROUND($H43*J43,2) -> 575.36 | L43: =+[192]Metrado!E38 -> 17 | M43: =+ROUND($H43*L43,2) -> 611.32 | N43: =+IF($L43-$J43>=0,$L43-$J43,0) -> 1 | O43: =+ROUND($H43*N43,2) -> 35.96 | Q43: =+ROUND($H43*P43,2) -> 0 | R43: =+IF($L43-$J43<=0,-$L43+$J43,0) -> 0 | S43: =+ROUND($H43*R43,2) -> 0 | U43: =+ROUND($H43*T43,2) -> 0 | Y43: 0
B44: 5.03 | C44: =+C43+1 -> #REF! | D44: Conjunto Aislador Line Post Polimérico en Cruceta: | G44: u | H44: 209.65 | J44: 40 | K44: =+ROUND($H44*J44,2) -> 8386 | L44: =+[192]Metrado!E40 -> 50 | M44: =+ROUND($H44*L44,2) -> 10482.5 | N44: =+IF($L44-$J44>=0,$L44-$J44,0) -> 10 | O44: =+ROUND($H44*N44,2) -> 2096.5 | Q44: =+ROUND($H44*P45,2) -> 0 | R44: =+IF($L44-$J44<=0,-$L44+$J44,0) -> 0 | S44: =+ROUND($H44*R44,2) -> 0 | U44: =+ROUND($H44*T45,2) -> 0 | Y44: 0
C45: =+C44+1 -> #REF! | D45: - Aislador Polimérico de 36 kV, Tipo Line Post con Espárrago de 19 mm Ø, 200 mm longitud (Alternativa a Conjunto Aislador-Espiga en Cruceta) | Y45: 0
B46: 5.04 | C46: =+#REF!+1 -> #REF! | D46: Espiga para cruceta, forjada de 381mm LONG. Para aislador Tipo Pin, Clase ANSI 56-3 | G46: u | I46: 49.41 | K46: =+ROUND($H46*J46,2) -> 0 | L46: =+[192]Metrado!E41 -> 8 | M46: =+ROUND($I46*L46,2) -> 395.28 | O46: =+ROUND($H46*N46,2) -> 0 | P46: =+L46 -> 8 | Q46: =+ROUND($I46*P46,2) -> 395.28 | S46: =+ROUND($H46*R46,2) -> 0 | U46: =+ROUND($H46*T46,2) -> 0 | Y46: 0
C47: =+#REF!+1 -> #REF! | F47: =+"SUB-TOTAL "&B41&": " -> SUB-TOTAL 5: | K47: =+SUM(K42:K46) -> 10184.56 | M47: =+SUM(M42:M46) -> 13400.35 | O47: =+SUM(O42:O46) -> 2820.51 | Q47: =+SUM(Q42:Q46) -> 395.28 | S47: =+SUM(S42:S46) -> 0 | U47: =+SUM(U42:U46) -> 0 | Y47: 0
B48: =+B41+1 -> 6 | C48: =+C47+1 -> #REF! | D48: AISLADORES DE SUSPENSIÓN Y ACCESORIOS | Y48: 0
B49: 6.01 | C49: =+C48+1 -> #REF! | D49: Grillete Recto | G49: u | H49: 17.76 | J49: 16 | K49: =+ROUND($H49*J49,2) -> 284.16 | L49: =+[192]Metrado!E44 -> 23 | M49: =+ROUND($H49*L49,2) -> 408.48 | N49: =+IF($L49-$J49>=0,$L49-$J49,0) -> 7 | O49: =+ROUND($H49*N49,2) -> 124.32 | Q49: =+ROUND($H49*P49,2) -> 0 | R49: =+IF($L49-$J49<=0,-$L49+$J49,0) -> 0 | S49: =+ROUND($H49*R49,2) -> 0 | U49: =+ROUND($H49*T49,2) -> 0 | Y49: 0
B50: 6.02 | C50: =+C49+1 -> #REF! | D50: Aislador Polimerico con Conexión Horquilla (Estructura) y Lengüeta (Linea) de 36 kV, según Especificacion Técnica. | G50: u | H50: 76.66 | J50: 16 | K50: =+ROUND($H50*J50,2) -> 1226.56 | L50: =+[192]Metrado!E45 -> 23 | M50: =+ROUND($H50*L50,2) -> 1763.18 | N50: =+IF($L50-$J50>=0,$L50-$J50,0) -> 7 | O50: =+ROUND($H50*N50,2) -> 536.62 | Q50: =+ROUND($H50*P50,2) -> 0 | R50: =+IF($L50-$J50<=0,-$L50+$J50,0) -> 0 | S50: =+ROUND($H50*R50,2) -> 0 | U50: =+ROUND($H50*T50,2) -> 0 | Y50: 0
C51: =+#REF!+1 -> #REF! | F51: =+"SUB-TOTAL "&B48&": " -> SUB-TOTAL 6: | K51: =+SUM(K49:K50) -> 1510.72 | M51: =+SUM(M49:M50) -> 2171.66 | O51: =+SUM(O49:O50) -> 660.94 | Q51: =+SUM(Q49:Q50) -> 0 | S51: =+SUM(S49:S50) -> 0 | U51: =+SUM(U49:U50) -> 0 | Y51: 0
B52: =+B48+1 -> 7 | C52: =+C51+1 -> #REF! | D52: CONDUCTOR DE ALEACIÓN DE ALUMINIO | Y52: 0
B53: 7.01 | C53: =+C52+1 -> #REF! | D53: Conductor de Aleacion de Aluminio de 35 mm² | G53: km | H53: 2249.62 | J53: 3.51 | K53: =+ROUND($H53*J53,2) -> 7896.17 | L53: =+[192]Metrado!E48 -> 3.9891798 | M53: =+ROUND($H53*L53,2) -> 8974.14 | N53: =+IF($L53-$J53>=0,$L53-$J53,0) -> 0.4791798 | O53: =+ROUND($H53*N53,2) -> 1077.97 | Q53: =+ROUND($H53*P53,2) -> 0 | R53: =+IF($L53-$J53<=0,-$L53+$J53,0) -> 0 | S53: =+ROUND($H53*R53,2) -> 0 | U53: =+ROUND($H53*T53,2) -> 0 | Y53: 0
C54: =+#REF!+1 -> #REF! | F54: =+"SUB-TOTAL "&B52&": " -> SUB-TOTAL 7: | K54: =+SUM(K53:K53) -> 7896.17 | M54: =+SUM(M53:M53) -> 8974.14 | O54: =+SUM(O53:O53) -> 1077.97 | Q54: =+SUM(Q53:Q53) -> 0 | S54: =+SUM(S53:S53) -> 0 | U54: =+SUM(U53:U53) -> 0 | Y54: 0
B55: =+B52+1 -> 8 | C55: =+C54+1 -> #REF! | D55: ACCESORIOS PARA CONDUCTOR DE ALEACION ALUMINIO | Y55: 0
B56: 8.01 | C56: =+C55+1 -> #REF! | D56: Varilla de Armar preformada Simple para Conductor de 35 mm² | G56: u | H56: 10.19 | J56: 41 | K56: =+ROUND($H56*J56,2) -> 417.79 | L56: =+[192]Metrado!E51 -> 47 | M56: =+ROUND($H56*L56,2) -> 478.93 | N56: =+IF($L56-$J56>=0,$L56-$J56,0) -> 6 | O56: =+ROUND($H56*N56,2) -> 61.14 | Q56: =+ROUND($H56*P56,2) -> 0 | R56: =+IF($L56-$J56<=0,-$L56+$J56,0) -> 0 | S56: =+ROUND($H56*R56,2) -> 0 | U56: =+ROUND($H56*T56,2) -> 0 | Y56: 0
B57: 8.02 | C57: =+C56+1 -> #REF! | D57: Grapa de Doble Via de Aluminio para Conductor de 35 mm² | G57: u | H57: 7.77 | J57: 41 | K57: =+ROUND($H57*J57,2) -> 318.57 | L57: =+[192]Metrado!E52 -> 40 | M57: =+ROUND($H57*L57,2) -> 310.8 | N57: =+IF($L57-$J57>=0,$L57-$J57,0) -> 0 | O57: =+ROUND($H57*N57,2) -> 0 | Q57: =+ROUND($H57*P57,2) -> 0 | R57: =+IF($L57-$J57<=0,-$L57+$J57,0) -> 1 | S57: =+ROUND($H57*R57,2) -> 7.77 | U57: =+ROUND($H57*T57,2) -> 0 | Y57: 0
B58: 8.03 | C58: =+C57+1 -> #REF! | D58: Alambre de Amarre Aluminio Recocido de 16 mm² | G58: m | H58: 1.41 | J58: 170 | K58: =+ROUND($H58*J58,2) -> 239.7 | L58: =+[192]Metrado!E53 -> 227.5 | M58: =+ROUND($H58*L58,2) -> 320.78 | N58: =+IF($L58-$J58>=0,$L58-$J58,0) -> 57.5 | O58: =+ROUND($H58*N58,2) -> 81.08 | Q58: =+ROUND($H58*P58,2) -> 0 | R58: =+IF($L58-$J58<=0,-$L58+$J58,0) -> 0 | S58: =+ROUND($H58*R58,2) -> 0 | U58: =+ROUND($H58*T58,2) -> 0 | Y58: 0
B59: 8.04 | C59: =+C58+1 -> #REF! | D59: Grapa de Anclaje para Conductor de 35 mm² | G59: u | H59: 25.34 | J59: 16 | K59: =+ROUND($H59*J59,2) -> 405.44 | L59: =+[192]Metrado!E54 -> 22 | M59: =+ROUND($H59*L59,2) -> 557.48 | N59: =+IF($L59-$J59>=0,$L59-$J59,0) -> 6 | O59: =+ROUND($H59*N59,2) -> 152.04 | Q59: =+ROUND($H59*P59,2) -> 0 | R59: =+IF($L59-$J59<=0,-$L59+$J59,0) -> 0 | S59: =+ROUND($H59*R59,2) -> 0 | U59: =+ROUND($H59*T59,2) -> 0 | Y59: 0
B60: 8.05 | C60: =+#REF!+1 -> #REF! | D60: Varilla de Armar preformada Doble para Conductor de 35 mm² | G60: u | I60: 11.72 | K60: =+ROUND($H60*J60,2) -> 0 | L60: =+[192]Metrado!E55 -> 3 | M60: =+ROUND($I60*L60,2) -> 35.16 | O60: =+ROUND($H60*N60,2) -> 0 | P60: =+L60 -> 3 | Q60: =+ROUND($I60*P60,2) -> 35.16 | S60: =+ROUND($H60*R60,2) -> 0 | U60: =+ROUND($H60*T60,2) -> 0 | Y60: 0
B61: 8.06 | C61: =+C60+1 -> #REF! | D61: Cinta plana de armar de aluminio | G61: m | I61: 1 | K61: =+ROUND($H61*J61,2) -> 0 | L61: =+[192]Metrado!E56 -> 13.8 | M61: =+ROUND($I61*L61,2) -> 13.8 | O61: =+ROUND($H61*N61,2) -> 0 | P61: =+L61 -> 13.8 | Q61: =+ROUND($I61*P61,2) -> 13.8 | S61: =+ROUND($H61*R61,2) -> 0 | U61: =+ROUND($H61*T61,2) -> 0 | Y61: 0
C62: =+C61+1 -> #REF! | F62: =+"SUB-TOTAL "&B55&": " -> SUB-TOTAL 8: | K62: =+SUM(K56:K61) -> 1381.5 | M62: =+SUM(M56:M61) -> 1716.95 | O62: =+SUM(O56:O61) -> 294.26 | Q62: =+SUM(Q56:Q61) -> 48.96 | S62: =+SUM(S56:S61) -> 7.77 | U62: =+SUM(U56:U61) -> 0 | Y62: 0
B63: =+B55+1 -> 9 | C63: =+C62+1 -> #REF! | D63: CONDUCTOR DE COBRE | Y63: 0
B64: 9.01 | C64: =+C63+1 -> #REF! | D64: Cable de Acero con Recubrimiento Metalúrgico de Cu de 4 AWG (21,15 mm²), para Puesta a Tierra | G64: m | H64: 12.8 | J64: 717.5 | K64: =+ROUND($H64*J64,2) -> 9184 | L64: =+[192]Metrado!E59 -> 431.5 | M64: =+ROUND($H64*L64,2) -> 5523.2 | N64: =+IF($L64-$J64>=0,$L64-$J64,0) -> 0 | O64: =+ROUND($H64*N64,2) -> 0 | Q64: =+ROUND($H64*P64,2) -> 0 | R64: =+IF($L64-$J64<=0,-$L64+$J64,0) -> 286 | S64: =+ROUND($H64*R64,2) -> 3660.8 | U64: =+ROUND($H64*T64,2) -> 0 | Y64: 0
C65: =+#REF!+1 -> #REF! | F65: =+"SUB-TOTAL "&B63&": " -> SUB-TOTAL 9: | K65: =+SUM(K64:K64) -> 9184 | M65: =+SUM(M64:M64) -> 5523.2 | O65: =+SUM(O64:O64) -> 0 | Q65: =+SUM(Q64:Q64) -> 0 | S65: =+SUM(S64:S64) -> 3660.8 | U65: =+SUM(U64:U64) -> 0 | Y65: 0
B66: =1+B63 -> 10 | C66: =+C65+1 -> #REF! | D66: MATERIAL DE FERRETERIA PARA POSTES Y CRUCETAS | Y66: 0
B67: 10.01 | C67: =+C61+1 -> #REF! | D67: Perno Cabeza Coche de AºGº de 13 mm Ø x 152 mm longitud, 76 mm maquinado, con Arandela, Tuerca y Contratuerca | G67: u | H67: 3.86 | J67: 13 | K67: =+ROUND($H67*J67,2) -> 50.18 | L67: =+[192]Metrado!E62 -> 20 | M67: =+ROUND($H67*L67,2) -> 77.2 | N67: =+IF($L67-$J67>=0,$L67-$J67,0) -> 7 | O67: =+ROUND($H67*N67,2) -> 27.02 | Q67: =+ROUND($H67*P67,2) -> 0 | R67: =+IF($L67-$J67<=0,-$L67+$J67,0) -> 0 | S67: =+ROUND($H67*R67,2) -> 0 | U67: =+ROUND($H67*T67,2) -> 0 | Y67: 0
B68: 10.02 | C68: =+C67+1 -> #REF! | D68: Perno de A°G° de 13 mm Ø x 305 mm, provisto de Tuerca y Contratuerca | G68: u | H68: 6.25 | J68: 13 | K68: =+ROUND($H68*J68,2) -> 81.25 | L68: =+[192]Metrado!E63 -> 15 | M68: =+ROUND($H68*L68,2) -> 93.75 | N68: =+IF($L68-$J68>=0,$L68-$J68,0) -> 2 | O68: =+ROUND($H68*N68,2) -> 12.5 | Q68: =+ROUND($H68*P68,2) -> 0 | R68: =+IF($L68-$J68<=0,-$L68+$J68,0) -> 0 | S68: =+ROUND($H68*R68,2) -> 0 | U68: =+ROUND($H68*T68,2) -> 0 | Y68: 0
B69: 10.03 | C69: =+C68+1 -> #REF! | D69: Perno de A°G° de 16 mm Ø x 254 mm, provisto de Tuerca y Contratuerca | G69: u | H69: 8.61 | J69: 32 | K69: =+ROUND($H69*J69,2) -> 275.52 | L69: =+[192]Metrado!E64 -> 25 | M69: =+ROUND($H69*L69,2) -> 215.25 | N69: =+IF($L69-$J69>=0,$L69-$J69,0) -> 0 | O69: =+ROUND($H69*N69,2) -> 0 | Q69: =+ROUND($H69*P69,2) -> 0 | R69: =+IF($L69-$J69<=0,-$L69+$J69,0) -> 7 | S69: =+ROUND($H69*R69,2) -> 60.27 | T69: =+N70+N71 -> 6 | U69: =+ROUND($H69*T69,2) -> 51.66 | V69: Se vincula con el mayor metrado de las partidas 10.04 y 10.05 | Y69: 0
B70: 10.04 | C70: =+C69+1 -> #REF! | D70: Perno de A°G° de 16 mm Ø x 305 mm, provisto de Tuerca y Contratuerca | G70: u | H70: 9.14 | J70: 26 | K70: =+ROUND($H70*J70,2) -> 237.64 | L70: =+[192]Metrado!E65 -> 30 | M70: =+ROUND($H70*L70,2) -> 274.2 | N70: =+IF($L70-$J70>=0,$L70-$J70,0) -> 4 | O70: =+ROUND($H70*N70,2) -> 36.56 | Q70: =+ROUND($H70*P70,2) -> 0 | R70: =+IF($L70-$J70<=0,-$L70+$J70,0) -> 0 | S70: =+ROUND($H70*R70,2) -> 0 | U70: =+ROUND($H70*T70,2) -> 0 | Y70: 0
B71: 10.05 | C71: =+C68+1 -> #REF! | D71: Perno de A°G° de 16 mm Ø x 356 mm, provisto de Tuerca y Contratuerca | G71: u | H71: 9.82 | J71: 13 | K71: =+ROUND($H71*J71,2) -> 127.66 | L71: =+[192]Metrado!E66 -> 15 | M71: =+ROUND($H71*L71,2) -> 147.3 | N71: =+IF($L71-$J71>=0,$L71-$J71,0) -> 2 | O71: =+ROUND($H71*N71,2) -> 19.64 | Q71: =+ROUND($H71*P71,2) -> 0 | R71: =+IF($L71-$J71<=0,-$L71+$J71,0) -> 0 | S71: =+ROUND($H71*R71,2) -> 0 | U71: =+ROUND($H71*T71,2) -> 0 | Y71: 0
B72: 10.06 | C72: =+C71+1 -> #REF! | D72: Perno Ojo de A°G° de 16 mm Ø x 254 mm, provisto de Tuerca y Contratuerca | G72: u | H72: 13.11 | J72: 16 | K72: =+ROUND($H72*J72,2) -> 209.76 | L72: =+[192]Metrado!E67 -> 7 | M72: =+ROUND($H72*L72,2) -> 91.77 | N72: =+IF($L72-$J72>=0,$L72-$J72,0) -> 0 | O72: =+ROUND($H72*N72,2) -> 0 | Q72: =+ROUND($H72*P72,2) -> 0 | R72: =+IF($L72-$J72<=0,-$L72+$J72,0) -> 9 | S72: =+ROUND($H72*R72,2) -> 117.99 | U72: =+ROUND($H72*T72,2) -> 0 | Y72: 0
B73: 10.07 | C73: =+C70+1 -> #REF! | D73: Perno Doble Armado de A°G° de 16 mm Ø x 508 mm, provisto de 4 Tuercas y 4 Contratuercas | G73: u | H73: 18.18 | J73: 50 | K73: =+ROUND($H73*J73,2) -> 909 | L73: =+[192]Metrado!E68 -> 60 | M73: =+ROUND($H73*L73,2) -> 1090.8 | N73: =+IF($L73-$J73>=0,$L73-$J73,0) -> 10 | O73: =+ROUND($H73*N73,2) -> 181.8 | Q73: =+ROUND($H73*P73,2) -> 0 | R73: =+IF($L73-$J73<=0,-$L73+$J73,0) -> 0 | S73: =+ROUND($H73*R73,2) -> 0 | U73: =+ROUND($H73*T73,2) -> 0 | Y73: 0
B74: 10.08 | C74: =+C66+1 -> #REF! | D74: Tirafondo de A°G° de 13 mm ø x 102 mm de longitud | G74: u | H74: 2.74 | J74: 2 | K74: =+ROUND($H74*J74,2) -> 5.48 | L74: =+[192]Metrado!E69 -> 0 | M74: =+ROUND($H74*L74,2) -> 0 | N74: =+IF($L74-$J74>=0,$L74-$J74,0) -> 0 | O74: =+ROUND($H74*N74,2) -> 0 | Q74: =+ROUND($H74*P74,2) -> 0 | R74: =+IF($L74-$J74<=0,-$L74+$J74,0) -> 2 | S74: =+ROUND($H74*R74,2) -> 5.48 | T74: =+R74 -> 2 | U74: =+ROUND($H74*T74,2) -> 5.48 | V74: Se vincula con el mayor metrado de la partida 10.02 | Y74: 0
B75: 10.09 | C75: =+C74+1 -> #REF! | D75: Brazo-Soporte (Riostra) de Perfil Angular de A°G° de 38 x 38 x 5 mm y 710 mm longitud | G75: u | H75: 22.46 | J75: 13 | K75: =+ROUND($H75*J75,2) -> 291.98 | L75: =+[192]Metrado!E70 -> 20 | M75: =+ROUND($H75*L75,2) -> 449.2 | N75: =+IF($L75-$J75>=0,$L75-$J75,0) -> 7 | O75: =+ROUND($H75*N75,2) -> 157.22 | Q75: =+ROUND($H75*P75,2) -> 0 | R75: =+IF($L75-$J75<=0,-$L75+$J75,0) -> 0 | S75: =+ROUND($H75*R75,2) -> 0 | U75: =+ROUND($H75*T75,2) -> 0 | Y75: 0
B76: 10.1 | C76: =+C75+1 -> #REF! | D76: Arandela Cuadrada Plana de A° G°, 57 x 57 x 5 mm, Agujero de 18 mm Ø | G76: u | H76: 1.67 | J76: 107 | K76: =+ROUND($H76*J76,2) -> 178.69 | L76: =+[192]Metrado!E71 -> 149 | M76: =+ROUND($H76*L76,2) -> 248.83 | N76: =+IF($L76-$J76>=0,$L76-$J76,0) -> 42 | O76: =+ROUND($H76*N76,2) -> 70.14 | Q76: =+ROUND($H76*P76,2) -> 0 | R76: =+IF($L76-$J76<=0,-$L76+$J76,0) -> 0 | S76: =+ROUND($H76*R76,2) -> 0 | U76: =+ROUND($H76*T76,2) -> 0 | Y76: 0
B77: 10.11 | C77: =+C76+1 -> #REF! | D77: Arandela Cuadrada Curva de A° G°, 57 x 57 x 5 mm, Agujero de 18 mm Ø | G77: u | H77: 1.67 | J77: 211 | K77: =+ROUND($H77*J77,2) -> 352.37 | L77: =+[192]Metrado!E72 -> 212 | M77: =+ROUND($H77*L77,2) -> 354.04 | N77: =+IF($L77-$J77>=0,$L77-$J77,0) -> 1 | O77: =+ROUND($H77*N77,2) -> 1.67 | Q77: =+ROUND($H77*P77,2) -> 0 | R77: =+IF($L77-$J77<=0,-$L77+$J77,0) -> 0 | S77: =+ROUND($H77*R77,2) -> 0 | T77: =+R77 -> 0 | U77: =+ROUND($H77*T77,2) -> 0 | V77: Se vincula con el mayor metrado de la partida 10.10 | Y77: 0
B78: 10.12 | C78: =+C75+1 -> #REF! | D78: Plantillas para Identificación y/o codificación de Postes (Peligro, Identificación y/o codificación y Fases) | G78: Jgo. | H78: 23.08 | J78: 34 | K78: =+ROUND($H78*J78,2) -> 784.72 | L78: =+[192]Metrado!E73 -> 17 | M78: =+ROUND($H78*L78,2) -> 392.36 | N78: =+IF($L78-$J78>=0,$L78-$J78,0) -> 0 | O78: =+ROUND($H78*N78,2) -> 0 | Q78: =+ROUND($H78*P78,2) -> 0 | R78: =+IF($L78-$J78<=0,-$L78+$J78,0) -> 17 | S78: =+ROUND($H78*R78,2) -> 392.36 | U78: =+ROUND($H78*T78,2) -> 0 | Y78: 0
B79: 10.13 | C79: =+C78+1 -> #REF! | D79: Placa de Señal de Peligro y accesorios de fijación | G79: u | H79: 18.24 | J79: 2 | K79: =+ROUND($H79*J79,2) -> 36.48 | L79: =+[192]Metrado!E74 -> 0 | M79: =+ROUND($H79*L79,2) -> 0 | N79: =+IF($L79-$J79>=0,$L79-$J79,0) -> 0 | O79: =+ROUND($H79*N79,2) -> 0 | Q79: =+ROUND($H79*P79,2) -> 0 | R79: =+IF($L79-$J79<=0,-$L79+$J79,0) -> 2 | S79: =+ROUND($H79*R79,2) -> 36.48 | U79: =+ROUND($H79*T79,2) -> 0 | Y79: 0
B80: 10.14 | C80: =+C77+1 -> #REF! | D80: Placa de Identificación y/o codificación de Estructura y accesorios de fijación | G80: u | H80: 16.84 | J80: 2 | K80: =+ROUND($H80*J80,2) -> 33.68 | L80: =+[192]Metrado!E75 -> 0 | M80: =+ROUND($H80*L80,2) -> 0 | N80: =+IF($L80-$J80>=0,$L80-$J80,0) -> 0 | O80: =+ROUND($H80*N80,2) -> 0 | Q80: =+ROUND($H80*P80,2) -> 0 | R80: =+IF($L80-$J80<=0,-$L80+$J80,0) -> 2 | S80: =+ROUND($H80*R80,2) -> 33.68 | U80: =+ROUND($H80*T80,2) -> 0 | Y80: 0
B81: 10.15 | C81: =+C80+1 -> #REF! | D81: Placa de Secuencia de Fases y accesorios de fijación | G81: u | H81: 18.78 | J81: 2 | K81: =+ROUND($H81*J81,2) -> 37.56 | L81: =+[192]Metrado!E76 -> 0 | M81: =+ROUND($H81*L81,2) -> 0 | N81: =+IF($L81-$J81>=0,$L81-$J81,0) -> 0 | O81: =+ROUND($H81*N81,2) -> 0 | Q81: =+ROUND($H81*P81,2) -> 0 | R81: =+IF($L81-$J81<=0,-$L81+$J81,0) -> 2 | S81: =+ROUND($H81*R81,2) -> 37.56 | U81: =+ROUND($H81*T81,2) -> 0 | Y81: 0
B82: 10.16 | C82: =+#REF!+1 -> #REF! | D82: Perno de A°G° de 16 mm Ø x 457 mm, provisto de tuerca y contratuerca | G82: u | I82: =+H71*1.5 -> 14.73 | K82: =+ROUND($H82*J82,2) -> 0 | L82: =+[192]Metrado!E77 -> 6 | M82: =+ROUND($I82*L82,2) -> 88.38 | O82: =+ROUND($H82*N82,2) -> 0 | P82: =+L82 -> 6 | Q82: =+ROUND($I82*P82,2) -> 88.38 | S82: =+ROUND($H82*R82,2) -> 0 | U82: =+ROUND($H82*T82,2) -> 0 | Y82: 0
B83: 10.17 | C83: =+#REF!+1 -> #REF! | D83: Soporte separador de vértice de poste de A°G° fabricado con platina de 76 x 6,4 mm | G83: u | I83: 31.42 | K83: =+ROUND($H83*J83,2) -> 0 | L83: =+[192]Metrado!E78 -> 6 | M83: =+ROUND($I83*L83,2) -> 188.52 | O83: =+ROUND($H83*N83,2) -> 0 | P83: =+L83 -> 6 | Q83: =+ROUND($I83*P83,2) -> 188.52 | S83: =+ROUND($H83*R83,2) -> 0 | U83: =+ROUND($H83*T83,2) -> 0 | Y83: 0
B84: 10.18 | C84: =+#REF!+1 -> #REF! | D84: Tubo espaciador de A°G° de 19 mm x 38 mm Ø | G84: u | I84: 3.98 | K84: =+ROUND($H84*J84,2) -> 0 | L84: =+[192]Metrado!E79 -> 6 | M84: =+ROUND($I84*L84,2) -> 23.88 | O84: =+ROUND($H84*N84,2) -> 0 | P84: =+L84 -> 6 | Q84: =+ROUND($I84*P84,2) -> 23.88 | S84: =+ROUND($H84*R84,2) -> 0 | U84: =+ROUND($H84*T84,2) -> 0 | Y84: 0
C85: =+C84+1 -> #REF! | F85: =+"SUB-TOTAL "&B66&": " -> SUB-TOTAL 10: | K85: =+SUM(K67:K84) -> 3611.97 | M85: =+SUM(M67:M84) -> 3735.48 | O85: =+SUM(O67:O84) -> 506.55 | Q85: =+SUM(Q67:Q84) -> 300.78 | S85: =+SUM(S67:S84) -> 683.82 | U85: =+SUM(U67:U84) -> 57.14 | Y85: 0
B86: =1+B66 -> 11 | C86: =+C18+1 -> 5 | D86: RETENIDAS Y ANCLAJES | Y86: 0
B87: 11.01 | C87: =+C86+1 -> 6 | D87: Cable de Acero Grado Siemens Martin, de 10 mm Ø, 7 hilos | G87: u | H87: 4.31 | J87: 154 | K87: =+ROUND($H87*J87,2) -> 663.74 | L87: =+[192]Metrado!E82 -> 0 | M87: =+ROUND($H87*L87,2) -> 0 | N87: =+IF($L87-$J87>=0,$L87-$J87,0) -> 0 | O87: =+ROUND($H87*N87,2) -> 0 | Q87: =+ROUND($H87*P87,2) -> 0 | R87: =+IF($L87-$J87<=0,-$L87+$J87,0) -> 154 | S87: =+ROUND($H87*R87,2) -> 663.74 | U87: =+ROUND($H87*T87,2) -> 0 | Y87: 0
B88: 11.02 | C88: =+C87+1 -> 7 | D88: Varilla de Anclaje de A°G° de 16 mm Ø x 2,40 m, provisto de Ojal Guardacabo en un extremo; Tuerca y Contratuerca en el otro | G88: u | H88: 46.85 | J88: 9 | K88: =+ROUND($H88*J88,2) -> 421.65 | L88: =+[192]Metrado!E83 -> 14 | M88: =+ROUND($H88*L88,2) -> 655.9 | N88: =+IF($L88-$J88>=0,$L88-$J88,0) -> 5 | O88: =+ROUND($H88*N88,2) -> 234.25 | Q88: =+ROUND($H88*P88,2) -> 0 | R88: =+IF($L88-$J88<=0,-$L88+$J88,0) -> 0 | S88: =+ROUND($H88*R88,2) -> 0 | U88: =+ROUND($H88*T88,2) -> 0 | Y88: 0
B89: 11.03 | C89: =+C88+1 -> 8 | D89: Mordaza Preformada de A°G° para Cable de 10 mm Ø | G89: u | H89: 11.69 | J89: 38 | K89: =+ROUND($H89*J89,2) -> 444.22 | L89: =+[192]Metrado!E84 -> 72 | M89: =+ROUND($H89*L89,2) -> 841.68 | N89: =+IF($L89-$J89>=0,$L89-$J89,0) -> 34 | O89: =+ROUND($H89*N89,2) -> 397.46 | Q89: =+ROUND($H89*P89,2) -> 0 | R89: =+IF($L89-$J89<=0,-$L89+$J89,0) -> 0 | S89: =+ROUND($H89*R89,2) -> 0 | U89: =+ROUND($H89*T89,2) -> 0 | Y89: 0
B90: 11.04 | C90: =+C89+1 -> 9 | D90: Alambre de Acero N° 14 para Entorchado | G90: u | H90: 0.71 | J90: 36 | K90: =+ROUND($H90*J90,2) -> 25.56 | L90: =+[192]Metrado!E85 -> 21 | M90: =+ROUND($H90*L90,2) -> 14.91 | N90: =+IF($L90-$J90>=0,$L90-$J90,0) -> 0 | O90: =+ROUND($H90*N90,2) -> 0 | Q90: =+ROUND($H90*P90,2) -> 0 | R90: =+IF($L90-$J90<=0,-$L90+$J90,0) -> 15 | S90: =+ROUND($H90*R90,2) -> 10.65 | U90: =+ROUND($H90*T90,2) -> 0 | Y90: 0
B91: 11.05 | C91: =+C90+1 -> 10 | D91: Arandela de Anclaje de A°G°, 102 x 102 x 6,35 mm, Agujero de 18 mmø | G91: u | H91: 5.46 | J91: 9 | K91: =+ROUND($H91*J91,2) -> 49.14 | L91: =+[192]Metrado!E86 -> 14 | M91: =+ROUND($H91*L91,2) -> 76.44 | N91: =+IF($L91-$J91>=0,$L91-$J91,0) -> 5 | O91: =+ROUND($H91*N91,2) -> 27.3 | Q91: =+ROUND($H91*P91,2) -> 0 | R91: =+IF($L91-$J91<=0,-$L91+$J91,0) -> 0 | S91: =+ROUND($H91*R91,2) -> 0 | U91: =+ROUND($H91*T91,2) -> 0 | Y91: 0
B92: 11.06 | C92: =+C91+1 -> 11 | D92: Grillete de Acero de 70 kN | G92: u | H92: 15.01 | J92: 16 | K92: =+ROUND($H92*J92,2) -> 240.16 | L92: =+[192]Metrado!E87 -> 14 | M92: =+ROUND($H92*L92,2) -> 210.14 | N92: =+IF($L92-$J92>=0,$L92-$J92,0) -> 0 | O92: =+ROUND($H92*N92,2) -> 0 | Q92: =+ROUND($H92*P92,2) -> 0 | R92: =+IF($L92-$J92<=0,-$L92+$J92,0) -> 2 | S92: =+ROUND($H92*R92,2) -> 30.02 | U92: =+ROUND($H92*T92,2) -> 0 | Y92: 0
B93: 11.07 | C93: =+C92+1 -> 12 | D93: Enlace metálico, de 254 mm x 75 mm x 38 mm, de 70 kN de resistencia | G93: m | H93: 28.99 | J93: 9 | K93: =+ROUND($H93*J93,2) -> 260.91 | L93: =+[192]Metrado!E88 -> 14 | M93: =+ROUND($H93*L93,2) -> 405.86 | N93: =+IF($L93-$J93>=0,$L93-$J93,0) -> 5 | O93: =+ROUND($H93*N93,2) -> 144.95 | Q93: =+ROUND($H93*P93,2) -> 0 | R93: =+IF($L93-$J93<=0,-$L93+$J93,0) -> 0 | S93: =+ROUND($H93*R93,2) -> 0 | U93: =+ROUND($H93*T93,2) -> 0 | Y93: 0
B94: 11.08 | C94: =+C93+1 -> 13 | D94: Aislador Polimerico con Conexión Horquilla (Estructura) y Lengüeta (Linea) de 36 kV, según Especificacion Técnica, para Retenida Aislada. | G94: u | H94: 76.66 | J94: 9 | K94: =+ROUND($H94*J94,2) -> 689.94 | L94: =+[192]Metrado!E89 -> 14 | M94: =+ROUND($H94*L94,2) -> 1073.24 | N94: =+IF($L94-$J94>=0,$L94-$J94,0) -> 5 | O94: =+ROUND($H94*N94,2) -> 383.3 | Q94: =+ROUND($H94*P94,2) -> 0 | R94: =+IF($L94-$J94<=0,-$L94+$J94,0) -> 0 | S94: =+ROUND($H94*R94,2) -> 0 | U94: =+ROUND($H94*T94,2) -> 0 | Y94: 0
B95: 11.09 | C95: =+C94+1 -> 14 | D95: Bloque de Concreto de 0,40 x 0,40 x 0,15 m | G95: u | H95: 40.94 | J95: 9 | K95: =+ROUND($H95*J95,2) -> 368.46 | L95: =+[192]Metrado!E90 -> 14 | M95: =+ROUND($H95*L95,2) -> 573.16 | N95: =+IF($L95-$J95>=0,$L95-$J95,0) -> 5 | O95: =+ROUND($H95*N95,2) -> 204.7 | Q95: =+ROUND($H95*P95,2) -> 0 | R95: =+IF($L95-$J95<=0,-$L95+$J95,0) -> 0 | S95: =+ROUND($H95*R95,2) -> 0 | U95: =+ROUND($H95*T95,2) -> 0 | Y95: 0
B96: 11.1 | C96: =+C95+1 -> 15 | D96: Tuerca-Ojo para Perno de 16 mm Ø | G96: u | H96: 11.17 | J96: 5 | K96: =+ROUND($H96*J96,2) -> 55.85 | L96: =+[192]Metrado!E91 -> 8 | M96: =+ROUND($H96*L96,2) -> 89.36 | N96: =+IF($L96-$J96>=0,$L96-$J96,0) -> 3 | O96: =+ROUND($H96*N96,2) -> 33.51 | Q96: =+ROUND($H96*P96,2) -> 0 | R96: =+IF($L96-$J96<=0,-$L96+$J96,0) -> 0 | S96: =+ROUND($H96*R96,2) -> 0 | U96: =+ROUND($H96*T96,2) -> 0 | Y96: 0
B97: 11.11 | C97: =+C96+1 -> 16 | D97: Abrazadera de 4 sectores para Retenida, de 75 mm de altura, 6,35 mm de espesor y 70 kN de resistencia. Diámetro según dimensiones del poste, incluye 4 pernos de 12,7 mm Ø x 63,5 mm y 4 arandelas | G97: u | H97: 81.85 | J97: 9 | K97: =+ROUND($H97*J97,2) -> 736.65 | L97: =+[192]Metrado!E92 -> 14 | M97: =+ROUND($H97*L97,2) -> 1145.9 | N97: =+IF($L97-$J97>=0,$L97-$J97,0) -> 5 | O97: =+ROUND($H97*N97,2) -> 409.25 | Q97: =+ROUND($H97*P97,2) -> 0 | R97: =+IF($L97-$J97<=0,-$L97+$J97,0) -> 0 | S97: =+ROUND($H97*R97,2) -> 0 | U97: =+ROUND($H97*T97,2) -> 0 | Y97: 0
B98: 11.12 | C98: =+C97+1 -> 17 | D98: Cable de acero grado Alta Resistencia (HS), de 10 mm ø, 7 hilos | G98: u | I98: =+H87 -> 4.31 | K98: =+ROUND($H98*J98,2) -> 0 | L98: =+[192]Metrado!E93 -> 212 | M98: =+ROUND($I98*L98,2) -> 913.72 | O98: =+ROUND($H98*N98,2) -> 0 | P98: =+L98 -> 212 | Q98: =+ROUND($I98*P98,2) -> 913.72 | R98: =+IF($L98-$J98<=0,-$L98+$J98,0) -> 0 | S98: =+ROUND($H98*R98,2) -> 0 | U98: =+ROUND($H98*T98,2) -> 0 | Y98: 0
C99: =+#REF!+1 -> #REF! | F99: =+"SUB-TOTAL "&B86&": " -> SUB-TOTAL 11: | K99: =+SUM(K87:K98) -> 3956.28 | M99: =+SUM(M87:M98) -> 6000.31 | O99: =+SUM(O87:O98) -> 1834.72 | Q99: =+SUM(Q87:Q98) -> 913.72 | S99: =+SUM(S87:S98) -> 704.41 | U99: =+SUM(U87:U98) -> 0 | Y99: 0
B100: =1+B86 -> 12 | C100: =+#REF!+1 -> #REF! | D100: MATERIAL PARA PUESTA A TIERRA | Y100: 0
B101: 12.01 | C101: =+C100+1 -> #REF! | D101: Electrodo de Acero Recubierto de Cobre de 16 mm Ø x 2,40 m | G101: u | H101: 66.7 | J101: 49 | K101: =+ROUND($H101*J101,2) -> 3268.3 | L101: =+[192]Metrado!E96 -> 45 | M101: =+ROUND($H101*L101,2) -> 3001.5 | N101: =+IF($L101-$J101>=0,$L101-$J101,0) -> 0 | O101: =+ROUND($H101*N101,2) -> 0 | Q101: =+ROUND($H101*P101,2) -> 0 | R101: =+IF($L101-$J101<=0,-$L101+$J101,0) -> 4 | S101: =+ROUND($H101*R101,2) -> 266.8 | U101: =+ROUND($H101*T101,2) -> 0 | Y101: 0
B102: 12.02 | C102: =+C101+1 -> #REF! | D102: Caja Registro de Concreto para Puesta a Tierra 0,50 x 0,50 x 0,45 m | G102: u | H102: 53.58 | J102: 49 | K102: =+ROUND($H102*J102,2) -> 2625.42 | L102: =+[192]Metrado!E97 -> 45 | M102: =+ROUND($H102*L102,2) -> 2411.1 | N102: =+IF($L102-$J102>=0,$L102-$J102,0) -> 0 | O102: =+ROUND($H102*N102,2) -> 0 | Q102: =+ROUND($H102*P102,2) -> 0 | R102: =+IF($L102-$J102<=0,-$L102+$J102,0) -> 4 | S102: =+ROUND($H102*R102,2) -> 214.32 | U102: =+ROUND($H102*T102,2) -> 0 | Y102: 0
B103: 12.03 | C103: =+C102+1 -> #REF! | D103: Plancha Doblada de Cobre para toma a Tierra de Espigas y/o Pernos | G103: u | H103: 10.54 | J103: 72 | K103: =+ROUND($H103*J103,2) -> 758.88 | L103: =+[192]Metrado!E98 -> 117 | M103: =+ROUND($H103*L103,2) -> 1233.18 | N103: =+IF($L103-$J103>=0,$L103-$J103,0) -> 45 | O103: =+ROUND($H103*N103,2) -> 474.3 | Q103: =+ROUND($H103*P103,2) -> 0 | R103: =+IF($L103-$J103<=0,-$L103+$J103,0) -> 0 | S103: =+ROUND($H103*R103,2) -> 0 | U103: =+ROUND($H103*T103,2) -> 0 | Y103: 0
B104: 12.04 | C104: =+C103+1 -> #REF! | D104: Conector de Bronce para Electrodo de 16 mm ø y Cable de Acero con Recubrimiento Metalúrgico de Cobre de 4 AWG (21,15 mm2) | G104: u | H104: 6.94 | J104: 49 | K104: =+ROUND($H104*J104,2) -> 340.06 | L104: =+[192]Metrado!E99 -> 45 | M104: =+ROUND($H104*L104,2) -> 312.3 | N104: =+IF($L104-$J104>=0,$L104-$J104,0) -> 0 | O104: =+ROUND($H104*N104,2) -> 0 | Q104: =+ROUND($H104*P104,2) -> 0 | R104: =+IF($L104-$J104<=0,-$L104+$J104,0) -> 4 | S104: =+ROUND($H104*R104,2) -> 27.76 | U104: =+ROUND($H104*T104,2) -> 0 | Y104: 0
B105: 12.05 | C105: =+C104+1 -> #REF! | D105: Conector de Cobre tipo Perno Partido para Cable de Acero con Recubrimiento Metalúrgico de Cobre de 4 AWG (21,15 mm2) | G105: u | H105: 7.4 | J105: 150 | K105: =+ROUND($H105*J105,2) -> 1110 | L105: =+[192]Metrado!E100 -> 101 | M105: =+ROUND($H105*L105,2) -> 747.4 | N105: =+IF($L105-$J105>=0,$L105-$J105,0) -> 0 | O105: =+ROUND($H105*N105,2) -> 0 | Q105: =+ROUND($H105*P105,2) -> 0 | R105: =+IF($L105-$J105<=0,-$L105+$J105,0) -> 49 | S105: =+ROUND($H105*R105,2) -> 362.6 | U105: =+ROUND($H105*T105,2) -> 0 | Y105: 0
B106: 12.06 | C106: =+C105+1 -> #REF! | D106: Grapa en "U" para fijar conductor de PAT a Madera | G106: u | H106: 0.47 | J106: 140 | K106: =+ROUND($H106*J106,2) -> 65.8 | L106: =+[192]Metrado!E101 -> 40 | M106: =+ROUND($H106*L106,2) -> 18.8 | N106: =+IF($L106-$J106>=0,$L106-$J106,0) -> 0 | O106: =+ROUND($H106*N106,2) -> 0 | Q106: =+ROUND($H106*P106,2) -> 0 | R106: =+IF($L106-$J106<=0,-$L106+$J106,0) -> 100 | S106: =+ROUND($H106*R106,2) -> 47 | U106: =+ROUND($H106*T106,2) -> 0 | Y106: 0
B107: 12.07 | C107: =+C106+1 -> #REF! | D107: Tubo Plastico de PVC SAP de 19 mm ø x 0,5 m ( incluye curva de plastico de 19 mm ø x 90º) | G107: u | H107: 2.39 | J107: 34 | K107: =+ROUND($H107*J107,2) -> 81.26 | L107: =+[192]Metrado!E102 -> 59 | M107: =+ROUND($H107*L107,2) -> 141.01 | N107: =+IF($L107-$J107>=0,$L107-$J107,0) -> 25 | O107: =+ROUND($H107*N107,2) -> 59.75 | Q107: =+ROUND($H107*P107,2) -> 0 | R107: =+IF($L107-$J107<=0,-$L107+$J107,0) -> 0 | S107: =+ROUND($H107*R107,2) -> 0 | U107: =+ROUND($H107*T107,2) -> 0 | Y107: 0
...

Sheet FP RP
B3: FORMULA POLINÓMICA
C6: PROYECTO :
C7: AMPLIACIÓN DEL SERVICIO DE ENERGÍA ELÉCTRICA EN LA PROVINCIA DEL SANTA Y EN EL DISTRITO DE PAMPAROMAS – DEPARTAMENTO DE ANCASH”
C9: REDES PRIMARIAS
C10: PRESUPUESTO BASE S/ | D10: =+'RES-RP'!H18 -> 370101.88 | L10: =D10=SUM(G13:G28) -> TRUE
B12: Nº | C12: ELEMENTO REPRESENTATIVO | D12: INDICE | E12: SIMBOLO | F12: SIMBOLO MONOMIO | G12: MONTO | H12: INCIDENCIA | I12: % PARCIAL | J12: COEFICIENTE
B13: 1 | C13: POSTES DE MADERA IMPORTADA | D13: 042 | E13: PM | F13: PC | G13: =+'Mtdo-Ppto RP'!M31 -> 0 | H13: =ROUND(G13/$D$10,3) -> 0 | I13: =ROUND(G13/SUM($G$13:$G$20),4) -> 0 | J13: =ROUND(SUM(H13:H20),3) -> 0.247
C14: CRUCETAS DE MADERA | D14: 043 | E14: CM | G14: =+'Mtdo-Ppto RP'!M22 -> 2021 | H14: =ROUND(G14/$D$10,3) -> 0.005 | I14: =ROUND(G14/SUM($G$13:$G$20),4) -> 0.022
C15: POSTES DE CONCRETO | D15: 062 | E15: PC | G15: =+'Mtdo-Ppto RP'!M28+'Mtdo-Ppto RP'!M35 -> 53371.71 | H15: =ROUND(G15/$D$10,3) -> 0.144 | I15: =ROUND(G15/SUM($G$13:$G$20),4)+0.0001 -> 0.5812
C16: OTROS MATERIALES DE CONCRETO ARMADO | D16: 062 | E16: CC | G16: =+'Mtdo-Ppto RP'!M40 -> 9029.5 | H16: =ROUND(G16/$D$10,3) -> 0.024 | I16: =ROUND(G16/SUM($G$13:$G$20),4) -> 0.0983
C17: FERRETERIA PARA POSTES Y CRUCETAS | D17: 002 | E17: FP | G17: =+'Mtdo-Ppto RP'!M85 -> 3735.48 | H17: =ROUND(G17/$D$10,3) -> 0.01 | I17: =ROUND(G17/SUM($G$13:$G$20),4) -> 0.0407
C18: RETENIDAS Y ANCLAJES | D18: 002 | E18: FE | G18: =+'Mtdo-Ppto RP'!M99 -> 6000.31 | H18: =ROUND(G18/$D$10,3) -> 0.016 | I18: =ROUND(G18/SUM($G$13:$G$20),4) -> 0.0653
C19: CONDUCTOR DE COBRE Y ACCESORIOS | D19: 006 | E19: CU | G19: =+'Mtdo-Ppto RP'!M65 -> 5523.2 | H19: =ROUND(G19/$D$10,3) -> 0.015 | I19: =ROUND(G19/SUM($G$13:$G$20),4) -> 0.0601
C20: MATERIAL PARA PUESTA A TIERRA | D20: 006 | E20: PT | G20: =+'Mtdo-Ppto RP'!M111 -> 12159.04 | H20: =ROUND(G20/$D$10,3+0.1) -> 0.033 | I20: =ROUND(G20/SUM($G$13:$G$20),4) -> 0.1324
B21: 2 | C21: EQUIPOS DE PROTECCIÓN | D21: 011 | E21: AE1 | F21: AE1 | G21: =+'Mtdo-Ppto RP'!M117 -> 14296.26 | H21: =ROUND(G21/$D$10,3) -> 0.039 | I21: =ROUND(G21/SUM($G$21:$G$24),4) -> 0.3262 | J21: =ROUND(SUM(H21:H24),3) -> 0.119
C22: AISLADORES Y ACCESORIOS | D22: 011 | E22: AE2 | G22: =+'Mtdo-Ppto RP'!M47+'Mtdo-Ppto RP'!M51 -> 15572.01 | H22: =ROUND(G22/$D$10,3) -> 0.042 | I22: =ROUND(G22/SUM($G$21:$G$24),4)+0.0001 -> 0.3554
C23: CABLES DE ENERGÍA | D23: 019 | E23: NY | G23: =+'Mtdo-Ppto RP'!M135 -> 3267.22 | H23: =ROUND(G23/$D$10,3) -> 0.009 | I23: =ROUND(G23/SUM($G$21:$G$24),4) -> 0.0745
C24: CONDUCTORES DE AAAC Y ACCESORIOS | D24: 030 | E24: DI | G24: =+'Mtdo-Ppto RP'!M54+'Mtdo-Ppto RP'!M62 -> 10691.09 | H24: =ROUND(G24/$D$10,3) -> 0.029 | I24: =ROUND(G24/SUM($G$21:$G$24),4) -> 0.2439
B25: 3 | C25: TRANSFORMADORES DE DISTRIBUCIÓN Y TABLEROS | D25: 048 | E25: EN | F25: EN | G25: =+'Mtdo-Ppto RP'!M124+'Mtdo-Ppto RP'!M130 -> 87538.77 | H25: =ROUND(G25/$D$10,3) -> 0.237 | I25: =ROUND(G25/SUM($G$25:$G$25),4) -> 1 | J25: =ROUND(SUM(H25),3) -> 0.237
B26: 4 | C26: MONTAJE ELECTROMECANICO | D26: 047 | E26: J | F26: J | G26: =+'Mtdo-Ppto RP'!M235 -> 84855.49 | H26: =ROUND(G26/$D$10,3) -> 0.229 | I26: =ROUND(G26/($G$26+$G$27),4) -> 0.8161 | J26: =ROUND(SUM(H26:H27),3) -> 0.281
C27: TRANSPORTE | D27: 032 | E27: FT | G27: =+'Mtdo-Ppto RP'!M356 -> 19115.26 | H27: =ROUND(G27/$D$10,3) -> 0.052 | I27: =ROUND(G27/($G$26+$G$27),4) -> 0.1839
B28: 5 | C28: GASTOS GENERALES Y UTILIDADES | D28: 039 | E28: GG | F28: GG | G28: =+'RES-RP'!H16+'RES-RP'!H17 -> 42925.54 | H28: =ROUND(G28/$D$10,3) -> 0.116 | I28: =+G28/G28 -> 1 | J28: =ROUND(SUM(H28),3) -> 0.116
B30: K= | C30: =J13&" PCr/PCo + "&J21&" AE1r/AE1o + "&J25&" ENr/ENo+ "&J26&" Jr/Jo + "&J28&" GGr/GGo" -> 0.247 PCr/PCo + 0.119 AE1r/AE1o + 0.237 ENr/ENo+ 0.281 Jr/Jo + 0.116 GGr/GGo
B33: NOTAS:
B35: 1.- | C35: En la fórmula los sub-indices "o" de cada símbolo corresponden al indice de precios según (CREPCO) a la
C36: fecha de Elaboración del Presupuesto (Presupuesto Base) y los sub-indices "r" al indice de precios al
C37: momento de reajuste o fecha de valorización
B38: 2.- | C38: En el caso de los monomios compuestos por varios indices se ha considerado para efecto de denominación
C39: el símbolo que tiene mayor porcentaje de incidencia
B40: 3.- | C40: En caso de cambios en el suministro se deberá actualizar la formula polinómica.
H42: =+IF(SUM(H13:H28)=1,"OK","X") -> OK | I42: =+IF(SUM(I13:I28)=5,"OK","X") -> OK | J42: =+IF(SUM(J13:J28)=1,"OK","X") -> OK

Sheet RES-RS
B2: RESUMEN PRESUPUESTO DE OBRA
B4: AMPLIACIÓN DEL SERVICIO DE ENERGÍA ELÉCTRICA EN LA PROVINCIA DEL SANTA Y EN EL DISTRITO DE PAMPAROMAS – DEPARTAMENTO DE ANCASH
B6: UBICACIÓN | C6: : | D6: ANCASH
B7: SECCIÓN III | C7: : | D7: REDES SECUNDARIAS | H7: Fecha: 30-May-2022
H8: T.C. (S/ /US$): 3,683
B9: ITEM | C9: DESCRIPCION | G9: PRESUPUESTO CONTRATO | H9: PRESUPUESTO ESTUDIO DEFINIVO | I9: ADICIONALES | K9: DEDUCTIVOS
I10: MAYORES METRADOS | J10: PARTIDAS NUEVAS | K10: MENOR METRADO | L10: DEDUCTIVO VINCULANTE
B12: A | D12: SUMINISTRO DE MATERIALES | G12: =+'Mtdo-Ppto RS'!K127 -> 301377.1 | H12: =+'Mtdo-Ppto RS'!M127 -> 420410.61 | I12: =+'Mtdo-Ppto RS'!O127 -> 56280.94 | J12: =+'Mtdo-Ppto RS'!Q127 -> 142438.64 | K12: =+'Mtdo-Ppto RS'!S127 -> 79686.08 | L12: =+'Mtdo-Ppto RS'!U127 -> 71672.95
B13: B | D13: MONTAJE ELECTROMECANICO | G13: =+'Mtdo-Ppto RS'!K240 -> 273560.14 | H13: =+'Mtdo-Ppto RS'!M240 -> 323016.92 | I13: =+'Mtdo-Ppto RS'!O240 -> 56606.16 | J13: =+'Mtdo-Ppto RS'!Q240 -> 20757.42 | K13: =+'Mtdo-Ppto RS'!S240 -> 27906.79 | L13: =+'Mtdo-Ppto RS'!U240 -> 25189.23
B14: C | D14: TRANSPORTE DE MATERIALES | G14: =+'Mtdo-Ppto RS'!K352 -> 39859.51 | H14: =+'Mtdo-Ppto RS'!M352 -> 46723.13 | I14: =+'Mtdo-Ppto RS'!O352 -> 4340.58 | J14: =+'Mtdo-Ppto RS'!Q352 -> 6469.06 | K14: =+'Mtdo-Ppto RS'!S352 -> 3946.02 | L14: =+'Mtdo-Ppto RS'!U352 -> 3211.37
B15: D | D15: TOTAL COSTO DIRECTO | G15: =+SUM(G12:G14) -> 614796.75 | H15: =+SUM(H12:H14) -> 790150.66 | I15: =+SUM(I12:I14) -> 117227.68 | J15: =+SUM(J12:J14) -> 169665.12 | K15: =+SUM(K12:K14) -> 111538.89 | L15: =+SUM(L12:L14) -> 100073.55
B16: E | D16: GASTOS GENERALES (10.12%) | G16: =ROUND(G15*10.12%,2) -> 62217.43 | H16: =ROUND(H15*10.12%,2) -> 79963.25 | I16: =ROUND(I15*10.12%,2) -> 11863.44 | J16: =ROUND(J15*10.12%,2) -> 17170.11 | K16: =ROUND(K15*10.12%,2) -> 11287.74 | L16: =ROUND(L15*10.12%,2) -> 10127.44
B17: F | D17: UTILIDADES (3%) | G17: =ROUND(G15*3%,2) -> 18443.9 | H17: =ROUND(H15*3%,2) -> 23704.52 | I17: =ROUND(I15*3%,2) -> 3516.83 | J17: =ROUND(J15*3%,2) -> 5089.95 | K17: =ROUND(K15*3%,2) -> 3346.17 | L17: =ROUND(L15*3%,2) -> 3002.21
B18: G | D18: COSTO TOTAL S/. (No incluye I.G.V.) | G18: =G17+G16+G15 -> 695458.08 | H18: =H17+H16+H15 -> 893818.43 | I18: =I17+I16+I15 -> 132607.95 | J18: =J17+J16+J15 -> 191925.18 | K18: =K17+K16+K15 -> 126172.8 | L18: =L17+L16+L15 -> 113203.2 | M18: =+H18-G18 -> 198360.35
D20: INCIDENCIA % | G20: =+G18/G18 -> 1 | H20: =+H18/$G$18 -> 1.2852226 | I20: =+I18/$G$18 -> 0.19067713 | J20: =+J18/$G$18 -> 0.27596944 | K20: =+K18/$G$18 -> 0.18142402 | L20: =+L18/$G$18 -> 0.16277502
H22: =+H18-I18+K18-J18 -> 695458.1 | K22: =+G12-H12+I12+J12-K12 -> -0.01
H23: =+G18-H22 -> -0.02 | K23: =+G13-H13+I13+J13-K13 -> 0.01
K24: =+G14-H14+I14+J14-K14 -> -1.0004442e-11
K25: =+G15-H15+I15+J15-K15 -> 0

Sheet Mtdo-Ppto RS
B6: PRESUPUESTO DE OBRA
B8: OBRA | E8: : | F8: =+'RES-GRAL OBRA'!F4:L4 -> AMPLIACIÓN DEL SERVICIO DE ENERGÍA ELÉCTRICA EN LA PROVINCIA DEL SANTA Y EN EL DISTRITO DE PAMPAROMAS – DEPARTAMENTO DE ANCASH
B9: DEPARTAMENTO | E9: : | F9: =+'RES-GRAL OBRA'!F5 -> ANCASH
B10: SECCIÓN III | E10: : | F10: REDES SECUNDARIAS
B12: ITEM | C12: DESCRIPCIÓN DE PARTIDAS | G12: UNID. | H12: Precio de Contrato | I12: Precio Pactado | J12: CONTRACTUAL | L12: ESTUDIO DEFINITIVO | N12: ADICIONALES | R12: DEDUCTIVOS | V12: OBSERVACIÓN
J13: Metrado | K13: TOTAL | L13: Metrado | M13: TOTAL | N13: MAYORES METRADOS | P13: PARTIDAS NUEVAS | R13: MENORES METRADOS | T13: DEDUCTIVO VINCULANTE
N14: Metrado | O14: TOTAL | P14: Metrado | Q14: TOTAL | R14: Metrado | S14: TOTAL | T14: Metrado | U14: TOTAL
H15: Unitario | I15: Unitario | J15: Cantidad | K15: S/. | L15: Cantidad | M15: S/. | N15: Cantidad | O15: S/. | P15: Cantidad | Q15: S/. | R15: Cantidad | S15: S/. | T15: Cantidad | U15: S/.
B16: A | D16: SUMINISTRO DE MATERIALES
B17: 1 | C17: 3 | D17: POSTES DE CONCRETO ARMADO Y MADERA IMPORTADA
B18: =+B17+0.01 -> 1.01 | C18: =+C17+1 -> 4 | D18: Poste de C.A.C. de 8 m/200 daN (Incluye perilla) | G18: u | H18: 372.21 | J18: 153 | K18: =+ROUND($H18*J18,2) -> 56948.13 | L18: =+[193]Metrado!F12 -> 141 | M18: =+ROUND($H18*L18,2) -> 52481.61 | N18: =+IF($L18-$J18>=0,$L18-$J18,0) -> 0 | O18: =+ROUND($H18*N18,2) -> 0 | Q18: =+ROUND($H18*P18,2) -> 0 | R18: =+IF($L18-$J18<=0,-$L18+$J18,0) -> 12 | S18: =+ROUND($H18*R18,2) -> 4466.52 | T18: =+R18 -> 12 | U18: =+ROUND($H18*T18,2) -> 4466.52 | V18: Se vincula con el mayor metrado de la partida 1.02 | Y18: 0
B19: =+B18+0.01 -> 1.02 | C19: =+C18+1 -> 5 | D19: Poste de C.A.C. de 8 m/300 daN (Incluye perilla) | G19: u | H19: 402.99 | J19: 79 | K19: =+ROUND($H19*J19,2) -> 31836.21 | L19: =+[193]Metrado!F13 -> 100 | M19: =+ROUND($H19*L19,2) -> 40299 | N19: =+IF($L19-$J19>=0,$L19-$J19,0) -> 21 | O19: =+ROUND($H19*N19,2) -> 8462.79 | Q19: =+ROUND($H19*P19,2) -> 0 | R19: =+IF($L19-$J19<=0,-$L19+$J19,0) -> 0 | S19: =+ROUND($H19*R19,2) -> 0 | U19: =+ROUND($H19*T19,2) -> 0 | Y19: 0
C20: =+C19+1 -> 6 | F20: =+"SUB-TOTAL "&B17&": " -> SUB-TOTAL 1: | K20: =+SUM(K18:K19) -> 88784.34 | M20: =+SUM(M18:M19) -> 92780.61 | O20: =+SUM(O18:O19) -> 8462.79 | Q20: =+SUM(Q18:Q19) -> 0 | S20: =+SUM(S18:S19) -> 4466.52 | U20: =+SUM(U18:U19) -> 4466.52 | W20: =+K20-M20+O20+Q20-S20 -> 0 | Y20: 0
B21: =1+B17 -> 2 | C21: =+C20+1 -> 7 | D21: POSTES DE MADERA IMPORTADA | Y21: 0
B22: =+B21+0.01 -> 2.01 | C22: =+C21+1 -> 8 | D22: Poste de madera importada (Pino Amarillo del Sur) de 8 m, Clase 7 | G22: u | H22: 805.66 | J22: 9 | K22: =+ROUND($H22*J22,2) -> 7250.94 | L22: =+[193]Metrado!F16 -> 0 | M22: =+ROUND($H22*L22,2) -> 0 | N22: =+IF($L22-$J22>=0,$L22-$J22,0) -> 0 | O22: =+ROUND($H22*N22,2) -> 0 | Q22: =+ROUND($H22*P22,2) -> 0 | R22: =+IF($L22-$J22<=0,-$L22+$J22,0) -> 9 | S22: =+ROUND($H22*R22,2) -> 7250.94 | T22: =+R22 -> 9 | U22: =+ROUND($H22*T22,2) -> 7250.94 | V22: Se vincula con la partida nueva 2.01A | Y22: 0
C23: =+C22+1 -> 9 | F23: =+"SUB-TOTAL "&B21&": " -> SUB-TOTAL 2: | K23: =+SUM(K22) -> 7250.94 | M23: =+SUM(M22) -> 0 | O23: =+SUM(O22) -> 0 | Q23: =+SUM(Q22) -> 0 | S23: =+SUM(S22) -> 7250.94 | U23: =+SUM(U22) -> 7250.94 | W23: =+K23-M23+O23+Q23-S23 -> 0 | Y23: 0
B24: 2.00A | C24: =+C23+1 -> 10 | D24: POSTES DE FIBRA DE VIDRIO | Y24: 0
B25: 2.01A | C25: =+C24+1 -> 11 | D25: Postes en Poliéster Reforzado con Fibra de Vidrio (P.R.F.V) de 8m/200 (Incluye tapa) | G25: u | I25: 830.68 | K25: =+ROUND($H25*J25,2) -> 0 | L25: =+[193]Metrado!F19 -> 14 | M25: =+ROUND($I25*L25,2) -> 11629.52 | O25: =+ROUND($H25*N25,2) -> 0 | P25: =+L25 -> 14 | Q25: =+ROUND($I25*P25,2) -> 11629.52 | S25: =+ROUND($H25*R25,2) -> 0 | U25: =+ROUND($H25*T25,2) -> 0 | Y25: 0
B26: 2.02A | C26: =+C25+1 -> 12 | D26: Postes en Poliéster Reforzado con Fibra de Vidrio (P.R.F.V) de 8m/300 (Incluye tapa) | G26: u | I26: 921.22133 | K26: =+ROUND($H26*J26,2) -> 0 | L26: =+[193]Metrado!F20 -> 16 | M26: =+ROUND($I26*L26,2) -> 14739.54 | O26: =+ROUND($H26*N26,2) -> 0 | P26: =+L26 -> 16 | Q26: =+ROUND($I26*P26,2) -> 14739.54 | S26: =+ROUND($H26*R26,2) -> 0 | U26: =+ROUND($H26*T26,2) -> 0 | Y26: 0
C27: =+C26+1 -> 13 | F27: =+"SUB-TOTAL "&B24&": " -> SUB-TOTAL 2.00A: | K27: =+SUM(K25:K26) -> 0 | M27: =+SUM(M25:M26) -> 26369.06 | O27: =+SUM(O25:O26) -> 0 | Q27: =+SUM(Q25:Q26) -> 26369.06 | S27: =+SUM(S25:S26) -> 0 | U27: =+SUM(U25:U26) -> 0 | Y27: 0
B28: =+B21+1 -> 3 | C28: =+C27+1 -> 14 | D28: CABLES Y CONDUCTORES DE ALUMINIO | Y28: 0
B29: =+B28+0.01 -> 3.01 | C29: =+C28+1 -> 15 | D29: Conductor Autoportante de Aluminio 2X25+16/25 mm² | G29: km | H29: 7749.03 | J29: 1.46 | K29: =+ROUND($H29*J29,2) -> 11313.58 | L29: =+[193]Metrado!F23 -> 0.53 | M29: =+ROUND($H29*L29,2) -> 4106.99 | N29: =+IF($L29-$J29>=0,$L29-$J29,0) -> 0 | O29: =+ROUND($H29*N29,2) -> 0 | Q29: =+ROUND($H29*P29,2) -> 0 | R29: =+IF($L29-$J29<=0,-$L29+$J29,0) -> 0.93 | S29: =+ROUND($H29*R29,2) -> 7206.6 | T29: =+R29 -> 0.93 | U29: =+ROUND($H29*T29,2) -> 7206.6 | V29: Se vincula con las partidas nuevas 3.06, 3.07 y 3.08 | Y29: 0
B30: =+B29+0.01 -> 3.02 | C30: =+C29+1 -> 16 | D30: Conductor Autoportante de Aluminio 2X16+16/25 mm² | G30: km | H30: 6431.99 | J30: 0.05 | K30: =+ROUND($H30*J30,2) -> 321.6 | L30: =+[193]Metrado!F24 -> 0 | M30: =+ROUND($H30*L30,2) -> 0 | N30: =+IF($L30-$J30>=0,$L30-$J30,0) -> 0 | O30: =+ROUND($H30*N30,2) -> 0 | Q30: =+ROUND($H30*P30,2) -> 0 | R30: =+IF($L30-$J30<=0,-$L30+$J30,0) -> 0.05 | S30: =+ROUND($H30*R30,2) -> 321.6 | T30: =+R30 -> 0.05 | U30: =+ROUND($H30*T30,2) -> 321.6 | V30: Se vincula con las partidas nuevas 3.06, 3.07 y 3.08 | Y30: 0
B31: =+B30+0.01 -> 3.03 | C31: =+C30+1 -> 17 | D31: Conductor Autoportante de Aluminio 2X25/25 mm² | G31: km | H31: 6248.95 | J31: 7.08 | K31: =+ROUND($H31*J31,2) -> 44242.57 | L31: =+[193]Metrado!F25 -> 3.61 | M31: =+ROUND($H31*L31,2) -> 22558.71 | N31: =+IF($L31-$J31>=0,$L31-$J31,0) -> 0 | O31: =+ROUND($H31*N31,2) -> 0 | Q31: =+ROUND($H31*P31,2) -> 0 | R31: =+IF($L31-$J31<=0,-$L31+$J31,0) -> 3.47 | S31: =+ROUND($H31*R31,2) -> 21683.86 | T31: =+R31 -> 3.47 | U31: =+ROUND($H31*T31,2) -> 21683.86 | V31: Se vincula con las partidas nuevas 3.06, 3.07 y 3.08 | Y31: 0
B32: =+B31+0.01 -> 3.04 | C32: =+C31+1 -> 18 | D32: Conductor Autoportante de Aluminio 1X16+16/25 mm² | G32: km | H32: 4940.38 | J32: 0.18 | K32: =+ROUND($H32*J32,2) -> 889.27 | L32: =+[193]Metrado!F26 -> 0 | M32: =+ROUND($H32*L32,2) -> 0 | N32: =+IF($L32-$J32>=0,$L32-$J32,0) -> 0 | O32: =+ROUND($H32*N32,2) -> 0 | Q32: =+ROUND($H32*P32,2) -> 0 | R32: =+IF($L32-$J32<=0,-$L32+$J32,0) -> 0.18 | S32: =+ROUND($H32*R32,2) -> 889.27 | T32: =+R32 -> 0.18 | U32: =+ROUND($H32*T32,2) -> 889.27 | V32: Se vincula con las partidas nuevas 3.06, 3.07 y 3.08 | Y32: 0
B33: =+B32+0.01 -> 3.05 | C33: =+C32+1 -> 19 | D33: Conductor Autoportante de Aluminio 1X16/25 mm² | G33: km | H33: 3440.29 | J33: 4.06 | K33: =+ROUND($H33*J33,2) -> 13967.58 | L33: =+[193]Metrado!F27 -> 0.06 | M33: =+ROUND($H33*L33,2) -> 206.42 | N33: =+IF($L33-$J33>=0,$L33-$J33,0) -> 0 | O33: =+ROUND($H33*N33,2) -> 0 | Q33: =+ROUND($H33*P33,2) -> 0 | R33: =+IF($L33-$J33<=0,-$L33+$J33,0) -> 4 | S33: =+ROUND($H33*R33,2) -> 13761.16 | T33: =+R33 -> 4 | U33: =+ROUND($H33*T33,2) -> 13761.16 | V33: Se vincula con las partidas nuevas 3.06, 3.07 y 3.08 | Y33: 0
B34: =+B33+0.01 -> 3.06 | C34: =+#REF!+1 -> #REF! | D34: Conductor Autoportante de Aluminio 2x35+16/NA25 mm² | G34: km | I34: 8623.15 | K34: =+ROUND($H34*J34,2) -> 0 | L34: =+[193]Metrado!F28 -> 0.44 | M34: =+ROUND($I34*L34,2) -> 3794.19 | O34: =+ROUND($H34*N34,2) -> 0 | P34: =+L34 -> 0.44 | Q34: =+ROUND($I34*P34,2) -> 3794.19 | S34: =+ROUND($H34*R34,2) -> 0 | U34: =+ROUND($H34*T34,2) -> 0 | Y34: 0
B35: =+B34+0.01 -> 3.07 | C35: =+#REF!+1 -> #REF! | D35: Conductor Autoportante de Aluminio 2x25+16/NA25 mm² | G35: km | I35: 7908.7 | K35: =+ROUND($H35*J35,2) -> 0 | L35: =+[193]Metrado!F29 -> 4.31 | M35: =+ROUND($I35*L35,2) -> 34086.5 | O35: =+ROUND($H35*N35,2) -> 0 | P35: =+L35 -> 4.31 | Q35: =+ROUND($I35*P35,2) -> 34086.5 | S35: =+ROUND($H35*R35,2) -> 0 | U35: =+ROUND($H35*T35,2) -> 0 | Y35: 0
B36: =+B35+0.01 -> 3.08 | C36: =+C35+1 -> #REF! | D36: Conductor Autoportante de Aluminio 2x25/NA25 mm² | G36: km | I36: 6504.86 | K36: =+ROUND($H36*J36,2) -> 0 | L36: =+[193]Metrado!F30 -> 5.25 | M36: =+ROUND($I36*L36,2) -> 34150.52 | O36: =+ROUND($H36*N36,2) -> 0 | P36: =+L36 -> 5.25 | Q36: =+ROUND($I36*P36,2) -> 34150.52 | S36: =+ROUND($H36*R36,2) -> 0 | U36: =+ROUND($H36*T36,2) -> 0 | Y36: 0
C37: =+C36+1 -> #REF! | F37: =+"SUB-TOTAL "&B28&": " -> SUB-TOTAL 3: | K37: =+SUM(K29:K36) -> 70734.6 | M37: =+SUM(M29:M36) -> 98903.33 | O37: =+SUM(O29:O36) -> 0 | Q37: =+SUM(Q29:Q36) -> 72031.21 | S37: =+SUM(S29:S36) -> 43862.49 | U37: =+SUM(U29:U36) -> 43862.49 | W37: =+K37-M37+O37+Q37-S37 -> -0.01 | Y37: 0
B38: =+B28+1 -> 4 | C38: =+C37+1 -> #REF! | D38: ACCESORIOS DE CABLES AUTOPORTANTES | Y38: 0
B39: =+B38+0.01 -> 4.01 | C39: =+C38+1 -> #REF! | D39: Grapa de Suspensión Angular para Conductor de Aleacion de Aluminio de 25 mm2 | G39: u | H39: 12 | J39: 163 | K39: =+ROUND($H39*J39,2) -> 1956 | L39: =+[193]Metrado!F33 -> 182 | M39: =+ROUND($H39*L39,2) -> 2184 | N39: =+IF($L39-$J39>=0,$L39-$J39,0) -> 19 | O39: =+ROUND($H39*N39,2) -> 228 | Q39: =+ROUND($H39*P39,2) -> 0 | R39: =+IF($L39-$J39<=0,-$L39+$J39,0) -> 0 | S39: =+ROUND($H39*R39,2) -> 0 | U39: =+ROUND($H39*T39,2) -> 0 | Y39: 0
B40: =+B39+0.01 -> 4.02 | C40: =+C39+1 -> #REF! | D40: Grapa de Anclaje Cónica para Conductor de Aleación de Aluminio de 25 mm2 | G40: u | H40: 16.87 | J40: 218 | K40: =+ROUND($H40*J40,2) -> 3677.66 | L40: =+[193]Metrado!F34 -> 287 | M40: =+ROUND($H40*L40,2) -> 4841.69 | N40: =+IF($L40-$J40>=0,$L40-$J40,0) -> 69 | O40: =+ROUND($H40*N40,2) -> 1164.03 | Q40: =+ROUND($H40*P40,2) -> 0 | R40: =+IF($L40-$J40<=0,-$L40+$J40,0) -> 0 | S40: =+ROUND($H40*R40,2) -> 0 | U40: =+ROUND($H40*T40,2) -> 0 | Y40: 0
B41: =+B40+0.01 -> 4.03 | C41: =+C40+1 -> #REF! | D41: Conector Bimetálico para Al 25 mm2 / Cu 4-10 mm2, para Neutro Desnudo, tipo Cuña | G41: u | H41: 5.21 | J41: 2 | K41: =+ROUND($H41*J41,2) -> 10.42 | L41: =+[193]Metrado!F35 -> 0 | M41: =+ROUND($H41*L41,2) -> 0 | N41: =+IF($L41-$J41>=0,$L41-$J41,0) -> 0 | O41: =+ROUND($H41*N41,2) -> 0 | Q41: =+ROUND($H41*P41,2) -> 0 | R41: =+IF($L41-$J41<=0,-$L41+$J41,0) -> 2 | S41: =+ROUND($H41*R41,2) -> 10.42 | T41: =+R41 -> 2 | U41: =+ROUND($H41*T41,2) -> 10.42 | V41: Se vincula con el mayor metrado de la partida 4.04 | Y41: 0
B42: =+B41+0.01 -> 4.04 | C42: =+C41+1 -> #REF! | D42: Conector Bimetalico Aislado, para Al 16-35 mm2 / Cu 4-10 mm2, para Fase Aislada, tipo Perforación | G42: u | H42: 7.04 | J42: 4 | K42: =+ROUND($H42*J42,2) -> 28.16 | L42: =+[193]Metrado!F36 -> 27 | M42: =+ROUND($H42*L42,2) -> 190.08 | N42: =+IF($L42-$J42>=0,$L42-$J42,0) -> 23 | O42: =+ROUND($H42*N42,2) -> 161.92 | Q42: =+ROUND($H42*P42,2) -> 0 | R42: =+IF($L42-$J42<=0,-$L42+$J42,0) -> 0 | S42: =+ROUND($H42*R42,2) -> 0 | U42: =+ROUND($H42*T42,2) -> 0 | Y42: 0
B43: =+B42+0.01 -> 4.05 | C43: =+C42+1 -> #REF! | D43: Conector para Al 25 mm², para Neutro Desnudo, tipo Cuña | G43: u | H43: 9.06 | J43: 26 | K43: =+ROUND($H43*J43,2) -> 235.56 | L43: =+[193]Metrado!F37 -> 12 | M43: =+ROUND($H43*L43,2) -> 108.72 | N43: =+IF($L43-$J43>=0,$L43-$J43,0) -> 0 | O43: =+ROUND($H43*N43,2) -> 0 | Q43: =+ROUND($H43*P43,2) -> 0 | R43: =+IF($L43-$J43<=0,-$L43+$J43,0) -> 14 | S43: =+ROUND($H43*R43,2) -> 126.84 | T43: =+R43 -> 14 | U43: =+ROUND($H43*T43,2) -> 126.84 | V43: Se vincula con el mayor metrado de la partida 4.04 | Y43: 0
B44: =+B43+0.01 -> 4.06 | C44: =+C43+1 -> #REF! | D44: Conector Aislado para Al 16-35 mm2, para Fase Aislada, tipo Perforación | G44: u | H44: 10.95 | J44: 52 | K44: =+ROUND($H44*J44,2) -> 569.4 | L44: =+[193]Metrado!F38 -> 232 | M44: =+ROUND($H44*L44,2) -> 2540.4 | N44: =+IF($L44-$J44>=0,$L44-$J44,0) -> 180 | O44: =+ROUND($H44*N44,2) -> 1971 | Q44: =+ROUND($H44*P44,2) -> 0 | R44: =+IF($L44-$J44<=0,-$L44+$J44,0) -> 0 | S44: =+ROUND($H44*R44,2) -> 0 | U44: =+ROUND($H44*T44,2) -> 0 | Y44: 0
B45: =+B44+0.01 -> 4.07 | C45: =+C44+1 -> #REF! | D45: Correa Plástica de Amarre, color negro | G45: u | H45: 0.4 | J45: 1838 | K45: =+ROUND($H45*J45,2) -> 735.2 | L45: =+[193]Metrado!F39 -> 2278 | M45: =+ROUND($H45*L45,2) -> 911.2 | N45: =+IF($L45-$J45>=0,$L45-$J45,0) -> 440 | O45: =+ROUND($H45*N45,2) -> 176 | Q45: =+ROUND($H45*P45,2) -> 0 | R45: =+IF($L45-$J45<=0,-$L45+$J45,0) -> 0 | S45: =+ROUND($H45*R45,2) -> 0 | U45: =+ROUND($H45*T45,2) -> 0 | Y45: 0
B46: =+B45+0.01 -> 4.08 | C46: =+C45+1 -> #REF! | D46: Cinta Autofundente para extremo de cable | G46: m | H46: 4.46 | J46: 51.3 | K46: =+ROUND($H46*J46,2) -> 228.8 | L46: =+[193]Metrado!F40 -> 61 | M46: =+ROUND($H46*L46,2) -> 272.06 | N46: =+IF($L46-$J46>=0,$L46-$J46,0) -> 9.7 | O46: =+ROUND($H46*N46,2) -> 43.26 | Q46: =+ROUND($H46*P46,2) -> 0 | R46: =+IF($L46-$J46<=0,-$L46+$J46,0) -> 0 | S46: =+ROUND($H46*R46,2) -> 0 | U46: =+ROUND($H46*T46,2) -> 0 | Y46: 0
B47: =+B46+0.01 -> 4.09 | C47: =+C46+1 -> #REF! | D47: Cinta aislante | G47: m | H47: 1.53 | J47: 19 | K47: =+ROUND($H47*J47,2) -> 29.07 | L47: =+[193]Metrado!F41 -> 183 | M47: =+ROUND($H47*L47,2) -> 279.99 | N47: =+IF($L47-$J47>=0,$L47-$J47,0) -> 164 | O47: =+ROUND($H47*N47,2) -> 250.92 | Q47: =+ROUND($H47*P47,2) -> 0 | R47: =+IF($L47-$J47<=0,-$L47+$J47,0) -> 0 | S47: =+ROUND($H47*R47,2) -> 0 | U47: =+ROUND($H47*T47,2) -> 0 | Y47: 0
B48: =+B47+0.01 -> 4.1 | C48: =+C47+1 -> #REF! | D48: Grapa de Anclaje para Conductor de 25 mm² | G48: u | I48: 25.34 | K48: =+ROUND($H48*J48,2) -> 0 | L48: =+[193]Metrado!F42 -> 9 | M48: =+ROUND($I48*L48,2) -> 228.06 | O48: =+ROUND($H48*N48,2) -> 0 | P48: =+L48 -> 9 | Q48: =+ROUND($I48*P48,2) -> 228.06 | S48: =+ROUND($H48*R48,2) -> 0 | U48: =+ROUND($H48*T48,2) -> 0 | Y48: 0
B49: =+B48+0.01 -> 4.11 | C49: =+C48+1 -> #REF! | D49: Cinta plana de armar 1.3 mm x 7.6 mm | G49: m | I49: 1 | K49: =+ROUND($H49*J49,2) -> 0 | L49: =+[193]Metrado!F43 -> 9 | M49: =+ROUND($I49*L49,2) -> 9 | O49: =+ROUND($H49*N49,2) -> 0 | P49: =+L49 -> 9 | Q49: =+ROUND($I49*P49,2) -> 9 | S49: =+ROUND($H49*R49,2) -> 0 | U49: =+ROUND($H49*T49,2) -> 0 | Y49: 0
B50: =+B49+0.01 -> 4.12 | C50: =+C49+1 -> #REF! | D50: Grillete A°G° tipo Lira | G50: u | I50: 17.76 | K50: =+ROUND($H50*J50,2) -> 0 | L50: =+[193]Metrado!F44 -> 9 | M50: =+ROUND($I50*L50,2) -> 159.84 | O50: =+ROUND($H50*N50,2) -> 0 | P50: =+L50 -> 9 | Q50: =+ROUND($I50*P50,2) -> 159.84 | S50: =+ROUND($H50*R50,2) -> 0 | U50: =+ROUND($H50*T50,2) -> 0 | Y50: 0
C51: =+C50+1 -> #REF! | F51: =+"SUB-TOTAL "&B38&": " -> SUB-TOTAL 4: | K51: =+SUM(K39:K50) -> 7470.27 | M51: =+SUM(M39:M50) -> 11725.04 | O51: =+SUM(O39:O50) -> 3995.13 | Q51: =+SUM(Q39:Q50) -> 396.9 | S51: =+SUM(S39:S50) -> 137.26 | U51: =+SUM(U39:U50) -> 137.26 | W51: =+K51-M51+O51+Q51-S51 -> 5.6843419e-13 | Y51: 0
B52: =+B38+1 -> 5 | C52: =+C51+1 -> #REF! | D52: CABLES Y CONDUCTORES DE COBRE | Y52: 0
B53: =+B52+0.01 -> 5.01 | C53: =+C52+1 -> #REF! | D53: Conductor de Cobre Recocido, tipo N2XY, Tripolar, 3 x 10 mm2, cubierta negra | G53: m | H53: 19.26 | J53: 1.2 | K53: =+ROUND($H53*J53,2) -> 23.11 | L53: =+[193]Metrado!F47 -> 18 | M53: =+ROUND($H53*L53,2) -> 346.68 | N53: =+IF($L53-$J53>=0,$L53-$J53,0) -> 16.8 | O53: =+ROUND($H53*N53,2) -> 323.57 | Q53: =+ROUND($H53*P53,2) -> 0 | R53: =+IF($L53-$J53<=0,-$L53+$J53,0) -> 0 | S53: =+ROUND($H53*R53,2) -> 0 | U53: =+ROUND($H53*T53,2) -> 0 | Y53: 0
B54: =+B53+0.01 -> 5.02 | C54: =+C53+1 -> #REF! | D54: Conductor de Cobre Recocido, tipo N2XY, Bipolar, 2 x 2,5 mm2 | G54: m | H54: 4.82 | J54: 111.5 | K54: =+ROUND($H54*J54,2) -> 537.43 | L54: =+[193]Metrado!F48 -> 160 | M54: =+ROUND($H54*L54,2) -> 771.2 | N54: =+IF($L54-$J54>=0,$L54-$J54,0) -> 48.5 | O54: =+ROUND($H54*N54,2) -> 233.77 | Q54: =+ROUND($H54*P54,2) -> 0 | R54: =+IF($L54-$J54<=0,-$L54+$J54,0) -> 0 | S54: =+ROUND($H54*R54,2) -> 0 | U54: =+ROUND($H54*T54,2) -> 0 | Y54: 0
B55: =+B54+0.01 -> 5.03 | C55: =+C54+1 -> #REF! | D55: Conductor de Cobre Concéntrico, 2 x 4 mm2, con aislamiento y cubierta de PVC | G55: m | H55: 4.8 | J55: 3985 | K55: =+ROUND($H55*J55,2) -> 19128 | L55: =+[193]Metrado!F49 -> 7465 | M55: =+ROUND($H55*L55,2) -> 35832 | N55: =+IF($L55-$J55>=0,$L55-$J55,0) -> 3480 | O55: =+ROUND($H55*N55,2) -> 16704 | Q55: =+ROUND($H55*P55,2) -> 0 | R55: =+IF($L55-$J55<=0,-$L55+$J55,0) -> 0 | S55: =+ROUND($H55*R55,2) -> 0 | U55: =+ROUND($H55*T55,2) -> 0 | Y55: 0
B56: =+B55+0.01 -> 5.04 | C56: =+C55+1 -> #REF! | D56: Cable de Acero con Recubrimiento Metalúrgico de Cu de 4 AWG (21,15 mm²), para Puesta a Tierra | G56: m | H56: 12.8 | J56: 925.5 | K56: =+ROUND($H56*J56,2) -> 11846.4 | L56: =+[193]Metrado!F50 -> 912 | M56: =+ROUND($H56*L56,2) -> 11673.6 | N56: =+IF($L56-$J56>=0,$L56-$J56,0) -> 0 | O56: =+ROUND($H56*N56,2) -> 0 | Q56: =+ROUND($H56*P56,2) -> 0 | R56: =+IF($L56-$J56<=0,-$L56+$J56,0) -> 13.5 | S56: =+ROUND($H56*R56,2) -> 172.8 | U56: =+ROUND($H56*T56,2) -> 0 | Y56: 0
C57: =+C56+1 -> #REF! | F57: =+"SUB-TOTAL "&B52&": " -> SUB-TOTAL 5: | K57: =+SUM(K53:K56) -> 31534.94 | M57: =+SUM(M53:M56) -> 48623.48 | O57: =+SUM(O53:O56) -> 17261.34 | Q57: =+SUM(Q53:Q56) -> 0 | S57: =+SUM(S53:S56) -> 172.8 | U57: =+SUM(U53:U56) -> 0 | W57: =+K57-M57+O57+Q57-S57 -> 6.5369932e-12 | Y57: 0
B58: =+B52+1 -> 6 | C58: =+C57+1 -> #REF! | D58: LUMINARIAS, LAMPARAS Y ACCESORIOS | Y58: 0
B59: =+B58+0.01 -> 6.01 | C59: =+C58+1 -> #REF! | D59: Pastoral tubo A°G° 38 mm Ø interior, 500 mm avance horizontal, 720 mm altura y 20° inclinación, provisto de 2 abrazaderas simples y 4 tirafondos para poste de madera | G59: u | H59: 55.07 | J59: 2 | K59: =+ROUND($H59*J59,2) -> 110.14 | L59: =+[193]Metrado!F53 -> 0 | M59: =+ROUND($H59*L59,2) -> 0 | N59: =+IF($L59-$J59>=0,$L59-$J59,0) -> 0 | O59: =+ROUND($H59*N59,2) -> 0 | Q59: =+ROUND($H59*P59,2) -> 0 | R59: =+IF($L59-$J59<=0,-$L59+$J59,0) -> 2 | S59: =+ROUND($H59*R59,2) -> 110.14 | T59: =+R59 -> 2 | U59: =+ROUND($H59*T59,2) -> 110.14 | V59: Se vincula con el mayor metrado de la partida 6.02 | Y59: 0
B60: =+B59+0.01 -> 6.02 | C60: =+C59+1 -> #REF! | D60: Pastoral tubo A°G° 38 mm Ø interior, 500 mm avance horizontal, 720 mm altura y 20° inclinación, provisto de 2 abrazaderas dobles para poste de concreto | G60: u | H60: 66.86 | J60: 43 | K60: =+ROUND($H60*J60,2) -> 2874.98 | L60: =+[193]Metrado!F54 -> 80 | M60: =+ROUND($H60*L60,2) -> 5348.8 | N60: =+IF($L60-$J60>=0,$L60-$J60,0) -> 37 | O60: =+ROUND($H60*N60,2) -> 2473.82 | Q60: =+ROUND($H60*P60,2) -> 0 | R60: =+IF($L60-$J60<=0,-$L60+$J60,0) -> 0 | S60: =+ROUND($H60*R60,2) -> 0 | U60: =+ROUND($H60*T60,2) -> 0 | Y60: 0
B61: =+B60+0.01 -> 6.03 | C61: =+C60+1 -> #REF! | D61: Luminaria completa con equipo para Lámpara de Vapor de Sodio de 50 W | G61: u | H61: 251.32 | J61: 45 | K61: =+ROUND($H61*J61,2) -> 11309.4 | L61: =+[193]Metrado!F55 -> 0 | M61: =+ROUND($H61*L61,2) -> 0 | N61: =+IF($L61-$J61>=0,$L61-$J61,0) -> 0 | O61: =+ROUND($H61*N61,2) -> 0 | Q61: =+ROUND($H61*P61,2) -> 0 | R61: =+IF($L61-$J61<=0,-$L61+$J61,0) -> 45 | S61: =+ROUND($H61*R61,2) -> 11309.4 | T61: =+R61 -> 45 | U61: =+ROUND($H61*T61,2) -> 11309.4 | V61: Se vincula con la partida nueva 6.08 | Y61: 0
B62: =+B61+0.01 -> 6.04 | C62: =+C61+1 -> #REF! | D62: Lámpara de Vapor de Sodio de Alta Presión de 50 W | G62: u | H62: 38.94 | J62: 45 | K62: =+ROUND($H62*J62,2) -> 1752.3 | L62: =+[193]Metrado!F56 -> 0 | M62: =+ROUND($H62*L62,2) -> 0 | N62: =+IF($L62-$J62>=0,$L62-$J62,0) -> 0 | O62: =+ROUND($H62*N62,2) -> 0 | Q62: =+ROUND($H62*P62,2) -> 0 | R62: =+IF($L62-$J62<=0,-$L62+$J62,0) -> 45 | S62: =+ROUND($H62*R62,2) -> 1752.3 | T62: =+R62 -> 45 | U62: =+ROUND($H62*T62,2) -> 1752.3 | V62: Se vincula con la partida nueva 6.08 | Y62: 0
B63: =+B62+0.01 -> 6.05 | C63: =+C62+1 -> #REF! | D63: Portafusible Unipolar 220 V, de 5 A, provisto con fusible de 1 A | G63: u | H63: 3.31 | J63: 45 | K63: =+ROUND($H63*J63,2) -> 148.95 | L63: =+[193]Metrado!F57 -> 80 | M63: =+ROUND($H63*L63,2) -> 264.8 | N63: =+IF($L63-$J63>=0,$L63-$J63,0) -> 35 | O63: =+ROUND($H63*N63,2) -> 115.85 | Q63: =+ROUND($H63*P63,2) -> 0 | R63: =+IF($L63-$J63<=0,-$L63+$J63,0) -> 0 | S63: =+ROUND($H63*R63,2) -> 0 | U63: =+ROUND($H63*T63,2) -> 0 | Y63: 0
B64: =+B63+0.01 -> 6.06 | C64: =+C63+1 -> #REF! | D64: Conector Bimetalico Aislado, para Al 16-35 mm2 / Cu 4-10 mm2, para Fase Aislada, tipo Perforación | G64: u | H64: 7.04 | J64: 45 | K64: =+ROUND($H64*J64,2) -> 316.8 | L64: =+[193]Metrado!F58 -> 143 | M64: =+ROUND($H64*L64,2) -> 1006.72 | N64: =+IF($L64-$J64>=0,$L64-$J64,0) -> 98 | O64: =+ROUND($H64*N64,2) -> 689.92 | Q64: =+ROUND($H64*P64,2) -> 0 | R64: =+IF($L64-$J64<=0,-$L64+$J64,0) -> 0 | S64: =+ROUND($H64*R64,2) -> 0 | U64: =+ROUND($H64*T64,2) -> 0 | Y64: 0
B65: =+B64+0.01 -> 6.07 | C65: =+C64+1 -> #REF! | D65: Conector Bimetálico para Al 25 mm2 / Cu 4-10 mm2, para Neutro Desnudo, tipo Cuña | G65: u | H65: 5.21 | J65: 45 | K65: =+ROUND($H65*J65,2) -> 234.45 | L65: =+[193]Metrado!F59 -> 17 | M65: =+ROUND($H65*L65,2) -> 88.57 | N65: =+IF($L65-$J65>=0,$L65-$J65,0) -> 0 | O65: =+ROUND($H65*N65,2) -> 0 | Q65: =+ROUND($H65*P65,2) -> 0 | R65: =+IF($L65-$J65<=0,-$L65+$J65,0) -> 28 | S65: =+ROUND($H65*R65,2) -> 145.88 | T65: =+R65 -> 28 | U65: =+ROUND($H65*T65,2) -> 145.88 | V65: Se vincula con el mayor metrado de la partida 6.06 | Y65: 0
B66: =+B65+0.01 -> 6.08 | C66: =+C65+1 -> #REF! | D66: Luminaria para alumbrado público con tecnología LED de 50W a 55W (incluye accesorios de encendido y protección) | G66: u | I66: 386.46 | K66: =+ROUND($H66*J66,2) -> 0 | L66: =+[193]Metrado!F60 -> 80 | M66: =+ROUND($I66*L66,2) -> 30916.8 | O66: =+ROUND($H66*N66,2) -> 0 | P66: =+L66 -> 80 | Q66: =+ROUND($I66*P66,2) -> 30916.8 | S66: =+ROUND($H66*R66,2) -> 0 | U66: =+ROUND($H66*T66,2) -> 0 | Y66: 0
C67: =+C66+1 -> #REF! | F67: =+"SUB-TOTAL "&B58&": " -> SUB-TOTAL 6: | K67: =+SUM(K59:K66) -> 16747.02 | M67: =+SUM(M59:M66) -> 37625.69 | O67: =+SUM(O59:O66) -> 3279.59 | Q67: =+SUM(Q59:Q66) -> 30916.8 | S67: =+SUM(S59:S66) -> 13317.72 | U67: =+SUM(U59:U66) -> 13317.72 | W67: =+K67-M67+O67+Q67-S67 -> 0 | Y67: 0
B68: =+B58+1 -> 7 | C68: =+C67+1 -> #REF! | D68: RETENIDAS Y ANCLAJES | Y68: 0
B69: =+B68+0.01 -> 7.01 | C69: =+C68+1 -> #REF! | D69: Cable de acero grado Siemens Martin, de 10 mm ø, 7 hilos | G69: m | H69: 4.31 | J69: 1076 | K69: =+ROUND($H69*J69,2) -> 4637.56 | L69: =+[193]Metrado!F63 -> 0 | M69: =+ROUND($H69*L69,2) -> 0 | N69: =+IF($L69-$J69>=0,$L69-$J69,0) -> 0 | O69: =+ROUND($H69*N69,2) -> 0 | Q69: =+ROUND($H69*P69,2) -> 0 | R69: =+IF($L69-$J69<=0,-$L69+$J69,0) -> 1076 | S69: =+ROUND($H69*R69,2) -> 4637.56 | U69: =+ROUND($H69*T69,2) -> 0 | Y69: 0
B70: =+B69+0.01 -> 7.02 | C70: =+C69+1 -> #REF! | D70: Perno Angular con Ojal Guardacabo de A°G°, 16 mm Ø x 254 mm, provisto de Tuerca y Contratuerca | G70: u | H70: 13.17 | J70: 106 | K70: =+ROUND($H70*J70,2) -> 1396.02 | L70: =+[193]Metrado!F64 -> 117 | M70: =+ROUND($H70*L70,2) -> 1540.89 | N70: =+IF($L70-$J70>=0,$L70-$J70,0) -> 11 | O70: =+ROUND($H70*N70,2) -> 144.87 | Q70: =+ROUND($H70*P70,2) -> 0 | R70: =+IF($L70-$J70<=0,-$L70+$J70,0) -> 0 | S70: =+ROUND($H70*R70,2) -> 0 | U70: =+ROUND($H70*T70,2) -> 0 | Y70: 0
B71: =+B70+0.01 -> 7.03 | C71: =+C70+1 -> #REF! | D71: Perno Angular con Ojal Guardacabo de A°G°, 16 mm Ø x 305 mm, provisto de Tuerca y Contratuerca | G71: u | H71: 14.23 | J71: 3 | K71: =+ROUND($H71*J71,2) -> 42.69 | L71: =+[193]Metrado!F65 -> 3 | M71: =+ROUND($H71*L71,2) -> 42.69 | N71: =+IF($L71-$J71>=0,$L71-$J71,0) -> 0 | O71: =+ROUND($H71*N71,2) -> 0 | Q71: =+ROUND($H71*P71,2) -> 0 | R71: =+IF($L71-$J71<=0,-$L71+$J71,0) -> 0 | S71: =+ROUND($H71*R71,2) -> 0 | U71: =+ROUND($H71*T71,2) -> 0 | Y71: 0
B72: =+B71+0.01 -> 7.04 | C72: =+C71+1 -> #REF! | D72: Varilla de Anclaje de A°G° de 16 mm Ø x 2,40 m, provisto de Ojal Guardacabo en un extremo; Tuerca y Contratuerca en el otro | G72: u | H72: 46.85 | J72: 109 | K72: =+ROUND($H72*J72,2) -> 5106.65 | L72: =+[193]Metrado!F66 -> 120 | M72: =+ROUND($H72*L72,2) -> 5622 | N72: =+IF($L72-$J72>=0,$L72-$J72,0) -> 11 | O72: =+ROUND($H72*N72,2) -> 515.35 | Q72: =+ROUND($H72*P72,2) -> 0 | R72: =+IF($L72-$J72<=0,-$L72+$J72,0) -> 0 | S72: =+ROUND($H72*R72,2) -> 0 | U72: =+ROUND($H72*T72,2) -> 0 | Y72: 0
B73: =+B72+0.01 -> 7.05 | C73: =+C72+1 -> #REF! | D73: Arandela de Anclaje de A°G°, 102 x 102 x 6,35 mm, Agujero de 18 mmø | G73: u | H73: 5.46 | J73: 109 | K73: =+ROUND($H73*J73,2) -> 595.14 | L73: =+[193]Metrado!F67 -> 120 | M73: =+ROUND($H73*L73,2) -> 655.2 | N73: =+IF($L73-$J73>=0,$L73-$J73,0) -> 11 | O73: =+ROUND($H73*N73,2) -> 60.06 | Q73: =+ROUND($H73*P73,2) -> 0 | R73: =+IF($L73-$J73<=0,-$L73+$J73,0) -> 0 | S73: =+ROUND($H73*R73,2) -> 0 | U73: =+ROUND($H73*T73,2) -> 0 | Y73: 0
B74: =+B73+0.01 -> 7.06 | C74: =+C73+1 -> #REF! | D74: Mordaza Preformada de A°G° para Cable de 10 mm Ø | G74: u | H74: 11.69 | J74: 218 | K74: =+ROUND($H74*J74,2) -> 2548.42 | L74: =+[193]Metrado!F68 -> 240 | M74: =+ROUND($H74*L74,2) -> 2805.6 | N74: =+IF($L74-$J74>=0,$L74-$J74,0) -> 22 | O74: =+ROUND($H74*N74,2) -> 257.18 | Q74: =+ROUND($H74*P74,2) -> 0 | R74: =+IF($L74-$J74<=0,-$L74+$J74,0) -> 0 | S74: =+ROUND($H74*R74,2) -> 0 | U74: =+ROUND($H74*T74,2) -> 0 | Y74: 0
B75: =+B74+0.01 -> 7.07 | C75: =+C74+1 -> #REF! | D75: Arandela Cuadrada Curva de A° G°, 57 x 57 x 5 mm, Agujero de 18 mm Ø | G75: u | H75: 1.67 | J75: 218 | K75: =+ROUND($H75*J75,2) -> 364.06 | L75: =+[193]Metrado!F69 -> 240 | M75: =+ROUND($H75*L75,2) -> 400.8 | N75: =+IF($L75-$J75>=0,$L75-$J75,0) -> 22 | O75: =+ROUND($H75*N75,2) -> 36.74 | Q75: =+ROUND($H75*P75,2) -> 0 | R75: =+IF($L75-$J75<=0,-$L75+$J75,0) -> 0 | S75: =+ROUND($H75*R75,2) -> 0 | U75: =+ROUND($H75*T75,2) -> 0 | Y75: 0
B76: =+B75+0.01 -> 7.08 | C76: =+C75+1 -> #REF! | D76: Soporte de Contrapunta de 51 mm ø x 1000 mm de longitud, con Abrazadera partida en un extremo y Grapa de Ajuste para Cable en el otro | G76: u | H76: 105.33 | J76: 14 | K76: =+ROUND($H76*J76,2) -> 1474.62 | L76: =+[193]Metrado!F70 -> 27 | M76: =+ROUND($H76*L76,2) -> 2843.91 | N76: =+IF($L76-$J76>=0,$L76-$J76,0) -> 13 | O76: =+ROUND($H76*N76,2) -> 1369.29 | Q76: =+ROUND($H76*P76,2) -> 0 | R76: =+IF($L76-$J76<=0,-$L76+$J76,0) -> 0 | S76: =+ROUND($H76*R76,2) -> 0 | U76: =+ROUND($H76*T76,2) -> 0 | Y76: 0
B77: =+B76+0.01 -> 7.09 | C77: =+C76+1 -> #REF! | D77: Alambre de Acero N° 12 para Entorchado | G77: m | H77: 0.69 | J77: 327 | K77: =+ROUND($H77*J77,2) -> 225.63 | L77: =+[193]Metrado!F71 -> 360 | M77: =+ROUND($H77*L77,2) -> 248.4 | N77: =+IF($L77-$J77>=0,$L77-$J77,0) -> 33 | O77: =+ROUND($H77*N77,2) -> 22.77 | Q77: =+ROUND($H77*P77,2) -> 0 | R77: =+IF($L77-$J77<=0,-$L77+$J77,0) -> 0 | S77: =+ROUND($H77*R77,2) -> 0 | U77: =+ROUND($H77*T77,2) -> 0 | Y77: 0
B78: =+B77+0.01 -> 7.1 | C78: =+C77+1 -> #REF! | D78: Bloque de concreto de 0,40 x 0,40 x 0,15 m | G78: u | H78: 40.94 | J78: 109 | K78: =+ROUND($H78*J78,2) -> 4462.46 | L78: =+[193]Metrado!F72 -> 120 | M78: =+ROUND($H78*L78,2) -> 4912.8 | N78: =+IF($L78-$J78>=0,$L78-$J78,0) -> 11 | O78: =+ROUND($H78*N78,2) -> 450.34 | Q78: =+ROUND($H78*P78,2) -> 0 | R78: =+IF($L78-$J78<=0,-$L78+$J78,0) -> 0 | S78: =+ROUND($H78*R78,2) -> 0 | U78: =+ROUND($H78*T78,2) -> 0 | Y78: 0
B79: =+B78+0.01 -> 7.11 | C79: =+C78+1 -> #REF! | D79: Conector Bimetálico para Al 25 mm2 / Cu 4-10 mm2, para Neutro Desnudo, tipo Cuña | G79: u | H79: 5.21 | J79: 109 | K79: =+ROUND($H79*J79,2) -> 567.89 | L79: =+[193]Metrado!F73 -> 120 | M79: =+ROUND($H79*L79,2) -> 625.2 | N79: =+IF($L79-$J79>=0,$L79-$J79,0) -> 11 | O79: =+ROUND($H79*N79,2) -> 57.31 | Q79: =+ROUND($H79*P79,2) -> 0 | R79: =+IF($L79-$J79<=0,-$L79+$J79,0) -> 0 | S79: =+ROUND($H79*R79,2) -> 0 | U79: =+ROUND($H79*T79,2) -> 0 | Y79: 0
B80: =+B79+0.01 -> 7.12 | C80: =+C79+1 -> #REF! | D80: Conector Doble Via Bimetálico para Cable de Acero de 10 mm ø y para Cable de Acero con Recubrimiento Metalúrgico de Cobre de 4 AWG (21,15 mm2) | G80: u | H80: 8.52 | J80: 109 | K80: =+ROUND($H80*J80,2) -> 928.68 | L80: =+[193]Metrado!F74 -> 120 | M80: =+ROUND($H80*L80,2) -> 1022.4 | N80: =+IF($L80-$J80>=0,$L80-$J80,0) -> 11 | O80: =+ROUND($H80*N80,2) -> 93.72 | Q80: =+ROUND($H80*P80,2) -> 0 | R80: =+IF($L80-$J80<=0,-$L80+$J80,0) -> 0 | S80: =+ROUND($H80*R80,2) -> 0 | U80: =+ROUND($H80*T80,2) -> 0 | Y80: 0
B81: =+B80+0.01 -> 7.13 | C81: =+C80+1 -> #REF! | D81: Cable de acero grado Alta Resistencia (HS), de 10 mm ø, 7 hilos | G81: m | I81: =+H69 -> 4.31 | K81: =+ROUND($H81*J81,2) -> 0 | L81: =+[193]Metrado!F75 -> 1173 | M81: =+ROUND($I81*L81,2) -> 5055.63 | O81: =+ROUND($H81*N81,2) -> 0 | P81: =+L81 -> 1173 | Q81: =+ROUND($I81*P81,2) -> 5055.63 | S81: =+ROUND($H81*R81,2) -> 0 | U81: =+ROUND($H81*T81,2) -> 0 | Y81: 0
B82: =+B81+0.01 -> 7.14 | C82: =+C81+1 -> #REF! | D82: Guardacabo de AºGº para cable de 10mm ø | G82: u | K82: =+ROUND($H82*J82,2) -> 0 | L82: 0 | M82: =+ROUND($I82*L82,2) -> 0 | O82: =+ROUND($H82*N82,2) -> 0 | P82: =+L82 -> 0 | Q82: =+ROUND($I82*P82,2) -> 0 | S82: =+ROUND($H82*R82,2) -> 0 | U82: =+ROUND($H82*T82,2) -> 0 | Y82: 0
C83: =+C82+1 -> #REF! | F83: =+"SUB-TOTAL "&B68&": " -> SUB-TOTAL 7: | K83: =+SUM(K69:K82) -> 22349.82 | M83: =+SUM(M69:M82) -> 25775.52 | O83: =+SUM(O69:O82) -> 3007.63 | Q83: =+SUM(Q69:Q82) -> 5055.63 | S83: =+SUM(S69:S82) -> 4637.56 | U83: =+SUM(U69:U82) -> 0 | W83: =+K83-M83+O83+Q83-S83 -> 0 | Y83: 0
B84: =+B68+1 -> 8 | C84: =+C83+1 -> #REF! | D84: ACCESORIOS DE FERRETERIA PARA ESTRUCTURAS | Y84: 0
B85: =+B84+0.01 -> 8.01 | C85: =+C84+1 -> #REF! | D85: Perno con Gancho de 16 mm Ø, provisto de Arandela, Tuerca y Contratuerca, longitud de 254 mm | G85: u | H85: 12.36 | J85: 141 | K85: =+ROUND($H85*J85,2) -> 1742.76 | L85: =+[193]Metrado!F79 -> 160 | M85: =+ROUND($H85*L85,2) -> 1977.6 | N85: =+IF($L85-$J85>=0,$L85-$J85,0) -> 19 | O85: =+ROUND($H85*N85,2) -> 234.84 | Q85: =+ROUND($H85*P85,2) -> 0 | R85: =+IF($L85-$J85<=0,-$L85+$J85,0) -> 0 | S85: =+ROUND($H85*R85,2) -> 0 | U85: =+ROUND($H85*T85,2) -> 0 | Y85: 0
B86: =+B85+0.01 -> 8.02 | C86: =+C85+1 -> #REF! | D86: Perno con Gancho de 16 mm Ø, provisto de Arandela, Tuerca y Contratuerca, longitud de 305 mm | G86: u | H86: 14.34 | J86: 22 | K86: =+ROUND($H86*J86,2) -> 315.48 | L86: =+[193]Metrado!F80 -> 22 | M86: =+ROUND($H86*L86,2) -> 315.48 | N86: =+IF($L86-$J86>=0,$L86-$J86,0) -> 0 | O86: =+ROUND($H86*N86,2) -> 0 | Q86: =+ROUND($H86*P86,2) -> 0 | R86: =+IF($L86-$J86<=0,-$L86+$J86,0) -> 0 | S86: =+ROUND($H86*R86,2) -> 0 | U86: =+ROUND($H86*T86,2) -> 0 | Y86: 0
B87: =+B86+0.01 -> 8.03 | C87: =+C86+1 -> #REF! | D87: Perno de A°G° de 13 mm Ø x 254 mm, provisto de Tuerca y Contratuerca | G87: u | H87: 5.57 | J87: 248 | K87: =+ROUND($H87*J87,2) -> 1381.36 | L87: =+[193]Metrado!F81 -> 126 | M87: =+ROUND($H87*L87,2) -> 701.82 | N87: =+IF($L87-$J87>=0,$L87-$J87,0) -> 0 | O87: =+ROUND($H87*N87,2) -> 0 | Q87: =+ROUND($H87*P87,2) -> 0 | R87: =+IF($L87-$J87<=0,-$L87+$J87,0) -> 122 | S87: =+ROUND($H87*R87,2) -> 679.54 | U87: =+ROUND($H87*T87,2) -> 0 | Y87: 0
B88: =+B87+0.01 -> 8.04 | C88: =+C87+1 -> #REF! | D88: Perno de A°G° de 13 mm Ø x 305 mm, provisto de Tuerca y Contratuerca | G88: u | H88: 6.25 | J88: 50 | K88: =+ROUND($H88*J88,2) -> 312.5 | L88: =+[193]Metrado!F82 -> 16 | M88: =+ROUND($H88*L88,2) -> 100 | N88: =+IF($L88-$J88>=0,$L88-$J88,0) -> 0 | O88: =+ROUND($H88*N88,2) -> 0 | Q88: =+ROUND($H88*P88,2) -> 0 | R88: =+IF($L88-$J88<=0,-$L88+$J88,0) -> 34 | S88: =+ROUND($H88*R88,2) -> 212.5 | U88: =+ROUND($H88*T88,2) -> 0 | Y88: 0
B89: =+B88+0.01 -> 8.05 | C89: =+C88+1 -> #REF! | D89: Perno Ojo de A°G° de 16 mm Ø x 254 mm, provisto de Tuerca y Contratuerca | G89: u | H89: 13.11 | J89: 127 | K89: =+ROUND($H89*J89,2) -> 1664.97 | L89: =+[193]Metrado!F83 -> 158 | M89: =+ROUND($H89*L89,2) -> 2071.38 | N89: =+IF($L89-$J89>=0,$L89-$J89,0) -> 31 | O89: =+ROUND($H89*N89,2) -> 406.41 | Q89: =+ROUND($H89*P89,2) -> 0 | R89: =+IF($L89-$J89<=0,-$L89+$J89,0) -> 0 | S89: =+ROUND($H89*R89,2) -> 0 | U89: =+ROUND($H89*T89,2) -> 0 | Y89: 0
B90: =+B89+0.01 -> 8.06 | C90: =+C89+1 -> #REF! | D90: Perno Ojo de A°G° de 16 mm Ø x 305 mm, provisto de Tuerca y Contratuerca | G90: u | H90: 14.35 | J90: 33 | K90: =+ROUND($H90*J90,2) -> 473.55 | L90: =+[193]Metrado!F84 -> 38 | M90: =+ROUND($H90*L90,2) -> 545.3 | N90: =+IF($L90-$J90>=0,$L90-$J90,0) -> 5 | O90: =+ROUND($H90*N90,2) -> 71.75 | Q90: =+ROUND($H90*P90,2) -> 0 | R90: =+IF($L90-$J90<=0,-$L90+$J90,0) -> 0 | S90: =+ROUND($H90*R90,2) -> 0 | U90: =+ROUND($H90*T90,2) -> 0 | Y90: 0
B91: =+B90+0.01 -> 8.07 | C91: =+C90+1 -> #REF! | D91: Tuerca-Ojo para Perno de 16 mm Ø | G91: u | H91: 11.17 | J91: 58 | K91: =+ROUND($H91*J91,2) -> 647.86 | L91: =+[193]Metrado!F85 -> 100 | M91: =+ROUND($H91*L91,2) -> 1117 | N91: =+IF($L91-$J91>=0,$L91-$J91,0) -> 42 | O91: =+ROUND($H91*N91,2) -> 469.14 | Q91: =+ROUND($H91*P91,2) -> 0 | R91: =+IF($L91-$J91<=0,-$L91+$J91,0) -> 0 | S91: =+ROUND($H91*R91,2) -> 0 | U91: =+ROUND($H91*T91,2) -> 0 | Y91: 0
B92: =+B91+0.01 -> 8.08 | C92: =+C91+1 -> #REF! | D92: Fleje de acero inoxidable de 19 mm provisto de hebilla | G92: m | H92: 6.02 | J92: 2 | K92: =+ROUND($H92*J92,2) -> 12.04 | L92: =+[193]Metrado!F86 -> 9 | M92: =+ROUND($H92*L92,2) -> 54.18 | N92: =+IF($L92-$J92>=0,$L92-$J92,0) -> 7 | O92: =+ROUND($H92*N92,2) -> 42.14 | Q92: =+ROUND($H92*P92,2) -> 0 | R92: =+IF($L92-$J92<=0,-$L92+$J92,0) -> 0 | S92: =+ROUND($H92*R92,2) -> 0 | U92: =+ROUND($H92*T92,2) -> 0 | Y92: 0
B93: =+B92+0.01 -> 8.09 | C93: =+C92+1 -> #REF! | D93: Arandela Cuadrada Curva de A° G°, 57 x 57 x 5 mm, Agujero de 14 mm Ø | G93: u | H93: 1.63 | J93: 296 | K93: =+ROUND($H93*J93,2) -> 482.48 | L93: =+[193]Metrado!F87 -> 80 | M93: =+ROUND($H93*L93,2) -> 130.4 | N93: =+IF($L93-$J93>=0,$L93-$J93,0) -> 0 | O93: =+ROUND($H93*N93,2) -> 0 | Q93: =+ROUND($H93*P93,2) -> 0 | R93: =+IF($L93-$J93<=0,-$L93+$J93,0) -> 216 | S93: =+ROUND($H93*R93,2) -> 352.08 | T93: =+N94 -> 97 | U93: =+ROUND($H93*T93,2) -> 158.11 | V93: Se vincula con el mayor metrado de la partida 8.10 | Y93: 0
B94: =+B93+0.01 -> 8.1 | C94: =+C93+1 -> #REF! | D94: Arandela Cuadrada Curva de A° G°, 57 x 57 x 5 mm, Agujero de 18 mm Ø | G94: u | H94: 1.67 | J94: 483 | K94: =+ROUND($H94*J94,2) -> 806.61 | L94: =+[193]Metrado!F88 -> 580 | M94: =+ROUND($H94*L94,2) -> 968.6 | N94: =+IF($L94-$J94>=0,$L94-$J94,0) -> 97 | O94: =+ROUND($H94*N94,2) -> 161.99 | Q94: =+ROUND($H94*P94,2) -> 0 | R94: =+IF($L94-$J94<=0,-$L94+$J94,0) -> 0 | S94: =+ROUND($H94*R94,2) -> 0 | U94: =+ROUND($H94*T94,2) -> 0 | Y94: 0
B95: =+B94+0.01 -> 8.11 | C95: =+C94+1 -> #REF! | D95: Caja de derivacion para acometidas, sistema 440-22O V (10 borneras en cada barra de cobre) | G95: u | H95: 133.02 | J95: 2 | K95: =+ROUND($H95*J95,2) -> 266.04 | L95: =+[193]Metrado!F89 -> 9 | M95: =+ROUND($H95*L95,2) -> 1197.18 | N95: =+IF($L95-$J95>=0,$L95-$J95,0) -> 7 | O95: =+ROUND($H95*N95,2) -> 931.14 | Q95: =+ROUND($H95*P95,2) -> 0 | R95: =+IF($L95-$J95<=0,-$L95+$J95,0) -> 0 | S95: =+ROUND($H95*R95,2) -> 0 | U95: =+ROUND($H95*T95,2) -> 0 | Y95: 0
B96: =+B95+0.01 -> 8.12 | C96: =+C95+1 -> #REF! | D96: Portalinea unipolar de AºGº, provisto de PIN de 10 mm Ø | G96: u | H96: 6.63 | J96: 300 | K96: =+ROUND($H96*J96,2) -> 1989 | L96: =+[193]Metrado!F90 -> 204 | M96: =+ROUND($H96*L96,2) -> 1352.52 | N96: =+IF($L96-$J96>=0,$L96-$J96,0) -> 0 | O96: =+ROUND($H96*N96,2) -> 0 | Q96: =+ROUND($H96*P96,2) -> 0 | R96: =+IF($L96-$J96<=0,-$L96+$J96,0) -> 96 | S96: =+ROUND($H96*R96,2) -> 636.48 | U96: =+ROUND($H96*T96,2) -> 0 | Y96: 0
B97: =+B96+0.01 -> 8.13 | C97: =+C96+1 -> #REF! | D97: Placa de Identificación y/o codificación de Estructura y accesorios de fijación | G97: u | H97: 16.84 | J97: 9 | K97: =+ROUND($H97*J97,2) -> 151.56 | L97: =+[193]Metrado!F91 -> 0 | M97: =+ROUND($H97*L97,2) -> 0 | N97: =+IF($L97-$J97>=0,$L97-$J97,0) -> 0 | O97: =+ROUND($H97*N97,2) -> 0 | Q97: =+ROUND($H97*P97,2) -> 0 | R97: =+IF($L97-$J97<=0,-$L97+$J97,0) -> 9 | S97: =+ROUND($H97*R97,2) -> 151.56 | T97: =+N98 -> 7 | U97: =+ROUND($H97*T97,2) -> 117.88 | V97: Se vincula con el mayor metrado de la partida 8.14 | Y97: 0
B98: =+B97+0.01 -> 8.14 | C98: =+C97+1 -> #REF! | D98: Plantillas para Identificación y/o codificación de Postes (Peligro, Identificación y/o codificación y Fases) | G98: Jgo. | H98: 23.08 | J98: 29 | K98: =+ROUND($H98*J98,2) -> 669.32 | L98: =+[193]Metrado!F92 -> 36 | M98: =+ROUND($H98*L98,2) -> 830.88 | N98: =+IF($L98-$J98>=0,$L98-$J98,0) -> 7 | O98: =+ROUND($H98*N98,2) -> 161.56 | Q98: =+ROUND($H98*P98,2) -> 0 | R98: =+IF($L98-$J98<=0,-$L98+$J98,0) -> 0 | S98: =+ROUND($H98*R98,2) -> 0 | U98: =+ROUND($H98*T98,2) -> 0 | Y98: 0
B99: =+B98+0.01 -> 8.15 | C99: =+C98+1 -> #REF! | D99: EXTENSOR A°G° 51mmØ, e=6mm x 1000mm DE LONGITUD, PLANCHA A°G° 254mmx305mmx6mm, CON 01 PERNO GANCHO DE SUSPENSION DE A°G° DE 16mmØX178 mm DE LONGITUD + 02 ROSCAS DE 25.4mm x16mmØ VER DETALLE | G99: Jgo. | I99: 262.98 | K99: =+ROUND($H99*J99,2) -> 0 | L99: =+[193]Metrado!F93 -> 3 | M99: =+ROUND($I99*L99,2) -> 788.94 | O99: =+ROUND($H99*N99,2) -> 0 | P99: =+L99 -> 3 | Q99: =+ROUND($I99*P99,2) -> 788.94 | S99: =+ROUND($H99*R99,2) -> 0 | U99: =+ROUND($H99*T99,2) -> 0 | Y99: 0
B100: =+B99+0.01 -> 8.16 | C100: =+C99+1 -> #REF! | D100: Perno de A°G° de 16 mm Ø x 203 mm, provisto de Tuerca y Contratuerca | G100: u | I100: =+H87*1.2 -> 6.684 | K100: =+ROUND($H100*J100,2) -> 0 | L100: =+[193]Metrado!F94 -> 6 | M100: =+ROUND($I100*L100,2) -> 40.1 | O100: =+ROUND($H100*N100,2) -> 0 | P100: =+L100 -> 6 | Q100: =+ROUND($I100*P100,2) -> 40.1 | S100: =+ROUND($H100*R100,2) -> 0 | U100: =+ROUND($H100*T100,2) -> 0 | Y100: 0
C101: =+C100+1 -> #REF! | F101: =+"SUB-TOTAL "&B84&": " -> SUB-TOTAL 8: | K101: =+SUM(K85:K100) -> 10915.53 | M101: =+SUM(M85:M100) -> 12191.38 | O101: =+SUM(O85:O100) -> 2478.97 | Q101: =+SUM(Q85:Q100) -> 829.04 | S101: =+SUM(S85:S100) -> 2032.16 | U101: =+SUM(U85:U100) -> 275.99 | W101: =+K101-M101+O101+Q101-S101 -> -2.2737368e-12 | Y101: 0
B102: =1+B84 -> 9 | C102: =+C101+1 -> #REF! | D102: PUESTA A TIERRA | Y102: 0
B103: =+B102+0.01 -> 9.01 | C103: =+C102+1 -> #REF! | D103: Electrodo de Acero Recubierto de Cobre de 16 mm Ø x 2,40 m | G103: u | H103: 66.7 | J103: 72 | K103: =+ROUND($H103*J103,2) -> 4802.4 | L103: =+[193]Metrado!F97 -> 76 | M103: =+ROUND($H103*L103,2) -> 5069.2 | N103: =+IF($L103-$J103>=0,$L103-$J103,0) -> 4 | O103: =+ROUND($H103*N103,2) -> 266.8 | Q103: =+ROUND($H103*P103,2) -> 0 | R103: =+IF($L103-$J103<=0,-$L103+$J103,0) -> 0 | S103: =+ROUND($H103*R103,2) -> 0 | U103: =+ROUND($H103*T103,2) -> 0 | Y103: 0
B104: =+B103+0.01 -> 9.02 | C104: =+C103+1 -> #REF! | D104: Conector bimetálico para Al 25 mm2 y Cobre de 25 mm2, tipo cuña | G104: u | H104: 7.89 | J104: 72 | K104: =+ROUND($H104*J104,2) -> 568.08 | L104: =+[193]Metrado!F98 -> 22 | M104: =+ROUND($H104*L104,2) -> 173.58 | N104: =+IF($L104-$J104>=0,$L104-$J104,0) -> 0 | O104: =+ROUND($H104*N104,2) -> 0 | Q104: =+ROUND($H104*P104,2) -> 0 | R104: =+IF($L104-$J104<=0,-$L104+$J104,0) -> 50 | S104: =+ROUND($H104*R104,2) -> 394.5 | U104: =+ROUND($H104*T104,2) -> 0 | Y104: 0
B105: =+B104+0.01 -> 9.03 | C105: =+C104+1 -> #REF! | D105: Conector de bronce para electrodo de 16 mm ø y Cable de Acero con Recubrimiento Metalúrgico de Cobre de 4 AWG (21,15 mm2) | G105: u | H105: 6.94 | J105: 72 | K105: =+ROUND($H105*J105,2) -> 499.68 | L105: =+[193]Metrado!F99 -> 76 | M105: =+ROUND($H105*L105,2) -> 527.44 | N105: =+IF($L105-$J105>=0,$L105-$J105,0) -> 4 | O105: =+ROUND($H105*N105,2) -> 27.76 | Q105: =+ROUND($H105*P105,2) -> 0 | R105: =+IF($L105-$J105<=0,-$L105+$J105,0) -> 0 | S105: =+ROUND($H105*R105,2) -> 0 | U105: =+ROUND($H105*T105,2) -> 0 | Y105: 0
B106: =+B105+0.01 -> 9.04 | C106: =+C105+1 -> #REF! | D106: Grapa en "U" para fijar conductor de PAT a Poste de Madera | G106: u | H106: 0.47 | J106: 60 | K106: =+ROUND($H106*J106,2) -> 28.2 | L106: =+[193]Metrado!F100 -> 0 | M106: =+ROUND($H106*L106,2) -> 0 | N106: =+IF($L106-$J106>=0,$L106-$J106,0) -> 0 | O106: =+ROUND($H106*N106,2) -> 0 | Q106: =+ROUND($H106*P106,2) -> 0 | R106: =+IF($L106-$J106<=0,-$L106+$J106,0) -> 60 | S106: =+ROUND($H106*R106,2) -> 28.2 | U106: =+ROUND($H106*T106,2) -> 0 | Y106: 0
B107: =+B106+0.01 -> 9.05 | C107: =+C106+1 -> #REF! | D107: Listón de madera tratada 50 x 19 mm sección, 2,7 m longitud (incluye clavos de fijación) | G107: u | H107: 27.35 | J107: 3 | K107: =+ROUND($H107*J107,2) -> 82.05 | L107: =+[193]Metrado!F101 -> 0 | M107: =+ROUND($H107*L107,2) -> 0 | N107: =+IF($L107-$J107>=0,$L107-$J107,0) -> 0 | O107: =+ROUND($H107*N107,2) -> 0 | Q107: =+ROUND($H107*P107,2) -> 0 | R107: =+IF($L107-$J107<=0,-$L107+$J107,0) -> 3 | S107: =+ROUND($H107*R107,2) -> 82.05 | U107: =+ROUND($H107*T107,2) -> 0 | Y107: 0
...

Sheet FP RS
B3: FÓRMULA POLINÓMICA
C6: PROYECTO :
C7: AMPLIACIÓN DEL SERVICIO DE ENERGÍA ELÉCTRICA EN LA PROVINCIA DEL SANTA Y EN EL DISTRITO DE PAMPAROMAS – DEPARTAMENTO DE ANCASH”
C9: REDES SECUNDARIAS, INCLUYE CONEXIONES DOMICILIARIAS
C10: PRESUPUESTO BASE S/ | D10: =+'RES-RS'!H18 -> 893818.43 | M10: =D10=SUM(G13:G25) -> TRUE
B12: Nº | C12: ELEMENTO REPRESENTATIVO | D12: INDICE UNIFICADO | E12: SIMBOLO | F12: SIMBOLO MONOMIO | G12: MONTO | H12: INCIDENCIA | I12: % PARCIAL | J12: COEFICIENTE
B13: 1 | C13: POSTES DE CONCRETO | D13: 062 | E13: PC | F13: PC | G13: =+'Mtdo-Ppto RS'!M20+'Mtdo-Ppto RS'!M27 -> 119149.67 | H13: =ROUND(G13/$D$10,3) -> 0.133 | I13: =ROUND(G13/SUM($G$13:$G$14),4) -> 1 | J13: =+ROUND(SUM(H13:H14),3) -> 0.133
C14: POSTE DE MADERA IMPORTADA | D14: 042 | E14: PM | G14: =+'Mtdo-Ppto RS'!M23 -> 0 | H14: =ROUND(G14/$D$10,3) -> 0 | I14: =ROUND(G14/SUM($G$13:$G$14),4) -> 0
B15: 2 | C15: CABLES Y CONDUCTORES DE ALUMINIO | D15: 030 | E15: DI1 | F15: DI1 | G15: =+'Mtdo-Ppto RS'!M37 -> 98903.33 | H15: =ROUND(G15/$D$10,3) -> 0.111 | I15: =ROUND(G15/SUM($G$15:$G$16),4) -> 0.6495 | J15: =+ROUND(SUM(H15:H16),3) -> 0.171
C16: CONEXIONES DOMICILIARIAS | D16: 030 | E16: DI2 | G16: =+'Mtdo-Ppto RS'!M126 -> 53380.89 | H16: =ROUND(G16/$D$10,3) -> 0.06 | I16: =ROUND(G16/SUM($G$15:$G$16),4) -> 0.3505
B17: 3 | C17: LUMINARIAS, LAMPARAS Y ACCESORIOS | D17: 011 | E17: AE1 | F17: CU | G17: =+'Mtdo-Ppto RS'!M67 -> 37625.69 | H17: =ROUND(G17/$D$10,3) -> 0.042 | I17: =ROUND(G17/SUM($G$17:$G$22),4) -> 0.2526 | J17: =+ROUND(SUM(H17:H22),3) -> 0.167
C18: ACCESORIOS PARA CABLES AUTOPORTANTES | D18: 002 | E18: AE2 | G18: =+'Mtdo-Ppto RS'!M51 -> 11725.04 | H18: =ROUND(G18/$D$10,3) -> 0.013 | I18: =ROUND(G18/SUM($G$17:$G$22),4) -> 0.0787
C19: RETENIDAS Y ANCLAJES | D19: 002 | E19: FE1 | G19: =+'Mtdo-Ppto RS'!M83 -> 25775.52 | H19: =ROUND(G19/$D$10,3) -> 0.029 | I19: =ROUND(G19/SUM($G$17:$G$22),4) -> 0.173
C20: ACCESORIOS DE FERRETERIA PARA ESTRUCTURAS | D20: 002 | E20: FE2 | G20: =+'Mtdo-Ppto RS'!M101 -> 12191.38 | H20: =ROUND(G20/$D$10,3) -> 0.014 | I20: =ROUND(G20/SUM($G$17:$G$22),4) -> 0.0818
C21: CABLES Y CONDUCTORES DE COBRE | D21: 006 | E21: CU | G21: =+'Mtdo-Ppto RS'!M57 -> 48623.48 | H21: =ROUND(G21/$D$10,3) -> 0.054 | I21: =ROUND(G21/SUM($G$17:$G$22),4) -> 0.3264
C22: PUESTA A TIERRA | D22: 006 | E22: PT | G22: =+'Mtdo-Ppto RS'!M111 -> 13035.61 | H22: =ROUND(G22/$D$10,3) -> 0.015 | I22: =ROUND(G22/SUM($G$17:$G$22),4) -> 0.0875
B23: 4 | C23: MONTAJE ELECTROMECANICO | D23: 047 | E23: J | F23: J | G23: =+'Mtdo-Ppto RS'!M240 -> 323016.92 | H23: =ROUND(G23/$D$10,3) -> 0.361 | I23: =ROUND(G23/($G$23+$G$24),4) -> 0.8736 | J23: =+ROUND(SUM(H23:H24),3) -> 0.413
C24: TRANSPORTE | D24: 032 | E24: FT | G24: =+'Mtdo-Ppto RS'!M352 -> 46723.13 | H24: =ROUND(G24/$D$10,3) -> 0.052 | I24: =ROUND(G24/($G$23+$G$24),4) -> 0.1264
B25: 5 | C25: GASTOS GENERALES Y UTILIDADES | D25: 039 | E25: GG | F25: GG | G25: =+'RES-RS'!H16+'RES-RS'!H17 -> 103667.77 | H25: =ROUND(G25/$D$10,3) -> 0.116 | I25: =+G25/(G25) -> 1 | J25: =+ROUND(SUM(H25),3) -> 0.116
H26: =SUM(H15:H25) -> 0.867
B27: K= | C27: =J13&" PCr/PCo + "&J15&" DI1r/DI1o + "&J17&" CUr/CUo+ "&J23&" Jr/Jo + "&J25&" GGr/GGo" -> 0.133 PCr/PCo + 0.171 DI1r/DI1o + 0.167 CUr/CUo+ 0.413 Jr/Jo + 0.116 GGr/GGo
B30: NOTAS:
B32: 1.- | C32: En la fórmula los sub-indices "o" de cada símbolo corresponden al indice de precios según (CREPCO) a la
C33: fecha de Elaboración del Presupuesto (Presupuesto Base) y los sub-indices "r" al indice de precios al
C34: momento de reajuste o fecha de valorización
B35: 2.- | C35: En el caso de los monomios compuestos por varios indices se ha considerado para efecto de denominación
C36: el símbolo que tiene mayor porcentaje de incidencia
B37: 3.- | C37: En caso de cambios en el suministro se deberá actualizar la formula polinómica.
H43: =+IF(SUM(H13:H25)=1,"OK","X") -> OK | I43: =+IF(SUM(I13:I25)=5,"OK","X") -> OK | J43: =+IF(SUM(J13:J25)=1,"OK","X") -> OK

Sheet RES- SFV
B2: RESUMEN PRESUPUESTO DE OBRA
B4: AMPLIACIÓN DEL SERVICIO DE ENERGÍA ELÉCTRICA EN LA PROVINCIA DEL SANTA Y EN EL DISTRITO DE PAMPAROMAS – DEPARTAMENTO DE ANCASH
B6: UBICACIÓN | C6: : | D6: ANCASH
B7: SECCIÓN IV | C7: : | D7: SISTEMA FOTOVOLTAICO | H7: Fecha: 30-May-2022
H8: T.C. (S/ /US$): 3,683
B9: ITEM | C9: DESCRIPCION | G9: PRESUPUESTO CONTRATO | H9: PRESUPUESTO ESTUDIO DEFINIVO | I9: ADICIONALES | K9: DEDUCTIVOS
I10: MAYORES METRADOS | J10: PARTIDAS NUEVAS | K10: MENOR METRADO | L10: DEDUCTIVO VINCULANTE
B12: A | D12: SUMINISTRO DE MATERIALES | G12: =+'Mtdo-Ppto SFV'!K119 -> 224739.45 | H12: =+'Mtdo-Ppto SFV'!M119 -> 231968.39 | I12: =+'Mtdo-Ppto SFV'!O119 -> 141.51 | J12: =+'Mtdo-Ppto SFV'!Q119 -> 103598.37 | K12: =+'Mtdo-Ppto SFV'!S119 -> 96510.94 | L12: =+'Mtdo-Ppto SFV'!U119 -> 0
B13: B | D13: MONTAJE ELECTROMECANICO | G13: =+'Mtdo-Ppto SFV'!K166 -> 51498.29 | H13: =+'Mtdo-Ppto SFV'!M166 -> 49238.78 | I13: =+'Mtdo-Ppto SFV'!O166 -> 228.49 | J13: =+'Mtdo-Ppto SFV'!Q166 -> 0 | K13: =+'Mtdo-Ppto SFV'!S166 -> 2488.02 | L13: =+'Mtdo-Ppto SFV'!U166 -> 0
B14: C | D14: TRANSPORTE DE MATERIALES | G14: =+'Mtdo-Ppto SFV'!K270 -> 5558.67 | H14: =+'Mtdo-Ppto SFV'!M270 -> 6557.14 | I14: =+'Mtdo-Ppto SFV'!O270 -> 5.72 | J14: =+'Mtdo-Ppto SFV'!Q270 -> 2262.55 | K14: =+'Mtdo-Ppto SFV'!S270 -> 1269.8 | L14: =+'Mtdo-Ppto SFV'!U270 -> 0
B15: D | D15: TOTAL COSTO DIRECTO | G15: =+SUM(G12:G14) -> 281796.41 | H15: =+SUM(H12:H14) -> 287764.31 | I15: =+SUM(I12:I14) -> 375.72 | J15: =+SUM(J12:J14) -> 105860.92 | K15: =+SUM(K12:K14) -> 100268.76 | L15: =+SUM(L12:L14) -> 0
B16: E | D16: GASTOS GENERALES (10.12%) | G16: =ROUND(G15*10.12%,2) -> 28517.8 | H16: =ROUND(H15*10.12%,2) -> 29121.75 | I16: =ROUND(I15*10.12%,2) -> 38.02 | J16: =ROUND(J15*10.12%,2) -> 10713.13 | K16: =ROUND(K15*10.12%,2) -> 10147.2 | L16: =ROUND(L15*10.12%,2) -> 0
B17: F | D17: UTILIDADES (3%) | G17: =ROUND(G15*3%,2) -> 8453.89 | H17: =ROUND(H15*3%,2) -> 8632.93 | I17: =ROUND(I15*3%,2) -> 11.27 | J17: =ROUND(J15*3%,2) -> 3175.83 | K17: =ROUND(K15*3%,2) -> 3008.06 | L17: =ROUND(L15*3%,2) -> 0
B18: G | D18: COSTO TOTAL S/. (No incluye I.G.V.) | G18: =G17+G16+G15 -> 318768.1 | H18: =H17+H16+H15 -> 325518.99 | I18: =I17+I16+I15 -> 425.01 | J18: =J17+J16+J15 -> 119749.88 | K18: =K17+K16+K15 -> 113424.02 | L18: =L17+L16+L15 -> 0 | M18: =+H18-G18 -> 6750.89
D20: INCIDENCIA % | G20: =+G18/G18 -> 1 | H20: =+H18/$G$18 -> 1.0211781 | I20: =+I18/$G$18 -> 0.001333289 | J20: =+J18/$G$18 -> 0.37566457 | K20: =+K18/$G$18 -> 0.35581986 | L20: =+L18/$G$18 -> 0
H22: =+H18-I18+K18-J18 -> 318768.12 | K22: =+G12-H12+I12+J12-K12 -> 0
H23: =+G18-H22 -> -0.02 | K23: =+G13-H13+I13+J13-K13 -> -0.02
K24: =+G14-H14+I14+J14-K14 -> 0
K25: =+G15-H15+I15+J15-K15 -> -0.02

Sheet Mtdo-Ppto SFV
B6: PRESUPUESTO DE OBRA
B8: OBRA | E8: : | F8: AMPLIACIÓN DEL SERVICIO DE ENERGÍA ELÉCTRICA EN LA PROVINCIA DEL SANTA Y EN EL DISTRITO DE PAMPAROMAS – DEPARTAMENTO DE ANCASH
B9: DEPARTAMENTO | E9: : | F9: ANCASH
B10: SECCIÓN IV | E10: : | F10: SISTEMA FOTOVOLTAICO
B12: ITEM | C12: DESCRIPCIÓN DE PARTIDAS | G12: UNID. | H12: Precio de Contrato | I12: Precio Pactado | J12: CONTRACTUAL | L12: ESTUDIO DEFINITIVO | N12: ADICIONALES | R12: DEDUCTIVOS | V12: OBSERVACIÓN
J13: Metrado | K13: TOTAL | L13: Metrado | M13: TOTAL | N13: MAYORES METRADOS | P13: PARTIDAS NUEVAS | R13: MENORES METRADOS | T13: DEDUCTIVO VINCULANTE
N14: Metrado | O14: TOTAL | P14: Metrado | Q14: TOTAL | R14: Metrado | S14: TOTAL | T14: Metrado | U14: TOTAL
H15: Unitario | I15: Unitario | J15: Cantidad | K15: S/. | L15: Cantidad | M15: S/. | N15: Cantidad | O15: S/. | P15: Cantidad | Q15: S/. | R15: Cantidad | S15: S/. | T15: Cantidad | U15: S/.
B16: A | D16: SUMINISTRO DE MATERIALES
B17: 1 | C17: 3 | D17: UNIDAD DE GENERACIÓN
B18: =+B17+0.01 -> 1.01 | C18: =+C17+1 -> 4 | D18: Módulo Fotovoltaico 160 Wp, 12Vdc, silicio cristalino | G18: u | H18: 418.54 | J18: 39 | K18: =+ROUND($H18*J18,2) -> 16323.06 | L18: 37 | M18: =+ROUND($H18*L18,2) -> 15485.98 | N18: =+IF($L18-$J18>=0,$L18-$J18,0) -> 0 | O18: =+ROUND($H18*N18,2) -> 0 | Q18: =+ROUND($H18*P18,2) -> 0 | R18: =+IF($L18-$J18<=0,-$L18+$J18,0) -> 2 | S18: =+ROUND($H18*R18,2) -> 837.08 | U18: =+ROUND($H18*T18,2) -> 0
B19: =+B18+0.01 -> 1.02 | C19: =+C18+1 -> 5 | D19: Modulo Soporte de F°G° para SFV 160 Wp según lámina de detalle. Incluye accesorios | G19: u | H19: 773.57 | J19: 39 | K19: =+ROUND($H19*J19,2) -> 30169.23 | L19: 37 | M19: =+ROUND($H19*L19,2) -> 28622.09 | N19: =+IF($L19-$J19>=0,$L19-$J19,0) -> 0 | O19: =+ROUND($H19*N19,2) -> 0 | Q19: =+ROUND($H19*P19,2) -> 0 | R19: =+IF($L19-$J19<=0,-$L19+$J19,0) -> 2 | S19: =+ROUND($H19*R19,2) -> 1547.14 | U19: =+ROUND($H19*T19,2) -> 0
C20: =+C19+1 -> 6 | F20: =+"SUB-TOTAL "&B17&": " -> SUB-TOTAL 1: | K20: =+SUM(K18:K19) -> 46492.29 | M20: =+SUM(M18:M19) -> 44108.07 | O20: =+SUM(O18:O19) -> 0 | Q20: =+SUM(Q18:Q19) -> 0 | S20: =+SUM(S18:S19) -> 2384.22 | U20: =+SUM(U18:U19) -> 0 | W20: =+K20-M20+O20+Q20-S20 -> 0
B21: =1+B17 -> 2 | C21: =+C20+1 -> 7 | D21: UNIDAD DE CONTROL
B22: =+B21+0.01 -> 2.01 | C22: =+C17+1 -> 4 | D22: Tablero de protección adosable de PVC, con puerta, 12 Vdc, 0 2 polos, IP 54, con riel DIN y accesorios de fijación | G22: u | H22: 13.24 | J22: 39 | K22: =+ROUND($H22*J22,2) -> 516.36 | L22: 37 | M22: =+ROUND($H22*L22,2) -> 489.88 | N22: =+IF($L22-$J22>=0,$L22-$J22,0) -> 0 | O22: =+ROUND($H22*N22,2) -> 0 | Q22: =+ROUND($H22*P22,2) -> 0 | R22: =+IF($L22-$J22<=0,-$L22+$J22,0) -> 2 | S22: =+ROUND($H22*R22,2) -> 26.48 | U22: =+ROUND($H22*T22,2) -> 0
B23: =+B22+0.01 -> 2.02 | C23: =+C18+1 -> 5 | D23: Interruptor termomagnético 12 Vdc, 16 A | G23: u | H23: 51.32 | J23: 39 | K23: =+ROUND($H23*J23,2) -> 2001.48 | L23: 37 | M23: =+ROUND($H23*L23,2) -> 1898.84 | N23: =+IF($L23-$J23>=0,$L23-$J23,0) -> 0 | O23: =+ROUND($H23*N23,2) -> 0 | Q23: =+ROUND($H23*P23,2) -> 0 | R23: =+IF($L23-$J23<=0,-$L23+$J23,0) -> 2 | S23: =+ROUND($H23*R23,2) -> 102.64 | U23: =+ROUND($H23*T23,2) -> 0
B24: =+B23+0.01 -> 2.03 | C24: =+C18+1 -> 5 | D24: Conector rectangular hermético tipo CONDUIT, de A°G° para tubería flexible de 3/4" | G24: u | H24: 6.98 | J24: 78 | K24: =+ROUND($H24*J24,2) -> 544.44 | L24: 74 | M24: =+ROUND($H24*L24,2) -> 516.52 | N24: =+IF($L24-$J24>=0,$L24-$J24,0) -> 0 | O24: =+ROUND($H24*N24,2) -> 0 | Q24: =+ROUND($H24*P24,2) -> 0 | R24: =+IF($L24-$J24<=0,-$L24+$J24,0) -> 4 | S24: =+ROUND($H24*R24,2) -> 27.92 | U24: =+ROUND($H24*T24,2) -> 0
B25: =+B24+0.01 -> 2.04 | C25: =+C20+1 -> 7 | D25: Caja de control de carga adosable de PVC, con puerta, IP54, con riel DIN, borne de puesta a tierra y accesorios de fijación | G25: u | H25: 61.82 | J25: 39 | K25: =+ROUND($H25*J25,2) -> 2410.98 | L25: 37 | M25: =+ROUND($H25*L25,2) -> 2287.34 | N25: =+IF($L25-$J25>=0,$L25-$J25,0) -> 0 | O25: =+ROUND($H25*N25,2) -> 0 | Q25: =+ROUND($H25*P25,2) -> 0 | R25: =+IF($L25-$J25<=0,-$L25+$J25,0) -> 2 | S25: =+ROUND($H25*R25,2) -> 123.64 | U25: =+ROUND($H25*T25,2) -> 0
B26: =+B25+0.01 -> 2.05 | C26: =+C21+1 -> 8 | D26: Controlador de carga tipo PWM 12/24 Vdc, 20A | G26: u | H26: 276.01 | J26: 39 | K26: =+ROUND($H26*J26,2) -> 10764.39 | L26: 37 | M26: =+ROUND($H26*L26,2) -> 10212.37 | N26: =+IF($L26-$J26>=0,$L26-$J26,0) -> 0 | O26: =+ROUND($H26*N26,2) -> 0 | Q26: =+ROUND($H26*P26,2) -> 0 | R26: =+IF($L26-$J26<=0,-$L26+$J26,0) -> 2 | S26: =+ROUND($H26*R26,2) -> 552.02 | U26: =+ROUND($H26*T26,2) -> 0
B27: =+B26+0.01 -> 2.06 | C27: =+C22+1 -> 5 | D27: Tubería eléctrica tipo CONDUIT flexible corrugada de F°G°, con forro corrugado de PVC y 3/4" de diámetro | G27: u | H27: 11.3 | J27: 39 | K27: =+ROUND($H27*J27,2) -> 440.7 | L27: 37 | M27: =+ROUND($H27*L27,2) -> 418.1 | N27: =+IF($L27-$J27>=0,$L27-$J27,0) -> 0 | O27: =+ROUND($H27*N27,2) -> 0 | Q27: =+ROUND($H27*P27,2) -> 0 | R27: =+IF($L27-$J27<=0,-$L27+$J27,0) -> 2 | S27: =+ROUND($H27*R27,2) -> 22.6 | U27: =+ROUND($H27*T27,2) -> 0
B28: =+B27+0.01 -> 2.07 | C28: =+C23+1 -> 6 | D28: Abrazadera de F°G° de dos orejas para tubo de PVC de 3/4" diámetro con accesorios de fijación | G28: u | H28: 0.62 | J28: 78 | K28: =+ROUND($H28*J28,2) -> 48.36 | L28: 74 | M28: =+ROUND($H28*L28,2) -> 45.88 | N28: =+IF($L28-$J28>=0,$L28-$J28,0) -> 0 | O28: =+ROUND($H28*N28,2) -> 0 | Q28: =+ROUND($H28*P28,2) -> 0 | R28: =+IF($L28-$J28<=0,-$L28+$J28,0) -> 4 | S28: =+ROUND($H28*R28,2) -> 2.48 | U28: =+ROUND($H28*T28,2) -> 0
B29: =+B28+0.01 -> 2.08 | C29: =+C23+1 -> 6 | D29: Caja estanca de PVC con tapa atornillable, IP 65, de 100x100x70 mm | G29: u | H29: 13.63 | J29: 39 | K29: =+ROUND($H29*J29,2) -> 531.57 | L29: 37 | M29: =+ROUND($H29*L29,2) -> 504.31 | N29: =+IF($L29-$J29>=0,$L29-$J29,0) -> 0 | O29: =+ROUND($H29*N29,2) -> 0 | Q29: =+ROUND($H29*P29,2) -> 0 | R29: =+IF($L29-$J29<=0,-$L29+$J29,0) -> 2 | S29: =+ROUND($H29*R29,2) -> 27.26 | U29: =+ROUND($H29*T29,2) -> 0
B30: =+B29+0.01 -> 2.09 | C30: =+C25+1 -> 8 | D30: Bornera de línea a tierra para 8 conductores de 16 mm2 Cu | G30: u | H30: 15.17 | J30: 39 | K30: =+ROUND($H30*J30,2) -> 591.63 | L30: 37 | M30: =+ROUND($H30*L30,2) -> 561.29 | N30: =+IF($L30-$J30>=0,$L30-$J30,0) -> 0 | O30: =+ROUND($H30*N30,2) -> 0 | Q30: =+ROUND($H30*P30,2) -> 0 | R30: =+IF($L30-$J30<=0,-$L30+$J30,0) -> 2 | S30: =+ROUND($H30*R30,2) -> 30.34 | U30: =+ROUND($H30*T30,2) -> 0
B31: =+B30+0.01 -> 2.1 | C31: =+C26+1 -> 9 | D31: Interruptor termomagnético 12 Vdc, 16 A (De requerirse) | G31: u | H31: 51.32 | J31: 39 | K31: =+ROUND($H31*J31,2) -> 2001.48 | L31: 37 | M31: =+ROUND($H31*L31,2) -> 1898.84 | N31: =+IF($L31-$J31>=0,$L31-$J31,0) -> 0 | O31: =+ROUND($H31*N31,2) -> 0 | Q31: =+ROUND($H31*P31,2) -> 0 | R31: =+IF($L31-$J31<=0,-$L31+$J31,0) -> 2 | S31: =+ROUND($H31*R31,2) -> 102.64 | U31: =+ROUND($H31*T31,2) -> 0
B32: =+B31+0.01 -> 2.11 | C32: =+C27+1 -> 6 | D32: Interruptor termomagnético 12 Vdc, 40 A (De requerirse) | G32: u | H32: 67.47 | J32: 39 | K32: =+ROUND($H32*J32,2) -> 2631.33 | L32: 37 | M32: =+ROUND($H32*L32,2) -> 2496.39 | N32: =+IF($L32-$J32>=0,$L32-$J32,0) -> 0 | O32: =+ROUND($H32*N32,2) -> 0 | Q32: =+ROUND($H32*P32,2) -> 0 | R32: =+IF($L32-$J32<=0,-$L32+$J32,0) -> 2 | S32: =+ROUND($H32*R32,2) -> 134.94 | U32: =+ROUND($H32*T32,2) -> 0
B33: =+B32+0.01 -> 2.12 | C33: =+C28+1 -> 7 | D33: Supresor de pico protección de sobretensión tipo II, Uoc 275V, In(8/20) us (KA) 5 | G33: u | I33: =406.78*1.2 -> 488.136 | K33: =+ROUND($H33*J33,2) -> 0 | L33: 37 | M33: =+ROUND($I33*L33,2) -> 18061.03 | O33: =+ROUND($H33*N33,2) -> 0 | P33: =+L33 -> 37 | Q33: =+ROUND($I33*P33,2) -> 18061.03 | R33: =+IF($L33-$J33<=0,-$L33+$J33,0) -> 0 | S33: =+ROUND($H33*R33,2) -> 0 | U33: =+ROUND($H33*T33,2) -> 0
C34: =+#REF!+1 -> #REF! | F34: =+"SUB-TOTAL "&B21&": " -> SUB-TOTAL 2: | K34: =+SUM(K22:K33) -> 22482.72 | M34: =+SUM(M22:M33) -> 39390.79 | O34: =+SUM(O22:O33) -> 0 | Q34: =+SUM(Q22:Q33) -> 18061.03 | S34: =+SUM(S22:S33) -> 1152.96 | U34: =+SUM(U22:U33) -> 0 | W34: =+K34-M34+O34+Q34-S34 -> 6.3664629e-12
B35: =+B21+1 -> 3 | C35: =+C34+1 -> #REF! | D35: UNIDAD DE ALMACENAMIENTO
B36: =+B35+0.01 -> 3.01 | C36: =+#REF!+1 -> #REF! | D36: Bateria de electrolito gelificado, 150 Ah, 12 Vdc | G36: u | H36: 1302.07 | J36: 39 | K36: =+ROUND($H36*J36,2) -> 50780.73 | M36: =+ROUND($H36*L36,2) -> 0 | N36: =+IF($L36-$J36>=0,$L36-$J36,0) -> 0 | O36: =+ROUND($H36*N36,2) -> 0 | Q36: =+ROUND($H36*P36,2) -> 0 | R36: =+IF($L36-$J36<=0,-$L36+$J36,0) -> 39 | S36: =+ROUND($H36*R36,2) -> 50780.73 | U36: =+ROUND($H36*T36,2) -> 0
B37: =+B36+0.01 -> 3.02 | C37: =+#REF!+1 -> #REF! | D37: Rack para bateria gelificada, 150 Ah, 12 Vdc, incluye accesorios de fijación y protección | G37: u | H37: 265.36 | J37: 39 | K37: =+ROUND($H37*J37,2) -> 10349.04 | M37: =+ROUND($H37*L37,2) -> 0 | N37: =+IF($L37-$J37>=0,$L37-$J37,0) -> 0 | O37: =+ROUND($H37*N37,2) -> 0 | Q37: =+ROUND($H37*P37,2) -> 0 | R37: =+IF($L37-$J37<=0,-$L37+$J37,0) -> 39 | S37: =+ROUND($H37*R37,2) -> 10349.04 | U37: =+ROUND($H37*T37,2) -> 0
B38: =+B37+0.01 -> 3.03 | C38: =+#REF!+1 -> #REF! | D38: Conductor THW de 6 mm2, Cu | G38: u | H38: 2.88 | J38: 156 | K38: =+ROUND($H38*J38,2) -> 449.28 | L38: 148 | M38: =+ROUND($H38*L38,2) -> 426.24 | N38: =+IF($L38-$J38>=0,$L38-$J38,0) -> 0 | O38: =+ROUND($H38*N38,2) -> 0 | Q38: =+ROUND($H38*P38,2) -> 0 | R38: =+IF($L38-$J38<=0,-$L38+$J38,0) -> 8 | S38: =+ROUND($H38*R38,2) -> 23.04 | U38: =+ROUND($H38*T38,2) -> 0
B39: =+B38+0.01 -> 3.04 | C39: =+C34+1 -> #REF! | D39: Tubería eléctrica tipo CONDUIT flexible corrugada de F°G°, con forro corrugado de PVC y 3/4" de diámetro | G39: u | H39: 11.3 | J39: 78 | K39: =+ROUND($H39*J39,2) -> 881.4 | L39: 74 | M39: =+ROUND($H39*L39,2) -> 836.2 | N39: =+IF($L39-$J39>=0,$L39-$J39,0) -> 0 | O39: =+ROUND($H39*N39,2) -> 0 | Q39: =+ROUND($H39*P39,2) -> 0 | R39: =+IF($L39-$J39<=0,-$L39+$J39,0) -> 4 | S39: =+ROUND($H39*R39,2) -> 45.2 | U39: =+ROUND($H39*T39,2) -> 0
B40: =+B39+0.01 -> 3.05 | C40: =+C35+1 -> #REF! | D40: Abrazadera de F°G° de dos orejas para tubo de PVC de 3/4" diámetro con accesorios de fijación | G40: u | H40: 0.62 | J40: 273 | K40: =+ROUND($H40*J40,2) -> 169.26 | L40: 259 | M40: =+ROUND($H40*L40,2) -> 160.58 | N40: =+IF($L40-$J40>=0,$L40-$J40,0) -> 0 | O40: =+ROUND($H40*N40,2) -> 0 | Q40: =+ROUND($H40*P40,2) -> 0 | R40: =+IF($L40-$J40<=0,-$L40+$J40,0) -> 14 | S40: =+ROUND($H40*R40,2) -> 8.68 | U40: =+ROUND($H40*T40,2) -> 0
B41: =+B40+0.01 -> 3.06 | C41: =+C36+1 -> #REF! | D41: Caja estanca de PVC con tapa atornillable, IP 65, de 100x100x70 mm | G41: u | H41: 13.63 | J41: 39 | K41: =+ROUND($H41*J41,2) -> 531.57 | L41: 37 | M41: =+ROUND($H41*L41,2) -> 504.31 | N41: =+IF($L41-$J41>=0,$L41-$J41,0) -> 0 | O41: =+ROUND($H41*N41,2) -> 0 | Q41: =+ROUND($H41*P41,2) -> 0 | R41: =+IF($L41-$J41<=0,-$L41+$J41,0) -> 2 | S41: =+ROUND($H41*R41,2) -> 27.26 | U41: =+ROUND($H41*T41,2) -> 0
B42: =+B41+0.01 -> 3.07 | C42: =+C37+1 -> #REF! | D42: Conector rectangular hermético de PVC para tubería eléctrica flexible de PVC corrugada de 3/4" | G42: u | H42: 2.06 | J42: 78 | K42: =+ROUND($H42*J42,2) -> 160.68 | L42: 74 | M42: =+ROUND($H42*L42,2) -> 152.44 | N42: =+IF($L42-$J42>=0,$L42-$J42,0) -> 0 | O42: =+ROUND($H42*N42,2) -> 0 | Q42: =+ROUND($H42*P42,2) -> 0 | R42: =+IF($L42-$J42<=0,-$L42+$J42,0) -> 4 | S42: =+ROUND($H42*R42,2) -> 8.24 | U42: =+ROUND($H42*T42,2) -> 0
B43: =+B42+0.01 -> 3.08 | C43: =+C37+1 -> #REF! | D43: Conector rectangular hermético tipo CONDUIT, de A°G° para tubería flexible de 3/4" | G43: u | H43: 6.98 | J43: 156 | K43: =+ROUND($H43*J43,2) -> 1088.88 | L43: 148 | M43: =+ROUND($H43*L43,2) -> 1033.04 | N43: =+IF($L43-$J43>=0,$L43-$J43,0) -> 0 | O43: =+ROUND($H43*N43,2) -> 0 | Q43: =+ROUND($H43*P43,2) -> 0 | R43: =+IF($L43-$J43<=0,-$L43+$J43,0) -> 8 | S43: =+ROUND($H43*R43,2) -> 55.84 | U43: =+ROUND($H43*T43,2) -> 0
B44: =+B43+0.01 -> 3.09 | C44: =+C39+1 -> #REF! | D44: Terminales para bateria y elementos de fijacion | G44: u | H44: 63.87 | J44: 39 | K44: =+ROUND($H44*J44,2) -> 2490.93 | L44: 37 | M44: =+ROUND($H44*L44,2) -> 2363.19 | N44: =+IF($L44-$J44>=0,$L44-$J44,0) -> 0 | O44: =+ROUND($H44*N44,2) -> 0 | Q44: =+ROUND($H44*P44,2) -> 0 | R44: =+IF($L44-$J44<=0,-$L44+$J44,0) -> 2 | S44: =+ROUND($H44*R44,2) -> 127.74 | U44: =+ROUND($H44*T44,2) -> 0
B45: =+B44+0.01 -> 3.1 | C45: =+C40+1 -> #REF! | D45: Tubería eléctrica flexible de PVC corrugada de 3/4" de diámetro | G45: u | H45: 8.63 | J45: 39 | K45: =+ROUND($H45*J45,2) -> 336.57 | L45: 37 | M45: =+ROUND($H45*L45,2) -> 319.31 | N45: =+IF($L45-$J45>=0,$L45-$J45,0) -> 0 | O45: =+ROUND($H45*N45,2) -> 0 | Q45: =+ROUND($H45*P45,2) -> 0 | R45: =+IF($L45-$J45<=0,-$L45+$J45,0) -> 2 | S45: =+ROUND($H45*R45,2) -> 17.26 | U45: =+ROUND($H45*T45,2) -> 0
B46: =+B45+0.01 -> 3.11 | C46: =+C40+1 -> #REF! | D46: Tubería eléctrica flexible de PVC corrugada de 3/4" de diámetro | G46: u | H46: 1.78 | J46: 39 | K46: =+ROUND($H46*J46,2) -> 69.42 | L46: 37 | M46: =+ROUND($H46*L46,2) -> 65.86 | N46: =+IF($L46-$J46>=0,$L46-$J46,0) -> 0 | O46: =+ROUND($H46*N46,2) -> 0 | Q46: =+ROUND($H46*P46,2) -> 0 | R46: =+IF($L46-$J46<=0,-$L46+$J46,0) -> 2 | S46: =+ROUND($H46*R46,2) -> 3.56 | U46: =+ROUND($H46*T46,2) -> 0
B47: =+B46+0.01 -> 3.12 | C47: =+C41+1 -> #REF! | D47: Cinta autofundente para bornes de baterías | G47: u | H47: 5.48 | J47: 78 | K47: =+ROUND($H47*J47,2) -> 427.44 | L47: 74 | M47: =+ROUND($H47*L47,2) -> 405.52 | N47: =+IF($L47-$J47>=0,$L47-$J47,0) -> 0 | O47: =+ROUND($H47*N47,2) -> 0 | Q47: =+ROUND($H47*P47,2) -> 0 | R47: =+IF($L47-$J47<=0,-$L47+$J47,0) -> 4 | S47: =+ROUND($H47*R47,2) -> 21.92 | U47: =+ROUND($H47*T47,2) -> 0
B48: =+B47+0.01 -> 3.13 | C48: =+#REF!+1 -> #REF! | D48: Bateria de electrolito gelificado, 100 Ah, 12 Vdc | G48: u | I48: =+H36 -> 1302.07 | K48: =+ROUND($H48*J48,2) -> 0 | L48: 37 | M48: =+ROUND($I48*L48,2) -> 48176.59 | O48: =+ROUND($H48*N48,2) -> 0 | P48: =+L48 -> 37 | Q48: =+ROUND($I48*P48,2) -> 48176.59 | R48: =+IF($L48-$J48<=0,-$L48+$J48,0) -> 0 | S48: =+ROUND($H48*R48,2) -> 0 | U48: =+ROUND($H48*T48,2) -> 0
B49: =+B48+0.01 -> 3.14 | C49: =+#REF!+1 -> #REF! | D49: Rack para bateria gelificada, 100 Ah, 12 Vdc, incluye accesorios de fijación y protección | G49: u | I49: =+H37 -> 265.36 | K49: =+ROUND($H49*J49,2) -> 0 | L49: 37 | M49: =+ROUND($I49*L49,2) -> 9818.32 | O49: =+ROUND($H49*N49,2) -> 0 | P49: =+L49 -> 37 | Q49: =+ROUND($I49*P49,2) -> 9818.32 | R49: =+IF($L49-$J49<=0,-$L49+$J49,0) -> 0 | S49: =+ROUND($H49*R49,2) -> 0 | U49: =+ROUND($H49*T49,2) -> 0
C50: =+#REF!+1 -> #REF! | F50: =+"SUB-TOTAL "&B35&": " -> SUB-TOTAL 3: | K50: =+SUM(K36:K49) -> 67735.2 | M50: =+SUM(M36:M49) -> 64261.6 | O50: =+SUM(O36:O49) -> 0 | Q50: =+SUM(Q36:Q49) -> 57994.91 | S50: =+SUM(S36:S49) -> 61468.51 | U50: =+SUM(U36:U49) -> 0 | W50: =+K50-M50+O50+Q50-S50 -> 0
B51: =+B35+1 -> 4 | C51: =+C50+1 -> #REF! | D51: UNIDAD DE INVERSOR DC/AC
B52: =+B51+0.01 -> 4.01 | C52: =+C51+1 -> #REF! | D52: Inversor de 300W continuos 12Vdc/220Vac, 60 Hz | G52: u | H52: 614.53 | J52: 39 | K52: =+ROUND($H52*J52,2) -> 23966.67 | M52: =+ROUND($H52*L52,2) -> 0 | N52: =+IF($L52-$J52>=0,$L52-$J52,0) -> 0 | O52: =+ROUND($H52*N52,2) -> 0 | Q52: =+ROUND($H52*P52,2) -> 0 | R52: =+IF($L52-$J52<=0,-$L52+$J52,0) -> 39 | S52: =+ROUND($H52*R52,2) -> 23966.67 | U52: =+ROUND($H52*T52,2) -> 0
B53: =+B52+0.01 -> 4.02 | C53: =+#REF!+1 -> #REF! | D53: Caja para el inversor adosable de PVC, con puerta, IP54, con riel DIN, borne de puesta a tierra y accesorios de fijación | G53: u | H53: 236.54 | J53: 39 | K53: =+ROUND($H53*J53,2) -> 9225.06 | L53: 37 | M53: =+ROUND($H53*L53,2) -> 8751.98 | N53: =+IF($L53-$J53>=0,$L53-$J53,0) -> 0 | O53: =+ROUND($H53*N53,2) -> 0 | Q53: =+ROUND($H53*P53,2) -> 0 | R53: =+IF($L53-$J53<=0,-$L53+$J53,0) -> 2 | S53: =+ROUND($H53*R53,2) -> 473.08 | U53: =+ROUND($H53*T53,2) -> 0
B54: =+B53+0.01 -> 4.03 | C54: =+C53+1 -> #REF! | D54: Conductor THW de 16mm2, Cu | G54: m | H54: 7.69 | J54: 156 | K54: =+ROUND($H54*J54,2) -> 1199.64 | L54: 148 | M54: =+ROUND($H54*L54,2) -> 1138.12 | N54: =+IF($L54-$J54>=0,$L54-$J54,0) -> 0 | O54: =+ROUND($H54*N54,2) -> 0 | Q54: =+ROUND($H54*P54,2) -> 0 | R54: =+IF($L54-$J54<=0,-$L54+$J54,0) -> 8 | S54: =+ROUND($H54*R54,2) -> 61.52 | U54: =+ROUND($H54*T54,2) -> 0
B55: =+B54+0.01 -> 4.04 | C55: =+C54+1 -> #REF! | D55: Tubería eléctrica tipo CONDUIT flexible corrugada de F°G°, con forro corrugado de PVC y 3/4" de diámetro | G55: m | H55: 11.3 | J55: 78 | K55: =+ROUND($H55*J55,2) -> 881.4 | L55: 74 | M55: =+ROUND($H55*L55,2) -> 836.2 | N55: =+IF($L55-$J55>=0,$L55-$J55,0) -> 0 | O55: =+ROUND($H55*N55,2) -> 0 | Q55: =+ROUND($H55*P55,2) -> 0 | R55: =+IF($L55-$J55<=0,-$L55+$J55,0) -> 4 | S55: =+ROUND($H55*R55,2) -> 45.2 | U55: =+ROUND($H55*T55,2) -> 0
B56: =+B55+0.01 -> 4.05 | C56: =+C55+1 -> #REF! | D56: Abrazadera de F°G° de dos orejas para tubo de PVC de 3/4" diámetro con accesorios de fijación | G56: u | H56: 0.62 | J56: 273 | K56: =+ROUND($H56*J56,2) -> 169.26 | L56: 259 | M56: =+ROUND($H56*L56,2) -> 160.58 | N56: =+IF($L56-$J56>=0,$L56-$J56,0) -> 0 | O56: =+ROUND($H56*N56,2) -> 0 | Q56: =+ROUND($H56*P56,2) -> 0 | R56: =+IF($L56-$J56<=0,-$L56+$J56,0) -> 14 | S56: =+ROUND($H56*R56,2) -> 8.68 | U56: =+ROUND($H56*T56,2) -> 0
B57: =+B56+0.01 -> 4.06 | C57: =+C52+1 -> #REF! | D57: Caja estanca de PVC con tapa atornillable, IP 65, de 100x100x70 mm | G57: u | H57: 13.63 | J57: 39 | K57: =+ROUND($H57*J57,2) -> 531.57 | L57: 37 | M57: =+ROUND($H57*L57,2) -> 504.31 | N57: =+IF($L57-$J57>=0,$L57-$J57,0) -> 0 | O57: =+ROUND($H57*N57,2) -> 0 | Q57: =+ROUND($H57*P57,2) -> 0 | R57: =+IF($L57-$J57<=0,-$L57+$J57,0) -> 2 | S57: =+ROUND($H57*R57,2) -> 27.26 | U57: =+ROUND($H57*T57,2) -> 0
B58: =+B57+0.01 -> 4.07 | C58: =+C57+1 -> #REF! | D58: Conector rectangular hermético tipo CONDUIT, de A°G° para tubería flexible de 3/4" | G58: u | H58: 6.98 | J58: 156 | K58: =+ROUND($H58*J58,2) -> 1088.88 | L58: 148 | M58: =+ROUND($H58*L58,2) -> 1033.04 | N58: =+IF($L58-$J58>=0,$L58-$J58,0) -> 0 | O58: =+ROUND($H58*N58,2) -> 0 | Q58: =+ROUND($H58*P58,2) -> 0 | R58: =+IF($L58-$J58<=0,-$L58+$J58,0) -> 8 | S58: =+ROUND($H58*R58,2) -> 55.84 | U58: =+ROUND($H58*T58,2) -> 0
B59: =+B58+0.01 -> 4.08 | C59: =+C58+1 -> #REF! | D59: Conector rectangular hermético de PVC para tubería eléctrica flexible de PVC corrugada de 3/4" | G59: u | H59: 2.06 | J59: 78 | K59: =+ROUND($H59*J59,2) -> 160.68 | L59: 74 | M59: =+ROUND($H59*L59,2) -> 152.44 | N59: =+IF($L59-$J59>=0,$L59-$J59,0) -> 0 | O59: =+ROUND($H59*N59,2) -> 0 | Q59: =+ROUND($H59*P59,2) -> 0 | R59: =+IF($L59-$J59<=0,-$L59+$J59,0) -> 4 | S59: =+ROUND($H59*R59,2) -> 8.24 | U59: =+ROUND($H59*T59,2) -> 0
B60: =+B59+0.01 -> 4.09 | C60: =+C59+1 -> #REF! | D60: Tubería eléctrica flexible de PVC corrugada de 3/4" de diámetro | G60: m | H60: 1.78 | J60: 39 | K60: =+ROUND($H60*J60,2) -> 69.42 | L60: 37 | M60: =+ROUND($H60*L60,2) -> 65.86 | N60: =+IF($L60-$J60>=0,$L60-$J60,0) -> 0 | O60: =+ROUND($H60*N60,2) -> 0 | Q60: =+ROUND($H60*P60,2) -> 0 | R60: =+IF($L60-$J60<=0,-$L60+$J60,0) -> 2 | S60: =+ROUND($H60*R60,2) -> 3.56 | U60: =+ROUND($H60*T60,2) -> 0
B61: =+B60+0.01 -> 4.1 | C61: =+C60+1 -> #REF! | D61: Inversor de 250VA continuos 12Vdc/220Vac, 60 Hz | G61: u | I61: =+H52 -> 614.53 | K61: =+ROUND($H61*J61,2) -> 0 | L61: 37 | M61: =+ROUND($I61*L61,2) -> 22737.61 | N61: =+IF($L61-$J61>=0,$L61-$J61,0) -> 37 | O61: =+ROUND($H61*N61,2) -> 0 | P61: =+L61 -> 37 | Q61: =+ROUND($I61*P61,2) -> 22737.61 | R61: =+IF($L61-$J61<=0,-$L61+$J61,0) -> 0 | S61: =+ROUND($H61*R61,2) -> 0 | U61: =+ROUND($H61*T61,2) -> 0
C62: =+#REF!+1 -> #REF! | F62: =+"SUB-TOTAL "&B51&": " -> SUB-TOTAL 4: | K62: =+SUM(K52:K61) -> 37292.58 | M62: =+SUM(M52:M61) -> 35380.14 | O62: =+SUM(O52:O61) -> 0 | Q62: =+SUM(Q52:Q61) -> 22737.61 | S62: =+SUM(S52:S61) -> 24650.05 | U62: =+SUM(U52:U61) -> 0 | W62: =+K62-M62+O62+Q62-S62 -> 0
B63: =+B51+1 -> 5 | C63: =+C62+1 -> #REF! | D63: UNIDAD DE PROTECCION 220 V AC
B64: =+B63+0.01 -> 5.01 | C64: =+C63+1 -> #REF! | D64: Tablero de protección adosable de PVC, con puerta, 220 V ac, 6 polos, IP 54, con riel DIN , accesorios de fijación y bornera de pat | G64: u | H64: 27.38 | J64: 39 | K64: =+ROUND($H64*J64,2) -> 1067.82 | L64: 37 | M64: =+ROUND($H64*L64,2) -> 1013.06 | N64: =+IF($L64-$J64>=0,$L64-$J64,0) -> 0 | O64: =+ROUND($H64*N64,2) -> 0 | Q64: =+ROUND($H64*P64,2) -> 0 | R64: =+IF($L64-$J64<=0,-$L64+$J64,0) -> 2 | S64: =+ROUND($H64*R64,2) -> 54.76 | U64: =+ROUND($H64*T64,2) -> 0
B65: =+B64+0.01 -> 5.02 | C65: =+C64+1 -> #REF! | D65: Interruptor termomagnético 220Vac, 6A, 6KA | G65: u | H65: 27.46 | J65: 78 | K65: =+ROUND($H65*J65,2) -> 2141.88 | L65: 74 | M65: =+ROUND($H65*L65,2) -> 2032.04 | N65: =+IF($L65-$J65>=0,$L65-$J65,0) -> 0 | O65: =+ROUND($H65*N65,2) -> 0 | Q65: =+ROUND($H65*P65,2) -> 0 | R65: =+IF($L65-$J65<=0,-$L65+$J65,0) -> 4 | S65: =+ROUND($H65*R65,2) -> 109.84 | U65: =+ROUND($H65*T65,2) -> 0
B66: =+B65+0.01 -> 5.03 | C66: =+C65+1 -> #REF! | D66: Interruptor automático y diferencial 220Vac, 25A, 30mA | G66: u | H66: 73.94 | J66: 39 | K66: =+ROUND($H66*J66,2) -> 2883.66 | L66: 37 | M66: =+ROUND($H66*L66,2) -> 2735.78 | N66: =+IF($L66-$J66>=0,$L66-$J66,0) -> 0 | O66: =+ROUND($H66*N66,2) -> 0 | Q66: =+ROUND($H66*P66,2) -> 0 | R66: =+IF($L66-$J66<=0,-$L66+$J66,0) -> 2 | S66: =+ROUND($H66*R66,2) -> 147.88 | U66: =+ROUND($H66*T66,2) -> 0
B67: =+B66+0.01 -> 5.04 | C67: =+C66+1 -> #REF! | D67: Conductor THW, 6 mm2, Cu, color rojo y negro | G67: u | H67: 2.88 | J67: 195 | K67: =+ROUND($H67*J67,2) -> 561.6 | L67: 185 | M67: =+ROUND($H67*L67,2) -> 532.8 | N67: =+IF($L67-$J67>=0,$L67-$J67,0) -> 0 | O67: =+ROUND($H67*N67,2) -> 0 | Q67: =+ROUND($H67*P67,2) -> 0 | R67: =+IF($L67-$J67<=0,-$L67+$J67,0) -> 10 | S67: =+ROUND($H67*R67,2) -> 28.8 | U67: =+ROUND($H67*T67,2) -> 0
B68: =+B67+0.01 -> 5.05 | C68: =+C67+1 -> #REF! | D68: Tubo PVC de 1/2" diámetro x 3 m longitud, clase pesada (SAP) | G68: u | H68: 4.64 | J68: 39 | K68: =+ROUND($H68*J68,2) -> 180.96 | L68: 37 | M68: =+ROUND($H68*L68,2) -> 171.68 | N68: =+IF($L68-$J68>=0,$L68-$J68,0) -> 0 | O68: =+ROUND($H68*N68,2) -> 0 | Q68: =+ROUND($H68*P68,2) -> 0 | R68: =+IF($L68-$J68<=0,-$L68+$J68,0) -> 2 | S68: =+ROUND($H68*R68,2) -> 9.28 | U68: =+ROUND($H68*T68,2) -> 0
B69: =+B68+0.01 -> 5.06 | C69: =+C68+1 -> #REF! | D69: Curva de PVC de 1/2" de diámetro, clase pesada (SAP) | G69: u | H69: 0.58 | J69: 78 | K69: =+ROUND($H69*J69,2) -> 45.24 | L69: 74 | M69: =+ROUND($H69*L69,2) -> 42.92 | N69: =+IF($L69-$J69>=0,$L69-$J69,0) -> 0 | O69: =+ROUND($H69*N69,2) -> 0 | Q69: =+ROUND($H69*P69,2) -> 0 | R69: =+IF($L69-$J69<=0,-$L69+$J69,0) -> 4 | S69: =+ROUND($H69*R69,2) -> 2.32 | U69: =+ROUND($H69*T69,2) -> 0
B70: =+B69+0.01 -> 5.07 | C70: =+C69+1 -> #REF! | D70: Conector de PVC, roscado con tuerca de ajuste de 1/2" SAP | G70: u | H70: 5.69 | J70: 78 | K70: =+ROUND($H70*J70,2) -> 443.82 | L70: 74 | M70: =+ROUND($H70*L70,2) -> 421.06 | N70: =+IF($L70-$J70>=0,$L70-$J70,0) -> 0 | O70: =+ROUND($H70*N70,2) -> 0 | Q70: =+ROUND($H70*P70,2) -> 0 | R70: =+IF($L70-$J70<=0,-$L70+$J70,0) -> 4 | S70: =+ROUND($H70*R70,2) -> 22.76 | U70: =+ROUND($H70*T70,2) -> 0
B71: =+B70+0.01 -> 5.08 | C71: =+C70+1 -> #REF! | D71: Abrazadera de F°G° de dos orejas para tubo de PVC de 1/2" diámetro con accesorios de fijación | G71: m | H71: 0.26 | J71: 195 | K71: =+ROUND($H71*J71,2) -> 50.7 | L71: 185 | M71: =+ROUND($H71*L71,2) -> 48.1 | N71: =+IF($L71-$J71>=0,$L71-$J71,0) -> 0 | O71: =+ROUND($H71*N71,2) -> 0 | Q71: =+ROUND($H71*P71,2) -> 0 | R71: =+IF($L71-$J71<=0,-$L71+$J71,0) -> 10 | S71: =+ROUND($H71*R71,2) -> 2.6 | U71: =+ROUND($H71*T71,2) -> 0
C72: =+#REF!+1 -> #REF! | F72: =+"SUB-TOTAL "&B63&": " -> SUB-TOTAL 5: | K72: =+SUM(K64:K71) -> 7375.68 | M72: =+SUM(M64:M71) -> 6997.44 | O72: =+SUM(O64:O71) -> 0 | Q72: =+SUM(Q64:Q71) -> 0 | S72: =+SUM(S64:S71) -> 378.24 | U72: =+SUM(U64:U71) -> 0 | W72: =+K72-M72+O72+Q72-S72 -> -2.0463631e-12
B73: =+B63+1 -> 6 | C73: =+C72+1 -> #REF! | D73: UNIDAD DE CARGAS 220V AC
B74: =+B73+0.01 -> 6.01 | C74: =+C64+1 -> #REF! | D74: Conductor para alumbrado THW, 2,5mm2, Cu, color rojo y negro | G74: m | H74: 1.24 | J74: 1560 | K74: =+ROUND($H74*J74,2) -> 1934.4 | L74: 1480 | M74: =+ROUND($H74*L74,2) -> 1835.2 | N74: =+IF($L74-$J74>=0,$L74-$J74,0) -> 0 | O74: =+ROUND($H74*N74,2) -> 0 | Q74: =+ROUND($H74*P74,2) -> 0 | R74: =+IF($L74-$J74<=0,-$L74+$J74,0) -> 80 | S74: =+ROUND($H74*R74,2) -> 99.2 | U74: =+ROUND($H74*T74,2) -> 0
B75: =+B74+0.01 -> 6.02 | C75: =+C74+1 -> #REF! | D75: Conductor para tomacorriente THW, 4mm2, Cu, color rojo y negro | G75: m | H75: 1.9 | J75: 1170 | K75: =+ROUND($H75*J75,2) -> 2223 | L75: 1110 | M75: =+ROUND($H75*L75,2) -> 2109 | N75: =+IF($L75-$J75>=0,$L75-$J75,0) -> 0 | O75: =+ROUND($H75*N75,2) -> 0 | Q75: =+ROUND($H75*P75,2) -> 0 | R75: =+IF($L75-$J75<=0,-$L75+$J75,0) -> 60 | S75: =+ROUND($H75*R75,2) -> 114 | U75: =+ROUND($H75*T75,2) -> 0
B76: =+B75+0.01 -> 6.03 | C76: =+C75+1 -> #REF! | D76: Conductor para tierra de protección THW 4mm2, Cu, color verde amarillo | G76: m | H76: 1.91 | J76: 585 | K76: =+ROUND($H76*J76,2) -> 1117.35 | L76: 555 | M76: =+ROUND($H76*L76,2) -> 1060.05 | N76: =+IF($L76-$J76>=0,$L76-$J76,0) -> 0 | O76: =+ROUND($H76*N76,2) -> 0 | Q76: =+ROUND($H76*P76,2) -> 0 | R76: =+IF($L76-$J76<=0,-$L76+$J76,0) -> 30 | S76: =+ROUND($H76*R76,2) -> 57.3 | U76: =+ROUND($H76*T76,2) -> 0
B77: =+B76+0.01 -> 6.04 | C77: =+C76+1 -> #REF! | D77: Caja de pase metálica octogonal pesada para salida de alumbrado | G77: m | H77: 18.26 | J77: 117 | K77: =+ROUND($H77*J77,2) -> 2136.42 | L77: 111 | M77: =+ROUND($H77*L77,2) -> 2026.86 | N77: =+IF($L77-$J77>=0,$L77-$J77,0) -> 0 | O77: =+ROUND($H77*N77,2) -> 0 | Q77: =+ROUND($H77*P77,2) -> 0 | R77: =+IF($L77-$J77<=0,-$L77+$J77,0) -> 6 | S77: =+ROUND($H77*R77,2) -> 109.56 | U77: =+ROUND($H77*T77,2) -> 0
B78: =+B77+0.01 -> 6.05 | C78: =+C68+1 -> #REF! | D78: Portalampara de material aislante con casquillo E27 con accesorios de fijación | G78: m | H78: 10.8 | J78: 117 | K78: =+ROUND($H78*J78,2) -> 1263.6 | L78: 111 | M78: =+ROUND($H78*L78,2) -> 1198.8 | N78: =+IF($L78-$J78>=0,$L78-$J78,0) -> 0 | O78: =+ROUND($H78*N78,2) -> 0 | Q78: =+ROUND($H78*P78,2) -> 0 | R78: =+IF($L78-$J78<=0,-$L78+$J78,0) -> 6 | S78: =+ROUND($H78*R78,2) -> 64.8 | U78: =+ROUND($H78*T78,2) -> 0
B79: =+B78+0.01 -> 6.06 | C79: =+C78+1 -> #REF! | D79: Lampara tipo LED 7W, 220Vac, color cálido | G79: m | H79: 17.36 | J79: 117 | K79: =+ROUND($H79*J79,2) -> 2031.12 | L79: 111 | M79: =+ROUND($H79*L79,2) -> 1926.96 | N79: =+IF($L79-$J79>=0,$L79-$J79,0) -> 0 | O79: =+ROUND($H79*N79,2) -> 0 | Q79: =+ROUND($H79*P79,2) -> 0 | R79: =+IF($L79-$J79<=0,-$L79+$J79,0) -> 6 | S79: =+ROUND($H79*R79,2) -> 104.16 | U79: =+ROUND($H79*T79,2) -> 0
B80: =+B79+0.01 -> 6.07 | C80: =+C79+1 -> #REF! | D80: Caja de pase rectangular de PVC de 2x4" para instalación adosada de interruptor. Incluye accesorios de fijación | G80: m | H80: 12.24 | J80: 117 | K80: =+ROUND($H80*J80,2) -> 1432.08 | L80: 111 | M80: =+ROUND($H80*L80,2) -> 1358.64 | N80: =+IF($L80-$J80>=0,$L80-$J80,0) -> 0 | O80: =+ROUND($H80*N80,2) -> 0 | Q80: =+ROUND($H80*P80,2) -> 0 | R80: =+IF($L80-$J80<=0,-$L80+$J80,0) -> 6 | S80: =+ROUND($H80*R80,2) -> 73.44 | U80: =+ROUND($H80*T80,2) -> 0
B81: =+B80+0.01 -> 6.08 | C81: =+C80+1 -> #REF! | D81: Cable de Acero con Recubrimiento Metalúrgico de Cu de 4 AWG (21,15 mm²), para Puesta a Tierra | G81: m | H81: 6.71 | J81: 117 | K81: =+ROUND($H81*J81,2) -> 785.07 | L81: 111 | M81: =+ROUND($H81*L81,2) -> 744.81 | N81: =+IF($L81-$J81>=0,$L81-$J81,0) -> 0 | O81: =+ROUND($H81*N81,2) -> 0 | Q81: =+ROUND($H81*P81,2) -> 0 | R81: =+IF($L81-$J81<=0,-$L81+$J81,0) -> 6 | S81: =+ROUND($H81*R81,2) -> 40.26 | U81: =+ROUND($H81*T81,2) -> 0
B82: =+B81+0.01 -> 6.09 | C82: =+#REF!+1 -> #REF! | D82: Caja de pase rectangualr de PVC, minimo IP54, de 80 mm x 80 mm x 35 mm | G82: m | H82: 8.11 | J82: 156 | K82: =+ROUND($H82*J82,2) -> 1265.16 | L82: 148 | M82: =+ROUND($H82*L82,2) -> 1200.28 | N82: =+IF($L82-$J82>=0,$L82-$J82,0) -> 0 | O82: =+ROUND($H82*N82,2) -> 0 | Q82: =+ROUND($H82*P82,2) -> 0 | R82: =+IF($L82-$J82<=0,-$L82+$J82,0) -> 8 | S82: =+ROUND($H82*R82,2) -> 64.88 | U82: =+ROUND($H82*T82,2) -> 0
B83: =+B82+0.01 -> 6.1 | C83: =+C82+1 -> #REF! | D83: Bornera de PVC de 15 A, para empalme de conductores (linea de 12 conectores) | G83: m | H83: 17.62 | J83: 39 | K83: =+ROUND($H83*J83,2) -> 687.18 | L83: 37 | M83: =+ROUND($H83*L83,2) -> 651.94 | N83: =+IF($L83-$J83>=0,$L83-$J83,0) -> 0 | O83: =+ROUND($H83*N83,2) -> 0 | Q83: =+ROUND($H83*P83,2) -> 0 | R83: =+IF($L83-$J83<=0,-$L83+$J83,0) -> 2 | S83: =+ROUND($H83*R83,2) -> 35.24 | U83: =+ROUND($H83*T83,2) -> 0
B84: =+B83+0.01 -> 6.11 | C84: =+C83+1 -> #REF! | D84: Caja de pase rectangular de PVC de 2x4" para instalación adosada de tomacorriente. Incluye accesorios de fijación | G84: m | H84: 12.24 | J84: 117 | K84: =+ROUND($H84*J84,2) -> 1432.08 | L84: 111 | M84: =+ROUND($H84*L84,2) -> 1358.64 | N84: =+IF($L84-$J84>=0,$L84-$J84,0) -> 0 | O84: =+ROUND($H84*N84,2) -> 0 | Q84: =+ROUND($H84*P84,2) -> 0 | R84: =+IF($L84-$J84<=0,-$L84+$J84,0) -> 6 | S84: =+ROUND($H84*R84,2) -> 73.44 | U84: =+ROUND($H84*T84,2) -> 0
B85: =+B84+0.01 -> 6.12 | C85: =+C84+1 -> #REF! | D85: Tomacorriente doble, bipolar, tipo universal 2x15A+T, con toma a tierra, de 250V | G85: m | H85: 21.94 | J85: 117 | K85: =+ROUND($H85*J85,2) -> 2566.98 | L85: 111 | M85: =+ROUND($H85*L85,2) -> 2435.34 | N85: =+IF($L85-$J85>=0,$L85-$J85,0) -> 0 | O85: =+ROUND($H85*N85,2) -> 0 | Q85: =+ROUND($H85*P85,2) -> 0 | R85: =+IF($L85-$J85<=0,-$L85+$J85,0) -> 6 | S85: =+ROUND($H85*R85,2) -> 131.64 | U85: =+ROUND($H85*T85,2) -> 0
B86: =+B85+0.01 -> 6.13 | C86: =+C73+1 -> #REF! | D86: Tubo PVC de 1/2" diámetro x 3 m longitud, clase pesada (SAP) | G86: m | H86: 4.64 | J86: 390 | K86: =+ROUND($H86*J86,2) -> 1809.6 | L86: 370 | M86: =+ROUND($H86*L86,2) -> 1716.8 | N86: =+IF($L86-$J86>=0,$L86-$J86,0) -> 0 | O86: =+ROUND($H86*N86,2) -> 0 | Q86: =+ROUND($H86*P86,2) -> 0 | R86: =+IF($L86-$J86<=0,-$L86+$J86,0) -> 20 | S86: =+ROUND($H86*R86,2) -> 92.8 | U86: =+ROUND($H86*T86,2) -> 0
B87: =+B86+0.01 -> 6.14 | C87: =+C86+1 -> #REF! | D87: Curva de PVC de 1/2" de diámetro, clase pesada (SAP) | G87: m | H87: 0.58 | J87: 585 | K87: =+ROUND($H87*J87,2) -> 339.3 | L87: 555 | M87: =+ROUND($H87*L87,2) -> 321.9 | N87: =+IF($L87-$J87>=0,$L87-$J87,0) -> 0 | O87: =+ROUND($H87*N87,2) -> 0 | Q87: =+ROUND($H87*P87,2) -> 0 | R87: =+IF($L87-$J87<=0,-$L87+$J87,0) -> 30 | S87: =+ROUND($H87*R87,2) -> 17.4 | U87: =+ROUND($H87*T87,2) -> 0
B88: =+B87+0.01 -> 6.15 | C88: =+C87+1 -> #REF! | D88: Conector hembra roscado de PVC de 1/2" con tuerca de ajuste, para fijación de tubo SAP a cajas | G88: m | H88: 5.69 | J88: 1014 | K88: =+ROUND($H88*J88,2) -> 5769.66 | L88: 962 | M88: =+ROUND($H88*L88,2) -> 5473.78 | N88: =+IF($L88-$J88>=0,$L88-$J88,0) -> 0 | O88: =+ROUND($H88*N88,2) -> 0 | Q88: =+ROUND($H88*P88,2) -> 0 | R88: =+IF($L88-$J88<=0,-$L88+$J88,0) -> 52 | S88: =+ROUND($H88*R88,2) -> 295.88 | U88: =+ROUND($H88*T88,2) -> 0
B89: =+B88+0.01 -> 6.16 | C89: =+C87+1 -> #REF! | D89: Abrazadera de F°G° de una oreja para tubo de PVC de 1/2" diámetro con accesorios de fijación | G89: m | H89: 0.62 | J89: 1755 | K89: =+ROUND($H89*J89,2) -> 1088.1 | L89: 1665 | M89: =+ROUND($H89*L89,2) -> 1032.3 | N89: =+IF($L89-$J89>=0,$L89-$J89,0) -> 0 | O89: =+ROUND($H89*N89,2) -> 0 | Q89: =+ROUND($H89*P89,2) -> 0 | R89: =+IF($L89-$J89<=0,-$L89+$J89,0) -> 90 | S89: =+ROUND($H89*R89,2) -> 55.8 | U89: =+ROUND($H89*T89,2) -> 0
B90: =+B89+0.01 -> 6.17 | C90: =+C88+1 -> #REF! | D90: Unión de PVC de 1/2" SAP | G90: m | H90: 0.47 | J90: 195 | K90: =+ROUND($H90*J90,2) -> 91.65 | L90: 185 | M90: =+ROUND($H90*L90,2) -> 86.95 | N90: =+IF($L90-$J90>=0,$L90-$J90,0) -> 0 | O90: =+ROUND($H90*N90,2) -> 0 | Q90: =+ROUND($H90*P90,2) -> 0 | R90: =+IF($L90-$J90<=0,-$L90+$J90,0) -> 10 | S90: =+ROUND($H90*R90,2) -> 4.7 | U90: =+ROUND($H90*T90,2) -> 0
C91: =+C90+1 -> #REF! | F91: =+"SUB-TOTAL "&B73&": " -> SUB-TOTAL 6: | K91: =+SUM(K74:K90) -> 27972.75 | M91: =+SUM(M74:M90) -> 26538.25 | O91: =+SUM(O74:O90) -> 0 | Q91: =+SUM(Q74:Q90) -> 0 | S91: =+SUM(S74:S90) -> 1434.5 | U91: =+SUM(U74:U90) -> 0 | W91: =+K91-M91+O91+Q91-S91 -> 0
B92: =+B73+1 -> 7 | C92: =+C91+1 -> #REF! | D92: RED EQUIPOTENCIAL
B93: =+B92+0.01 -> 7.01 | C93: =+C92+1 -> #REF! | D93: Conductor de conexión a tierra de equipo a barra de tierra, conductor 1x4mm2 THW, Cu | G93: u | H93: 2.08 | J93: 585 | K93: =+ROUND($H93*J93,2) -> 1216.8 | L93: 555 | M93: =+ROUND($H93*L93,2) -> 1154.4 | N93: =+IF($L93-$J93>=0,$L93-$J93,0) -> 0 | O93: =+ROUND($H93*N93,2) -> 0 | Q93: =+ROUND($H93*P93,2) -> 0 | R93: =+IF($L93-$J93<=0,-$L93+$J93,0) -> 30 | S93: =+ROUND($H93*R93,2) -> 62.4 | U93: =+ROUND($H93*T93,2) -> 0
B94: =+B93+0.01 -> 7.02 | C94: =+C93+1 -> #REF! | D94: Luminaria completa con equipo para Lámpara de Vapor de Sodio de 50 W | G94: u | H94: 11.3 | J94: 39 | K94: =+ROUND($H94*J94,2) -> 440.7 | L94: 37 | M94: =+ROUND($H94*L94,2) -> 418.1 | N94: =+IF($L94-$J94>=0,$L94-$J94,0) -> 0 | O94: =+ROUND($H94*N94,2) -> 0 | Q94: =+ROUND($H94*P94,2) -> 0 | R94: =+IF($L94-$J94<=0,-$L94+$J94,0) -> 2 | S94: =+ROUND($H94*R94,2) -> 22.6 | U94: =+ROUND($H94*T94,2) -> 0
B95: =+B94+0.01 -> 7.03 | C95: =+C94+1 -> #REF! | D95: Abrazadera de F°G° de dos orejas para tubo de PVC de 1/2" diámetro con accesorios de fijación | G95: u | H95: 0.26 | J95: 195 | K95: =+ROUND($H95*J95,2) -> 50.7 | L95: 185 | M95: =+ROUND($H95*L95,2) -> 48.1 | N95: =+IF($L95-$J95>=0,$L95-$J95,0) -> 0 | O95: =+ROUND($H95*N95,2) -> 0 | Q95: =+ROUND($H95*P95,2) -> 0 | R95: =+IF($L95-$J95<=0,-$L95+$J95,0) -> 10 | S95: =+ROUND($H95*R95,2) -> 2.6 | U95: =+ROUND($H95*T95,2) -> 0
B96: =+B95+0.01 -> 7.04 | C96: =+C95+1 -> #REF! | D96: Conector rectangular hermético tipo CONDUIT, de A°G° para tubería flexible de 3/4" | G96: u | H96: 6.98 | J96: 78 | K96: =+ROUND($H96*J96,2) -> 544.44 | L96: 74 | M96: =+ROUND($H96*L96,2) -> 516.52 | N96: =+IF($L96-$J96>=0,$L96-$J96,0) -> 0 | O96: =+ROUND($H96*N96,2) -> 0 | Q96: =+ROUND($H96*P96,2) -> 0 | R96: =+IF($L96-$J96<=0,-$L96+$J96,0) -> 4 | S96: =+ROUND($H96*R96,2) -> 27.92 | U96: =+ROUND($H96*T96,2) -> 0
B97: =+B96+0.01 -> 7.05 | C97: =+C96+1 -> #REF! | D97: Caja estanca de PVC con tapa atornillable, IP 65, de 100x100x70 mm | G97: u | H97: 13.63 | J97: 39 | K97: =+ROUND($H97*J97,2) -> 531.57 | L97: 37 | M97: =+ROUND($H97*L97,2) -> 504.31 | N97: =+IF($L97-$J97>=0,$L97-$J97,0) -> 0 | O97: =+ROUND($H97*N97,2) -> 0 | Q97: =+ROUND($H97*P97,2) -> 0 | R97: =+IF($L97-$J97<=0,-$L97+$J97,0) -> 2 | S97: =+ROUND($H97*R97,2) -> 27.26 | U97: =+ROUND($H97*T97,2) -> 0
C98: =+#REF!+1 -> #REF! | F98: =+"SUB-TOTAL "&B92&": " -> SUB-TOTAL 7: | K98: =+SUM(K93:K97) -> 2784.21 | M98: =+SUM(M93:M97) -> 2641.43 | O98: =+SUM(O93:O97) -> 0 | Q98: =+SUM(Q93:Q97) -> 0 | S98: =+SUM(S93:S97) -> 142.78 | U98: =+SUM(U93:U97) -> 0 | W98: =+K98-M98+O98+Q98-S98 -> 6.5369932e-13
B99: =+B92+1 -> 8 | C99: =+C98+1 -> #REF! | D99: PUESTA A TIERRA
B100: =+B99+0.01 -> 8.01 | C100: =+C99+1 -> #REF! | D100: Electrodo de Acero Recubierto de Cobre de 16 mm Ø x 2,40 m | G100: m | H100: 66.7 | J100: 39 | K100: =+ROUND($H100*J100,2) -> 2601.3 | L100: 37 | M100: =+ROUND($H100*L100,2) -> 2467.9 | N100: =+IF($L100-$J100>=0,$L100-$J100,0) -> 0 | O100: =+ROUND($H100*N100,2) -> 0 | Q100: =+ROUND($H100*P100,2) -> 0 | R100: =+IF($L100-$J100<=0,-$L100+$J100,0) -> 2 | S100: =+ROUND($H100*R100,2) -> 133.4 | U100: =+ROUND($H100*T100,2) -> 0
B101: =+B100+0.01 -> 8.02 | C101: =+C100+1 -> #REF! | D101: Conductor desnudo de bajada a Puesta a Tierra, Cu recocido 1x10mm2 | G101: u | H101: 3.86 | J101: 234 | K101: =+ROUND($H101*J101,2) -> 903.24 | L101: 222 | M101: =+ROUND($H101*L101,2) -> 856.92 | N101: =+IF($L101-$J101>=0,$L101-$J101,0) -> 0 | O101: =+ROUND($H101*N101,2) -> 0 | Q101: =+ROUND($H101*P101,2) -> 0 | R101: =+IF($L101-$J101<=0,-$L101+$J101,0) -> 12 | S101: =+ROUND($H101*R101,2) -> 46.32 | U101: =+ROUND($H101*T101,2) -> 0
B102: =+B101+0.01 -> 8.03 | C102: =+C101+1 -> #REF! | D102: Conector de Bronce para Electrodo de 16 mm ø y Conductor de Cobre de 10 mm2 | G102: u | H102: 9.51 | J102: 78 | K102: =+ROUND($H102*J102,2) -> 741.78 | L102: 74 | M102: =+ROUND($H102*L102,2) -> 703.74 | N102: =+IF($L102-$J102>=0,$L102-$J102,0) -> 0 | O102: =+ROUND($H102*N102,2) -> 0 | Q102: =+ROUND($H102*P102,2) -> 0 | R102: =+IF($L102-$J102<=0,-$L102+$J102,0) -> 4 | S102: =+ROUND($H102*R102,2) -> 38.04 | U102: =+ROUND($H102*T102,2) -> 0
B103: =+B102+0.01 -> 8.04 | C103: =+C102+1 -> #REF! | D103: Arandela de Anclaje de A°G°, 102 x 102 x 6,35 mm, Agujero de 18 mmø | G103: u | H103: 5.46 | J103: 39 | K103: =+ROUND($H103*J103,2) -> 212.94 | L103: 37 | M103: =+ROUND($H103*L103,2) -> 202.02 | N103: =+IF($L103-$J103>=0,$L103-$J103,0) -> 0 | O103: =+ROUND($H103*N103,2) -> 0 | Q103: =+ROUND($H103*P103,2) -> 0 | R103: =+IF($L103-$J103<=0,-$L103+$J103,0) -> 2 | S103: =+ROUND($H103*R103,2) -> 10.92 | U103: =+ROUND($H103*T103,2) -> 0
B104: =+B103+0.01 -> 8.05 | C104: =+C103+1 -> #REF! | D104: Caja Registro de Concreto para Puesta a Tierra ø 0,40 m x 0,30 m | G104: u | H104: 40.09 | J104: 39 | K104: =+ROUND($H104*J104,2) -> 1563.51 | L104: 37 | M104: =+ROUND($H104*L104,2) -> 1483.33 | N104: =+IF($L104-$J104>=0,$L104-$J104,0) -> 0 | O104: =+ROUND($H104*N104,2) -> 0 | Q104: =+ROUND($H104*P104,2) -> 0 | R104: =+IF($L104-$J104<=0,-$L104+$J104,0) -> 2 | S104: =+ROUND($H104*R104,2) -> 80.18 | U104: =+ROUND($H104*T104,2) -> 0
B105: =+B104+0.01 -> 8.06 | C105: =+C104+1 -> #REF! | D105: Tubo PVC de 3/4" diámetro x 3 m longitud, clase pesada (SAP) | G105: u | H105: 11.86 | J105: 39 | K105: =+ROUND($H105*J105,2) -> 462.54 | L105: 37 | M105: =+ROUND($H105*L105,2) -> 438.82 | N105: =+IF($L105-$J105>=0,$L105-$J105,0) -> 0 | O105: =+ROUND($H105*N105,2) -> 0 | Q105: =+ROUND($H105*P105,2) -> 0 | R105: =+IF($L105-$J105<=0,-$L105+$J105,0) -> 2 | S105: =+ROUND($H105*R105,2) -> 23.72 | U105: =+ROUND($H105*T105,2) -> 0
B106: =+B105+0.01 -> 8.07 | C106: =+C105+1 -> #REF! | D106: Curva de PVC de 3/4" de diámetro, clase pesada (SAP) | G106: u | H106: 0.58 | J106: 39 | K106: =+ROUND($H106*J106,2) -> 22.62 | L106: 111 | M106: =+ROUND($H106*L106,2) -> 64.38 | N106: =+IF($L106-$J106>=0,$L106-$J106,0) -> 72 | O106: =+ROUND($H106*N106,2) -> 41.76 | Q106: =+ROUND($H106*P106,2) -> 0 | R106: =+IF($L106-$J106<=0,-$L106+$J106,0) -> 0 | S106: =+ROUND($H106*R106,2) -> 0 | U106: =+ROUND($H106*T106,2) -> 0
B107: =+B106+0.01 -> 8.08 | C107: =+C106+1 -> #REF! | D107: Cemento conductivo en bolsa de 25 kg | G107: u | H107: 115.14 | J107: 39 | K107: =+ROUND($H107*J107,2) -> 4490.46 | M107: =+ROUND($H107*L107,2) -> 0 | N107: =+IF($L107-$J107>=0,$L107-$J107,0) -> 0 | O107: =+ROUND($H107*N107,2) -> 0 | Q107: =+ROUND($H107*P107,2) -> 0 | R107: =+IF($L107-$J107<=0,-$L107+$J107,0) -> 39 | S107: =+ROUND($H107*R107,2) -> 4490.46 | U107: =+ROUND($H107*T107,2) -> 0
...

Sheet FP  SFVS
B3: FÓRMULA POLINÓMICA
C6: PROYECTO :
C7: AMPLIACIÓN DEL SERVICIO DE ENERGÍA ELÉCTRICA EN LA PROVINCIA DEL SANTA Y EN EL DISTRITO DE PAMPAROMAS – DEPARTAMENTO DE ANCASH”
