Workbook

Sheet Resumen Total
B2: Resumen General del Valor Referencial (Obra y Estudio)
B3: Proyecto | D3: : | E3: “AMPLIACIÓN DEL SERVICIO DE ENERGÍA ELÉCTRICA EN LA PROVINCIA DEL SANTA Y EN EL DISTRITO DE PAMPAROMAS – DEPARTAMENTO DE ANCASH”
B4: Departamento | D4: : | E4: ANCASH | H4: Fecha: | I4: 44711
B5: Ítem | C5: Descripción | G5: Total Sin I.G.V. (S/) | H5: I.G.V. | I5: Total S/
B6: A | D6: COSTO DE OBRA | G6: =+#REF! -> #REF! | H6: =ROUND(+G6*0.18,2) -> #REF! | I6: =SUM(G6:H6) -> #REF! | L6: =+I11-L11 -> 3137339.3 | N6: =+L6/I6 -> #REF!
B7: B | D7: COSTO DE EXPEDIENTE TÉCNICO | G7: =+'EXPED-TECNICO'!K193 -> 200121.88 | H7: =ROUND(+G7*0.18,2) -> 36021.94 | I7: =SUM(G7:H7) -> 236143.82
D8: TOTAL | G8: =SUM(G6:G7) -> #REF! | H8: =SUM(H6:H7) -> #REF! | I8: =+ROUND(SUM(I6:I7),2) -> #REF!
H11: 3748314.6 | I11: 3373483.1 | L11: =+ROUND(I11*7%,2) -> 236143.82
H12: =+I11-I8 -> #REF! | I12: =+I11/I8 -> #REF!
F14: Inversiones
F15: Componentes | G15: US$ sin IGV) | H15: Cantidad
F16: US$ / km Línea Primaria | G16: =+#REF! -> #REF! | H16: US$ / km
F17: US$ / Conexión Línea Primaria | G17: =+#REF! -> #REF! | H17: US$ / Conexión
F18: US$ / Conexión Red Primaria (1/) | G18: =+#REF! -> #REF! | H18: US$ / Conexión
F19: US$ / Conexión Red Secundaria y Conexiones Domiciliarias | G19: =+#REF! -> #REF! | H19: US$ / Conexión
F20: US$ Conexión Total (incluye IGV) | G20: =+#REF! -> #REF! | H20: US$ / Conexión

Sheet G. GENERALES
A1: “AMPLIACIÓN DEL SERVICIO DE ENERGÍA ELÉCTRICA EN LA PROVINCIA DEL SANTA Y EN EL DISTRITO DE PAMPAROMAS – DEPARTAMENTO DE ANCASH”
A3: CALCULO DE LOS GASTOS GENERALES DIRECTOS E INDIRECTOS
B5: Sección : | C5: LINEAS PRIMARIAS, REDES PRIMARIAS Y REDES SECUNDARIAS
B6: Departamento : | C6: ANCASH
B7: Plazo de Obra + Expediente Técnico: | C7: =+F9+F10 -> 10 | D7: meses
A9: 1.0 | B9: GASTOS GENERALES VARIABLES-GG DIRECTOS | E9: Estudio Definitivo : | F9: 4 | G9: meses
E10: Obra : | F10: 6 | G10: meses
A11: 1.1 | B11: Personal Profesional Principal
B12: Descripción | C12: Unidad | D12: Cant. | E12: Particip. | F12: Tiempo | G12: Sueldo | H12: Parcial
E13: % | F13: (meses) | G13: (S/) | H13: (S/)
B14: Ingeniero Residente de la Obra | C14: Und. | D14: 1 | E14: 1 | F14: 10 | G14: 7500 | H14: =+ROUND(+G14*F14*D14*E14,2) -> 75000
B15: Ing. de Seguridad e Higiene Ocupacional | C15: Und. | D15: 1 | E15: 1 | F15: 6 | G15: 5500 | H15: =+ROUND(+G15*F15*D15*E15,2) -> 33000
B16: Ing. Especialista en Sistemas Fotovoltaicos | C16: Und. | D16: 1 | E16: 0.4 | F16: 6 | G16: 5500 | H16: =+ROUND(+G16*F16*D16*E16,2) -> 13200
B17: Ing. Especialista en Redes de Distribución | C17: Und. | D17: 1 | E17: 0.5 | F17: 6 | G17: 5500 | H17: =+ROUND(+G17*F17*D17*E17,2) -> 16500
B19: PARCIAL 1,1 | H19: =SUM(H14:H18) -> 137700
A22: 1.2 | B22: Personal de Auxiliar y Apoyo
B23: Descripción | C23: Und. | D23: Cant. | E23: Particip. | F23: Tiempo | G23: Sueldo | H23: Parcial
E24: % | F24: (meses) | G24: (S/) | H24: (S/)
B25: Administrador | C25: Und. | D25: 1 | E25: 0.8 | F25: 6 | G25: 3000 | H25: =+ROUND(+G25*F25*D25*E25,2) -> 14400
B26: Dibujante en Autocad y otros programas | C26: Und. | D26: 1 | E26: 0.5 | F26: 6 | G26: 1800 | H26: =+ROUND(+G26*F26*D26*E26,2) -> 5400
B27: Almacenero | C27: Und. | D27: 1 | E27: 0.8 | F27: 6 | G27: 1800 | H27: =+ROUND(+G27*F27*D27*E27,2) -> 8640
B28: Técnico mecánico | C28: Und. | D28: 1 | E28: 0.3 | F28: 6 | G28: 1800 | H28: =+ROUND(+G28*F28*D28*E28,2) -> 3240
B29: Chofer | C29: Und. | D29: 1 | E29: 1 | F29: 6 | G29: 1700 | H29: =+ROUND(+G29*F29*D29*E29,2) -> 10200
B30: Seguridad en obra (Guardian) | C30: Und. | D30: 1 | E30: 0.7 | F30: 6 | G30: 1500 | H30: =+ROUND(+G30*F30*D30*E30,2) -> 6300
B32: PARCIAL 1,2 | H32: =SUM(H25:H31) -> 48180
A35: 1.3 | B35: Hospedajes, Oficina, Campamentos, alimentación y movilidad del personal principal, auxiliar y apoyo
B36: Descripción | C36: Und. | D36: Cant. | E36: Particip. | F36: Tiempo | G36: Gasto/ Und. | H36: Parcial
E37: % | F37: (meses) | G37: (S/) | H37: (S/)
B38: Hospedajes | C38: Glb/mes | D38: 1 | E38: 1 | F38: 6 | G38: 1200 | H38: =+ROUND(+G38*F38*D38*E38,2) -> 7200
B39: Alquiler de Oficina en Obra (Incluye agua y luz) | C39: Glb/mes | D39: 1 | E39: 1 | F39: 6 | G39: 350 | H39: =+ROUND(+G39*F39*D39*E39,2) -> 2100
B40: Alquiler de casa almacén (incluye agua y luz) | C40: Glb/mes | D40: 1 | E40: 1 | F40: 6 | G40: 450 | H40: =+ROUND(+G40*F40*D40*E40,2) -> 2700
B41: Comunicaciones: telefono, fax, internet, radio, etc. | C41: Glb/mes | D41: 1 | E41: 1 | F41: 6 | G41: 550 | H41: =+ROUND(+G41*F41*D41*E41,2) -> 3300
B42: Alimentación | C42: Glb/mes | D42: 1 | E42: 1 | F42: 6 | G42: 1200 | H42: =+ROUND(+G42*F42*D42*E42,2) -> 7200
B43: Pasajes | C43: Glb/mes | D43: 1 | E43: 1 | F43: 6 | G43: 650 | H43: =+ROUND(+G43*F43*D43*E43,2) -> 3900
B45: PARCIAL 1,3 | H45: =SUM(H38:H44) -> 26400
A47: 1.4 | B47: Mobiliario, equipo, material de oficina y otros
B48: Descripción | C48: Und. | D48: Cant. | E48: Desgaste | F48: Tiempo | G48: Gasto/ Und.xmes | H48: Parcial
E49: % | F49: (meses) | G49: (S/) | H49: (S/)
B50: Mobiliario de oficina | C50: Glb/mes | D50: 1 | E50: 0.05 | F50: 6 | G50: 900 | H50: =+ROUND(G50*F50*E50*D50,2) -> 270
B51: Computadora | C51: Glb/mes | D51: 1 | E51: 0.05 | F51: 6 | G51: 900 | H51: =+ROUND(G51*F51*E51*D51,2) -> 270
B52: Impresora | C52: Glb/mes | D52: 1 | E52: 0.05 | F52: 6 | G52: 350 | H52: =+ROUND(G52*F52*E52*D52,2) -> 105
B53: Útiles de Oficina | C53: Glb/mes | D53: 1 | E53: 0.1 | F53: 6 | G53: 300 | H53: =+ROUND(G53*F53*E53*D53,2) -> 180
B54: Camioneta pick up (*) | C54: Glb/mes | D54: 1 | E54: 0.016666667 | F54: 6 | G54: 114763.5 | H54: =+ROUND(G54*F54*E54*D54,2) -> 11476.35
B55: Combustible | C55: Glb/mes | D55: 1 | E55: 1 | F55: 6 | G55: 650 | H55: =+ROUND(G55*F55*E55*D55,2) -> 3900
B56: Mantenimiento | C56: Glb/mes | D56: 1 | E56: 1 | F56: 6 | G56: 550 | H56: =+ROUND(G56*F56*E56*D56,2) -> 3300
B58: PARCIAL 1,4 | H58: =SUM(H50:H57) -> 19501.35
B60: (*) El desgaste de las camionetas ha sido calculado considerando una depreciación líneal en 60 meses de vida útil. - Fuente: SUNAT
A62: 1.5 | B62: Gastos financieros y otros gastos
B63: Descripción | C63: Und. | D63: Costo Directo | E63: % de CD | F63: Costo/mes | G63: Tiempo | H63: Parcial
D64: Obra (S/) | E64: al mes | F64: S/ | G64: (meses) | H64: S/
B65: Cartas Fianzas (incluye Comisión y costos por elaboración de cartas fianzas) | C65: Gbl | H65: 35494.32
B66: Seguros | C66: Gbl | H66: 5084.75
B67: PARCIAL 1,5 | H67: =SUM(H65:H66) -> 40579.07
B69: PARCIAL GASTOS GENERALES VARIABLES (1) | H69: =ROUND(+H67+H58+H45+H32+H19,2) -> 272360.42
A71: 2.0 | B71: GASTOS GENERALES FIJOS INDIRECTOS
A72: 2.1 | B72: Personal en la sede central de la Empresa
B74: Descripción | C74: Und. | D74: Cant. | E74: Participacion | F74: Gasto/ Und. | G74: Tiempo efectivo | H74: Total
E75: % | F75: S/ | G75: (meses) | H75: S/
B76: Gerente | C76: Und. | D76: 1 | E76: 0.05 | F76: 6000 | G76: 10 | H76: =+ROUND(+G76*F76*E76*D76,2) -> 3000
B77: Ingeniero-Supervisión Técnica Empresa | C77: Und. | D77: 1 | E77: 0.05 | F77: 5000 | G77: 10 | H77: =+ROUND(+G77*F77*E77*D77,2) -> 2500
B78: Contador | C78: Und. | D78: 1 | E78: 0.05 | F78: 3500 | G78: 10 | H78: =+ROUND(+G78*F78*E78*D78,2) -> 1750
B79: Auxiliar en Contabilidad | C79: Und. | D79: 1 | E79: 0.05 | F79: 2500 | G79: 10 | H79: =+ROUND(+G79*F79*E79*D79,2) -> 1250
B80: Secretaria | C80: Und. | D80: 1 | E80: 0.05 | F80: 1500 | G80: 10 | H80: =+ROUND(+G80*F80*E80*D80,2) -> 750
B81: Chofer | C81: Und. | D81: 1 | E81: 0.05 | F81: 1700 | G81: 10 | H81: =+ROUND(+G81*F81*E81*D81,2) -> 850
B82: PARCIAL 2,1 | H82: =SUM(H76:H81) -> 10100
A84: 2.2 | B84: Gastos de oficina principal y gastos varios
B85: Descripción | C85: Und. | D85: Cantidad | E85: Participacion | F85: Gasto/ Und. | G85: Tiempo efectivo | H85: Total
E86: % | F86: S/ | G86: (meses) | H86: S/
B87: Oficina (Incluye agua y luz) | C87: Und. | D87: 1 | E87: 0.05 | F87: 450 | G87: 10 | H87: =+ROUND(+G87*F87*E87*D87,2) -> 225
B88: Comunicaciones: telef., fax, Internet, radio | C88: Glob | D88: 1 | E88: 0.05 | F88: 400 | G88: 10 | H88: =+ROUND(+G88*F88*E88*D88,2) -> 200
B89: Material y Equipos de Oficina | C89: Glob | D89: 1 | E89: 0.05 | F89: 500 | G89: 10 | H89: =+ROUND(+G89*F89*E89*D89,2) -> 250
B90: Mantenimiento y limpieza | C90: Glob | D90: 1 | E90: 0.05 | F90: 500 | G90: 10 | H90: =+ROUND(+G90*F90*E90*D90,2) -> 250
B91: PARCIAL 2,2 | H91: =SUM(H87:H90) -> 925
A93: 2.3 | B93: Gastos de preparación de oferta e imprevistos
B94: Descripción | C94: Und. | D94: Cantidad | E94: % de CD | F94: Costo Directo | G94: Tiempo efectivo | H94: Parcial
F95: S/ | G95: (meses) | H95: S/
B96: Elaboración de propuesta | C96: Gbl | D96: 1 | E96: 0.0002 | F96: =+#REF! -> #REF! | G96: 1 | H96: =+ROUND(+G96*F96*E96*D96,2) -> #REF!
B97: Imprevistos de obra y personal en oficina central | C97: Gbl | D97: 1 | E97: 0.0002 | F97: =+F96 -> #REF! | G97: 1 | H97: =+ROUND(+G97*F97*E97*D97,2) -> #REF!
B98: PARCIAL 2,3 | H98: =+H97+H96 -> #REF!
A100: 2.4 | B100: Operación Experimental
B101: Descripción | C101: Und. | D101: Cant. | E101: Particip. | F101: Tiempo | G101: Sueldo | H101: Parcial
E102: % | F102: (meses) | G102: (S/) | H102: (S/)
B103: Ingeniero Residente de la Obra | C103: Unid. | D103: 1 | E103: 0.15 | F103: 1 | G103: 7500 | H103: =+ROUND(+G103*F103*E103*D103,2) -> 1125
B104: Operario | C104: Unid. | D104: 1 | E104: 0.15 | F104: 1 | G104: 1800 | H104: =+ROUND(+G104*F104*E104*D104,2) -> 270
B105: Alquiler de Camioneta pick up(Incluye Chofer y Combustible ) | C105: Unid. | D105: 1 | E105: 0.15 | F105: 1 | G105: 9000 | H105: =+ROUND(+G105*F105*E105*D105,2) -> 1350
B107: PARCIAL 2,4 | H107: =SUM(H103:H106) -> 2745
A109: 2.5 | B109: Registro de datos solicitados por la Empresa Concesionaria en Sistema GIS y Registro de Expediente por cada beneficiario, incluye prescinto de medidor y caja.
B110: Descripción | C110: Und. | D110: Cant. | E110: Particip. | F110: Tiempo | G110: Sueldo | H110: Parcial
E111: % | F111: (meses) | G111: (S/) | H111: (S/)
B112: Digitador incluye equipo de cómputo (conocimiento de software Maximus, GIS u otros) | C112: Unid. | D112: 1 | E112: 1 | F112: 0.8 | G112: 2714.08 | H112: =+ROUND(+G112*F112*E112*D112,2) -> 2171.26
B114: PARCIAL 2,5 | H114: =SUM(H112:H113) -> 2171.26
B115: PARCIAL GASTOS GENERALES FIJOS (2) | H115: =+ROUND(H98+H91+H82+H107+H114,2) -> #REF!
B117: TOTAL GASTOS GENERALES (1)+(2) | H117: =+H115+H69 -> #REF!
A119: 3.0 | B119: RESUMEN | H119: S/
B120: GASTOS GENERALES VARIABLES DIRECTOS | H120: =+H69 -> 272360.42
B121: GASTOS GENERALES FIJOS INDIRECTOS | H121: =+H115 -> #REF!
B122: TOTAL GASTOS GENERALES (1)+(2) | H122: =+H121+H120 -> #REF!

Sheet CRONOG_VALORIZ
B1: CRONOGRAMA DE DESEMBOLSOS MENSUALES DE OBRA
B3: PROYECTO | E3: : | F3: “AMPLIACIÓN DEL SERVICIO DE ENERGÍA ELÉCTRICA EN LA PROVINCIA DEL SANTA Y EN EL DISTRITO DE PAMPAROMAS – DEPARTAMENTO DE ANCASH”
B4: SECCION I, II y III | E4: : | F4: LINEAS PRIMARIAS, REDES PRIMARIAS Y REDES SECUNDARIAS
B5: DEPARTAMENTO | E5: : | F5: ANCASH
B6: PROVINCIA | E6: : | F6: HUAYLAS Y SANTA
B7: DISTRITO | E7: : | F7: VARIOS | Q7: Fecha: 30-Mayo-2022
H8: PERIODO DE ESTUDIO DEFINITIVO | L8: PERIODO DE OBRA
B9: ITEM | C9: DESCRIPCION | G9: TOTAL S/ | H9: MES 1 | I9: MES 2 | J9: MES 3 | K9: MES 4 | L9: MES 5 | M9: MES 6 | N9: MES 7 | O9: MES 8 | P9: MES 9 | Q9: MES 10
B11: A | D11: SUMINISTROS DE MATERIALES | G11: =+#REF! -> #REF! | L11: =+ROUND($G$11*L25,2) -> #REF! | M11: =+ROUND($G$11*M25,2) -> #REF! | N11: =+ROUND($G$11*N25,2) -> #REF! | O11: =+ROUND($G$11*O25,2) -> #REF! | P11: =+G11-L11-M11-N11-O11-Q11 -> #REF! | Q11: =+ROUND($G$11*Q25,2) -> #REF!
B12: B | D12: MONTAJE ELECTROMECANICO | G12: =+#REF! -> #REF! | L12: =+ROUND($G$12*L26,2) -> #REF! | M12: =+ROUND($G$12*M26,2) -> #REF! | N12: =+ROUND($G$12*N26,2) -> #REF! | O12: =+ROUND($G$12*O26,2) -> #REF! | P12: =+ROUND($G$12*P26,2) -> #REF! | Q12: =+G12-O12-N12-M12-L12-P12 -> #REF!
B13: C | D13: TRANSPORTE DE MATERIALES | G13: =+#REF! -> #REF! | L13: =+ROUND($G$13*L27,2) -> #REF! | M13: =+ROUND($G$13*M27,2) -> #REF! | N13: =+ROUND($G$13*N27,2) -> #REF! | O13: =+ROUND($G$13*O27,2) -> #REF! | P13: =+G13-L13-M13-N13-O13-Q13 -> #REF! | Q13: =+ROUND($G$13*Q27,2) -> #REF!
B15: D | D15: COSTO DIRECTO ( C.D. ) | G15: =+#REF! -> #REF! | L15: =SUM(L11:L13) -> #REF! | M15: =SUM(M11:M13) -> #REF! | N15: =SUM(N11:N13) -> #REF! | O15: =SUM(O11:O13) -> #REF! | P15: =SUM(P11:P13) -> #REF! | Q15: =SUM(Q11:Q13) -> #REF!
B17: E | F17: GASTOS GENERALES | G17: =+#REF! -> #REF! | L17: =+ROUND(L15*($G$17/$G$15),2) -> #REF! | M17: =+ROUND(M15*($G$17/$G$15),2) -> #REF! | N17: =+ROUND(N15*($G$17/$G$15),2) -> #REF! | O17: =+ROUND(O15*($G$17/$G$15),2) -> #REF! | P17: =+ROUND(P15*($G$17/$G$15),2) -> #REF! | Q17: =+G17-O17-N17-M17-L17-P17 -> #REF!
B18: F | F18: UTILIDADES | G18: =+#REF! -> #REF! | L18: =+ROUND(L15*0.08,2) -> #REF! | M18: =+ROUND(M15*0.08,2) -> #REF! | N18: =+ROUND(N15*0.08,2) -> #REF! | O18: =+ROUND(O15*0.08,2) -> #REF! | P18: =+ROUND(P15*0.08,2) -> #REF! | Q18: =+G18-O18-N18-M18-L18-P18 -> #REF!
D21: =+"SUB-TOTAL SIN I.G.V. (S/)" -> SUB-TOTAL SIN I.G.V. (S/) | G21: =+#REF! -> #REF! | L21: =SUM(L15:L18) -> #REF! | M21: =SUM(M15:M18) -> #REF! | N21: =SUM(N15:N18) -> #REF! | O21: =SUM(O15:O18) -> #REF! | P21: =SUM(P15:P18) -> #REF! | Q21: =SUM(Q15:Q18) -> #REF!
D23: IMPUESTO GENERAL A LAS VENTAS IGV (18%) | G23: =+#REF! -> #REF! | L23: =+ROUND(L21*0.18,2) -> #REF! | M23: =+ROUND(M21*0.18,2) -> #REF! | N23: =+ROUND(N21*0.18,2) -> #REF! | O23: =+ROUND(O21*0.18,2) -> #REF! | P23: =+ROUND(P21*0.18,2) -> #REF! | Q23: =+G23-L23-M23-N23-O23-P23 -> #REF!
D24: COSTO TOTAL OBRA (Incluye I.G.V.) | G24: =+#REF! -> #REF! | L24: =SUM(L21:L23) -> #REF! | M24: =SUM(M21:M23) -> #REF! | N24: =SUM(N21:N23) -> #REF! | O24: =SUM(O21:O23) -> #REF! | P24: =SUM(P21:P23) -> #REF! | Q24: =SUM(Q21:Q23) -> #REF!
G25: SUMINISTROS | L25: 0 | M25: 0.255 | N25: 0.36 | O25: 0.335 | P25: 0.05
G26: MONTAJE | L26: 0.15 | M26: 0.2 | N26: 0.25 | O26: 0.15 | P26: 0.15 | Q26: 0.1
G27: TRANSPORTE | L27: 0 | M27: =+M25 -> 0.255 | N27: =+N25 -> 0.36 | O27: =+O25 -> 0.335 | P27: =+P25 -> 0.05

Sheet EXPED-TECNICO
D4: ANALISIS DE COSTOS PARA CONTRATACION DE LA ELABORACION DEL
D5: ESTUDIO DEFINITIVO DEL PROYECTO
D6: “AMPLIACION DEL SISTEMA ELECTRICO RURAL EN LA PROVINCIA DEL SANTA Y EN EL DISTRITO DE PAMPAROMAS - DEPARTAMENTO DE ANCASH”
D9: A. | E9: COSTO DE PERSONAL
D12: A1 | E12: COSTO DE PERSONAL PROFESIONAL
I13: PLAZO : | J13: 4 | K13: MESES
G14: PROFES. | H14: INCIDENCIA | I14: REMUNERACIÓN | J14: TIEMPO | K14: TOTAL
E15: CATEGORIA | G15: ASIGNADO | H15: (c) | I15: Total/mes (7) | J15: EFECTIVO | K15: HONORARIOS
G16: (b) | H16: % | I16: S/ (d) | J16: (Meses) (e)=(a)*(c) | K16: S/ (f)=(b)*(d)*(e)
E18: ESTUDIOS ELECTROMECANICOS
D19: A | E19: Jefe de Estudios | G19: 1 | H19: 1 | I19: 7000 | J19: =+ROUND(+H19*$J$13,2) -> 4 | K19: =+ROUND(I19*J19*G19,2) -> 28000 | M19: =+N199 -> 0
D20: B | E20: Epecialista en Análisis y Diseños de Líneas y Redes Primarias | G20: 1 | H20: 0.5 | I20: 6000 | J20: =+ROUND(+H20*$J$13,1) -> 2 | K20: =+ROUND(I20*J20*G20,2) -> 12000
D21: C | E21: Especialista en Analisis de Sistemas Electricos y Estudio de Coordinación de la Protección | G21: 1 | H21: 0.25 | I21: 6000 | J21: =+ROUND(+H21*$J$13,1) -> 1 | K21: =+ROUND(I21*J21*G21,2) -> 6000
D22: D | E22: Especialista en Analisis y Diseños de Redes Secundarias | G22: 1 | H22: 0.5 | I22: 6000 | J22: =+ROUND(+H22*$J$13,1) -> 2 | K22: =+ROUND(I22*J22*G22,2) -> 12000
D23: E | E23: Especialista en Energias Renovables - Sistemas Fotovoltaicos | G23: 1 | H23: 0.25 | I23: 5000 | J23: =+ROUND(+H23*$J$13,1) -> 1 | K23: =+ROUND(I23*J23*G23,2) -> 5000
D24: F | E24: Especialista en Trabajos Geológicos, Geotécnicos y Diseño de Cimentaciones | G24: 1 | H24: 0.25 | I24: 5000 | J24: =+ROUND(+H24*$J$13,1) -> 1 | K24: =+ROUND(I24*J24*G24,2) -> 5000
D25: G | E25: Especialista en Estudios de Impacto Ambiental | G25: 1 | H25: 0.3753 | I25: 5000 | J25: =+ROUND(+H25*$J$13,1) -> 1.5 | K25: =+ROUND(I25*J25*G25,2) -> 7500
D26: H | E26: Arqueologo, Especialista en Proyectos de Electrificacion | G26: 1 | H26: 0.25 | I26: 5000 | J26: =+ROUND(+H26*$J$13,1) -> 1 | K26: =+ROUND(I26*J26*G26,2) -> 5000
D27: I | E27: Especialista en Gestion de Riesgos | G27: 1 | H27: 0.25 | I27: 5000 | J27: =+ROUND(+H27*$J$13,1) -> 1 | K27: =+ROUND(I27*J27*G27,2) -> 5000
G29: =SUM(G19:G28) -> 9 | I29: COSTO DE PERSONAL | K29: =SUM(K19:K28) -> 85500
D32: A2 | E32: COSTO DE PERSONAL AUXILIAR
G34: PERSONAL | I34: SUELDO | J34: TIEMPO | K34: TOTAL
E35: DESCRIPCION | G35: ASIGNADO | H35: INCIDENCIA | I35: Total/mes | J35: EFECTIVO | K35: HONORARIOS
I36: S/ | J36: (Meses) | K36: S/
E37: Ingenieros Asistentes para labores de Gabinete | G37: =G20 -> 1 | H37: 0.5 | I37: 3500 | J37: =+ROUND(+H37*$J$13,1) -> 2 | K37: =+ROUND(I37*J37*G37,2) -> 7000
E38: Secretaria | G38: 1 | H38: 0.35 | I38: 2000 | J38: =+ROUND(+H38*$J$13,1) -> 1.4 | K38: =+ROUND(I38*J38*G38,2) -> 2800
E39: Dibujantes en Autocad | G39: 1 | H39: 0.5 | I39: 2500 | J39: =+ROUND(+H39*$J$13,2) -> 2 | K39: =+ROUND(I39*J39*G39,2) -> 5000
E40: Personal de campo no calificado | G40: 5 % de A1 | K40: =+ROUND(K29*0.05,2) -> 4275
I42: COSTO PERS. AUXILIAR | K42: =SUM(K37:K40) -> 19075
D43: NOTA | E43: LA REMUNERACIÓN INCLUYE LEYES SOCIALES.
F46: COSTO TOTAL DE PERSONAL (A1 + A2) | J46: S/ | K46: =+K42+K29 -> 104575
D50: ANALISIS DE COSTOS PARA CONTRATACION DE LA ELABORACION DEL
D51: ESTUDIO DEFINITIVO DEL PROYECTO
D52: =+D6 -> “AMPLIACION DEL SISTEMA ELECTRICO RURAL EN LA PROVINCIA DEL SANTA Y EN EL DISTRITO DE PAMPAROMAS - DEPARTAMENTO DE ANCASH”
D56: B | E56: TRABAJOS TOPOGRAFICOS PARA EL DISEÑO TÉCNICO DEL PROYECTO Y REPLANTEO DE OBRA
D59: B1 | E59: LEVANTAMIENTO TOPOGRAFIO DE LINEAS DE MEDIA TENSION (INCLUYE TRABAJOS DE GABINETE)
H61: COSTO POR km DE LINEA DE M.T. | K61: 450
E63: LONGITUD DE LINEA DE MEDIA TENSIÓN | I63: 22.95 | J63: km
H64: SUB TOTAL B1 | J64: S/ | K64: =ROUND(+I63*K61,2) -> 10327.5
D67: B2 | E67: LEVANTAMIENTO TOPOGRAFICO PARA ELABORACION DE PLANOS CATASTRALES (INCLUYE TRABAJOS DE GABINETE)
H70: COSTO POR LOC. | K70: 420
E72: NÚMERO DE LOCALIDADES | I72: 30 | J72: LOCALIDADES
E73: COSTO TOTAL DE LEVANTAMIENTO Y ELABORACIÓN DE PLANOS PLANOS CATASTRALES | J73: S/ | K73: =+I72*K70 -> 12600
D76: B | E76: TOTAL TOPOGRAFIA PARA DISEÑO TÉCNICO DEL PROYECTO (B1 + B2) | K76: =+K73+K64 -> 22927.5
D83: C | E83: GASTOS PRINCIPALES PARA DESARROLLO DE LOS ESTUDIOS
D87: C1 | E87: VIATICOS Y ALOJAMIENTO DE PROFESIONALES
E89: DESCRIPCION | G89: ASIGN./DIA | I89: NUMERO | J89: SUBTOTAL
G90: S/ | I90: DIAS | J90: S/
E91: Alimentación | G91: 50 | I91: 20 | J91: =+G91*I91 -> 1000
E92: Alojamiento | G92: 80 | I92: =+I91 -> 20 | J92: =+G92*I92 -> 1600
I93: SUB TOTAL C1 | K93: =SUM(J91:J92) -> 2600
D96: C2 | E96: VEHICULO, COMBUSTIBLE y OTROS ASIGNADOS A PROFESIONALES EN CAMPO
G98: ASIGN./DIA | I98: NUMERO | J98: SUBTOTAL
G99: S/ | I99: DIAS | J99: S/
E100: Alquiler de vehiculo 4x4, incluye chofer | G100: 300 | I100: 20 | J100: =+G100*I100 -> 6000
E101: Combustibe y lubricante | G101: 200 | I101: 20 | J101: =+G101*I101 -> 4000
E102: Otros equipos y materiales de campo ( 2 % de A1) | J102: =+ROUND(+K29*2/100,2) -> 1710
I103: SUB TOTAL C2 | K103: =SUM(J100:J102) -> 11710
D106: C3 | E106: OTROS GASTOS
D108: ITEM | G108: Unidad | H108: Cant. | I108: P.Unit. | J108: Sub Total
I109: S/ | J109: S/
D110: 1 | E110: Movilidad y Equipos -Incluye Operador (1) | K110: =SUM(J111:J113) -> 4289.72
E111: Movilidad local (1 Und.) | G111: Global | H111: 1 | I111: 1633.99 | J111: =+H111*I111 -> 1633.99
E112: Equipo Medición de resistividad de terreno | G112: Global | H112: 1 | I112: 1395.03 | J112: =+H112*I112 -> 1395.03 | N112: =+N199 -> 0
E113: Equipos GPS Navegadores de Alta Precisión | G113: Global | H113: 1 | I113: 1260.7 | J113: =+H113*I113 -> 1260.7
D115: 2 | E115: Calicatas,Analisis de Muestras y otros | K115: =SUM(J116:J122) -> 16792.68
D116: =0.1+D115 -> 2.1 | E116: - Comprende desplazamiento toma de muestras y | G116: Und. | H116: 6 | I116: 1390.13 | J116: =ROUND(H116*I116,2) -> 8340.78
E117: Análisis en Laboratorio: Capacidad Portante, angulo de fricción, granulometría, | G117: -
E118: peso volumen, contenido de sales y sulfatos. (Según requerimiento de los TDR) | G118: -
D119: =0.1+D116 -> 2.2 | E119: - Construcción y monumentación de hitos de acuerdo a requerimientos | G119: Und. | H119: 58 | I119: 95.3 | J119: =ROUND(H119*I119,2) -> 5527.4
E120: de especicifación técnica de la DGE/MEM
D121: =0.1+D119 -> 2.3 | E121: ¨- Padron Final de Usuarios | G121: Glb | H121: 1 | I121: 2924.5 | J121: =ROUND(H121*I121,2) -> 2924.5
D123: 3 | E123: Pasajes a la Lima - Obra - Lima | K123: =SUM(J124:J124) -> 4497.85
D124: =0.1+D123 -> 3.1 | E124: Viajes vía terrestre | G124: Und. | H124: 7 | I124: 642.55 | J124: =ROUND(H124*I124,2) -> 4497.85
D126: 4 | E126: Mediciones de Parametros Ambientales Basicos para DIA | K126: =SUM(J127:J131) -> 5880
D127: =0.1+D126 -> 4.1 | E127: Parametros de calidad de aire | G127: Global | H127: 1 | I127: 1400 | J127: =ROUND(+H127*I127,2) -> 1400
D128: =0.1+D127 -> 4.2 | E128: Niveles de Ruido | G128: Global | H128: 1 | I128: 1400 | J128: =ROUND(+H128*I128,2) -> 1400
D129: =0.1+D128 -> 4.3 | E129: Radiaciones Electromagneticas | G129: Global | H129: 1 | I129: 1400 | J129: =ROUND(+H129*I129,2) -> 1400
D130: =0.1+D129 -> 4.4 | E130: Calidad de Agua Superficial | G130: Global | H130: 1 | I130: 1400 | J130: =ROUND(+H130*I130,2) -> 1400
D131: =0.1+D130 -> 4.5 | E131: Materiales menores (5% de Mediciones de Parametros) | G131: Global | H131: 0.05 | I131: =+SUM(J127:J130) -> 5600 | J131: =ROUND(+H131*I131,2) -> 280
D133: 5 | E133: Documentaciones y Utiles | K133: =SUM(J134:J141) -> 5407.5
D134: =0.1+D133 -> 5.1 | E134: Bases, notaría,etc | G134: Glb. | H134: 1 | I134: 950 | J134: =ROUND(H134*I134,29) -> 950
D135: =0.1+D134 -> 5.2 | E135: Papel para textos | G135: Glb. | H135: 1 | I135: 900 | J135: =ROUND(H135*I135,29) -> 900
D136: =0.1+D135 -> 5.3 | E136: Papel para planos | G136: Glb. | H136: 1 | I136: 650 | J136: =ROUND(H136*I136,29) -> 650
D137: =0.1+D136 -> 5.4 | E137: Fotocopia de textos, planos y láminas | G137: Glb. | H137: 1 | I137: 750 | J137: =ROUND(H137*I137,29) -> 750
D138: =0.1+D137 -> 5.5 | E138: Registros fotográficos digitalizado e impreso | G138: Glb. | H138: 1 | I138: 600 | J138: =ROUND(H138*I138,29) -> 600
D139: =0.1+D138 -> 5.6 | E139: Cartas IGN 1/100 000 (Incluye juego de copias) | G139: Glb. | H139: 1 | I139: 650 | J139: =ROUND(H139*I139,29) -> 650
D140: =0.1+D139 -> 5.7 | E140: Cartas IGN 1/25 000 (Incluye juego de copias) | G140: Glb. | H140: 1 | I140: 650 | J140: =ROUND(H140*I140,29) -> 650
D141: =0.1+D140 -> 5.8 | E141: Otros utiles (5 % Documentos y Utiles) | G141: % | H141: 0.05 | I141: =SUM(J134:J140) -> 5150 | J141: =ROUND(H141*I141,29) -> 257.5
I143: SUB TOTAL C3 | K143: =SUM(K110:K142) -> 36867.75
D144: NOTAS | E144: (1) INCLUYE EL COSTO DEL OPERADOR
D147: C | E147: TOTAL GASTOS PRINCIPALES PARA DESARROLLO DEL ESTUDIO (D1 +D2 + D3) | J147: S/ | K147: =+K143+K103+K93 -> 51177.75
D152: D | E152: GASTOS GENERALES
D156: D1 | E156: GASTOS GENERALES
E158: DESCRIPCION | G158: Unidad | H158: Costo Directo | I158: % Costo Directo | J158: Sub Total
H159: S/ | I159: S/ | J159: S/
E160: Gastos Generales | G160: Global | H160: =+$K$186 -> 178680.25 | I160: 0.07 | J160: =ROUND(H160*I160,2) -> 12507.62
I161: SUB TOTAL D1 | K161: =SUM(J160:J160) -> 12507.62
D165: D | E165: TOTAL GASTOS GENERALES (D1 + D2) | J165: S/ | K165: =+K161 -> 12507.62
D169: VALOR REFERENCIAL
...

Sheet RESUMEN LP
B2: VALOR REFERENCIAL
B3: LINEAS PRIMARIAS
B4: “AMPLIACIÓN DEL SERVICIO DE ENERGÍA ELÉCTRICA EN LA PROVINCIA DEL SANTA Y EN EL DISTRITO DE PAMPAROMAS – DEPARTAMENTO DE ANCASH”
B6: UBICACIÓN | D6: : | E6: ANCASH
B7: SECCIÓN I | D7: : | E7: LINEAS PRIMARIAS
F8: =+#REF! -> #REF!
F9: =+#REF! -> #REF!
B10: ITEM | C10: DESCRIPCION | F10: TOTAL S/
B12: A | D12: SUMINISTRO DE MATERIALES | F12: =+'SUMINISTRO LP'!J129 -> 628325.26
B13: B | D13: MONTAJE ELECTROMECANICO | F13: =+'MONTAJE LP'!J130 -> 461491.17
B14: C | D14: TRANSPORTE DE MATERIALES | F14: =+TRANS_LP!J130 -> 60052.8 | G14: =+F14/F12 -> 0.095575976
B15: D | D15: TOTAL COSTO DIRECTO | F15: =SUM(F12:F14) -> 1149869.2
B17: E | E17: GASTOS GENERALES | F17: =+ROUND(F15*H17,2) -> #REF! | H17: =+#REF! -> #REF!
B18: F | E18: UTILIDADES | F18: =+ROUND(F15*H18,2) -> #REF! | H18: =+#REF! -> #REF!
D20: COSTO TOTAL S/ (No incluye I.G.V.) | F20: =SUM(F15:F18) -> #REF! | H20: =F20=#REF! -> #REF!

Sheet Alternativa-LP
B3: ="RESUMEN DEL VALOR REFERENCIAL " -> RESUMEN DEL VALOR REFERENCIAL
B5: UBICACIÓN | D5: :
B6: SECCIÓN I | D6: :
B9: ITEM | C9: DESCRIPCION | F9: TOTAL (S/.)
I10: =F11*0.07 -> 43982.768
B11: A | D11: SUMINISTROS DE MATERIALES | F11: =+'RESUMEN LP'!F12 -> 628325.26 | I11: =F11*0.1 -> 62832.526
D12: Origen Nacional | F12: =+F11-F13 -> 315414.07
D13: Origen Importado | F13: =+'SUMINISTRO LP'!J25+'SUMINISTRO LP'!J36+'SUMINISTRO LP'!J40+'SUMINISTRO LP'!J44+'SUMINISTRO LP'!J62+'SUMINISTRO LP'!J116+'SUMINISTRO LP'!J120 -> 312911.19
B15: B | D15: MONTAJE ELECTROMECANICO | F15: =+'RESUMEN LP'!F13 -> 461491.17 | H15: =+F15/$F$11 -> 0.73447814
D16: M.O. Calificada | F16: =ROUND(N16*F15,2) -> 290739.44 | N16: 0.63
D17: M.O. No Calificada | F17: =ROUND(N17*F15,2) -> 170751.73 | N17: =1-N16 -> 0.37
B19: B.1 | D19: ACTIVIDADES COMPLEMENTARIAS DE MONTAJE | F19: 0
B21: C | D21: TRANSPORTE DE MATERIALES | F21: =+'RESUMEN LP'!F14 -> 60052.8 | H21: 0.1
B24: D | D24: TOTAL COSTO DIRECTO (C.D.) | F24: =+F21+F15+F11+F19 -> 1149869.2

Sheet SUMINISTRO LP
B1: VALOR REFERENCIAL
B2: SUMINISTRO DE MATERIALES LÍNEAS PRIMARIAS
B3: UBICACIÓN | E3: : | F3: ANCASH
B4: SECCIÓN I | E4: : | F4: LÍNEAS PRIMARIAS
B5: A: SUMINISTRO DE MATERIALES
B7: Item | C7: Descripción de Partidas | G7: Unid. | H7: Metrado Cant. | I7: Costo Unitario | J7: SubTotal S/
D9: LINEAS PRIMARIAS
B11: 1 | D11: CRUCETAS DE MADERA DE PROCEDENCIA NACIONAL
B12: =+B11+0.01 -> 1.01 | D12: Cruceta de madera tratada de 90 mm x 115 mm x 1,20 m | G12: u | H12: 11 | I12: 105 | J12: =+ROUND(I12*H12,2) -> 1155 | L12: =IFERROR(VLOOKUP(D12,#REF!,2,FALSE),"")
B13: =+B12+0.01 -> 1.02 | D13: Cruceta de madera tratada de 90 mm x 115 mm x 2,00 m | G13: u | H13: 2 | I13: 178 | J13: =+ROUND(I13*H13,2) -> 356 | L13: =IFERROR(VLOOKUP(D13,#REF!,2,FALSE),"")
B14: =+B13+0.01 -> 1.03 | D14: Cruceta de madera tratada de 90 mm x 115 mm x 2,40 m | G14: u | H14: 1 | I14: 205 | J14: =+ROUND(I14*H14,2) -> 205 | L14: =IFERROR(VLOOKUP(D14,#REF!,2,FALSE),"")
B15: =+B14+0.01 -> 1.04 | D15: Listón de madera tratada 50 x 19 mm sección, 2,7 m longitud (incluye clavos de fijación) | G15: u | H15: 9 | I15: 27.35 | J15: =+ROUND(I15*H15,2) -> 246.15 | L15: =IFERROR(VLOOKUP(D15,#REF!,2,FALSE),"")
F16: =+"SUB-TOTAL "&B11&": " -> SUB-TOTAL 1: | J16: =SUM(J12:J15) -> 1962.15 | L16: =IFERROR(VLOOKUP(D16,#REF!,2,FALSE),"")
B17: 2 | D17: POSTES DE CONCRETO ARMADO CENTRIFUGADO | L17: =IFERROR(VLOOKUP(D17,#REF!,2,FALSE),"")
B18: =+B17+0.01 -> 2.01 | D18: Poste de C.A.C. de 12 m/200 daN (Incluye perilla) | G18: u | H18: 15 | I18: 837.45 | J18: =+ROUND(I18*H18,2) -> 12561.75 | L18: =IFERROR(VLOOKUP(D18,#REF!,2,FALSE),"")
B19: =+B18+0.01 -> 2.02 | D19: Poste de C.A.C. de 12 m/300 daN (Incluye perilla) | G19: u | H19: 6 | I19: 923.47 | J19: =+ROUND(I19*H19,2) -> 5540.82 | L19: =IFERROR(VLOOKUP(D19,#REF!,2,FALSE),"")
B20: =+B19+0.01 -> 2.03 | D20: Poste de C.A.C. de 13 m/300 daN (Incluye perilla) | G20: u | H20: 118 | I20: 1085.14 | J20: =+ROUND(I20*H20,2) -> 128046.52 | L20: =IFERROR(VLOOKUP(D20,#REF!,2,FALSE),"")
B21: =+B20+0.01 -> 2.04 | D21: Poste de C.A.C. de 13 m/400 daN (Incluye perilla) | G21: u | H21: 32 | I21: 1207.94 | J21: =+ROUND(I21*H21,2) -> 38654.08 | L21: =IFERROR(VLOOKUP(D21,#REF!,2,FALSE),"")
F22: =+"SUB-TOTAL "&B17&": " -> SUB-TOTAL 2: | J22: =SUM(J18:J21) -> 184803.17 | L22: =IFERROR(VLOOKUP(D22,#REF!,2,FALSE),"")
B23: 3 | D23: POSTES DE MADERA IMPORTADA | L23: =IFERROR(VLOOKUP(D23,#REF!,2,FALSE),"")
B24: =+B23+0.01 -> 3.01 | D24: Poste de madera importada (Pino Amarillo del Sur) de 12 m, Clase 6 | G24: u | H24: 9 | I24: 1703.39 | J24: =+ROUND(I24*H24,2) -> 15330.51 | L24: =IFERROR(VLOOKUP(D24,#REF!,2,FALSE),"")
F25: =+"SUB-TOTAL "&B23&": " -> SUB-TOTAL 3: | J25: =+SUM(J24) -> 15330.51 | L25: =IFERROR(VLOOKUP(D25,#REF!,2,FALSE),"")
B26: 4 | D26: OTROS MATERIALES DE CONCRETO ARMADO | L26: =IFERROR(VLOOKUP(D26,#REF!,2,FALSE),"")
B27: =+B26+0.01 -> 4.01 | D27: Cruceta Asimétrica de C.A.V. Za / 1,5 / 0,9 / 250 / 200 / 100 daN (Za / L / L1/ T / F / V) | G27: u | H27: 2 | I27: 120.3 | J27: =+ROUND(I27*H27,2) -> 240.6 | L27: =IFERROR(VLOOKUP(D27,#REF!,2,FALSE),"")
B28: =+B27+0.01 -> 4.02 | D28: Ménsula de C.A.V. M / 1,2 / 250 / 150 / 150 daN (M / L / T / F / V) | G28: u | H28: 393 | I28: 88.8 | J28: =+ROUND(I28*H28,2) -> 34898.4 | L28: =IFERROR(VLOOKUP(D28,#REF!,2,FALSE),"")
B29: =+B28+0.01 -> 4.03 | D29: Ménsula de C.A.V. M / 0,8 / 250 / 150 / 150 daN (M / L / T / F / V) | G29: u | H29: 1 | I29: 92.26 | J29: =+ROUND(I29*H29,2) -> 92.26 | L29: =IFERROR(VLOOKUP(D29,#REF!,2,FALSE),"")
F30: =+"SUB-TOTAL "&B26&": " -> SUB-TOTAL 4: | J30: =SUM(J27:J29) -> 35231.26 | L30: =IFERROR(VLOOKUP(D30,#REF!,2,FALSE),"")
B31: =1+B26 -> 5 | D31: AISLADORES Y ACCESORIOS | L31: =IFERROR(VLOOKUP(D31,#REF!,2,FALSE),"")
B32: =+B31+0.01 -> 5.01 | D32: Aislador de Porcelana Tipo Pin, Clase ANSI 56-3 | G32: u | H32: 29 | I32: 76.45 | J32: =+ROUND(I32*H32,2) -> 2217.05 | L32: =IFERROR(VLOOKUP(D32,#REF!,2,FALSE),"")
B33: =+B32+0.01 -> 5.02 | D33: Espiga de AºGº de 609 mm longitud, para Cabeza de Poste y Aislador ANSI 56-3 | G33: u | H33: 29 | I33: 35.96 | J33: =+ROUND(I33*H33,2) -> 1042.84 | L33: =IFERROR(VLOOKUP(D33,#REF!,2,FALSE),"")
B34: =+B33+0.01 -> 5.03 | D34: Conjunto Aislador Line Post Polimérico en Mesula y Cruceta: | L34: =IFERROR(VLOOKUP(D34,#REF!,2,FALSE),"")
D35: - Aislador Polimérico de 36 kV, Tipo Line Post con Espárrago de 19 mm Ø, 200 mm longitud (Alternativa a Conjunto Aislador-Espiga en Cruceta) | G35: u | H35: 369 | I35: 209.65 | J35: =+ROUND(I35*H35,2) -> 77360.85 | L35: =IFERROR(VLOOKUP(D35,#REF!,2,FALSE),"")
F36: =+"SUB-TOTAL "&B31&": " -> SUB-TOTAL 5: | J36: =+SUM(J31:J35) -> 80620.74 | L36: =IFERROR(VLOOKUP(D36,#REF!,2,FALSE),"")
B37: =1+B31 -> 6 | D37: AISLADORES DE SUSPENSION Y ACCESORIOS | L37: =IFERROR(VLOOKUP(D37,#REF!,2,FALSE),"")
B38: =0.01+B37 -> 6.01 | D38: Grillete Recto | G38: u | H38: 155 | I38: 17.76 | J38: =+ROUND(I38*H38,2) -> 2752.8 | L38: =IFERROR(VLOOKUP(D38,#REF!,2,FALSE),"")
B39: =0.01+B38 -> 6.02 | D39: Aislador Polimerico con Conexión Horquilla (Estructura) y Lengüeta (Linea) de 36 kV, según Especificacion Técnica. | G39: u | H39: 155 | I39: 76.66 | J39: =+ROUND(I39*H39,2) -> 11882.3 | L39: =IFERROR(VLOOKUP(D39,#REF!,2,FALSE),"")
F40: =+"SUB-TOTAL "&B37&": " -> SUB-TOTAL 6: | J40: =SUM(J38:J39) -> 14635.1 | L40: =IFERROR(VLOOKUP(D40,#REF!,2,FALSE),"")
B41: =1+B37 -> 7 | D41: CONDUCTOR DE ALEACIÓN DE ALUMINIO | L41: =IFERROR(VLOOKUP(D41,#REF!,2,FALSE),"")
B42: =+B41+0.01 -> 7.01 | D42: Conductor de Aleacion de Aluminio de 35 mm² | G42: km | H42: 53.4 | I42: 2249.62 | J42: =+ROUND(I42*H42,2) -> 120129.71 | L42: =IFERROR(VLOOKUP(D42,#REF!,2,FALSE),"")
B43: =+B42+0.01 -> 7.02 | D43: Conductor de Aleacion de Aluminio de 70 mm² | G43: km | H43: 1.91 | I43: 4157 | J43: =+ROUND(I43*H43,2) -> 7939.87 | L43: =IFERROR(VLOOKUP(D43,#REF!,2,FALSE),"")
F44: =+"SUB-TOTAL "&B41&": " -> SUB-TOTAL 7: | J44: =SUM(J42:J43) -> 128069.58 | L44: =IFERROR(VLOOKUP(D44,#REF!,2,FALSE),"")
B45: =1+B41 -> 8 | D45: ACCESORIOS PARA CONDUCTOR DE ALEACION DE ALUMINIO | L45: =IFERROR(VLOOKUP(D45,#REF!,2,FALSE),"")
B46: =+B45+0.01 -> 8.01 | D46: Varilla de Armar preformada Simple para Conductor de 35 mm² | G46: u | H46: 326 | I46: 10.19 | J46: =+ROUND(I46*H46,2) -> 3321.94 | L46: =IFERROR(VLOOKUP(D46,#REF!,2,FALSE),"")
B47: =+B46+0.01 -> 8.02 | D47: Varilla de Armar preformada Simple para Conductor de 70 mm² | G47: u | H47: 2 | I47: 17.38 | J47: =+ROUND(I47*H47,2) -> 34.76 | L47: =IFERROR(VLOOKUP(D47,#REF!,2,FALSE),"")
B48: =+B47+0.01 -> 8.03 | D48: Manguito de Empalme para Conductor de 35 mm² | G48: u | H48: 17 | I48: 12.11 | J48: =+ROUND(I48*H48,2) -> 205.87 | L48: =IFERROR(VLOOKUP(D48,#REF!,2,FALSE),"")
B49: =+B48+0.01 -> 8.04 | D49: Manguito de Reparacion para Conductor de 35 mm² | G49: u | H49: 7 | I49: 11.59 | J49: =+ROUND(I49*H49,2) -> 81.13 | L49: =IFERROR(VLOOKUP(D49,#REF!,2,FALSE),"")
B50: =+B49+0.01 -> 8.05 | D50: Grapa de Doble Via de Aluminio para Conductor de 35 mm² | G50: u | H50: 84 | I50: 7.77 | J50: =+ROUND(I50*H50,2) -> 652.68 | L50: =IFERROR(VLOOKUP(D50,#REF!,2,FALSE),"")
B51: =+B50+0.01 -> 8.06 | D51: Grapa de Doble Via de Aluminio para Conductor de 70 mm² | G51: u | H51: 2 | I51: 10.36 | J51: =+ROUND(I51*H51,2) -> 20.72 | L51: =IFERROR(VLOOKUP(D51,#REF!,2,FALSE),"")
B52: =+B51+0.01 -> 8.07 | D52: Alambre de Amarre Aluminio Recocido de 16 mm² | G52: m | H52: 1052.3 | I52: 1.41 | J52: =+ROUND(I52*H52,2) -> 1483.74 | L52: =IFERROR(VLOOKUP(D52,#REF!,2,FALSE),"")
B53: =+B52+0.01 -> 8.08 | D53: Amortiguador de Vibracion Tipo Stockbridge para Conductor de 35 mm² | G53: u | H53: 4 | I53: 36.01 | J53: =+ROUND(I53*H53,2) -> 144.04 | L53: =IFERROR(VLOOKUP(D53,#REF!,2,FALSE),"")
B54: =+B53+0.01 -> 8.09 | D54: Amortiguador de Vibracion Tipo Stockbridge para Conductor de 70 mm² | G54: u | H54: 8 | I54: 44.34 | J54: =+ROUND(I54*H54,2) -> 354.72 | L54: =IFERROR(VLOOKUP(D54,#REF!,2,FALSE),"")
B55: =+B54+0.01 -> 8.1 | D55: Grapa de Angulo para Conductor de 35 mm² | G55: u | H55: 14 | I55: 29.37 | J55: =+ROUND(I55*H55,2) -> 411.18 | L55: =IFERROR(VLOOKUP(D55,#REF!,2,FALSE),"")
B56: =+B55+0.01 -> 8.11 | D56: Grapa de Angulo para Conductor de 70 mm² | G56: u | H56: 4 | I56: 47.48 | J56: =+ROUND(I56*H56,2) -> 189.92 | L56: =IFERROR(VLOOKUP(D56,#REF!,2,FALSE),"")
B57: =+B56+0.01 -> 8.12 | D57: Grapa de Anclaje para Conductor de 35 mm² | G57: u | H57: 129 | I57: 25.34 | J57: =+ROUND(I57*H57,2) -> 3268.86 | L57: =IFERROR(VLOOKUP(D57,#REF!,2,FALSE),"")
B58: =+B57+0.01 -> 8.13 | D58: Grapa de Anclaje para Conductor de 70 mm² | G58: u | H58: 8 | I58: 49.03 | J58: =+ROUND(I58*H58,2) -> 392.24 | L58: =IFERROR(VLOOKUP(D58,#REF!,2,FALSE),"")
F59: =+"SUB-TOTAL "&B45&": " -> SUB-TOTAL 8: | J59: =SUM(J46:J58) -> 10561.8 | L59: =IFERROR(VLOOKUP(D59,#REF!,2,FALSE),"")
B60: =1+B45 -> 9 | D60: CONDUCTOR DE COBRE | L60: =IFERROR(VLOOKUP(D60,#REF!,2,FALSE),"")
B61: =+B60+0.01 -> 9.01 | D61: Cable de Acero con Recubrimiento Metalúrgico de Cu de 4 AWG (21,15 mm²), para Puesta a Tierra | G61: m | H61: 2936.1 | I61: 12.8 | J61: =+ROUND(I61*H61,2) -> 37582.08 | L61: =IFERROR(VLOOKUP(D61,#REF!,2,FALSE),"")
F62: =+"SUB-TOTAL "&B60&": " -> SUB-TOTAL 9: | J62: =+SUM(J61:J61) -> 37582.08 | L62: =IFERROR(VLOOKUP(D62,#REF!,2,FALSE),"")
B63: =1+B60 -> 10 | D63: MATERIAL DE FERRETERIA PARA POSTES Y CRUCETAS | L63: =IFERROR(VLOOKUP(D63,#REF!,2,FALSE),"")
B64: =+B63+0.01 -> 10.01 | D64: Perno Cabeza Coche de AºGº de 13 mm Ø x 152 mm longitud, 76 mm maquinado, con Arandela, Tuerca y Contratuerca | G64: u | H64: 9 | I64: 3.86 | J64: =+ROUND(I64*H64,2) -> 34.74 | L64: =IFERROR(VLOOKUP(D64,#REF!,2,FALSE),"")
B65: =+B64+0.01 -> 10.02 | D65: Perno de A°G° de 13 mm Ø x 254 mm, provisto de Tuerca y Contratuerca | G65: u | H65: 26 | I65: 5.57 | J65: =+ROUND(I65*H65,2) -> 144.82 | L65: =IFERROR(VLOOKUP(D65,#REF!,2,FALSE),"")
B66: =+B65+0.01 -> 10.03 | D66: Perno de A°G° de 13 mm Ø x 305 mm, provisto de Tuerca y Contratuerca | G66: u | H66: 7 | I66: 6.25 | J66: =+ROUND(I66*H66,2) -> 43.75 | L66: =IFERROR(VLOOKUP(D66,#REF!,2,FALSE),"")
B67: =+B66+0.01 -> 10.04 | D67: Perno de A°G° de 16 mm Ø x 254 mm, provisto de Tuerca y Contratuerca | G67: u | H67: 18 | I67: 8.61 | J67: =+ROUND(I67*H67,2) -> 154.98 | L67: =IFERROR(VLOOKUP(D67,#REF!,2,FALSE),"")
B68: =+B67+0.01 -> 10.05 | D68: Perno de A°G° de 16 mm Ø x 305 mm, provisto de Tuerca y Contratuerca | G68: u | H68: 18 | I68: 9.14 | J68: =+ROUND(I68*H68,2) -> 164.52 | L68: =IFERROR(VLOOKUP(D68,#REF!,2,FALSE),"")
B69: =+B68+0.01 -> 10.06 | D69: Perno de A°G° de 16 mm Ø x 356 mm, provisto de Tuerca y Contratuerca | G69: u | H69: 8 | I69: 9.82 | J69: =+ROUND(I69*H69,2) -> 78.56 | L69: =IFERROR(VLOOKUP(D69,#REF!,2,FALSE),"")
B70: =+B69+0.01 -> 10.07 | D70: Perno de A°G° de 16 mm Ø x 508 mm, provisto de Tuerca y Contratuerca | G70: u | H70: 3 | I70: 12.54 | J70: =+ROUND(I70*H70,2) -> 37.62 | L70: =IFERROR(VLOOKUP(D70,#REF!,2,FALSE),"")
B71: =+B70+0.01 -> 10.08 | D71: Perno Doble Armado de A°G° de 16 mm Ø x 508 mm, provisto de 4 Tuercas y 4 Contratuercas | G71: u | H71: 380 | I71: 18.18 | J71: =+ROUND(I71*H71,2) -> 6908.4 | L71: =IFERROR(VLOOKUP(D71,#REF!,2,FALSE),"")
B72: =+B71+0.01 -> 10.09 | D72: Perno Ojo de A°G° de 16 mm Ø x 254 mm, provisto de Tuerca y Contratuerca | G72: u | H72: 61 | I72: 13.11 | J72: =+ROUND(I72*H72,2) -> 799.71 | L72: =IFERROR(VLOOKUP(D72,#REF!,2,FALSE),"")
B73: =+B72+0.01 -> 10.1 | D73: Perno Ojo de A°G° de 16 mm Ø x 305 mm, provisto de Tuerca y Contratuerca | G73: u | H73: 47 | I73: 14.35 | J73: =+ROUND(I73*H73,2) -> 674.45 | L73: =IFERROR(VLOOKUP(D73,#REF!,2,FALSE),"")
B74: =+B73+0.01 -> 10.11 | D74: Perno Ojo de A°G° de 16 mm Ø x 356 mm, provisto de Tuerca y Contratuerca | G74: u | H74: 9 | I74: 14.6 | J74: =+ROUND(I74*H74,2) -> 131.4 | L74: =IFERROR(VLOOKUP(D74,#REF!,2,FALSE),"")
B75: =+B74+0.01 -> 10.12 | D75: Tuerca-Ojo para Perno de 16 mm Ø | G75: u | H75: 38 | I75: 11.17 | J75: =+ROUND(I75*H75,2) -> 424.46 | L75: =IFERROR(VLOOKUP(D75,#REF!,2,FALSE),"")
... B83: =+B82+0.01 -> 10.2 | D83: Placa de Secuencia de Fases y accesorios de fijación | G83: u | H83: 9 | I83: 18.78 | J83: =+ROUND(I83*H83,2) -> 169.02 | L83: =IFERROR(VLOOKUP(D83,#REF!,2,FALSE),"")
F84: =+"SUB-TOTAL "&B63&": " -> SUB-TOTAL 10: | J84: =SUM(J64:J83) -> 13536.76 | L84: =IFERROR(VLOOKUP(D84,#REF!,2,FALSE),"")
B85: =1+B63 -> 11 | D85: RETENIDAS Y ANCLAJES | L85: =IFERROR(VLOOKUP(D85,#REF!,2,FALSE),"")
B86: =+B85+0.01 -> 11.01 | D86: Cable de Acero Grado Siemens Martin, de 10 mm Ø, 7 hilos | G86: m | H86: 881 | I86: 4.31 | J86: =+ROUND(I86*H86,2) -> 3797.11 | L86: =IFERROR(VLOOKUP(D86,#REF!,2,FALSE),"")
B87: =+B86+0.01 -> 11.02 | D87: Varilla de Anclaje de A°G° de 16 mm Ø x 2,40 m, provisto de Ojal Guardacabo en un extremo; Tuerca y Contratuerca en el otro | G87: u | H87: 66 | I87: 46.85 | J87: =+ROUND(I87*H87,2) -> 3092.1 | L87: =IFERROR(VLOOKUP(D87,#REF!,2,FALSE),"")
B88: =+B87+0.01 -> 11.03 | D88: Mordaza Preformada de A°G° para Cable de 10 mm Ø | G88: u | H88: 208 | I88: 11.69 | J88: =+ROUND(I88*H88,2) -> 2431.52 | L88: =IFERROR(VLOOKUP(D88,#REF!,2,FALSE),"")
B89: =+B88+0.01 -> 11.04 | D89: Alambre de Acero N° 14 para Entorchado | G89: m | H89: 312 | I89: 0.71 | J89: =+ROUND(I89*H89,2) -> 221.52 | L89: =IFERROR(VLOOKUP(D89,#REF!,2,FALSE),"")
B90: =+B89+0.01 -> 11.05 | D90: Arandela de Anclaje de A°G°, 102 x 102 x 6,35 mm, Agujero de 18 mmø | G90: u | H90: 66 | I90: 5.46 | J90: =+ROUND(I90*H90,2) -> 360.36 | L90: =IFERROR(VLOOKUP(D90,#REF!,2,FALSE),"")
B91: =+B90+0.01 -> 11.06 | D91: Soporte de Contrapunta de 51 mm ø x 1200 mm de longitud, con Abrazadera partida en un extremo y Grapa de Ajuste para Cable en el otro | G91: u | H91: 12 | I91: 112.06 | J91: =+ROUND(I91*H91,2) -> 1344.72 | L91: =IFERROR(VLOOKUP(D91,#REF!,2,FALSE),"")
B92: =+B91+0.01 -> 11.07 | D92: Abrazadera de 4 sectores para Retenida, de 75 mm de altura, 6,35 mm de espesor y 70 kN de resistencia. Diámetro según dimensiones del poste, incluye 4 pernos de 12,7 mm Ø x 63,5 mm y 4 arandelas | G92: u | H92: 66 | I92: 81.85 | J92: =+ROUND(I92*H92,2) -> 5402.1 | L92: =IFERROR(VLOOKUP(D92,#REF!,2,FALSE),"")
B93: =+B92+0.01 -> 11.08 | D93: Enlace metálico, de 254 mm x 75 mm x 38 mm, de 70 kN de resistencia | G93: u | H93: 66 | I93: 28.99 | J93: =+ROUND(I93*H93,2) -> 1913.34 | L93: =IFERROR(VLOOKUP(D93,#REF!,2,FALSE),"")
B94: =+B93+0.01 -> 11.09 | D94: Aislador Polimerico con Conexión Horquilla (Estructura) y Lengüeta (Linea) de 36 kV, según Especificacion Técnica, para Retenida Aislada. | G94: u | H94: 66 | I94: 76.66 | J94: =+ROUND(I94*H94,2) -> 5059.56 | L94: =IFERROR(VLOOKUP(D94,#REF!,2,FALSE),"")
B95: =+B94+0.01 -> 11.1 | D95: Grillete de Acero de 70 kN | G95: u | H95: 85 | I95: 15.01 | J95: =+ROUND(I95*H95,2) -> 1275.85 | L95: =IFERROR(VLOOKUP(D95,#REF!,2,FALSE),"")
B96: =+B95+0.01 -> 11.11 | D96: Bloque de Concreto de 0,40 x 0,40 x 0,15 m | G96: u | H96: 66 | I96: 40.94 | J96: =+ROUND(I96*H96,2) -> 2702.04 | L96: =IFERROR(VLOOKUP(D96,#REF!,2,FALSE),"")
B97: =+B96+0.01 -> 11.12 | D97: Tuerca-Ojo para Perno de 16 mm Ø | G97: u | H97: 22 | I97: 11.17 | J97: =+ROUND(I97*H97,2) -> 245.74 | L97: =IFERROR(VLOOKUP(D97,#REF!,2,FALSE),"")
B98: =+B97+0.01 -> 11.13 | D98: Arandela Cuadrada Plana de A° G°, 57 x 57 x 5 mm, Agujero de 18 mm Ø | G98: u | H98: 39 | I98: 1.67 | J98: =+ROUND(I98*H98,2) -> 65.13 | L98: =IFERROR(VLOOKUP(D98,#REF!,2,FALSE),"")
F99: =+"SUB-TOTAL "&B85&": " -> SUB-TOTAL 11: | J99: =SUM(J86:J98) -> 27911.09 | L99: =IFERROR(VLOOKUP(D99,#REF!,2,FALSE),"")
B100: =1+B85 -> 12 | D100: MATERIAL PARA PUESTA A TIERRA | L100: =IFERROR(VLOOKUP(D100,#REF!,2,FALSE),"")
B101: =+B100+0.01 -> 12.01 | D101: Electrodo de Acero Recubierto de Cobre de 16 mm Ø x 2,40 m | G101: u | H101: 15 | I101: 66.7 | J101: =+ROUND(I101*H101,2) -> 1000.5 | L101: =IFERROR(VLOOKUP(D101,#REF!,2,FALSE),"")
B102: =+B101+0.01 -> 12.02 | D102: Plancha Doblada de Cobre para toma a Tierra de Espigas y/o Pernos | G102: u | H102: 518 | I102: 10.54 | J102: =+ROUND(I102*H102,2) -> 5459.72 | L102: =IFERROR(VLOOKUP(D102,#REF!,2,FALSE),"")
B103: =+B102+0.01 -> 12.03 | D103: Conector de Bronce para Electrodo de 16 mm ø y Cable de Acero con Recubrimiento Metalúrgico de Cobre de 4 AWG (21,15 mm2) | G103: u | H103: 15 | I103: 6.94 | J103: =+ROUND(I103*H103,2) -> 104.1 | L103: =IFERROR(VLOOKUP(D103,#REF!,2,FALSE),"")
B104: =+B103+0.01 -> 12.04 | D104: Conector de Cobre tipo Perno Partido para Cable de Acero con Recubrimiento Metalúrgico de Cobre de 4 AWG (21,15 mm2) | G104: u | H104: 428 | I104: 7.4 | J104: =+ROUND(I104*H104,2) -> 3167.2 | L104: =IFERROR(VLOOKUP(D104,#REF!,2,FALSE),"")
B105: =+B104+0.01 -> 12.05 | D105: Caja Registro de Concreto para Puesta a Tierra 0,50 x 0,50 x 0,45 m | G105: u | H105: 15 | I105: 53.58 | J105: =+ROUND(I105*H105,2) -> 803.7 | L105: =IFERROR(VLOOKUP(D105,#REF!,2,FALSE),"")
B106: =+B105+0.01 -> 12.06 | D106: Grapa en "U" para fijar conductor de PAT a Madera | G106: u | H106: 204 | I106: 0.47 | J106: =+ROUND(I106*H106,2) -> 95.88 | L106: =IFERROR(VLOOKUP(D106,#REF!,2,FALSE),"")
B107: =+B106+0.01 -> 12.07 | D107: Placa de Señalización de Poste (Puesta a Tierra) | G107: u | H107: 2 | I107: 17.43 | J107: =+ROUND(I107*H107,2) -> 34.86 | L107: =IFERROR(VLOOKUP(D107,#REF!,2,FALSE),"")
B108: =+B107+0.01 -> 12.08 | D108: Plantilla para Señalización de Poste (Puesta a Tierra) | G108: u | H108: 6 | I108: 16.25 | J108: =+ROUND(I108*H108,2) -> 97.5 | L108: =IFERROR(VLOOKUP(D108,#REF!,2,FALSE),"")
B109: =+B108+0.01 -> 12.09 | D109: Tubo Plastico de PVC SAP de 19 mm ø x 0,5 m ( incluye curva de plastico de 19 mm ø x 90º) | G109: u | H109: 180 | I109: 2.39 | J109: =+ROUND(I109*H109,2) -> 430.2 | L109: =IFERROR(VLOOKUP(D109,#REF!,2,FALSE),"")
F110: =+"SUB-TOTAL "&B100&": " -> SUB-TOTAL 12: | J110: =SUM(J101:J109) -> 11193.66 | L110: =IFERROR(VLOOKUP(D110,#REF!,2,FALSE),"")
...

Sheet MONTAJE LP
B1: VALOR REFERENCIAL
B2: MONTAJE ELECTROMECÁNICO DE LÍNEAS PRIMARIAS
B3: UBICACIÓN | E3: : | F3: ANCASH
B4: SECCIÓN I | E4: : | F4: LÍNEAS PRIMARIAS
B5: B: MONTAJE ELECTROMECÁNICO
B7: Item | C7: Descripción de Partidas | G7: Unid. | H7: Metrado Cant. | I7: Costo Unitario | J7: SubTotal S/ | L7: Costo Unitario | M7: 0.9
B9: 1 | D9: OBRAS PRELIMINARES
B10: =B9+0.01 -> 1.01 | D10: Estudio de Coordinación de la Protección y Balance de Cargas | G10: Global | H10: 1 | I10: 5182.52 | J10: =+ROUND(I10*H10,2) -> 5182.52 | L10: 5758.36 | M10: =+ROUND(L10*$M$7,2) -> 5182.52
B11: =B10+0.01 -> 1.02 | D11: Monitoreo e Inspección del Ministerio de Cultura ( Incluye Líneas Primarias, Redes Primarias, Redes Secundarias y SFV ) | G11: Global | H11: 1 | I11: 7070.38 | J11: =+ROUND(I11*H11,2) -> 7070.38 | L11: 7855.98 | M11: =+ROUND(L11*$M$7,2) -> 7070.38
B12: =B11+0.01 -> 1.03 | D12: Programa de Monitoreo Ambiental (Incluye Línea Primarias, Red Primaria, Red Secundaria y SFV) | G12: Global | H12: 1 | I12: 4953.82 | J12: =+ROUND(I12*H12,2) -> 4953.82 | K12: =+#REF! -> #REF! | L12: 5735.13 | M12: =+ROUND(L12*$M$7,2) -> 5161.62
B13: =B12+0.01 -> 1.04 | D13: Programa de Manejo de Residuos | G13: Global | H13: 1 | I13: 5429.3 | J13: =+ROUND(I13*H13,2) -> 5429.3 | K13: =+#REF! -> #REF! | L13: 6280 | M13: =+ROUND(L13*$M$7,2) -> 5652
B14: =B13+0.01 -> 1.05 | D14: Programa de Talleres de Información y de Medidas Preventivas y/o Correctivas | G14: Global | H14: 1 | I14: 1947.8 | J14: =+ROUND(I14*H14,2) -> 1947.8 | L14: 2151.58 | M14: =+ROUND(L14*$M$7,2) -> 1936.42
B15: =B14+0.01 -> 1.06 | D15: Cartel para Obra | G15: u | H15: 1 | I15: 1703.1 | J15: =+ROUND(I15*H15,2) -> 1703.1 | L15: 1892.33 | M15: =+ROUND(L15*$M$7,2) -> 1703.1
B16: =B15+0.01 -> 1.07 | D16: Despeje de Árboles Dentro de la Franja de Servidumbre | G16: Ha | H16: 0.68 | I16: 2340.59 | J16: =+ROUND(I16*H16,2) -> 1591.6 | L16: 2600.66 | M16: =+ROUND(L16*$M$7,2) -> 2340.59
B17: =B16+0.01 -> 1.08 | D17: Elaboración del Expediente Técnico Sustentatorio de Gestión de Servidumbre (1original + 3copias). Incluye Levantamiento Topografico, y presentacion digitalizada del Expediente | G17: km | H17: 22.95 | I17: 585.06 | J17: =+ROUND(I17*H17,2) -> 13427.13 | L17: 716.73 | M17: =+ROUND(L17*$M$7,2) -> 645.06
F18: =+"SUB-TOTAL "&B9&": " -> SUB-TOTAL 1: | J18: =+SUM(J8:J17) -> 41305.65
B19: 2 | D19: TRANSPORTE DE MATERIALES DE ALMACEN EN OBRA A PUNTO DE INSTALACIÒN
B20: =+B19+0.01 -> 2.01 | D20: Transporte de Poste de 12 m/200 daN de Almacen a Punto de Izaje, en Terreno con Acceso Carrozable | G20: u | H20: 14 | I20: 247.05 | J20: =+ROUND(I20*H20,2) -> 3458.7 | L20: 274.5 | M20: =+ROUND(L20*$M$7,2) -> 247.05
B21: =+B20+0.01 -> 2.02 | D21: Transporte de Poste de 12 m/200 daN de Almacen a Punto de Izaje, en Terreno sin Acceso Carrozable (< 1000 m) | G21: u | H21: 1 | I21: 375.26 | J21: =+ROUND(I21*H21,2) -> 375.26 | L21: 416.95 | M21: =+ROUND(L21*$M$7,2) -> 375.26
B22: =+B21+0.01 -> 2.03 | D22: Transporte de Poste de 12 m/300 daN de Almacen a Punto de Izaje, en Terreno con Acceso Carrozable | G22: u | H22: 5 | I22: 270.59 | J22: =+ROUND(I22*H22,2) -> 1352.95 | L22: 300.66 | M22: =+ROUND(L22*$M$7,2) -> 270.59
B23: =+B22+0.01 -> 2.04 | D23: Transporte de Poste de 12 m/300 daN de Almacen a Punto de Izaje, en Terreno sin Acceso Carrozable (< 1000 m) | G23: u | H23: 1 | I23: 416.46 | J23: =+ROUND(I23*H23,2) -> 416.46 | L23: 462.73 | M23: =+ROUND(L23*$M$7,2) -> 416.46
B24: =+B23+0.01 -> 2.05 | D24: Transporte de Poste de 13 m/300 daN de Almacen a Punto de Izaje, en Terreno con Acceso Carrozable | G24: u | H24: 118 | I24: 301.46 | J24: =+ROUND(I24*H24,2) -> 35572.28 | L24: 334.95 | M24: =+ROUND(L24*$M$7,2) -> 301.46
B25: =+B24+0.01 -> 2.06 | D25: Transporte de Poste de 13 m/400 daN de Almacen a Punto de Izaje, en Terreno con Acceso Carrozable | G25: u | H25: 32 | I25: 338.24 | J25: =+ROUND(I25*H25,2) -> 10823.68 | L25: 375.82 | M25: =+ROUND(L25*$M$7,2) -> 338.24
B26: =+B25+0.01 -> 2.07 | D26: Transporte de Poste de madera importada (Pino Amarillo del Sur) de 12m, Clase 6 de Almacen a Punto de Izaje, en Terreno con Acceso Carrozable | G26: u | H26: 2 | I26: 176.17 | J26: =+ROUND(I26*H26,2) -> 352.34 | L26: 195.74 | M26: =+ROUND(L26*$M$7,2) -> 176.17
B27: =+B26+0.01 -> 2.08 | D27: Transporte de Poste de madera importada (Pino Amarillo del Sur) de 12m, Clase 6 de Almacen a Punto de Izaje, en Terreno sin Acceso Carrozable (< 1000 m) | G27: u | H27: 7 | I27: 244.71 | J27: =+ROUND(I27*H27,2) -> 1712.97 | L27: 271.9 | M27: =+ROUND(L27*$M$7,2) -> 244.71
B28: =+B27+0.01 -> 2.09 | D28: Transporte de Cruceta de madera tratada de 90 mm x 115 mm x 1,20 m, de Almacen a Punto de Instalaciòn en Terreno con Acceso Carrozable | G28: u | H28: 10 | I28: 5.43 | J28: =+ROUND(I28*H28,2) -> 54.3 | L28: 6.03 | M28: =+ROUND(L28*$M$7,2) -> 5.43
B29: =+B28+0.01 -> 2.1 | D29: Transporte de Cruceta de madera tratada de 90 mm x 115 mm x 1,20 m, de Almacen a Punto de Instalaciòn en Terreno sin Acceso Carrozable (< 1000 m) | G29: u | H29: 1 | I29: 7.06 | J29: =+ROUND(I29*H29,2) -> 7.06 | L29: 7.84 | M29: =+ROUND(L29*$M$7,2) -> 7.06
B30: =+B29+0.01 -> 2.11 | D30: Transporte de Ménsula de C.A.V y Cruceta Asimétrica de C.A.V, de Almacen a Punto de Instalaciòn en Terreno con Acceso Carrozable | G30: u | H30: 396 | I30: 13.3 | J30: =+ROUND(I30*H30,2) -> 5266.8 | L30: 14.78 | M30: =+ROUND(L30*$M$7,2) -> 13.3
B31: =+B30+0.01 -> 2.12 | D31: Transporte de Cruceta de madera tratada de 90 mm x 115 mm x 2,40 m y 2,00 m, de Almacen a Punto de Instalaciòn en Terreno con Acceso Carrozable | G31: u | H31: 3 | I31: 13.1 | J31: =+ROUND(I31*H31,2) -> 39.3 | L31: 14.56 | M31: =+ROUND(L31*$M$7,2) -> 13.1
... B54: =+B53+0.01 -> 2.35 | D54: Transporte de Accesorios de Ferreteria (Para Postes , conductores, Retenidas y PAT) de Almacen a Punto de Instalaciòn sin Acceso Carrozable (< 1000 m) | G54: Global | H54: 1 | I54: 2275.69 | J54: =+ROUND(I54*H54,2) -> 2275.69 | L54: 2528.54 | M54: =+ROUND(L54*$M$7,2) -> 2275.69
F55: =+"SUB-TOTAL "&B19&": " -> SUB-TOTAL 2: | J55: =+SUM(J19:J54) -> 82420.02
B56: 3 | D56: INSTALACION DE POSTES
B57: =+B56+0.01 -> 3.01 | D57: Excavación en Terreno Tipo I (Arcilloso y Conglomerado) | H57: 190.59 | I57: 61.15 | J57: =+ROUND(I57*H57,2) -> 11654.58 | L57: 67.94 | M57: =+ROUND(L57*$M$7,2) -> 61.15
B58: =+B57+0.01 -> 3.02 | D58: Excavación en Terreno Tipo II (Rocoso) | H58: 6.55 | I58: 208.14 | J58: =+ROUND(I58*H58,2) -> 1363.32 | L58: 231.27 | M58: =+ROUND(L58*$M$7,2) -> 208.14
B59: =+B58+0.01 -> 3.03 | D59: Izaje, Identificación y/o codificación, y Señalización de Poste de madera importada de 12 m, Clase 6 (*) | G59: u | H59: 9 | I59: 95.92 | J59: =+ROUND(I59*H59,2) -> 863.28 | L59: 106.58 | M59: =+ROUND(L59*$M$7,2) -> 95.92
B60: =+B59+0.01 -> 3.04 | D60: Izaje, Identificación y/o codificación, y Señalización de Poste de 13 m/300 daN (*) | G60: u | H60: 118 | I60: 154.07 | J60: =+ROUND(I60*H60,2) -> 18180.26 | L60: 171.19 | M60: =+ROUND(L60*$M$7,2) -> 154.07
B61: =+B60+0.01 -> 3.05 | D61: Izaje, Identificación y/o codificación, y Señalización de Poste de 13 m/400 daN (*) | G61: u | H61: 32 | I61: 194.85 | J61: =+ROUND(I61*H61,2) -> 6235.2 | L61: 216.5 | M61: =+ROUND(L61*$M$7,2) -> 194.85
B62: =+B61+0.01 -> 3.06 | D62: Izaje, Identificación y/o codificación, y Señalización de Poste de 12 m/300 daN (*) | G62: u | H62: 6 | I62: 128.47 | J62: =+ROUND(I62*H62,2) -> 770.82 | L62: 142.74 | M62: =+ROUND(L62*$M$7,2) -> 128.47
B63: =+B62+0.01 -> 3.07 | D63: Izaje, Identificación y/o codificación, y Señalización de Poste de 12 m/200 daN (*) | G63: u | H63: 15 | I63: 123.37 | J63: =+ROUND(I63*H63,2) -> 1850.55 | L63: 137.08 | M63: =+ROUND(L63*$M$7,2) -> 123.37
B64: =+B63+0.01 -> 3.08 | D64: Relleno y Compactación para cimentación de Poste 12m, en Terreno Tipo I (Arcilloso y Conglomerado) | H64: 19.7 | I64: 109.4 | J64: =+ROUND(I64*H64,2) -> 2155.18 | L64: 121.56 | M64: =+ROUND(L64*$M$7,2) -> 109.4
B65: =+B64+0.01 -> 3.09 | D65: Relleno y Compactación para cimentación de Poste 12m, en Terreno Tipo II (Rocoso) | H65: 5.11 | I65: 115.42 | J65: =+ROUND(I65*H65,2) -> 589.8 | L65: 128.24 | M65: =+ROUND(L65*$M$7,2) -> 115.42
B66: =+B65+0.01 -> 3.1 | D66: Cimentación con Concreto Ciclópeo de Poste de 13m en Terreno Tipo I (Arcilloso y Conglomerado) | G66: u | H66: 143 | I66: 279.45 | J66: =+ROUND(I66*H66,2) -> 39961.35 | L66: 310.5 | M66: =+ROUND(L66*$M$7,2) -> 279.45
B67: =+B66+0.01 -> 3.11 | D67: Cimentación con Concreto Ciclópeo de Poste de 13m en Terreno Tipo II (Rocoso) | G67: u | H67: 7 | I67: 270.54 | J67: =+ROUND(I67*H67,2) -> 1893.78 | L67: 300.6 | M67: =+ROUND(L67*$M$7,2) -> 270.54
B68: =+B67+0.01 -> 3.12 | D68: Solado para poste de concreto (e=0.10 m. C:H, 1:8) | G68: u | H68: 150 | I68: 25.38 | J68: =+ROUND(I68*H68,2) -> 3807 | L68: 28.2 | M68: =+ROUND(L68*$M$7,2) -> 25.38
F69: =+"SUB-TOTAL "&B56&": " -> SUB-TOTAL 3: | J69: =+SUM(J56:J68) -> 89325.12
B70: 4 | D70: INSTALACION DE RETENIDAS
B71: =+B70+0.01 -> 4.01 | D71: Excavación en Terreno Tipo I (Arcilloso y Conglomerado) | H71: 69.44 | I71: 61.15 | J71: =+ROUND(I71*H71,2) -> 4246.26 | L71: 67.94 | M71: =+ROUND(L71*$M$7,2) -> 61.15
B72: =+B71+0.01 -> 4.02 | D72: Excavación en Terreno Tipo II (Rocoso) | H72: 4.48 | I72: 208.14 | J72: =+ROUND(I72*H72,2) -> 932.47 | L72: 231.27 | M72: =+ROUND(L72*$M$7,2) -> 208.14
B73: =+B72+0.01 -> 4.03 | D73: Instalación de Retenida Inclinada | G73: u | H73: 36 | I73: 87.45 | J73: =+ROUND(I73*H73,2) -> 3148.2 | L73: 97.17 | M73: =+ROUND(L73*$M$7,2) -> 87.45
B74: =+B73+0.01 -> 4.04 | D74: Instalación de Retenida Inclinada en Y | G74: u | H74: 18 | I74: 103.71 | J74: =+ROUND(I74*H74,2) -> 1866.78 | L74: 115.23 | M74: =+ROUND(L74*$M$7,2) -> 103.71
B75: =+B74+0.01 -> 4.05 | D75: Instalación de Retenida Vertical | G75: u | H75: 11 | I75: 96.37 | J75: =+ROUND(I75*H75,2) -> 1060.07 | L75: 107.08 | M75: =+ROUND(L75*$M$7,2) -> 96.37
B76: =+B75+0.01 -> 4.06 | D76: Instalación de Retenida Vertical en Y | G76: u | H76: 1 | I76: 114.54 | J76: =+ROUND(I76*H76,2) -> 114.54 | L76: 127.27 | M76: =+ROUND(L76*$M$7,2) -> 114.54
B77: =+B76+0.01 -> 4.07 | D77: Relleno y Compactación en Terreno Tipo I de Retenida | H77: 68.2 | I77: 90.22 | J77: =+ROUND(I77*H77,2) -> 6153 | L77: 100.24 | M77: =+ROUND(L77*$M$7,2) -> 90.22
B78: =+B77+0.01 -> 4.08 | D78: Relleno y Compactación en Terreno Tipo II de Retenida | H78: 4.4 | I78: 96.57 | J78: =+ROUND(I78*H78,2) -> 424.91 | L78: 107.3 | M78: =+ROUND(L78*$M$7,2) -> 96.57
F79: =+"SUB-TOTAL "&B70&": " -> SUB-TOTAL 4: | J79: =+SUM(J70:J78) -> 17946.23
B80: 5 | D80: MONTAJE DE ARMADOS
B81: =+B80+0.01 -> 5.01 | D81: Armado PS1-0 (0°-5°) Monofasico retorno por tierra | G81: Jgo. | H81: 2 | I81: 61.22 | J81: =+ROUND(I81*H81,2) -> 122.44 | L81: 68.02 | M81: =+ROUND(L81*$M$7,2) -> 61.22
B82: =+B81+0.01 -> 5.02 | D82: Armado PA2-0 (30°-60°) Monofásico retorno por tierra | G82: Jgo. | H82: 1 | I82: 57.34 | J82: =+ROUND(I82*H82,2) -> 57.34 | L82: 63.71 | M82: =+ROUND(L82*$M$7,2) -> 57.34
B83: =+B82+0.01 -> 5.03 | D83: Armado PR3-0 Anclaje Monofásico retorno por tierra | G83: Jgo. | H83: 11 | I83: 66.02 | J83: =+ROUND(I83*H83,2) -> 726.22 | L83: 73.35 | M83: =+ROUND(L83*$M$7,2) -> 66.02
B84: =+B83+0.01 -> 5.04 | D84: Armado TS-0 Soporte de Retención, monofásico, retorno por tierra | G84: Jgo. | H84: 9 | I84: 80.37 | J84: =+ROUND(I84*H84,2) -> 723.33 | L84: 89.3 | M84: =+ROUND(L84*$M$7,2) -> 80.37
B85: =+B84+0.01 -> 5.05 | D85: Armado Tipo PSVE-3M Soporte de suspensión vertical 0° a 10° trifásico | G85: Jgo. | H85: 80 | I85: 102.97 | J85: =+ROUND(I85*H85,2) -> 8237.6 | L85: 114.41 | M85: =+ROUND(L85*$M$7,2) -> 102.97
B86: =+B85+0.01 -> 5.06 | D86: Armado DS-0 Soporte derivación no tensada monofásico sin neutro | G86: Jgo. | H86: 7 | I86: 31.21 | J86: =+ROUND(I86*H86,2) -> 218.47 | L86: 34.68 | M86: =+ROUND(L86*$M$7,2) -> 31.21
B87: =+B86+0.01 -> 5.07 | D87: Armado DS-2 Soporte derivación no tensada bifásico sin neutro | G87: Jgo. | H87: 1 | I87: 95.86 | J87: =+ROUND(I87*H87,2) -> 95.86 | L87: 106.51 | M87: =+ROUND(L87*$M$7,2) -> 95.86
B88: =+B87+0.01 -> 5.08 | D88: Armado DS-3 Soporte derivación tensada trifásico sin neutro | G88: Jgo. | H88: 1 | I88: 110.21 | J88: =+ROUND(I88*H88,2) -> 110.21 | L88: 122.46 | M88: =+ROUND(L88*$M$7,2) -> 110.21
B89: =+B88+0.01 -> 5.09 | D89: Armado PSVE-2 Soporte de suspensión vertical 0° a 10° bifásico sin neutro | G89: Jgo. | H89: 33 | I89: 50.37 | J89: =+ROUND(I89*H89,2) -> 1662.21 | L89: 55.97 | M89: =+ROUND(L89*$M$7,2) -> 50.37
B90: =+B89+0.01 -> 5.1 | D90: Armado TSVE-2M Sopte. Retención, susp. vertical, bifasico | G90: Jgo. | H90: 9 | I90: 118.56 | J90: =+ROUND(I90*H90,2) -> 1067.04 | L90: 131.73 | M90: =+ROUND(L90*$M$7,2) -> 118.56
B91: =+B90+0.01 -> 5.11 | D91: Armado TSECVE-3PM Soporte Secc. 3ø,retorno p/ tierra c | G91: Jgo. | H91: 1 | I91: 138.79 | J91: =+ROUND(I91*H91,2) -> 138.79 | L91: 154.21 | M91: =+ROUND(L91*$M$7,2) -> 138.79
B92: =+B91+0.01 -> 5.12 | D92: Armado TSEC-0P Soporte Secc. 1ø,retorno p/ tierra c/ Pararrayos | G92: Jgo. | H92: 7 | I92: 91.04 | J92: =+ROUND(I92*H92,2) -> 637.28 | L92: 101.15 | M92: =+ROUND(L92*$M$7,2) -> 91.04
... B102: =+B101+0.01 -> 5.22 | D102: Armado TSVE-3M Soporte . 3ø,retorno p/ tierra c | G102: Jgo. | H102: 3 | I102: 127.07 | J102: =+ROUND(I102*H102,2) -> 381.21 | L102: 141.19 | M102: =+ROUND(L102*$M$7,2) -> 127.07
F103: =+"SUB-TOTAL "&B80&": " -> SUB-TOTAL 5: | J103: =+SUM(J81:J102) -> 17271.58
B104: 6 | D104: MONTAJE DE CONDUCTORES
B105: =+B104+0.01 -> 6.01 | D105: Tendido y Puesta en Flecha de Conductor de Aleación de aluminio de 35 mm², Por Fase, Incluye Instalación de Amortiguadores. | G105: km | H105: 53.4 | I105: 1416.22 | J105: =+ROUND(I105*H105,2) -> 75626.15 | L105: 1573.58 | M105: =+ROUND(L105*$M$7,2) -> 1416.22
B106: =+B105+0.01 -> 6.02 | D106: Tendido y Puesta en Flecha de Conductor de Aleación de aluminio de 70 mm², Por Fase, Incluye Instalación de Amortiguadores. | G106: km | H106: 1.91 | I106: 1514.94 | J106: =+ROUND(I106*H106,2) -> 2893.54 | L106: 1683.27 | M106: =+ROUND(L106*$M$7,2) -> 1514.94
F107: =+"SUB-TOTAL "&B104&": " -> SUB-TOTAL 6: | J107: =+SUM(J105:J106) -> 78519.69
B108: 7 | D108: INSTALACION DE PUESTA A TIERRA
B109: =+B108+0.01 -> 7.01 | D109: Excavación en Terreno Tipo I (Arcilloso y Conglomerado) | H109: 261.15 | I109: 61.15 | J109: =+ROUND(I109*H109,2) -> 15969.32 | L109: 67.94 | M109: =+ROUND(L109*$M$7,2) -> 61.15
B110: =+B109+0.01 -> 7.02 | D110: Excavación en Terreno Tipo II (Rocoso) | H110: 12.56 | I110: 208.14 | J110: =+ROUND(I110*H110,2) -> 2614.24 | L110: 231.27 | M110: =+ROUND(L110*$M$7,2) -> 208.14
B111: =+B110+0.01 -> 7.03 | D111: Instalacion de Puesta a Tierra Tipo PAT-1C (Contrapeso). Instalación en Poste de Concreto Armado | G111: u | H111: 158 | I111: 39.47 | J111: =+ROUND(I111*H111,2) -> 6236.26 | L111: 43.86 | M111: =+ROUND(L111*$M$7,2) -> 39.47
B112: =+B111+0.01 -> 7.04 | D112: Instalación de Puesta a Tierra Tipo PAT-1 con un Electrodo Vertical. Instalación en Poste de Concreto Armado Centrifugado (Incluye instalación de una Caja de Registro). | G112: u | H112: 13 | I112: 54.98 | J112: =+ROUND(I112*H112,2) -> 714.74 | L112: 61.09 | M112: =+ROUND(L112*$M$7,2) -> 54.98
B113: =+B112+0.01 -> 7.05 | D113: Instalacion de Puesta a Tierra Tipo PAT-1C (Contrapeso). Instalación en Poste de Madera. | G113: u | H113: 7 | I113: 54.34 | J113: =+ROUND(I113*H113,2) -> 380.38 | L113: 60.38 | M113: =+ROUND(L113*$M$7,2) -> 54.34
B114: =+B113+0.01 -> 7.06 | D114: Instalación de Puesta a Tierra Tipo PAT-1 con un Electrodo Vertical. Instalación en Poste de Madera (Incluye instalación de una Caja de Registro). | G114: u | H114: 2 | I114: 63.45 | J114: =+ROUND(I114*H114,2) -> 126.9 | L114: 70.5 | M114: =+ROUND(L114*$M$7,2) -> 63.45
B115: =+B114+0.01 -> 7.07 | D115: Relleno y compactación de puesta a tierra con material adecuado | H115: 269.6 | I115: 68.82 | J115: =+ROUND(I115*H115,2) -> 18553.87 | L115: 76.47 | M115: =+ROUND(L115*$M$7,2) -> 68.82
F116: =+"SUB-TOTAL "&B108&": " -> SUB-TOTAL 7: | J116: =+SUM(J109:J115) -> 44595.71
B117: =1+B108 -> 8 | D117: MONTAJE DE REDES SUBTERRANEAS
B118: =+B117+0.01 -> 8.01 | D118: Excavacion de Zanja en Terreno Tipo I (Arcilloso y Conglomerado) | H118: 86.3 | I118: 61.15 | J118: =+ROUND(I118*H118,2) -> 5277.25 | L118: 67.94 | M118: =+ROUND(L118*$M$7,2) -> 61.15
B119: =+B118+0.01 -> 8.02 | D119: Excavacion de Zanja en Terreno Tipo II (Rocoso) | H119: 12.33 | I119: 208.14 | J119: =+ROUND(I119*H119,2) -> 2566.37 | L119: 231.27 | M119: =+ROUND(L119*$M$7,2) -> 208.14
B120: =+B119+0.01 -> 8.03 | D120: Relleno y compactacion de Zanja con material adecuado | H120: 98.63 | I120: 68.82 | J120: =+ROUND(I120*H120,2) -> 6787.72 | L120: 76.47 | M120: =+ROUND(L120*$M$7,2) -> 68.82
B121: =+B120+0.01 -> 8.04 | D121: Instalación de ductos de 2 Vias | G121: u | H121: 60 | I121: 24.62 | J121: =+ROUND(I121*H121,2) -> 1477.2 | L121: 27.36 | M121: =+ROUND(L121*$M$7,2) -> 24.62
B122: =+B121+0.01 -> 8.05 | D122: Tendido de Cable de Energía N2XSY 1x50 mm2 8,7/15 KV (Incluye conexionado) | G122: m | H122: 673.12 | I122: 77.4 | J122: =+ROUND(I122*H122,2) -> 52099.49 | L122: 86 | M122: =+ROUND(L122*$M$7,2) -> 77.4
B123: =+B122+0.01 -> 8.06 | D123: Instalacion de Terminales Autocontraibles Exterior | G123: u | H123: 30 | I123: 276.64 | J123: =+ROUND(I123*H123,2) -> 8299.2 | L123: 307.38 | M123: =+ROUND(L123*$M$7,2) -> 276.64
F124: =+"SUB-TOTAL "&B117&": " -> SUB-TOTAL 8: | J124: =+SUM(J118:J123) -> 76507.23
B125: =1+B117 -> 9 | D125: PRUEBAS Y PUESTA EN SERVICIO
B126: =+B125+0.01 -> 9.01 | D126: Pruebas y Puesta en Servicio de Lineas Primarias | G126: km | H126: 22.95 | I126: 289.92 | J126: =+ROUND(I126*H126,2) -> 6653.66 | L126: 366.58 | M126: =+ROUND(L126*$M$7,2) -> 329.92
B127: =+B126+0.01 -> 9.02 | D127: Expediente Técnico Final Conforme a Obra y de Concesión Rural de Líneas Primarias (1 Original + 3 Copias), incluye la presentacion digitalizada de textos y planos en CD. | G127: km | H127: 22.95 | I127: 302.67 | J127: =+ROUND(I127*H127,2) -> 6946.28 | L127: 391.85 | M127: =+ROUND(L127*$M$7,2) -> 352.67
F128: =+"SUB-TOTAL "&B125&": " -> SUB-TOTAL 9: | J128: =+SUM(J126:J127) -> 13599.94
D130: TOTAL MONTAJE ELECTROMECÁNICO | J130: =+ROUND(SUM(J9:J129)/2,2) -> 461491.17
D131: Nota = (*) El Contratista coordinará con la empresa concesionaria para definir los detalles para la identificación y señalización finalde los postes.
J133: =+J128+J124+J116+J107+J103+J79+J69+J55+J18 -> 461491.17
J134: =J133=J130 -> TRUE

Sheet TRANS_LP
B1: VALOR REFERENCIAL
B2: TRANSPORTE DE MATERIALES LÍNEAS PRIMARIAS
B3: UBICACIÓN | E3: : | F3: ANCASH
B4: SECCIÓN I | E4: : | F4: LÍNEAS PRIMARIAS
B5: C: TRANSPORTE DE MATERIALES
B7: Item | C7: Descripción de Partidas | G7: Unid. | H7: Metrado Cant. | I7: Costo Unitario | J7: SubTotal S/
D9: LINEAS PRIMARIAS
B11: 1 | D11: CRUCETAS DE MADERA DE PROCEDENCIA NACIONAL | P11: Indice Unificado
B12: =+B11+0.01 -> 1.01 | D12: =+'SUMINISTRO LP'!D12 -> Cruceta de madera tratada de 90 mm x 115 mm x 1,20 m | G12: u | H12: =+'SUMINISTRO LP'!H12 -> 11 | I12: 5.72 | J12: =+ROUND(I12*H12,2) -> 62.92 | O12: IU | P12: 44440 | Q12: 44682 | R12: Incremento
B13: =+B12+0.01 -> 1.02 | D13: =+'SUMINISTRO LP'!D13 -> Cruceta de madera tratada de 90 mm x 115 mm x 2,00 m | G13: u | H13: =+'SUMINISTRO LP'!H13 -> 2 | I13: 9.87 | J13: =+ROUND(I13*H13,2) -> 19.74 | O13: 32 | P13: 507.42 | Q13: 513.36 | R13: =+Q13/P13 -> 1.0117063
B14: =+B13+0.01 -> 1.03 | D14: =+'SUMINISTRO LP'!D14 -> Cruceta de madera tratada de 90 mm x 115 mm x 2,40 m | G14: u | H14: =+'SUMINISTRO LP'!H14 -> 1 | I14: 13.23 | J14: =+ROUND(I14*H14,2) -> 13.23
B15: =+B14+0.01 -> 1.04 | D15: =+'SUMINISTRO LP'!D15 -> Listón de madera tratada 50 x 19 mm sección, 2,7 m longitud (incluye clavos de fijación) | G15: u | H15: =+'SUMINISTRO LP'!H15 -> 9 | I15: 2.86 | J15: =+ROUND(I15*H15,2) -> 25.74
F16: =+"SUB-TOTAL "&B11&": " -> SUB-TOTAL 1: | J16: =+SUM(J11:J15) -> 121.63
B17: 2 | D17: POSTES DE CONCRETO ARMADO CENTRIFUGADO
B18: =+B17+0.01 -> 2.01 | D18: =+'SUMINISTRO LP'!D18 -> Poste de C.A.C. de 12 m/200 daN (Incluye perilla) | G18: u | H18: =+'SUMINISTRO LP'!H18 -> 15 | I18: 149.76 | J18: =+ROUND(I18*H18,2) -> 2246.4
B19: =+B18+0.01 -> 2.02 | D19: =+'SUMINISTRO LP'!D19 -> Poste de C.A.C. de 12 m/300 daN (Incluye perilla) | G19: u | H19: =+'SUMINISTRO LP'!H19 -> 6 | I19: 156.56 | J19: =+ROUND(I19*H19,2) -> 939.36
B20: =+B19+0.01 -> 2.03 | D20: =+'SUMINISTRO LP'!D20 -> Poste de C.A.C. de 13 m/300 daN (Incluye perilla) | G20: u | H20: =+'SUMINISTRO LP'!H20 -> 118 | I20: 178.72 | J20: =+ROUND(I20*H20,2) -> 21088.96
B21: =+B20+0.01 -> 2.04 | D21: =+'SUMINISTRO LP'!D21 -> Poste de C.A.C. de 13 m/400 daN (Incluye perilla) | G21: u | H21: =+'SUMINISTRO LP'!H21 -> 32 | I21: 191.36 | J21: =+ROUND(I21*H21,2) -> 6123.52
F22: =+"SUB-TOTAL "&B17&": " -> SUB-TOTAL 2: | J22: =+SUM(J18:J21) -> 30398.24
B23: 3 | D23: =+'SUMINISTRO LP'!D23 -> POSTES DE MADERA IMPORTADA
B24: =+B23+0.01 -> 3.01 | D24: =+'SUMINISTRO LP'!D24 -> Poste de madera importada (Pino Amarillo del Sur) de 12 m, Clase 6 | G24: =+'SUMINISTRO LP'!G24 -> u | H24: =+'SUMINISTRO LP'!H24 -> 9 | I24: 167.7 | J24: =+ROUND(I24*H24,2) -> 1509.3
F25: =+"SUB-TOTAL "&B23&": " -> SUB-TOTAL 3: | J25: =+SUM(J24) -> 1509.3
B26: 4 | D26: OTROS MATERIALES DE CONCRETO ARMADO
B27: =+B26+0.01 -> 4.01 | D27: =+'SUMINISTRO LP'!D27 -> Cruceta Asimétrica de C.A.V. Za / 1,5 / 0,9 / 250 / 200 / 100 daN (Za / L / L1/ T / F / V) | G27: u | H27: =+'SUMINISTRO LP'!H27 -> 2 | I27: 17.3 | J27: =+ROUND(I27*H27,2) -> 34.6
B28: =+B27+0.01 -> 4.02 | D28: =+'SUMINISTRO LP'!D28 -> Ménsula de C.A.V. M / 1,2 / 250 / 150 / 150 daN (M / L / T / F / V) | G28: u | H28: =+'SUMINISTRO LP'!H28 -> 393 | I28: 25.6 | J28: =+ROUND(I28*H28,2) -> 10060.8
B29: =+B28+0.01 -> 4.03 | D29: =+'SUMINISTRO LP'!D29 -> Ménsula de C.A.V. M / 0,8 / 250 / 150 / 150 daN (M / L / T / F / V) | G29: u | H29: =+'SUMINISTRO LP'!H29 -> 1 | I29: 22.28 | J29: =+ROUND(I29*H29,2) -> 22.28
F30: =+"SUB-TOTAL "&B26&": " -> SUB-TOTAL 4: | J30: =+SUM(J26:J29) -> 10117.68
B31: =1+B26 -> 5 | D31: AISLADORES Y ACCESORIOS
B32: =+B31+0.01 -> 5.01 | D32: Aislador de Porcelana Tipo Pin, Clase ANSI 56-3 | G32: u | H32: =+'SUMINISTRO LP'!H32 -> 29 | I32: 4.43 | J32: =+ROUND(I32*H32,2) -> 128.47
B33: =+B32+0.01 -> 5.02 | D33: Espiga de AºGº de 609 mm longitud, para Cabeza de Poste y Aislador ANSI 56-3 | G33: u | H33: =+'SUMINISTRO LP'!H33 -> 29 | I33: 2.84 | J33: =+ROUND(I33*H33,2) -> 82.36
B34: =+B33+0.01 -> 5.03 | D34: Conjunto Aislador Line Post Polimérico en Cruceta:
D35: - Aislador Polimérico de 36 kV, Tipo Line Post con Espárrago de 19 mm Ø, 200 mm longitud (Alternativa a Conjunto Aislador-Espiga en Cruceta) | G35: u | H35: =+'SUMINISTRO LP'!H35 -> 369 | I35: 1.64 | J35: =+ROUND(I35*H35,2) -> 605.16
F36: =+"SUB-TOTAL "&B31&": " -> SUB-TOTAL 5: | J36: =+SUM(J31:J35) -> 815.99
B37: =1+B31 -> 6 | D37: AISLADORES DE SUSPENSION Y ACCESORIOS
B38: =0.01+B37 -> 6.01 | D38: Grillete Recto | G38: u | H38: =+'SUMINISTRO LP'!H38 -> 155 | I38: 1.69 | J38: =+ROUND(I38*H38,2) -> 261.95
B39: =0.01+B38 -> 6.02 | D39: Aislador Polimerico con Conexión Horquilla (Estructura) y Lengüeta (Linea) de 36 kV, según Especificacion Técnica. | G39: u | H39: =+'SUMINISTRO LP'!H39 -> 155 | I39: 4.13 | J39: =+ROUND(I39*H39,2) -> 640.15
F40: =+"SUB-TOTAL "&B37&": " -> SUB-TOTAL 6: | J40: =+SUM(J37:J39) -> 902.1
B41: =1+B37 -> 7 | D41: CONDUCTOR DE ALEACIÓN DE ALUMINIO
B42: =+B41+0.01 -> 7.01 | D42: Conductor de Aleacion de Aluminio de 35 mm² | G42: km | H42: =+'SUMINISTRO LP'!H42 -> 53.4 | I42: 83.54 | J42: =+ROUND(I42*H42,2) -> 4461.04
B43: =+B42+0.01 -> 7.02 | D43: Conductor de Aleacion de Aluminio de 70 mm² | G43: km | H43: =+'SUMINISTRO LP'!H43 -> 1.91 | I43: 162.78 | J43: =+ROUND(I43*H43,2) -> 310.91
F44: =+"SUB-TOTAL "&B41&": " -> SUB-TOTAL 7: | J44: =+SUM(J42:J43) -> 4771.95
B45: =1+B41 -> 8 | D45: ACCESORIOS PARA CONDUCTOR DE ALEACION DE ALUMINIO
B46: =+B45+0.01 -> 8.01 | D46: Varilla de Armar preformada Simple para Conductor de 35 mm² | G46: u | H46: =+'SUMINISTRO LP'!H46 -> 326 | I46: 0.68 | J46: =+ROUND(I46*H46,2) -> 221.68
B47: =+B46+0.01 -> 8.02 | D47: Varilla de Armar preformada Simple para Conductor de 70 mm² | G47: u | H47: =+'SUMINISTRO LP'!H47 -> 2 | I47: 0.69 | J47: =+ROUND(I47*H47,2) -> 1.38
B48: =+B47+0.01 -> 8.03 | D48: Manguito de Empalme para Conductor de 35 mm² | G48: u | H48: =+'SUMINISTRO LP'!H48 -> 17 | I48: 0.9 | J48: =+ROUND(I48*H48,2) -> 15.3
B49: =+B48+0.01 -> 8.04 | D49: Manguito de Reparacion para Conductor de 35 mm² | G49: u | H49: =+'SUMINISTRO LP'!H49 -> 7 | I49: 0.27 | J49: =+ROUND(I49*H49,2) -> 1.89
B50: =+B49+0.01 -> 8.05 | D50: Grapa de Doble Via de Aluminio para Conductor de 35 mm² | G50: u | H50: =+'SUMINISTRO LP'!H50 -> 84 | I50: 0.35 | J50: =+ROUND(I50*H50,2) -> 29.4
B51: =+B50+0.01 -> 8.06 | D51: Grapa de Doble Via de Aluminio para Conductor de 70 mm² | G51: u | H51: =+'SUMINISTRO LP'!H51 -> 2 | I51: 0.41 | J51: =+ROUND(I51*H51,2) -> 0.82
B52: =+B51+0.01 -> 8.07 | D52: Alambre de Amarre Aluminio Recocido de 16 mm² | G52: m | H52: =+'SUMINISTRO LP'!H52 -> 1052.3 | I52: 0.42 | J52: =+ROUND(I52*H52,2) -> 441.97
B53: =+B52+0.01 -> 8.08 | D53: Amortiguador de Vibracion Tipo Stockbridge para Conductor de 35 mm² | G53: u | H53: =+'SUMINISTRO LP'!H53 -> 4 | I53: 0.8 | J53: =+ROUND(I53*H53,2) -> 3.2
B54: =+B53+0.01 -> 8.09 | D54: Amortiguador de Vibracion Tipo Stockbridge para Conductor de 70 mm² | G54: u | H54: =+'SUMINISTRO LP'!H54 -> 8 | I54: 1.49 | J54: =+ROUND(I54*H54,2) -> 11.92
B55: =+B54+0.01 -> 8.1 | D55: Grapa de Angulo para Conductor de 35 mm² | G55: u | H55: =+'SUMINISTRO LP'!H55 -> 14 | I55: 0.81 | J55: =+ROUND(I55*H55,2) -> 11.34
B56: =+B55+0.01 -> 8.11 | D56: Grapa de Angulo para Conductor de 70 mm² | G56: u | H56: =+'SUMINISTRO LP'!H56 -> 4 | I56: 1.34 | J56: =+ROUND(I56*H56,2) -> 5.36
B57: =+B56+0.01 -> 8.12 | D57: Grapa de Anclaje para Conductor de 35 mm² | G57: u | H57: =+'SUMINISTRO LP'!H57 -> 129 | I57: 0.88 | J57: =+ROUND(I57*H57,2) -> 113.52
B58: =+B57+0.01 -> 8.13 | D58: Grapa de Anclaje para Conductor de 70 mm² | G58: u | H58: =+'SUMINISTRO LP'!H58 -> 8 | I58: 1.12 | J58: =+ROUND(I58*H58,2) -> 8.96
F59: =+"SUB-TOTAL "&B45&": " -> SUB-TOTAL 8: | J59: =+SUM(J46:J58) -> 866.74
B60: =1+B45 -> 9 | D60: CONDUCTOR DE COBRE
B61: =+B60+0.01 -> 9.01 | D61: Cable de Acero con Recubrimiento Metalúrgico de Cu de 4 AWG (21,15 mm²), para Puesta a Tierra | G61: m | H61: =+'SUMINISTRO LP'!H61 -> 2936.1 | I61: 0.84 | J61: =+ROUND(I61*H61,2) -> 2466.32
F62: =+"SUB-TOTAL "&B60&": " -> SUB-TOTAL 9: | J62: =+SUM(J61:J61) -> 2466.32
B63: =1+B60 -> 10 | D63: MATERIAL DE FERRETERIA PARA POSTES Y CRUCETAS
B64: =+B63+0.01 -> 10.01 | D64: =+'SUMINISTRO LP'!D64 -> Perno Cabeza Coche de AºGº de 13 mm Ø x 152 mm longitud, 76 mm maquinado, con Arandela, Tuerca y Contratuerca | G64: u | H64: =+'SUMINISTRO LP'!H64 -> 9 | I64: 0.32 | J64: =+ROUND(I64*H64,2) -> 2.88
B65: =+B64+0.01 -> 10.02 | D65: =+'SUMINISTRO LP'!D65 -> Perno de A°G° de 13 mm Ø x 254 mm, provisto de Tuerca y Contratuerca | G65: u | H65: =+'SUMINISTRO LP'!H65 -> 26 | I65: 0.32 | J65: =+ROUND(I65*H65,2) -> 8.32
B66: =+B65+0.01 -> 10.03 | D66: =+'SUMINISTRO LP'!D66 -> Perno de A°G° de 13 mm Ø x 305 mm, provisto de Tuerca y Contratuerca | G66: u | H66: =+'SUMINISTRO LP'!H66 -> 7 | I66: 0.32 | J66: =+ROUND(I66*H66,2) -> 2.24
B67: =+B66+0.01 -> 10.04 | D67: =+'SUMINISTRO LP'!D67 -> Perno de A°G° de 16 mm Ø x 254 mm, provisto de Tuerca y Contratuerca | G67: u | H67: =+'SUMINISTRO LP'!H67 -> 18 | I67: 0.31 | J67: =+ROUND(I67*H67,2) -> 5.58
B68: =+B67+0.01 -> 10.05 | D68: =+'SUMINISTRO LP'!D68 -> Perno de A°G° de 16 mm Ø x 305 mm, provisto de Tuerca y Contratuerca | G68: u | H68: =+'SUMINISTRO LP'!H68 -> 18 | I68: 0.34 | J68: =+ROUND(I68*H68,2) -> 6.12
B69: =+B68+0.01 -> 10.06 | D69: =+'SUMINISTRO LP'!D69 -> Perno de A°G° de 16 mm Ø x 356 mm, provisto de Tuerca y Contratuerca | G69: u | H69: =+'SUMINISTRO LP'!H69 -> 8 | I69: 0.36 | J69: =+ROUND(I69*H69,2) -> 2.88
B70: =+B69+0.01 -> 10.07 | D70: =+'SUMINISTRO LP'!D70 -> Perno de A°G° de 16 mm Ø x 508 mm, provisto de Tuerca y Contratuerca | G70: u | H70: =+'SUMINISTRO LP'!H70 -> 3 | I70: 0.46 | J70: =+ROUND(I70*H70,2) -> 1.38
B71: =+B70+0.01 -> 10.08 | D71: =+'SUMINISTRO LP'!D71 -> Perno Doble Armado de A°G° de 16 mm Ø x 508 mm, provisto de 4 Tuercas y 4 Contratuercas | G71: u | H71: =+'SUMINISTRO LP'!H71 -> 380 | I71: 0.41 | J71: =+ROUND(I71*H71,2) -> 155.8
B72: =+B71+0.01 -> 10.09 | D72: =+'SUMINISTRO LP'!D72 -> Perno Ojo de A°G° de 16 mm Ø x 254 mm, provisto de Tuerca y Contratuerca | G72: u | H72: =+'SUMINISTRO LP'!H72 -> 61 | I72: 0.45 | J72: =+ROUND(I72*H72,2) -> 27.45
B73: =+B72+0.01 -> 10.1 | D73: =+'SUMINISTRO LP'!D73 -> Perno Ojo de A°G° de 16 mm Ø x 305 mm, provisto de Tuerca y Contratuerca | G73: u | H73: =+'SUMINISTRO LP'!H73 -> 47 | I73: 0.54 | J73: =+ROUND(I73*H73,2) -> 25.38
B74: =+B73+0.01 -> 10.11 | D74: =+'SUMINISTRO LP'!D74 -> Perno Ojo de A°G° de 16 mm Ø x 356 mm, provisto de Tuerca y Contratuerca | G74: u | H74: =+'SUMINISTRO LP'!H74 -> 9 | I74: 0.64 | J74: =+ROUND(I74*H74,2) -> 5.76
B75: =+B74+0.01 -> 10.12 | D75: =+'SUMINISTRO LP'!D75 -> Tuerca-Ojo para Perno de 16 mm Ø | G75: u | H75: =+'SUMINISTRO LP'!H75 -> 38 | I75: 0.48 | J75: =+ROUND(I75*H75,2) -> 18.24
... B80: =+B79+0.01 -> 10.17 | D80: =+'SUMINISTRO LP'!D80 -> Plantillas para Identificación y/o codificación de Postes (Peligro, Identificación y/o codificación y Fases) | G80: Jgo. | H80: =+'SUMINISTRO LP'!H80 -> 21 | I80: 0.22 | J80: =+ROUND(I80*H80,2) -> 4.62
B81: =+B80+0.01 -> 10.18 | D81: =+'SUMINISTRO LP'!D81 -> Placa de Señal de Peligro y accesorios de fijación | G81: =+'SUMINISTRO LP'!G81 -> u | H81: =+'SUMINISTRO LP'!H81 -> 9 | I81: 0.12 | J81: =+ROUND(I81*H81,2) -> 1.08
B82: =+B81+0.01 -> 10.19 | D82: =+'SUMINISTRO LP'!D82 -> Placa de Identificación y/o codificación de Estructura y accesorios de fijación | G82: =+'SUMINISTRO LP'!G82 -> u | H82: =+'SUMINISTRO LP'!H82 -> 9 | I82: 0.1 | J82: =+ROUND(I82*H82,2) -> 0.9
B83: =+B82+0.01 -> 10.2 | D83: =+'SUMINISTRO LP'!D83 -> Placa de Secuencia de Fases y accesorios de fijación | G83: =+'SUMINISTRO LP'!G83 -> u | H83: =+'SUMINISTRO LP'!H83 -> 9 | I83: 0.07 | J83: =+ROUND(I83*H83,2) -> 0.63
F84: =+"SUB-TOTAL "&B63&": " -> SUB-TOTAL 10: | J84: =+SUM(J64:J83) -> 432.24
B85: =1+B63 -> 11 | D85: RETENIDAS Y ANCLAJES
B86: =+B85+0.01 -> 11.01 | D86: Cable de Acero Grado Siemens Martin, de 10 mm Ø, 7 hilos | G86: m | H86: =+'SUMINISTRO LP'!H86 -> 881 | I86: 0.58 | J86: =+ROUND(I86*H86,2) -> 510.98
B87: =+B86+0.01 -> 11.02 | D87: Varilla de Anclaje de A°G° de 16 mm Ø x 2,40 m, provisto de Ojal Guardacabo en un extremo; Tuerca y Contratuerca en el otro | G87: u | H87: =+'SUMINISTRO LP'!H87 -> 66 | I87: 2.37 | J87: =+ROUND(I87*H87,2) -> 156.42
B88: =+B87+0.01 -> 11.03 | D88: Mordaza Preformada de A°G° para Cable de 10 mm Ø | G88: u | H88: =+'SUMINISTRO LP'!H88 -> 208 | I88: 0.85 | J88: =+ROUND(I88*H88,2) -> 176.8
B89: =+B88+0.01 -> 11.04 | D89: Alambre de Acero N° 14 para Entorchado | G89: m | H89: =+'SUMINISTRO LP'!H89 -> 312 | I89: 0.02 | J89: =+ROUND(I89*H89,2) -> 6.24
B90: =+B89+0.01 -> 11.05 | D90: Arandela de Anclaje de A°G°, 102 x 102 x 6,35 mm, Agujero de 18 mmø | G90: u | H90: =+'SUMINISTRO LP'!H90 -> 66 | I90: 0.2 | J90: =+ROUND(I90*H90,2) -> 13.2
B91: =+B90+0.01 -> 11.06 | D91: Soporte de Contrapunta de 51 mm ø x 1200 mm de longitud, con Abrazadera partida en un extremo y Grapa de Ajuste para Cable en el otro | G91: u | H91: =+'SUMINISTRO LP'!H91 -> 12 | I91: 2.9 | J91: =+ROUND(I91*H91,2) -> 34.8
B92: =+B91+0.01 -> 11.07 | D92: Abrazadera de 4 sectores para Retenida, de 75 mm de altura, 6,35 mm de espesor y 70 kN de resistencia. Diámetro según dimensiones del poste, incluye 4 pernos de 12,7 mm Ø x 63,5 mm y 4 arandelas | G92: u | H92: =+'SUMINISTRO LP'!H92 -> 66 | I92: 2.75 | J92: =+ROUND(I92*H92,2) -> 181.5
B93: =+B92+0.01 -> 11.08 | D93: Enlace metálico, de 254 mm x 75 mm x 38 mm, de 70 kN de resistencia | G93: u | H93: =+'SUMINISTRO LP'!H93 -> 66 | I93: 0.25 | J93: =+ROUND(I93*H93,2) -> 16.5
B94: =+B93+0.01 -> 11.09 | D94: Aislador Polimerico con Conexión Horquilla (Estructura) y Lengüeta (Linea) de 36 kV, según Especificacion Técnica, para Retenida Aislada. | G94: u | H94: =+'SUMINISTRO LP'!H94 -> 66 | I94: 4.13 | J94: =+ROUND(I94*H94,2) -> 272.58
B95: =+B94+0.01 -> 11.1 | D95: Grillete de Acero de 70 kN | G95: u | H95: =+'SUMINISTRO LP'!H95 -> 85 | I95: 1.15 | J95: =+ROUND(I95*H95,2) -> 97.75
B96: =+B95+0.01 -> 11.11 | D96: Bloque de Concreto de 0,40 x 0,40 x 0,15 m | G96: u | H96: =+'SUMINISTRO LP'!H96 -> 66 | I96: 23.88 | J96: =+ROUND(I96*H96,2) -> 1576.08
B97: =+B96+0.01 -> 11.12 | D97: Tuerca-Ojo para Perno de 16 mm Ø | G97: u | H97: =+'SUMINISTRO LP'!H97 -> 22 | I97: 0.48 | J97: =+ROUND(I97*H97,2) -> 10.56
B98: =+B97+0.01 -> 11.13 | D98: Arandela Cuadrada Plana de A° G°, 57 x 57 x 5 mm, Agujero de 18 mm Ø | G98: u | H98: =+'SUMINISTRO LP'!H98 -> 39 | I98: 0.09 | J98: =+ROUND(I98*H98,2) -> 3.51
F99: =+"SUB-TOTAL "&B85&": " -> SUB-TOTAL 11: | J99: =+SUM(J86:J98) -> 3056.92
B100: =1+B85 -> 12 | D100: MATERIAL PARA PUESTA A TIERRA
B101: =+B100+0.01 -> 12.01 | D101: =+'SUMINISTRO LP'!D101 -> Electrodo de Acero Recubierto de Cobre de 16 mm Ø x 2,40 m | G101: u | H101: =+'SUMINISTRO LP'!H101 -> 15 | I101: 2.59 | J101: =+ROUND(I101*H101,2) -> 38.85
B102: =+B101+0.01 -> 12.02 | D102: =+'SUMINISTRO LP'!D102 -> Plancha Doblada de Cobre para toma a Tierra de Espigas y/o Pernos | G102: u | H102: =+'SUMINISTRO LP'!H102 -> 518 | I102: 0.07 | J102: =+ROUND(I102*H102,2) -> 36.26
B103: =+B102+0.01 -> 12.03 | D103: =+'SUMINISTRO LP'!D103 -> Conector de Bronce para Electrodo de 16 mm ø y Cable de Acero con Recubrimiento Metalúrgico de Cobre de 4 AWG (21,15 mm2) | G103: u | H103: =+'SUMINISTRO LP'!H103 -> 15 | I103: 0.24 | J103: =+ROUND(I103*H103,2) -> 3.6
B104: =+B103+0.01 -> 12.04 | D104: =+'SUMINISTRO LP'!D104 -> Conector de Cobre tipo Perno Partido para Cable de Acero con Recubrimiento Metalúrgico de Cobre de 4 AWG (21,15 mm2) | G104: u | H104: =+'SUMINISTRO LP'!H104 -> 428 | I104: 0.16 | J104: =+ROUND(I104*H104,2) -> 68.48
B105: =+B104+0.01 -> 12.05 | D105: =+'SUMINISTRO LP'!D105 -> Caja Registro de Concreto para Puesta a Tierra 0,50 x 0,50 x 0,45 m | G105: u | H105: =+'SUMINISTRO LP'!H105 -> 15 | I105: 23.88 | J105: =+ROUND(I105*H105,2) -> 358.2
B106: =+B105+0.01 -> 12.06 | D106: =+'SUMINISTRO LP'!D106 -> Grapa en "U" para fijar conductor de PAT a Madera | G106: u | H106: =+'SUMINISTRO LP'!H106 -> 204 | I106: 0.05 | J106: =+ROUND(I106*H106,2) -> 10.2
B107: =+B106+0.01 -> 12.07 | D107: =+'SUMINISTRO LP'!D107 -> Placa de Señalización de Poste (Puesta a Tierra) | G107: u | H107: =+'SUMINISTRO LP'!H107 -> 2 | I107: 0.16 | J107: =+ROUND(I107*H107,2) -> 0.32
...

Sheet POLINOMICA LP
B3: FORMULA POLINÓMICA
C6: PROYECTO :
C7: AMPLIACIÓN DEL SERVICIO DE ENERGÍA ELÉCTRICA EN LA PROVINCIA DEL SANTA Y EN EL DISTRITO DE PAMPAROMAS – DEPARTAMENTO DE ANCASH”
C9: LINEAS PRIMARIAS
C10: PRESUPUESTO BASE S/ | D10: =+'RESUMEN LP'!F20 -> #REF! | K10: =D10=SUM(G13:G27) -> #REF! | L10: =D10='RESUMEN LP'!F20 -> #REF!
B12: Nº | C12: ELEMENTO REPRESENTATIVO | D12: INDICE | E12: SIMBOLO | F12: SIMBOLO MONOMIO | G12: MONTO | H12: INCIDENCIA | I12: % PARCIAL | J12: COEFICIENTE
B13: 1 | C13: POSTES DE MADERA IMPORTADA | D13: 042 | E13: PM | F13: PC | G13: =+'SUMINISTRO LP'!J25 -> 15330.51 | H13: =ROUND(G13/$D$10,3) -> #REF! | I13: =ROUND(G13/SUM($G$13:$G$16),4) -> 0.0646 | J13: =ROUND(SUM(H13:H16),3) -> #REF!
C14: CRUCETAS DE MADERA | D14: 043 | E14: CM | G14: =+'SUMINISTRO LP'!J16 -> 1962.15 | H14: =ROUND(G14/$D$10,3) -> #REF! | I14: =ROUND(G14/SUM($G$13:$G$16),4) -> 0.0083
C15: POSTES DE CONCRETO | D15: 062 | E15: PC | G15: =+'SUMINISTRO LP'!J22 -> 184803.17 | H15: =ROUND(G15/$D$10,3) -> #REF! | I15: =ROUND(G15/SUM($G$13:$G$16),4) -> 0.7787
C16: OTROS MATERIALES DE CONCRETO ARMADO | D16: 062 | E16: CC | G16: =+'SUMINISTRO LP'!J30 -> 35231.26 | H16: =ROUND(G16/$D$10,3) -> #REF! | I16: =ROUND(G16/SUM($G$13:$G$16),4) -> 0.1485
B17: 2 | C17: CONDUCTORES DE AAAC Y ACCESORIOS | D17: 030 | E17: DI | F17: DI | G17: =+'SUMINISTRO LP'!J44+'SUMINISTRO LP'!J59 -> 138631.38 | H17: =ROUND(G17/$D$10,3) -> #REF! | I17: =ROUND(G17/SUM($G$17:$G$18),4) -> 0.9343 | J17: =ROUND(SUM(H17:H18),3) -> #REF!
C18: EQUIPOS DE PROTECCIÓN | D18: 011 | E18: AE1 | G18: =+'SUMINISTRO LP'!J116 -> 9748.38 | H18: =ROUND(G18/$D$10,3) -> #REF! | I18: =ROUND(G18/SUM($G$17:$G$18),4) -> 0.0657
B19: 3 | C19: AISLADORES Y ACCESORIOS | D19: 011 | E19: AE2 | F19: AE2 | G19: =+'SUMINISTRO LP'!J36+'SUMINISTRO LP'!J40 -> 95255.84 | H19: =ROUND(G19/$D$10,3) -> #REF! | I19: =ROUND(G19/SUM($G$19:$G$24),4) -> 0.3926 | J19: =ROUND(SUM(H19:H24),3) -> #REF!
C20: RETENIDAS Y ANCLAJES | D20: 002 | E20: FE | G20: =+'SUMINISTRO LP'!J99 -> 27911.09 | H20: =ROUND(G20/$D$10,3) -> #REF! | I20: =ROUND(G20/SUM($G$19:$G$24),4) -> 0.115
C21: FERRETERIA PARA POSTES Y CRUCETAS | D21: 002 | E21: FP | G21: =+'SUMINISTRO LP'!J84 -> 13536.76 | H21: =ROUND(G21/$D$10,3) -> #REF! | I21: =ROUND(G21/SUM($G$19:$G$24),4) -> 0.0558
C22: CONDUCTOR DE COBRE | D22: 006 | E22: CU | G22: =+'SUMINISTRO LP'!J62 -> 37582.08 | H22: =ROUND(G22/$D$10,3) -> #REF! | I22: =ROUND(G22/SUM($G$19:$G$24),4) -> 0.1549
C23: MATERIAL PARA PUESTA A TIERRA | D23: 006 | E23: PT | G23: =+'SUMINISTRO LP'!J110 -> 11193.66 | H23: =ROUND(G23/$D$10,3) -> #REF! | I23: =ROUND(G23/SUM($G$19:$G$24),4) -> 0.0461
C24: TRAMO SUBTERRANEO | D24: 006 | E24: TS | G24: =+'SUMINISTRO LP'!J128 -> 57138.98 | H24: =ROUND(G24/$D$10,3) -> #REF! | I24: =ROUND(G24/SUM($G$19:$G$24),4) -> 0.2355
B25: 4 | C25: MONTAJE ELECTROMECANICO | D25: 047 | E25: J | F25: J | G25: =+'MONTAJE LP'!J130 -> 461491.17 | H25: =ROUND(G25/$D$10,3) -> #REF! | I25: =ROUND(G25/($G$25+$G$26),4) -> 0.8849 | J25: =ROUND(SUM(H25:H26),3) -> #REF!
C26: TRANSPORTE | D26: 032 | E26: FT | G26: =+TRANS_LP!J130 -> 60052.8 | H26: =ROUND(G26/$D$10,3) -> #REF! | I26: =ROUND(G26/($G$25+$G$26),4) -> 0.1151
B27: 5 | C27: GASTOS GENERALES Y UTILIDADES | D27: 039 | E27: GG | F27: GU | G27: =+'RESUMEN LP'!F17+'RESUMEN LP'!F18 -> #REF! | H27: =ROUND(G27/$D$10,3) -> #REF! | I27: =+G27/G27 -> #REF! | J27: =ROUND(SUM(H27),3) -> #REF!
B29: K= | C29: =J13&" PCr/PCo + "&J17&" DIr/DIo + "&J19&" AE2r/AE2o+ "&J25&" Jr/Jo + "&J27&" GUr/GUo" -> #REF!
B32: NOTAS:
B34: 1.- | C34: En la fórmula los sub-indices "o" de cada símbolo corresponden al indice de precios según (CREPCO) a la
C35: fecha de Elaboración del Presupuesto (Presupuesto Base) y los sub-indices "r" al indice de precios al
C36: momento de reajuste o fecha de valorización
B37: 2.- | C37: En el caso de los monomios compuestos por varios indices se ha considerado para efecto de denominación
C38: el símbolo que tiene mayor porcentaje de incidencia
B39: 3.- | C39: En caso de cambios en el suministro se deberá actualizar la formula polinómica.
H46: =+IF(SUM(H13:H27)=1,"OK","X") -> #REF! | I46: =+IF(SUM(I13:I27)=5,"OK","X") -> #REF! | J46: =+IF(SUM(J13:J27)=1,"OK","X") -> #REF!

Sheet RESUMEN RP
B2: VALOR REFERENCIAL
B3: REDES PRIMARIAS
B4: “AMPLIACIÓN DEL SERVICIO DE ENERGÍA ELÉCTRICA EN LA PROVINCIA DEL SANTA Y EN EL DISTRITO DE PAMPAROMAS – DEPARTAMENTO DE ANCASH”
B7: UBICACIÓN | D7: : | E7: ANCASH
B8: SECCIÓN II | D8: : | E8: REDES PRIMARIAS
F9: =+#REF! -> #REF!
F10: =+#REF! -> #REF!
B11: ITEM | C11: DESCRIPCION | F11: TOTAL S/
B13: A | D13: SUMINISTRO DE MATERIALES | F13: =+'SUMINISTRO RP'!J108 -> 202256.75
B14: B | D14: MONTAJE ELECTROMECANICO | F14: =+'MONTAJE RP'!J90 -> 85459.52
B15: C | D15: TRANSPORTE DE MATERIALES | F15: =+TRANS._RP!J109 -> 16212.19 | G15: =+F15/F13 -> 0.080156484
B16: D | D16: TOTAL COSTO DIRECTO | F16: =SUM(F13:F15) -> 303928.46
B18: E | E18: GASTOS GENERALES | F18: =+ROUND(F16*H18,2) -> #REF! | H18: =+#REF! -> #REF!
B19: F | E19: UTILIDADES | F19: =+ROUND(F16*H19,2) -> #REF! | H19: =+#REF! -> #REF!
D21: COSTO TOTAL S/ (No incluye I.G.V.) | F21: =SUM(F16:F19) -> #REF! | H21: =F21=#REF! -> #REF!

Sheet Alternativa-RP
B2: “ELABORACIÓN DEL PERFIL DEL PROYECTO “AMPLIACION DEL SERVICIO DE ELECTRIFICACIÓN RURAL EN LAS PROVINCIAS DE LEONCIO PRADO Y MARAÑON DEL DEPARTAMENTO DE HUANUCO Y LA PROVINCIA DE TOCACHE DEL DEPARTAMENTO DE SAN MARTIN”
B3: ="RESUMEN DEL VALOR REFERENCIAL " -> RESUMEN DEL VALOR REFERENCIAL
B5: UBICACIÓN | D5: :
B6: SECCIÓN I | D6: : | E6: RP
B9: ITEM | C9: DESCRIPCION | F9: TOTAL (S/.)
I10: =F11*0.07 -> 14157.973
B11: A | D11: SUMINISTROS DE MATERIALES | F11: =+'RESUMEN RP'!F13 -> 202256.75 | I11: =F11*0.1 -> 20225.675
D12: Origen Nacional | F12: =+F11-F13 -> 164615.74
D13: Origen Importado | F13: =+'SUMINISTRO RP'!J26+'SUMINISTRO RP'!J28+'SUMINISTRO RP'!J36+'SUMINISTRO RP'!J48+'SUMINISTRO RP'!J94+'SUMINISTRO RP'!J107 -> 37641.01
B15: B | D15: MONTAJE ELECTROMECANICO | F15: =+'RESUMEN RP'!F14 -> 85459.52 | H15: =+F15/$F$11 -> 0.42252988
D16: M.O. Calificada | F16: =ROUND(N16*F15,2) -> 53839.5 | N16: 0.63
D17: M.O. No Calificada | F17: =ROUND(N17*F15,2) -> 31620.02 | N17: =1-N16 -> 0.37
B19: B.1 | D19: ACTIVIDADES COMPLEMENTARIAS DE MONTAJE | F19: 0
B21: C | D21: TRANSPORTE DE MATERIALES | F21: =+'RESUMEN RP'!F15 -> 16212.19 | H21: 0.1
B24: D | D24: TOTAL COSTO DIRECTO (C.D.) | F24: =+F21+F15+F11+F19 -> 303928.46

Sheet SUMINISTRO RP
B1: VALOR REFERENCIAL
B2: SUMINISTRO DE MATERIALES REDES PRIMARIAS
B3: UBICACIÓN | E3: : | F3: ANCASH
B4: SECCIÓN II | E4: : | F4: REDES PRIMARIAS
B5: A: SUMINISTRO DE MATERIALES
B7: Item | C7: Descripción de Partidas | G7: Unid. | H7: Metrado Cant. | I7: Costo Unitario | J7: SubTotal S/
B9: 1 | D9: CRUCETAS DE MADERA DE PROCEDENCIA NACIONAL
B10: =+B9+0.01 -> 1.01 | D10: Cruceta de madera tratada de 90 mm x 115 mm x 1,20 m | G10: u | H10: 13 | I10: 105 | J10: =+ROUND(I10*H10,2) -> 1365
B11: =+B10+0.01 -> 1.02 | D11: Listón de madera tratada 50 x 19 mm sección, 2,7 m longitud (incluye clavos de fijación) | G11: u | H11: 2 | I11: 27.35 | J11: =+ROUND(I11*H11,2) -> 54.7
F12: =+"SUB-TOTAL "&B9&": " -> SUB-TOTAL 1: | J12: =SUM(J10:J11) -> 1419.7
B13: =1+B9 -> 2 | D13: POSTES DE CONCRETO ARMADO CENTRIFUGADO
B14: =+B13+0.01 -> 2.01 | D14: Poste de C.A.C. de 12 m/200 daN (Incluye perilla) | G14: u | H14: 3 | I14: 837.45 | J14: =+ROUND(I14*H14,2) -> 2512.35
B15: =+B14+0.01 -> 2.02 | D15: Poste de C.A.C. de 12 m/300 daN (Incluye perilla) | G15: u | H15: 11 | I15: 923.47 | J15: =+ROUND(I15*H15,2) -> 10158.17
B16: =+B15+0.01 -> 2.03 | D16: Poste de C.A.C. de 13 m/300 daN (Incluye perilla) | G16: u | H16: 10 | I16: 1085.14 | J16: =+ROUND(I16*H16,2) -> 10851.4
B17: =+B16+0.01 -> 2.04 | D17: Poste de C.A.C. de 13 m/400 daN (Incluye perilla) | G17: u | H17: 10 | I17: 1207.94 | J17: =+ROUND(I17*H17,2) -> 12079.4
F18: =+"SUB-TOTAL "&B13&": " -> SUB-TOTAL 2: | J18: =SUM(J14:J17) -> 35601.32
B19: 3 | D19: POSTES DE MADERA IMPORTADA
B20: =+B19+0.01 -> 3.01 | D20: Poste de madera importada (Pino Amarillo del Sur) de 12 m, Clase 5 | G20: u | H20: 2 | I20: 1864.52 | J20: =+ROUND(I20*H20,2) -> 3729.04
F21: =+"SUB-TOTAL "&B19&": " -> SUB-TOTAL 3: | J21: =+SUM(J19:J20) -> 3729.04
B22: =1+B19 -> 4 | D22: OTROS MATERIALES DE CONCRETO ARMADO
B23: =+B22+0.01 -> 4.01 | D23: Cruceta Asimétrica de C.A.V. Za / 1,5 / 0,9 / 250 / 200 / 100 daN (Za / L / L1/ T / F / V) | G23: u | H23: 5 | I23: 120.3 | J23: =+ROUND(I23*H23,2) -> 601.5
B24: =+B23+0.01 -> 4.02 | D24: Ménsula de C.A.V. M / 1,2 / 250 / 150 / 150 daN (M / L / T / F / V) | G24: u | H24: 40 | I24: 88.8 | J24: =+ROUND(I24*H24,2) -> 3552
B25: =+B24+0.01 -> 4.03 | D25: Plataforma de Concreto Soporte de Transformador de 2,20 m, carga de trabajo de 500 daN | G25: u | H25: 5 | I25: 620 | J25: =+ROUND(I25*H25,2) -> 3100
F26: =+"SUB-TOTAL "&B22&": " -> SUB-TOTAL 4: | J26: =SUM(J23:J25) -> 7253.5
B27: =1+B22 -> 5 | D27: AISLADORES Y ACCESORIOS
B28: =+B27+0.01 -> 5.01 | D28: Aislador de Porcelana Tipo Pin, Clase ANSI 56-3 | G28: u | H28: 16 | I28: 76.45 | J28: =+ROUND(I28*H28,2) -> 1223.2
B29: =+B28+0.01 -> 5.02 | D29: Espiga de AºGº de 609 mm longitud, para Cabeza de Poste y Aislador ANSI 56-3 | G29: u | H29: 16 | I29: 35.96 | J29: =+ROUND(I29*H29,2) -> 575.36
B30: =+B29+0.01 -> 5.03 | D30: Conjunto Aislador Line Post Polimérico en Cruceta:
D31: - Aislador Polimérico de 36 kV, Tipo Line Post con Espárrago de 19 mm Ø, 200 mm longitud (Alternativa a Conjunto Aislador-Espiga en Cruceta) | G31: u | H31: 40 | I31: 209.65 | J31: =+ROUND(I31*H31,2) -> 8386
F32: =+"SUB-TOTAL "&B27&": " -> SUB-TOTAL 5: | J32: =+SUM(J28:J31) -> 10184.56
B33: =1+B27 -> 6 | D33: AISLADORES DE SUSPENSIÓN Y ACCESORIOS
B34: =+B33+0.01 -> 6.01 | D34: Grillete Recto | G34: u | H34: 16 | I34: 17.76 | J34: =+ROUND(I34*H34,2) -> 284.16
B35: =+B34+0.01 -> 6.02 | D35: Aislador Polimerico con Conexión Horquilla (Estructura) y Lengüeta (Linea) de 36 kV, según Especificacion Técnica. | G35: u | H35: 16 | I35: 76.66 | J35: =+ROUND(I35*H35,2) -> 1226.56
F36: =+"SUB-TOTAL "&B33&": " -> SUB-TOTAL 6: | J36: =+SUM(J33:J35) -> 1510.72
B37: =1+B33 -> 7 | D37: CONDUCTOR DE ALEACIÓN DE ALUMINIO
B38: =+B37+0.01 -> 7.01 | D38: Conductor de Aleacion de Aluminio de 35 mm² | G38: km | H38: 3.51 | I38: 2249.62 | J38: =+ROUND(I38*H38,2) -> 7896.17
F39: =+"SUB-TOTAL "&B37&": " -> SUB-TOTAL 7: | J39: =+SUM(J38:J38) -> 7896.17
B40: =B37+1 -> 8 | D40: ACCESORIOS PARA CONDUCTOR DE ALEACION ALUMINIO
B41: =+B40+0.01 -> 8.01 | D41: Varilla de Armar preformada Simple para Conductor de 35 mm² | G41: u | H41: 41 | I41: 10.19 | J41: =+ROUND(I41*H41,2) -> 417.79
B42: =+B41+0.01 -> 8.02 | D42: Grapa de Doble Via de Aluminio para Conductor de 35 mm² | G42: u | H42: 41 | I42: 7.77 | J42: =+ROUND(I42*H42,2) -> 318.57
B43: =+B42+0.01 -> 8.03 | D43: Alambre de Amarre Aluminio Recocido de 16 mm² | G43: m | H43: 170 | I43: 1.41 | J43: =+ROUND(I43*H43,2) -> 239.7
B44: =+B43+0.01 -> 8.04 | D44: Grapa de Anclaje para Conductor de 35 mm² | G44: u | H44: 16 | I44: 25.34 | J44: =+ROUND(I44*H44,2) -> 405.44
F45: =+"SUB-TOTAL "&B40&": " -> SUB-TOTAL 8: | J45: =+SUM(J41:J44) -> 1381.5
B46: =1+B40 -> 9 | D46: CONDUCTOR DE COBRE
B47: =B46+0.01 -> 9.01 | D47: Cable de Acero con Recubrimiento Metalúrgico de Cu de 4 AWG (21,15 mm²), para Puesta a Tierra | G47: m | H47: 717.5 | I47: 12.8 | J47: =+ROUND(I47*H47,2) -> 9184
F48: =+"SUB-TOTAL "&B46&": " -> SUB-TOTAL 9: | J48: =+SUM(J47:J47) -> 9184
B49: =1+B46 -> 10 | D49: MATERIAL DE FERRETERIA PARA POSTES Y CRUCETAS
B50: =+B49+0.01 -> 10.01 | D50: Perno Cabeza Coche de AºGº de 13 mm Ø x 152 mm longitud, 76 mm maquinado, con Arandela, Tuerca y Contratuerca | G50: u | H50: 13 | I50: 3.86 | J50: =+ROUND(I50*H50,2) -> 50.18
B51: =+B50+0.01 -> 10.02 | D51: Perno de A°G° de 13 mm Ø x 305 mm, provisto de Tuerca y Contratuerca | G51: u | H51: 13 | I51: 6.25 | J51: =+ROUND(I51*H51,2) -> 81.25
B52: =+B51+0.01 -> 10.03 | D52: Perno de A°G° de 16 mm Ø x 254 mm, provisto de Tuerca y Contratuerca | G52: u | H52: 32 | I52: 8.61 | J52: =+ROUND(I52*H52,2) -> 275.52
B53: =+B52+0.01 -> 10.04 | D53: Perno de A°G° de 16 mm Ø x 305 mm, provisto de Tuerca y Contratuerca | G53: u | H53: 26 | I53: 9.14 | J53: =+ROUND(I53*H53,2) -> 237.64
B54: =+B53+0.01 -> 10.05 | D54: Perno de A°G° de 16 mm Ø x 356 mm, provisto de Tuerca y Contratuerca | G54: u | H54: 13 | I54: 9.82 | J54: =+ROUND(I54*H54,2) -> 127.66
B55: =+B54+0.01 -> 10.06 | D55: Perno Ojo de A°G° de 16 mm Ø x 254 mm, provisto de Tuerca y Contratuerca | G55: u | H55: 16 | I55: 13.11 | J55: =+ROUND(I55*H55,2) -> 209.76
B56: =+B55+0.01 -> 10.07 | D56: Perno Doble Armado de A°G° de 16 mm Ø x 508 mm, provisto de 4 Tuercas y 4 Contratuercas | G56: u | H56: 50 | I56: 18.18 | J56: =+ROUND(I56*H56,2) -> 909
B57: =+B56+0.01 -> 10.08 | D57: Tirafondo de A°G° de 13 mm ø x 102 mm de longitud | G57: u | H57: 2 | I57: 2.74 | J57: =+ROUND(I57*H57,2) -> 5.48
B58: =+B57+0.01 -> 10.09 | D58: Brazo-Soporte (Riostra) de Perfil Angular de A°G° de 38 x 38 x 5 mm y 710 mm longitud | G58: u | H58: 13 | I58: 22.46 | J58: =+ROUND(I58*H58,2) -> 291.98
B59: =+B58+0.01 -> 10.1 | D59: Arandela Cuadrada Plana de A° G°, 57 x 57 x 5 mm, Agujero de 18 mm Ø | G59: u | H59: 107 | I59: 1.67 | J59: =+ROUND(I59*H59,2) -> 178.69
B60: =+B59+0.01 -> 10.11 | D60: Arandela Cuadrada Curva de A° G°, 57 x 57 x 5 mm, Agujero de 18 mm Ø | G60: u | H60: 211 | I60: 1.67 | J60: =+ROUND(I60*H60,2) -> 352.37
B61: =+B60+0.01 -> 10.12 | D61: Plantillas para Identificación y/o codificación de Postes (Peligro, Identificación y/o codificación y Fases) | G61: Jgo. | H61: 34 | I61: 23.08 | J61: =+ROUND(I61*H61,2) -> 784.72
... B64: =+B63+0.01 -> 10.15 | D64: Placa de Secuencia de Fases y accesorios de fijación | G64: u | H64: 2 | I64: 18.78 | J64: =+ROUND(I64*H64,2) -> 37.56
F65: =+"SUB-TOTAL "&B49&": " -> SUB-TOTAL 10: | J65: =SUM(J50:J64) -> 3611.97
B66: =1+B49 -> 11 | D66: RETENIDAS Y ANCLAJES
B67: =+B66+0.01 -> 11.01 | D67: Cable de Acero Grado Siemens Martin, de 10 mm Ø, 7 hilos | G67: m | H67: 154 | I67: 4.31 | J67: =+ROUND(I67*H67,2) -> 663.74
B68: =+B67+0.01 -> 11.02 | D68: Varilla de Anclaje de A°G° de 16 mm Ø x 2,40 m, provisto de Ojal Guardacabo en un extremo; Tuerca y Contratuerca en el otro | G68: u | H68: 9 | I68: 46.85 | J68: =+ROUND(I68*H68,2) -> 421.65
B69: =+B68+0.01 -> 11.03 | D69: Mordaza Preformada de A°G° para Cable de 10 mm Ø | G69: u | H69: 38 | I69: 11.69 | J69: =+ROUND(I69*H69,2) -> 444.22
B70: =+B69+0.01 -> 11.04 | D70: Alambre de Acero N° 14 para Entorchado | G70: m | H70: 36 | I70: 0.71 | J70: =+ROUND(I70*H70,2) -> 25.56
B71: =+B70+0.01 -> 11.05 | D71: Arandela de Anclaje de A°G°, 102 x 102 x 6,35 mm, Agujero de 18 mmø | G71: u | H71: 9 | I71: 5.46 | J71: =+ROUND(I71*H71,2) -> 49.14
B72: =+B71+0.01 -> 11.06 | D72: Grillete de Acero de 70 kN | G72: u | H72: 16 | I72: 15.01 | J72: =+ROUND(I72*H72,2) -> 240.16
B73: =+B72+0.01 -> 11.07 | D73: Enlace metálico, de 254 mm x 75 mm x 38 mm, de 70 kN de resistencia | G73: u | H73: 9 | I73: 28.99 | J73: =+ROUND(I73*H73,2) -> 260.91
B74: =+B73+0.01 -> 11.08 | D74: Aislador Polimerico con Conexión Horquilla (Estructura) y Lengüeta (Linea) de 36 kV, según Especificacion Técnica, para Retenida Aislada. | G74: u | H74: 9 | I74: 76.66 | J74: =+ROUND(I74*H74,2) -> 689.94
B75: =+B74+0.01 -> 11.09 | D75: Bloque de Concreto de 0,40 x 0,40 x 0,15 m | G75: u | H75: 9 | I75: 40.94 | J75: =+ROUND(I75*H75,2) -> 368.46
B76: =+B75+0.01 -> 11.1 | D76: Tuerca-Ojo para Perno de 16 mm Ø | G76: u | H76: 5 | I76: 11.17 | J76: =+ROUND(I76*H76,2) -> 55.85
B77: =+B76+0.01 -> 11.11 | D77: Abrazadera de 4 sectores para Retenida, de 75 mm de altura, 6,35 mm de espesor y 70 kN de resistencia. Diámetro según dimensiones del poste, incluye 4 pernos de 12,7 mm Ø x 63,5 mm y 4 arandelas | G77: u | H77: 9 | I77: 81.85 | J77: =+ROUND(I77*H77,2) -> 736.65
F78: =+"SUB-TOTAL "&B66&": " -> SUB-TOTAL 11: | J78: =SUM(J67:J77) -> 3956.28
B79: =1+B66 -> 12 | D79: MATERIAL PARA PUESTA A TIERRA
B80: =+B79+0.01 -> 12.01 | D80: Electrodo de Acero Recubierto de Cobre de 16 mm Ø x 2,40 m | G80: u | H80: 49 | I80: 66.7 | J80: =+ROUND(I80*H80,2) -> 3268.3
B81: =+B80+0.01 -> 12.02 | D81: Caja Registro de Concreto para Puesta a Tierra 0,50 x 0,50 x 0,45 m | G81: u | H81: 49 | I81: 53.58 | J81: =+ROUND(I81*H81,2) -> 2625.42
B82: =+B81+0.01 -> 12.03 | D82: Plancha Doblada de Cobre para toma a Tierra de Espigas y/o Pernos | G82: u | H82: 72 | I82: 10.54 | J82: =+ROUND(I82*H82,2) -> 758.88
B83: =+B82+0.01 -> 12.04 | D83: Conector de Bronce para Electrodo de 16 mm ø y Cable de Acero con Recubrimiento Metalúrgico de Cobre de 4 AWG (21,15 mm2) | G83: u | H83: 49 | I83: 6.94 | J83: =+ROUND(I83*H83,2) -> 340.06
B84: =+B83+0.01 -> 12.05 | D84: Conector de Cobre tipo Perno Partido para Cable de Acero con Recubrimiento Metalúrgico de Cobre de 4 AWG (21,15 mm2) | G84: u | H84: 150 | I84: 7.4 | J84: =+ROUND(I84*H84,2) -> 1110
B85: =+B84+0.01 -> 12.06 | D85: Grapa en "U" para fijar conductor de PAT a Madera | G85: u | H85: 140 | I85: 0.47 | J85: =+ROUND(I85*H85,2) -> 65.8
B86: =+B85+0.01 -> 12.07 | D86: Tubo Plastico de PVC SAP de 19 mm ø x 0,5 m ( incluye curva de plastico de 19 mm ø x 90º) | G86: u | H86: 34 | I86: 2.39 | J86: =+ROUND(I86*H86,2) -> 81.26
B87: =+B86+0.01 -> 12.08 | D87: Placa de Señalización de Poste (Puesta a Tierra) | G87: u | H87: 2 | I87: 17.43 | J87: =+ROUND(I87*H87,2) -> 34.86
B88: =+B87+0.01 -> 12.09 | D88: Plantilla para Señalización de Poste (Puesta a Tierra) | G88: u | H88: 34 | I88: 16.25 | J88: =+ROUND(I88*H88,2) -> 552.5
F89: =+"SUB-TOTAL "&B79&": " -> SUB-TOTAL 12: | J89: =SUM(J80:J88) -> 8837.08
B90: =B79+1 -> 13 | D90: EQUIPO DE PROTECCION Y MANIOBRA
B91: =+B90+0.01 -> 13.01 | D91: Seccionador Fusible Unipolar Tipo Expulsion (Cut-Out) de 27/38 kV, 100A, 150 kV-BIL. | G91: u | H91: 23 | I91: 377.78 | J91: =+ROUND(I91*H91,2) -> 8688.94
B92: =+B91+0.01 -> 13.02 | D92: Fusible Tipo Expulsion de 2 A, Tipo K | G92: u | H92: 23 | I92: 7.19 | J92: =+ROUND(I92*H92,2) -> 165.37
B93: =+B92+0.01 -> 13.03 | D93: Pararrayos de Oxido Metalico, 21 kV, 10 KA Clase 1 | G93: u | H93: 23 | I93: 264.86 | J93: =+ROUND(I93*H93,2) -> 6091.78
F94: =+"SUB-TOTAL "&B90&": " -> SUB-TOTAL 13: | J94: =+SUM(J91:J93) -> 14946.09
B95: =1+B90 -> 14 | D95: TRANSFORMADORES DE DISTRIBUCION
B96: =+B95+0.01 -> 14.01 | D96: Transformador Monofásico Fase - Neutro de 5 kVA; 13,2 / 0,46-0,23 kV | G96: u | H96: 13 | I96: 3066.26 | J96: =+ROUND(I96*H96,2) -> 39861.38
B97: =+B96+0.01 -> 14.02 | D97: Transformador Monofásico Fase - Fase de 5 kVA; 13,8 / 0,46-0,23 kV | G97: u | H97: 3 | I97: 2790 | J97: =+ROUND(I97*H97,2) -> 8370
B98: =+B97+0.01 -> 14.03 | D98: Transformador Monofásico Fase - Fase de 10 kVA; 13,8 / 0,46-0,23 kV | G98: u | H98: 2 | I98: 3538 | J98: =+ROUND(I98*H98,2) -> 7076
F99: =+"SUB-TOTAL "&B95&": " -> SUB-TOTAL 14: | J99: =+SUM(J95:J98) -> 55307.38
B100: =1+B95 -> 15 | D100: TABLEROS DE DISTRIBUCIÓN
B101: =0.01+B100 -> 15.01 | D101: Tableros de Distribución Completa para S.E. Monofásica de 5 kVA; 440-220V | G101: u | H101: 16 | I101: 1884.53 | J101: =+ROUND(I101*H101,2) -> 30152.48
B102: =0.01+B101 -> 15.02 | D102: Tableros de Distribución Completa para S.E. Monofásica de 10 kVA; 440-220V | G102: u | H102: 2 | I102: 1880.73 | J102: =+ROUND(I102*H102,2) -> 3761.46
F103: =+"SUB-TOTAL "&B100&": " -> SUB-TOTAL 15: | J103: =+SUM(J100:J102) -> 33913.94
B104: =B100+1 -> 16 | D104: CABLES DE ENERGÍA DE BAJA TENSIÓN
...

Sheet MONTAJE RP
B1: VALOR REFERENCIAL
B2: MONTAJE ELECTROMECÁNICO DE REDES PRIMARIAS
B3: UBICACIÓN | E3: : | F3: ANCASH
B4: SECCIÓN II | E4: : | F4: REDES PRIMARIAS
B5: B: MONTAJE ELECTROMECÁNICO
B7: Item | C7: Descripción de Partidas | G7: Unid. | H7: Metrado Cant. | I7: Costo Unitario | J7: SubTotal S/ | L7: Costo Unitario | M7: 0.9
B9: 1 | D9: TRANSPORTE DE MATERIALES DE ALMACEN EN OBRA A PUNTO DE INSTALACIÒN
B10: =+B9+0.01 -> 1.01 | D10: Transporte de Poste de 12 m/200 daN de Almacen a Punto de Izaje, en Terreno con Acceso Carrozable | G10: u | H10: 3 | I10: 247.05 | J10: =+ROUND(I10*H10,2) -> 741.15 | L10: 274.5 | M10: =+ROUND(L10*$M$7,2) -> 247.05
B11: =+B10+0.01 -> 1.02 | D11: Transporte de Poste de 12 m/300 daN de Almacen a Punto de Izaje, en Terreno con Acceso Carrozable | G11: u | H11: 11 | I11: 270.59 | J11: =+ROUND(I11*H11,2) -> 2976.49 | L11: 300.66 | M11: =+ROUND(L11*$M$7,2) -> 270.59
B12: =+B11+0.01 -> 1.03 | D12: Transporte de Poste de 13 m/300 daN de Almacen a Punto de Izaje, en Terreno con Acceso Carrozable | G12: u | H12: 10 | I12: 301.46 | J12: =+ROUND(I12*H12,2) -> 3014.6 | L12: 334.95 | M12: =+ROUND(L12*$M$7,2) -> 301.46
B13: =+B12+0.01 -> 1.04 | D13: Transporte de Poste de 13 m/400 daN de Almacen a Punto de Izaje, en Terreno con Acceso Carrozable | G13: u | H13: 10 | I13: 338.24 | J13: =+ROUND(I13*H13,2) -> 3382.4 | L13: 375.82 | M13: =+ROUND(L13*$M$7,2) -> 338.24
B14: =+B13+0.01 -> 1.05 | D14: Transporte de Poste de madera importado de 12 m, Clase 5 de Almacen a Punto de Izaje, en Terreno sin Acceso Carrozable (< 1000 m) | G14: u | H14: 2 | I14: 272.39 | J14: =+ROUND(I14*H14,2) -> 544.78 | L14: 302.66 | M14: =+ROUND(L14*$M$7,2) -> 272.39
B15: =+B14+0.01 -> 1.06 | D15: Transporte de Cruceta de madera tratada de 90 mm x 115 mm x 1,20 m, de Almacen a Punto de Instalaciòn en Terreno con Acceso Carrozable | G15: u | H15: 11 | I15: 5.43 | J15: =+ROUND(I15*H15,2) -> 59.73 | L15: 6.03 | M15: =+ROUND(L15*$M$7,2) -> 5.43
B16: =+B15+0.01 -> 1.07 | D16: Transporte de Cruceta de madera tratada de 90 mm x 115 mm x 1,20 m, de Almacen a Punto de Instalaciòn en Terreno sin Acceso Carrozable (< 1000 m) | G16: u | H16: 2 | I16: 7.06 | J16: =+ROUND(I16*H16,2) -> 14.12 | L16: 7.84 | M16: =+ROUND(L16*$M$7,2) -> 7.06
B17: =+B16+0.01 -> 1.08 | D17: Transporte de Aislador de Porcelana Tipo Pin, Clase ANSI 56-3 de Almacén a Punto de Instalaciòn en Terreno con Acceso Carrozable | G17: u | H17: 14 | I17: 10.62 | J17: =+ROUND(I17*H17,2) -> 148.68 | L17: 11.8 | M17: =+ROUND(L17*$M$7,2) -> 10.62
B18: =+B17+0.01 -> 1.09 | D18: Transporte de Aislador de Porcelana Tipo Pin, Clase ANSI 56-3 de Almacén a Punto de Instalaciòn en Terreno sin Acceso Carrozable (< 1000 m) | G18: u | H18: 2 | I18: 13.11 | J18: =+ROUND(I18*H18,2) -> 26.22 | L18: 14.57 | M18: =+ROUND(L18*$M$7,2) -> 13.11
B19: =+B18+0.01 -> 1.1 | D19: Transporte de Aislador Line Post Polimérico de Almacén a Punto de Instalaciòn en Terreno con Acceso Carrozable | G19: u | H19: 40 | I19: 13.1 | J19: =+ROUND(I19*H19,2) -> 524 | L19: 14.56 | M19: =+ROUND(L19*$M$7,2) -> 13.1
B20: =+B19+0.01 -> 1.11 | D20: Transporte de Aislador Polimerico con Conexión Horquilla (Estructura) y Lengüeta (Linea), de 36 Kv y según Especificacion Técnica. de Almacen a Punto de Intalaciòn en Terreno con Acceso Carrozable | G20: u | H20: 25 | I20: 5.43 | J20: =+ROUND(I20*H20,2) -> 135.75 | L20: 6.03 | M20: =+ROUND(L20*$M$7,2) -> 5.43
B21: =+B20+0.01 -> 1.12 | D21: Transporte de Conductor de Aleacion de Aluminio de 35 mm² de Almacen a Punto de Intalaciòn en Terreno con Acceso Carrozable | G21: km | H21: 3.46 | I21: 64.56 | J21: =+ROUND(I21*H21,2) -> 223.38 | L21: 71.73 | M21: =+ROUND(L21*$M$7,2) -> 64.56
... B39: =+B38+0.01 -> 1.3 | D39: Transporte de Plataforma de Concreto Soporte de Transformador, de Almacen a Punto de Instalaciòn en Terreno con Acceso Carrozable | G39: u | H39: 5 | I39: 99.31 | J39: =+ROUND(I39*H39,2) -> 496.55 | L39: 110.34 | M39: =+ROUND(L39*$M$7,2) -> 99.31
F40: =+"SUB-TOTAL "&B9&": " -> SUB-TOTAL 1: | J40: =SUM(J10:J39) -> 22429.41
B41: 2 | D41: INSTALACION DE POSTES
B42: =+B41+0.01 -> 2.01 | D42: Excavación en Terreno Tipo I (Arcilloso y Conglomerado) | H42: 29.79 | I42: 61.15 | J42: =+ROUND(I42*H42,2) -> 1821.66 | L42: 67.94 | M42: =+ROUND(L42*$M$7,2) -> 61.15
B43: =+B42+0.01 -> 2.02 | D43: Excavación en Terreno Tipo II (Rocoso) | H43: 7.14 | I43: 208.14 | J43: =+ROUND(I43*H43,2) -> 1486.12 | L43: 231.27 | M43: =+ROUND(L43*$M$7,2) -> 208.14
B44: =+B43+0.01 -> 2.03 | D44: Izaje, Identificación y/o codificación, y Señalización de Poste de 12 m/200 daN (*) | G44: u | H44: 3 | I44: 123.37 | J44: =+ROUND(I44*H44,2) -> 370.11 | L44: 137.08 | M44: =+ROUND(L44*$M$7,2) -> 123.37
B45: =+B44+0.01 -> 2.04 | D45: Izaje, Identificación y/o codificación, y Señalización de Poste de 12 m/300 daN (*) | G45: u | H45: 11 | I45: 128.47 | J45: =+ROUND(I45*H45,2) -> 1413.17 | L45: 142.74 | M45: =+ROUND(L45*$M$7,2) -> 128.47
B46: =+B45+0.01 -> 2.05 | D46: Izaje, Identificación y/o codificación, y Señalización de Poste de 13 m/300 daN (*) | G46: u | H46: 10 | I46: 154.07 | J46: =+ROUND(I46*H46,2) -> 1540.7 | L46: 171.19 | M46: =+ROUND(L46*$M$7,2) -> 154.07
B47: =+B46+0.01 -> 2.06 | D47: Izaje, Identificación y/o codificación, y Señalización de Poste de 13 m/400 daN (*) | G47: u | H47: 10 | I47: 194.85 | J47: =+ROUND(I47*H47,2) -> 1948.5 | L47: 216.5 | M47: =+ROUND(L47*$M$7,2) -> 194.85
B48: =+B47+0.01 -> 2.07 | D48: Izaje, Identificación y/o codificación, y Señalización de Poste de madera importada de 12 m, Clase 5 (*) | G48: u | H48: 2 | I48: 105.19 | J48: =+ROUND(I48*H48,2) -> 210.38 | L48: 116.88 | M48: =+ROUND(L48*$M$7,2) -> 105.19
B49: =+B48+0.01 -> 2.08 | D49: Relleno y Compactación para cimentación de Poste 12m, en Terreno Tipo I (Arcilloso y Conglomerado) | H49: 12.32 | I49: 109.4 | J49: =+ROUND(I49*H49,2) -> 1347.81 | L49: 121.56 | M49: =+ROUND(L49*$M$7,2) -> 109.4
B50: =+B49+0.01 -> 2.09 | D50: Cimentación con Concreto Ciclópeo de Poste de 13m en Terreno Tipo I (Arcilloso y Conglomerado) | G50: u | H50: 13 | I50: 279.45 | J50: =+ROUND(I50*H50,2) -> 3632.85 | L50: 310.5 | M50: =+ROUND(L50*$M$7,2) -> 279.45
B51: =+B50+0.01 -> 2.1 | D51: Cimentación con concreto ciclópeo de Poste de 13m en Terreno Tipo II (Rocoso) | G51: u | H51: 7 | I51: 270.54 | J51: =+ROUND(I51*H51,2) -> 1893.78 | L51: 300.6 | M51: =+ROUND(L51*$M$7,2) -> 270.54
B52: =+B51+0.01 -> 2.11 | D52: Solado para poste de concreto (e=0.10 m. C:H, 1:8) | G52: u | H52: 20 | I52: 25.38 | J52: =+ROUND(I52*H52,2) -> 507.6 | L52: 28.2 | M52: =+ROUND(L52*$M$7,2) -> 25.38
F53: =+"SUB-TOTAL "&B41&": " -> SUB-TOTAL 2: | J53: =+SUM(J42:J52) -> 16172.68
B54: 3 | D54: INSTALACION DE RETENIDAS
B55: =+B54+0.01 -> 3.01 | D55: Excavación en Terreno Tipo I (Arcilloso y Conglomerado) | H55: 7.84 | I55: 61.15 | J55: =+ROUND(I55*H55,2) -> 479.42 | L55: 67.94 | M55: =+ROUND(L55*$M$7,2) -> 61.15
B56: =+B55+0.01 -> 3.02 | D56: Excavación en Terreno Tipo II (Rocoso) | H56: 2.24 | I56: 208.14 | J56: =+ROUND(I56*H56,2) -> 466.23 | L56: 231.27 | M56: =+ROUND(L56*$M$7,2) -> 208.14
B57: =+B56+0.01 -> 3.03 | D57: Instalación de Retenida Inclinada | G57: u | H57: 4 | I57: 87.45 | J57: =+ROUND(I57*H57,2) -> 349.8 | L57: 97.17 | M57: =+ROUND(L57*$M$7,2) -> 87.45
B58: =+B57+0.01 -> 3.04 | D58: Instalación de Retenida Inclinada en Y | G58: u | H58: 5 | I58: 103.71 | J58: =+ROUND(I58*H58,2) -> 518.55 | L58: 115.23 | M58: =+ROUND(L58*$M$7,2) -> 103.71
B59: =+B58+0.01 -> 3.05 | D59: Relleno y Compactación en Terreno Tipo I de Retenida | H59: 7.7 | I59: 90.22 | J59: =+ROUND(I59*H59,2) -> 694.69 | L59: 100.24 | M59: =+ROUND(L59*$M$7,2) -> 90.22
B60: =+B59+0.01 -> 3.06 | D60: Relleno y Compactación en Terreno Tipo II de Retenida | H60: 2.2 | I60: 96.57 | J60: =+ROUND(I60*H60,2) -> 212.45 | L60: 107.3 | M60: =+ROUND(L60*$M$7,2) -> 96.57
F61: =+"SUB-TOTAL "&B54&": " -> SUB-TOTAL 3: | J61: =+SUM(J55:J60) -> 2721.14
B62: 4 | D62: MONTAJE DE ARMADOS
B63: =+B62+0.01 -> 4.01 | D63: Armado PS1-0 (0°-5°) Monofasico retorno por tierra | G63: Jgo. | H63: 13 | I63: 61.22 | J63: =+ROUND(I63*H63,2) -> 795.86 | L63: 68.02 | M63: =+ROUND(L63*$M$7,2) -> 61.22
B64: =+B63+0.01 -> 4.02 | D64: Armado TS-0 Soporte de Retención, monofásico, retorno por tierra | G64: Jgo. | H64: 3 | I64: 80.37 | J64: =+ROUND(I64*H64,2) -> 241.11 | L64: 89.3 | M64: =+ROUND(L64*$M$7,2) -> 80.37
B65: =+B64+0.01 -> 4.03 | D65: Armado DT-0 Soporte derivación tensada monofásico retorno por tierra | G65: Jgo. | H65: 1 | I65: 69.13 | J65: =+ROUND(I65*H65,2) -> 69.13 | L65: 76.81 | M65: =+ROUND(L65*$M$7,2) -> 69.13
B66: =+B65+0.01 -> 4.04 | D66: Armado DS-0 Soporte derivación no tensada monofásico sin neutro | G66: Jgo. | H66: 6 | I66: 31.21 | J66: =+ROUND(I66*H66,2) -> 187.26 | L66: 34.68 | M66: =+ROUND(L66*$M$7,2) -> 31.21
B67: =+B66+0.01 -> 4.05 | D67: Armado DS-2V Soporte derivación monofásico | G67: Jgo. | H67: 5 | I67: 37.55 | J67: =+ROUND(I67*H67,2) -> 187.75 | L67: 41.72 | M67: =+ROUND(L67*$M$7,2) -> 37.55
B68: =+B67+0.01 -> 4.06 | D68: Armado TSVE-2 Sopte. Retención, susp. vertical, bifasico | G68: Jgo. | H68: 6 | I68: 110.21 | J68: =+ROUND(I68*H68,2) -> 661.26 | L68: 122.46 | M68: =+ROUND(L68*$M$7,2) -> 110.21
B69: =+B68+0.01 -> 4.07 | D69: Armado PA1VE-2 Soporte de ángulo vertical 10° a 30° bifásico sin neutro | G69: Jgo. | H69: 1 | I69: 102.97 | J69: =+ROUND(I69*H69,2) -> 102.97 | L69: 114.41 | M69: =+ROUND(L69*$M$7,2) -> 102.97
B70: =+B69+0.01 -> 4.08 | D70: Armado PSVE-2 Soporte de suspensión vertical 0° a 10° bifásico sin neutro | G70: Jgo. | H70: 13 | I70: 50.37 | J70: =+ROUND(I70*H70,2) -> 654.81 | L70: 55.97 | M70: =+ROUND(L70*$M$7,2) -> 50.37
B71: =+B70+0.01 -> 4.09 | D71: Armado SMM-2P S.E. 1ø, Monoposte en alineamiento, con pararrayos. | G71: Jgo. | H71: 13 | I71: 295.25 | J71: =+ROUND(I71*H71,2) -> 3838.25 | L71: 328.06 | M71: =+ROUND(L71*$M$7,2) -> 295.25
B72: =+B71+0.01 -> 4.1 | D72: Armado SBM-2V S.E. 2ø, Monoposte en alineamiento, con pararrayos. | G72: Jgo. | H72: 5 | I72: 306.71 | J72: =+ROUND(I72*H72,2) -> 1533.55 | L72: 340.79 | M72: =+ROUND(L72*$M$7,2) -> 306.71
F73: =+"SUB-TOTAL "&B62&": " -> SUB-TOTAL 4: | J73: =+SUM(J63:J72) -> 8271.95
B74: 5 | D74: MONTAJE DE CONDUCTORES
B75: =+B74+0.01 -> 5.01 | D75: Tendido y Puesta en Flecha de Conductor de Aleación de aluminio de 35 mm², Por Fase, Incluye Instalación de Amortiguadores. | G75: km | H75: 3.51 | I75: 1416.22 | J75: =+ROUND(I75*H75,2) -> 4970.93 | L75: 1573.58 | M75: =+ROUND(L75*$M$7,2) -> 1416.22
F76: =+"SUB-TOTAL "&B74&": " -> SUB-TOTAL 5: | J76: =+SUM(J75:J75) -> 4970.93
B77: =1+B74 -> 6 | D77: INSTALACION DE PUESTA A TIERRA
B78: =+B77+0.01 -> 6.01 | D78: Excavación en Terreno Tipo I (Arcilloso y Conglomerado) | H78: 101.09 | I78: 61.15 | J78: =+ROUND(I78*H78,2) -> 6181.65 | L78: 67.94 | M78: =+ROUND(L78*$M$7,2) -> 61.15
B79: =+B78+0.01 -> 6.02 | D79: Excavación en Terreno Tipo II (Rocoso) | H79: 14.31 | I79: 208.14 | J79: =+ROUND(I79*H79,2) -> 2978.48 | L79: 231.27 | M79: =+ROUND(L79*$M$7,2) -> 208.14
B80: =+B79+0.01 -> 6.03 | D80: Instalacion de Puesta a Tierra Tipo PAT-1C (Contrapeso). Instalación en Poste de Concreto Armado | G80: u | H80: 18 | I80: 39.47 | J80: =+ROUND(I80*H80,2) -> 710.46 | L80: 43.86 | M80: =+ROUND(L80*$M$7,2) -> 39.47
B81: =+B80+0.01 -> 6.04 | D81: Instalación de Puesta a Tierra Tipo PAT-2 con dos Electrodos Verticales. Instalación en Poste de Concreto Armado Centrifugado (Incluye instalación de dos Cajas de Registro) | G81: u | H81: 5 | I81: 99.81 | J81: =+ROUND(I81*H81,2) -> 499.05 | L81: 110.9 | M81: =+ROUND(L81*$M$7,2) -> 99.81
B82: =+B81+0.01 -> 6.05 | D82: Instalación de Puesta a Tierra Tipo PAT-3 con tres Electrodos Verticales. Instalación en Poste de Concreto Armado Centrifugado (Incluye instalación de tres Cajas de Registro). | G82: u | H82: 11 | I82: 143.37 | J82: =+ROUND(I82*H82,2) -> 1577.07 | L82: 159.3 | M82: =+ROUND(L82*$M$7,2) -> 143.37
B83: =+B82+0.01 -> 6.06 | D83: Instalación de Puesta a Tierra Tipo PAT-3 con tres Electrodos Verticales. Instalación en Poste de Madera (Incluye instalación de tres Cajas de Registro) | G83: u | H83: 2 | I83: 165.54 | J83: =+ROUND(I83*H83,2) -> 331.08 | L83: 183.93 | M83: =+ROUND(L83*$M$7,2) -> 165.54
B84: =+B83+0.01 -> 6.07 | D84: Relleno y Compactación de Puesta a Tierra con material adecuado | H84: 113.37 | I84: 68.82 | J84: =+ROUND(I84*H84,2) -> 7802.12 | L84: 76.47 | M84: =+ROUND(L84*$M$7,2) -> 68.82
F85: =+"SUB-TOTAL "&B77&": " -> SUB-TOTAL 6: | J85: =SUM(J78:J84) -> 20079.91
B86: =1+B77 -> 7 | D86: PRUEBAS Y PUESTA EN SERVICIO
B87: =+B86+0.01 -> 7.01 | D87: Pruebas y Puesta en Servicio de Redes Primarias | G87: Loc. | H87: 18 | I87: 350.5 | J87: =+ROUND(I87*H87,2) -> 6309 | L87: 447.22 | M87: =+ROUND(L87*$M$7,2) -> 402.5
B88: =+B87+0.01 -> 7.02 | D88: Expediente Técnico Final Conforme a Obra y de Concesión Rural de Redes Primarias (1 Original + 3 Copias), incluye la presentacion digitalizada de textos y planos en CD. | G88: Loc. | H88: 18 | I88: 250.25 | J88: =+ROUND(I88*H88,2) -> 4504.5 | L88: 332.5 | M88: =+ROUND(L88*$M$7,2) -> 299.25
F89: =+"SUB-TOTAL "&B86&": " -> SUB-TOTAL 7: | J89: =+SUM(J87:J88) -> 10813.5
D90: TOTAL MONTAJE ELECTROMECÁNICO | J90: =+ROUND(SUM(J9:J89)/2,2) -> 85459.52
B92: Nota:
B93: 02 localidades consideradas en el proyecto no se han considerado RP debido a que solo se realizaran ampliación de RS:
B94: - Miraflores los Alamos
B95: - Anchacancha-Jacanan
J97: =+J89+J85+J76+J73+J61+J53+J40 -> 85459.52
J98: =J97=J90 -> TRUE

Sheet TRANS._RP
B1: VALOR REFERENCIAL
B2: TRANSPORTE DE MATERIALES DE REDES PRIMARIAS
B3: UBICACIÓN | E3: : | F3: ANCASH
B4: SECCIÓN II | E4: : | F4: REDES PRIMARIAS
B5: C: TRANSPORTE DE MATERIALES
B7: Item | C7: Descripción de Partidas | G7: Unid. | H7: Metrado Cant. | I7: Costo Unitario | J7: SubTotal S/
B9: 1 | D9: CRUCETAS DE MADERA DE PROCEDENCIA NACIONAL
B10: =+B9+0.01 -> 1.01 | D10: =+'SUMINISTRO RP'!D10 -> Cruceta de madera tratada de 90 mm x 115 mm x 1,20 m | G10: =+'SUMINISTRO RP'!G10 -> u | H10: =+'SUMINISTRO RP'!H10 -> 13 | I10: 5.72 | J10: =+ROUND(I10*H10,2) -> 74.36 | Q10: Indice Unificado
B11: =+B10+0.01 -> 1.02 | D11: =+'SUMINISTRO RP'!D11 -> Listón de madera tratada 50 x 19 mm sección, 2,7 m longitud (incluye clavos de fijación) | G11: =+'SUMINISTRO RP'!G11 -> u | H11: =+'SUMINISTRO RP'!H11 -> 2 | I11: 2.86 | J11: =+ROUND(I11*H11,2) -> 5.72 | P11: IU | Q11: 44440 | R11: 44682 | S11: Incremento
F12: =+"SUB-TOTAL "&B9&": " -> SUB-TOTAL 1: | J12: =SUM(J10:J11) -> 80.08 | P12: 32 | Q12: 507.42 | R12: 513.36 | S12: =+R12/Q12 -> 1.0117063
B13: =1+B9 -> 2 | D13: POSTES DE CONCRETO ARMADO CENTRIFUGADO
B14: =+B13+0.01 -> 2.01 | D14: =+'SUMINISTRO RP'!D14 -> Poste de C.A.C. de 12 m/200 daN (Incluye perilla) | G14: =+'SUMINISTRO RP'!G14 -> u | H14: =+'SUMINISTRO RP'!H14 -> 3 | I14: 149.76 | J14: =+ROUND(I14*H14,2) -> 449.28
B15: =+B14+0.01 -> 2.02 | D15: =+'SUMINISTRO RP'!D15 -> Poste de C.A.C. de 12 m/300 daN (Incluye perilla) | G15: =+'SUMINISTRO RP'!G15 -> u | H15: =+'SUMINISTRO RP'!H15 -> 11 | I15: 156.56 | J15: =+ROUND(I15*H15,2) -> 1722.16
B16: =+B15+0.01 -> 2.03 | D16: =+'SUMINISTRO RP'!D16 -> Poste de C.A.C. de 13 m/300 daN (Incluye perilla) | G16: =+'SUMINISTRO RP'!G16 -> u | H16: =+'SUMINISTRO RP'!H16 -> 10 | I16: 178.72 | J16: =+ROUND(I16*H16,2) -> 1787.2
B17: =+B16+0.01 -> 2.04 | D17: =+'SUMINISTRO RP'!D17 -> Poste de C.A.C. de 13 m/400 daN (Incluye perilla) | G17: =+'SUMINISTRO RP'!G17 -> u | H17: =+'SUMINISTRO RP'!H17 -> 10 | I17: 191.36 | J17: =+ROUND(I17*H17,2) -> 1913.6
F18: =+"SUB-TOTAL "&B13&": " -> SUB-TOTAL 2: | J18: =+SUM(J14:J17) -> 5872.24
B19: 3 | D19: POSTES DE MADERA IMPORTADA
B20: =+B19+0.01 -> 3.01 | D20: =+'SUMINISTRO RP'!D20 -> Poste de madera importada (Pino Amarillo del Sur) de 12 m, Clase 5 | G20: =+'SUMINISTRO RP'!G20 -> u | H20: =+'SUMINISTRO RP'!H20 -> 2 | I20: 174.7 | J20: =+ROUND(I20*H20,2) -> 349.4
F21: =+"SUB-TOTAL "&B19&": " -> SUB-TOTAL 3: | J21: =+SUM(J19:J20) -> 349.4
B22: 4 | D22: OTROS MATERIALES DE CONCRETO ARMADO
B23: =+B22+0.01 -> 4.01 | D23: =+'SUMINISTRO RP'!D23 -> Cruceta Asimétrica de C.A.V. Za / 1,5 / 0,9 / 250 / 200 / 100 daN (Za / L / L1/ T / F / V) | G23: =+'SUMINISTRO RP'!G23 -> u | H23: =+'SUMINISTRO RP'!H23 -> 5 | I23: 17.3 | J23: =+ROUND(I23*H23,2) -> 86.5
B24: =+B23+0.01 -> 4.02 | D24: =+'SUMINISTRO RP'!D24 -> Ménsula de C.A.V. M / 1,2 / 250 / 150 / 150 daN (M / L / T / F / V) | G24: =+'SUMINISTRO RP'!G24 -> u | H24: =+'SUMINISTRO RP'!H24 -> 40 | I24: 25.6 | J24: =+ROUND(I24*H24,2) -> 1024
B25: =+B24+0.01 -> 4.03 | D25: =+'SUMINISTRO RP'!D25 -> Plataforma de Concreto Soporte de Transformador de 2,20 m, carga de trabajo de 500 daN | G25: =+'SUMINISTRO RP'!G25 -> u | H25: =+'SUMINISTRO RP'!H25 -> 5 | I25: 27.61 | J25: =+ROUND(I25*H25,2) -> 138.05
F26: =+"SUB-TOTAL "&B22&": " -> SUB-TOTAL 4: | J26: =+SUM(J23:J25) -> 1248.55
B27: =1+B22 -> 5 | D27: AISLADORES Y ACCESORIOS
B28: =+B27+0.01 -> 5.01 | D28: =+'SUMINISTRO RP'!D28 -> Aislador de Porcelana Tipo Pin, Clase ANSI 56-3 | G28: =+'SUMINISTRO RP'!G28 -> u | H28: =+'SUMINISTRO RP'!H28 -> 16 | I28: 4.43 | J28: =+ROUND(I28*H28,2) -> 70.88
B29: =+B28+0.01 -> 5.02 | D29: =+'SUMINISTRO RP'!D29 -> Espiga de AºGº de 609 mm longitud, para Cabeza de Poste y Aislador ANSI 56-3 | G29: =+'SUMINISTRO RP'!G29 -> u | H29: =+'SUMINISTRO RP'!H29 -> 16 | I29: 2.84 | J29: =+ROUND(I29*H29,2) -> 45.44
B30: =+B29+0.01 -> 5.03 | D30: =+'SUMINISTRO RP'!D30 -> Conjunto Aislador Line Post Polimérico en Cruceta:
D31: =+'SUMINISTRO RP'!D31 -> - Aislador Polimérico de 36 kV, Tipo Line Post con Espárrago de 19 mm Ø, 200 mm longitud (Alternativa a Conjunto Aislador-Espiga en Cruceta) | G31: =+'SUMINISTRO RP'!G31 -> u | H31: =+'SUMINISTRO RP'!H31 -> 40 | I31: 1.64 | J31: =+ROUND(I31*H31,2) -> 65.6
F32: =+"SUB-TOTAL "&B27&": " -> SUB-TOTAL 5: | J32: =+SUM(J28:J31) -> 181.92
B33: =1+B27 -> 6 | D33: AISLADORES DE SUSPENSIÓN Y ACCESORIOS
B34: =+B33+0.01 -> 6.01 | D34: =+'SUMINISTRO RP'!D34 -> Grillete Recto | G34: =+'SUMINISTRO RP'!G34 -> u | H34: =+'SUMINISTRO RP'!H34 -> 16 | I34: 1.69 | J34: =+ROUND(I34*H34,2) -> 27.04
B35: =+B34+0.01 -> 6.02 | D35: =+'SUMINISTRO RP'!D35 -> Aislador Polimerico con Conexión Horquilla (Estructura) y Lengüeta (Linea) de 36 kV, según Especificacion Técnica. | G35: =+'SUMINISTRO RP'!G35 -> u | H35: =+'SUMINISTRO RP'!H35 -> 16 | I35: 4.13 | J35: =+ROUND(I35*H35,2) -> 66.08
F36: =+"SUB-TOTAL "&B33&": " -> SUB-TOTAL 6: | J36: =+SUM(J33:J35) -> 93.12
B37: =1+B33 -> 7 | D37: CONDUCTOR DE ALEACIÓN DE ALUMINIO
B38: =+B37+0.01 -> 7.01 | D38: =+'SUMINISTRO RP'!D38 -> Conductor de Aleacion de Aluminio de 35 mm² | G38: =+'SUMINISTRO RP'!G38 -> km | H38: =+'SUMINISTRO RP'!H38 -> 3.51 | I38: 83.54 | J38: =+ROUND(I38*H38,2) -> 293.23
F39: =+"SUB-TOTAL "&B37&": " -> SUB-TOTAL 7: | J39: =+SUM(J38:J38) -> 293.23
B40: =B37+1 -> 8 | D40: ACCESORIOS PARA CONDUCTOR DE ALEACION ALUMINIO
B41: =+B40+0.01 -> 8.01 | D41: =+'SUMINISTRO RP'!D41 -> Varilla de Armar preformada Simple para Conductor de 35 mm² | G41: =+'SUMINISTRO RP'!G41 -> u | H41: =+'SUMINISTRO RP'!H41 -> 41 | I41: 0.68 | J41: =+ROUND(I41*H41,2) -> 27.88
B42: =+B41+0.01 -> 8.02 | D42: =+'SUMINISTRO RP'!D42 -> Grapa de Doble Via de Aluminio para Conductor de 35 mm² | G42: =+'SUMINISTRO RP'!G42 -> u | H42: =+'SUMINISTRO RP'!H42 -> 41 | I42: 0.35 | J42: =+ROUND(I42*H42,2) -> 14.35
B43: =+B42+0.01 -> 8.03 | D43: =+'SUMINISTRO RP'!D43 -> Alambre de Amarre Aluminio Recocido de 16 mm² | G43: =+'SUMINISTRO RP'!G43 -> m | H43: =+'SUMINISTRO RP'!H43 -> 170 | I43: 0.42 | J43: =+ROUND(I43*H43,2) -> 71.4
B44: =+B43+0.01 -> 8.04 | D44: =+'SUMINISTRO RP'!D44 -> Grapa de Anclaje para Conductor de 35 mm² | G44: =+'SUMINISTRO RP'!G44 -> u | H44: =+'SUMINISTRO RP'!H44 -> 16 | I44: 0.88 | J44: =+ROUND(I44*H44,2) -> 14.08
F45: =+"SUB-TOTAL "&B40&": " -> SUB-TOTAL 8: | J45: =+SUM(J41:J44) -> 127.71
B46: =1+B40 -> 9 | D46: CONDUCTOR DE COBRE
B47: =B46+0.01 -> 9.01 | D47: =+'SUMINISTRO RP'!D47 -> Cable de Acero con Recubrimiento Metalúrgico de Cu de 4 AWG (21,15 mm²), para Puesta a Tierra | G47: =+'SUMINISTRO RP'!G47 -> m | H47: =+'SUMINISTRO RP'!H47 -> 717.5 | I47: 0.84 | J47: =+ROUND(I47*H47,2) -> 602.7
F48: =+"SUB-TOTAL "&B46&": " -> SUB-TOTAL 9: | J48: =+SUM(J47:J47) -> 602.7
B49: =1+B46 -> 10 | D49: MATERIAL DE FERRETERIA PARA POSTES Y CRUCETAS
B50: =+B49+0.01 -> 10.01 | D50: =+'SUMINISTRO RP'!D50 -> Perno Cabeza Coche de AºGº de 13 mm Ø x 152 mm longitud, 76 mm maquinado, con Arandela, Tuerca y Contratuerca | G50: =+'SUMINISTRO RP'!G50 -> u | H50: =+'SUMINISTRO RP'!H50 -> 13 | I50: 0.32 | J50: =+ROUND(I50*H50,2) -> 4.16
B51: =+B50+0.01 -> 10.02 | D51: =+'SUMINISTRO RP'!D51 -> Perno de A°G° de 13 mm Ø x 305 mm, provisto de Tuerca y Contratuerca | G51: =+'SUMINISTRO RP'!G51 -> u | H51: =+'SUMINISTRO RP'!H51 -> 13 | I51: 0.32 | J51: =+ROUND(I51*H51,2) -> 4.16
B52: =+B51+0.01 -> 10.03 | D52: =+'SUMINISTRO RP'!D52 -> Perno de A°G° de 16 mm Ø x 254 mm, provisto de Tuerca y Contratuerca | G52: =+'SUMINISTRO RP'!G52 -> u | H52: =+'SUMINISTRO RP'!H52 -> 32 | I52: 0.31 | J52: =+ROUND(I52*H52,2) -> 9.92
B53: =+B52+0.01 -> 10.04 | D53: =+'SUMINISTRO RP'!D53 -> Perno de A°G° de 16 mm Ø x 305 mm, provisto de Tuerca y Contratuerca | G53: =+'SUMINISTRO RP'!G53 -> u | H53: =+'SUMINISTRO RP'!H53 -> 26 | I53: 0.34 | J53: =+ROUND(I53*H53,2) -> 8.84
B54: =+B53+0.01 -> 10.05 | D54: =+'SUMINISTRO RP'!D54 -> Perno de A°G° de 16 mm Ø x 356 mm, provisto de Tuerca y Contratuerca | G54: =+'SUMINISTRO RP'!G54 -> u | H54: =+'SUMINISTRO RP'!H54 -> 13 | I54: 0.36 | J54: =+ROUND(I54*H54,2) -> 4.68
B55: =+B54+0.01 -> 10.06 | D55: =+'SUMINISTRO RP'!D55 -> Perno Ojo de A°G° de 16 mm Ø x 254 mm, provisto de Tuerca y Contratuerca | G55: =+'SUMINISTRO RP'!G55 -> u | H55: =+'SUMINISTRO RP'!H55 -> 16 | I55: 0.45 | J55: =+ROUND(I55*H55,2) -> 7.2
B56: =+B55+0.01 -> 10.07 | D56: =+'SUMINISTRO RP'!D56 -> Perno Doble Armado de A°G° de 16 mm Ø x 508 mm, provisto de 4 Tuercas y 4 Contratuercas | G56: =+'SUMINISTRO RP'!G56 -> u | H56: =+'SUMINISTRO RP'!H56 -> 50 | I56: 0.41 | J56: =+ROUND(I56*H56,2) -> 20.5
B57: =+B56+0.01 -> 10.08 | D57: =+'SUMINISTRO RP'!D57 -> Tirafondo de A°G° de 13 mm ø x 102 mm de longitud | G57: =+'SUMINISTRO RP'!G57 -> u | H57: =+'SUMINISTRO RP'!H57 -> 2 | I57: 0.49 | J57: =+ROUND(I57*H57,2) -> 0.98
B58: =+B57+0.01 -> 10.09 | D58: =+'SUMINISTRO RP'!D58 -> Brazo-Soporte (Riostra) de Perfil Angular de A°G° de 38 x 38 x 5 mm y 710 mm longitud | G58: =+'SUMINISTRO RP'!G58 -> u | H58: =+'SUMINISTRO RP'!H58 -> 13 | I58: 1.33 | J58: =+ROUND(I58*H58,2) -> 17.29
B59: =+B58+0.01 -> 10.1 | D59: =+'SUMINISTRO RP'!D59 -> Arandela Cuadrada Plana de A° G°, 57 x 57 x 5 mm, Agujero de 18 mm Ø | G59: =+'SUMINISTRO RP'!G59 -> u | H59: =+'SUMINISTRO RP'!H59 -> 107 | I59: 0.09 | J59: =+ROUND(I59*H59,2) -> 9.63
B60: =+B59+0.01 -> 10.11 | D60: =+'SUMINISTRO RP'!D60 -> Arandela Cuadrada Curva de A° G°, 57 x 57 x 5 mm, Agujero de 18 mm Ø | G60: =+'SUMINISTRO RP'!G60 -> u | H60: =+'SUMINISTRO RP'!H60 -> 211 | I60: 0.09 | J60: =+ROUND(I60*H60,2) -> 18.99
B61: =+B60+0.01 -> 10.12 | D61: =+'SUMINISTRO RP'!D61 -> Plantillas para Identificación y/o codificación de Postes (Peligro, Identificación y/o codificación y Fases) | G61: =+'SUMINISTRO RP'!G61 -> Jgo. | H61: =+'SUMINISTRO RP'!H61 -> 34 | I61: 0.22 | J61: =+ROUND(I61*H61,2) -> 7.48
... B64: =+B63+0.01 -> 10.15 | D64: =+'SUMINISTRO RP'!D64 -> Placa de Secuencia de Fases y accesorios de fijación | G64: =+'SUMINISTRO RP'!G64 -> u | H64: =+'SUMINISTRO RP'!H64 -> 2 | I64: 0.07 | J64: =+ROUND(I64*H64,2) -> 0.14
F65: =+"SUB-TOTAL "&B49&": " -> SUB-TOTAL 10: | J65: =+SUM(J50:J64) -> 114.41
B66: =1+B49 -> 11 | D66: RETENIDAS Y ANCLAJES
B67: =+B66+0.01 -> 11.01 | D67: =+'SUMINISTRO RP'!D67 -> Cable de Acero Grado Siemens Martin, de 10 mm Ø, 7 hilos | G67: =+'SUMINISTRO RP'!G67 -> m | H67: =+'SUMINISTRO RP'!H67 -> 154 | I67: 0.58 | J67: =+ROUND(I67*H67,2) -> 89.32
B68: =+B67+0.01 -> 11.02 | D68: =+'SUMINISTRO RP'!D68 -> Varilla de Anclaje de A°G° de 16 mm Ø x 2,40 m, provisto de Ojal Guardacabo en un extremo; Tuerca y Contratuerca en el otro | G68: =+'SUMINISTRO RP'!G68 -> u | H68: =+'SUMINISTRO RP'!H68 -> 9 | I68: 2.37 | J68: =+ROUND(I68*H68,2) -> 21.33
B69: =+B68+0.01 -> 11.03 | D69: =+'SUMINISTRO RP'!D69 -> Mordaza Preformada de A°G° para Cable de 10 mm Ø | G69: =+'SUMINISTRO RP'!G69 -> u | H69: =+'SUMINISTRO RP'!H69 -> 38 | I69: 0.85 | J69: =+ROUND(I69*H69,2) -> 32.3
B70: =+B69+0.01 -> 11.04 | D70: =+'SUMINISTRO RP'!D70 -> Alambre de Acero N° 14 para Entorchado | G70: =+'SUMINISTRO RP'!G70 -> m | H70: =+'SUMINISTRO RP'!H70 -> 36 | I70: 0.02 | J70: =+ROUND(I70*H70,2) -> 0.72
B71: =+B70+0.01 -> 11.05 | D71: =+'SUMINISTRO RP'!D71 -> Arandela de Anclaje de A°G°, 102 x 102 x 6,35 mm, Agujero de 18 mmø | G71: =+'SUMINISTRO RP'!G71 -> u | H71: =+'SUMINISTRO RP'!H71 -> 9 | I71: 0.2 | J71: =+ROUND(I71*H71,2) -> 1.8
B72: =+B71+0.01 -> 11.06 | D72: =+'SUMINISTRO RP'!D72 -> Grillete de Acero de 70 kN | G72: =+'SUMINISTRO RP'!G72 -> u | H72: =+'SUMINISTRO RP'!H72 -> 16 | I72: 1.15 | J72: =+ROUND(I72*H72,2) -> 18.4
B73: =+B72+0.01 -> 11.07 | D73: =+'SUMINISTRO RP'!D73 -> Enlace metálico, de 254 mm x 75 mm x 38 mm, de 70 kN de resistencia | G73: =+'SUMINISTRO RP'!G73 -> u | H73: =+'SUMINISTRO RP'!H73 -> 9 | I73: 0.25 | J73: =+ROUND(I73*H73,2) -> 2.25
B74: =+B73+0.01 -> 11.08 | D74: =+'SUMINISTRO RP'!D74 -> Aislador Polimerico con Conexión Horquilla (Estructura) y Lengüeta (Linea) de 36 kV, según Especificacion Técnica, para Retenida Aislada. | G74: =+'SUMINISTRO RP'!G74 -> u | H74: =+'SUMINISTRO RP'!H74 -> 9 | I74: 4.13 | J74: =+ROUND(I74*H74,2) -> 37.17
B75: =+B74+0.01 -> 11.09 | D75: =+'SUMINISTRO RP'!D75 -> Bloque de Concreto de 0,40 x 0,40 x 0,15 m | G75: =+'SUMINISTRO RP'!G75 -> u | H75: =+'SUMINISTRO RP'!H75 -> 9 | I75: 23.88 | J75: =+ROUND(I75*H75,2) -> 214.92
B76: =+B75+0.01 -> 11.1 | D76: =+'SUMINISTRO RP'!D76 -> Tuerca-Ojo para Perno de 16 mm Ø | G76: =+'SUMINISTRO RP'!G76 -> u | H76: =+'SUMINISTRO RP'!H76 -> 5 | I76: 0.48 | J76: =+ROUND(I76*H76,2) -> 2.4
B77: =+B76+0.01 -> 11.11 | D77: =+'SUMINISTRO RP'!D77 -> Abrazadera de 4 sectores para Retenida, de 75 mm de altura, 6,35 mm de espesor y 70 kN de resistencia. Diámetro según dimensiones del poste, incluye 4 pernos de 12,7 mm Ø x 63,5 mm y 4 arandelas | G77: =+'SUMINISTRO RP'!G77 -> u | H77: =+'SUMINISTRO RP'!H77 -> 9 | I77: 2.75 | J77: =+ROUND(I77*H77,2) -> 24.75
F78: =+"SUB-TOTAL "&B66&": " -> SUB-TOTAL 11: | J78: =+SUM(J67:J77) -> 445.36
B79: =1+B66 -> 12 | D79: MATERIAL PARA PUESTA A TIERRA
B80: =+B79+0.01 -> 12.01 | D80: =+'SUMINISTRO RP'!D80 -> Electrodo de Acero Recubierto de Cobre de 16 mm Ø x 2,40 m | G80: =+'SUMINISTRO RP'!G80 -> u | H80: =+'SUMINISTRO RP'!H80 -> 49 | I80: 2.59 | J80: =+ROUND(I80*H80,2) -> 126.91
B81: =+B80+0.01 -> 12.02 | D81: =+'SUMINISTRO RP'!D81 -> Caja Registro de Concreto para Puesta a Tierra 0,50 x 0,50 x 0,45 m | G81: =+'SUMINISTRO RP'!G81 -> u | H81: =+'SUMINISTRO RP'!H81 -> 49 | I81: 23.88 | J81: =+ROUND(I81*H81,2) -> 1170.12
B82: =+B81+0.01 -> 12.03 | D82: =+'SUMINISTRO RP'!D82 -> Plancha Doblada de Cobre para toma a Tierra de Espigas y/o Pernos | G82: =+'SUMINISTRO RP'!G82 -> u | H82: =+'SUMINISTRO RP'!H82 -> 72 | I82: 0.07 | J82: =+ROUND(I82*H82,2) -> 5.04
B83: =+B82+0.01 -> 12.04 | D83: =+'SUMINISTRO RP'!D83 -> Conector de Bronce para Electrodo de 16 mm ø y Cable de Acero con Recubrimiento Metalúrgico de Cobre de 4 AWG (21,15 mm2) | G83: =+'SUMINISTRO RP'!G83 -> u | H83: =+'SUMINISTRO RP'!H83 -> 49 | I83: 0.24 | J83: =+ROUND(I83*H83,2) -> 11.76
B84: =+B83+0.01 -> 12.05 | D84: =+'SUMINISTRO RP'!D84 -> Conector de Cobre tipo Perno Partido para Cable de Acero con Recubrimiento Metalúrgico de Cobre de 4 AWG (21,15 mm2) | G84: =+'SUMINISTRO RP'!G84 -> u | H84: =+'SUMINISTRO RP'!H84 -> 150 | I84: 0.16 | J84: =+ROUND(I84*H84,2) -> 24
B85: =+B84+0.01 -> 12.06 | D85: =+'SUMINISTRO RP'!D85 -> Grapa en "U" para fijar conductor de PAT a Madera | G85: =+'SUMINISTRO RP'!G85 -> u | H85: =+'SUMINISTRO RP'!H85 -> 140 | I85: 0.05 | J85: =+ROUND(I85*H85,2) -> 7
B86: =+B85+0.01 -> 12.07 | D86: =+'SUMINISTRO RP'!D86 -> Tubo Plastico de PVC SAP de 19 mm ø x 0,5 m ( incluye curva de plastico de 19 mm ø x 90º) | G86: =+'SUMINISTRO RP'!G86 -> u | H86: =+'SUMINISTRO RP'!H86 -> 34 | I86: 0.12 | J86: =+ROUND(I86*H86,2) -> 4.08
B87: =+B86+0.01 -> 12.08 | D87: =+'SUMINISTRO RP'!D87 -> Placa de Señalización de Poste (Puesta a Tierra) | G87: =+'SUMINISTRO RP'!G87 -> u | H87: =+'SUMINISTRO RP'!H87 -> 2 | I87: 0.16 | J87: =+ROUND(I87*H87,2) -> 0.32
B88: =+B87+0.01 -> 12.09 | D88: =+'SUMINISTRO RP'!D88 -> Plantilla para Señalización de Poste (Puesta a Tierra) | G88: =+'SUMINISTRO RP'!G88 -> u | H88: =+'SUMINISTRO RP'!H88 -> 34 | I88: 0.12 | J88: =+ROUND(I88*H88,2) -> 4.08
F89: =+"SUB-TOTAL "&B79&": " -> SUB-TOTAL 12: | J89: =+SUM(J80:J88) -> 1353.31
B90: =B79+1 -> 13 | D90: EQUIPO DE PROTECCION Y MANIOBRA
B91: =+B90+0.01 -> 13.01 | D91: =+'SUMINISTRO RP'!D91 -> Seccionador Fusible Unipolar Tipo Expulsion (Cut-Out) de 27/38 kV, 100A, 150 kV-BIL. | G91: =+'SUMINISTRO RP'!G91 -> u | H91: =+'SUMINISTRO RP'!H91 -> 23 | I91: 8.47 | J91: =+ROUND(I91*H91,2) -> 194.81
B92: =+B91+0.01 -> 13.02 | D92: =+'SUMINISTRO RP'!D92 -> Fusible Tipo Expulsion de 2 A, Tipo K | G92: =+'SUMINISTRO RP'!G92 -> u | H92: =+'SUMINISTRO RP'!H92 -> 23 | I92: 0.12 | J92: =+ROUND(I92*H92,2) -> 2.76
B93: =+B92+0.01 -> 13.03 | D93: =+'SUMINISTRO RP'!D93 -> Pararrayos de Oxido Metalico, 21 kV, 10 KA Clase 1 | G93: =+'SUMINISTRO RP'!G93 -> u | H93: =+'SUMINISTRO RP'!H93 -> 23 | I93: 3.18 | J93: =+ROUND(I93*H93,2) -> 73.14
F94: =+"SUB-TOTAL "&B90&": " -> SUB-TOTAL 13: | J94: =+SUM(J91:J93) -> 270.71
B95: =1+B90 -> 14 | D95: TRANSFORMADORES DE DISTRIBUCION
B96: =+B95+0.01 -> 14.01 | D96: =+'SUMINISTRO RP'!D96 -> Transformador Monofásico Fase - Neutro de 5 kVA; 13,2 / 0,46-0,23 kV | G96: =+'SUMINISTRO RP'!G96 -> u | H96: =+'SUMINISTRO RP'!H96 -> 13 | I96: 244.19 | J96: =+ROUND(I96*H96,2) -> 3174.47
B97: =+B96+0.01 -> 14.02 | D97: =+'SUMINISTRO RP'!D97 -> Transformador Monofásico Fase - Fase de 5 kVA; 13,8 / 0,46-0,23 kV | G97: =+'SUMINISTRO RP'!G97 -> u | H97: =+'SUMINISTRO RP'!H97 -> 3 | I97: 253.96 | J97: =+ROUND(I97*H97,2) -> 761.88
B98: =+B97+0.01 -> 14.03 | D98: =+'SUMINISTRO RP'!D98 -> Transformador Monofásico Fase - Fase de 10 kVA; 13,8 / 0,46-0,23 kV | G98: =+'SUMINISTRO RP'!G98 -> u | H98: =+'SUMINISTRO RP'!H98 -> 2 | I98: 264.53 | J98: =+ROUND(I98*H98,2) -> 529.06
F99: =+"SUB-TOTAL "&B95&": " -> SUB-TOTAL 14: | J99: =+SUM(J95:J98) -> 4465.41
B100: =1+B95 -> 15 | D100: TABLEROS DE DISTRIBUCIÓN
B101: =0.01+B100 -> 15.01 | D101: =+'SUMINISTRO RP'!D101 -> Tableros de Distribución Completa para S.E. Monofásica de 5 kVA; 440-220V | G101: =+'SUMINISTRO RP'!G101 -> u | H101: =+'SUMINISTRO RP'!H101 -> 16 | I101: 35.28 | J101: =+ROUND(I101*H101,2) -> 564.48
B102: =0.01+B101 -> 15.02 | D102: =+'SUMINISTRO RP'!D102 -> Tableros de Distribución Completa para S.E. Monofásica de 10 kVA; 440-220V | G102: =+'SUMINISTRO RP'!G102 -> u | H102: =+'SUMINISTRO RP'!H102 -> 2 | I102: 39.68 | J102: =+ROUND(I102*H102,2) -> 79.36
F103: =+"SUB-TOTAL "&B100&": " -> SUB-TOTAL 15: | J103: =+SUM(J100:J102) -> 643.84
B104: =B100+1 -> 16 | D104: CABLES DE ENERGÍA DE BAJA TENSIÓN
...

Sheet POLINOMICA RP
B3: FORMULA POLINÓMICA
C6: PROYECTO :
C7: AMPLIACIÓN DEL SERVICIO DE ENERGÍA ELÉCTRICA EN LA PROVINCIA DEL SANTA Y EN EL DISTRITO DE PAMPAROMAS – DEPARTAMENTO DE ANCASH”
C9: REDES PRIMARIAS
C10: PRESUPUESTO BASE S/ | D10: =+'RESUMEN RP'!F21 -> #REF! | L10: =D10=SUM(G13:G28) -> #REF! | M10: =D10='RESUMEN RP'!F21 -> #REF!
B12: Nº | C12: ELEMENTO REPRESENTATIVO | D12: INDICE | E12: SIMBOLO | F12: SIMBOLO MONOMIO | G12: MONTO | H12: INCIDENCIA | I12: % PARCIAL | J12: COEFICIENTE
B13: 1 | C13: POSTES DE MADERA IMPORTADA | D13: 042 | E13: PM | F13: PC | G13: =+'SUMINISTRO RP'!J21 -> 3729.04 | H13: =ROUND(G13/$D$10,3) -> #REF! | I13: =ROUND(G13/SUM($G$13:$G$20),4) -> 0.0497 | J13: =ROUND(SUM(H13:H20),3) -> #REF!
C14: CRUCETAS DE MADERA | D14: 043 | E14: CM | G14: =+'SUMINISTRO RP'!J12 -> 1419.7 | H14: =ROUND(G14/$D$10,3) -> #REF! | I14: =ROUND(G14/SUM($G$13:$G$20),4) -> 0.0189
C15: POSTES DE CONCRETO | D15: 062 | E15: PC | G15: =+'SUMINISTRO RP'!J18 -> 35601.32 | H15: =ROUND(G15/$D$10,3) -> #REF! | I15: =ROUND(G15/SUM($G$13:$G$20),4) -> 0.4748
C16: OTROS MATERIALES DE CONCRETO ARMADO | D16: 062 | E16: CC | G16: =+'SUMINISTRO RP'!J26 -> 7253.5 | H16: =ROUND(G16/$D$10,3) -> #REF! | I16: =ROUND(G16/SUM($G$13:$G$20),4) -> 0.0967
C17: FERRETERIA PARA POSTES Y CRUCETAS | D17: 002 | E17: FP | G17: =+'SUMINISTRO RP'!J65 -> 3611.97 | H17: =ROUND(G17/$D$10,3) -> #REF! | I17: =ROUND(G17/SUM($G$13:$G$20),4) -> 0.0482
C18: RETENIDAS Y ANCLAJES | D18: 002 | E18: FE | G18: =+'SUMINISTRO RP'!J78 -> 3956.28 | H18: =ROUND(G18/$D$10,3) -> #REF! | I18: =ROUND(G18/SUM($G$13:$G$20),4) -> 0.0528
C19: CONDUCTOR DE COBRE Y ACCESORIOS | D19: 006 | E19: CU | G19: =+'SUMINISTRO RP'!J45+'SUMINISTRO RP'!J48 -> 10565.5 | H19: =ROUND(G19/$D$10,3) -> #REF! | I19: =ROUND(G19/SUM($G$13:$G$20),4) -> 0.1409
C20: MATERIAL PARA PUESTA A TIERRA | D20: 006 | E20: PT | G20: =+'SUMINISTRO RP'!J89 -> 8837.08 | H20: =ROUND(G20/$D$10,3) -> #REF! | I20: =ROUND(G20/SUM($G$13:$G$20),4) -> 0.1179
B21: 2 | C21: EQUIPOS DE PROTECCIÓN | D21: 011 | E21: AE1 | F21: AE1 | G21: =+'SUMINISTRO RP'!J94 -> 14946.09 | H21: =ROUND(G21/$D$10,3) -> #REF! | I21: =ROUND(G21/SUM($G$21:$G$24),4) -> 0.3927 | J21: =ROUND(SUM(H21:H24),3) -> #REF!
C22: AISLADORES Y ACCESORIOS | D22: 011 | E22: AE2 | G22: =+'SUMINISTRO RP'!J32+'SUMINISTRO RP'!J36 -> 11695.28 | H22: =ROUND(G22/$D$10,3) -> #REF! | I22: =ROUND(G22/SUM($G$21:$G$24),4) -> 0.3073
C23: CABLES DE ENERGÍA | D23: 019 | E23: NY | G23: =+'SUMINISTRO RP'!J39 -> 7896.17 | H23: =ROUND(G23/$D$10,3) -> #REF! | I23: =ROUND(G23/SUM($G$21:$G$24),4) -> 0.2075
C24: CONDUCTORES DE AAAC Y ACCESORIOS | D24: 030 | E24: DI | G24: =+'SUMINISTRO RP'!J107 -> 3523.5 | H24: =ROUND(G24/$D$10,3) -> #REF! | I24: =ROUND(G24/SUM($G$21:$G$24),4) -> 0.0926
B25: 3 | C25: TRANSFORMADORES DE DISTRIBUCIÓN Y TABLEROS | D25: 048 | E25: EN | F25: EN | G25: =+'SUMINISTRO RP'!J99+'SUMINISTRO RP'!J103 -> 89221.32 | H25: =ROUND(G25/$D$10,3) -> #REF! | I25: =ROUND(G25/SUM($G$25:$G$25),4) -> 1 | J25: =ROUND(SUM(H25),3) -> #REF!
B26: 4 | C26: MONTAJE ELECTROMECANICO | D26: 047 | E26: J | F26: J | G26: =+'MONTAJE RP'!J90 -> 85459.52 | H26: =ROUND(G26/$D$10,3) -> #REF! | I26: =ROUND(G26/($G$26+$G$27),4) -> 0.8405 | J26: =ROUND(SUM(H26:H27),3) -> #REF!
C27: TRANSPORTE | D27: 032 | E27: FT | G27: =+TRANS._RP!J109 -> 16212.19 | H27: =ROUND(G27/$D$10,3) -> #REF! | I27: =ROUND(G27/($G$26+$G$27),4) -> 0.1595
B28: 5 | C28: GASTOS GENERALES Y UTILIDADES | D28: 039 | E28: GG | F28: GG | G28: =+'RESUMEN RP'!F18+'RESUMEN RP'!F19 -> #REF! | H28: =ROUND(G28/$D$10,3) -> #REF! | I28: =+G28/G28 -> #REF! | J28: =ROUND(SUM(H28),3) -> #REF!
B30: K= | C30: =J13&" PCr/PCo + "&J21&" AE1r/AE1o + "&J25&" ENr/ENo+ "&J26&" Jr/Jo + "&J28&" GGr/GGo" -> #REF!
B33: NOTAS:
B35: 1.- | C35: En la fórmula los sub-indices "o" de cada símbolo corresponden al indice de precios según (CREPCO) a la
C36: fecha de Elaboración del Presupuesto (Presupuesto Base) y los sub-indices "r" al indice de precios al
C37: momento de reajuste o fecha de valorización
B38: 2.- | C38: En el caso de los monomios compuestos por varios indices se ha considerado para efecto de denominación
C39: el símbolo que tiene mayor porcentaje de incidencia
B40: 3.- | C40: En caso de cambios en el suministro se deberá actualizar la formula polinómica.
H42: =+IF(SUM(H13:H28)=1,"OK","X") -> #REF! | I42: =+IF(SUM(I13:I28)=5,"OK","X") -> #REF! | J42: =+IF(SUM(J13:J28)=1,"OK","X") -> #REF!

Sheet RESUMEN RS
B2: VALOR REFERENCIAL
B3: REDES SECUNDARIAS
B5: “AMPLIACIÓN DEL SERVICIO DE ENERGÍA ELÉCTRICA EN LA PROVINCIA DEL SANTA Y EN EL DISTRITO DE PAMPAROMAS – DEPARTAMENTO DE ANCASH”
B7: UBICACIÓN | D7: : | E7: ANCASH
B8: SECCIÓN II | D8: : | E8: REDES SECUNDARIAS
F9: =+#REF! -> #REF!
F10: =+#REF! -> #REF!
B11: ITEM | C11: DESCRIPCION | F11: TOTAL S/
B13: A | D13: SUMINISTRO DE MATERIALES | F13: =+'SUMINISTRO RS'!J103 -> 301377.1
B14: B | D14: MONTAJE ELECTROMECANICO | F14: =+'MONTAJE RS'!J96 -> 273560.14
B15: C | D15: TRANSPORTE DE MATERIALES | F15: =+TRANS.RS!J103 -> 39859.51 | G15: Ñ
B16: D | D16: TOTAL COSTO DIRECTO | F16: =SUM(F13:F15) -> 614796.75
B18: E | E18: GASTOS GENERALES | F18: =+ROUND(F16*H18,2) -> #REF! | H18: =+#REF! -> #REF!
B19: F | E19: UTILIDADES | F19: =+ROUND(F16*H19,2) -> #REF! | H19: =+#REF! -> #REF!
D21: COSTO TOTAL S/ (No incluye I.G.V.) | F21: =SUM(F16:F19) -> #REF! | H21: =F21=#REF! -> #REF!

Sheet Alternativa-RS
B3: RESUMEN DEL VALOR REFERENCIAL
B5: UBICACIÓN | D5: :
B6: SECCIÓN I | D6: : | E6: RESUMEN GENERAL REDES SECUNDARIAS
B9: ITEM | C9: DESCRIPCION | F9: TOTAL (S/.)
B11: A | D11: SUMINISTROS DE MATERIALES | F11: =+'RESUMEN RS'!F13 -> 301377.1
D12: Origen Nacional | F12: =+F11-F13 -> 191856.62
D13: Origen Importado | F13: =+'SUMINISTRO RS'!J22+'SUMINISTRO RS'!J14+'SUMINISTRO RS'!J39 -> 109520.48
B15: B | D15: MONTAJE ELECTROMECANICO | F15: =+'RESUMEN RS'!F14 -> 273560.14
D16: M.O. Calificada | F16: =ROUND(H16*F15,2) -> 172342.89 | H16: 0.63
D17: M.O. No Calificada | F17: =ROUND(H17*F15,2) -> 101217.25 | H17: 0.37
B19: B.1 | D19: ACTIVIDADES COMPLEMENTARIAS DE MONTAJE | F19: 0
B21: C | D21: TRANSPORTE DE MATERIALES | F21: =+'RESUMEN RS'!F15 -> 39859.51
B24: D | D24: TOTAL COSTO DIRECTO (C.D.) | F24: =+F11+F15+F21+F19 -> 614796.75
F32: =+F24+F27+F29 -> 614796.75

Sheet SUMINISTRO RS
B1: VALOR REFERENCIAL
B2: SUMINISTRO DE MATERIALES REDES SECUNDARIAS
B3: UBICACIÓN | E3: : | F3: ANCASH
B4: SECCIÓN III | E4: : | F4: REDES SECUNDARIAS
B5: A: SUMINISTRO DE MATERIALES
B7: Item | C7: Descripción de Partidas | G7: Unid. | H7: Metrado Cant. | I7: Costo Unitario | J7: SubTotal S/
B9: 1 | D9: POSTES DE CONCRETO ARMADO Y MADERA IMPORTADA
B10: =+B9+0.01 -> 1.01 | D10: Poste de C.A.C. de 8 m/200 daN (Incluye perilla) | G10: u | H10: 153 | I10: 372.21 | J10: =+ROUND(I10*H10,2) -> 56948.13
B11: =+B10+0.01 -> 1.02 | D11: Poste de C.A.C. de 8 m/300 daN (Incluye perilla) | G11: u | H11: 79 | I11: 402.99 | J11: =+ROUND(I11*H11,2) -> 31836.21
F12: =+"SUB-TOTAL "&B9&": " -> SUB-TOTAL 1: | J12: =SUM(J10:J11) -> 88784.34
B13: =1+B9 -> 2 | D13: POSTES DE MADERA IMPORTADA
B14: =+B13+0.01 -> 2.01 | D14: Poste de madera importada (Pino Amarillo del Sur) de 8 m, Clase 7 | G14: u | H14: 9 | I14: 805.66 | J14: =+ROUND(I14*H14,2) -> 7250.94
F15: =+"SUB-TOTAL "&B13&": " -> SUB-TOTAL 2: | J15: =SUM(J14) -> 7250.94
B16: =+B13+1 -> 3 | D16: CABLES Y CONDUCTORES DE ALUMINIO
B17: =+B16+0.01 -> 3.01 | D17: Conductor Autoportante de Aluminio 2X25+16/25 mm² | G17: km | H17: 1.46 | I17: 7749.03 | J17: =+ROUND(I17*H17,2) -> 11313.58
B18: =+B17+0.01 -> 3.02 | D18: Conductor Autoportante de Aluminio 2X16+16/25 mm² | G18: km | H18: 0.05 | I18: 6431.99 | J18: =+ROUND(I18*H18,2) -> 321.6
B19: =+B18+0.01 -> 3.03 | D19: Conductor Autoportante de Aluminio 2X25/25 mm² | G19: km | H19: 7.08 | I19: 6248.95 | J19: =+ROUND(I19*H19,2) -> 44242.57
B20: =+B19+0.01 -> 3.04 | D20: Conductor Autoportante de Aluminio 1X16+16/25 mm² | G20: km | H20: 0.18 | I20: 4940.38 | J20: =+ROUND(I20*H20,2) -> 889.27
B21: =+B20+0.01 -> 3.05 | D21: Conductor Autoportante de Aluminio 1X16/25 mm² | G21: km | H21: 4.06 | I21: 3440.29 | J21: =+ROUND(I21*H21,2) -> 13967.58
F22: =+"SUB-TOTAL "&B16&": " -> SUB-TOTAL 3: | J22: =+SUM(J17:J21) -> 70734.6
B23: =+B16+1 -> 4 | D23: ACCESORIOS DE CABLES AUTOPORTANTES
B24: =+B23+0.01 -> 4.01 | D24: Grapa de Suspensión Angular para Conductor de Aleacion de Aluminio de 25 mm2 | G24: u | H24: 163 | I24: 12 | J24: =+ROUND(I24*H24,2) -> 1956
B25: =+B24+0.01 -> 4.02 | D25: Grapa de Anclaje Cónica para Conductor de Aleación de Aluminio de 25 mm2 | G25: u | H25: 218 | I25: 16.87 | J25: =+ROUND(I25*H25,2) -> 3677.66
B26: =+B25+0.01 -> 4.03 | D26: Conector Bimetálico para Al 25 mm2 / Cu 4-10 mm2, para Neutro Desnudo, tipo Cuña | G26: u | H26: 2 | I26: 5.21 | J26: =+ROUND(I26*H26,2) -> 10.42
B27: =+B26+0.01 -> 4.04 | D27: Conector Bimetalico Aislado, para Al 16-35 mm2 / Cu 4-10 mm2, para Fase Aislada, tipo Perforación | G27: u | H27: 4 | I27: 7.04 | J27: =+ROUND(I27*H27,2) -> 28.16
B28: =+B27+0.01 -> 4.05 | D28: Conector para Al 25 mm², para Neutro Desnudo, tipo Cuña | G28: u | H28: 26 | I28: 9.06 | J28: =+ROUND(I28*H28,2) -> 235.56
B29: =+B28+0.01 -> 4.06 | D29: Conector Aislado para Al 16-35 mm2, para Fase Aislada, tipo Perforación | G29: u | H29: 52 | I29: 10.95 | J29: =+ROUND(I29*H29,2) -> 569.4
B30: =+B29+0.01 -> 4.07 | D30: Correa Plástica de Amarre, color negro | G30: u | H30: 1838 | I30: 0.4 | J30: =+ROUND(I30*H30,2) -> 735.2
B31: =+B30+0.01 -> 4.08 | D31: Cinta Autofundente para extremo de cable | G31: m | H31: 51.3 | I31: 4.46 | J31: =+ROUND(I31*H31,2) -> 228.8
B32: =+B31+0.01 -> 4.09 | D32: Cinta aislante | G32: m | H32: 19 | I32: 1.53 | J32: =+ROUND(I32*H32,2) -> 29.07
F33: =+"SUB-TOTAL "&B23&": " -> SUB-TOTAL 4: | J33: =+SUM(J23:J32) -> 7470.27
B34: =+B23+1 -> 5 | D34: CABLES Y CONDUCTORES DE COBRE
B35: =+B34+0.01 -> 5.01 | D35: Conductor de Cobre Recocido, tipo N2XY, Tripolar, 3 x 10 mm2, cubierta negra | G35: m | H35: 1.2 | I35: 19.26 | J35: =+ROUND(I35*H35,2) -> 23.11
B36: =+B35+0.01 -> 5.02 | D36: Conductor de Cobre Recocido, tipo N2XY, Bipolar, 2 x 2,5 mm2 | G36: m | H36: 111.5 | I36: 4.82 | J36: =+ROUND(I36*H36,2) -> 537.43
B37: =+B36+0.01 -> 5.03 | D37: Conductor de Cobre Concéntrico, 2 x 4 mm2, con aislamiento y cubierta de PVC | G37: m | H37: 3985 | I37: 4.8 | J37: =+ROUND(I37*H37,2) -> 19128
B38: =+B37+0.01 -> 5.04 | D38: Cable de Acero con Recubrimiento Metalúrgico de Cu de 4 AWG (21,15 mm²), para Puesta a Tierra | G38: m | H38: 925.5 | I38: 12.8 | J38: =+ROUND(I38*H38,2) -> 11846.4
F39: =+"SUB-TOTAL "&B34&": " -> SUB-TOTAL 5: | J39: =+SUM(J35:J38) -> 31534.94
B40: =+B34+1 -> 6 | D40: LUMINARIAS, LAMPARAS Y ACCESORIOS
B41: =+B40+0.01 -> 6.01 | D41: Pastoral tubo A°G° 38 mm Ø interior, 500 mm avance horizontal, 720 mm altura y 20° inclinación, provisto de 2 abrazaderas simples y 4 tirafondos para poste de madera | G41: u | H41: 2 | I41: 55.07 | J41: =+ROUND(I41*H41,2) -> 110.14
B42: =+B41+0.01 -> 6.02 | D42: Pastoral tubo A°G° 38 mm Ø interior, 500 mm avance horizontal, 720 mm altura y 20° inclinación, provisto de 2 abrazaderas dobles para poste de concreto | G42: u | H42: 43 | I42: 66.86 | J42: =+ROUND(I42*H42,2) -> 2874.98
B43: =+B42+0.01 -> 6.03 | D43: Luminaria completa con equipo para Lámpara de Vapor de Sodio de 50 W | G43: u | H43: 45 | I43: 251.32 | J43: =+ROUND(I43*H43,2) -> 11309.4
B44: =+B43+0.01 -> 6.04 | D44: Lámpara de Vapor de Sodio de Alta Presión de 50 W | G44: u | H44: 45 | I44: 38.94 | J44: =+ROUND(I44*H44,2) -> 1752.3
B45: =+B44+0.01 -> 6.05 | D45: Portafusible Unipolar 220 V, de 5 A, provisto con fusible de 1 A | G45: u | H45: 45 | I45: 3.31 | J45: =+ROUND(I45*H45,2) -> 148.95
B46: =+B45+0.01 -> 6.06 | D46: Conector Bimetalico Aislado, para Al 16-35 mm2 / Cu 4-10 mm2, para Fase Aislada, tipo Perforación | G46: u | H46: 45 | I46: 7.04 | J46: =+ROUND(I46*H46,2) -> 316.8
B47: =+B46+0.01 -> 6.07 | D47: Conector Bimetálico para Al 25 mm2 / Cu 4-10 mm2, para Neutro Desnudo, tipo Cuña | G47: u | H47: 45 | I47: 5.21 | J47: =+ROUND(I47*H47,2) -> 234.45
F48: =+"SUB-TOTAL "&B40&": " -> SUB-TOTAL 6: | J48: =+SUM(J41:J47) -> 16747.02
B49: =+B40+1 -> 7 | D49: RETENIDAS Y ANCLAJES
B50: =+B49+0.01 -> 7.01 | D50: Cable de acero grado Siemens Martin, de 10 mm ø, 7 hilos | G50: m | H50: 1076 | I50: 4.31 | J50: =+ROUND(I50*H50,2) -> 4637.56
B51: =+B50+0.01 -> 7.02 | D51: Perno Angular con Ojal Guardacabo de A°G°, 16 mm Ø x 254 mm, provisto de Tuerca y Contratuerca | G51: u | H51: 106 | I51: 13.17 | J51: =+ROUND(I51*H51,2) -> 1396.02
B52: =+B51+0.01 -> 7.03 | D52: Perno Angular con Ojal Guardacabo de A°G°, 16 mm Ø x 305 mm, provisto de Tuerca y Contratuerca | G52: u | H52: 3 | I52: 14.23 | J52: =+ROUND(I52*H52,2) -> 42.69
B53: =+B52+0.01 -> 7.04 | D53: Varilla de Anclaje de A°G° de 16 mm Ø x 2,40 m, provisto de Ojal Guardacabo en un extremo; Tuerca y Contratuerca en el otro | G53: u | H53: 109 | I53: 46.85 | J53: =+ROUND(I53*H53,2) -> 5106.65
B54: =+B53+0.01 -> 7.05 | D54: Arandela de Anclaje de A°G°, 102 x 102 x 6,35 mm, Agujero de 18 mmø | G54: u | H54: 109 | I54: 5.46 | J54: =+ROUND(I54*H54,2) -> 595.14
B55: =+B54+0.01 -> 7.06 | D55: Mordaza Preformada de A°G° para Cable de 10 mm Ø | G55: u | H55: 218 | I55: 11.69 | J55: =+ROUND(I55*H55,2) -> 2548.42
B56: =+B55+0.01 -> 7.07 | D56: Arandela Cuadrada Curva de A° G°, 57 x 57 x 5 mm, Agujero de 18 mm Ø | G56: u | H56: 218 | I56: 1.67 | J56: =+ROUND(I56*H56,2) -> 364.06
B57: =+B56+0.01 -> 7.08 | D57: Soporte de Contrapunta de 51 mm ø x 1000 mm de longitud, con Abrazadera partida en un extremo y Grapa de Ajuste para Cable en el otro | G57: u | H57: 14 | I57: 105.33 | J57: =+ROUND(I57*H57,2) -> 1474.62
B58: =+B57+0.01 -> 7.09 | D58: Alambre de Acero N° 12 para Entorchado | G58: m | H58: 327 | I58: 0.69 | J58: =+ROUND(I58*H58,2) -> 225.63
B59: =+B58+0.01 -> 7.1 | D59: Bloque de concreto de 0,40 x 0,40 x 0,15 m | G59: u | H59: 109 | I59: 40.94 | J59: =+ROUND(I59*H59,2) -> 4462.46
B60: =+B59+0.01 -> 7.11 | D60: Conector Bimetálico para Al 25 mm2 / Cu 4-10 mm2, para Neutro Desnudo, tipo Cuña | G60: u | H60: 109 | I60: 5.21 | J60: =+ROUND(I60*H60,2) -> 567.89
B61: =+B60+0.01 -> 7.12 | D61: Conector Doble Via Bimetálico para Cable de Acero de 10 mm ø y para Cable de Acero con Recubrimiento Metalúrgico de Cobre de 4 AWG (21,15 mm2) | G61: u | H61: 109 | I61: 8.52 | J61: =+ROUND(I61*H61,2) -> 928.68
F62: =+"SUB-TOTAL "&B49&": " -> SUB-TOTAL 7: | J62: =+SUM(J50:J61) -> 22349.82
B63: =+B49+1 -> 8 | D63: ACCESORIOS DE FERRETERIA PARA ESTRUCTURAS
B64: =+B63+0.01 -> 8.01 | D64: Perno con Gancho de 16 mm Ø, provisto de Arandela, Tuerca y Contratuerca, longitud de 254 mm | G64: u | H64: 141 | I64: 12.36 | J64: =+ROUND(I64*H64,2) -> 1742.76
B65: =+B64+0.01 -> 8.02 | D65: Perno con Gancho de 16 mm Ø, provisto de Arandela, Tuerca y Contratuerca, longitud de 305 mm | G65: u | H65: 22 | I65: 14.34 | J65: =+ROUND(I65*H65,2) -> 315.48
B66: =+B65+0.01 -> 8.03 | D66: Perno de A°G° de 13 mm Ø x 254 mm, provisto de Tuerca y Contratuerca | G66: u | H66: 248 | I66: 5.57 | J66: =+ROUND(I66*H66,2) -> 1381.36
B67: =+B66+0.01 -> 8.04 | D67: Perno de A°G° de 13 mm Ø x 305 mm, provisto de Tuerca y Contratuerca | G67: u | H67: 50 | I67: 6.25 | J67: =+ROUND(I67*H67,2) -> 312.5
B68: =+B67+0.01 -> 8.05 | D68: Perno Ojo de A°G° de 16 mm Ø x 254 mm, provisto de Tuerca y Contratuerca | G68: u | H68: 127 | I68: 13.11 | J68: =+ROUND(I68*H68,2) -> 1664.97
B69: =+B68+0.01 -> 8.06 | D69: Perno Ojo de A°G° de 16 mm Ø x 305 mm, provisto de Tuerca y Contratuerca | G69: u | H69: 33 | I69: 14.35 | J69: =+ROUND(I69*H69,2) -> 473.55
B70: =+B69+0.01 -> 8.07 | D70: Tuerca-Ojo para Perno de 16 mm Ø | G70: u | H70: 58 | I70: 11.17 | J70: =+ROUND(I70*H70,2) -> 647.86
B71: =+B70+0.01 -> 8.08 | D71: Fleje de acero inoxidable de 19 mm provisto de hebilla | G71: m | H71: 2 | I71: 6.02 | J71: =+ROUND(I71*H71,2) -> 12.04
B72: =+B71+0.01 -> 8.09 | D72: Arandela Cuadrada Curva de A° G°, 57 x 57 x 5 mm, Agujero de 14 mm Ø | G72: u | H72: 296 | I72: 1.63 | J72: =+ROUND(I72*H72,2) -> 482.48
B73: =+B72+0.01 -> 8.1 | D73: Arandela Cuadrada Curva de A° G°, 57 x 57 x 5 mm, Agujero de 18 mm Ø | G73: u | H73: 483 | I73: 1.67 | J73: =+ROUND(I73*H73,2) -> 806.61
B74: =+B73+0.01 -> 8.11 | D74: Caja de derivacion para acometidas, sistema 440-22O V (10 borneras en cada barra de cobre) | G74: u | H74: 2 | I74: 133.02 | J74: =+ROUND(I74*H74,2) -> 266.04
B75: =+B74+0.01 -> 8.12 | D75: Portalinea unipolar de AºGº, provisto de PIN de 10 mm Ø | G75: u | H75: 300 | I75: 6.63 | J75: =+ROUND(I75*H75,2) -> 1989
... B77: =+B76+0.01 -> 8.14 | D77: Plantillas para Identificación y/o codificación de Postes (Peligro, Identificación y/o codificación y Fases) | G77: Jgo. | H77: 29 | I77: 23.08 | J77: =+ROUND(I77*H77,2) -> 669.32
F78: =+"SUB-TOTAL "&B63&": " -> SUB-TOTAL 8: | J78: =+SUM(J63:J77) -> 10915.53
B79: =1+B63 -> 9 | D79: PUESTA A TIERRA
B80: =+B79+0.01 -> 9.01 | D80: Electrodo de Acero Recubierto de Cobre de 16 mm Ø x 2,40 m | G80: u | H80: 72 | I80: 66.7 | J80: =+ROUND(I80*H80,2) -> 4802.4
B81: =+B80+0.01 -> 9.02 | D81: Conector bimetálico para Al 25 mm2 y Cobre de 25 mm2, tipo cuña | G81: u | H81: 72 | I81: 7.89 | J81: =+ROUND(I81*H81,2) -> 568.08
B82: =+B81+0.01 -> 9.03 | D82: Conector de bronce para electrodo de 16 mm ø y Cable de Acero con Recubrimiento Metalúrgico de Cobre de 4 AWG (21,15 mm2) | G82: u | H82: 72 | I82: 6.94 | J82: =+ROUND(I82*H82,2) -> 499.68
B83: =+B82+0.01 -> 9.04 | D83: Grapa en "U" para fijar conductor de PAT a Poste de Madera | G83: u | H83: 60 | I83: 0.47 | J83: =+ROUND(I83*H83,2) -> 28.2
B84: =+B83+0.01 -> 9.05 | D84: Listón de madera tratada 50 x 19 mm sección, 2,7 m longitud (incluye clavos de fijación) | G84: u | H84: 3 | I84: 27.35 | J84: =+ROUND(I84*H84,2) -> 82.05
B85: =+B84+0.01 -> 9.06 | D85: Plantilla para Señalización de Poste (Puesta a Tierra) | G85: u | H85: 72 | I85: 16.25 | J85: =+ROUND(I85*H85,2) -> 1170
B86: =+B85+0.01 -> 9.07 | D86: Tubo Plastico de PVC SAP de 19 mm ø x 0,5 m ( incluye curva de plastico de 19 mm ø x 90º) | G86: u | H86: 68 | I86: 2.39 | J86: =+ROUND(I86*H86,2) -> 162.52
F87: =+"SUB-TOTAL "&B79&": " -> SUB-TOTAL 9: | J87: =+SUM(J80:J86) -> 7312.93
B88: =1+B79 -> 10 | D88: CONEXIONES DOMICILIARIAS
B89: =+B88+0.01 -> 10.01 | D89: Tubo de AºGº standard / redondo de 19 mm Ø x 1,5 mm x 2,5 m, provisto de codo | G89: u | H89: 147 | I89: 29.39 | J89: =+ROUND(I89*H89,2) -> 4320.33
B90: =+B89+0.01 -> 10.02 | D90: Tubo de AºGº standard / redondo de 19 mm Ø x 1,5 mm x 4,0 m, provisto de codo | G90: u | H90: 68 | I90: 45.75 | J90: =+ROUND(I90*H90,2) -> 3111
B91: =+B90+0.01 -> 10.03 | D91: Tubo de AºGº standard / redondo de 19 mm Ø x 1,5 mm x 6,0 m, provisto de codo | G91: u | H91: 28 | I91: 62.96 | J91: =+ROUND(I91*H91,2) -> 1762.88
B92: =+B91+0.01 -> 10.04 | D92: Tubo de AºGº standard / redondo de 38 mm Ø x 1,5 mm x 6,0 m, provisto de codo | G92: u | H92: 40 | I92: 117.61 | J92: =+ROUND(I92*H92,2) -> 4704.4
B93: =+B92+0.01 -> 10.05 | D93: Armella Tirafondo de 10 mm Ø x 64 mm de longitud | G93: u | H93: 39 | I93: 1.47 | J93: =+ROUND(I93*H93,2) -> 57.33
B94: =+B93+0.01 -> 10.06 | D94: Tarugo de cedro de 13 mm x 50 mm | G94: u | H94: 39 | I94: 0.4 | J94: =+ROUND(I94*H94,2) -> 15.6
B95: =+B94+0.01 -> 10.07 | D95: Alambre de Acero N° 12 para Entorchado | G95: m | H95: 933 | I95: 0.69 | J95: =+ROUND(I95*H95,2) -> 643.77
B96: =+B95+0.01 -> 10.08 | D96: Conector Bimetálico para Al 25 mm2 / Cu 4-10 mm2, para Neutro Desnudo, tipo Cuña | G96: u | H96: 175 | I96: 5.21 | J96: =+ROUND(I96*H96,2) -> 911.75
B97: =+B96+0.01 -> 10.09 | D97: Conector Bimetalico Aislado, para Al 16-35 mm2 / Cu 4-10 mm2, para Fase Aislada, tipo Perforación | G97: u | H97: 175 | I97: 7.04 | J97: =+ROUND(I97*H97,2) -> 1232
B98: =+B97+0.01 -> 10.1 | D98: Templador de AºGº | G98: u | H98: 350 | I98: 2.85 | J98: =+ROUND(I98*H98,2) -> 997.5
B99: =+B98+0.01 -> 10.11 | D99: Correa Plástica de Amarre, color negro | G99: u | H99: 756 | I99: 0.4 | J99: =+ROUND(I99*H99,2) -> 302.4
B100: =+B99+0.01 -> 10.12 | D100: Caja Metálica Portamedidor, equipado con Interruptor Termomagnético de 10A | G100: u | H100: 175 | I100: 61.52 | J100: =+ROUND(I100*H100,2) -> 10766
B101: =+B100+0.01 -> 10.13 | D101: Medidor Monofásico de Energía Activa, tipo Electrónico con Micro Procesador de 220 V; 2 hilos, 10-40 A, 60 Hz, Clase 1 | G101: u | H101: 175 | I101: 54.01 | J101: =+ROUND(I101*H101,2) -> 9451.75
F102: =+"SUB-TOTAL "&B88&": " -> SUB-TOTAL 10: | J102: =+SUM(J89:J101) -> 38276.71
D103: TOTAL SUMINISTRO DE MATERIALES | J103: =+ROUND(SUM(J9:J102)/2,2) -> 301377.1
...

Sheet MONTAJE RS
B1: VALOR REFERENCIAL
B2: MONTAJE ELECTROMECÁNICO DE REDES SECUNDARIAS
B3: UBICACIÓN | E3: : | F3: ANCASH
B4: SECCIÓN III | E4: : | F4: REDES SECUNDARIAS
B5: B: MONTAJE ELECTROMECÁNICO
B7: Item | C7: Descripción de Partidas | G7: Unid. | H7: Metrado Cant. | I7: Costo Unitario | J7: SubTotal S/ | L7: Costo Unitario | M7: 0.9
B9: 1 | D9: TRANSPORTE DE MATERIALES DE ALMACEN EN OBRA A PUNTO DE INSTALACIÒN
B10: =+B9+0.01 -> 1.01 | D10: Transporte de Poste de 8 m/200 daN de Almacen a Punto de Izaje, en Terreno con Acceso Carrozable | G10: u | H10: 153 | I10: 153.05 | J10: =+ROUND(I10*H10,2) -> 23416.65 | L10: 170.05 | M10: =+ROUND(L10*$M$7,2) -> 153.05
B11: =+B10+0.01 -> 1.02 | D11: Transporte de Poste de 8 m/300 daN de Almacen a Punto de Izaje, en Terreno con Acceso Carrozable | G11: u | H11: 79 | I11: 164.1 | J11: =+ROUND(I11*H11,2) -> 12963.9 | L11: 182.33 | M11: =+ROUND(L11*$M$7,2) -> 164.1
B12: =+B11+0.01 -> 1.03 | D12: Transporte de Poste de madera importado de 8 m, Clase 7 de Almacen a Punto de Izaje, en Terreno sin Acceso Carrozable (< 1000 m) | G12: u | H12: 9 | I12: 211.63 | J12: =+ROUND(I12*H12,2) -> 1904.67 | L12: 235.14 | M12: =+ROUND(L12*$M$7,2) -> 211.63
B13: =+B12+0.01 -> 1.04 | D13: Transporte de Bloque de Concreto de 0,40 x 0,40 x 0,15 m, de Almacen a Punto de Instalaciòn en Terreno con Acceso Carrozable | G13: u | H13: 105 | I13: 62.87 | J13: =+ROUND(I13*H13,2) -> 6601.35 | L13: 69.86 | M13: =+ROUND(L13*$M$7,2) -> 62.87
B14: =+B13+0.01 -> 1.05 | D14: Transporte de Bloque de Concreto de 0,40 x 0,40 x 0,15 m, de Almacen a Punto de Instalaciòn en Terreno sin Acceso Carrozable (< 1000 m) | G14: u | H14: 4 | I14: 73.71 | J14: =+ROUND(I14*H14,2) -> 294.84 | L14: 81.9 | M14: =+ROUND(L14*$M$7,2) -> 73.71
B15: =+B14+0.01 -> 1.06 | D15: Transporte de Accesorios de Ferreteria (Para Postes , conductores, Retenidas y PAT) de Almacen a Punto de Instalaciòn con Acceso Carrozable | G15: Glob | H15: 1 | I15: 1571.83 | J15: =+ROUND(I15*H15,2) -> 1571.83 | L15: 1746.48 | M15: =+ROUND(L15*$M$7,2) -> 1571.83
B16: =+B15+0.01 -> 1.07 | D16: Transporte de Accesorios de Ferreteria (Para Postes , conductores, Retenidas y PAT) de Almacen a Punto de Instalaciòn sin Acceso Carrozable (< 1000 m) | G16: Glob | H16: 1 | I16: 2275.69 | J16: =+ROUND(I16*H16,2) -> 2275.69 | L16: 2528.54 | M16: =+ROUND(L16*$M$7,2) -> 2275.69
B17: =+B16+0.01 -> 1.08 | D17: Transporte de Conductor Autoportante de Aluminio de 2x25+16/25 mm² de Almacen a Punto de Instalación en terreno con acceso carrozable | G17: km | H17: 1.46 | I17: 68.03 | J17: =+ROUND(I17*H17,2) -> 99.32 | L17: 75.59 | M17: =+ROUND(L17*$M$7,2) -> 68.03
B18: =+B17+0.01 -> 1.09 | D18: Transporte de Conductor Autoportante de Aluminio de 2x16+16/25 mm² de Almacen a Punto de Instalación en terreno con acceso carrozable | G18: km | H18: 0.05 | I18: 59.41 | J18: =+ROUND(I18*H18,2) -> 2.97 | L18: 66.01 | M18: =+ROUND(L18*$M$7,2) -> 59.41
B19: =+B18+0.01 -> 1.1 | D19: Transporte de Conductor Autoportante de Aluminio de 2x25/25 mm² de Almacen a Punto de Instalación en terreno con acceso carrozable | G19: km | H19: 7.08 | I19: 55.09 | J19: =+ROUND(I19*H19,2) -> 390.04 | L19: 61.21 | M19: =+ROUND(L19*$M$7,2) -> 55.09
B20: =+B19+0.01 -> 1.11 | D20: Transporte de Conductor Autoportante de Aluminio de 1x16+16/25 mm² de Almacen a Punto de Instalación en terreno con acceso carrozable | G20: km | H20: 0.18 | I20: 53.76 | J20: =+ROUND(I20*H20,2) -> 9.68 | L20: 59.73 | M20: =+ROUND(L20*$M$7,2) -> 53.76
B21: =+B20+0.01 -> 1.12 | D21: Transporte de Conductor Autoportante de Aluminio de 1x16/25 mm² de Almacen a Punto de Instalación en terreno con acceso carrozable | G21: km | H21: 3.52 | I21: 42.66 | J21: =+ROUND(I21*H21,2) -> 150.16 | L21: 47.4 | M21: =+ROUND(L21*$M$7,2) -> 42.66
... B24: =+B23+0.01 -> 1.15 | D24: Transporte de cable de acero con recubrimiento metalurgico de Cu de 4AWG de Almacen a Punto de Intalaciòn en Terreno sin Acceso Carrozable (< 1000 m) | G24: km | H24: 0.05 | I24: 91.14 | J24: =+ROUND(I24*H24,2) -> 4.56 | L24: 101.27 | M24: =+ROUND(L24*$M$7,2) -> 91.14
F25: =+"SUB-TOTAL "&B9&": " -> SUB-TOTAL 1: | J25: =SUM(J10:J24) -> 49788.05
B26: 2 | D26: INSTALACION DE POSTES
B27: =+B26+0.01 -> 2.01 | D27: Excavación en terreno Tipo I (arcilloso y conglomerado) | H27: 126.36 | I27: 61.15 | J27: =+ROUND(I27*H27,2) -> 7726.91 | L27: 67.94 | M27: =+ROUND(L27*$M$7,2) -> 61.15
B28: =+B27+0.01 -> 2.02 | D28: Excavación en terreno Tipo II (Rocoso) | H28: 2.94 | I28: 208.14 | J28: =+ROUND(I28*H28,2) -> 611.93 | L28: 231.27 | M28: =+ROUND(L28*$M$7,2) -> 208.14
B29: =+B28+0.01 -> 2.03 | D29: Izaje, Identificación y/o codificación, y Señalización de Poste de 8 m/200 daN (*) | G29: u | H29: 153 | I29: 72.7 | J29: =+ROUND(I29*H29,2) -> 11123.1 | L29: 80.78 | M29: =+ROUND(L29*$M$7,2) -> 72.7
B30: =+B29+0.01 -> 2.04 | D30: Izaje, Identificación y/o codificación, y Señalización de Poste de 8 m/300 daN (*) | G30: u | H30: 79 | I30: 81.34 | J30: =+ROUND(I30*H30,2) -> 6425.86 | L30: 90.38 | M30: =+ROUND(L30*$M$7,2) -> 81.34
B31: =+B30+0.01 -> 2.05 | D31: Izaje, Identificación y/o codificación, y Señalización de Poste de madera importado de 8 m, Clase 7 | G31: u | H31: 9 | I31: 57.73 | J31: =+ROUND(I31*H31,2) -> 519.57 | L31: 64.14 | M31: =+ROUND(L31*$M$7,2) -> 57.73
B32: =+B31+0.01 -> 2.06 | D32: Cimentación con Concreto Ciclópeo de Poste de 8m en Terreno Tipo I (Arcilloso y Conglomerado) | G32: u | H32: 225 | I32: 197.37 | J32: =+ROUND(I32*H32,2) -> 44408.25 | L32: 219.3 | M32: =+ROUND(L32*$M$7,2) -> 197.37
B33: =+B32+0.01 -> 2.07 | D33: Cimentación con Concreto Ciclópeo de Poste de 8m en Terreno Tipo II (Rocoso) | G33: u | H33: 7 | I33: 191.97 | J33: =+ROUND(I33*H33,2) -> 1343.79 | L33: 213.3 | M33: =+ROUND(L33*$M$7,2) -> 191.97
B34: =+B33+0.01 -> 2.08 | D34: Relleno y Compactación para cimentación de Poste 8m, en Terreno Tipo I (Arcilloso y Conglomerado) | H34: 4.32 | I34: 90.22 | J34: =+ROUND(I34*H34,2) -> 389.75 | L34: 100.24 | M34: =+ROUND(L34*$M$7,2) -> 90.22
F35: =+"SUB-TOTAL "&B26&": " -> SUB-TOTAL 2: | J35: =SUM(J27:J34) -> 72549.16
B36: 3 | D36: INSTALACION DE RETENIDAS
B37: =+B36+0.01 -> 3.01 | D37: Excavación en terreno Tipo I (arcilloso y conglomerado) | H37: 101.44 | I37: 61.15 | J37: =+ROUND(I37*H37,2) -> 6203.06 | L37: 67.94 | M37: =+ROUND(L37*$M$7,2) -> 61.15
B38: =+B37+0.01 -> 3.02 | D38: Excavación en terreno Tipo II (rocoso) | H38: 12.48 | I38: 208.14 | J38: =+ROUND(I38*H38,2) -> 2597.59 | L38: 231.27 | M38: =+ROUND(L38*$M$7,2) -> 208.14
B39: =+B38+0.01 -> 3.03 | D39: Instalación de retenida inclinada | G39: u | H39: 95 | I39: 58.28 | J39: =+ROUND(I39*H39,2) -> 5536.6 | L39: 64.76 | M39: =+ROUND(L39*$M$7,2) -> 58.28
B40: =+B39+0.01 -> 3.04 | D40: Instalación de retenida vertical | G40: u | H40: 14 | I40: 64.03 | J40: =+ROUND(I40*H40,2) -> 896.42 | L40: 71.14 | M40: =+ROUND(L40*$M$7,2) -> 64.03
B41: =+B40+0.01 -> 3.05 | D41: Relleno y Compactación en Terreno Tipo I de Retenida | H41: 99.5 | I41: 90.22 | J41: =+ROUND(I41*H41,2) -> 8976.89 | L41: 100.24 | M41: =+ROUND(L41*$M$7,2) -> 90.22
B42: =+B41+0.01 -> 3.06 | D42: Relleno y Compactación en Terreno Tipo II de Retenida | H42: 12.24 | I42: 96.57 | J42: =+ROUND(I42*H42,2) -> 1182.02 | L42: 107.3 | M42: =+ROUND(L42*$M$7,2) -> 96.57
F43: =+"SUB-TOTAL "&B36&": " -> SUB-TOTAL 3: | J43: =SUM(J37:J42) -> 25392.58
B44: 4 | D44: MONTAJE DE ARMADOS
B45: =+B44+0.01 -> 4.01 | D45: Armado Tipo E1/S, E'1/S Alineamiento y Angulo - Conductor Autoportante sin Caja de Derivación para Acometida | G45: Jgo. | H45: 142 | I45: 24.88 | J45: =+ROUND(I45*H45,2) -> 3532.96 | L45: 27.64 | M45: =+ROUND(L45*$M$7,2) -> 24.88
B46: =+B45+0.01 -> 4.02 | D46: Armado Tipo E2/S, E'2/S Anclaje y Cambio de Sección - Conductor Autoportante sin Caja de Derivación para Acometida | G46: Jgo. | H46: 1 | I46: 31.13 | J46: =+ROUND(I46*H46,2) -> 31.13 | L46: 34.59 | M46: =+ROUND(L46*$M$7,2) -> 31.13
B47: =+B46+0.01 -> 4.03 | D47: Armado Tipo E3/S, E'3/S Extremo de Línea - Conductor Autoportante sin Caja de Derivación para Acometida | G47: Jgo. | H47: 77 | I47: 24.58 | J47: =+ROUND(I47*H47,2) -> 1892.66 | L47: 27.31 | M47: =+ROUND(L47*$M$7,2) -> 24.58
B48: =+B47+0.01 -> 4.04 | D48: Armado Tipo E4, E'4 Extremo de Línea con Derivación - Conductor Autoportante con Caja de Derivación para Acometida | G48: Jgo. | H48: 2 | I48: 34.23 | J48: =+ROUND(I48*H48,2) -> 68.46 | L48: 38.03 | M48: =+ROUND(L48*$M$7,2) -> 34.23
B49: =+B48+0.01 -> 4.05 | D49: Armado Tipo E4/S, E'4/S Extremo de Línea con Derivación - Conductor Autoportante sin Caja de Derivación para Acometida | G49: Jgo. | H49: 51 | I49: 31.13 | J49: =+ROUND(I49*H49,2) -> 1587.63 | L49: 34.59 | M49: =+ROUND(L49*$M$7,2) -> 31.13
B50: =+B49+0.01 -> 4.06 | D50: Armado Tipo E5/S, E'5/S Alineamiento con Derivación - Conductor Autoportante sin Caja de Derivación para Acometida | G50: Jgo. | H50: 21 | I50: 38.84 | J50: =+ROUND(I50*H50,2) -> 815.64 | L50: 43.15 | M50: =+ROUND(L50*$M$7,2) -> 38.84
B51: =+B50+0.01 -> 4.07 | D51: Armado Tipo E6/S, E'6/S Anclaje con Derivación - Conductor Autoportante sin Caja de Derivación para Acometida | G51: Jgo. | H51: 4 | I51: 46.54 | J51: =+ROUND(I51*H51,2) -> 186.16 | L51: 51.71 | M51: =+ROUND(L51*$M$7,2) -> 46.54
F52: =+"SUB-TOTAL "&B44&": " -> SUB-TOTAL 4: | J52: =SUM(J45:J51) -> 8114.64
B53: 5 | D53: MONTAJE DE CONDUCTORES AUTOPORTANTES
D54: Comprende Tendido y puesta en Flecha de :
B55: =+B53+0.01 -> 5.01 | D55: Tendido y Puesta en Flecha de Conductor Autoportante de Aluminio de 2x25+16/25 mm² | G55: km | H55: 1.46 | I55: 1274.1 | J55: =+ROUND(I55*H55,2) -> 1860.19 | L55: 1415.67 | M55: =+ROUND(L55*$M$7,2) -> 1274.1
B56: =+B55+0.01 -> 5.02 | D56: Tendido y Puesta en Flecha de Conductor Autoportante de Aluminio de 2x16+16/25 mm² | G56: km | H56: 0.05 | I56: 1025.75 | J56: =+ROUND(I56*H56,2) -> 51.29 | L56: 1139.72 | M56: =+ROUND(L56*$M$7,2) -> 1025.75
B57: =+B56+0.01 -> 5.03 | D57: Tendido y Puesta en Flecha de Conductor Autoportante de Aluminio de 2x25/25 mm² | G57: km | H57: 7.08 | I57: 1066.56 | J57: =+ROUND(I57*H57,2) -> 7551.24 | L57: 1185.07 | M57: =+ROUND(L57*$M$7,2) -> 1066.56
B58: =+B57+0.01 -> 5.04 | D58: Tendido y Puesta en Flecha de Conductor Autoportante de Aluminio de 1x16+16/25 mm² | G58: km | H58: 0.18 | I58: 860.76 | J58: =+ROUND(I58*H58,2) -> 154.94 | L58: 956.4 | M58: =+ROUND(L58*$M$7,2) -> 860.76
B59: =+B58+0.01 -> 5.05 | D59: Tendido y Puesta en Flecha de Conductor Autoportante de Aluminio de 1x16/25 mm² | G59: km | H59: 4.06 | I59: 834.36 | J59: =+ROUND(I59*H59,2) -> 3387.5 | L59: 927.07 | M59: =+ROUND(L59*$M$7,2) -> 834.36
F60: =+"SUB-TOTAL "&B53&": " -> SUB-TOTAL 5: | J60: =+SUM(J54:J59) -> 13005.16
B61: 6 | D61: INSTALACION DE PUESTA A TIERRA
B62: =+B61+0.01 -> 6.01 | D62: Excavación en terreno Tipo I (arcilloso y conglomerado) | H62: 98.91 | I62: 61.15 | J62: =+ROUND(I62*H62,2) -> 6048.35 | L62: 67.94 | M62: =+ROUND(L62*$M$7,2) -> 61.15
B63: =+B62+0.01 -> 6.02 | D63: Excavación en terreno Tipo II (rocoso) | H63: 14.13 | I63: 208.14 | J63: =+ROUND(I63*H63,2) -> 2941.02 | L63: 231.27 | M63: =+ROUND(L63*$M$7,2) -> 208.14
B64: =+B63+0.01 -> 6.03 | D64: Instalación de Puesta a Tierra Tipo PAT-1 con un Electrodo Vertical. Instalación en Poste de Concreto Armado Centrifugado. | G64: u | H64: 69 | I64: 49.91 | J64: =+ROUND(I64*H64,2) -> 3443.79 | L64: 55.46 | M64: =+ROUND(L64*$M$7,2) -> 49.91
B65: =+B64+0.01 -> 6.04 | D65: Instalación de Puesta a Tierra Tipo PAT-1 con un Electrodo Vertical. Instalación en Poste de Madera. | G65: u | H65: 3 | I65: 59.05 | J65: =+ROUND(I65*H65,2) -> 177.15 | L65: 65.61 | M65: =+ROUND(L65*$M$7,2) -> 59.05
B66: =+B65+0.01 -> 6.05 | D66: Relleno y Compactación de Puesta a Tierra con Material Adecuado | H66: 113.04 | I66: 68.82 | J66: =+ROUND(I66*H66,2) -> 7779.41 | L66: 76.47 | M66: =+ROUND(L66*$M$7,2) -> 68.82
F67: =+"SUB-TOTAL "&B61&": " -> SUB-TOTAL 6: | J67: =+SUM(J62:J66) -> 20389.72
B68: 7 | D68: PASTORALES, LUMINARIAS Y LAMPARAS
B69: =+B68+0.01 -> 7.01 | D69: Instalación de Pastoral de A° G° | G69: u | H69: 45 | I69: 32.8 | J69: =+ROUND(I69*H69,2) -> 1476 | L69: 36.44 | M69: =+ROUND(L69*$M$7,2) -> 32.8
B70: =+B69+0.01 -> 7.02 | D70: Instalación de Luminaria, Lámpara y Accesorios | G70: u | H70: 45 | I70: 58.39 | J70: =+ROUND(I70*H70,2) -> 2627.55 | L70: 64.88 | M70: =+ROUND(L70*$M$7,2) -> 58.39
F71: =+"SUB-TOTAL "&B68&": " -> SUB-TOTAL 7: | J71: =+SUM(J69:J70) -> 4103.55
B72: 8 | D72: CONEXIONES DOMICILIARIAS
D73: Instalación de Acometida Domiciliaria, que comprende: Conexión de Acometida Domiciliaria, Montaje de Medidor y Contraste de Medidor.
B74: =+B72+0.01 -> 8.01 | D74: Conexión de Acometidas Domiciliarias, Configuración: Corta en Murete (no incluye medidor de energía activa) | G74: u | H74: 68 | I74: 53.11 | J74: =+ROUND(I74*H74,2) -> 3611.48 | L74: 59.01 | M74: =+ROUND(L74*$M$7,2) -> 53.11
B75: =+B74+0.01 -> 8.02 | D75: Conexión de Acometidas Domiciliarias, Configuración: Larga en Murete (no incluye medidor de energía activa) | G75: u | H75: 40 | I75: 61.41 | J75: =+ROUND(I75*H75,2) -> 2456.4 | L75: 68.23 | M75: =+ROUND(L75*$M$7,2) -> 61.41
B76: =+B75+0.01 -> 8.03 | D76: Conexión de Acometidas Domiciliarias, Configuración: Corta (no incluye medidor de energía activa) | G76: u | H76: 39 | I76: 59.13 | J76: =+ROUND(I76*H76,2) -> 2306.07 | L76: 65.7 | M76: =+ROUND(L76*$M$7,2) -> 59.13
B77: =+B76+0.01 -> 8.04 | D77: Conexión de Acometidas Domiciliarias, Configuración: Larga (no incluye medidor de energía activa) | G77: u | H77: 28 | I77: 71.58 | J77: =+ROUND(I77*H77,2) -> 2004.24 | L77: 79.53 | M77: =+ROUND(L77*$M$7,2) -> 71.58
B78: =+B77+0.01 -> 8.05 | D78: Instalación de Medidor Monofásico de Energia Activa y Caja Portamedidor (incluye conexión a cable de acometida) | G78: u | H78: 175 | I78: 19.12 | J78: =+ROUND(I78*H78,2) -> 3346 | L78: 21.24 | M78: =+ROUND(L78*$M$7,2) -> 19.12
B79: =+B78+0.01 -> 8.06 | D79: Contraste de medidor monofásico de energía activa - electrónico | G79: u | H79: 175 | I79: 24.45 | J79: =+ROUND(I79*H79,2) -> 4278.75 | L79: 27.17 | M79: =+ROUND(L79*$M$7,2) -> 24.45
B80: =+B79+0.01 -> 8.07 | D80: Murete de Concreto de 1,65m de altura libre y 0,30m de profundidad. F'c=100 kg/cm², incluye transporte | G80: u | H80: 108 | I80: 334.65 | J80: =+ROUND(I80*H80,2) -> 36142.2 | L80: 371.83 | M80: =+ROUND(L80*$M$7,2) -> 334.65
F81: =+"SUB-TOTAL "&B72&": " -> SUB-TOTAL 8: | J81: =+SUM(J74:J80) -> 54145.14
B82: =1+B72 -> 9 | D82: DESMONTAJE DE REDES SECUNDARIAS EXISTENTES
B83: =+B82+0.01 -> 9.01 | D83: Desmontaje de Poste para Baja Tension (incluye resane de terreno y Transporte a Almacen de propietario) | G83: u | H83: 7 | I83: 67.71 | J83: =+ROUND(I83*H83,2) -> 473.97 | L83: 75.23 | M83: =+ROUND(L83*$M$7,2) -> 67.71
B84: =+B83+0.01 -> 9.02 | D84: Desmontaje de Conductor en Baja Tensión( Incluye Traslado a Almacén de Propietario) | G84: km | H84: 0.35 | I84: 741.66 | J84: =+ROUND(I84*H84,2) -> 259.58 | L84: 824.07 | M84: =+ROUND(L84*$M$7,2) -> 741.66
B85: =+B84+0.01 -> 9.03 | D85: Desmontaje de pastoral de de A°G° y luminarias con lámparas de vapor ( Incluye Traslado a almacén de propietario) | G85: u | H85: 3 | I85: 35.42 | J85: =+ROUND(I85*H85,2) -> 106.26 | L85: 39.36 | M85: =+ROUND(L85*$M$7,2) -> 35.42
B86: =+B85+0.01 -> 9.04 | D86: Desmontaje de Retenida (incluye Varilla y Bloque de Anclaje, y accesorios y Traslado a Almacén de propietario) | G86: u | H86: 6 | I86: 81.18 | J86: =+ROUND(I86*H86,2) -> 487.08 | L86: 90.2 | M86: =+ROUND(L86*$M$7,2) -> 81.18
B87: =+B86+0.01 -> 9.05 | D87: Desmontaje de la ferreteria de los armados (E1, E2, E3, E4, E5 Y E6) | G87: Jgo. | H87: 7 | I87: 61.17 | J87: =+ROUND(I87*H87,2) -> 428.19 | L87: 67.97 | M87: =+ROUND(L87*$M$7,2) -> 61.17
B88: =+B87+0.01 -> 9.06 | D88: Desmontaje de Medidor de Energia y Conexión Domiciliaria ( Incluye Traslado a Almacén de Propietario) | G88: u | H88: 3 | I88: 18.38 | J88: =+ROUND(I88*H88,2) -> 55.14 | L88: 20.42 | M88: =+ROUND(L88*$M$7,2) -> 18.38
B89: =+B88+0.01 -> 9.07 | D89: Transporte de Accesorios de Ferreteria de desmontaje (Para Postes , conductores, Retenidas y PAT) a almacen de propietario | G89: Glob | H89: 1 | I89: 2262.12 | J89: =+ROUND(I89*H89,2) -> 2262.12 | L89: 2513.47 | M89: =+ROUND(L89*$M$7,2) -> 2262.12
F90: =+"SUB-TOTAL "&B82&": " -> SUB-TOTAL 9: | J90: =SUM(J83:J89) -> 4072.34
B91: =1+B82 -> 10 | D91: PRUEBAS Y PUESTA EN SERVICIO:
B92: =+B91+0.01 -> 10.01 | D92: Prueba y Puesta en Servicio de Redes Secundarias | G92: Loc. | H92: 20 | I92: 805.01 | J92: =+ROUND(I92*H92,2) -> 16100.2 | L92: 894.45 | M92: =+ROUND(L92*$M$7,2) -> 805.01
B93: =+B92+0.01 -> 10.02 | D93: Expediente Técnico Final Conforme a Obra y de Concesión Rural de Redes Secundarias (1 Original + 3 Copias), incluye la presentacion digitalizada de textos y planos en CD. | G93: Loc. | H93: 20 | I93: 294.98 | J93: =+ROUND(I93*H93,2) -> 5899.6 | L93: 327.76 | M93: =+ROUND(L93*$M$7,2) -> 294.98
F94: =+"SUB-TOTAL "&B91&": " -> SUB-TOTAL 10: | J94: =SUM(J92:J93) -> 21999.8
D96: TOTAL MONTAJE ELECTROMECÁNICO | J96: =+ROUND(SUM(J9:J95)/2,2) -> 273560.14
D97: Nota = (*) El Contratista coordinará con la empresa concesionaria para definir los detalles para la identificación y señalización final de los postes.
J99: =+J94+J90+J81+J71+J67+J60+J52+J43+J35+J25 -> 273560.14
J100: =J99=J96 -> TRUE

Sheet TRANS.RS
B1: VALOR REFERENCIAL
B2: TRANSPORTE DE MATERIALES DE REDES SECUNDARIAS
B3: UBICACIÓN | E3: : | F3: ANCASH
B4: SECCIÓN III | E4: : | F4: REDES SECUNDARIAS
B5: C: TRANSPORTE DE MATERIALES
B7: Item | C7: Descripción de Partidas | G7: Unid. | H7: Metrado Cant. | I7: Costo Unitario | J7: SubTotal S/
B9: 1 | D9: POSTES DE CONCRETO ARMADO Y MADERA IMPORTADA | N9: Indice Unificado
B10: =+B9+0.01 -> 1.01 | D10: =+'SUMINISTRO RS'!D10 -> Poste de C.A.C. de 8 m/200 daN (Incluye perilla) | G10: =+'SUMINISTRO RS'!G10 -> u | H10: =+'SUMINISTRO RS'!H10 -> 153 | I10: 132.13 | J10: =+ROUND(I10*H10,2) -> 20215.89 | M10: IU | N10: 44440 | O10: 44682 | P10: Incremento
B11: =+B10+0.01 -> 1.02 | D11: =+'SUMINISTRO RS'!D11 -> Poste de C.A.C. de 8 m/300 daN (Incluye perilla) | G11: =+'SUMINISTRO RS'!G11 -> u | H11: =+'SUMINISTRO RS'!H11 -> 79 | I11: 136.68 | J11: =+ROUND(I11*H11,2) -> 10797.72 | M11: 32 | N11: 507.42 | O11: 513.36 | P11: =+O11/N11 -> 1.0117063
F12: =+"SUB-TOTAL "&B9&": " -> SUB-TOTAL 1: | J12: =SUM(J10:J11) -> 31013.61
B13: =1+B9 -> 2 | D13: POSTES DE MADERA IMPORTADA
B14: =+B13+0.01 -> 2.01 | D14: =+'SUMINISTRO RS'!D14 -> Poste de madera importada (Pino Amarillo del Sur) de 8 m, Clase 7 | G14: =+'SUMINISTRO RS'!G14 -> u | H14: =+'SUMINISTRO RS'!H14 -> 9 | I14: 93.17 | J14: =+ROUND(I14*H14,2) -> 838.53
F15: =+"SUB-TOTAL "&B13&": " -> SUB-TOTAL 2: | J15: =SUM(J14) -> 838.53
B16: =+B13+1 -> 3 | D16: CABLES Y CONDUCTORES DE ALUMINIO
B17: =+B16+0.01 -> 3.01 | D17: =+'SUMINISTRO RS'!D17 -> Conductor Autoportante de Aluminio 2X25+16/25 mm² | G17: =+'SUMINISTRO RS'!G17 -> km | H17: =+'SUMINISTRO RS'!H17 -> 1.46 | I17: 86.41 | J17: =+ROUND(I17*H17,2) -> 126.16
B18: =+B17+0.01 -> 3.02 | D18: =+'SUMINISTRO RS'!D18 -> Conductor Autoportante de Aluminio 2X16+16/25 mm² | G18: =+'SUMINISTRO RS'!G18 -> km | H18: =+'SUMINISTRO RS'!H18 -> 0.05 | I18: 79.37 | J18: =+ROUND(I18*H18,2) -> 3.97
B19: =+B18+0.01 -> 3.03 | D19: =+'SUMINISTRO RS'!D19 -> Conductor Autoportante de Aluminio 2X25/25 mm² | G19: =+'SUMINISTRO RS'!G19 -> km | H19: =+'SUMINISTRO RS'!H19 -> 7.08 | I19: 104.03 | J19: =+ROUND(I19*H19,2) -> 736.53
B20: =+B19+0.01 -> 3.04 | D20: =+'SUMINISTRO RS'!D20 -> Conductor Autoportante de Aluminio 1X16+16/25 mm² | G20: =+'SUMINISTRO RS'!G20 -> km | H20: =+'SUMINISTRO RS'!H20 -> 0.18 | I20: 68.78 | J20: =+ROUND(I20*H20,2) -> 12.38
B21: =+B20+0.01 -> 3.05 | D21: =+'SUMINISTRO RS'!D21 -> Conductor Autoportante de Aluminio 1X16/25 mm² | G21: =+'SUMINISTRO RS'!G21 -> km | H21: =+'SUMINISTRO RS'!H21 -> 4.06 | I21: 38.8 | J21: =+ROUND(I21*H21,2) -> 157.53
F22: =+"SUB-TOTAL "&B16&": " -> SUB-TOTAL 3: | J22: =+SUM(J17:J21) -> 1036.57
B23: =+B16+1 -> 4 | D23: ACCESORIOS DE CABLES AUTOPORTANTES
B24: =+B23+0.01 -> 4.01 | D24: =+'SUMINISTRO RS'!D24 -> Grapa de Suspensión Angular para Conductor de Aleacion de Aluminio de 25 mm2 | G24: =+'SUMINISTRO RS'!G24 -> u | H24: =+'SUMINISTRO RS'!H24 -> 163 | I24: 0.12 | J24: =+ROUND(I24*H24,2) -> 19.56
B25: =+B24+0.01 -> 4.02 | D25: =+'SUMINISTRO RS'!D25 -> Grapa de Anclaje Cónica para Conductor de Aleación de Aluminio de 25 mm2 | G25: =+'SUMINISTRO RS'!G25 -> u | H25: =+'SUMINISTRO RS'!H25 -> 218 | I25: 0.06 | J25: =+ROUND(I25*H25,2) -> 13.08
B26: =+B25+0.01 -> 4.03 | D26: =+'SUMINISTRO RS'!D26 -> Conector Bimetálico para Al 25 mm2 / Cu 4-10 mm2, para Neutro Desnudo, tipo Cuña | G26: =+'SUMINISTRO RS'!G26 -> u | H26: =+'SUMINISTRO RS'!H26 -> 2 | I26: 0.02 | J26: =+ROUND(I26*H26,2) -> 0.04
B27: =+B26+0.01 -> 4.04 | D27: =+'SUMINISTRO RS'!D27 -> Conector Bimetalico Aislado, para Al 16-35 mm2 / Cu 4-10 mm2, para Fase Aislada, tipo Perforación | G27: =+'SUMINISTRO RS'!G27 -> u | H27: =+'SUMINISTRO RS'!H27 -> 4 | I27: 0.03 | J27: =+ROUND(I27*H27,2) -> 0.12
B28: =+B27+0.01 -> 4.05 | D28: =+'SUMINISTRO RS'!D28 -> Conector para Al 25 mm², para Neutro Desnudo, tipo Cuña | G28: =+'SUMINISTRO RS'!G28 -> u | H28: =+'SUMINISTRO RS'!H28 -> 26 | I28: 0.02 | J28: =+ROUND(I28*H28,2) -> 0.52
B29: =+B28+0.01 -> 4.06 | D29: =+'SUMINISTRO RS'!D29 -> Conector Aislado para Al 16-35 mm2, para Fase Aislada, tipo Perforación | G29: =+'SUMINISTRO RS'!G29 -> u | H29: =+'SUMINISTRO RS'!H29 -> 52 | I29: 0.02 | J29: =+ROUND(I29*H29,2) -> 1.04
B30: =+B29+0.01 -> 4.07 | D30: =+'SUMINISTRO RS'!D30 -> Correa Plástica de Amarre, color negro | G30: =+'SUMINISTRO RS'!G30 -> u | H30: =+'SUMINISTRO RS'!H30 -> 1838 | I30: 0.01 | J30: =+ROUND(I30*H30,2) -> 18.38
B31: =+B30+0.01 -> 4.08 | D31: =+'SUMINISTRO RS'!D31 -> Cinta Autofundente para extremo de cable | G31: =+'SUMINISTRO RS'!G31 -> m | H31: =+'SUMINISTRO RS'!H31 -> 51.3 | I31: 0.01 | J31: =+ROUND(I31*H31,2) -> 0.51
B32: =+B31+0.01 -> 4.09 | D32: =+'SUMINISTRO RS'!D32 -> Cinta aislante | G32: =+'SUMINISTRO RS'!G32 -> m | H32: =+'SUMINISTRO RS'!H32 -> 19 | I32: 0.01 | J32: =+ROUND(I32*H32,2) -> 0.19
F33: =+"SUB-TOTAL "&B23&": " -> SUB-TOTAL 4: | J33: =+SUM(J23:J32) -> 53.44
B34: =+B23+1 -> 5 | D34: CABLES Y CONDUCTORES DE COBRE
B35: =+B34+0.01 -> 5.01 | D35: =+'SUMINISTRO RS'!D35 -> Conductor de Cobre Recocido, tipo N2XY, Tripolar, 3 x 10 mm2, cubierta negra | G35: =+'SUMINISTRO RS'!G35 -> m | H35: =+'SUMINISTRO RS'!H35 -> 1.2 | I35: 0.12 | J35: =+ROUND(I35*H35,2) -> 0.14
B36: =+B35+0.01 -> 5.02 | D36: =+'SUMINISTRO RS'!D36 -> Conductor de Cobre Recocido, tipo N2XY, Bipolar, 2 x 2,5 mm2 | G36: =+'SUMINISTRO RS'!G36 -> m | H36: =+'SUMINISTRO RS'!H36 -> 111.5 | I36: 0.1 | J36: =+ROUND(I36*H36,2) -> 11.15
B37: =+B36+0.01 -> 5.03 | D37: =+'SUMINISTRO RS'!D37 -> Conductor de Cobre Concéntrico, 2 x 4 mm2, con aislamiento y cubierta de PVC | G37: =+'SUMINISTRO RS'!G37 -> m | H37: =+'SUMINISTRO RS'!H37 -> 3985 | I37: 0.12 | J37: =+ROUND(I37*H37,2) -> 478.2
B38: =+B37+0.01 -> 5.04 | D38: =+'SUMINISTRO RS'!D38 -> Cable de Acero con Recubrimiento Metalúrgico de Cu de 4 AWG (21,15 mm²), para Puesta a Tierra | G38: =+'SUMINISTRO RS'!G38 -> m | H38: =+'SUMINISTRO RS'!H38 -> 925.5 | I38: 0.84 | J38: =+ROUND(I38*H38,2) -> 777.42
F39: =+"SUB-TOTAL "&B34&": " -> SUB-TOTAL 5: | J39: =+SUM(J35:J38) -> 1266.91
B40: =+B34+1 -> 6 | D40: LUMINARIAS, LAMPARAS Y ACCESORIOS
B41: =+B40+0.01 -> 6.01 | D41: =+'SUMINISTRO RS'!D41 -> Pastoral tubo A°G° 38 mm Ø interior, 500 mm avance horizontal, 720 mm altura y 20° inclinación, provisto de 2 abrazaderas simples y 4 tirafondos para poste de madera | G41: =+'SUMINISTRO RS'!G41 -> u | H41: =+'SUMINISTRO RS'!H41 -> 2 | I41: 3.76 | J41: =+ROUND(I41*H41,2) -> 7.52
B42: =+B41+0.01 -> 6.02 | D42: =+'SUMINISTRO RS'!D42 -> Pastoral tubo A°G° 38 mm Ø interior, 500 mm avance horizontal, 720 mm altura y 20° inclinación, provisto de 2 abrazaderas dobles para poste de concreto | G42: =+'SUMINISTRO RS'!G42 -> u | H42: =+'SUMINISTRO RS'!H42 -> 43 | I42: 3.76 | J42: =+ROUND(I42*H42,2) -> 161.68
B43: =+B42+0.01 -> 6.03 | D43: =+'SUMINISTRO RS'!D43 -> Luminaria completa con equipo para Lámpara de Vapor de Sodio de 50 W | G43: =+'SUMINISTRO RS'!G43 -> u | H43: =+'SUMINISTRO RS'!H43 -> 45 | I43: 1.5 | J43: =+ROUND(I43*H43,2) -> 67.5
B44: =+B43+0.01 -> 6.04 | D44: =+'SUMINISTRO RS'!D44 -> Lámpara de Vapor de Sodio de Alta Presión de 50 W | G44: =+'SUMINISTRO RS'!G44 -> u | H44: =+'SUMINISTRO RS'!H44 -> 45 | I44: 0.26 | J44: =+ROUND(I44*H44,2) -> 11.7
B45: =+B44+0.01 -> 6.05 | D45: =+'SUMINISTRO RS'!D45 -> Portafusible Unipolar 220 V, de 5 A, provisto con fusible de 1 A | G45: =+'SUMINISTRO RS'!G45 -> u | H45: =+'SUMINISTRO RS'!H45 -> 45 | I45: 0.04 | J45: =+ROUND(I45*H45,2) -> 1.8
B46: =+B45+0.01 -> 6.06 | D46: =+'SUMINISTRO RS'!D46 -> Conector Bimetalico Aislado, para Al 16-35 mm2 / Cu 4-10 mm2, para Fase Aislada, tipo Perforación | G46: =+'SUMINISTRO RS'!G46 -> u | H46: =+'SUMINISTRO RS'!H46 -> 45 | I46: 0.03 | J46: =+ROUND(I46*H46,2) -> 1.35
B47: =+B46+0.01 -> 6.07 | D47: =+'SUMINISTRO RS'!D47 -> Conector Bimetálico para Al 25 mm2 / Cu 4-10 mm2, para Neutro Desnudo, tipo Cuña | G47: =+'SUMINISTRO RS'!G47 -> u | H47: =+'SUMINISTRO RS'!H47 -> 45 | I47: 0.02 | J47: =+ROUND(I47*H47,2) -> 0.9
F48: =+"SUB-TOTAL "&B40&": " -> SUB-TOTAL 6: | J48: =+SUM(J41:J47) -> 252.45
B49: =+B40+1 -> 7 | D49: RETENIDAS Y ANCLAJES
B50: =+B49+0.01 -> 7.01 | D50: =+'SUMINISTRO RS'!D50 -> Cable de acero grado Siemens Martin, de 10 mm ø, 7 hilos | G50: =+'SUMINISTRO RS'!G50 -> m | H50: =+'SUMINISTRO RS'!H50 -> 1076 | I50: 0.58 | J50: =+ROUND(I50*H50,2) -> 624.08
B51: =+B50+0.01 -> 7.02 | D51: =+'SUMINISTRO RS'!D51 -> Perno Angular con Ojal Guardacabo de A°G°, 16 mm Ø x 254 mm, provisto de Tuerca y Contratuerca | G51: =+'SUMINISTRO RS'!G51 -> u | H51: =+'SUMINISTRO RS'!H51 -> 106 | I51: 0.36 | J51: =+ROUND(I51*H51,2) -> 38.16
B52: =+B51+0.01 -> 7.03 | D52: =+'SUMINISTRO RS'!D52 -> Perno Angular con Ojal Guardacabo de A°G°, 16 mm Ø x 305 mm, provisto de Tuerca y Contratuerca | G52: =+'SUMINISTRO RS'!G52 -> u | H52: =+'SUMINISTRO RS'!H52 -> 3 | I52: 0.38 | J52: =+ROUND(I52*H52,2) -> 1.14
B53: =+B52+0.01 -> 7.04 | D53: =+'SUMINISTRO RS'!D53 -> Varilla de Anclaje de A°G° de 16 mm Ø x 2,40 m, provisto de Ojal Guardacabo en un extremo; Tuerca y Contratuerca en el otro | G53: =+'SUMINISTRO RS'!G53 -> u | H53: =+'SUMINISTRO RS'!H53 -> 109 | I53: 2.37 | J53: =+ROUND(I53*H53,2) -> 258.33
B54: =+B53+0.01 -> 7.05 | D54: =+'SUMINISTRO RS'!D54 -> Arandela de Anclaje de A°G°, 102 x 102 x 6,35 mm, Agujero de 18 mmø | G54: =+'SUMINISTRO RS'!G54 -> u | H54: =+'SUMINISTRO RS'!H54 -> 109 | I54: 0.2 | J54: =+ROUND(I54*H54,2) -> 21.8
B55: =+B54+0.01 -> 7.06 | D55: =+'SUMINISTRO RS'!D55 -> Mordaza Preformada de A°G° para Cable de 10 mm Ø | G55: =+'SUMINISTRO RS'!G55 -> u | H55: =+'SUMINISTRO RS'!H55 -> 218 | I55: 0.85 | J55: =+ROUND(I55*H55,2) -> 185.3
B56: =+B55+0.01 -> 7.07 | D56: =+'SUMINISTRO RS'!D56 -> Arandela Cuadrada Curva de A° G°, 57 x 57 x 5 mm, Agujero de 18 mm Ø | G56: =+'SUMINISTRO RS'!G56 -> u | H56: =+'SUMINISTRO RS'!H56 -> 218 | I56: 0.09 | J56: =+ROUND(I56*H56,2) -> 19.62
B57: =+B56+0.01 -> 7.08 | D57: =+'SUMINISTRO RS'!D57 -> Soporte de Contrapunta de 51 mm ø x 1000 mm de longitud, con Abrazadera partida en un extremo y Grapa de Ajuste para Cable en el otro | G57: =+'SUMINISTRO RS'!G57 -> u | H57: =+'SUMINISTRO RS'!H57 -> 14 | I57: 1.59 | J57: =+ROUND(I57*H57,2) -> 22.26
B58: =+B57+0.01 -> 7.09 | D58: =+'SUMINISTRO RS'!D58 -> Alambre de Acero N° 12 para Entorchado | G58: =+'SUMINISTRO RS'!G58 -> m | H58: =+'SUMINISTRO RS'!H58 -> 327 | I58: 0.02 | J58: =+ROUND(I58*H58,2) -> 6.54
B59: =+B58+0.01 -> 7.1 | D59: =+'SUMINISTRO RS'!D59 -> Bloque de concreto de 0,40 x 0,40 x 0,15 m | G59: =+'SUMINISTRO RS'!G59 -> u | H59: =+'SUMINISTRO RS'!H59 -> 109 | I59: 23.88 | J59: =+ROUND(I59*H59,2) -> 2602.92
B60: =+B59+0.01 -> 7.11 | D60: =+'SUMINISTRO RS'!D60 -> Conector Bimetálico para Al 25 mm2 / Cu 4-10 mm2, para Neutro Desnudo, tipo Cuña | G60: =+'SUMINISTRO RS'!G60 -> u | H60: =+'SUMINISTRO RS'!H60 -> 109 | I60: 0.02 | J60: =+ROUND(I60*H60,2) -> 2.18
B61: =+B60+0.01 -> 7.12 | D61: =+'SUMINISTRO RS'!D61 -> Conector Doble Via Bimetálico para Cable de Acero de 10 mm ø y para Cable de Acero con Recubrimiento Metalúrgico de Cobre de 4 AWG (21,15 mm2) | G61: =+'SUMINISTRO RS'!G61 -> u | H61: =+'SUMINISTRO RS'!H61 -> 109 | I61: 0.12 | J61: =+ROUND(I61*H61,2) -> 13.08
F62: =+"SUB-TOTAL "&B49&": " -> SUB-TOTAL 7: | J62: =+SUM(J50:J61) -> 3795.41
B63: =+B49+1 -> 8 | D63: ACCESORIOS DE FERRETERIA PARA ESTRUCTURAS
B64: =+B63+0.01 -> 8.01 | D64: =+'SUMINISTRO RS'!D64 -> Perno con Gancho de 16 mm Ø, provisto de Arandela, Tuerca y Contratuerca, longitud de 254 mm | G64: =+'SUMINISTRO RS'!G64 -> u | H64: =+'SUMINISTRO RS'!H64 -> 141 | I64: 0.5 | J64: =+ROUND(I64*H64,2) -> 70.5
B65: =+B64+0.01 -> 8.02 | D65: =+'SUMINISTRO RS'!D65 -> Perno con Gancho de 16 mm Ø, provisto de Arandela, Tuerca y Contratuerca, longitud de 305 mm | G65: =+'SUMINISTRO RS'!G65 -> u | H65: =+'SUMINISTRO RS'!H65 -> 22 | I65: 0.54 | J65: =+ROUND(I65*H65,2) -> 11.88
B66: =+B65+0.01 -> 8.03 | D66: =+'SUMINISTRO RS'!D66 -> Perno de A°G° de 13 mm Ø x 254 mm, provisto de Tuerca y Contratuerca | G66: =+'SUMINISTRO RS'!G66 -> u | H66: =+'SUMINISTRO RS'!H66 -> 248 | I66: 0.32 | J66: =+ROUND(I66*H66,2) -> 79.36
B67: =+B66+0.01 -> 8.04 | D67: =+'SUMINISTRO RS'!D67 -> Perno de A°G° de 13 mm Ø x 305 mm, provisto de Tuerca y Contratuerca | G67: =+'SUMINISTRO RS'!G67 -> u | H67: =+'SUMINISTRO RS'!H67 -> 50 | I67: 0.32 | J67: =+ROUND(I67*H67,2) -> 16
B68: =+B67+0.01 -> 8.05 | D68: =+'SUMINISTRO RS'!D68 -> Perno Ojo de A°G° de 16 mm Ø x 254 mm, provisto de Tuerca y Contratuerca | G68: =+'SUMINISTRO RS'!G68 -> u | H68: =+'SUMINISTRO RS'!H68 -> 127 | I68: 0.45 | J68: =+ROUND(I68*H68,2) -> 57.15
B69: =+B68+0.01 -> 8.06 | D69: =+'SUMINISTRO RS'!D69 -> Perno Ojo de A°G° de 16 mm Ø x 305 mm, provisto de Tuerca y Contratuerca | G69: =+'SUMINISTRO RS'!G69 -> u | H69: =+'SUMINISTRO RS'!H69 -> 33 | I69: 0.54 | J69: =+ROUND(I69*H69,2) -> 17.82
B70: =+B69+0.01 -> 8.07 | D70: =+'SUMINISTRO RS'!D70 -> Tuerca-Ojo para Perno de 16 mm Ø | G70: =+'SUMINISTRO RS'!G70 -> u | H70: =+'SUMINISTRO RS'!H70 -> 58 | I70: 0.48 | J70: =+ROUND(I70*H70,2) -> 27.84
B71: =+B70+0.01 -> 8.08 | D71: =+'SUMINISTRO RS'!D71 -> Fleje de acero inoxidable de 19 mm provisto de hebilla | G71: =+'SUMINISTRO RS'!G71 -> m | H71: =+'SUMINISTRO RS'!H71 -> 2 | I71: 0.45 | J71: =+ROUND(I71*H71,2) -> 0.9
B72: =+B71+0.01 -> 8.09 | D72: =+'SUMINISTRO RS'!D72 -> Arandela Cuadrada Curva de A° G°, 57 x 57 x 5 mm, Agujero de 14 mm Ø | G72: =+'SUMINISTRO RS'!G72 -> u | H72: =+'SUMINISTRO RS'!H72 -> 296 | I72: 0.07 | J72: =+ROUND(I72*H72,2) -> 20.72
B73: =+B72+0.01 -> 8.1 | D73: =+'SUMINISTRO RS'!D73 -> Arandela Cuadrada Curva de A° G°, 57 x 57 x 5 mm, Agujero de 18 mm Ø | G73: =+'SUMINISTRO RS'!G73 -> u | H73: =+'SUMINISTRO RS'!H73 -> 483 | I73: 0.09 | J73: =+ROUND(I73*H73,2) -> 43.47
B74: =+B73+0.01 -> 8.11 | D74: =+'SUMINISTRO RS'!D74 -> Caja de derivacion para acometidas, sistema 440-22O V (10 borneras en cada barra de cobre) | G74: =+'SUMINISTRO RS'!G74 -> u | H74: =+'SUMINISTRO RS'!H74 -> 2 | I74: 1.05 | J74: =+ROUND(I74*H74,2) -> 2.1
B75: =+B74+0.01 -> 8.12 | D75: =+'SUMINISTRO RS'!D75 -> Portalinea unipolar de AºGº, provisto de PIN de 10 mm Ø | G75: =+'SUMINISTRO RS'!G75 -> u | H75: =+'SUMINISTRO RS'!H75 -> 300 | I75: 0.19 | J75: =+ROUND(I75*H75,2) -> 57
... B77: =+B76+0.01 -> 8.14 | D77: =+'SUMINISTRO RS'!D77 -> Plantillas para Identificación y/o codificación de Postes (Peligro, Identificación y/o codificación y Fases) | G77: =+'SUMINISTRO RS'!G77 -> Jgo. | H77: =+'SUMINISTRO RS'!H77 -> 29 | I77: 0.22 | J77: =+ROUND(I77*H77,2) -> 6.38
F78: =+"SUB-TOTAL "&B63&": " -> SUB-TOTAL 8: | J78: =+SUM(J63:J77) -> 412.02
B79: =1+B63 -> 9 | D79: PUESTA A TIERRA
B80: =+B79+0.01 -> 9.01 | D80: =+'SUMINISTRO RS'!D80 -> Electrodo de Acero Recubierto de Cobre de 16 mm Ø x 2,40 m | G80: =+'SUMINISTRO RS'!G80 -> u | H80: =+'SUMINISTRO RS'!H80 -> 72 | I80: 2.59 | J80: =+ROUND(I80*H80,2) -> 186.48
B81: =+B80+0.01 -> 9.02 | D81: =+'SUMINISTRO RS'!D81 -> Conector bimetálico para Al 25 mm2 y Cobre de 25 mm2, tipo cuña | G81: =+'SUMINISTRO RS'!G81 -> u | H81: =+'SUMINISTRO RS'!H81 -> 72 | I81: 0.02 | J81: =+ROUND(I81*H81,2) -> 1.44
B82: =+B81+0.01 -> 9.03 | D82: =+'SUMINISTRO RS'!D82 -> Conector de bronce para electrodo de 16 mm ø y Cable de Acero con Recubrimiento Metalúrgico de Cobre de 4 AWG (21,15 mm2) | G82: =+'SUMINISTRO RS'!G82 -> u | H82: =+'SUMINISTRO RS'!H82 -> 72 | I82: 0.24 | J82: =+ROUND(I82*H82,2) -> 17.28
B83: =+B82+0.01 -> 9.04 | D83: =+'SUMINISTRO RS'!D83 -> Grapa en "U" para fijar conductor de PAT a Poste de Madera | G83: =+'SUMINISTRO RS'!G83 -> u | H83: =+'SUMINISTRO RS'!H83 -> 60 | I83: 0.05 | J83: =+ROUND(I83*H83,2) -> 3
B84: =+B83+0.01 -> 9.05 | D84: =+'SUMINISTRO RS'!D84 -> Listón de madera tratada 50 x 19 mm sección, 2,7 m longitud (incluye clavos de fijación) | G84: =+'SUMINISTRO RS'!G84 -> u | H84: =+'SUMINISTRO RS'!H84 -> 3 | I84: 2.86 | J84: =+ROUND(I84*H84,2) -> 8.58
B85: =+B84+0.01 -> 9.06 | D85: =+'SUMINISTRO RS'!D85 -> Plantilla para Señalización de Poste (Puesta a Tierra) | G85: =+'SUMINISTRO RS'!G85 -> u | H85: =+'SUMINISTRO RS'!H85 -> 72 | I85: 0.12 | J85: =+ROUND(I85*H85,2) -> 8.64
B86: =+B85+0.01 -> 9.07 | D86: =+'SUMINISTRO RS'!D86 -> Tubo Plastico de PVC SAP de 19 mm ø x 0,5 m ( incluye curva de plastico de 19 mm ø x 90º) | G86: =+'SUMINISTRO RS'!G86 -> u | H86: =+'SUMINISTRO RS'!H86 -> 68 | I86: 0.12 | J86: =+ROUND(I86*H86,2) -> 8.16
F87: =+"SUB-TOTAL "&B79&": " -> SUB-TOTAL 9: | J87: =+SUM(J80:J86) -> 233.58
B88: =1+B79 -> 10 | D88: CONEXIONES DOMICILIARIAS
B89: =+B88+0.01 -> 10.01 | D89: =+'SUMINISTRO RS'!D89 -> Tubo de AºGº standard / redondo de 19 mm Ø x 1,5 mm x 2,5 m, provisto de codo | G89: =+'SUMINISTRO RS'!G89 -> u | H89: =+'SUMINISTRO RS'!H89 -> 147 | I89: 1.59 | J89: =+ROUND(I89*H89,2) -> 233.73
B90: =+B89+0.01 -> 10.02 | D90: =+'SUMINISTRO RS'!D90 -> Tubo de AºGº standard / redondo de 19 mm Ø x 1,5 mm x 4,0 m, provisto de codo | G90: =+'SUMINISTRO RS'!G90 -> u | H90: =+'SUMINISTRO RS'!H90 -> 68 | I90: 2.21 | J90: =+ROUND(I90*H90,2) -> 150.28
B91: =+B90+0.01 -> 10.03 | D91: =+'SUMINISTRO RS'!D91 -> Tubo de AºGº standard / redondo de 19 mm Ø x 1,5 mm x 6,0 m, provisto de codo | G91: =+'SUMINISTRO RS'!G91 -> u | H91: =+'SUMINISTRO RS'!H91 -> 28 | I91: 2.75 | J91: =+ROUND(I91*H91,2) -> 77
B92: =+B91+0.01 -> 10.04 | D92: =+'SUMINISTRO RS'!D92 -> Tubo de AºGº standard / redondo de 38 mm Ø x 1,5 mm x 6,0 m, provisto de codo | G92: =+'SUMINISTRO RS'!G92 -> u | H92: =+'SUMINISTRO RS'!H92 -> 40 | I92: 4.7 | J92: =+ROUND(I92*H92,2) -> 188
B93: =+B92+0.01 -> 10.05 | D93: =+'SUMINISTRO RS'!D93 -> Armella Tirafondo de 10 mm Ø x 64 mm de longitud | G93: =+'SUMINISTRO RS'!G93 -> u | H93: =+'SUMINISTRO RS'!H93 -> 39 | I93: 0.01 | J93: =+ROUND(I93*H93,2) -> 0.39
B94: =+B93+0.01 -> 10.06 | D94: =+'SUMINISTRO RS'!D94 -> Tarugo de cedro de 13 mm x 50 mm | G94: =+'SUMINISTRO RS'!G94 -> u | H94: =+'SUMINISTRO RS'!H94 -> 39 | I94: 0.08 | J94: =+ROUND(I94*H94,2) -> 3.12
B95: =+B94+0.01 -> 10.07 | D95: =+'SUMINISTRO RS'!D95 -> Alambre de Acero N° 12 para Entorchado | G95: =+'SUMINISTRO RS'!G95 -> m | H95: =+'SUMINISTRO RS'!H95 -> 933 | I95: 0.02 | J95: =+ROUND(I95*H95,2) -> 18.66
B96: =+B95+0.01 -> 10.08 | D96: =+'SUMINISTRO RS'!D96 -> Conector Bimetálico para Al 25 mm2 / Cu 4-10 mm2, para Neutro Desnudo, tipo Cuña | G96: =+'SUMINISTRO RS'!G96 -> u | H96: =+'SUMINISTRO RS'!H96 -> 175 | I96: 0.02 | J96: =+ROUND(I96*H96,2) -> 3.5
B97: =+B96+0.01 -> 10.09 | D97: =+'SUMINISTRO RS'!D97 -> Conector Bimetalico Aislado, para Al 16-35 mm2 / Cu 4-10 mm2, para Fase Aislada, tipo Perforación | G97: =+'SUMINISTRO RS'!G97 -> u | H97: =+'SUMINISTRO RS'!H97 -> 175 | I97: 0.03 | J97: =+ROUND(I97*H97,2) -> 5.25
B98: =+B97+0.01 -> 10.1 | D98: =+'SUMINISTRO RS'!D98 -> Templador de AºGº | G98: =+'SUMINISTRO RS'!G98 -> u | H98: =+'SUMINISTRO RS'!H98 -> 350 | I98: 0.04 | J98: =+ROUND(I98*H98,2) -> 14
B99: =+B98+0.01 -> 10.11 | D99: =+'SUMINISTRO RS'!D99 -> Correa Plástica de Amarre, color negro | G99: =+'SUMINISTRO RS'!G99 -> u | H99: =+'SUMINISTRO RS'!H99 -> 756 | I99: 0.01 | J99: =+ROUND(I99*H99,2) -> 7.56
B100: =+B99+0.01 -> 10.12 | D100: =+'SUMINISTRO RS'!D100 -> Caja Metálica Portamedidor, equipado con Interruptor Termomagnético de 10A | G100: =+'SUMINISTRO RS'!G100 -> u | H100: =+'SUMINISTRO RS'!H100 -> 175 | I100: 0.51 | J100: =+ROUND(I100*H100,2) -> 89.25
B101: =+B100+0.01 -> 10.13 | D101: =+'SUMINISTRO RS'!D101 -> Medidor Monofásico de Energía Activa, tipo Electrónico con Micro Procesador de 220 V; 2 hilos, 10-40 A, 60 Hz, Clase 1 | G101: =+'SUMINISTRO RS'!G101 -> u | H101: =+'SUMINISTRO RS'!H101 -> 175 | I101: 0.95 | J101: =+ROUND(I101*H101,2) -> 166.25
F102: =+"SUB-TOTAL "&B88&": " -> SUB-TOTAL 10: | J102: =+SUM(J89:J101) -> 956.99
D103: TOTAL TRANSPORTE DE MATERIALES | J103: =+ROUND(SUM(J10:J102)/2,2) -> 39859.51
...

Sheet POLINOMICA RS
B3: FÓRMULA POLINÓMICA
C6: PROYECTO :
C7: AMPLIACIÓN DEL SERVICIO DE ENERGÍA ELÉCTRICA EN LA PROVINCIA DEL SANTA Y EN EL DISTRITO DE PAMPAROMAS – DEPARTAMENTO DE ANCASH”
C9: REDES SECUNDARIAS, INCLUYE CONEXIONES DOMICILIARIAS
C10: PRESUPUESTO BASE S/ | D10: =+'RESUMEN RS'!F21 -> #REF! | M10: =D10=SUM(G13:G25) -> #REF! | N10: =D10='RESUMEN RS'!F21 -> #REF!
B12: Nº | C12: ELEMENTO REPRESENTATIVO | D12: INDICE UNIFICADO | E12: SIMBOLO | F12: SIMBOLO MONOMIO | G12: MONTO | H12: INCIDENCIA | I12: % PARCIAL | J12: COEFICIENTE
B13: 1 | C13: POSTES DE CONCRETO | D13: 062 | E13: PC | F13: PC | G13: =+'SUMINISTRO RS'!J12 -> 88784.34 | H13: =ROUND(G13/$D$10,3) -> #REF! | I13: =ROUND(G13/SUM($G$13:$G$14),4) -> 0.9245 | J13: =+ROUND(SUM(H13:H14),3) -> #REF!
C14: POSTE DE MADERA IMPORTADA | D14: 042 | E14: PM | G14: =+'SUMINISTRO RS'!J15 -> 7250.94 | H14: =ROUND(G14/$D$10,3) -> #REF! | I14: =ROUND(G14/SUM($G$13:$G$14),4) -> 0.0755
B15: 2 | C15: CABLES Y CONDUCTORES DE ALUMINIO | D15: 030 | E15: DI1 | F15: DI1 | G15: =+'SUMINISTRO RS'!J22 -> 70734.6 | H15: =ROUND(G15/$D$10,3) -> #REF! | I15: =ROUND(G15/SUM($G$15:$G$16),4) -> 0.6489 | J15: =+ROUND(SUM(H15:H16),3) -> #REF!
C16: CONEXIONES DOMICILIARIAS | D16: 030 | E16: DI2 | G16: =+'SUMINISTRO RS'!J102 -> 38276.71 | H16: =ROUND(G16/$D$10,3) -> #REF! | I16: =ROUND(G16/SUM($G$15:$G$16),4) -> 0.3511
B17: 3 | C17: LUMINARIAS, LAMPARAS Y ACCESORIOS | D17: 011 | E17: AE1 | F17: CU | G17: =+'SUMINISTRO RS'!J48 -> 16747.02 | H17: =ROUND(G17/$D$10,3) -> #REF! | I17: =ROUND(G17/SUM($G$17:$G$22),4) -> 0.1738 | J17: =+ROUND(SUM(H17:H22),3) -> #REF!
C18: ACCESORIOS PARA CABLES AUTOPORTANTES | D18: 002 | E18: AE2 | G18: =+'SUMINISTRO RS'!J33 -> 7470.27 | H18: =ROUND(G18/$D$10,3) -> #REF! | I18: =ROUND(G18/SUM($G$17:$G$22)+0.0001,4) -> 0.0776
C19: RETENIDAS Y ANCLAJES | D19: 002 | E19: FE1 | G19: =+'SUMINISTRO RS'!J62 -> 22349.82 | H19: =ROUND(G19/$D$10,3) -> #REF! | I19: =ROUND(G19/SUM($G$17:$G$22),4) -> 0.232
C20: ACCESORIOS DE FERRETERIA PARA ESTRUCTURAS | D20: 002 | E20: FE2 | G20: =+'SUMINISTRO RS'!J78 -> 10915.53 | H20: =ROUND(G20/$D$10,3) -> #REF! | I20: =ROUND(G20/SUM($G$17:$G$22),4) -> 0.1133
C21: CABLES Y CONDUCTORES DE COBRE | D21: 006 | E21: CU | G21: =+'SUMINISTRO RS'!J39 -> 31534.94 | H21: =ROUND(G21/$D$10,3) -> #REF! | I21: =ROUND(G21/SUM($G$17:$G$22),4) -> 0.3274
C22: PUESTA A TIERRA | D22: 006 | E22: PT | G22: =+'SUMINISTRO RS'!J87 -> 7312.93 | H22: =ROUND(G22/$D$10,3) -> #REF! | I22: =ROUND(G22/SUM($G$17:$G$22),4) -> 0.0759
B23: 4 | C23: MONTAJE ELECTROMECANICO | D23: 047 | E23: J | F23: J | G23: =+'MONTAJE RS'!J96 -> 273560.14 | H23: =ROUND(G23/$D$10-0.001,3) -> #REF! | I23: =ROUND(G23/($G$23+$G$24),4) -> 0.8728 | J23: =+ROUND(SUM(H23:H24),3) -> #REF!
C24: TRANSPORTE | D24: 032 | E24: FT | G24: =+TRANS.RS!J103 -> 39859.51 | H24: =ROUND(G24/$D$10,3) -> #REF! | I24: =ROUND(G24/($G$23+$G$24),4) -> 0.1272
B25: 5 | C25: GASTOS GENERALES Y UTILIDADES | D25: 039 | E25: GG | F25: GG | G25: =+'RESUMEN RS'!F18+'RESUMEN RS'!F19 -> #REF! | H25: =ROUND(G25/$D$10,3) -> #REF! | I25: =+G25/(G25) -> #REF! | J25: =+ROUND(SUM(H25),3) -> #REF!
H26: =SUM(H15:H25) -> #REF!
B27: K= | C27: =J13&" PCr/PCo + "&J15&" DI1r/DI1o + "&J17&" CUr/CUo+ "&J23&" Jr/Jo + "&J25&" GGr/GGo" -> #REF!
B30: NOTAS:
B32: 1.- | C32: En la fórmula los sub-indices "o" de cada símbolo corresponden al indice de precios según (CREPCO) a la
C33: fecha de Elaboración del Presupuesto (Presupuesto Base) y los sub-indices "r" al indice de precios al
C34: momento de reajuste o fecha de valorización
B35: 2.- | C35: En el caso de los monomios compuestos por varios indices se ha considerado para efecto de denominación
C36: el símbolo que tiene mayor porcentaje de incidencia
B37: 3.- | C37: En caso de cambios en el suministro se deberá actualizar la formula polinómica.
H43: =+IF(SUM(H13:H25)=1,"OK","X") -> #REF! | I43: =+IF(SUM(I13:I25)=5,"OK","X") -> #REF! | J43: =+IF(SUM(J13:J25)=1,"OK","X") -> #REF!

Sheet Alternativa-SFV)
B3: RESUMEN DEL VALOR REFERENCIAL
B5: UBICACIÓN | D5: :
B6: SECCIÓN I | D6: : | E6: RESUMEN GENERAL FOTOVOLTAICO
B9: ITEM | C9: DESCRIPCION | F9: TOTAL (S/.)
B11: A | D11: SUMINISTROS DE MATERIALES | F11: =+#REF! -> #REF!
D12: Origen Nacional | F12: =+F11-F13 -> #REF!
D13: Origen Importado | F13: =+SFVS!#REF!+SFVS!#REF!+SFVS!#REF!+SFVS!#REF!+SFVS!#REF!+SFVS!#REF!+SFVS!#REF!+SFVS!#REF!+SFVS!#REF!+SFVS!#REF!+SFVS!#REF!+SFVS!#REF!+SFVS!#REF!+SFVS!#REF!+SFVS!#REF!+SFVS!#REF! -> #REF!
B15: B | D15: MONTAJE ELECTROMECANICO | F15: =+#REF! -> #REF!
D16: M.O. Calificada | F16: =ROUND(H16*F15,2) -> #REF! | H16: 0.63
D17: M.O. No Calificada | F17: =ROUND(H17*F15,2) -> #REF! | H17: 0.37
B19: B.1 | D19: ACTIVIDADES COMPLEMENTARIAS DE MONTAJE | F19: 0
B21: C | D21: TRANSPORTE DE MATERIALES | F21: =+#REF! -> #REF!
B24: D | D24: TOTAL COSTO DIRECTO (C.D.) | F24: =+F11+F15+F21+F19 -> #REF!
F32: =+F24+F27+F29 -> #REF!

Sheet SFVS
B1: METRADO ESTUDIO DEFINITIVO
B2: SUMINISTRO DE MATERIALES DE SISTEMAS FOTOVOLTAICOS
B3: UBICACIÓN | D3: : | E3: ANCASH | J3: CANTU | K3: COCHANAN | L3: IRCAN | M3: PALMADERA HURAN | N3: PINQUEY | O3: ICHIC MARCA | P3: POCHCOS | Q3: LA CUCHILLA | R3: CAYHUAMARCA | S3: MESITA (NAHUIN) | T3: ALIZO | U3: COTOHUAIN
B4: SECCIÓN IV | D4: : | E4: SISTEMAS FOTOVOLTAICOS
B5: A: SUMINISTRO DE MATERIALES
B7: Item | C7: Descripción de Partidas | G7: Unid. | H7: Metrado | J7: 1 | K7: 2 | L7: 3 | M7: 4 | N7: 5 | O7: 6 | P7: 7 | Q7: 8 | R7: 9 | S7: 10 | T7: 11 | U7: 12
B8: A | D8: SUMINISTRO DE MATERIALES
B9: 1 | D9: UNIDAD DE GENERACIÓN
B10: =+B9+0.01 -> 1.01 | D10: Módulo Fotovoltaico 160 Wp, 12Vdc, silicio cristalino | G10: u | H10: =SUM(J10:U10) -> 37 | J10: 10 | K10: 4 | L10: 3 | M10: 3 | N10: 5 | O10: 2 | Q10: 3 | R10: 6 | S10: 1 | T10: 0
B11: =+B10+0.01 -> 1.02 | D11: Modulo Soporte de F°G° para SFV 160 Wp según lámina de detalle. Incluye accesorios | G11: u | H11: =SUM(J11:U11) -> 37 | J11: =+J$10 -> 10 | K11: =+K$10 -> 4 | L11: =+L$10 -> 3 | M11: =+M$10 -> 3 | N11: =+N$10 -> 5 | O11: =+O$10 -> 2 | P11: =+P$10 -> 0 | Q11: =+Q$10 -> 3 | ... U11: =+U$10 -> 0
B13: =+B9+1 -> 2 | D13: UNIDAD DE CONTROL
B14: =+B13+0.01 -> 2.01 | D14: Tablero de protección adosable de PVC, con puerta, 12 Vdc, 0 2 polos, IP 54, con riel DIN y accesorios de fijación | G14: u | H14: =SUM(J14:U14) -> 37 | J14: =+J$10 -> 10 | K14: =+K$10 -> 4 | L14: =+L$10 -> 3 | M14: =+M$10 -> 3 | N14: =+N$10 -> 5 | O14: =+O$10 -> 2 | P14: =+P$10 -> 0 | Q14: =+Q$10 -> 3 | ... U14: =+U$10 -> 0 | Y14: =SUM(Y16:Y33) -> 22.27
B15: =+B14+0.01 -> 2.02 | D15: Interruptor termomagnético 12 Vdc, 16 A | G15: u | H15: =SUM(J15:U15) -> 37 | J15: =+J$10 -> 10 | K15: =+K$10 -> 4 | L15: =+L$10 -> 3 | M15: =+M$10 -> 3 | N15: =+N$10 -> 5 | O15: =+O$10 -> 2 | P15: =+P$10 -> 0 | Q15: =+Q$10 -> 3 | ... U15: =+U$10 -> 0
B16: =+B15+0.01 -> 2.03 | D16: Conector rectangular hermético tipo CONDUIT, de A°G° para tubería flexible de 3/4" | G16: u | H16: =SUM(J16:U16) -> 74 | J16: =2*J$10 -> 20 | K16: =2*K$10 -> 8 | L16: =2*L$10 -> 6 | M16: =2*M$10 -> 6 | N16: =2*N$10 -> 10 | O16: =2*O$10 -> 4 | P16: =2*P$10 -> 0 | Q16: =2*Q$10 -> 6 | ... U16: =2*U$10 -> 0 | Y16: 0.3
B17: =+B16+0.01 -> 2.04 | D17: Caja de control de carga adosable de PVC, con puerta, IP54, con riel DIN, borne de puesta a tierra y accesorios de fijación | G17: u | H17: =SUM(J17:U17) -> 37 | J17: =+J$10 -> 10 | K17: =+K$10 -> 4 | L17: =+L$10 -> 3 | M17: =+M$10 -> 3 | N17: =+N$10 -> 5 | O17: =+O$10 -> 2 | P17: =+P$10 -> 0 | Q17: =+Q$10 -> 3 | ... U17: =+U$10 -> 0 | X17: =SUM(X18:X27) -> 21.66 | Y17: 0.3
B18: =+B17+0.01 -> 2.05 | D18: Controlador de carga tipo PWM 12/24 Vdc, 20A | G18: u | H18: =SUM(J18:U18) -> 37 | J18: =+J$10 -> 10 | K18: =+K$10 -> 4 | L18: =+L$10 -> 3 | M18: =+M$10 -> 3 | N18: =+N$10 -> 5 | O18: =+O$10 -> 2 | P18: =+P$10 -> 0 | Q18: =+Q$10 -> 3 | ... U18: =+U$10 -> 0 | X18: 0.58 | Y18: 0.48
B19: =+B18+0.01 -> 2.06 | D19: Tubería eléctrica tipo CONDUIT flexible corrugada de F°G°, con forro corrugado de PVC y 3/4" de diámetro | G19: m | H19: =SUM(J19:U19) -> 37 | J19: =+J$10 -> 10 | K19: =+K$10 -> 4 | L19: =+L$10 -> 3 | M19: =+M$10 -> 3 | N19: =+N$10 -> 5 | O19: =+O$10 -> 2 | P19: =+P$10 -> 0 | Q19: =+Q$10 -> 3 | ... U19: =+U$10 -> 0 | X19: 0.37 | Y19: 0.64
B20: =+B19+0.01 -> 2.07 | D20: Abrazadera de F°G° de dos orejas para tubo de PVC de 3/4" diámetro con accesorios de fijación | G20: u | H20: =SUM(J20:U20) -> 74 | J20: =2*J$10 -> 20 | K20: =2*K$10 -> 8 | L20: =2*L$10 -> 6 | M20: =2*M$10 -> 6 | N20: =2*N$10 -> 10 | O20: =2*O$10 -> 4 | P20: =2*P$10 -> 0 | Q20: =2*Q$10 -> 6 | ... U20: =2*U$10 -> 0 | X20: 0.74 | Y20: 0.23.
B21: =+B20+0.01 -> 2.08 | D21: Caja estanca de PVC con tapa atornillable, IP 65, de 100x100x70 mm | G21: u | H21: =SUM(J21:U21) -> 37 | J21: =+J$10 -> 10 | K21: =+K$10 -> 4 | L21: =+L$10 -> 3 | M21: =+M$10 -> 3 | N21: =+N$10 -> 5 | O21: =+O$10 -> 2 | P21: =+P$10 -> 0 | Q21: =+Q$10 -> 3 | ... U21: =+U$10 -> 0 | X21: 1.2 | Y21: 0.3
B22: =+B21+0.01 -> 2.09 | D22: Bornera de línea a tierra para 8 conductores de 16 mm2 Cu | G22: u | H22: =SUM(J22:U22) -> 37 | J22: =+J$10 -> 10 | K22: =+K$10 -> 4 | L22: =+L$10 -> 3 | M22: =+M$10 -> 3 | N22: =+N$10 -> 5 | O22: =+O$10 -> 2 | P22: =+P$10 -> 0 | Q22: =+Q$10 -> 3 | ... U22: =+U$10 -> 0 | X22: 0.71 | Y22: 0.2
B23: =+B22+0.01 -> 2.1 | D23: Interruptor termomagnético 12 Vdc, 16 A (De requerirse) | G23: u | H23: =SUM(J23:U23) -> 37 | J23: =+J$10 -> 10 | K23: =+K$10 -> 4 | L23: =+L$10 -> 3 | M23: =+M$10 -> 3 | N23: =+N$10 -> 5 | O23: =+O$10 -> 2 | P23: =+P$10 -> 0 | Q23: =+Q$10 -> 3 | ... U23: =+U$10 -> 0 | X23: 9.63 | Y23: 0.37
B24: =+B23+0.01 -> 2.11 | D24: Interruptor termomagnético 12 Vdc, 40 A (De requerirse) | G24: u | H24: =SUM(J24:U24) -> 37 | J24: =+J$10 -> 10 | K24: =+K$10 -> 4 | L24: =+L$10 -> 3 | M24: =+M$10 -> 3 | N24: =+N$10 -> 5 | O24: =+O$10 -> 2 | P24: =+P$10 -> 0 | Q24: =+Q$10 -> 3 | ... U24: =+U$10 -> 0 | X24: 3.03 | Y24: 0.9
D25: Supresor de pico protección de sobretensión tipo II, Uoc 275V, In(8/20 us) 5kA | G25: u | H25: =SUM(J25:U25) -> 37 | J25: =+J$10 -> 10 | K25: =+K$10 -> 4 | L25: =+L$10 -> 3 | M25: =+M$10 -> 3 | N25: =+N$10 -> 5 | O25: =+O$10 -> 2 | P25: =+P$10 -> 0 | Q25: =+Q$10 -> 3 | ... U25: =+U$10 -> 0
X26: 3.06 | Y26: 0.45
B27: =+B13+1 -> 3 | D27: UNIDAD DE ALMACENAMIENTO | X27: 2.34 | Y27: 0.61
B28: =+B27+0.01 -> 3.01 | D28: Bateria de electrolito gelificado, 150 Ah, 12 Vdc | G28: u | H28: =SUM(J28:U28) -> 0 | J28: 0 | K28: 0 | L28: 0 | M28: 0 | N28: 0 | O28: 0 | P28: 0 | Q28: 0 | R28: 0 | S28: 0 | T28: 0 | U28: 0 | Y28: 0.4
B29: =+B28+0.01 -> 3.02 | D29: Rack para bateria gelificada, 150 Ah, 12 Vdc, incluye accesorios de fijación y protección | G29: u | H29: =SUM(J29:U29) -> 0 | J29: 0 | K29: 0 | L29: 0 | M29: 0 | N29: 0 | O29: 0 | P29: 0 | Q29: 0 | R29: 0 | S29: 0 | T29: 0 | U29: 0 | Y29: 7.89
B30: =+B29+0.01 -> 3.03 | D30: Conductor THW de 6 mm2, Cu | G30: m | H30: =SUM(J30:U30) -> 148 | J30: =4*J$10 -> 40 | K30: =4*K$10 -> 16 | L30: =4*L$10 -> 12 | M30: =4*M$10 -> 12 | N30: =4*N$10 -> 20 | O30: =4*O$10 -> 8 | P30: =4*P$10 -> 0 | Q30: =4*Q$10 -> 12 | ... U30: =4*U$10 -> 0 | Y30: 2.01
B31: =+B30+0.01 -> 3.04 | D31: Tubería eléctrica tipo CONDUIT flexible corrugada de F°G°, con forro corrugado de PVC y 3/4" de diámetro | G31: m | H31: =SUM(J31:U31) -> 74 | J31: =2*J$10 -> 20 | K31: =2*K$10 -> 8 | L31: =2*L$10 -> 6 | M31: =2*M$10 -> 6 | N31: =2*N$10 -> 10 | O31: =2*O$10 -> 4 | P31: =2*P$10 -> 0 | Q31: =2*Q$10 -> 6 | ... U31: =2*U$10 -> 0 | Y31: 2.98
B32: =+B31+0.01 -> 3.05 | D32: Abrazadera de F°G° de dos orejas para tubo de PVC de 3/4" diámetro con accesorios de fijación | G32: u | H32: =SUM(J32:U32) -> 259 | J32: =7*J$10 -> 70 | K32: =7*K$10 -> 28 | L32: =7*L$10 -> 21 | M32: =7*M$10 -> 21 | N32: =7*N$10 -> 35 | O32: =7*O$10 -> 14 | P32: =7*P$10 -> 0 | Q32: =7*Q$10 -> 21 | ... U32: =7*U$10 -> 0 | Y32: 2.34
B33: =+B32+0.01 -> 3.06 | D33: Caja estanca de PVC con tapa atornillable, IP 65, de 100x100x70 mm | G33: u | H33: =SUM(J33:U33) -> 37 | J33: =+J$10 -> 10 | K33: =+K$10 -> 4 | L33: =+L$10 -> 3 | M33: =+M$10 -> 3 | N33: =+N$10 -> 5 | O33: =+O$10 -> 2 | P33: =+P$10 -> 0 | Q33: =+Q$10 -> 3 | ... U33: =+U$10 -> 0 | Y33: 2.1
B34: =+B33+0.01 -> 3.07 | D34: Conector rectangular hermético de PVC para tubería eléctrica flexible de PVC corrugada de 3/4" | G34: u | H34: =SUM(J34:U34) -> 74 | J34: =2*J$10 -> 20 | K34: =2*K$10 -> 8 | L34: =2*L$10 -> 6 | M34: =2*M$10 -> 6 | N34: =2*N$10 -> 10 | O34: =2*O$10 -> 4 | P34: =2*P$10 -> 0 | Q34: =2*Q$10 -> 6 | ... U34: =2*U$10 -> 0
B35: =+B34+0.01 -> 3.08 | D35: Conector rectangular hermético tipo CONDUIT, de A°G° para tubería flexible de 3/4" | G35: u | H35: =SUM(J35:U35) -> 148 | J35: =4*J$10 -> 40 | K35: =4*K$10 -> 16 | L35: =4*L$10 -> 12 | M35: =4*M$10 -> 12 | N35: =4*N$10 -> 20 | O35: =4*O$10 -> 8 | P35: =4*P$10 -> 0 | Q35: =4*Q$10 -> 12 | ... U35: =4*U$10 -> 0
B36: =+B35+0.01 -> 3.09 | D36: Terminales para bateria y elementos de fijacion | G36: par | H36: =SUM(J36:U36) -> 37 | J36: =+J$10 -> 10 | K36: =+K$10 -> 4 | L36: =+L$10 -> 3 | M36: =+M$10 -> 3 | N36: =+N$10 -> 5 | O36: =+O$10 -> 2 | P36: =+P$10 -> 0 | Q36: =+Q$10 -> 3 | ... U36: =+U$10 -> 0
B37: =+B36+0.01 -> 3.1 | D37: Conector de puesta a tierra para conductor de cobre de 10mm2 | G37: u | H37: =SUM(J37:U37) -> 37 | J37: =+J$10 -> 10 | K37: =+K$10 -> 4 | L37: =+L$10 -> 3 | M37: =+M$10 -> 3 | N37: =+N$10 -> 5 | O37: =+O$10 -> 2 | P37: =+P$10 -> 0 | Q37: =+Q$10 -> 3 | ... U37: =+U$10 -> 0
