Workbook
Name _10ELECSURME: '[35]Unit-op-cartel'!#REF!
Name _13ELECT: '[35]Unit-op-cartel'!#REF!
Name _16ELECTROL: '[35]Unit-op-cartel'!#REF!
Name _19ELEORIE: '[35]Unit-op-cartel'!#REF!
Name _1EL: '[35]Unit-op-cartel'!#REF!
Name _22ELNO: '[35]Unit-op-cartel'!#REF!
Name _25ELSURE: '[35]Unit-op-cartel'!#REF!
Name _28HIDRAND: '[35]Unit-op-cartel'!#REF!
Name _31S: '[35]Unit-op-cartel'!#REF!
Name _4ELCEN: '[35]Unit-op-cartel'!#REF!
Name _7ELECSURE: '[35]Unit-op-cartel'!#REF!
Name _sec01: '[44]Datos'!$D$26
Name _sec02: '[44]Datos'!$D$27
Name _sec03: '[44]Datos'!$D$28
Name _sec04: '[44]Datos'!$D$29
Name _sec05: '[44]Datos'!$D$30
Name A: '[4]REV3'!$A$32
Name AAA: #REF!
Name ABC: '[51]#¡REF'!#REF!
Name ADV: '[58]#¡REF'!#REF!
Name AEFecha: '[44]Datos'!$D$32
Name AMFecha: '[44]Datos'!$D$33
Name BB: #REF!
Name CD: #REF!
Name DDD: [105]CALCULO!#REF!
Name Departamento: '[92]DATOS DE CAMPO LP'!#REF!
Name DESCRIPCION: #REF!
Name DETAILED: '[112]#¡REF'!#REF!
Name DETALLE: '[112]#¡REF'!#REF!
Name dolar: #REF!
Name Fecha: #REF!
Name fr: '[44]Datos'!$D$9
Name ggd: '[44]Datos'!$D$6
Name ggi: '[44]Datos'!$D$7
Name I: '[127]#¡REF'!#REF!
Name INDICE: #REF!
Name INDICEUNIFICADO: #REF!
Name List_Mon_RS: #REF!
Name List_Res_dger: #REF!
Name Lista_Mon_LP: #REF!
Name localidades: '[141]Aux. Disgregados'!$F$46
Name MNP: '[58]#¡REF'!#REF!
Name name_proy: '[151]RES-GRAL'!$F$4
Name ncon: '[44]Datos'!$D$3
Name ncont: '[44]Datos'!$D$4
Name npro: '[44]Datos'!$D$2
Name p: #REF!
Name PARTIDA: #REF!
Name PBCD: '[44]Datos'!$D$16
Name PBLP: '[44]Datos'!$D$12
Name PBRP: '[44]Datos'!$D$13
Name PBRS: '[44]Datos'!$D$15
Name PBSE: '[44]Datos'!$D$14
Name PCCD: '[44]Datos'!$D$23
Name PCLP: '[44]Datos'!$D$19
Name PCRP: '[44]Datos'!$D$20
Name PCRS: '[44]Datos'!$D$22
Name PCSE: '[44]Datos'!$D$21
Name Q: '[58]1'!#REF!
Name QQQ: '[34]#¡REF'!#REF!

Sheet RESUMEN TOTAL
B2: RESUMEN GENERAL DEL PRESUPUESTO (OBRA Y EXPEDIENTE TÉCNICO)
B4: PROYECTO | C4: : | D4: AMPLIACIÓN DEL SERVICIO DE ENERGÍA ELÉCTRICA EN LA PROVINCIA DEL SANTA Y EN EL DISTRITO DE PAMPAROMAS – DEPARTAMENTO DE ANCASH
B5: DEPARTAMENTO | C5: : | D5: ANCASH
J6: Fecha: 30-May-2022
J7: T.C. (S/ /US$): 3,683
E9: CONTRACTUAL | H9: ESTUDIO DEFINITIVO
B10: ITEM | D10: Descripcion | E10: Total Sin I.G.V. (S/.) | F10: I.G.V. | G10: TOTAL S/. | H10: Total Sin I.G.V. (S/.) | I10: I.G.V. | J10: TOTAL S/.
B12: A | D12: COSTO DE OBRA | E12: =+'RES-GRAL OBRA'!G15 -> #REF! | F12: =+'RES-GRAL OBRA'!G16 -> #REF! | G12: =+SUM(E12:F12) -> #REF! | H12: =+'RES-GRAL OBRA'!H15 -> #REF! | I12: =+'RES-GRAL OBRA'!H16 -> #REF! | J12: =+SUM(H12:I12) -> #REF!
B14: B | D14: COSTO DE EXPEDIENTE TÉCNICO | E14: 200121.88 | F14: 36021.94 | G14: =+SUM(E14:F14) -> 236143.82 | H14: =+E14 -> 200121.88 | I14: =+F14 -> 36021.94 | J14: =+SUM(H14:I14) -> 236143.82
G15: =+SUM(E15:F15) -> 0
D16: TOTAL | E16: =E12+E14 -> #REF! | F16: =F12+F14 -> #REF! | G16: =G12+G14 -> #REF! | H16: =H12+H14 -> #REF! | I16: =I12+I14 -> #REF! | J16: =J12+J14 -> #REF!
G18: % DE INCIDENCIA SOBRE EL CONTRACTUAL | J18: =ROUND((J16/G16),4) -> #REF!
J21: =+J12/G12 -> #REF!

Sheet RES-GRAL OBRA
B2: RESUMEN GENERAL PRESUPUESTO DE OBRA
B4: PROYECTO | E4: : | F4: AMPLIACIÓN DEL SERVICIO DE ENERGÍA ELÉCTRICA EN LA PROVINCIA DEL SANTA Y EN EL DISTRITO DE PAMPAROMAS – DEPARTAMENTO DE ANCASH
B5: DEPARTAMENTO | E5: : | F5: ANCASH | H5: Fecha: 30-May-2022
H6: T.C. (S/ /US$): 3,683
B7: ITEM | C7: DESCRIPCION | G7: PRESUPUESTO CONTRATO | H7: PRESUPUESTO ESTUDIO DEFINITIVO | I7: ADICIONALES | K7: DEDUCTIVOS
I8: MAYORES METRADOS | J8: PARTIDAS NUEVAS | K8: MENOR METRADO | L8: DEDUCTIVO VINCULANTE
B9: A | D9: SUMINISTROS DE MATERIALES | G9: =+'RES-LP'!G12+'RES-RP'!G12+'RES-RS'!G12+'RES- SFV'!G12 -> 1356698.6 | H9: =+'RES-LP'!H12+'RES-RP'!H12+'RES-RS'!H12+'RES- SFV'!H12 -> 1559314.8 | I9: =+'RES-LP'!I12+'RES-RP'!I12+'RES-RS'!I12+'RES- SFV'!I12 -> #REF! | J9: =+'RES-LP'!J12+'RES-RP'!J12+'RES-RS'!J12+'RES- SFV'!J12 -> #REF! | K9: =+'RES-LP'!K12+'RES-RP'!K12+'RES-RS'!K12+'RES- SFV'!K12 -> #REF! | L9: =+'RES-LP'!L12+'RES-RP'!L12+'RES-RS'!L12+'RES- SFV'!L12 -> #REF!
B10: B | D10: MONTAJE ELECTROMECANICO | G10: =+'RES-LP'!G13+'RES-RP'!G13+'RES-RS'!G13+'RES- SFV'!G13 -> #REF! | H10: =+'RES-LP'!H13+'RES-RP'!H13+'RES-RS'!H13+'RES- SFV'!H13 -> #REF! | I10: =+'RES-LP'!I13+'RES-RP'!I13+'RES-RS'!I13+'RES- SFV'!I13 -> #REF! | J10: =+'RES-LP'!J13+'RES-RP'!J13+'RES-RS'!J13+'RES- SFV'!J13 -> #REF! | K10: =+'RES-LP'!K13+'RES-RP'!K13+'RES-RS'!K13+'RES- SFV'!K13 -> #REF! | L10: =+'RES-LP'!L13+'RES-RP'!L13+'RES-RS'!L13+'RES- SFV'!L13 -> #REF!
B11: C | D11: TRANSPORTE DE MATERIALES | G11: =+'RES-LP'!G14+'RES-RP'!G14+'RES-RS'!G14+'RES- SFV'!G14 -> #REF! | H11: =+'RES-LP'!H14+'RES-RP'!H14+'RES-RS'!H14+'RES- SFV'!H14 -> #REF! | I11: =+'RES-LP'!I14+'RES-RP'!I14+'RES-RS'!I14+'RES- SFV'!I14 -> #REF! | J11: =+'RES-LP'!J14+'RES-RP'!J14+'RES-RS'!J14+'RES- SFV'!J14 -> #REF! | K11: =+'RES-LP'!K14+'RES-RP'!K14+'RES-RS'!K14+'RES- SFV'!K14 -> #REF! | L11: =+'RES-LP'!L14+'RES-RP'!L14+'RES-RS'!L14+'RES- SFV'!L14 -> #REF!
B12: D | D12: COSTO DIRECTO ( C.D. ) | G12: =ROUND(SUM(G9:G11),2) -> #REF! | H12: =ROUND(SUM(H9:H11),2) -> #REF! | I12: =ROUND(SUM(I9:I11),2) -> #REF! | J12: =ROUND(SUM(J9:J11),2) -> #REF! | K12: =ROUND(SUM(K9:K11),2) -> #REF! | L12: =ROUND(SUM(L9:L11),2) -> #REF!
B13: E | D13: GASTOS GENERALES (10.12%) | G13: =ROUND(G12*10.12%,2) -> #REF! | H13: =ROUND(H12*10.12%,2) -> #REF! | I13: =ROUND(I12*10.12%,2) -> #REF! | J13: =ROUND(J12*10.12%,2) -> #REF! | K13: =ROUND(K12*10.12%,2) -> #REF! | L13: =ROUND(L12*10.12%,2) -> #REF! | M13: =+H13-G13 -> #REF!
B14: F | D14: UTILIDADES (3%) | G14: =ROUND(G12*3%,2) -> #REF! | H14: =ROUND(H12*3%,2) -> #REF! | I14: =ROUND(I12*3%,2) -> #REF! | J14: =ROUND(J12*3%,2) -> #REF! | K14: =ROUND(K12*3%,2) -> #REF! | L14: =ROUND(L12*3%,2) -> #REF! | M14: =+H14-G14 -> #REF!
D15: SUB-TOTAL SIN I.G.V. (S/.) | G15: =G14+G13+G12 -> #REF! | H15: =H14+H13+H12 -> #REF! | I15: =I14+I13+I12 -> #REF! | J15: =J14+J13+J12 -> #REF! | K15: =K14+K13+K12 -> #REF! | L15: =L14+L13+L12 -> #REF! | M15: =+H15-G15 -> #REF!
D16: IMPUESTO GENERAL A LAS VENTAS IGV (18%) | G16: =ROUND(G15*0.18,2) -> #REF! | H16: =ROUND(H15*0.18,2) -> #REF! | I16: =ROUND(I15*0.18,2) -> #REF! | J16: =ROUND(J15*0.18,2) -> #REF! | K16: =ROUND(K15*0.18,2) -> #REF! | L16: =ROUND(L15*0.18,2) -> #REF!
D17: COSTO TOTAL (Incluye I.G.V.) S/. | G17: =G15+G16 -> #REF! | H17: =H15+H16 -> #REF! | I17: =I15+I16 -> #REF! | J17: =J15+J16 -> #REF! | K17: =K15+K16 -> #REF! | L17: =L15+L16 -> #REF!
D19: INCIDENCIA RESPECTO AL CONTRACTUAL % | H19: =+ROUND(H17/$G$17,4) -> #REF! | I19: =+ROUND(I17/$G$17,4) -> #REF! | J19: =+ROUND(J17/$G$17,4) -> #REF! | K19: =+ROUND(K17/$G$17,4) -> #REF! | L19: =+ROUND(L17/$G$17,4) -> #REF!
H23: =+G17+I17+J17-K17 -> #REF! | I23: =+H17-G17 -> #REF! | J23: =+I17+J17-K17 -> #REF!
H24: =+H17-H23 -> #REF! | J24: =+I23-J23 -> #REF!

Sheet RG
B2: RESUMEN DE PRESUPUESTO CONTRATCUAL REPLANTEO
B4: PROYECTO | E4: : | F4: CREACIÓN INSTALACIÓN DEL SUBSISTEMA DE DISTRIBUCIÓN PRIMARIA 10-22,9 KV Y SUBSISTEMA DE DISTRIBUCIÓN SECUNDARIA 380/220 V E INSTALACIÓN DE ALUMBRADO PÚBLICO LUCAS CUTIVALU DEL DISTRITO DE MIGUEL CHECA - PROVINCIA DE SULLANA - DEPARTAMENTO DE PIURA
B5: DEPARTAMENTOS | E5: : | F5: PIURA
B6: ITEM | C6: DESCRIPCION | G6: LINEAS PRIMARIAS | I6: REDES PRIMARIAS | K6: REDES SECUNDARIAS | M6: TOTAL
G7: PRESUPUESTO CONTRATO | H7: PRESUPUESTO REPLANTEO | I7: PRESUPUESTO CONTRATO | J7: PRESUPUESTO REPLANTEO | K7: PRESUPUESTO CONTRATO | L7: PRESUPUESTO REPLANTEO | M7: PRESUPUESTO CONTRATO | N7: PRESUPUESTO REPLANTEO
B9: A | D9: SUMINISTROS DE MATERIALES | G9: =+#REF! -> #REF! | H9: =+#REF! -> #REF! | I9: =+#REF! -> #REF! | J9: =+#REF! -> #REF! | K9: =+'RES-RS'!G12 -> 301377.1 | L9: =+'RES-RS'!H12 -> 420410.61 | M9: =+G9+I9+K9 -> #REF! | N9: =+H9+J9+L9 -> #REF!
B10: B | D10: MONTAJE ELECTROMECANICO | G10: =+#REF! -> #REF! | H10: =+#REF! -> #REF! | I10: =+#REF! -> #REF! | J10: =+#REF! -> #REF! | K10: =+'RES-RS'!G13 -> #REF! | L10: =+'RES-RS'!H13 -> #REF! | M10: =+G10+I10+K10 -> #REF! | N10: =+H10+J10+L10 -> #REF!
B11: C | D11: TRANSPORTE DE MATERIALES | G11: =+#REF! -> #REF! | H11: =+#REF! -> #REF! | I11: =+#REF! -> #REF! | J11: =+#REF! -> #REF! | K11: =+'RES-RS'!G14 -> #REF! | L11: =+'RES-RS'!H14 -> #REF! | M11: =+G11+I11+K11 -> #REF! | N11: =+H11+J11+L11 -> #REF!
B13: D | D13: COSTO DIRECTO ( C.D. ) | G13: =SUM(G9:G12) -> #REF! | H13: =SUM(H9:H12) -> #REF! | I13: =SUM(I9:I12) -> #REF! | J13: =SUM(J9:J12) -> #REF! | K13: =SUM(K9:K12) -> #REF! | L13: =SUM(L9:L12) -> #REF! | M13: =SUM(M9:M12) -> #REF! | N13: =SUM(N9:N12) -> #REF!
B15: E | D15: GASTOS GENERALES (30.52%) | G15: =ROUND(G13*30.52%,2) -> #REF! | H15: =ROUND(H13*30.52%,2) -> #REF! | I15: =ROUND(I13*30.52%,2) -> #REF! | J15: =ROUND(J13*30.52%,2) -> #REF! | K15: =ROUND(K13*30.52%,2) -> #REF! | L15: =ROUND(L13*30.52%,2) -> #REF! | M15: =ROUND(M13*30.52%,2) -> #REF! | N15: =ROUND(N13*30.52%,2) -> #REF!
B16: F | D16: UTILIDADES (4.01%) | G16: =ROUND(G13*4.01%,2) -> #REF! | H16: =ROUND(H13*4.01%,2) -> #REF! | I16: =ROUND(I13*4.01%,2) -> #REF! | J16: =ROUND(J13*4.01%,2) -> #REF! | K16: =ROUND(K13*4.01%,2) -> #REF! | L16: =ROUND(L13*4.01%,2) -> #REF! | M16: =ROUND(M13*4.01%,2) -> #REF! | N16: =ROUND(N13*4.01%,2) -> #REF!
D19: SUB-TOTAL SIN I.G.V. (S/.) | G19: =G16+G15+G13 -> #REF! | H19: =H16+H15+H13 -> #REF! | I19: =I16+I15+I13 -> #REF! | J19: =J16+J15+J13 -> #REF! | K19: =K16+K15+K13 -> #REF! | L19: =L16+L15+L13 -> #REF! | M19: =M16+M15+M13 -> #REF! | N19: =N16+N15+N13 -> #REF!
D21: IMPUESTO GENERAL A LAS VENTAS IGV (18%) | G21: =ROUND(G19*0.18,2) -> #REF! | H21: =ROUND(H19*0.18,2) -> #REF! | I21: =ROUND(I19*0.18,2) -> #REF! | J21: =ROUND(J19*0.18,2) -> #REF! | K21: =ROUND(K19*0.18,2) -> #REF! | L21: =ROUND(L19*0.18,2) -> #REF! | M21: =ROUND(M19*0.18,2) -> #REF! | N21: =ROUND(N19*0.18,2) -> #REF!
D22: COSTO TOTAL (Incluye I.G.V.) S/. | G22: =G19+G21 -> #REF! | H22: =H19+H21 -> #REF! | I22: =I19+I21 -> #REF! | J22: =J19+J21 -> #REF! | K22: =K19+K21 -> #REF! | L22: =L19+L21 -> #REF! | M22: =M19+M21 -> #REF! | N22: =N19+N21 -> #REF!
D23: INCIDENCIA RESPECTO AL CONTRACTUAL % | H23: =+H22/$G$22 -> #REF! | J23: =+J22/$I$22 -> #REF! | L23: =+L22/$L$22 -> #REF! | N23: =+N22/$M$22 -> #REF!
D24: INCIDENCIA DEL ADICIONAL % | G24: =+(I22+J22-L22)/G22 -> #REF!
D25: INCIDENCIA DEL MAYOR METRADO % | G25: =+K22/G22 -> #REF!
D26: INCIDENCIA DEL ADICONAL + MAYOR METRADO % | G26: =+(I22+J22+K22-L22)/G22 -> #REF!
H29: =+H22-K22+M22 -> #REF! | M29: 1495463.1 | N29: 1557304.6
H30: =+H29-G22 -> #REF!

Sheet GG Contr.
B1: CREACIÓN INSTALACIÓN DEL SUBSISTEMA DE DISTRIBUCIÓN PRIMARIA 10-22,9 KV Y SUBSISTEMA DE DISTRIBUCIÓN SECUNDARIA 380/220 V E INSTALACIÓN DE ALUMBRADO PÚBLICO LUCAS CUTIVALU DEL DISTRITO DE MIGUEL CHECA - PROVINCIA DE SULLANA - DEPARTAMENTO DE PIURA
B3: CALCULO DE LOS GASTOS GENERALES DIRECTOS E INDIRECTOS
C5: Sección : | D5: LINEAS PRIMARIAS, REDES PRIMARIAS Y REDES SECUNDARIAS
C6: Departamento : | D6: PIURA | K6: =I190/E69 -> 0.30530483
C7: Plazo de Obra : | D7: 5 | E7: meses
B9: 1.0 | C9: GASTOS GENERALES VARIABLES-GG DIRECTOS | I9: 942051.3
B11: 1.1 | C11: Personal Profesional Principal
C12: Descripción | D12: Unidad | E12: Cant. | F12: Particip. | G12: Tiempo | H12: Sueldo | I12: Parcial
F13: % | G13: (meses) | H13: (S/.) | I13: (S/.)
C14: Gerente de Obra | D14: Und. | E14: 0 | F14: 0.5 | G14: 2.5 | H14: 10000 | I14: 0
C15: Ingeniero Residente de la Obra | D15: Und. | E15: 1 | F15: 1 | G15: 5 | H15: 6000 | I15: =ROUND(E15*F15*G15*H15,2) -> 30000
C16: Ingeniero Asistente de Obra | D16: Und. | E16: 0 | F16: 0.82 | G16: 4.1 | H16: 6500 | I16: 0
C17: Gestor de Servidumbre | D17: Und. | E17: 0 | F17: 0.5 | G17: 2.5 | H17: 4500 | I17: 0
C18: Ingeniero de Seguridad e Higiene Ocupacional | D18: Und. | E18: 1 | F18: 1 | G18: 5 | H18: 4500 | I18: =ROUND(E18*F18*G18*H18,2) -> 22500
C19: Ingeniero Asistente de Residente de Obra | D19: Und. | E19: 1 | F19: 1 | G19: 5 | H19: 4000 | I19: =ROUND(E19*F19*G19*H19,2) -> 20000
C21: PARCIAL 1,1 | I21: =SUM(I14:I20) -> 72500
C22: Nota: El sueldo considerado por cada profesional incluye impuestos y leyes sociales
B24: 1.2 | C24: Personal de Auxiliar y Apoyo
C25: Descripción | D25: Und. | E25: Cant. | F25: Particip. | G25: Tiempo | H25: Sueldo | I25: Parcial
F26: % | G26: (meses) | H26: (S/.) | I26: (S/.)
C27: Administrador | D27: Und. | E27: 1 | F27: 1 | G27: 5 | H27: 3500 | I27: =ROUND(E27*F27*G27*H27,2) -> 17500
C28: Asistente de administrador | D28: Und. | E28: 0 | F28: 0.8 | G28: 4 | H28: 1500 | I28: =ROUND(E28*F28*G28*H28,2) -> 0
C29: Dibujante en Autocad y otros programas | D29: Und. | E29: 1 | F29: 1 | G29: 5 | H29: 1500 | I29: =ROUND(E29*F29*G29*H29,2) -> 7500
C30: Almacenero | D30: Und. | E30: 1 | F30: 1 | G30: 5 | H30: 1800 | I30: =ROUND(E30*F30*G30*H30,2) -> 9000
C31: Asistente de almacen | D31: Und. | E31: 0 | F31: 1 | G31: 5 | H31: 1050 | I31: =ROUND(E31*F31*G31*H31,2) -> 0
C32: Técnico mecánico | D32: Und. | E32: 0 | F32: 1 | G32: 5 | H32: 1200 | I32: =ROUND(E32*F32*G32*H32,2) -> 0
C33: Chofer | D33: Und. | E33: 1 | F33: 1 | G33: 5 | H33: 1500 | I33: =ROUND(E33*F33*G33*H33,2) -> 7500
C34: Seguridad en obra (Guardian) | D34: Und. | E34: 1 | F34: 1 | G34: 5 | H34: 1047 | I34: =ROUND(E34*F34*G34*H34,2) -> 5235
C36: PARCIAL 1,2 | I36: =SUM(I27:I35) -> 46735 | K36: 46735
C37: Nota: El sueldo considerado por trabajador incluye impuestos y leyes sociales
B39: 1.3 | C39: Hospedajes, Oficina, Campamentos, alimentación y movilidad del personal principal, auxiliar y apoyo
C40: Descripción | D40: Und. | E40: Cant. | F40: Particip. | G40: Tiempo | H40: Gasto/ Und. | I40: Parcial
F41: % | G41: (meses) | H41: (S/.) | I41: (S/.)
C42: Hospedajes | D42: Glb/mes | E42: 1 | F42: 1 | G42: 5 | H42: 1500 | I42: =ROUND(E42*F42*G42*H42,2) -> 7500
C43: Alquiler de Oficina - Almacen en Obra (Incluye agua y luz) | D43: Glb/mes | E43: 1 | F43: 1 | G43: 5 | H43: 849.88 | I43: =ROUND(E43*F43*G43*H43,2) -> 4249.4
C44: Alquiler de casa almacén (incluye agua y luz) | D44: Glb/mes | E44: 0 | F44: 1 | G44: 5 | H44: 450 | I44: =ROUND(E44*F44*G44*H44,2) -> 0
C45: Comunicaciones: telefono, fax, internet, radio, etc. | D45: Glb/mes | E45: 1 | F45: 1 | G45: 5 | H45: 550 | I45: =ROUND(E45*F45*G45*H45,2) -> 2750
C46: Alimentación | D46: Glb/mes | E46: 1 | F46: 1 | G46: 5 | H46: 2000 | I46: =ROUND(E46*F46*G46*H46,2) -> 10000
C47: Pasajes | D47: Glb/mes | E47: 1 | F47: 1 | G47: 5 | H47: 650 | I47: =ROUND(E47*F47*G47*H47,2) -> 3250
C49: PARCIAL 1,3 | I49: =SUM(I42:I48) -> 27749.4
B51: 1.4 | C51: Mobiliario, equipo, material de oficina y otros
C52: Descripción | D52: Und. | E52: Cant. | F52: Desgaste | G52: Tiempo | H52: Gasto/ Und.xmes | I52: Parcial
F53: % | G53: (meses) | H53: (S/.) | I53: (S/.)
C54: Mobiliario de oficina | D54: Glb/mes | E54: 3 | F54: 0.020833333 | G54: 5 | H54: 2500 | I54: =ROUND(E54*F54*G54*H54,2) -> 781.25
C55: Computadora | D55: Glb/mes | E55: 3 | F55: 0.020833333 | G55: 5 | H55: 3500 | I55: =ROUND(E55*F55*G55*H55,2) -> 1093.75
C56: Impresora | D56: Glb/mes | E56: 2 | F56: 0.020833333 | G56: 5 | H56: 1000 | I56: =ROUND(E56*F56*G56*H56,2) -> 208.33
C57: Útiles de Oficina | D57: Glb/mes | E57: 1 | F57: 0.020833333 | G57: 5 | H57: 1200 | I57: =ROUND(E57*F57*G57*H57,2) -> 125
C58: Camioneta pick up | D58: Glb/mes | E58: 1 | F58: 0.0631315 | G58: 5 | H58: 118800 | I58: =ROUND(E58*F58*G58*H58,2) -> 37500.11
C59: Combustible | D59: Glb/mes | E59: 1 | F59: 1 | G59: 5 | H59: 3000 | I59: =ROUND(E59*F59*G59*H59,2) -> 15000
C60: Mantenimiento | D60: Glb/mes | E60: 1 | F60: 0.7 | G60: 5 | H60: 1500 | I60: =ROUND(E60*F60*G60*H60,2) -> 5250
C62: PARCIAL 1,4 | I62: =SUM(I54:I61) -> 59958.44 | K62: 59958.44
C63: Nota: El desgaste de los equipos ha sido calculado considerando una depreciación líneal en 36 meses de vida útil.
C64: El desgaste de las camionetas ha sido calculado considerando una depreciación líneal en 120 meses de vida útil.
B66: 1.5 | C66: Gastos financieros y otros gastos
C67: Descripción | D67: Und. | E67: Costo Directo | F67: % de CD | G67: Costo/mes | H67: Tiempo | I67: Parcial
E68: Obra (s/.) | F68: al mes | G68: S/. | H68: (meses) | I68: S/.
C69: Cartas fianza | D69: mes | E69: 942051.3 | F69: 0.0005 | G69: 495.26 | H69: 7 | I69: =ROUND(G69*H69,2) -> 3466.82 | K69: =+G69*H69 -> 3466.82
C70: Seguros | D70: Gbl | E70: 942051.3 | F70: 0.0002 | G70: 198.1 | H70: 6 | I70: =ROUND(G70*H70,2) -> 1188.6
C72: PARCIAL 1,6 | I72: =SUM(I69:I71) -> 4655.42 | K72: 4655.42
C74: PARCIAL GASTOS GENERALES VARIABLES (1) | I74: =+I72+I62+I49+I36+I21 -> 211598.26 | K74: 256598.26
B77: 1.6 | C77: Plan para la vigilancia, prevención y control de COVID-19 - ( R.M. N° 448-2020-MINSA)
C78: Descripción | D78: Und. | E78: Cant. | F78: Particip. | G78: Tiempo | H78: Costo/mes | I78: Parcial
F79: % | G79: (meses) | H79: (S/.) | I79: (S/.)
C80: A.1 Personal Profesional Principal
C81: - Profesional Técnico de la Salud | D81: Global | E81: 1 | H81: 3000 | I81: =ROUND(E81*H81,2) -> 3000
C82: A.2 Personal Auxiliar y de Apoyo
C83: - Operario de Limpieza y Desinfección (COVID-19) | D83: Global | E83: 1 | H83: 1800 | I83: =ROUND(E83*H83,2) -> 1800
C84: SUB-TOTAL A | I84: =SUM(I80:I83) -> 4800 | K84: 8550
C86: Descripción | D86: Und. | E86: Cant. | F86: Particip. | G86: Tiempo | H86: Gasto/ Und. | I86: Parcial
F87: % | G87: (meses) | H87: (S/.) | I87: (S/.)
C88: B.1 Plan para la Vigilancia, Prevención, y Control de la COVID-19 en el Trabajo
C89: - Elaboración, Aprobación, y Registro en el MINSA | D89: Global | E89: 1 | H89: 1200 | I89: =ROUND(E89*H89,2) -> 1200
C90: B.2 Evaluación Médico Ocupacionales
C91: - Termómetro Digital Infrarrojo (4) | D91: Und. | E91: 1 | F91: 0.083333333 | G91: 5 | H91: 590 | I91: =ROUND(E91*F91*G91*H91,2) -> 245.83
C92: - Pruebas de descarte de la COVID-19 | D92: Global | E92: 1 | H92: 4993.2 | I92: =ROUND(E92*H92,2) -> 4993.2
C93: B.3 Equipos de Proteccion Personal (EPPs)
C94: - Mascarilla Quirúrgica descartable | D94: Und. | E94: 60 | F94: 1 | G94: 5 | H94: 0.8 | I94: =ROUND(E94*F94*G94*H94,2) -> 240
C95: - Mascarilla Facial Textil comunitaria | D95: Global | E95: 1 | H95: 558.7 | I95: =ROUND(E95*H95,2) -> 558.7
C96: - Careta Facial | D96: Global | E96: 1 | H96: 2567 | I96: =ROUND(E96*H96,2) -> 2567
C97: - Guante Quirúrgico descartable | D97: Und. | E97: 60 | F97: 1 | G97: 5 | H97: 0.75 | I97: =ROUND(E97*G97*H97,2) -> 225 | K97: =+E97*G97*H97 -> 225
C98: - Gafas de Protección | D98: Und. | E98: 1 | F98: 1 | G98: 5 | H98: 12 | I98: =ROUND(E98*G98*H98,2) -> 60
C99: B.4 Lavado y Desinfección de Manos y de Planta de Calzado
C100: - Jabón líquido, Papel Toalla, Alcohol Gel Antibacterial, Solución de Alcohol al 96%, Lejia, Bandeja de Limpieza | D100: Glb/mes | E100: 1 | F100: 1 | G100: 5 | H100: 726.85 | I100: =ROUND(G100*H100,2) -> 3634.25 | K100: 3634.25
C101: B.5 Lavado, Desinfección y Fumigación del Centro Laboral (ambientes, mobiliario, herramientas, equipos, unidades de transporte en obra, etc
C102: - Lejia, Detergente | D102: Glb/mes | E102: 1 | F102: 1 | G102: 5 | H102: 564.2 | I102: =ROUND(G102*H102,2) -> 2821 | K102: 2821
C103: B.6 Actividades Varias
C104: - Charlas de Capacitación y de Sensibilizacion (Medidas Preventivas, Uso de EPPs, lavado correcto, información sobre el COVID-19) (3) | D104: Glb/mes | E104: 1 | F104: 1 | G104: 5 | H104: 250 | I104: =ROUND(G104*H104,2) -> 1250 | K104: 1250
C105: - Señaléticas de Prevención: Carteles de Prevencion, Infografias (Uso de Mascarillas, Distanciamiento, Lavado de manos, Uso obligatorio de EPPs). | D105: Global | E105: 1 | H105: 350 | I105: =ROUND(E105*H105,2) -> 350 | K105: 350
C106: - Cilindros para acopio de material deshechable | D106: Und. | E106: 2 | F106: 1 | G106: 1 | H106: 350 | I106: =ROUND(E106*F106*G106*H106,2) -> 700 | K106: 700
C107: B.7 Hospedaje, oficina, alimentación y movilidad del personal principal, auxiliar y de apoyo
C108: - Hospedaje. | D108: Glb/mes | E108: 1 | F108: 1 | G108: 5 | H108: 200 | I108: =ROUND(E108*F108*G108*H108,2) -> 1000 | K108: 1000
C109: - Alquiler de Oficina en Obra para Evaluación Médico Ocupacional (Incluye agua y luz). | D109: Glb/mes | E109: 1 | F109: 1 | G109: 5 | H109: 250 | I109: =ROUND(E109*F109*G109*H109,2) -> 1250 | K109: 1250
C110: - Comunicaciones: telefono, fax, internet, radio, etc. | D110: Glb/mes | E110: 1 | F110: 1 | G110: 5 | H110: 110 | I110: =ROUND(E110*F110*G110*H110,2) -> 550 | K110: 550
C111: - Alimentación | D111: Glb/mes | E111: 1 | F111: 1 | G111: 5 | H111: 610 | I111: =ROUND(E111*F111*G111*H111,2) -> 3050 | K111: 3050
C112: - Pasajes | D112: Glb/mes | E112: 1 | F112: 1 | G112: 5 | H112: 125 | I112: =ROUND(E112*F112*G112*H112,2) -> 625 | K112: 625
C113: B.8 Transporte de Personal en Obra
C114: - Traslado desde campamento a punto de instalación (incluye unidad móvil tipo Minivan con capacidad mínima de 11 pasajeros, chofer, combustible, mantenimiento) | D114: Global | E114: 1 | H114: 2479.5 | I114: =ROUND(E114*H114,2) -> 2479.5
C115: B.9 Mobiliario, equipo, material de oficina y otros (4)
C116: - Equipamiento Médico para Evaluación Médico Ocupacional (camilla, estetoscopio, mobiliario médico, etc) | D116: Glb/mes | E116: 1 | F116: 0.05 | G116: 5 | H116: 1800 | I116: =ROUND(E116*F116*G116*H116,2) -> 450
C117: - Mobiliario de oficina | D117: Glb/mes | E117: 1 | F117: 0.05 | G117: 5 | H117: 1200 | I117: =ROUND(E117*F117*G117*H117,2) -> 300
...

Sheet RES-LP
B2: RESUMEN PRESUPUESTO DE OBRA
B4: AMPLIACIÓN DEL SERVICIO DE ENERGÍA ELÉCTRICA EN LA PROVINCIA DEL SANTA Y EN EL DISTRITO DE PAMPAROMAS – DEPARTAMENTO DE ANCASH
B6: UBICACIÓN | C6: : | D6: ANCASH
B7: SECCIÓN I | C7: : | D7: LINEAS PRIMARIAS | H7: Fecha: 30-May-2022
H8: T.C. (S/ /US$): 3,683
B9: ITEM | C9: DESCRIPCION | G9: PRESUPUESTO CONTRATO | H9: PRESUPUESTO ESTUDIO DEFINIVO | I9: ADICIONALES | K9: DEDUCTIVOS
I10: MAYORES METRADOS | J10: PARTIDAS NUEVAS | K10: MENOR METRADO | L10: DEDUCTIVO VINCULANTE
B12: A | D12: SUMINISTRO DE MATERIALES | G12: =+LP!J154 -> 628325.26 | H12: =+LP!L154 -> 683730.19 | I12: =+LP!#REF! -> #REF! | J12: =+LP!#REF! -> #REF! | K12: =+LP!#REF! -> #REF! | L12: =+LP!#REF! -> #REF!
B13: B | D13: MONTAJE ELECTROMECANICO | G13: =+LP!#REF! -> #REF! | H13: =+LP!#REF! -> #REF! | I13: =+LP!#REF! -> #REF! | J13: =+LP!#REF! -> #REF! | K13: =+LP!#REF! -> #REF! | L13: =+LP!#REF! -> #REF!
B14: C | D14: TRANSPORTE DE MATERIALES | G14: =+LP!#REF! -> #REF! | H14: =+LP!#REF! -> #REF! | I14: =+LP!#REF! -> #REF! | J14: =+LP!#REF! -> #REF! | K14: =+LP!#REF! -> #REF! | L14: =+LP!#REF! -> #REF!
B15: D | D15: TOTAL COSTO DIRECTO | G15: =+SUM(G12:G14) -> #REF! | H15: =+SUM(H12:H14) -> #REF! | I15: =+SUM(I12:I14) -> #REF! | J15: =+SUM(J12:J14) -> #REF! | K15: =+SUM(K12:K14) -> #REF! | L15: =+SUM(L12:L14) -> #REF!
B16: E | D16: GASTOS GENERALES (10.12%) | G16: =ROUND(G15*10.12%,2) -> #REF! | H16: =ROUND(H15*10.12%,2) -> #REF! | I16: =ROUND(I15*10.12%,2) -> #REF! | J16: =ROUND(J15*10.12%,2) -> #REF! | K16: =ROUND(K15*10.12%,2) -> #REF! | L16: =ROUND(L15*10.12%,2) -> #REF!
B17: F | D17: UTILIDADES (3%) | G17: =ROUND(G15*3%,2) -> #REF! | H17: =ROUND(H15*3%,2) -> #REF! | I17: =ROUND(I15*3%,2) -> #REF! | J17: =ROUND(J15*3%,2) -> #REF! | K17: =ROUND(K15*3%,2) -> #REF! | L17: =ROUND(L15*3%,2) -> #REF!
B18: G | D18: COSTO TOTAL S/. (No incluye I.G.V.) | G18: =G17+G16+G15 -> #REF! | H18: =H17+H16+H15 -> #REF! | I18: =I17+I16+I15 -> #REF! | J18: =J17+J16+J15 -> #REF! | K18: =K17+K16+K15 -> #REF! | L18: =L17+L16+L15 -> #REF! | M18: =+H18-G18 -> #REF!
D20: INCIDENCIA % | G20: =+G18/G18 -> #REF! | H20: =+H18/$G$18 -> #REF! | I20: =+I18/$G$18 -> #REF! | J20: =+J18/$G$18 -> #REF! | K20: =+K18/$G$18 -> #REF! | L20: =+L18/$G$18 -> #REF!
H22: =+H18-I18+K18-J18 -> #REF! | K22: =+G12-H12+I12+J12-K12 -> #REF!
H23: =+G18-H22 -> #REF! | K23: =+G13-H13+I13+J13-K13 -> #REF!
K24: =+G14-H14+I14+J14-K14 -> #REF!
K25: =+G15-H15+I15+J15-K15 -> #REF!

Sheet LP
J1: VARI | K1: VARI
A6: COMPARATIVO DE PRECIOS
A8: OBRA | D8: : | E8: AMPLIACIÓN DEL SERVICIO DE ENERGÍA ELÉCTRICA EN LA PROVINCIA DEL SANTA Y EN EL DISTRITO DE PAMPAROMAS – DEPARTAMENTO DE ANCASH
A9: DEPARTAMENTO | D9: : | E9: ANCASH
A10: SECCIÓN I | D10: : | E10: LINEAS PRIMARIAS
A12: ITEM | B12: DESCRIPCIÓN DE PARTIDAS | F12: UNID. | G12: Precio de Contrato | H12: Precio Pactado | I12: CONTRACTUAL | K12: ESTUDIO DEFINITIVO | M12: PRECIO DE VENTA | N12: MENDOZA | Q12: DIFERENCIA DE PRECIOS | T12: PRECIO DE VENTA | U12: GELCO/Group Electric JYM Sac PU | X12: PRECIO DE VENTA | Y12: EL DETALLE | AB12: PRECIO DE VENTA | AC12: CIE
I13: Metrado | J13: TOTAL | K13: Metrado | L13: TOTAL | N13: Metrado | O13: TOTAL | P13: % | U13: Metrado | V13: TOTAL | W13: % | Y13: Metrado | Z13: TOTAL | AA13: % | AC13: Metrado | AD13: TOTAL | AE13: %
G15: Unitario | H15: Unitario | I15: Cantidad | J15: S/. | K15: Cantidad | L15: S/. | M15: S/. | N15: Cantidad | O15: S/. | Q15: S/. | R15: TDT | S15: PROYECTO | T15: S/. | U15: Cantidad | V15: S/. | X15: S/. | Y15: Cantidad | Z15: S/. | AB15: S/. | AC15: Cantidad | AD15: S/.
A16: A | C16: SUMINISTRO DE MATERIALES
A17: 1 | B17: 3 | C17: CRUCETAS DE MADERA DE PROCEDENCIA NACIONAL
A18: 1.01 | B18: =+B17+1 -> 4 | C18: Cruceta de madera tratada de 90 mm x 115 mm x 1,20 m | F18: u | G18: 105 | I18: 11 | J18: =+ROUND($G18*I18,2) -> 1155 | K18: =+[191]Metrados!E19 -> 7 | L18: =+ROUND($G18*K18,2) -> 735 | M18: 0 | N18: =K18 -> 7 | O18: =+ROUND($M18*N18,2) -> 0 | P18: =+M18/($G18+$H18) -> 0 | Q18: =+G18-M18 -> 105 | T18: 0 | U18: =$K18 -> 7 | V18: =+ROUND($T18*U18,2) -> 0 | W18: =+T18/($G18+$H18) -> 0 | X18: 0 | Y18: =$K18 -> 7 | Z18: =+ROUND($X18*Y18,2) -> 0 | AA18: =+X18/($G18+$H18) -> 0 | AB18: 0 | AC18: =$K18 -> 7 | AD18: =+ROUND($AB18*AC18,2) -> 0 | AE18: =+AB18/($G18+$H18) -> 0 | AF18: =+M18+O18+X18 -> 0
A19: 1.02 | B19: =+B18+1 -> 5 | C19: Cruceta de madera tratada de 90 mm x 115 mm x 2,00 m | F19: u | G19: 178 | I19: 2 | J19: =+ROUND($G19*I19,2) -> 356 | K19: =+'[191]Metrados'!E20 -> 1 | L19: =+ROUND($G19*K19,2) -> 178 | M19: 0 | N19: =K19 -> 1 | O19: =+ROUND($M19*N19,2) -> 0 | P19: =+M19/($G19+$H19) -> 0 | Q19: =+G19-M19 -> 178 | T19: 0 | U19: =$K19 -> 1 | V19: =+ROUND($T19*U19,2) -> 0 | W19: =+T19/($G19+$H19) -> 0 | X19: 0 | Y19: =$K19 -> 1 | Z19: =+ROUND($X19*Y19,2) -> 0 | AA19: =+X19/($G19+$H19) -> 0 | AB19: 0 | AC19: =$K19 -> 1 | AD19: =+ROUND($AB19*AC19,2) -> 0 | AE19: =+AB19/($G19+$H19) -> 0 | AF19: =+M19+O19+X19 -> 0
A20: 1.03 | B20: =+B19+1 -> 6 | C20: Cruceta de madera tratada de 90 mm x 115 mm x 2,40 m | F20: u | G20: 205 | I20: 1 | J20: =+ROUND($G20*I20,2) -> 205 | K20: =+'[191]Metrados'!E21 -> 13 | L20: =+ROUND($G20*K20,2) -> 2665 | M20: 0 | N20: =K20 -> 13 | O20: =+ROUND($M20*N20,2) -> 0 | P20: =+M20/($G20+$H20) -> 0 | Q20: =+G20-M20 -> 205 | T20: 0 | U20: =$K20 -> 13 | V20: =+ROUND($T20*U20,2) -> 0 | W20: =+T20/($G20+$H20) -> 0 | X20: 0 | Y20: =$K20 -> 13 | Z20: =+ROUND($X20*Y20,2) -> 0 | AA20: =+X20/($G20+$H20) -> 0 | AB20: 0 | AC20: =$K20 -> 13 | AD20: =+ROUND($AB20*AC20,2) -> 0 | AE20: =+AB20/($G20+$H20) -> 0 | AF20: =+M20+O20+X20 -> 0
A21: 1.04 | B21: =+B20+1 -> 7 | C21: Listón de madera tratada 50 x 19 mm sección, 2,7 m longitud (incluye clavos de fijación) | F21: u | G21: 27.35 | I21: 9 | J21: =+ROUND($G21*I21,2) -> 246.15 | K21: =+'[191]Metrados'!E22 -> 0 | L21: =+ROUND($G21*K21,2) -> 0 | M21: 0 | N21: =K21 -> 0 | O21: =+ROUND($M21*N21,2) -> 0 | P21: =+M21/($G21+$H21) -> 0 | Q21: =+G21-M21 -> 27.35 | T21: 0 | U21: =$K21 -> 0 | V21: =+ROUND($T21*U21,2) -> 0 | W21: =+T21/($G21+$H21) -> 0 | X21: 0 | Y21: =$K21 -> 0 | Z21: =+ROUND($X21*Y21,2) -> 0 | AA21: =+X21/($G21+$H21) -> 0 | AB21: 0 | AC21: =$K21 -> 0 | AD21: =+ROUND($AB21*AC21,2) -> 0 | AE21: =+AB21/($G21+$H21) -> 0 | AF21: =+M21+O21+X21 -> 0
B22: =B21+1 -> 8 | E22: =+"SUB-TOTAL "&A17&": " -> SUB-TOTAL 1: | J22: =+SUM(J18:J21) -> 1962.15 | L22: =+SUM(L18:L21) -> 3578 | M22: 0 | N22: =K22 -> 0 | O22: =+SUM(O18:O21) -> 0 | Q22: =+G22-M22 -> 0 | T22: 0 | U22: =$K22 -> 0 | V22: =+SUM(V18:V21) -> 0 | X22: 0 | Y22: =$K22 -> 0 | Z22: =+SUM(Z18:Z21) -> 0 | AB22: 0 | AC22: =$K22 -> 0 | AD22: =+SUM(AD18:AD21) -> 0 | AF22: =+M22+O22+X22 -> 0
A23: 2 | B23: =+B22+1 -> 9 | C23: POSTES DE CONCRETO ARMADO CENTRIFUGADO | M23: 0 | N23: =K23 -> 0 | Q23: =+G23-M23 -> 0 | T23: 0 | U23: =$K23 -> 0 | X23: 0 | Y23: =$K23 -> 0 | AB23: 0 | AC23: =$K23 -> 0 | AF23: =+M23+O23+X23 -> 0
A24: 2.01 | B24: =+B23+1 -> 10 | C24: Poste de C.A.C. de 12 m/200 daN (Incluye perilla) | F24: u | G24: 837.45 | I24: 15 | J24: =+ROUND($G24*I24,2) -> 12561.75 | K24: =+'[191]Metrados'!E25 -> 3 | L24: =+ROUND($G24*K24,2) -> 2512.35 | M24: 0 | N24: =K24 -> 3 | O24: =+ROUND($M24*N24,2) -> 0 | P24: =+M24/($G24+$H24) -> 0 | Q24: =+G24-M24 -> 837.45 | T24: 0 | U24: =$K24 -> 3 | V24: =+ROUND($T24*U24,2) -> 0 | W24: =+T24/($G24+$H24) -> 0 | X24: 0 | Y24: =$K24 -> 3 | Z24: =+ROUND($X24*Y24,2) -> 0 | AA24: =+X24/($G24+$H24) -> 0 | AB24: 0 | AC24: =$K24 -> 3 | AD24: =+ROUND($AB24*AC24,2) -> 0 | AE24: =+AB24/($G24+$H24) -> 0 | AF24: =+M24+O24+X24 -> 0
A25: 2.02 | B25: =+B24+1 -> 11 | C25: Poste de C.A.C. de 12 m/300 daN (Incluye perilla) | F25: u | G25: 923.47 | I25: 6 | J25: =+ROUND($G25*I25,2) -> 5540.82 | K25: =+'[191]Metrados'!E26 -> 6 | L25: =+ROUND($G25*K25,2) -> 5540.82 | M25: 0 | N25: =K25 -> 6 | O25: =+ROUND($M25*N25,2) -> 0 | P25: =+M25/($G25+$H25) -> 0 | Q25: =+G25-M25 -> 923.47 | T25: 0 | U25: =$K25 -> 6 | V25: =+ROUND($T25*U25,2) -> 0 | W25: =+T25/($G25+$H25) -> 0 | X25: 0 | Y25: =$K25 -> 6 | Z25: =+ROUND($X25*Y25,2) -> 0 | AA25: =+X25/($G25+$H25) -> 0 | AB25: 0 | AC25: =$K25 -> 6 | AD25: =+ROUND($AB25*AC25,2) -> 0 | AE25: =+AB25/($G25+$H25) -> 0 | AF25: =+M25+O25+X25 -> 0
A26: 2.03 | B26: =+B25+1 -> 12 | C26: Poste de C.A.C. de 13 m/300 daN (Incluye perilla) | F26: u | G26: 1085.14 | I26: 118 | J26: =+ROUND($G26*I26,2) -> 128046.52 | K26: =+'[191]Metrados'!E27 -> 96 | L26: =+ROUND($G26*K26,2) -> 104173.44 | M26: 0 | N26: =K26 -> 96 | O26: =+ROUND($M26*N26,2) -> 0 | P26: =+M26/($G26+$H26) -> 0 | Q26: =+G26-M26 -> 1085.14 | T26: 0 | U26: =$K26 -> 96 | V26: =+ROUND($T26*U26,2) -> 0 | W26: =+T26/($G26+$H26) -> 0 | X26: 0 | Y26: =$K26 -> 96 | Z26: =+ROUND($X26*Y26,2) -> 0 | AA26: =+X26/($G26+$H26) -> 0 | AB26: 0 | AC26: =$K26 -> 96 | AD26: =+ROUND($AB26*AC26,2) -> 0 | AE26: =+AB26/($G26+$H26) -> 0 | AF26: =+M26+O26+X26 -> 0
A27: 2.04 | B27: =+B26+1 -> 13 | C27: Poste de C.A.C. de 13 m/400 daN (Incluye perilla) | F27: u | G27: 1207.94 | I27: 32 | J27: =+ROUND($G27*I27,2) -> 38654.08 | K27: =+'[191]Metrados'!E28 -> 60 | L27: =+ROUND($G27*K27,2) -> 72476.4 | M27: 0 | N27: =K27 -> 60 | O27: =+ROUND($M27*N27,2) -> 0 | P27: =+M27/($G27+$H27) -> 0 | Q27: =+G27-M27 -> 1207.94 | T27: 0 | U27: =$K27 -> 60 | V27: =+ROUND($T27*U27,2) -> 0 | W27: =+T27/($G27+$H27) -> 0 | X27: 0 | Y27: =$K27 -> 60 | Z27: =+ROUND($X27*Y27,2) -> 0 | AA27: =+X27/($G27+$H27) -> 0 | AB27: 0 | AC27: =$K27 -> 60 | AD27: =+ROUND($AB27*AC27,2) -> 0 | AE27: =+AB27/($G27+$H27) -> 0 | AF27: =+M27+O27+X27 -> 0
A28: =+A27+0.01 -> 2.05 | B28: =+B27+1 -> 14 | C28: Poste de C.A.C. de 15 m/400 daN (Incluye perilla) | F28: u | H28: 0 | J28: =+ROUND($G28*I28,2) -> 0 | K28: =+'[191]Metrados'!E29 -> 0 | L28: =+ROUND($H28*K28,2) -> 0 | M28: 0 | N28: =K28 -> 0 | O28: =+ROUND($M28*N28,2) -> 0 | Q28: =+G28-M28 -> 0 | T28: 0 | U28: =$K28 -> 0 | V28: =+ROUND($T28*U28,2) -> 0 | X28: 0 | Y28: =$K28 -> 0 | Z28: =+ROUND($X28*Y28,2) -> 0 | AB28: 0 | AC28: =$K28 -> 0 | AD28: =+ROUND($AB28*AC28,2) -> 0 | AF28: =+M28+O28+X28 -> 0
B29: =+B28+1 -> 15 | E29: =+"SUB-TOTAL "&A23&": " -> SUB-TOTAL 2: | J29: =+SUM(J24:J28) -> 184803.17 | L29: =+SUM(L24:L28) -> 184703.01 | M29: 0 | N29: =K29 -> 0 | O29: =+SUM(O24:O28) -> 0 | Q29: =+G29-M29 -> 0 | T29: 0 | U29: =$K29 -> 0 | V29: =+SUM(V24:V28) -> 0 | X29: 0 | Y29: =$K29 -> 0 | Z29: =+SUM(Z24:Z28) -> 0 | AB29: 0 | AC29: =$K29 -> 0 | AD29: =+SUM(AD24:AD28) -> 0 | AF29: =+M29+O29+X29 -> 0
A30: 3 | B30: =+B29+1 -> 16 | C30: POSTES DE MADERA IMPORTADA | M30: 0 | N30: =K30 -> 0 | Q30: =+G30-M30 -> 0 | T30: 0 | U30: =$K30 -> 0 | X30: 0 | Y30: =$K30 -> 0 | AB30: 0 | AC30: =$K30 -> 0 | AF30: =+M30+O30+X30 -> 0
A31: 3.01 | B31: =+B30+1 -> 17 | C31: Poste de madera importada (Pino Amarillo del Sur) de 12 m, Clase 6 | F31: u | G31: 1703.39 | I31: 9 | J31: =+ROUND($G31*I31,2) -> 15330.51 | K31: =+'[191]Metrados'!E32 -> 0 | L31: =+ROUND($G31*K31,2) -> 0 | M31: 0 | N31: =K31 -> 0 | O31: =+ROUND($M31*N31,2) -> 0 | P31: =+M31/($G31+$H31) -> 0 | Q31: =+G31-M31 -> 1703.39 | T31: 0 | U31: =$K31 -> 0 | V31: =+ROUND($T31*U31,2) -> 0 | W31: =+T31/($G31+$H31) -> 0 | X31: 0 | Y31: =$K31 -> 0 | Z31: =+ROUND($X31*Y31,2) -> 0 | AA31: =+X31/($G31+$H31) -> 0 | AB31: 0 | AC31: =$K31 -> 0 | AD31: =+ROUND($AB31*AC31,2) -> 0 | AE31: =+AB31/($G31+$H31) -> 0 | AF31: =+M31+O31+X31 -> 0
B32: =+B31+1 -> 18 | E32: =+"SUB-TOTAL "&A30&": " -> SUB-TOTAL 3: | J32: =+SUM(J31:J31) -> 15330.51 | L32: =+SUM(L31:L31) -> 0 | M32: 0 | N32: =K32 -> 0 | O32: =+SUM(O31:O31) -> 0 | Q32: =+G32-M32 -> 0 | T32: 0 | U32: =$K32 -> 0 | V32: =+SUM(V31:V31) -> 0 | X32: 0 | Y32: =$K32 -> 0 | Z32: =+SUM(Z31:Z31) -> 0 | AB32: 0 | AC32: =$K32 -> 0 | AD32: =+SUM(AD31:AD31) -> 0 | AF32: =+M32+O32+X32 -> 0
A33: 3.00A | B33: =+B32+1 -> 19 | C33: POSTES DE FIBRA DE VIDRIO | M33: 0 | N33: =K33 -> 0 | Q33: =+G33-M33 -> 0 | T33: 0 | U33: =$K33 -> 0 | X33: 0 | Y33: =$K33 -> 0 | AB33: 0 | AC33: =$K33 -> 0 | AF33: =+M33+O33+X33 -> 0
A34: 3.01A | B34: =+B33+1 -> 20 | C34: Poste de PRFV de 12 m/200 daN | F34: u | G34: 1958.01 | H34: 1958.01 | J34: =+ROUND($G34*I34,2) -> 0 | K34: =+'[191]Metrados'!E35 -> 4 | L34: =+ROUND($H34*K34,2) -> 7832.04 | M34: 0 | N34: =K34 -> 4 | O34: =+ROUND($M34*N34,2) -> 0 | P34: =+M34/($G34+$H34) -> 0 | Q34: =+G34-M34 -> 1958.01 | T34: 1480.75 | U34: =$K34 -> 4 | V34: =+ROUND($T34*U34,2) -> 5923 | W34: =+T34/($G34+$H34) -> 0.37812626 | X34: 0 | Y34: =$K34 -> 4 | Z34: =+ROUND($X34*Y34,2) -> 0 | AA34: =+X34/($G34+$H34) -> 0 | AB34: 0 | AC34: =$K34 -> 4 | AD34: =+ROUND($AB34*AC34,2) -> 0 | AE34: =+AB34/($G34+$H34) -> 0 | AF34: =+M34+O34+X34 -> 0
A35: 3.02A | B35: =+B34+1 -> 21 | C35: Poste de PRFV de 12 m/300 daN | F35: u | G35: 2336.29 | H35: 2336.29 | J35: =+ROUND($G35*I35,2) -> 0 | K35: =+'[191]Metrados'!E36 -> 11 | L35: =+ROUND($H35*K35,2) -> 25699.19 | M35: 0 | N35: =K35 -> 11 | O35: =+ROUND($M35*N35,2) -> 0 | P35: =+M35/($G35+$H35) -> 0 | Q35: =+G35-M35 -> 2336.29 | T35: 1573.3 | U35: =$K35 -> 11 | V35: =+ROUND($T35*U35,2) -> 17306.3 | W35: =+T35/($G35+$H35) -> 0.33670906 | X35: 0 | Y35: =$K35 -> 11 | Z35: =+ROUND($X35*Y35,2) -> 0 | AA35: =+X35/($G35+$H35) -> 0 | AB35: 0 | AC35: =$K35 -> 11 | AD35: =+ROUND($AB35*AC35,2) -> 0 | AE35: =+AB35/($G35+$H35) -> 0 | AF35: =+M35+O35+X35 -> 0
B36: =+B35+1 -> 22 | E36: =+"SUB-TOTAL "&A33&": " -> SUB-TOTAL 3.00A: | L36: =+L34+L35 -> 33531.23 | M36: 0 | N36: =K36 -> 0 | O36: =+O34+O35 -> 0 | Q36: =+G36-M36 -> 0 | T36: 0 | U36: =$K36 -> 0 | V36: =+V34+V35 -> 23229.3 | X36: 0 | Y36: =$K36 -> 0 | AB36: 0 | AC36: =$K36 -> 0 | AF36: =+M36+O36+X36 -> 0
A37: 4 | B37: =+B36+1 -> 23 | C37: OTROS MATERIALES DE CONCRETO ARMADO | M37: 0 | N37: =K37 -> 0 | Q37: =+G37-M37 -> 0 | T37: 0 | U37: =$K37 -> 0 | X37: 0 | Y37: =$K37 -> 0 | AB37: 0 | AC37: =$K37 -> 0 | AF37: =+M37+O37+X37 -> 0
A38: 4.01 | B38: =+B37+1 -> 24 | C38: Cruceta Asimétrica de C.A.V. Za / 1,5 / 0,9 / 250 / 200 / 100 daN (Za / L / L1/ T / F / V) | F38: u | G38: 120.3 | I38: 2 | J38: =+ROUND($G38*I38,2) -> 240.6 | K38: =+'[191]Metrados'!E39 -> 0 | L38: =+ROUND($G38*K38,2) -> 0 | M38: 0 | N38: =K38 -> 0 | O38: =+ROUND($M38*N38,2) -> 0 | P38: =+M38/($G38+$H38) -> 0 | Q38: =+G38-M38 -> 120.3 | T38: 0 | U38: =$K38 -> 0 | V38: =+ROUND($T38*U38,2) -> 0 | W38: =+T38/($G38+$H38) -> 0 | X38: 0 | Y38: =$K38 -> 0 | Z38: =+ROUND($X38*Y38,2) -> 0 | AA38: =+X38/($G38+$H38) -> 0 | AB38: 0 | AC38: =$K38 -> 0 | AD38: =+ROUND($AB38*AC38,2) -> 0 | AE38: =+AB38/($G38+$H38) -> 0 | AF38: =+M38+O38+X38 -> 0
A39: 4.02 | B39: =+B38+1 -> 25 | C39: Ménsula de C.A.V. M / 1,2 / 250 / 150 / 150 daN (M / L / T / F / V) | F39: u | G39: 88.8 | I39: 393 | J39: =+ROUND($G39*I39,2) -> 34898.4 | K39: =+'[191]Metrados'!E40 -> 84 | L39: =+ROUND($G39*K39,2) -> 7459.2 | M39: 0 | N39: =K39 -> 84 | O39: =+ROUND($M39*N39,2) -> 0 | P39: =+M39/($G39+$H39) -> 0 | Q39: =+G39-M39 -> 88.8 | T39: 0 | U39: =$K39 -> 84 | V39: =+ROUND($T39*U39,2) -> 0 | W39: =+T39/($G39+$H39) -> 0 | X39: 0 | Y39: =$K39 -> 84 | Z39: =+ROUND($X39*Y39,2) -> 0 | AA39: =+X39/($G39+$H39) -> 0 | AB39: 0 | AC39: =$K39 -> 84 | AD39: =+ROUND($AB39*AC39,2) -> 0 | AE39: =+AB39/($G39+$H39) -> 0 | AF39: =+M39+O39+X39 -> 0
A40: 4.03 | B40: =+B39+1 -> 26 | C40: Ménsula de C.A.V. M / 0,8 / 250 / 150 / 150 daN (M / L / T / F / V) | F40: u | G40: 92.26 | I40: 1 | J40: =+ROUND($G40*I40,2) -> 92.26 | K40: =+'[191]Metrados'!E41 -> 0 | L40: =+ROUND($G40*K40,2) -> 0 | M40: 0 | N40: =K40 -> 0 | O40: =+ROUND($M40*N40,2) -> 0 | P40: =+M40/($G40+$H40) -> 0 | Q40: =+G40-M40 -> 92.26 | T40: 0 | U40: =$K40 -> 0 | V40: =+ROUND($T40*U40,2) -> 0 | W40: =+T40/($G40+$H40) -> 0 | X40: 0 | Y40: =$K40 -> 0 | Z40: =+ROUND($X40*Y40,2) -> 0 | AA40: =+X40/($G40+$H40) -> 0 | AB40: 0 | AC40: =$K40 -> 0 | AD40: =+ROUND($AB40*AC40,2) -> 0 | AE40: =+AB40/($G40+$H40) -> 0 | AF40: =+M40+O40+X40 -> 0
A41: 4.05 | B41: =+B40+1 -> 27 | C41: Cruceta Simétrica de C.A.V. Z / 2,4 / 300 / 300 / 150 daN (Z/ L / T / F / V) | F41: u | G41: 230 | H41: 230 | J41: =+ROUND($G41*I41,2) -> 0 | K41: =+'[191]Metrados'!E42 -> 122 | L41: =+ROUND($H41*K41,2) -> 28060 | M41: 0 | N41: =K41 -> 122 | O41: =+ROUND($M41*N41,2) -> 0 | P41: =+M41/($G41+$H41) -> 0 | Q41: =+G41-M41 -> 230 | T41: 0 | U41: =$K41 -> 122 | V41: =+ROUND($T41*U41,2) -> 0 | W41: =+T41/($G41+$H41) -> 0 | X41: 0 | Y41: =$K41 -> 122 | Z41: =+ROUND($X41*Y41,2) -> 0 | AA41: =+X41/($G41+$H41) -> 0 | AB41: 0 | AC41: =$K41 -> 122 | AD41: =+ROUND($AB41*AC41,2) -> 0 | AE41: =+AB41/($G41+$H41) -> 0 | AF41: =+M41+O41+X41 -> 0
B42: =+B41+1 -> 28 | E42: =+"SUB-TOTAL "&A37&": " -> SUB-TOTAL 4: | J42: =+SUM(J38:J41) -> 35231.26 | L42: =+SUM(L38:L41) -> 35519.2 | M42: 0 | N42: =K42 -> 0 | O42: =+SUM(O38:O41) -> 0 | Q42: =+G42-M42 -> 0 | T42: 0 | U42: =$K42 -> 0 | V42: =+SUM(V38:V41) -> 0 | X42: 0 | Y42: =$K42 -> 0 | Z42: =+SUM(Z38:Z41) -> 0 | AB42: 0 | AC42: =$K42 -> 0 | AD42: =+SUM(AD38:AD41) -> 0 | AF42: =+M42+O42+X42 -> 0
A43: 5 | B43: =+B42+1 -> 29 | C43: AISLADORES Y ACCESORIOS | M43: 0 | N43: =K43 -> 0 | Q43: =+G43-M43 -> 0 | T43: 0 | U43: =$K43 -> 0 | X43: 0 | Y43: =$K43 -> 0 | AB43: 0 | AC43: =$K43 -> 0 | AF43: =+M43+O43+X43 -> 0
A44: 5.01 | B44: =+B43+1 -> 30 | C44: Aislador de Porcelana Tipo Pin, Clase ANSI 56-3 | F44: u | G44: 76.45 | I44: 29 | J44: =+ROUND($G44*I44,2) -> 2217.05 | K44: =+'[191]Metrados'!E45 -> 24 | L44: =+ROUND($G44*K44,2) -> 1834.8 | M44: 0 | N44: =K44 -> 24 | O44: =+ROUND($M44*N44,2) -> 0 | P44: =+M44/($G44+$H44) -> 0 | Q44: =+G44-M44 -> 76.45 | T44: 0 | U44: =$K44 -> 24 | V44: =+ROUND($T44*U44,2) -> 0 | W44: =+T44/($G44+$H44) -> 0 | X44: 0 | Y44: =$K44 -> 24 | Z44: =+ROUND($X44*Y44,2) -> 0 | AA44: =+X44/($G44+$H44) -> 0 | AB44: 0 | AC44: =$K44 -> 24 | AD44: =+ROUND($AB44*AC44,2) -> 0 | AE44: =+AB44/($G44+$H44) -> 0 | AF44: =+M44+O44+X44 -> 0
A45: 5.02 | B45: =+B44+1 -> 31 | C45: Espiga de AºGº de 609 mm longitud, para Cabeza de Poste y Aislador ANSI 56-3 | F45: u | G45: 35.96 | I45: 29 | J45: =+ROUND($G45*I45,2) -> 1042.84 | K45: =+'[191]Metrados'!E46 -> 24 | L45: =+ROUND($G45*K45,2) -> 863.04 | M45: 29.85 | N45: =K45 -> 24 | O45: =+ROUND($M45*N45,2) -> 716.4 | P45: =+M45/($G45+$H45) -> 0.83008899 | Q45: =+(G45+H45)-M45 -> 6.11 | R45: SI | T45: 0 | U45: =$K45 -> 24 | V45: =+ROUND($T45*U45,2) -> 0 | W45: =+T45/($G45+$H45) -> 0 | X45: 22.8823 | Y45: =$K45 -> 24 | Z45: =+ROUND($X45*Y45,2) -> 549.18 | AA45: =+X45/($G45+$H45) -> 0.63632647 | AB45: 0 | AC45: =$K45 -> 24 | AD45: =+ROUND($AB45*AC45,2) -> 0 | AE45: =+AB45/($G45+$H45) -> 0 | AF45: =+M45+O45+X45 -> 769.1323
A46: 5.03 | B46: =+B45+1 -> 32 | C46: Conjunto Aislador Line Post Polimérico en Mesula y Cruceta: | F46: u | G46: 209.65 | I46: 369 | J46: =+ROUND($G46*I46,2) -> 77360.85 | K46: =+[191]Metrados!E48 -> 307 | L46: =+ROUND($G46*K46,2) -> 64362.55 | M46: 0 | N46: =K46 -> 307 | O46: =+ROUND($M46*N46,2) -> 0 | P46: =+M46/($G46+$H46) -> 0 | Q46: =+G46-M46 -> 209.65 | T46: 0 | U46: =$K46 -> 307 | V46: =+ROUND($T46*U46,2) -> 0 | W46: =+T46/($G46+$H46) -> 0 | X46: 0 | Y46: =$K46 -> 307 | Z46: =+ROUND($X46*Y46,2) -> 0 | AA46: =+X46/($G46+$H46) -> 0 | AB46: 0 | AC46: =$K46 -> 307 | AD46: =+ROUND($AB46*AC46,2) -> 0 | AE46: =+AB46/($G46+$H46) -> 0 | AF46: =+M46+O46+X46 -> 0
B47: =+B46+1 -> 33 | C47: .- Aislador Polimérico de 36 kV, Tipo Line Post con Espárrago de 19 mm Ø, 200 mm longitud (Alternativa a Conjunto Aislador-Espiga en Cruceta) | M47: 0 | Q47: =+G47-M47 -> 0 | T47: 0 | U47: =$K47 -> 0 | X47: 0 | Y47: =$K47 -> 0 | AB47: 0 | AC47: =$K47 -> 0 | AF47: =+M47+O47+X47 -> 0
B48: =+B47+1 -> 34 | E48: =+"SUB-TOTAL "&A43&": " -> SUB-TOTAL 5: | J48: =+SUM(J44:J47) -> 80620.74 | L48: =+SUM(L44:L47) -> 67060.39 | M48: 0 | N48: =K48 -> 0 | O48: =+SUM(O44:O47) -> 716.4 | Q48: =+G48-M48 -> 0 | T48: 0 | U48: =$K48 -> 0 | V48: =+SUM(V44:V47) -> 0 | X48: 0 | Y48: =$K48 -> 0 | Z48: =+SUM(Z44:Z47) -> 549.18 | AB48: 0 | AC48: =$K48 -> 0 | AD48: =+SUM(AD44:AD47) -> 0 | AF48: =+M48+O48+X48 -> 716.4
A49: 6 | B49: =+B48+1 -> 35 | C49: AISLADORES DE SUSPENSION Y ACCESORIOS | M49: 0 | N49: =K49 -> 0 | Q49: =+G49-M49 -> 0 | T49: 0 | U49: =$K49 -> 0 | X49: 0 | Y49: =$K49 -> 0 | AB49: 0 | AC49: =$K49 -> 0 | AF49: =+M49+O49+X49 -> 0
A50: 6.01 | B50: =+B49+1 -> 36 | C50: Grillete Recto | F50: u | G50: 17.76 | I50: 155 | J50: =+ROUND($G50*I50,2) -> 2752.8 | K50: =+[191]Metrados!E51 -> 283 | L50: =+ROUND($G50*K50,2) -> 5026.08 | M50: 10.64 | N50: =K50 -> 283 | O50: =+ROUND($M50*N50,2) -> 3011.12 | P50: =+M50/($G50+$H50) -> 0.5990991 | Q50: =+(G50+H50)-M50 -> 7.12 | S50: NO | T50: 0 | U50: =$K50 -> 283 | V50: =+ROUND($T50*U50,2) -> 0 | W50: =+T50/($G50+$H50) -> 0 | X50: 7.8521 | Y50: =$K50 -> 283 | Z50: =+ROUND($X50*Y50,2) -> 2222.14 | AA50: =+X50/($G50+$H50) -> 0.44212275 | AB50: 6.5 | AC50: =$K50 -> 283 | AD50: =+ROUND($AB50*AC50,2) -> 1839.5 | AE50: =+AB50/($G50+$H50) -> 0.36599099 | AF50: =+M50+O50+X50 -> 3029.6121
A51: 6.02 | B51: =+B50+1 -> 37 | C51: Aislador Polimerico con Conexión Horquilla (Estructura) y Lengüeta (Linea) de 36 kV, según Especificacion Técnica. | F51: u | G51: 76.66 | I51: 155 | J51: =+ROUND($G51*I51,2) -> 11882.3 | K51: =+'[191]Metrados'!E52 -> 283 | L51: =+ROUND($G51*K51,2) -> 21694.78 | M51: 0 | N51: =K51 -> 283 | O51: =+ROUND($M51*N51,2) -> 0 | P51: =+M51/($G51+$H51) -> 0 | Q51: =+G51-M51 -> 76.66 | T51: 0 | U51: =$K51 -> 283 | V51: =+ROUND($T51*U51,2) -> 0 | W51: =+T51/($G51+$H51) -> 0 | X51: 0 | Y51: =$K51 -> 283 | Z51: =+ROUND($X51*Y51,2) -> 0 | AA51: =+X51/($G51+$H51) -> 0 | AB51: 0 | AC51: =$K51 -> 283 | AD51: =+ROUND($AB51*AC51,2) -> 0 | AE51: =+AB51/($G51+$H51) -> 0 | AF51: =+M51+O51+X51 -> 0
B52: =+B51+1 -> 38 | E52: =+"SUB-TOTAL "&A49&": " -> SUB-TOTAL 6: | J52: =+SUM(J50:J51) -> 14635.1 | L52: =+SUM(L50:L51) -> 26720.86 | M52: 0 | N52: =K52 -> 0 | O52: =+SUM(O50:O51) -> 3011.12 | Q52: =+G52-M52 -> 0 | T52: 0 | U52: =$K52 -> 0 | V52: =+SUM(V50:V51) -> 0 | X52: 0 | Y52: =$K52 -> 0 | Z52: =+SUM(Z50:Z51) -> 2222.14 | AB52: 0 | AC52: =$K52 -> 0 | AD52: =+SUM(AD50:AD51) -> 1839.5 | AF52: =+M52+O52+X52 -> 3011.12
A53: 7 | B53: =+B52+1 -> 39 | C53: CONDUCTOR DE ALEACIÓN DE ALUMINIO | M53: 0 | N53: =K53 -> 0 | Q53: =+G53-M53 -> 0 | T53: 0 | U53: =$K53 -> 0 | X53: 0 | Y53: =$K53 -> 0 | AB53: 0 | AC53: =$K53 -> 0 | AF53: =+M53+O53+X53 -> 0
A54: 7.01 | B54: =+B53+1 -> 40 | C54: Conductor de Aleacion de Aluminio de 35 mm² | F54: km | G54: 2249.62 | I54: 53.4 | J54: =+ROUND($G54*I54,2) -> 120129.71 | K54: =+'[191]Metrados'!E55 -> 51.19 | L54: =+ROUND($G54*K54,2) -> 115158.05 | M54: 1449.1 | N54: =K54 -> 51.19 | O54: =+ROUND($M54*N54,2) -> 74179.43 | P54: =+M54/($G54+$H54) -> 0.64415323 | Q54: =+G54-M54 -> 800.52 | T54: 1330 | U54: =$K54 -> 51.19 | V54: =+ROUND($T54*U54,2) -> 68082.7 | W54: =+T54/($G54+$H54) -> 0.59121096 | X54: 0 | Y54: =$K54 -> 51.19 | Z54: =+ROUND($X54*Y54,2) -> 0 | AA54: =+X54/($G54+$H54) -> 0 | AB54: 0 | AC54: =$K54 -> 51.19 | AD54: =+ROUND($AB54*AC54,2) -> 0 | AE54: =+AB54/($G54+$H54) -> 0 | AF54: =+M54+O54+X54 -> 75628.53
A55: 7.02 | B55: =+B54+1 -> 41 | C55: Conductor de Aleacion de Aluminio de 70 mm² | F55: km | G55: 4157 | I55: 1.91 | J55: =+ROUND($G55*I55,2) -> 7939.87 | K55: =+'[191]Metrados'!E56 -> 1.17 | L55: =+ROUND($G55*K55,2) -> 4863.69 | M55: 2601.64 | N55: =K55 -> 1.17 | O55: =+ROUND($M55*N55,2) -> 3043.92 | P55: =+M55/($G55+$H55) -> 0.62584556 | Q55: =+G55-M55 -> 1555.36 | T55: 2940 | U55: =$K55 -> 1.17 | V55: =+ROUND($T55*U55,2) -> 3439.8 | W55: =+T55/($G55+$H55) -> 0.7072408 | X55: 0 | Y55: =$K55 -> 1.17 | Z55: =+ROUND($X55*Y55,2) -> 0 | AA55: =+X55/($G55+$H55) -> 0 | AB55: 0 | AC55: =$K55 -> 1.17 | AD55: =+ROUND($AB55*AC55,2) -> 0 | AE55: =+AB55/($G55+$H55) -> 0 | AF55: =+M55+O55+X55 -> 5645.56
B56: =+B55+1 -> 42 | E56: =+"SUB-TOTAL "&A53&": " -> SUB-TOTAL 7: | J56: =+SUM(J54:J55) -> 128069.58 | L56: =+L54+L55 -> 120021.74 | M56: 0 | N56: =K56 -> 0 | O56: =+SUM(O54:O55) -> 77223.35 | Q56: =+G56-M56 -> 0 | T56: 0 | U56: =$K56 -> 0 | V56: =+V54+V55 -> 71522.5 | X56: 0 | Y56: =$K56 -> 0 | Z56: =+SUM(Z54:Z55) -> 0 | AB56: 0 | AC56: =$K56 -> 0 | AD56: =+SUM(AD54:AD55) -> 0 | AF56: =+M56+O56+X56 -> 77223.35
A57: 8 | B57: =+B56+1 -> 43 | C57: ACCESORIOS PARA CONDUCTOR DE ALEACION DE ALUMINIO | M57: 0 | N57: =K57 -> 0 | Q57: =+G57-M57 -> 0 | T57: 0 | U57: =$K57 -> 0 | X57: 0 | Y57: =$K57 -> 0 | AB57: 0 | AC57: =$K57 -> 0 | AF57: =+M57+O57+X57 -> 0
A58: 8.01 | B58: =+B57+1 -> 44 | C58: Varilla de Armar preformada Simple para Conductor de 35 mm² | F58: u | G58: 10.19 | I58: 326 | J58: =+ROUND($G58*I58,2) -> 3321.94 | K58: =+'[191]Metrados'!E59 -> 275 | L58: =+ROUND($G58*K58,2) -> 2802.25 | M58: 6.17 | N58: =K58 -> 275 | O58: =+ROUND($M58*N58,2) -> 1696.75 | P58: =+M58/($G58+$H58) -> 0.60549558 | Q58: =+(G58+H58)-M58 -> 4.02 | R58: SI | T58: 0 | U58: =$K58 -> 275 | V58: =+ROUND($T58*U58,2) -> 0 | W58: =+T58/($G58+$H58) -> 0 | X58: 7.5151 | Y58: =$K58 -> 275 | Z58: =+ROUND($X58*Y58,2) -> 2066.65 | AA58: =+X58/($G58+$H58) -> 0.73749755 | AB58: 5.5 | AC58: =$K58 -> 275 | AD58: =+ROUND($AB58*AC58,2) -> 1512.5 | AE58: =+AB58/($G58+$H58) -> 0.53974485 | AF58: =+M58+O58+X58 -> 1710.4351
A59: 8.02 | B59: =+B58+1 -> 45 | C59: Varilla de Armar preformada Simple para Conductor de 70 mm² | F59: u | G59: 17.38 | I59: 2 | J59: =+ROUND($G59*I59,2) -> 34.76 | K59: =+'[191]Metrados'!E60 -> 2 | L59: =+ROUND($G59*K59,2) -> 34.76 | M59: 10.46 | N59: =K59 -> 2 | O59: =+ROUND($M59*N59,2) -> 20.92 | P59: =+M59/($G59+$H59) -> 0.6018412 | Q59: =+(G59+H59)-M59 -> 6.92 | R59: SI | T59: 0 | U59: =$K59 -> 2 | V59: =+ROUND($T59*U59,2) -> 0 | W59: =+T59/($G59+$H59) -> 0 | X59: 10.4807 | Y59: =$K59 -> 2 | Z59: =+ROUND($X59*Y59,2) -> 20.96 | AA59: =+X59/($G59+$H59) -> 0.60303222 | AB59: 8 | AC59: =$K59 -> 2 | AD59: =+ROUND($AB59*AC59,2) -> 16 | AE59: =+AB59/($G59+$H59) -> 0.46029919 | AF59: =+M59+O59+X59 -> 41.8607
A60: 8.03 | B60: =+B59+1 -> 46 | C60: Manguito de Empalme para Conductor de 35 mm² | F60: u | G60: 12.11 | I60: 17 | J60: =+ROUND($G60*I60,2) -> 205.87 | K60: =+'[191]Metrados'!E61 -> 0 | L60: =+ROUND($G60*K60,2) -> 0 | M60: 0 | N60: =K60 -> 0 | O60: =+ROUND($M60*N60,2) -> 0 | P60: =+M60/($G60+$H60) -> 0 | Q60: =+G60-M60 -> 12.11 | T60: 0 | U60: =$K60 -> 0 | V60: =+ROUND($T60*U60,2) -> 0 | W60: =+T60/($G60+$H60) -> 0 | X60: 0 | Y60: =$K60 -> 0 | Z60: =+ROUND($X60*Y60,2) -> 0 | AA60: =+X60/($G60+$H60) -> 0 | AB60: 0 | AC60: =$K60 -> 0 | AD60: =+ROUND($AB60*AC60,2) -> 0 | AE60: =+AB60/($G60+$H60) -> 0 | AF60: =+M60+O60+X60 -> 0
A61: 8.04 | B61: =+B60+1 -> 47 | C61: Manguito de Reparacion para Conductor de 35 mm² | F61: u | G61: 11.59 | I61: 7 | J61: =+ROUND($G61*I61,2) -> 81.13 | K61: =+'[191]Metrados'!E62 -> 0 | L61: =+ROUND($G61*K61,2) -> 0 | M61: 0 | N61: =K61 -> 0 | O61: =+ROUND($M61*N61,2) -> 0 | P61: =+M61/($G61+$H61) -> 0 | Q61: =+G61-M61 -> 11.59 | T61: 0 | U61: =$K61 -> 0 | V61: =+ROUND($T61*U61,2) -> 0 | W61: =+T61/($G61+$H61) -> 0 | X61: 0 | Y61: =$K61 -> 0 | Z61: =+ROUND($X61*Y61,2) -> 0 | AA61: =+X61/($G61+$H61) -> 0 | AB61: 0 | AC61: =$K61 -> 0 | AD61: =+ROUND($AB61*AC61,2) -> 0 | AE61: =+AB61/($G61+$H61) -> 0 | AF61: =+M61+O61+X61 -> 0
A62: 8.05 | B62: =+B61+1 -> 48 | C62: Grapa de Doble Via de Aluminio para Conductor de 35 mm² | F62: u | G62: 7.77 | I62: 84 | J62: =+ROUND($G62*I62,2) -> 652.68 | K62: =+'[191]Metrados'!E63 -> 190 | L62: =+ROUND($G62*K62,2) -> 1476.3 | M62: 3.8 | N62: =K62 -> 190 | O62: =+ROUND($M62*N62,2) -> 722 | P62: =+M62/($G62+$H62) -> 0.48906049 | Q62: =+(G62+H62)-M62 -> 3.97 | R62: SI | T62: 0 | U62: =$K62 -> 190 | V62: =+ROUND($T62*U62,2) -> 0 | W62: =+T62/($G62+$H62) -> 0 | X62: 4.7517 | Y62: =$K62 -> 190 | Z62: =+ROUND($X62*Y62,2) -> 902.82 | AA62: =+X62/($G62+$H62) -> 0.6115444 | AB62: 0 | AC62: =$K62 -> 190 | AD62: =+ROUND($AB62*AC62,2) -> 0 | AE62: =+AB62/($G62+$H62) -> 0 | AF62: =+M62+O62+X62 -> 730.5517
A63: 8.06 | B63: =+B62+1 -> 49 | C63: Grapa de Doble Via de Aluminio para Conductor de 70 mm² | F63: u | G63: 10.36 | I63: 2 | J63: =+ROUND($G63*I63,2) -> 20.72 | K63: =+'[191]Metrados'!E64 -> 6 | L63: =+ROUND($G63*K63,2) -> 62.16 | M63: 5.32 | N63: =K63 -> 6 | O63: =+ROUND($M63*N63,2) -> 31.92 | P63: =+M63/($G63+$H63) -> 0.51351351 | Q63: =+(G63+H63)-M63 -> 5.04 | R63: SI | T63: 0 | U63: =$K63 -> 6 | V63: =+ROUND($T63*U63,2) -> 0 | W63: =+T63/($G63+$H63) -> 0 | X63: 4.7517 | Y63: =$K63 -> 6 | Z63: =+ROUND($X63*Y63,2) -> 28.51 | AA63: =+X63/($G63+$H63) -> 0.4586583 | AB63: 0 | AC63: =$K63 -> 6 | AD63: =+ROUND($AB63*AC63,2) -> 0 | AE63: =+AB63/($G63+$H63) -> 0 | AF63: =+M63+O63+X63 -> 41.9917
A64: 8.07 | B64: =+B63+1 -> 50 | C64: Alambre de Amarre Aluminio Recocido de 16 mm² | F64: m | G64: 1.41 | I64: 1052.3 | J64: =+ROUND($G64*I64,2) -> 1483.74 | K64: =+'[191]Metrados'!E65 -> 905 | L64: =+ROUND($G64*K64,2) -> 1276.05 | M64: 1.06 | N64: =K64 -> 905 | O64: =+ROUND($M64*N64,2) -> 959.3 | P64: =+M64/($G64+$H64) -> 0.75177305 | Q64: =+(G64+H64)-M64 -> 0.35 | S64: NO | T64: 0 | U64: =$K64 -> 905 | V64: =+ROUND($T64*U64,2) -> 0 | W64: =+T64/($G64+$H64) -> 0 | X64: 0.8762 | Y64: =$K64 -> 905 | Z64: =+ROUND($X64*Y64,2) -> 792.96 | AA64: =+X64/($G64+$H64) -> 0.62141844 | AB64: 1.1 | AC64: =$K64 -> 905 | AD64: =+ROUND($AB64*AC64,2) -> 995.5 | AE64: =+AB64/($G64+$H64) -> 0.78014184 | AF64: =+M64+O64+X64 -> 961.2362
A65: 8.08 | B65: =+B64+1 -> 51 | C65: Amortiguador de Vibracion Tipo Stockbridge para Conductor de 35 mm² | F65: u | G65: 36.01 | I65: 4 | J65: =+ROUND($G65*I65,2) -> 144.04 | K65: =+'[191]Metrados'!E66 -> 2 | L65: =+ROUND($G65*K65,2) -> 72.02 | M65: 31.49 | N65: =K65 -> 2 | O65: =+ROUND($M65*N65,2) -> 62.98 | P65: =+M65/($G65+$H65) -> 0.87447931 | Q65: =+(G65+H65)-M65 -> 4.52 | R65: SI | T65: 0 | U65: =$K65 -> 2 | V65: =+ROUND($T65*U65,2) -> 0 | W65: =+T65/($G65+$H65) -> 0 | X65: 24.1966 | Y65: =$K65 -> 2 | Z65: =+ROUND($X65*Y65,2) -> 48.39 | AA65: =+X65/($G65+$H65) -> 0.67194113 | AB65: 31 | AC65: =$K65 -> 2 | AD65: =+ROUND($AB65*AC65,2) -> 62 | AE65: =+AB65/($G65+$H65) -> 0.86087198 | AF65: =+M65+O65+X65 -> 118.6666
A66: 8.09 | B66: =+B65+1 -> 52 | C66: Amortiguador de Vibracion Tipo Stockbridge para Conductor de 70 mm² | F66: u | G66: 44.34 | I66: 8 | J66: =+ROUND($G66*I66,2) -> 354.72 | K66: =+'[191]Metrados'!E67 -> 6 | L66: =+ROUND($G66*K66,2) -> 266.04 | M66: 31.49 | N66: =K66 -> 6 | O66: =+ROUND($M66*N66,2) -> 188.94 | P66: =+M66/($G66+$H66) -> 0.71019396 | Q66: =+(G66+H66)-M66 -> 12.85 | R66: SI | T66: 0 | U66: =$K66 -> 6 | V66: =+ROUND($T66*U66,2) -> 0 | W66: =+T66/($G66+$H66) -> 0 | X66: 34.6436 | Y66: =$K66 -> 6 | Z66: =+ROUND($X66*Y66,2) -> 207.86 | AA66: =+X66/($G66+$H66) -> 0.7813171 | AB66: 33 | AC66: =$K66 -> 6 | AD66: =+ROUND($AB66*AC66,2) -> 198 | AE66: =+AB66/($G66+$H66) -> 0.74424899 | AF66: =+M66+O66+X66 -> 255.0736
A67: 8.1 | B67: =+B66+1 -> 53 | C67: Grapa de Angulo para Conductor de 35 mm² | F67: u | G67: 29.37 | I67: 14 | J67: =+ROUND($G67*I67,2) -> 411.18 | K67: =+'[191]Metrados'!E68 -> 2 | L67: =+ROUND($G67*K67,2) -> 58.74 | M67: 20.79 | N67: =K67 -> 2 | O67: =+ROUND($M67*N67,2) -> 41.58 | P67: =+M67/($G67+$H67) -> 0.70786517 | Q67: =+(G67+H67)-M67 -> 8.58 | R67: SI | T67: 0 | U67: =$K67 -> 2 | V67: =+ROUND($T67*U67,2) -> 0 | W67: =+T67/($G67+$H67) -> 0 | X67: 18.9731 | Y67: =$K67 -> 2 | Z67: =+ROUND($X67*Y67,2) -> 37.95 | AA67: =+X67/($G67+$H67) -> 0.64600272 | AB67: 17 | AC67: =$K67 -> 2 | AD67: =+ROUND($AB67*AC67,2) -> 34 | AE67: =+AB67/($G67+$H67) -> 0.57882193 | AF67: =+M67+O67+X67 -> 81.3431
A68: 8.11 | B68: =+B67+1 -> 54 | C68: Grapa de Angulo para Conductor de 70 mm² | F68: u | G68: 47.48 | I68: 4 | J68: =+ROUND($G68*I68,2) -> 189.92 | K68: =+'[191]Metrados'!E69 -> 0 | L68: =+ROUND($G68*K68,2) -> 0 | M68: 0 | N68: =K68 -> 0 | O68: =+ROUND($M68*N68,2) -> 0 | P68: =+M68/($G68+$H68) -> 0 | Q68: =+G68-M68 -> 47.48 | T68: 0 | U68: =$K68 -> 0 | V68: =+ROUND($T68*U68,2) -> 0 | W68: =+T68/($G68+$H68) -> 0 | X68: 0 | Y68: =$K68 -> 0 | Z68: =+ROUND($X68*Y68,2) -> 0 | AA68: =+X68/($G68+$H68) -> 0 | AB68: 0 | AC68: =$K68 -> 0 | AD68: =+ROUND($AB68*AC68,2) -> 0 | AE68: =+AB68/($G68+$H68) -> 0 | AF68: =+M68+O68+X68 -> 0
A69: 8.12 | B69: =+B68+1 -> 55 | C69: Grapa de Anclaje para Conductor de 35 mm² | F69: u | G69: 25.34 | I69: 129 | J69: =+ROUND($G69*I69,2) -> 3268.86 | K69: =+'[191]Metrados'!E70 -> 273 | L69: =+ROUND($G69*K69,2) -> 6917.82 | M69: 17.33 | N69: =K69 -> 273 | O69: =+ROUND($M69*N69,2) -> 4731.09 | P69: =+M69/($G69+$H69) -> 0.68389897 | Q69: =+(G69+H69)-M69 -> 8.01 | R69: SI | T69: 0 | U69: =$K69 -> 273 | V69: =+ROUND($T69*U69,2) -> 0 | W69: =+T69/($G69+$H69) -> 0 | X69: 15.3672 | Y69: =$K69 -> 273 | Z69: =+ROUND($X69*Y69,2) -> 4195.25 | AA69: =+X69/($G69+$H69) -> 0.60644041 | AB69: 17.8 | AC69: =$K69 -> 273 | AD69: =+ROUND($AB69*AC69,2) -> 4859.4 | AE69: =+AB69/($G69+$H69) -> 0.70244672 | AF69: =+M69+O69+X69 -> 4763.7872
A70: 8.13 | B70: =+B69+1 -> 56 | C70: Grapa de Anclaje para Conductor de 70 mm² | F70: u | G70: 49.03 | I70: 8 | J70: =+ROUND($G70*I70,2) -> 392.24 | K70: =+'[191]Metrados'!E71 -> 8 | L70: =+ROUND($G70*K70,2) -> 392.24 | M70: 31.92 | N70: =K70 -> 8 | O70: =+ROUND($M70*N70,2) -> 255.36 | P70: =+M70/($G70+$H70) -> 0.65102998 | Q70: =+(G70+H70)-M70 -> 17.11 | R70: SI | T70: 0 | U70: =$K70 -> 8 | V70: =+ROUND($T70*U70,2) -> 0 | W70: =+T70/($G70+$H70) -> 0 | X70: 17.3218 | Y70: =$K70 -> 8 | Z70: =+ROUND($X70*Y70,2) -> 138.57 | AA70: =+X70/($G70+$H70) -> 0.35328982 | AB70: 21.5 | AC70: =$K70 -> 8 | AD70: =+ROUND($AB70*AC70,2) -> 172 | AE70: =+AB70/($G70+$H70) -> 0.43850704 | AF70: =+M70+O70+X70 -> 304.6018
A71: 8.14 | B71: =+B70+1 -> 57 | C71: Cinta plana de armar de aluminio | F71: m | H71: 1 | J71: =+ROUND($G71*I71,2) -> 0 | K71: =+'[191]Metrados'!E72 -> 281 | L71: =+ROUND($H71*K71,2) -> 281 | M71: 1.06 | N71: =K71 -> 281 | O71: =+ROUND($M71*N71,2) -> 297.86 | P71: =+M71/($G71+$H71) -> 1.06 | Q71: =+(G71+H71)-M71 -> -0.06 | S71: NO | T71: 0 | U71: =$K71 -> 281 | V71: =+ROUND($T71*U71,2) -> 0 | W71: =+T71/($G71+$H71) -> 0 | X71: 0.8088 | Y71: =$K71 -> 281 | Z71: =+ROUND($X71*Y71,2) -> 227.27 | AA71: =+X71/($G71+$H71) -> 0.8088 | AB71: 0 | AC71: =$K71 -> 281 | AD71: =+ROUND($AB71*AC71,2) -> 0 | AE71: =+AB71/($G71+$H71) -> 0 | AF71: =+M71+O71+X71 -> 299.7288
A72: 8.15 | B72: =+B71+1 -> 58 | C72: Varilla de Armar preformada Doble para Conductor de 35 mm² | F72: u | H72: 15.8 | J72: =+ROUND($G72*I72,2) -> 0 | K72: =+'[191]Metrados'!E73 -> 2 | L72: =+ROUND($H72*K72,2) -> 31.6 | M72: 7.87 | N72: =K72 -> 2 | O72: =+ROUND($M72*N72,2) -> 15.74 | P72: =+M72/($G72+$H72) -> 0.49810127 | Q72: =+(G72+H72)-M72 -> 7.93 | S72: NO | T72: 0 | U72: =$K72 -> 2 | V72: =+ROUND($T72*U72,2) -> 0 | W72: =+T72/($G72+$H72) -> 0 | X72: 9.1664 | Y72: =$K72 -> 2 | Z72: =+ROUND($X72*Y72,2) -> 18.33 | AA72: =+X72/($G72+$H72) -> 0.5801519 | AB72: 0 | AC72: =$K72 -> 2 | AD72: =+ROUND($AB72*AC72,2) -> 0 | AE72: =+AB72/($G72+$H72) -> 0 | AF72: =+M72+O72+X72 -> 32.7764
B73: =+B72+1 -> 59 | E73: =+"SUB-TOTAL "&A57&": " -> SUB-TOTAL 8: | J73: =+SUM(J58:J72) -> 10561.8 | L73: =+SUM(L58:L72) -> 13670.98 | M73: 0 | N73: =K73 -> 0 | O73: =+SUM(O58:O72) -> 9024.44 | Q73: =+G73-M73 -> 0 | T73: 0 | U73: =$K73 -> 0 | V73: =+SUM(V58:V72) -> 0 | X73: 0 | Y73: =$K73 -> 0 | Z73: =+SUM(Z58:Z72) -> 8685.52 | AB73: 0 | AC73: =$K73 -> 0 | AD73: =+SUM(AD58:AD72) -> 7849.4 | AF73: =+M73+O73+X73 -> 9024.44
A74: 9 | B74: =+B73+1 -> 60 | C74: CONDUCTOR DE COBRE | M74: 0 | N74: =K74 -> 0 | Q74: =+G74-M74 -> 0 | T74: 0 | U74: =$K74 -> 0 | X74: 0 | Y74: =$K74 -> 0 | AB74: 0 | AC74: =$K74 -> 0 | AF74: =+M74+O74+X74 -> 0
A75: 9.01 | B75: =+B74+1 -> 61 | C75: Cable de Acero con Recubrimiento Metalúrgico de Cu de 4 AWG (21,15 mm²), para Puesta a Tierra | F75: m | G75: 12.8 | I75: 2936.1 | J75: =+ROUND($G75*I75,2) -> 37582.08 | K75: =+'[191]Metrados'!E76 -> 3162.9 | L75: =+ROUND($G75*K75,2) -> 40485.12 | M75: 6.2 | N75: =K75 -> 3162.9 | O75: =+ROUND($M75*N75,2) -> 19609.98 | P75: =+M75/($G75+$H75) -> 0.484375 | Q75: =+(G75+H75)-M75 -> 6.6 | R75: SI | T75: 0 | U75: =$K75 -> 3162.9 | V75: =+ROUND($T75*U75,2) -> 0 | W75: =+T75/($G75+$H75) -> 0 | X75: 0 | Y75: =$K75 -> 3162.9 | Z75: =+ROUND($X75*Y75,2) -> 0 | AA75: =+X75/($G75+$H75) -> 0 | AB75: 0 | AC75: =$K75 -> 3162.9 | AD75: =+ROUND($AB75*AC75,2) -> 0 | AE75: =+AB75/($G75+$H75) -> 0 | AF75: =+M75+O75+X75 -> 19616.18
B76: =+B75+1 -> 62 | E76: =+"SUB-TOTAL "&A74&": " -> SUB-TOTAL 9: | J76: =+SUM(J75:J75) -> 37582.08 | L76: =+SUM(L75:L75) -> 40485.12 | M76: 0 | N76: =K76 -> 0 | O76: =+SUM(O75:O75) -> 19609.98 | Q76: =+G76-M76 -> 0 | T76: 0 | U76: =$K76 -> 0 | V76: =+SUM(V75:V75) -> 0 | X76: 0 | Y76: =$K76 -> 0 | Z76: =+SUM(Z75:Z75) -> 0 | AB76: 0 | AC76: =$K76 -> 0 | AD76: =+SUM(AD75:AD75) -> 0 | AF76: =+M76+O76+X76 -> 19609.98
A77: 10 | B77: =+B76+1 -> 63 | C77: MATERIAL DE FERRETERIA PARA POSTES Y CRUCETAS | M77: 0 | N77: =K77 -> 0 | Q77: =+G77-M77 -> 0 | T77: 0 | U77: =$K77 -> 0 | X77: 0 | Y77: =$K77 -> 0 | AB77: 0 | AC77: =$K77 -> 0 | AF77: =+M77+O77+X77 -> 0
A78: 10.01 | B78: =+B77+1 -> 64 | C78: Perno Cabeza Coche de AºGº de 13 mm Ø x 152 mm longitud, 76 mm maquinado, con Arandela, Tuerca y Contratuerca | F78: u | G78: 3.86 | I78: 9 | J78: =+ROUND($G78*I78,2) -> 34.74 | K78: =+'[191]Metrados'!E79 -> 33 | L78: =+ROUND($G78*K78,2) -> 127.38 | M78: 3.34 | N78: =K78 -> 33 | O78: =+ROUND($M78*N78,2) -> 110.22 | P78: =+M78/($G78+$H78) -> 0.86528497 | Q78: =+(G78+H78)-M78 -> 0.52 | S78: NO | T78: 0 | U78: =$K78 -> 33 | V78: =+ROUND($T78*U78,2) -> 0 | W78: =+T78/($G78+$H78) -> 0 | X78: 3.2015 | Y78: =$K78 -> 33 | Z78: =+ROUND($X78*Y78,2) -> 105.65 | AA78: =+X78/($G78+$H78) -> 0.82940415 | AB78: 1.7 | AC78: =$K78 -> 33 | AD78: =+ROUND($AB78*AC78,2) -> 56.1 | AE78: =+AB78/($G78+$H78) -> 0.44041451 | AF78: =+M78+O78+X78 -> 116.7615
A79: 10.02 | B79: =+B78+1 -> 65 | C79: Perno de A°G° de 13 mm Ø x 254 mm, provisto de Tuerca y Contratuerca | F79: u | G79: 5.57 | I79: 26 | J79: =+ROUND($G79*I79,2) -> 144.82 | K79: =+'[191]Metrados'!E80 -> 0 | L79: =+ROUND($G79*K79,2) -> 0 | M79: 0 | N79: =K79 -> 0 | O79: =+ROUND($M79*N79,2) -> 0 | P79: =+M79/($G79+$H79) -> 0 | Q79: =+G79-M79 -> 5.57 | T79: 0 | U79: =$K79 -> 0 | V79: =+ROUND($T79*U79,2) -> 0 | W79: =+T79/($G79+$H79) -> 0 | X79: 0 | Y79: =$K79 -> 0 | Z79: =+ROUND($X79*Y79,2) -> 0 | AA79: =+X79/($G79+$H79) -> 0 | AB79: 2.5 | AC79: =$K79 -> 0 | AD79: =+ROUND($AB79*AC79,2) -> 0 | AE79: =+AB79/($G79+$H79) -> 0.44883303 | AF79: =+M79+O79+X79 -> 0
A80: 10.03 | B80: =+B79+1 -> 66 | C80: Perno de A°G° de 13 mm Ø x 305 mm, provisto de Tuerca y Contratuerca | F80: u | G80: 6.25 | I80: 7 | J80: =+ROUND($G80*I80,2) -> 43.75 | K80: =+'[191]Metrados'!E81 -> 21 | L80: =+ROUND($G80*K80,2) -> 131.25 | M80: 6.38 | N80: =K80 -> 21 | O80: =+ROUND($M80*N80,2) -> 133.98 | P80: =+M80/($G80+$H80) -> 1.0208 | Q80: =+(G80+H80)-M80 -> -0.13 | R80: SI | T80: 0 | U80: =$K80 -> 21 | V80: =+ROUND($T80*U80,2) -> 0 | W80: =+T80/($G80+$H80) -> 0 | X80: 4.4147 | Y80: =$K80 -> 21 | Z80: =+ROUND($X80*Y80,2) -> 92.71 | AA80: =+X80/($G80+$H80) -> 0.706352 | AB80: 2.74 | AC80: =$K80 -> 21 | AD80: =+ROUND($AB80*AC80,2) -> 57.54 | AE80: =+AB80/($G80+$H80) -> 0.4384 | AF80: =+M80+O80+X80 -> 144.7747
A81: 10.04 | B81: =+B80+1 -> 67 | C81: Perno de A°G° de 16 mm Ø x 254 mm, provisto de Tuerca y Contratuerca | F81: u | G81: 8.61 | I81: 18 | J81: =+ROUND($G81*I81,2) -> 154.98 | K81: =+'[191]Metrados'!E82 -> 172 | L81: =+ROUND($G81*K81,2) -> 1480.92 | M81: 6.9 | N81: =K81 -> 172 | O81: =+ROUND($M81*N81,2) -> 1186.8 | P81: =+M81/($G81+$H81) -> 0.80139373 | Q81: =+(G81+H81)-M81 -> 1.71 | R81: SI | T81: 0 | U81: =$K81 -> 172 | V81: =+ROUND($T81*U81,2) -> 0 | W81: =+T81/($G81+$H81) -> 0 | X81: 5.4931 | Y81: =$K81 -> 172 | Z81: =+ROUND($X81*Y81,2) -> 944.81 | AA81: =+X81/($G81+$H81) -> 0.63799071 | AB81: 4.1 | AC81: =$K81 -> 172 | AD81: =+ROUND($AB81*AC81,2) -> 705.2 | AE81: =+AB81/($G81+$H81) -> 0.47619048 | AF81: =+M81+O81+X81 -> 1199.1931
A82: 10.05 | B82: =+B81+1 -> 68 | C82: Perno de A°G° de 16 mm Ø x 305 mm, provisto de Tuerca y Contratuerca | F82: u | G82: 9.14 | I82: 18 | J82: =+ROUND($G82*I82,2) -> 164.52 | K82: =+'[191]Metrados'!E83 -> 14 | L82: =+ROUND($G82*K82,2) -> 127.96 | M82: 7.39 | N82: =K82 -> 14 | O82: =+ROUND($M82*N82,2) -> 103.46 | P82: =+M82/($G82+$H82) -> 0.80853392 | Q82: =+(G82+H82)-M82 -> 1.75 | R82: SI | T82: 0 | U82: =$K82 -> 14 | V82: =+ROUND($T82*U82,2) -> 0 | W82: =+T82/($G82+$H82) -> 0 | X82: 6.0323 | Y82: =$K82 -> 14 | Z82: =+ROUND($X82*Y82,2) -> 84.45 | AA82: =+X82/($G82+$H82) -> 0.65998906 | AB82: 4.35 | AC82: =$K82 -> 14 | AD82: =+ROUND($AB82*AC82,2) -> 60.9 | AE82: =+AB82/($G82+$H82) -> 0.47592998 | AF82: =+M82+O82+X82 -> 116.8823
A83: 10.06 | B83: =+B82+1 -> 69 | C83: Perno de A°G° de 16 mm Ø x 356 mm, provisto de Tuerca y Contratuerca | F83: u | G83: 9.82 | I83: 8 | J83: =+ROUND($G83*I83,2) -> 78.56 | K83: =+'[191]Metrados'!E84 -> 5 | L83: =+ROUND($G83*K83,2) -> 49.1 | M83: 8.97 | N83: =K83 -> 5 | O83: =+ROUND($M83*N83,2) -> 44.85 | P83: =+M83/($G83+$H83) -> 0.91344196 | Q83: =+(G83+H83)-M83 -> 0.85 | R83: SI | T83: 0 | U83: =$K83 -> 5 | V83: =+ROUND($T83*U83,2) -> 0 | W83: =+T83/($G83+$H83) -> 0 | X83: 6.6052 | Y83: =$K83 -> 5 | Z83: =+ROUND($X83*Y83,2) -> 33.03 | AA83: =+X83/($G83+$H83) -> 0.67262729 | AB83: 4.9 | AC83: =$K83 -> 5 | AD83: =+ROUND($AB83*AC83,2) -> 24.5 | AE83: =+AB83/($G83+$H83) -> 0.49898167 | AF83: =+M83+O83+X83 -> 60.4252
A84: 10.07 | B84: =+B83+1 -> 70 | C84: Perno de A°G° de 16 mm Ø x 508 mm, provisto de Tuerca y Contratuerca | F84: u | G84: 12.54 | I84: 3 | J84: =+ROUND($G84*I84,2) -> 37.62 | K84: =+'[191]Metrados'!E85 -> 104 | L84: =+ROUND($G84*K84,2) -> 1304.16 | M84: 12.16 | N84: =K84 -> 104 | O84: =+ROUND($M84*N84,2) -> 1264.64 | P84: =+M84/($G84+$H84) -> 0.96969697 | Q84: =+(G84+H84)-M84 -> 0.38 | R84: SI | T84: 0 | U84: =$K84 -> 104 | V84: =+ROUND($T84*U84,2) -> 0 | W84: =+T84/($G84+$H84) -> 0 | X84: 8.5935 | Y84: =$K84 -> 104 | Z84: =+ROUND($X84*Y84,2) -> 893.72 | AA84: =+X84/($G84+$H84) -> 0.68528708 | AB84: 9 | AC84: =$K84 -> 104 | AD84: =+ROUND($AB84*AC84,2) -> 936 | AE84: =+AB84/($G84+$H84) -> 0.71770335 | AF84: =+M84+O84+X84 -> 1285.3935
A85: 10.08 | B85: =+B84+1 -> 71 | C85: Perno Doble Armado de A°G° de 16 mm Ø x 508 mm, provisto de 4 Tuercas y 4 Contratuercas | F85: u | G85: 18.18 | I85: 380 | J85: =+ROUND($G85*I85,2) -> 6908.4 | K85: =+'[191]Metrados'!E86 -> 107 | L85: =+ROUND($G85*K85,2) -> 1945.26 | M85: 11.98 | N85: =K85 -> 107 | O85: =+ROUND($M85*N85,2) -> 1281.86 | P85: =+M85/($G85+$H85) -> 0.6589659 | Q85: =+(G85+H85)-M85 -> 6.2 | R85: SI | T85: 0 | U85: =$K85 -> 107 | V85: =+ROUND($T85*U85,2) -> 0 | W85: =+T85/($G85+$H85) -> 0 | X85: 11.5591 | Y85: =$K85 -> 107 | Z85: =+ROUND($X85*Y85,2) -> 1236.82 | AA85: =+X85/($G85+$H85) -> 0.63581408 | AB85: 8 | AC85: =$K85 -> 107 | AD85: =+ROUND($AB85*AC85,2) -> 856 | AE85: =+AB85/($G85+$H85) -> 0.440044 | AF85: =+M85+O85+X85 -> 1305.3991
A86: 10.09 | B86: =+B85+1 -> 72 | C86: Perno Ojo de A°G° de 16 mm Ø x 254 mm, provisto de Tuerca y Contratuerca | F86: u | G86: 13.11 | I86: 61 | J86: =+ROUND($G86*I86,2) -> 799.71 | K86: =+'[191]Metrados'!E87 -> 70 | L86: =+ROUND($G86*K86,2) -> 917.7 | M86: 8.36 | N86: =K86 -> 70 | O86: =+ROUND($M86*N86,2) -> 585.2 | P86: =+M86/($G86+$H86) -> 0.63768116 | Q86: =+(G86+H86)-M86 -> 4.75 | R86: SI | T86: 0 | U86: =$K86 -> 70 | V86: =+ROUND($T86*U86,2) -> 0 | W86: =+T86/($G86+$H86) -> 0 | X86: 8.5598 | Y86: =$K86 -> 70 | Z86: =+ROUND($X86*Y86,2) -> 599.19 | AA86: =+X86/($G86+$H86) -> 0.65292143 | AB86: 7 | AC86: =$K86 -> 70 | AD86: =+ROUND($AB86*AC86,2) -> 490 | AE86: =+AB86/($G86+$H86) -> 0.53394355 | AF86: =+M86+O86+X86 -> 602.1198
A87: 10.1 | B87: =+B86+1 -> 73 | C87: Perno Ojo de A°G° de 16 mm Ø x 305 mm, provisto de Tuerca y Contratuerca | F87: u | G87: 14.35 | I87: 47 | J87: =+ROUND($G87*I87,2) -> 674.45 | K87: =+'[191]Metrados'!E88 -> 21 | L87: =+ROUND($G87*K87,2) -> 301.35 | M87: 9.12 | N87: =K87 -> 21 | O87: =+ROUND($M87*N87,2) -> 191.52 | P87: =+M87/($G87+$H87) -> 0.63554007 | Q87: =+(G87+H87)-M87 -> 5.23 | R87: SI | T87: 0 | U87: =$K87 -> 21 | V87: =+ROUND($T87*U87,2) -> 0 | W87: =+T87/($G87+$H87) -> 0 | X87: 9.3012 | Y87: =$K87 -> 21 | Z87: =+ROUND($X87*Y87,2) -> 195.33 | AA87: =+X87/($G87+$H87) -> 0.64816725 | AB87: 7.5 | AC87: =$K87 -> 21 | AD87: =+ROUND($AB87*AC87,2) -> 157.5 | AE87: =+AB87/($G87+$H87) -> 0.52264808 | AF87: =+M87+O87+X87 -> 209.9412
A88: 10.11 | B88: =+B87+1 -> 74 | C88: Perno Ojo de A°G° de 16 mm Ø x 356 mm, provisto de Tuerca y Contratuerca | F88: u | G88: 14.6 | I88: 9 | J88: =+ROUND($G88*I88,2) -> 131.4 | K88: =+'[191]Metrados'!E89 -> 0 | L88: =+ROUND($G88*K88,2) -> 0 | M88: 0 | N88: =K88 -> 0 | O88: =+ROUND($M88*N88,2) -> 0 | P88: =+M88/($G88+$H88) -> 0 | Q88: =+G88-M88 -> 14.6 | T88: 0 | U88: =$K88 -> 0 | V88: =+ROUND($T88*U88,2) -> 0 | W88: =+T88/($G88+$H88) -> 0 | X88: 0 | Y88: =$K88 -> 0 | Z88: =+ROUND($X88*Y88,2) -> 0 | AA88: =+X88/($G88+$H88) -> 0 | AB88: 0 | AC88: =$K88 -> 0 | AD88: =+ROUND($AB88*AC88,2) -> 0 | AE88: =+AB88/($G88+$H88) -> 0 | AF88: =+M88+O88+X88 -> 0
A89: 10.12 | B89: =+B88+1 -> 75 | C89: Tuerca-Ojo para Perno de 16 mm Ø | F89: u | G89: 11.17 | I89: 38 | J89: =+ROUND($G89*I89,2) -> 424.46 | K89: =+'[191]Metrados'!E90 -> 112 | L89: =+ROUND($G89*K89,2) -> 1251.04 | M89: 8.69 | N89: =K89 -> 112 | O89: =+ROUND($M89*N89,2) -> 973.28 | P89: =+M89/($G89+$H89) -> 0.77797672 | Q89: =+(G89+H89)-M89 -> 2.48 | R89: SI | T89: 0 | U89: =$K89 -> 112 | V89: =+ROUND($T89*U89,2) -> 0 | W89: =+T89/($G89+$H89) -> 0 | X89: 6.2008 | Y89: =$K89 -> 112 | Z89: =+ROUND($X89*Y89,2) -> 694.49 | AA89: =+X89/($G89+$H89) -> 0.55512981 | AB89: 5.4 | AC89: =$K89 -> 112 | AD89: =+ROUND($AB89*AC89,2) -> 604.8 | AE89: =+AB89/($G89+$H89) -> 0.48343778 | AF89: =+M89+O89+X89 -> 988.1708
A90: 10.13 | B90: =+B89+1 -> 76 | C90: Tirafondo de A°G° de 13 mm ø x 102 mm de longitud | F90: u | G90: 2.74 | I90: 4 | J90: =+ROUND($G90*I90,2) -> 10.96 | K90: =+'[191]Metrados'!E91 -> 0 | L90: =+ROUND($G90*K90,2) -> 0 | M90: 0 | N90: =K90 -> 0 | O90: =+ROUND($M90*N90,2) -> 0 | P90: =+M90/($G90+$H90) -> 0 | Q90: =+G90-M90 -> 2.74 | T90: 0 | U90: =$K90 -> 0 | V90: =+ROUND($T90*U90,2) -> 0 | W90: =+T90/($G90+$H90) -> 0 | X90: 0 | Y90: =$K90 -> 0 | Z90: =+ROUND($X90*Y90,2) -> 0 | AA90: =+X90/($G90+$H90) -> 0 | AB90: 0 | AC90: =$K90 -> 0 | AD90: =+ROUND($AB90*AC90,2) -> 0 | AE90: =+AB90/($G90+$H90) -> 0 | AF90: =+M90+O90+X90 -> 0
A91: 10.14 | B91: =+B90+1 -> 77 | C91: Brazo-Soporte (Riostra) de Perfil Angular de A°G° de 38 x 38 x 5 mm y 710 mm longitud | F91: u | G91: 22.46 | I91: 13 | J91: =+ROUND($G91*I91,2) -> 291.98 | K91: =+'[191]Metrados'!E92 -> 33 | L91: =+ROUND($G91*K91,2) -> 741.18 | M91: 14.93 | N91: =K91 -> 33 | O91: =+ROUND($M91*N91,2) -> 492.69 | P91: =+M91/($G91+$H91) -> 0.66473731 | Q91: =+(G91+H91)-M91 -> 7.53 | R91: SI | T91: 0 | U91: =$K91 -> 33 | V91: =+ROUND($T91*U91,2) -> 0 | W91: =+T91/($G91+$H91) -> 0 | X91: 13.0756 | Y91: =$K91 -> 33 | Z91: =+ROUND($X91*Y91,2) -> 431.49 | AA91: =+X91/($G91+$H91) -> 0.58217275 | AB91: 23 | AC91: =$K91 -> 33 | AD91: =+ROUND($AB91*AC91,2) -> 759 | AE91: =+AB91/($G91+$H91) -> 1.0240427 | AF91: =+M91+O91+X91 -> 520.6956
A92: 10.15 | B92: =+B91+1 -> 78 | C92: Arandela Cuadrada Plana de A° G°, 57 x 57 x 5 mm, Agujero de 18 mm Ø | F92: u | G92: 1.67 | I92: 618 | J92: =+ROUND($G92*I92,2) -> 1032.06 | K92: =+'[191]Metrados'!E93 -> 518 | L92: =+ROUND($G92*K92,2) -> 865.06 | M92: 1.28 | N92: =K92 -> 518 | O92: =+ROUND($M92*N92,2) -> 663.04 | P92: =+M92/($G92+$H92) -> 0.76646707 | Q92: =+(G92+H92)-M92 -> 0.39 | R92: SI | T92: 0 | U92: =$K92 -> 518 | V92: =+ROUND($T92*U92,2) -> 0 | W92: =+T92/($G92+$H92) -> 0 | X92: 1.0447 | Y92: =$K92 -> 518 | Z92: =+ROUND($X92*Y92,2) -> 541.15 | AA92: =+X92/($G92+$H92) -> 0.62556886 | AB92: 1.5 | AC92: =$K92 -> 518 | AD92: =+ROUND($AB92*AC92,2) -> 777 | AE92: =+AB92/($G92+$H92) -> 0.89820359 | AF92: =+M92+O92+X92 -> 665.3647
A93: 10.16 | B93: =+B92+1 -> 79 | C93: Arandela Cuadrada curva de A° G°, 57 x 57 x 5 mm, Agujero de 18 mm Ø | F93: u | G93: 1.67 | I93: 979 | J93: =+ROUND($G93*I93,2) -> 1634.93 | K93: =+'[191]Metrados'!E94 -> 772 | L93: =+ROUND($G93*K93,2) -> 1289.24 | M93: 1.22 | N93: =K93 -> 772 | O93: =+ROUND($M93*N93,2) -> 941.84 | P93: =+M93/($G93+$H93) -> 0.73053892 | Q93: =+(G93+H93)-M93 -> 0.45 | R93: SI | T93: 0 | U93: =$K93 -> 772 | V93: =+ROUND($T93*U93,2) -> 0 | W93: =+T93/($G93+$H93) -> 0 | X93: 1.0447 | Y93: =$K93 -> 772 | Z93: =+ROUND($X93*Y93,2) -> 806.51 | AA93: =+X93/($G93+$H93) -> 0.62556886 | AB93: 1.5 | AC93: =$K93 -> 772 | AD93: =+ROUND($AB93*AC93,2) -> 1158 | AE93: =+AB93/($G93+$H93) -> 0.89820359 | AF93: =+M93+O93+X93 -> 944.1047
A94: 10.17 | B94: =+B93+1 -> 80 | C94: Plantillas para Identificación y/o codificación de Postes (Peligro, Identificación y/o codificación y Fases) | F94: Jgo. | G94: 23.08 | I94: 21 | J94: =+ROUND($G94*I94,2) -> 484.68 | K94: =+'[191]Metrados'!E95 -> 22 | L94: =+ROUND($G94*K94,2) -> 507.76 | M94: 0 | N94: =K94 -> 22 | O94: =+ROUND($M94*N94,2) -> 0 | P94: =+M94/($G94+$H94) -> 0 | Q94: =+G94-M94 -> 23.08 | T94: 0 | U94: =$K94 -> 22 | V94: =+ROUND($T94*U94,2) -> 0 | W94: =+T94/($G94+$H94) -> 0 | X94: 0 | Y94: =$K94 -> 22 | Z94: =+ROUND($X94*Y94,2) -> 0 | AA94: =+X94/($G94+$H94) -> 0 | AB94: 0 | AC94: =$K94 -> 22 | AD94: =+ROUND($AB94*AC94,2) -> 0 | AE94: =+AB94/($G94+$H94) -> 0 | AF94: =+M94+O94+X94 -> 0
A95: 10.18 | B95: =+B94+1 -> 81 | C95: Placa de Señal de Peligro y accesorios de fijación | F95: u | G95: 18.24 | I95: 9 | J95: =+ROUND($G95*I95,2) -> 164.16 | K95: =+'[191]Metrados'!E96 -> 0 | L95: =+ROUND($G95*K95,2) -> 0 | M95: 0 | N95: =K95 -> 0 | O95: =+ROUND($M95*N95,2) -> 0 | P95: =+M95/($G95+$H95) -> 0 | Q95: =+G95-M95 -> 18.24 | T95: 0 | U95: =$K95 -> 0 | V95: =+ROUND($T95*U95,2) -> 0 | W95: =+T95/($G95+$H95) -> 0 | X95: 0 | Y95: =$K95 -> 0 | Z95: =+ROUND($X95*Y95,2) -> 0 | AA95: =+X95/($G95+$H95) -> 0 | AB95: 0 | AC95: =$K95 -> 0 | AD95: =+ROUND($AB95*AC95,2) -> 0 | AE95: =+AB95/($G95+$H95) -> 0 | AF95: =+M95+O95+X95 -> 0
A96: 10.19 | B96: =+B95+1 -> 82 | C96: Placa de Identificación y/o codificación de Estructura y accesorios de fijación | F96: u | G96: 16.84 | I96: 9 | J96: =+ROUND($G96*I96,2) -> 151.56 | K96: =+'[191]Metrados'!E97 -> 0 | L96: =+ROUND($G96*K96,2) -> 0 | M96: 0 | N96: =K96 -> 0 | O96: =+ROUND($M96*N96,2) -> 0 | P96: =+M96/($G96+$H96) -> 0 | Q96: =+G96-M96 -> 16.84 | T96: 0 | U96: =$K96 -> 0 | V96: =+ROUND($T96*U96,2) -> 0 | W96: =+T96/($G96+$H96) -> 0 | X96: 0 | Y96: =$K96 -> 0 | Z96: =+ROUND($X96*Y96,2) -> 0 | AA96: =+X96/($G96+$H96) -> 0 | AB96: 0 | AC96: =$K96 -> 0 | AD96: =+ROUND($AB96*AC96,2) -> 0 | AE96: =+AB96/($G96+$H96) -> 0 | AF96: =+M96+O96+X96 -> 0
A97: 10.2 | B97: =+B96+1 -> 83 | C97: Placa de Secuencia de Fases y accesorios de fijación | F97: u | G97: 18.78 | I97: 9 | J97: =+ROUND($G97*I97,2) -> 169.02 | K97: =+'[191]Metrados'!E98 -> 0 | L97: =+ROUND($G97*K97,2) -> 0 | M97: 0 | N97: =K97 -> 0 | O97: =+ROUND($M97*N97,2) -> 0 | P97: =+M97/($G97+$H97) -> 0 | Q97: =+G97-M97 -> 18.78 | T97: 0 | U97: =$K97 -> 0 | V97: =+ROUND($T97*U97,2) -> 0 | W97: =+T97/($G97+$H97) -> 0 | X97: 0 | Y97: =$K97 -> 0 | Z97: =+ROUND($X97*Y97,2) -> 0 | AA97: =+X97/($G97+$H97) -> 0 | AB97: 0 | AC97: =$K97 -> 0 | AD97: =+ROUND($AB97*AC97,2) -> 0 | AE97: =+AB97/($G97+$H97) -> 0 | AF97: =+M97+O97+X97 -> 0
A98: 10.21 | B98: =+B97+1 -> 84 | C98: Perno Ojo de A°G° de 16 mm Ø x 203 mm, provisto de Tuerca y Contratuerca | F98: u | H98: =+G86*0.9 -> 11.799 | J98: =+ROUND($G98*I98,2) -> 0 | K98: =+'[191]Metrados'!E99 -> 24 | L98: =+ROUND($H98*K98,2) -> 283.18 | M98: 7.45 | N98: =K98 -> 24 | O98: =+ROUND($M98*N98,2) -> 178.8 | P98: =+M98/($G98+$H98) -> 0.63140944 | Q98: =+(G98+H98)-M98 -> 4.349 | R98: SI | T98: 0 | U98: =$K98 -> 24 | V98: =+ROUND($T98*U98,2) -> 0 | W98: =+T98/($G98+$H98) -> 0 | X98: 8.1217 | Y98: =$K98 -> 24 | Z98: =+ROUND($X98*Y98,2) -> 194.92 | AA98: =+X98/($G98+$H98) -> 0.68833799 | AB98: 6.7 | AC98: =$K98 -> 24 | AD98: =+ROUND($AB98*AC98,2) -> 160.8 | AE98: =+AB98/($G98+$H98) -> 0.56784473 | AF98: =+M98+O98+X98 -> 194.3717
A99: 10.22 | B99: =+B98+1 -> 85 | C99: Soporte separador de vertice de postes de A°G° fabricado con platina de 76 X 6,4 mm | F99: u | H99: 38 | J99: =+ROUND($G99*I99,2) -> 0 | K99: =+[191]Metrados!E100 -> 2 | L99: =+ROUND($H99*K99,2) -> 76 | M99: 20.19 | N99: =K99 -> 2 | O99: =+ROUND($M99*N99,2) -> 40.38 | P99: =+M99/($G99+$H99) -> 0.53131579 | Q99: =+(G99+H99)-M99 -> 17.81 | R99: SI | T99: 0 | U99: =$K99 -> 2 | V99: =+ROUND($T99*U99,2) -> 0 | W99: =+T99/($G99+$H99) -> 0 | X99: 25.5109 | Y99: =$K99 -> 2 | Z99: =+ROUND($X99*Y99,2) -> 51.02 | AA99: =+X99/($G99+$H99) -> 0.67133947 | AB99: 19 | AC99: =$K99 -> 2 | AD99: =+ROUND($AB99*AC99,2) -> 38 | AE99: =+AB99/($G99+$H99) -> 0.5 | AF99: =+M99+O99+X99 -> 86.0809
A100: 10.23 | B100: =+B99+1 -> 86 | C100: Braquete de A°G° para soporte de aislador tipo Line Post en cabea de poste | F100: u | H100: 50 | J100: =+ROUND($G100*I100,2) -> 0 | K100: =+'[191]Metrados'!E101 -> 75 | L100: =+ROUND($H100*K100,2) -> 3750 | M100: 55 | N100: =K100 -> 75 | O100: =+ROUND($M100*N100,2) -> 4125 | P100: =+M100/($G100+$H100) -> 1.1 | Q100: =+(G100+H100)-M100 -> -5 | R100: NO | T100: 0 | U100: =$K100 -> 75 | V100: =+ROUND($T100*U100,2) -> 0 | W100: =+T100/($G100+$H100) -> 0 | X100: 61.7721 | Y100: =$K100 -> 75 | Z100: =+ROUND($X100*Y100,2) -> 4632.91 | AA100: =+X100/($G100+$H100) -> 1.235442 | AB100: 45 | AC100: =$K100 -> 75 | AD100: =+ROUND($AB100*AC100,2) -> 3375 | AE100: =+AB100/($G100+$H100) -> 0.9 | AF100: =+M100+O100+X100 -> 4241.7721
B101: =+B100+1 -> 87 | E101: =+"SUB-TOTAL "&A77&": " -> SUB-TOTAL 10: | J101: =+SUM(J78:J100) -> 13536.76 | L101: =+SUM(L78:L100) -> 15148.54 | M101: 0 | N101: =K101 -> 0 | O101: =+SUM(O78:O100) -> 12317.56 | Q101: =+G101-M101 -> 0 | T101: 0 | U101: =$K101 -> 0 | V101: =+SUM(V78:V100) -> 0 | X101: 0 | Y101: =$K101 -> 0 | Z101: =+SUM(Z78:Z100) -> 11538.2 | AB101: 0 | AC101: =$K101 -> 0 | AD101: =+SUM(AD78:AD100) -> 10216.34 | AF101: =+M101+O101+X101 -> 12317.56
A102: 11 | B102: =+B101+1 -> 88 | C102: RETENIDAS Y ANCLAJES | M102: 0 | N102: =K102 -> 0 | Q102: =+G102-M102 -> 0 | T102: 0 | U102: =$K102 -> 0 | X102: 0 | Y102: =$K102 -> 0 | AB102: 0 | AC102: =$K102 -> 0 | AF102: =+M102+O102+X102 -> 0
A103: 11.01 | B103: =+B102+1 -> 89 | C103: Cable de Acero Grado Siemens Martin, de 10 mm Ø, 7 hilos | F103: m | G103: 4.31 | I103: 881 | J103: =+ROUND($G103*I103,2) -> 3797.11 | K103: =+'[191]Metrados'!E104 -> 0 | L103: =+ROUND($G103*K103,2) -> 0 | M103: 0 | N103: =K103 -> 0 | O103: =+ROUND($M103*N103,2) -> 0 | P103: =+M103/($G103+$H103) -> 0 | Q103: =+G103-M103 -> 4.31 | T103: 0 | U103: =$K103 -> 0 | V103: =+ROUND($T103*U103,2) -> 0 | W103: =+T103/($G103+$H103) -> 0 | X103: 0 | Y103: =$K103 -> 0 | Z103: =+ROUND($X103*Y103,2) -> 0 | AA103: =+X103/($G103+$H103) -> 0 | AB103: 3.1 | AC103: =$K103 -> 0 | AD103: =+ROUND($AB103*AC103,2) -> 0 | AE103: =+AB103/($G103+$H103) -> 0.71925754 | AF103: =+M103+O103+X103 -> 0
A104: 11.02 | B104: =+B103+1 -> 90 | C104: Varilla de Anclaje de A°G° de 16 mm Ø x 2,40 m, provisto de Ojal Guardacabo en un extremo; Tuerca y Contratuerca en el otro | F104: u | G104: 46.85 | I104: 66 | J104: =+ROUND($G104*I104,2) -> 3092.1 | K104: =+'[191]Metrados'!E105 -> 83 | L104: =+ROUND($G104*K104,2) -> 3888.55 | M104: 34.96 | N104: =K104 -> 83 | O104: =+ROUND($M104*N104,2) -> 2901.68 | P104: =+M104/($G104+$H104) -> 0.74621131 | Q104: =+(G104+H104)-M104 -> 11.89 | R104: SI | T104: 0 | U104: =$K104 -> 83 | V104: =+ROUND($T104*U104,2) -> 0 | W104: =+T104/($G104+$H104) -> 0 | X104: 32.0487 | Y104: =$K104 -> 83 | Z104: =+ROUND($X104*Y104,2) -> 2660.04 | AA104: =+X104/($G104+$H104) -> 0.68407044 | AB104: 27.5 | AC104: =$K104 -> 83 | AD104: =+ROUND($AB104*AC104,2) -> 2282.5 | AE104: =+AB104/($G104+$H104) -> 0.58697972 | AF104: =+M104+O104+X104 -> 2968.6887
A105: 11.03 | B105: =+B104+1 -> 91 | C105: Mordaza Preformada de A°G° para Cable de 10 mm Ø | F105: u | G105: 11.69 | I105: 208 | J105: =+ROUND($G105*I105,2) -> 2431.52 | K105: =+'[191]Metrados'!E106 -> 166 | L105: =+ROUND($G105*K105,2) -> 1940.54 | M105: 8.5 | N105: =K105 -> 166 | O105: =+ROUND($M105*N105,2) -> 1411 | P105: =+M105/($G105+$H105) -> 0.72711719 | Q105: =+(G105+H105)-M105 -> 3.19 | R105: SI | T105: 8.20 | U105: =$K105 -> 166 | V105: =+ROUND($T105*U105,2) -> 1361.2 | W105: =+T105/($G105+$H105) -> 0.70145423 | X105: 7.1781 | Y105: =$K105 -> 166 | Z105: =+ROUND($X105*Y105,2) -> 1191.56 | AA105: =+X105/($G105+$H105) -> 0.61403764 | AB105: 7.5 | AC105: =$K105 -> 166 | AD105: =+ROUND($AB105*AC105,2) -> 1245 | AE105: =+AB105/($G105+$H105) -> 0.64157399 | AF105: =+M105+O105+X105 -> 1426.6781
A106: 11.04 | B106: =+B105+1 -> 92 | C106: Alambre de Acero N° 14 para Entorchado | F106: m | G106: 0.71 | I106: 312 | J106: =+ROUND($G106*I106,2) -> 221.52 | K106: =+'[191]Metrados'!E107 -> 124.5 | L106: =+ROUND($G106*K106,2) -> 88.4 | M106: 0.4 | N106: =K106 -> 124.5 | O106: =+ROUND($M106*N106,2) -> 49.8 | P106: =+M106/($G106+$H106) -> 0.56338028 | Q106: =+(G106+H106)-M106 -> 0.31 | S106: NO | T106: 0 | U106: =$K106 -> 124.5 | V106: =+ROUND($T106*U106,2) -> 0 | W106: =+T106/($G106+$H106) -> 0 | X106: 0.2359 | Y106: =$K106 -> 124.5 | Z106: =+ROUND($X106*Y106,2) -> 29.37 | AA106: =+X106/($G106+$H106) -> 0.33225352 | AB106: 0.6 | AC106: =$K106 -> 124.5 | AD106: =+ROUND($AB106*AC106,2) -> 74.7 | AE106: =+AB106/($G106+$H106) -> 0.84507042 | AF106: =+M106+O106+X106 -> 50.4359
A107: 11.05 | B107: =+B106+1 -> 93 | C107: Arandela de Anclaje de A°G°, 102 x 102 x 6,35 mm, Agujero de 18 mmø | F107: u | G107: 5.46 | I107: 66 | J107: =+ROUND($G107*I107,2) -> 360.36 | K107: =+'[191]Metrados'!E108 -> 83 | L107: =+ROUND($G107*K107,2) -> 453.18 | M107: 4.56 | N107: =K107 -> 83 | O107: =+ROUND($M107*N107,2) -> 378.48 | P107: =+M107/($G107+$H107) -> 0.83516484 | Q107: =+(G107+H107)-M107 -> 0.9 | R107: SI | T107: 0 | U107: =$K107 -> 83 | V107: =+ROUND($T107*U107,2) -> 0 | W107: =+T107/($G107+$H107) -> 0 | X107: 4.4147 | Y107: =$K107 -> 83 | Z107: =+ROUND($X107*Y107,2) -> 366.42 | AA107: =+X107/($G107+$H107) -> 0.80855311 | AB107: 5 | AC107: =$K107 -> 83 | AD107: =+ROUND($AB107*AC107,2) -> 415 | AE107: =+AB107/($G107+$H107) -> 0.91575092 | AF107: =+M107+O107+X107 -> 387.4547
...

Sheet FP LP
B3: FORMULA POLINÓMICA
C6: PROYECTO :
C7: AMPLIACIÓN DEL SERVICIO DE ENERGÍA ELÉCTRICA EN LA PROVINCIA DEL SANTA Y EN EL DISTRITO DE PAMPAROMAS – DEPARTAMENTO DE ANCASH”
C9: LINEAS PRIMARIAS
C10: PRESUPUESTO BASE S/ | D10: =+'RES-LP'!H18 -> #REF! | K10: =D10=SUM(G13:G27) -> #REF!
B12: Nº | C12: ELEMENTO REPRESENTATIVO | D12: INDICE | E12: SIMBOLO | F12: SIMBOLO MONOMIO | G12: MONTO | H12: INCIDENCIA | I12: % PARCIAL | J12: COEFICIENTE
B13: 1 | C13: POSTES DE MADERA IMPORTADA | D13: 042 | E13: PM | F13: PC | G13: =+LP!L32 -> 0 | H13: =ROUND(G13/$D$10,3) -> #REF! | I13: =ROUND(G13/SUM($G$13:$G$16),4) -> 0 | J13: =ROUND(SUM(H13:H16),3) -> #REF!
C14: CRUCETAS DE MADERA | D14: 043 | E14: CM | G14: =+LP!L22 -> 3578 | H14: =ROUND(G14/$D$10,3) -> #REF! | I14: =ROUND(G14/SUM($G$13:$G$16),4) -> 0.0139
C15: POSTES DE CONCRETO | D15: 062 | E15: PC | G15: =+LP!L29+LP!L36 -> 218234.24 | H15: =ROUND(G15/$D$10,3-0.1) -> #REF! | I15: =ROUND(G15/SUM($G$13:$G$16),4) -> 0.8481
C16: OTROS MATERIALES DE CONCRETO ARMADO | D16: 062 | E16: CC | G16: =+LP!L42 -> 35519.2 | H16: =ROUND(G16/$D$10,3) -> #REF! | I16: =ROUND(G16/SUM($G$13:$G$16),4) -> 0.138
B17: 2 | C17: CONDUCTORES DE AAAC Y ACCESORIOS | D17: 030 | E17: DI | F17: DI | G17: =+LP!L56+LP!L73 -> 133692.72 | H17: =ROUND(G17/$D$10,3) -> #REF! | I17: =ROUND(G17/SUM($G$17:$G$18),4) -> 0.9068 | J17: =ROUND(SUM(H17:H18),3) -> #REF!
C18: EQUIPOS DE PROTECCIÓN | D18: 011 | E18: AE1 | G18: =+LP!L136 -> 13745.66 | H18: =ROUND(G18/$D$10,3) -> #REF! | I18: =ROUND(G18/SUM($G$17:$G$18),4) -> 0.0932
B19: 3 | C19: AISLADORES Y ACCESORIOS | D19: 011 | E19: AE2 | F19: AE2 | G19: =+LP!L48+LP!L52 -> 93781.25 | H19: =ROUND(G19/$D$10,3) -> #REF! | I19: =ROUND(G19/SUM($G$19:$G$24),4) -> 0.3362 | J19: =ROUND(SUM(H19:H24),3) -> #REF!
C20: RETENIDAS Y ANCLAJES | D20: 002 | E20: FE | G20: =+LP!L117 -> 31585.24 | H20: =ROUND(G20/$D$10,3) -> #REF! | I20: =ROUND(G20/SUM($G$19:$G$24),4) -> 0.1132
C21: FERRETERIA PARA POSTES Y CRUCETAS | D21: 002 | E21: FP | G21: =+LP!L101 -> 15148.54 | H21: =ROUND(G21/$D$10,3) -> #REF! | I21: =ROUND(G21/SUM($G$19:$G$24),4) -> 0.0543
C22: CONDUCTOR DE COBRE | D22: 006 | E22: CU | G22: =+LP!L76 -> 40485.12 | H22: =ROUND(G22/$D$10,3) -> #REF! | I22: =ROUND(G22/SUM($G$19:$G$24),4) -> 0.1451
C23: MATERIAL PARA PUESTA A TIERRA | D23: 006 | E23: PT | G23: =+LP!L129 -> 11437.24 | H23: =ROUND(G23/$D$10,3) -> #REF! | I23: =ROUND(G23/SUM($G$19:$G$24),4) -> 0.041
C24: TRAMO SUBTERRANEO | D24: 006 | E24: TS | G24: =+LP!L153 -> 86522.98 | H24: =ROUND(G24/$D$10,3) -> #REF! | I24: =ROUND(G24/SUM($G$19:$G$24),4) -> 0.3102
B25: 4 | C25: MONTAJE ELECTROMECANICO | D25: 047 | E25: J | F25: J | G25: =+LP!#REF! -> #REF! | H25: =ROUND(G25/$D$10,3) -> #REF! | I25: =ROUND(G25/($G$25+$G$26),4) -> #REF! | J25: =ROUND(SUM(H25:H26),3) -> #REF!
C26: TRANSPORTE | D26: 032 | E26: FT | G26: =+LP!#REF! -> #REF! | H26: =ROUND(G26/$D$10,3) -> #REF! | I26: =ROUND(G26/($G$25+$G$26),4) -> #REF!
B27: 5 | C27: GASTOS GENERALES Y UTILIDADES | D27: 039 | E27: GG | F27: GU | G27: =+'RES-LP'!H16+'RES-LP'!H17 -> #REF! | H27: =ROUND(G27/$D$10,3) -> #REF! | I27: =+G27/G27 -> #REF! | J27: =ROUND(SUM(H27),3) -> #REF!
B29: K= | C29: =J13&" PCr/PCo + "&J17&" DIr/DIo + "&J19&" AE2r/AE2o+ "&J25&" Jr/Jo + "&J27&" GUr/GUo" -> #REF!
B32: NOTAS:
B34: 1.- | C34: En la fórmula los sub-indices "o" de cada símbolo corresponden al indice de precios según (CREPCO) a la
C35: fecha de Elaboración del Presupuesto (Presupuesto Base) y los sub-indices "r" al indice de precios al
C36: momento de reajuste o fecha de valorización
B37: 2.- | C37: En el caso de los monomios compuestos por varios indices se ha considerado para efecto de denominación
C38: el símbolo que tiene mayor porcentaje de incidencia
B39: 3.- | C39: En caso de cambios en el suministro se deberá actualizar la formula polinómica.
H46: =+IF(SUM(H13:H27)=1,"OK","X") -> #REF! | I46: =+IF(SUM(I13:I27)=5,"OK","X") -> #REF! | J46: =+IF(SUM(J13:J27)=1,"OK","X") -> #REF!

Sheet RES-RP
B2: RESUMEN PRESUPUESTO DE OBRA
B4: AMPLIACIÓN DEL SERVICIO DE ENERGÍA ELÉCTRICA EN LA PROVINCIA DEL SANTA Y EN EL DISTRITO DE PAMPAROMAS – DEPARTAMENTO DE ANCASH
B6: UBICACIÓN | C6: : | D6: ANCASH
B7: SECCIÓN II | C7: : | D7: REDES PRIMARIAS | H7: Fecha: 30-May-2022
H8: T.C. (S/./US$): 3,642
B9: ITEM | C9: DESCRIPCION | G9: PRESUPUESTO CONTRATO | H9: PRESUPUESTO ESTUDIO DEFINIVO | I9: ADICIONALES | K9: DEDUCTIVOS
I10: MAYORES METRADOS | J10: PARTIDAS NUEVAS | K10: MENOR METRADO | L10: DEDUCTIVO VINCULANTE
B12: A | D12: SUMINISTRO DE MATERIALES | G12: =+RP!K136 -> 202256.75 | H12: =+RP!M136 -> 223205.59 | I12: =+RP!#REF! -> #REF! | J12: =+RP!#REF! -> #REF! | K12: =+RP!#REF! -> #REF! | L12: =+RP!#REF! -> #REF!
B13: B | D13: MONTAJE ELECTROMECANICO | G13: =+RP!#REF! -> #REF! | H13: =+RP!#REF! -> #REF! | I13: =+RP!#REF! -> #REF! | J13: =+RP!#REF! -> #REF! | K13: =+RP!#REF! -> #REF! | L13: =+RP!#REF! -> #REF!
B14: C | D14: TRANSPORTE DE MATERIALES | G14: =+RP!#REF! -> #REF! | H14: =+RP!#REF! -> #REF! | I14: =+RP!#REF! -> #REF! | J14: =+RP!#REF! -> #REF! | K14: =+RP!#REF! -> #REF! | L14: =+RP!#REF! -> #REF!
B15: D | D15: TOTAL COSTO DIRECTO | G15: =+SUM(G12:G14) -> #REF! | H15: =+SUM(H12:H14) -> #REF! | I15: =+SUM(I12:I14) -> #REF! | J15: =+SUM(J12:J14) -> #REF! | K15: =+SUM(K12:K14) -> #REF! | L15: =+SUM(L12:L14) -> #REF!
B16: E | D16: GASTOS GENERALES (10.12%) | G16: =ROUND(G15*10.12%,2) -> #REF! | H16: =ROUND(H15*10.12%,2) -> #REF! | I16: =ROUND(I15*10.12%,2) -> #REF! | J16: =ROUND(J15*10.12%,2) -> #REF! | K16: =ROUND(K15*10.12%,2) -> #REF! | L16: =ROUND(L15*10.12%,2) -> #REF!
B17: F | D17: UTILIDADES (3%) | G17: =ROUND(G15*3%,2) -> #REF! | H17: =ROUND(H15*3%,2) -> #REF! | I17: =ROUND(I15*3%,2) -> #REF! | J17: =ROUND(J15*3%,2) -> #REF! | K17: =ROUND(K15*3%,2) -> #REF! | L17: =ROUND(L15*3%,2) -> #REF!
B18: G | D18: COSTO TOTAL S/. (No incluye I.G.V.) | G18: =G17+G16+G15 -> #REF! | H18: =H17+H16+H15 -> #REF! | I18: =I17+I16+I15 -> #REF! | J18: =J17+J16+J15 -> #REF! | K18: =K17+K16+K15 -> #REF! | L18: =L17+L16+L15 -> #REF! | M18: =+H18-G18 -> #REF!
D20: INCIDENCIA % | G20: =+G18/G18 -> #REF! | H20: =+H18/$G$18 -> #REF! | I20: =+I18/$G$18 -> #REF! | J20: =+J18/$G$18 -> #REF! | K20: =+K18/$G$18 -> #REF! | L20: =+L18/$G$18 -> #REF!
H22: =+H18-I18+K18-J18 -> #REF! | K22: =+G12-H12+I12+J12-K12 -> #REF!
H23: =+G18-H22 -> #REF! | K23: =+G13-H13+I13+J13-K13 -> #REF!
K24: =+G14-H14+I14+J14-K14 -> #REF!
K25: =+G15-H15+I15+J15-K15 -> #REF!

Sheet RP
B6: COMPARATIVO DE PRECIOS
B8: OBRA | E8: : | F8: AMPLIACIÓN DEL SERVICIO DE ENERGÍA ELÉCTRICA EN LA PROVINCIA DEL SANTA Y EN EL DISTRITO DE PAMPAROMAS – DEPARTAMENTO DE ANCASH
B9: DEPARTAMENTO | E9: : | F9: ANCASH
B10: SECCIÓN II | E10: : | F10: REDES PRIMARIAS
B12: ITEM | C12: DESCRIPCIÓN DE PARTIDAS | G12: UNID. | H12: Precio de Contrato | I12: Precio Pactado | J12: CONTRACTUAL | L12: ESTUDIO DEFINITIVO | N12: PRECIO DE VENTA | O12: MENDOZA | R12: DIFERENCIA DE PRECIOS | U12: PRECIO DE VENTA | V12: GELCO/Group Electric JYM Sac PU | Y12: PRECIO DE VENTA | Z12: EL DETALLE | AC12: PRECIO DE VENTA | AD12: CIE
J13: Metrado | K13: TOTAL | L13: Metrado | M13: TOTAL | O13: Metrado | P13: TOTAL | Q13: % | V13: Metrado | W13: TOTAL | X13: % | Z13: Metrado | AA13: TOTAL | AB13: % | AD13: Metrado | AE13: TOTAL | AF13: %
H15: Unitario | I15: Unitario | J15: Cantidad | K15: S/. | L15: Cantidad | M15: S/. | N15: S/. | O15: Cantidad | P15: S/. | R15: S/. | S15: TDT | T15: PROYECTO | U15: S/. | V15: Cantidad | W15: S/. | Y15: S/. | Z15: Cantidad | AA15: S/. | AC15: S/. | AD15: Cantidad | AE15: S/.
B16: A | D16: SUMINISTRO DE MATERIALES
B17: 1 | C17: 3 | D17: CRUCETAS DE MADERA DE PROCEDENCIA NACIONAL
B18: =+B17+0.01 -> 1.01 | C18: =+C17+1 -> 4 | D18: Cruceta de madera tratada de 90 mm x 115 mm x 1,20 m | G18: u | H18: 105 | J18: 13 | K18: =+ROUND($H18*J18,2) -> 1365 | L18: =+[193]Metrado!E13 -> 10 | M18: =+ROUND($H18*L18,2) -> 1050 | N18: 0 | O18: =L18 -> 10 | P18: =+ROUND($N18*O18,2) -> 0 | Q18: =+N18/($H18+$I18) -> 0 | R18: =+(H18+I18)-N18 -> 105 | U18: 0 | V18: =$L18 -> 10 | W18: =+ROUND($U18*V18,2) -> 0 | X18: =+U18/($H18+$I18) -> 0 | Y18: 0 | Z18: =$L18 -> 10 | AA18: =+ROUND($Y18*Z18,2) -> 0 | AB18: =+Y18/($H18+$I18) -> 0 | AC18: 0 | AD18: =$L18 -> 10 | AE18: =+ROUND($AC18*AD18,2) -> 0 | AF18: =+AC18/($H18+$I18) -> 0
B19: =+B18+0.01 -> 1.02 | C19: =+C18+1 -> 5 | D19: Listón de madera tratada 50 x 19 mm sección, 2,7 m longitud (incluye clavos de fijación) | G19: u | H19: 27.35 | J19: 2 | K19: =+ROUND($H19*J19,2) -> 54.7 | L19: =+'[193]Metrado'!E14 -> 0 | M19: =+ROUND($H19*L19,2) -> 0 | N19: 0 | O19: =L19 -> 0 | P19: =+ROUND($N19*O19,2) -> 0 | Q19: =+N19/($H19+$I19) -> 0 | R19: =+(H19+I19)-N19 -> 27.35 | U19: 0 | V19: =$L19 -> 0 | W19: =+ROUND($U19*V19,2) -> 0 | X19: =+U19/($H19+$I19) -> 0 | Y19: 0 | Z19: =$L19 -> 0 | AA19: =+ROUND($Y19*Z19,2) -> 0 | AB19: =+Y19/($H19+$I19) -> 0 | AC19: 0 | AD19: =$L19 -> 0 | AE19: =+ROUND($AC19*AD19,2) -> 0 | AF19: =+AC19/($H19+$I19) -> 0
B20: 1.03 | C20: =+C19+1 -> 6 | D20: Cruceta de madera tratada de 90 mm x 115 mm x 2,00 m | G20: u | I20: =+LP!G19 -> 178 | K20: =+ROUND($H20*J20,2) -> 0 | L20: =+'[193]Metrado'!E15 -> 2 | M20: =+ROUND($I20*L20,2) -> 356 | N20: 0 | O20: =L20 -> 2 | P20: =+ROUND($N20*O20,2) -> 0 | Q20: =+N20/($H20+$I20) -> 0 | R20: =+(H20+I20)-N20 -> 178 | U20: 0 | V20: =$L20 -> 2 | W20: =+ROUND($U20*V20,2) -> 0 | X20: =+U20/($H20+$I20) -> 0 | Y20: 0 | Z20: =$L20 -> 2 | AA20: =+ROUND($Y20*Z20,2) -> 0 | AB20: =+Y20/($H20+$I20) -> 0 | AC20: 0 | AD20: =$L20 -> 2 | AE20: =+ROUND($AC20*AD20,2) -> 0 | AF20: =+AC20/($H20+$I20) -> 0
B21: 1.04 | C21: =+C20+1 -> 7 | D21: Cruceta de madera tratada de 90 mm x 115 mm x 2,40 m | G21: u | I21: =+LP!G20 -> 205 | K21: =+ROUND($H21*J21,2) -> 0 | L21: =+'[193]Metrado'!E16 -> 3 | M21: =+ROUND($I21*L21,2) -> 615 | N21: 0 | O21: =L21 -> 3 | P21: =+ROUND($N21*O21,2) -> 0 | Q21: =+N21/($H21+$I21) -> 0 | R21: =+(H21+I21)-N21 -> 205 | U21: 0 | V21: =$L21 -> 3 | W21: =+ROUND($U21*V21,2) -> 0 | X21: =+U21/($H21+$I21) -> 0 | Y21: 0 | Z21: =$L21 -> 3 | AA21: =+ROUND($Y21*Z21,2) -> 0 | AB21: =+Y21/($H21+$I21) -> 0 | AC21: 0 | AD21: =$L21 -> 3 | AE21: =+ROUND($AC21*AD21,2) -> 0 | AF21: =+AC21/($H21+$I21) -> 0
C22: =+C19+1 -> 6 | F22: =+"SUB-TOTAL "&B17&": " -> SUB-TOTAL 1: | K22: =+SUM(K18:K21) -> 1419.7 | M22: =+SUM(M18:M21) -> 2021 | N22: 0 | O22: =L22 -> 0 | P22: =+SUM(P18:P21) -> 0 | R22: =+(H22+I22)-N22 -> 0 | U22: 0 | V22: =$L22 -> 0 | W22: =+SUM(W18:W21) -> 0 | Y22: 0 | Z22: =$L22 -> 0 | AA22: =+SUM(AA18:AA21) -> 0 | AC22: 0 | AD22: =$L22 -> 0 | AE22: =+SUM(AE18:AE21) -> 0
B23: =1+B17 -> 2 | C23: =+C22+1 -> 7 | D23: POSTES DE CONCRETO ARMADO CENTRIFUGADO | N23: 0 | O23: =L23 -> 0 | R23: =+(H23+I23)-N23 -> 0 | U23: 0 | V23: =$L23 -> 0 | Y23: 0 | Z23: =$L23 -> 0 | AC23: 0 | AD23: =$L23 -> 0
B24: 2.01 | C24: =+C20+1 -> 7 | D24: Poste de C.A.C. de 12 m/200 daN (Incluye perilla) | G24: u | H24: 837.45 | J24: 3 | K24: =+ROUND($H24*J24,2) -> 2512.35 | L24: =+'[193]Metrado'!E19 -> 1 | M24: =+ROUND($H24*L24,2) -> 837.45 | N24: 0 | O24: =L24 -> 1 | P24: =+ROUND($N24*O24,2) -> 0 | Q24: =+N24/($H24+$I24) -> 0 | R24: =+(H24+I24)-N24 -> 837.45 | U24: 0 | V24: =$L24 -> 1 | W24: =+ROUND($U24*V24,2) -> 0 | X24: =+U24/($H24+$I24) -> 0 | Y24: 0 | Z24: =$L24 -> 1 | AA24: =+ROUND($Y24*Z24,2) -> 0 | AB24: =+Y24/($H24+$I24) -> 0 | AC24: 0 | AD24: =$L24 -> 1 | AE24: =+ROUND($AC24*AD24,2) -> 0 | AF24: =+AC24/($H24+$I24) -> 0
B25: 2.02 | C25: =+C21+1 -> 8 | D25: Poste de C.A.C. de 12 m/300 daN (Incluye perilla) | G25: u | H25: 923.47 | J25: 11 | K25: =+ROUND($H25*J25,2) -> 10158.17 | L25: =+'[193]Metrado'!E20 -> 13 | M25: =+ROUND($H25*L25,2) -> 12005.11 | N25: 0 | O25: =L25 -> 13 | P25: =+ROUND($N25*O25,2) -> 0 | Q25: =+N25/($H25+$I25) -> 0 | R25: =+(H25+I25)-N25 -> 923.47 | U25: 0 | V25: =$L25 -> 13 | W25: =+ROUND($U25*V25,2) -> 0 | X25: =+U25/($H25+$I25) -> 0 | Y25: 0 | Z25: =$L25 -> 13 | AA25: =+ROUND($Y25*Z25,2) -> 0 | AB25: =+Y25/($H25+$I25) -> 0 | AC25: 0 | AD25: =$L25 -> 13 | AE25: =+ROUND($AC25*AD25,2) -> 0 | AF25: =+AC25/($H25+$I25) -> 0
B26: 2.03 | C26: =+C22+1 -> 7 | D26: Poste de C.A.C. de 13 m/300 daN (Incluye perilla) | G26: u | H26: 1085.14 | J26: 10 | K26: =+ROUND($H26*J26,2) -> 10851.4 | L26: =+'[193]Metrado'!E21 -> 11 | M26: =+ROUND($H26*L26,2) -> 11936.54 | N26: 0 | O26: =L26 -> 11 | P26: =+ROUND($N26*O26,2) -> 0 | Q26: =+N26/($H26+$I26) -> 0 | R26: =+(H26+I26)-N26 -> 1085.14 | U26: 0 | V26: =$L26 -> 11 | W26: =+ROUND($U26*V26,2) -> 0 | X26: =+U26/($H26+$I26) -> 0 | Y26: 0 | Z26: =$L26 -> 11 | AA26: =+ROUND($Y26*Z26,2) -> 0 | AB26: =+Y26/($H26+$I26) -> 0 | AC26: 0 | AD26: =$L26 -> 11 | AE26: =+ROUND($AC26*AD26,2) -> 0 | AF26: =+AC26/($H26+$I26) -> 0
B27: 2.04 | C27: =+C23+1 -> 8 | D27: Poste de C.A.C. de 13 m/400 daN (Incluye perilla) | G27: u | H27: 1207.94 | J27: 10 | K27: =+ROUND($H27*J27,2) -> 12079.4 | L27: =+'[193]Metrado'!E22 -> 14 | M27: =+ROUND($H27*L27,2) -> 16911.16 | N27: 0 | O27: =L27 -> 14 | P27: =+ROUND($N27*O27,2) -> 0 | Q27: =+N27/($H27+$I27) -> 0 | R27: =+(H27+I27)-N27 -> 1207.94 | U27: 0 | V27: =$L27 -> 14 | W27: =+ROUND($U27*V27,2) -> 0 | X27: =+U27/($H27+$I27) -> 0 | Y27: 0 | Z27: =$L27 -> 14 | AA27: =+ROUND($Y27*Z27,2) -> 0 | AB27: =+Y27/($H27+$I27) -> 0 | AC27: 0 | AD27: =$L27 -> 14 | AE27: =+ROUND($AC27*AD27,2) -> 0 | AF27: =+AC27/($H27+$I27) -> 0
C28: =+C27+1 -> 9 | F28: =+"SUB-TOTAL "&B23&": " -> SUB-TOTAL 2: | K28: =+SUM(K24:K27) -> 35601.32 | M28: =+SUM(M24:M27) -> 41690.26 | N28: 0 | O28: =L28 -> 0 | P28: =+SUM(P24:P27) -> 0 | R28: =+(H28+I28)-N28 -> 0 | U28: 0 | V28: =$L28 -> 0 | W28: =+SUM(W24:W27) -> 0 | Y28: 0 | Z28: =$L28 -> 0 | AA28: =+SUM(AA24:AA27) -> 0 | AC28: 0 | AD28: =$L28 -> 0 | AE28: =+SUM(AE24:AE27) -> 0
B29: 3 | C29: =+C28+1 -> 10 | D29: POSTES DE MADERA IMPORTADA | N29: 0 | O29: =L29 -> 0 | R29: =+(H29+I29)-N29 -> 0 | U29: 0 | V29: =$L29 -> 0 | Y29: 0 | Z29: =$L29 -> 0 | AC29: 0 | AD29: =$L29 -> 0
B30: 3.01 | C30: =+#REF!+1 -> #REF! | D30: Poste de madera importada (Pino Amarillo del Sur) de 12 m, Clase 5 | G30: u | H30: 1864.52 | J30: 2 | K30: =+ROUND($H30*J30,2) -> 3729.04 | L30: =+'[193]Metrado'!E25 -> 0 | M30: =+ROUND($H30*L30,2) -> 0 | N30: 0 | O30: =L30 -> 0 | P30: =+ROUND($N30*O30,2) -> 0 | Q30: =+N30/($H30+$I30) -> 0 | R30: =+(H30+I30)-N30 -> 1864.52 | U30: 0 | V30: =$L30 -> 0 | W30: =+ROUND($U30*V30,2) -> 0 | X30: =+U30/($H30+$I30) -> 0 | Y30: 0 | Z30: =$L30 -> 0 | AA30: =+ROUND($Y30*Z30,2) -> 0 | AB30: =+Y30/($H30+$I30) -> 0 | AC30: 0 | AD30: =$L30 -> 0 | AE30: =+ROUND($AC30*AD30,2) -> 0 | AF30: =+AC30/($H30+$I30) -> 0
C31: =+#REF!+1 -> #REF! | F31: =+"SUB-TOTAL "&B29&": " -> SUB-TOTAL 3: | K31: =+SUM(K30:K30) -> 3729.04 | M31: =+SUM(M30:M30) -> 0 | N31: 0 | O31: =L31 -> 0 | P31: =+SUM(P30:P30) -> 0 | R31: =+(H31+I31)-N31 -> 0 | U31: 0 | V31: =$L31 -> 0 | W31: =+SUM(W30:W30) -> 0 | Y31: 0 | Z31: =$L31 -> 0 | AA31: =+SUM(AA30:AA30) -> 0 | AC31: 0 | AD31: =$L31 -> 0 | AE31: =+SUM(AE30:AE30) -> 0
B32: 3.00A | C32: =+C31+1 -> #REF! | D32: POSTES DE FIBRA DE VIDRIO | N32: 0 | O32: =L32 -> 0 | R32: =+(H32+I32)-N32 -> 0 | U32: 0 | V32: =$L32 -> 0 | Y32: 0 | Z32: =$L32 -> 0 | AC32: 0 | AD32: =$L32 -> 0
B33: 3.01A | C33: =+C32+1 -> #REF! | D33: Poste de PRFV de 12 m/200 daN | I33: 1958.01 | K33: =+ROUND($H33*J33,2) -> 0 | L33: =+'[193]Metrado'!E28 -> 0 | M33: =+ROUND($I33*L33,2) -> 0 | N33: 0 | O33: =L33 -> 0 | P33: =+ROUND($N33*O33,2) -> 0 | Q33: =+N33/($H33+$I33) -> 0 | R33: =+(H33+I33)-N33 -> 1958.01 | U33: 0 | V33: =$L33 -> 0 | W33: =+ROUND($U33*V33,2) -> 0 | X33: =+U33/($H33+$I33) -> 0 | Y33: 0 | Z33: =$L33 -> 0 | AA33: =+ROUND($Y33*Z33,2) -> 0 | AB33: =+Y33/($H33+$I33) -> 0 | AC33: 0 | AD33: =$L33 -> 0 | AE33: =+ROUND($AC33*AD33,2) -> 0 | AF33: =+AC33/($H33+$I33) -> 0
B34: 3.02A | C34: =+C33+1 -> #REF! | D34: Poste de PRFV de 12 m/300 daN | I34: 2336.29 | K34: =+ROUND($H34*J34,2) -> 0 | L34: =+'[193]Metrado'!E29 -> 5 | M34: =+ROUND($I34*L34,2) -> 11681.45 | N34: 0 | O34: =L34 -> 5 | P34: =+ROUND($N34*O34,2) -> 0 | Q34: =+N34/($H34+$I34) -> 0 | R34: =+(H34+I34)-N34 -> 2336.29 | U34: 0 | V34: =$L34 -> 5 | W34: =+ROUND($U34*V34,2) -> 0 | X34: =+U34/($H34+$I34) -> 0 | Y34: 0 | Z34: =$L34 -> 5 | AA34: =+ROUND($Y34*Z34,2) -> 0 | AB34: =+Y34/($H34+$I34) -> 0 | AC34: 0 | AD34: =$L34 -> 5 | AE34: =+ROUND($AC34*AD34,2) -> 0 | AF34: =+AC34/($H34+$I34) -> 0
C35: =+C34+1 -> #REF! | F35: =+"SUB-TOTAL "&B32&": " -> SUB-TOTAL 3.00A: | M35: =+SUM(M33:M34) -> 11681.45 | N35: 0 | O35: =L35 -> 0 | R35: =+(H35+I35)-N35 -> 0 | U35: 0 | V35: =$L35 -> 0 | Y35: 0 | Z35: =$L35 -> 0 | AC35: 0 | AD35: =$L35 -> 0
B36: =+B29+1 -> 4 | C36: =+C31+1 -> #REF! | D36: OTROS MATERIALES DE CONCRETO ARMADO | N36: 0 | O36: =L36 -> 0 | R36: =+(H36+I36)-N36 -> 0 | U36: 0 | V36: =$L36 -> 0 | Y36: 0 | Z36: =$L36 -> 0 | AC36: 0 | AD36: =$L36 -> 0
B37: 4.01 | C37: =+C36+1 -> #REF! | D37: Cruceta Asimétrica de C.A.V. Za / 1,5 / 0,9 / 250 / 200 / 100 daN (Za / L / L1/ T / F / V) | G37: u | H37: 120.3 | J37: 5 | K37: =+ROUND($H37*J37,2) -> 601.5 | L37: =+'[193]Metrado'!E32 -> 5 | M37: =+ROUND($H37*L37,2) -> 601.5 | N37: 0 | O37: =L37 -> 5 | P37: =+ROUND($N37*O37,2) -> 0 | Q37: =+N37/($H37+$I37) -> 0 | R37: =+(H37+I37)-N37 -> 120.3 | U37: 0 | V37: =$L37 -> 5 | W37: =+ROUND($U37*V37,2) -> 0 | X37: =+U37/($H37+$I37) -> 0 | Y37: 0 | Z37: =$L37 -> 5 | AA37: =+ROUND($Y37*Z37,2) -> 0 | AB37: =+Y37/($H37+$I37) -> 0 | AC37: 0 | AD37: =$L37 -> 5 | AE37: =+ROUND($AC37*AD37,2) -> 0 | AF37: =+AC37/($H37+$I37) -> 0
B38: 4.02 | C38: =+C37+1 -> #REF! | D38: Ménsula de C.A.V. M / 1,2 / 250 / 150 / 150 daN (M / L / T / F / V) | G38: u | H38: 88.8 | J38: 40 | K38: =+ROUND($H38*J38,2) -> 3552 | L38: =+'[193]Metrado'!E33 -> 60 | M38: =+ROUND($H38*L38,2) -> 5328 | N38: 0 | O38: =L38 -> 60 | P38: =+ROUND($N38*O38,2) -> 0 | Q38: =+N38/($H38+$I38) -> 0 | R38: =+(H38+I38)-N38 -> 88.8 | U38: 0 | V38: =$L38 -> 60 | W38: =+ROUND($U38*V38,2) -> 0 | X38: =+U38/($H38+$I38) -> 0 | Y38: 0 | Z38: =$L38 -> 60 | AA38: =+ROUND($Y38*Z38,2) -> 0 | AB38: =+Y38/($H38+$I38) -> 0 | AC38: 0 | AD38: =$L38 -> 60 | AE38: =+ROUND($AC38*AD38,2) -> 0 | AF38: =+AC38/($H38+$I38) -> 0
B39: 4.03 | C39: =+C38+1 -> #REF! | D39: Plataforma de Concreto Soporte de Transformador de 2,20 m, carga de trabajo de 500 daN | G39: u | H39: 620 | J39: 5 | K39: =+ROUND($H39*J39,2) -> 3100 | L39: =+'[193]Metrado'!E34 -> 5 | M39: =+ROUND($H39*L39,2) -> 3100 | N39: 0 | O39: =L39 -> 5 | P39: =+ROUND($N39*O39,2) -> 0 | Q39: =+N39/($H39+$I39) -> 0 | R39: =+(H39+I39)-N39 -> 620 | U39: 0 | V39: =$L39 -> 5 | W39: =+ROUND($U39*V39,2) -> 0 | X39: =+U39/($H39+$I39) -> 0 | Y39: 0 | Z39: =$L39 -> 5 | AA39: =+ROUND($Y39*Z39,2) -> 0 | AB39: =+Y39/($H39+$I39) -> 0 | AC39: 0 | AD39: =$L39 -> 5 | AE39: =+ROUND($AC39*AD39,2) -> 0 | AF39: =+AC39/($H39+$I39) -> 0
C40: =+#REF!+1 -> #REF! | F40: =+"SUB-TOTAL "&B36&": " -> SUB-TOTAL 4: | K40: =+SUM(K37:K39) -> 7253.5 | M40: =+SUM(M37:M39) -> 9029.5 | N40: 0 | O40: =L40 -> 0 | P40: =+SUM(P37:P39) -> 0 | R40: =+(H40+I40)-N40 -> 0 | U40: 0 | V40: =$L40 -> 0 | W40: =+SUM(W37:W39) -> 0 | Y40: 0 | Z40: =$L40 -> 0 | AA40: =+SUM(AA37:AA39) -> 0 | AC40: 0 | AD40: =$L40 -> 0 | AE40: =+SUM(AE37:AE39) -> 0
B41: =+B36+1 -> 5 | C41: =+C40+1 -> #REF! | D41: AISLADORES Y ACCESORIOS | N41: 0 | O41: =L41 -> 0 | R41: =+(H41+I41)-N41 -> 0 | U41: 0 | V41: =$L41 -> 0 | Y41: 0 | Z41: =$L41 -> 0 | AC41: 0 | AD41: =$L41 -> 0
B42: 5.01 | C42: =+C41+1 -> #REF! | D42: Aislador de Porcelana Tipo Pin, Clase ANSI 56-3 | G42: u | H42: 76.45 | J42: 16 | K42: =+ROUND($H42*J42,2) -> 1223.2 | L42: =+'[193]Metrado'!E37 -> 25 | M42: =+ROUND($H42*L42,2) -> 1911.25 | N42: 0 | O42: =L42 -> 25 | P42: =+ROUND($N42*O42,2) -> 0 | Q42: =+N42/($H42+$I42) -> 0 | R42: =+(H42+I42)-N42 -> 76.45 | U42: 0 | V42: =$L42 -> 25 | W42: =+ROUND($U42*V42,2) -> 0 | X42: =+U42/($H42+$I42) -> 0 | Y42: 0 | Z42: =$L42 -> 25 | AA42: =+ROUND($Y42*Z42,2) -> 0 | AB42: =+Y42/($H42+$I42) -> 0 | AC42: 0 | AD42: =$L42 -> 25 | AE42: =+ROUND($AC42*AD42,2) -> 0 | AF42: =+AC42/($H42+$I42) -> 0
B43: 5.02 | C43: =+C42+1 -> #REF! | D43: Espiga de AºGº de 609 mm longitud, para Cabeza de Poste y Aislador ANSI 56-3 | G43: u | H43: 35.96 | J43: 16 | K43: =+ROUND($H43*J43,2) -> 575.36 | L43: =+'[193]Metrado'!E38 -> 17 | M43: =+ROUND($H43*L43,2) -> 611.32 | N43: 29.85 | O43: =L43 -> 17 | P43: =+ROUND($N43*O43,2) -> 507.45 | Q43: =+N43/($H43+$I43) -> 0.83008899 | R43: =+(H43+I43)-N43 -> 6.11 | S43: =+IFERROR(VLOOKUP(D43,LP!C45:S128,15,0),0) -> 6.11 | T43: =+IFERROR(VLOOKUP(D43,LP!A45:S128,16,0),0) -> 0 | U43: 0 | V43: =$L43 -> 17 | W43: =+ROUND($U43*V43,2) -> 0 | X43: =+U43/($H43+$I43) -> 0 | Y43: 0 | Z43: =$L43 -> 17 | AA43: =+ROUND($Y43*Z43,2) -> 0 | AB43: =+Y43/($H43+$I43) -> 0 | AC43: 0 | AD43: =$L43 -> 17 | AE43: =+ROUND($AC43*AD43,2) -> 0 | AF43: =+AC43/($H43+$I43) -> 0
B44: 5.03 | C44: =+C43+1 -> #REF! | D44: Conjunto Aislador Line Post Polimérico en Cruceta: | G44: u | H44: 209.65 | J44: 40 | K44: =+ROUND($H44*J44,2) -> 8386 | L44: =+[193]Metrado!E40 -> 50 | M44: =+ROUND($H44*L44,2) -> 10482.5 | N44: 0 | O44: =L44 -> 50 | P44: =+ROUND($N44*O44,2) -> 0 | Q44: =+N44/($H44+$I44) -> 0 | R44: =+(H44+I44)-N44 -> 209.65 | U44: 0 | V44: =$L44 -> 50 | W44: =+ROUND($U44*V44,2) -> 0 | X44: =+U44/($H44+$I44) -> 0 | Y44: 0 | Z44: =$L44 -> 50 | AA44: =+ROUND($Y44*Z44,2) -> 0 | AB44: =+Y44/($H44+$I44) -> 0 | AC44: 0 | AD44: =$L44 -> 50 | AE44: =+ROUND($AC44*AD44,2) -> 0 | AF44: =+AC44/($H44+$I44) -> 0
C45: =+C44+1 -> #REF! | D45: - Aislador Polimérico de 36 kV, Tipo Line Post con Espárrago de 19 mm Ø, 200 mm longitud (Alternativa a Conjunto Aislador-Espiga en Cruceta) | N45: 0 | R45: =+(H45+I45)-N45 -> 0 | U45: 0 | V45: =$L45 -> 0 | Y45: 0 | Z45: =$L45 -> 0 | AC45: 0 | AD45: =$L45 -> 0
B46: 5.04 | C46: =+#REF!+1 -> #REF! | D46: Espiga para cruceta, forjada de 381mm LONG. Para aislador Tipo Pin, Clase ANSI 56-3 | G46: u | I46: 49.41 | K46: =+ROUND($H46*J46,2) -> 0 | L46: =+[193]Metrado!E41 -> 8 | M46: =+ROUND($I46*L46,2) -> 395.28 | N46: 35.87 | O46: =L46 -> 8 | P46: =+ROUND($N46*O46,2) -> 286.96 | Q46: =+N46/($H46+$I46) -> 0.7259664 | R46: =+(H46+I46)-N46 -> 13.54 | S46: =+IFERROR(VLOOKUP(D46,LP!C48:S131,15,0),0) -> 0 | T46: =+IFERROR(VLOOKUP(D46,LP!A48:S131,16,0),0) -> 0 | U46: 0 | V46: =$L46 -> 8 | W46: =+ROUND($U46*V46,2) -> 0 | X46: =+U46/($H46+$I46) -> 0 | Y46: 0 | Z46: =$L46 -> 8 | AA46: =+ROUND($Y46*Z46,2) -> 0 | AB46: =+Y46/($H46+$I46) -> 0 | AC46: 0 | AD46: =$L46 -> 8 | AE46: =+ROUND($AC46*AD46,2) -> 0 | AF46: =+AC46/($H46+$I46) -> 0
C47: =+#REF!+1 -> #REF! | F47: =+"SUB-TOTAL "&B41&": " -> SUB-TOTAL 5: | K47: =+SUM(K42:K46) -> 10184.56 | M47: =+SUM(M42:M46) -> 13400.35 | N47: 0 | O47: =L47 -> 0 | P47: =+SUM(P42:P46) -> 794.41 | R47: =+(H47+I47)-N47 -> 0 | U47: 0 | V47: =$L47 -> 0 | W47: =+SUM(W42:W46) -> 0 | Y47: 0 | Z47: =$L47 -> 0 | AA47: =+SUM(AA42:AA46) -> 0 | AC47: 0 | AD47: =$L47 -> 0 | AE47: =+SUM(AE42:AE46) -> 0
B48: =+B41+1 -> 6 | C48: =+C47+1 -> #REF! | D48: AISLADORES DE SUSPENSIÓN Y ACCESORIOS | N48: 0 | O48: =L48 -> 0 | R48: =+(H48+I48)-N48 -> 0 | U48: 0 | V48: =$L48 -> 0 | Y48: 0 | Z48: =$L48 -> 0 | AC48: 0 | AD48: =$L48 -> 0
B49: 6.01 | C49: =+C48+1 -> #REF! | D49: Grillete Recto | G49: u | H49: 17.76 | J49: 16 | K49: =+ROUND($H49*J49,2) -> 284.16 | L49: =+[193]Metrado!E44 -> 23 | M49: =+ROUND($H49*L49,2) -> 408.48 | N49: 10.64 | O49: =L49 -> 23 | P49: =+ROUND($N49*O49,2) -> 244.72 | Q49: =+N49/($H49+$I49) -> 0.5990991 | R49: =+(H49+I49)-N49 -> 7.12 | S49: =+IFERROR(VLOOKUP(D49,LP!C51:S134,15,0),0) -> 0 | T49: =+IFERROR(VLOOKUP(D49,LP!A51:S134,16,0),0) -> 0 | U49: 0 | V49: =$L49 -> 23 | W49: =+ROUND($U49*V49,2) -> 0 | X49: =+U49/($H49+$I49) -> 0 | Y49: 0 | Z49: =$L49 -> 23 | AA49: =+ROUND($Y49*Z49,2) -> 0 | AB49: =+Y49/($H49+$I49) -> 0 | AC49: 6.5 | AD49: =$L49 -> 23 | AE49: =+ROUND($AC49*AD49,2) -> 149.5 | AF49: =+AC49/($H49+$I49) -> 0.36599099
B50: 6.02 | C50: =+C49+1 -> #REF! | D50: Aislador Polimerico con Conexión Horquilla (Estructura) y Lengüeta (Linea) de 36 kV, según Especificacion Técnica. | G50: u | H50: 76.66 | J50: 16 | K50: =+ROUND($H50*J50,2) -> 1226.56 | L50: =+'[193]Metrado'!E45 -> 23 | M50: =+ROUND($H50*L50,2) -> 1763.18 | N50: 0 | O50: =L50 -> 23 | P50: =+ROUND($N50*O50,2) -> 0 | Q50: =+N50/($H50+$I50) -> 0 | R50: =+(H50+I50)-N50 -> 76.66 | U50: 0 | V50: =$L50 -> 23 | W50: =+ROUND($U50*V50,2) -> 0 | X50: =+U50/($H50+$I50) -> 0 | Y50: 0 | Z50: =$L50 -> 23 | AA50: =+ROUND($Y50*Z50,2) -> 0 | AB50: =+Y50/($H50+$I50) -> 0 | AC50: 0 | AD50: =$L50 -> 23 | AE50: =+ROUND($AC50*AD50,2) -> 0 | AF50: =+AC50/($H50+$I50) -> 0
C51: =+#REF!+1 -> #REF! | F51: =+"SUB-TOTAL "&B48&": " -> SUB-TOTAL 6: | K51: =+SUM(K49:K50) -> 1510.72 | M51: =+SUM(M49:M50) -> 2171.66 | N51: 0 | O51: =L51 -> 0 | P51: =+SUM(P49:P50) -> 244.72 | R51: =+(H51+I51)-N51 -> 0 | U51: 0 | V51: =$L51 -> 0 | W51: =+SUM(W49:W50) -> 0 | Y51: 0 | Z51: =$L51 -> 0 | AA51: =+SUM(AA49:AA50) -> 0 | AC51: 0 | AD51: =$L51 -> 0 | AE51: =+SUM(AE49:AE50) -> 149.5
B52: =+B48+1 -> 7 | C52: =+C51+1 -> #REF! | D52: CONDUCTOR DE ALEACIÓN DE ALUMINIO | N52: 0 | O52: =L52 -> 0 | R52: =+(H52+I52)-N52 -> 0 | U52: 0 | V52: =$L52 -> 0 | Y52: 0 | Z52: =$L52 -> 0 | AC52: 0 | AD52: =$L52 -> 0
B53: 7.01 | C53: =+C52+1 -> #REF! | D53: Conductor de Aleacion de Aluminio de 35 mm² | G53: km | H53: 2249.62 | J53: 3.51 | K53: =+ROUND($H53*J53,2) -> 7896.17 | L53: =+'[193]Metrado'!E48 -> 3.9891798 | M53: =+ROUND($H53*L53,2) -> 8974.14 | N53: 1449.1 | O53: =L53 -> 3.9891798 | P53: =+ROUND($N53*O53,2) -> 5780.72 | Q53: =+N53/($H53+$I53) -> 0.64415323 | R53: =+(H53+I53)-N53 -> 800.52 | U53: 0 | V53: =$L53 -> 3.9891798 | W53: =+ROUND($U53*V53,2) -> 0 | X53: =+U53/($H53+$I53) -> 0 | Y53: 0 | Z53: =$L53 -> 3.9891798 | AA53: =+ROUND($Y53*Z53,2) -> 0 | AB53: =+Y53/($H53+$I53) -> 0 | AC53: 0 | AD53: =$L53 -> 3.9891798 | AE53: =+ROUND($AC53*AD53,2) -> 0 | AF53: =+AC53/($H53+$I53) -> 0
C54: =+#REF!+1 -> #REF! | F54: =+"SUB-TOTAL "&B52&": " -> SUB-TOTAL 7: | K54: =+SUM(K53:K53) -> 7896.17 | M54: =+SUM(M53:M53) -> 8974.14 | N54: 0 | O54: =L54 -> 0 | P54: =+SUM(P53:P53) -> 5780.72 | R54: =+(H54+I54)-N54 -> 0 | U54: 0 | V54: =$L54 -> 0 | W54: =+SUM(W53:W53) -> 0 | Y54: 0 | Z54: =$L54 -> 0 | AA54: =+SUM(AA53:AA53) -> 0 | AC54: 0 | AD54: =$L54 -> 0 | AE54: =+SUM(AE53:AE53) -> 0
B55: =+B52+1 -> 8 | C55: =+C54+1 -> #REF! | D55: ACCESORIOS PARA CONDUCTOR DE ALEACION ALUMINIO | N55: 0 | O55: =L55 -> 0 | R55: =+(H55+I55)-N55 -> 0 | U55: 0 | V55: =$L55 -> 0 | Y55: 0 | Z55: =$L55 -> 0 | AC55: 0 | AD55: =$L55 -> 0
B56: 8.01 | C56: =+C55+1 -> #REF! | D56: Varilla de Armar preformada Simple para Conductor de 35 mm² | G56: u | H56: 10.19 | J56: 41 | K56: =+ROUND($H56*J56,2) -> 417.79 | L56: =+'[193]Metrado'!E51 -> 47 | M56: =+ROUND($H56*L56,2) -> 478.93 | N56: 6.17 | O56: =L56 -> 47 | P56: =+ROUND($N56*O56,2) -> 289.99 | Q56: =+N56/($H56+$I56) -> 0.60549558 | R56: =+(H56+I56)-N56 -> 4.02 | S56: =+IFERROR(VLOOKUP(D56,LP!C58:S141,15,0),0) -> 4.02 | T56: =+IFERROR(VLOOKUP(D56,LP!A58:S141,16,0),0) -> 0 | U56: 0 | V56: =$L56 -> 47 | W56: =+ROUND($U56*V56,2) -> 0 | X56: =+U56/($H56+$I56) -> 0 | Y56: 0 | Z56: =$L56 -> 47 | AA56: =+ROUND($Y56*Z56,2) -> 0 | AB56: =+Y56/($H56+$I56) -> 0 | AC56: 5.5 | AD56: =$L56 -> 47 | AE56: =+ROUND($AC56*AD56,2) -> 258.5 | AF56: =+AC56/($H56+$I56) -> 0.53974485
B57: 8.02 | C57: =+C56+1 -> #REF! | D57: Grapa de Doble Via de Aluminio para Conductor de 35 mm² | G57: u | H57: 7.77 | J57: 41 | K57: =+ROUND($H57*J57,2) -> 318.57 | L57: =+'[193]Metrado'!E52 -> 40 | M57: =+ROUND($H57*L57,2) -> 310.8 | N57: 3.8 | O57: =L57 -> 40 | P57: =+ROUND($N57*O57,2) -> 152 | Q57: =+N57/($H57+$I57) -> 0.48906049 | R57: =+(H57+I57)-N57 -> 3.97 | S57: =+IFERROR(VLOOKUP(D57,LP!C59:S142,15,0),0) -> 3.97 | T57: =+IFERROR(VLOOKUP(D57,LP!A59:S142,16,0),0) -> 0 | U57: 0 | V57: =$L57 -> 40 | W57: =+ROUND($U57*V57,2) -> 0 | X57: =+U57/($H57+$I57) -> 0 | Y57: 0 | Z57: =$L57 -> 40 | AA57: =+ROUND($Y57*Z57,2) -> 0 | AB57: =+Y57/($H57+$I57) -> 0 | AC57: 0 | AD57: =$L57 -> 40 | AE57: =+ROUND($AC57*AD57,2) -> 0 | AF57: =+AC57/($H57+$I57) -> 0
B58: 8.03 | C58: =+C57+1 -> #REF! | D58: Alambre de Amarre Aluminio Recocido de 16 mm² | G58: m | H58: 1.41 | J58: 170 | K58: =+ROUND($H58*J58,2) -> 239.7 | L58: =+'[193]Metrado'!E53 -> 227.5 | M58: =+ROUND($H58*L58,2) -> 320.78 | N58: 1.06 | O58: =L58 -> 227.5 | P58: =+ROUND($N58*O58,2) -> 241.15 | Q58: =+N58/($H58+$I58) -> 0.75177305 | R58: =+(H58+I58)-N58 -> 0.35 | S58: =+IFERROR(VLOOKUP(D58,LP!C60:S143,15,0),0) -> 0.35 | T58: =+IFERROR(VLOOKUP(D58,LP!A60:S143,16,0),0) -> 0 | U58: 0 | V58: =$L58 -> 227.5 | W58: =+ROUND($U58*V58,2) -> 0 | X58: =+U58/($H58+$I58) -> 0 | Y58: 0 | Z58: =$L58 -> 227.5 | AA58: =+ROUND($Y58*Z58,2) -> 0 | AB58: =+Y58/($H58+$I58) -> 0 | AC58: 1.1 | AD58: =$L58 -> 227.5 | AE58: =+ROUND($AC58*AD58,2) -> 250.25 | AF58: =+AC58/($H58+$I58) -> 0.78014184
B59: 8.04 | C59: =+C58+1 -> #REF! | D59: Grapa de Anclaje para Conductor de 35 mm² | G59: u | H59: 25.34 | J59: 16 | K59: =+ROUND($H59*J59,2) -> 405.44 | L59: =+'[193]Metrado'!E54 -> 22 | M59: =+ROUND($H59*L59,2) -> 557.48 | N59: 17.33 | O59: =L59 -> 22 | P59: =+ROUND($N59*O59,2) -> 381.26 | Q59: =+N59/($H59+$I59) -> 0.68389897 | R59: =+(H59+I59)-N59 -> 8.01 | S59: =+IFERROR(VLOOKUP(D59,LP!C61:S144,15,0),0) -> 8.01 | T59: =+IFERROR(VLOOKUP(D59,LP!A61:S144,16,0),0) -> 0 | U59: 0 | V59: =$L59 -> 22 | W59: =+ROUND($U59*V59,2) -> 0 | X59: =+U59/($H59+$I59) -> 0 | Y59: 0 | Z59: =$L59 -> 22 | AA59: =+ROUND($Y59*Z59,2) -> 0 | AB59: =+Y59/($H59+$I59) -> 0 | AC59: 17.8 | AD59: =$L59 -> 22 | AE59: =+ROUND($AC59*AD59,2) -> 391.6 | AF59: =+AC59/($H59+$I59) -> 0.70244672
B60: 8.05 | C60: =+#REF!+1 -> #REF! | D60: Varilla de Armar preformada Doble para Conductor de 35 mm² | G60: u | I60: 11.72 | K60: =+ROUND($H60*J60,2) -> 0 | L60: =+'[193]Metrado'!E55 -> 3 | M60: =+ROUND($I60*L60,2) -> 35.16 | N60: 7.87 | O60: =L60 -> 3 | P60: =+ROUND($N60*O60,2) -> 23.61 | Q60: =+N60/($H60+$I60) -> 0.67150171 | R60: =+(H60+I60)-N60 -> 3.85 | S60: =+IFERROR(VLOOKUP(D60,LP!C62:S145,15,0),0) -> 7.93 | T60: =+IFERROR(VLOOKUP(D60,LP!A62:S145,16,0),0) -> 0 | U60: 0 | V60: =$L60 -> 3 | W60: =+ROUND($U60*V60,2) -> 0 | X60: =+U60/($H60+$I60) -> 0 | Y60: 0 | Z60: =$L60 -> 3 | AA60: =+ROUND($Y60*Z60,2) -> 0 | AB60: =+Y60/($H60+$I60) -> 0 | AC60: 6.5 | AD60: =$L60 -> 3 | AE60: =+ROUND($AC60*AD60,2) -> 19.5 | AF60: =+AC60/($H60+$I60) -> 0.55460751
B61: 8.06 | C61: =+C60+1 -> #REF! | D61: Cinta plana de armar de aluminio | G61: m | I61: 1 | K61: =+ROUND($H61*J61,2) -> 0 | L61: =+'[193]Metrado'!E56 -> 13.8 | M61: =+ROUND($I61*L61,2) -> 13.8 | N61: 1.06 | O61: =L61 -> 13.8 | P61: =+ROUND($N61*O61,2) -> 14.63 | Q61: =+N61/($H61+$I61) -> 1.06 | R61: =+(H61+I61)-N61 -> -0.06 | S61: =+IFERROR(VLOOKUP(D61,LP!C63:S146,15,0),0) -> -0.06 | T61: =+IFERROR(VLOOKUP(D61,LP!A63:S146,16,0),0) -> 0 | U61: 0 | V61: =$L61 -> 13.8 | W61: =+ROUND($U61*V61,2) -> 0 | X61: =+U61/($H61+$I61) -> 0 | Y61: 0 | Z61: =$L61 -> 13.8 | AA61: =+ROUND($Y61*Z61,2) -> 0 | AB61: =+Y61/($H61+$I61) -> 0 | AC61: 0.98 | AD61: =$L61 -> 13.8 | AE61: =+ROUND($AC61*AD61,2) -> 13.52 | AF61: =+AC61/($H61+$I61) -> 0.98
C62: =+C61+1 -> #REF! | F62: =+"SUB-TOTAL "&B55&": " -> SUB-TOTAL 8: | K62: =+SUM(K56:K61) -> 1381.5 | M62: =+SUM(M56:M61) -> 1716.95 | N62: 0 | O62: =L62 -> 0 | P62: =+SUM(P56:P61) -> 1102.64 | R62: =+(H62+I62)-N62 -> 0 | U62: 0 | V62: =$L62 -> 0 | W62: =+SUM(W56:W61) -> 0 | Y62: 0 | Z62: =$L62 -> 0 | AA62: =+SUM(AA56:AA61) -> 0 | AC62: 0 | AD62: =$L62 -> 0 | AE62: =+SUM(AE56:AE61) -> 933.37
B63: =+B55+1 -> 9 | C63: =+C62+1 -> #REF! | D63: CONDUCTOR DE COBRE | N63: 0 | O63: =L63 -> 0 | R63: =+(H63+I63)-N63 -> 0 | U63: 0 | V63: =$L63 -> 0 | Y63: 0 | Z63: =$L63 -> 0 | AC63: 0 | AD63: =$L63 -> 0
B64: 9.01 | C64: =+C63+1 -> #REF! | D64: Cable de Acero con Recubrimiento Metalúrgico de Cu de 4 AWG (21,15 mm²), para Puesta a Tierra | G64: m | H64: 12.8 | J64: 717.5 | K64: =+ROUND($H64*J64,2) -> 9184 | L64: =+'[193]Metrado'!E59 -> 431.5 | M64: =+ROUND($H64*L64,2) -> 5523.2 | N64: 6.2 | O64: =L64 -> 431.5 | P64: =+ROUND($N64*O64,2) -> 2675.3 | Q64: =+N64/($H64+$I64) -> 0.484375 | R64: =+(H64+I64)-N64 -> 6.6 | S64: =+IFERROR(VLOOKUP(D64,LP!C66:S149,15,0),0) -> 6.6 | T64: =+IFERROR(VLOOKUP(D64,LP!A66:S149,16,0),0) -> 0 | U64: 0 | V64: =$L64 -> 431.5 | W64: =+ROUND($U64*V64,2) -> 0 | X64: =+U64/($H64+$I64) -> 0 | Y64: 0 | Z64: =$L64 -> 431.5 | AA64: =+ROUND($Y64*Z64,2) -> 0 | AB64: =+Y64/($H64+$I64) -> 0 | AC64: 0 | AD64: =$L64 -> 431.5 | AE64: =+ROUND($AC64*AD64,2) -> 0 | AF64: =+AC64/($H64+$I64) -> 0
C65: =+#REF!+1 -> #REF! | F65: =+"SUB-TOTAL "&B63&": " -> SUB-TOTAL 9: | K65: =+SUM(K64:K64) -> 9184 | M65: =+SUM(M64:M64) -> 5523.2 | N65: 0 | O65: =L65 -> 0 | P65: =+SUM(P64:P64) -> 2675.3 | R65: =+(H65+I65)-N65 -> 0 | U65: 0 | V65: =$L65 -> 0 | W65: =+SUM(W64:W64) -> 0 | Y65: 0 | Z65: =$L65 -> 0 | AA65: =+SUM(AA64:AA64) -> 0 | AC65: 0 | AD65: =$L65 -> 0 | AE65: =+SUM(AE64:AE64) -> 0
B66: =1+B63 -> 10 | C66: =+C65+1 -> #REF! | D66: MATERIAL DE FERRETERIA PARA POSTES Y CRUCETAS | N66: 0 | O66: =L66 -> 0 | R66: =+(H66+I66)-N66 -> 0 | U66: 0 | V66: =$L66 -> 0 | Y66: 0 | Z66: =$L66 -> 0 | AC66: 0 | AD66: =$L66 -> 0
B67: 10.01 | C67: =+C61+1 -> #REF! | D67: Perno Cabeza Coche de AºGº de 13 mm Ø x 152 mm longitud, 76 mm maquinado, con Arandela, Tuerca y Contratuerca | G67: u | H67: 3.86 | J67: 13 | K67: =+ROUND($H67*J67,2) -> 50.18 | L67: =+'[193]Metrado'!E62 -> 20 | M67: =+ROUND($H67*L67,2) -> 77.2 | N67: 3.34 | O67: =L67 -> 20 | P67: =+ROUND($N67*O67,2) -> 66.8 | Q67: =+N67/($H67+$I67) -> 0.86528497 | R67: =+(H67+I67)-N67 -> 0.52 | S67: =+IFERROR(VLOOKUP(D67,LP!C69:S152,15,0),0) -> 0.52 | T67: =+IFERROR(VLOOKUP(D67,LP!A69:S152,16,0),0) -> 0 | U67: 0 | V67: =$L67 -> 20 | W67: =+ROUND($U67*V67,2) -> 0 | X67: =+U67/($H67+$I67) -> 0 | Y67: 0 | Z67: =$L67 -> 20 | AA67: =+ROUND($Y67*Z67,2) -> 0 | AB67: =+Y67/($H67+$I67) -> 0 | AC67: 1.7 | AD67: =$L67 -> 20 | AE67: =+ROUND($AC67*AD67,2) -> 34 | AF67: =+AC67/($H67+$I67) -> 0.44041451
B68: 10.02 | C68: =+C67+1 -> #REF! | D68: Perno de A°G° de 13 mm Ø x 305 mm, provisto de Tuerca y Contratuerca | G68: u | H68: 6.25 | J68: 13 | K68: =+ROUND($H68*J68,2) -> 81.25 | L68: =+'[193]Metrado'!E63 -> 15 | M68: =+ROUND($H68*L68,2) -> 93.75 | N68: 6.38 | O68: =L68 -> 15 | P68: =+ROUND($N68*O68,2) -> 95.7 | Q68: =+N68/($H68+$I68) -> 1.0208 | R68: =+(H68+I68)-N68 -> -0.13 | S68: =+IFERROR(VLOOKUP(D68,LP!C70:S153,15,0),0) -> -0.13 | T68: =+IFERROR(VLOOKUP(D68,LP!A70:S153,16,0),0) -> 0 | U68: 0 | V68: =$L68 -> 15 | W68: =+ROUND($U68*V68,2) -> 0 | X68: =+U68/($H68+$I68) -> 0 | Y68: 0 | Z68: =$L68 -> 15 | AA68: =+ROUND($Y68*Z68,2) -> 0 | AB68: =+Y68/($H68+$I68) -> 0 | AC68: 2.74 | AD68: =$L68 -> 15 | AE68: =+ROUND($AC68*AD68,2) -> 41.1 | AF68: =+AC68/($H68+$I68) -> 0.4384
B69: 10.03 | C69: =+C68+1 -> #REF! | D69: Perno de A°G° de 16 mm Ø x 254 mm, provisto de Tuerca y Contratuerca | G69: u | H69: 8.61 | J69: 32 | K69: =+ROUND($H69*J69,2) -> 275.52 | L69: =+'[193]Metrado'!E64 -> 25 | M69: =+ROUND($H69*L69,2) -> 215.25 | N69: 6.9 | O69: =L69 -> 25 | P69: =+ROUND($N69*O69,2) -> 172.5 | Q69: =+N69/($H69+$I69) -> 0.80139373 | R69: =+(H69+I69)-N69 -> 1.71 | S69: =+IFERROR(VLOOKUP(D69,LP!C71:S154,15,0),0) -> 1.71 | T69: =+IFERROR(VLOOKUP(D69,LP!A71:S154,16,0),0) -> 0 | U69: 0 | V69: =$L69 -> 25 | W69: =+ROUND($U69*V69,2) -> 0 | X69: =+U69/($H69+$I69) -> 0 | Y69: 0 | Z69: =$L69 -> 25 | AA69: =+ROUND($Y69*Z69,2) -> 0 | AB69: =+Y69/($H69+$I69) -> 0 | AC69: 4.1 | AD69: =$L69 -> 25 | AE69: =+ROUND($AC69*AD69,2) -> 102.5 | AF69: =+AC69/($H69+$I69) -> 0.47619048
B70: 10.04 | C70: =+C69+1 -> #REF! | D70: Perno de A°G° de 16 mm Ø x 305 mm, provisto de Tuerca y Contratuerca | G70: u | H70: 9.14 | J70: 26 | K70: =+ROUND($H70*J70,2) -> 237.64 | L70: =+'[193]Metrado'!E65 -> 30 | M70: =+ROUND($H70*L70,2) -> 274.2 | N70: 7.39 | O70: =L70 -> 30 | P70: =+ROUND($N70*O70,2) -> 221.7 | Q70: =+N70/($H70+$I70) -> 0.80853392 | R70: =+(H70+I70)-N70 -> 1.75 | S70: =+IFERROR(VLOOKUP(D70,LP!C72:S154,15,0),0) -> 1.75 | T70: =+IFERROR(VLOOKUP(D70,LP!A72:S154,16,0),0) -> 0 | U70: 0 | V70: =$L70 -> 30 | W70: =+ROUND($U70*V70,2) -> 0 | X70: =+U70/($H70+$I70) -> 0 | Y70: 0 | Z70: =$L70 -> 30 | AA70: =+ROUND($Y70*Z70,2) -> 0 | AB70: =+Y70/($H70+$I70) -> 0 | AC70: 4.35 | AD70: =$L70 -> 30 | AE70: =+ROUND($AC70*AD70,2) -> 130.5 | AF70: =+AC70/($H70+$I70) -> 0.47592998
B71: 10.05 | C71: =+C68+1 -> #REF! | D71: Perno de A°G° de 16 mm Ø x 356 mm, provisto de Tuerca y Contratuerca | G71: u | H71: 9.82 | J71: 13 | K71: =+ROUND($H71*J71,2) -> 127.66 | L71: =+'[193]Metrado'!E66 -> 15 | M71: =+ROUND($H71*L71,2) -> 147.3 | N71: 8.97 | O71: =L71 -> 15 | P71: =+ROUND($N71*O71,2) -> 134.55 | Q71: =+N71/($H71+$I71) -> 0.91344196 | R71: =+(H71+I71)-N71 -> 0.85 | S71: =+IFERROR(VLOOKUP(D71,LP!C73:S154,15,0),0) -> 0.85 | T71: =+IFERROR(VLOOKUP(D71,LP!A73:S154,16,0),0) -> 0 | U71: 0 | V71: =$L71 -> 15 | W71: =+ROUND($U71*V71,2) -> 0 | X71: =+U71/($H71+$I71) -> 0 | Y71: 0 | Z71: =$L71 -> 15 | AA71: =+ROUND($Y71*Z71,2) -> 0 | AB71: =+Y71/($H71+$I71) -> 0 | AC71: 4.9 | AD71: =$L71 -> 15 | AE71: =+ROUND($AC71*AD71,2) -> 73.5 | AF71: =+AC71/($H71+$I71) -> 0.49898167
B72: 10.06 | C72: =+C71+1 -> #REF! | D72: Perno Ojo de A°G° de 16 mm Ø x 254 mm, provisto de Tuerca y Contratuerca | G72: u | H72: 13.11 | J72: 16 | K72: =+ROUND($H72*J72,2) -> 209.76 | L72: =+'[193]Metrado'!E67 -> 7 | M72: =+ROUND($H72*L72,2) -> 91.77 | N72: 8.36 | O72: =L72 -> 7 | P72: =+ROUND($N72*O72,2) -> 58.52 | Q72: =+N72/($H72+$I72) -> 0.63768116 | R72: =+(H72+I72)-N72 -> 4.75 | S72: =+IFERROR(VLOOKUP(D72,LP!C74:S154,15,0),0) -> 4.75 | T72: =+IFERROR(VLOOKUP(D72,LP!A74:S154,16,0),0) -> 0 | U72: 0 | V72: =$L72 -> 7 | W72: =+ROUND($U72*V72,2) -> 0 | X72: =+U72/($H72+$I72) -> 0 | Y72: 0 | Z72: =$L72 -> 7 | AA72: =+ROUND($Y72*Z72,2) -> 0 | AB72: =+Y72/($H72+$I72) -> 0 | AC72: 7 | AD72: =$L72 -> 7 | AE72: =+ROUND($AC72*AD72,2) -> 49 | AF72: =+AC72/($H72+$I72) -> 0.53394355
B73: 10.07 | C73: =+C70+1 -> #REF! | D73: Perno Doble Armado de A°G° de 16 mm Ø x 508 mm, provisto de 4 Tuercas y 4 Contratuercas | G73: u | H73: 18.18 | J73: 50 | K73: =+ROUND($H73*J73,2) -> 909 | L73: =+'[193]Metrado'!E68 -> 60 | M73: =+ROUND($H73*L73,2) -> 1090.8 | N73: 11.98 | O73: =L73 -> 60 | P73: =+ROUND($N73*O73,2) -> 718.8 | Q73: =+N73/($H73+$I73) -> 0.6589659 | R73: =+(H73+I73)-N73 -> 6.2 | S73: =+IFERROR(VLOOKUP(D73,LP!C75:S154,15,0),0) -> 6.2 | T73: =+IFERROR(VLOOKUP(D73,LP!A75:S154,16,0),0) -> 0 | U73: 0 | V73: =$L73 -> 60 | W73: =+ROUND($U73*V73,2) -> 0 | X73: =+U73/($H73+$I73) -> 0 | Y73: 0 | Z73: =$L73 -> 60 | AA73: =+ROUND($Y73*Z73,2) -> 0 | AB73: =+Y73/($H73+$I73) -> 0 | AC73: 8 | AD73: =$L73 -> 60 | AE73: =+ROUND($AC73*AD73,2) -> 480 | AF73: =+AC73/($H73+$I73) -> 0.440044
B74: 10.08 | C74: =+C66+1 -> #REF! | D74: Tirafondo de A°G° de 13 mm ø x 102 mm de longitud | G74: u | H74: 2.74 | J74: 2 | K74: =+ROUND($H74*J74,2) -> 5.48 | L74: =+'[193]Metrado'!E69 -> 0 | M74: =+ROUND($H74*L74,2) -> 0 | N74: 0 | O74: =L74 -> 0 | P74: =+ROUND($N74*O74,2) -> 0 | Q74: =+N74/($H74+$I74) -> 0 | R74: =+(H74+I74)-N74 -> 2.74 | U74: 0 | V74: =$L74 -> 0 | W74: =+ROUND($U74*V74,2) -> 0 | X74: =+U74/($H74+$I74) -> 0 | Y74: 0 | Z74: =$L74 -> 0 | AA74: =+ROUND($Y74*Z74,2) -> 0 | AB74: =+Y74/($H74+$I74) -> 0 | AC74: 0 | AD74: =$L74 -> 0 | AE74: =+ROUND($AC74*AD74,2) -> 0 | AF74: =+AC74/($H74+$I74) -> 0
B75: 10.09 | C75: =+C74+1 -> #REF! | D75: Brazo-Soporte (Riostra) de Perfil Angular de A°G° de 38 x 38 x 5 mm y 710 mm longitud | G75: u | H75: 22.46 | J75: 13 | K75: =+ROUND($H75*J75,2) -> 291.98 | L75: =+'[193]Metrado'!E70 -> 20 | M75: =+ROUND($H75*L75,2) -> 449.2 | N75: 14.93 | O75: =L75 -> 20 | P75: =+ROUND($N75*O75,2) -> 298.6 | Q75: =+N75/($H75+$I75) -> 0.66473731 | R75: =+(H75+I75)-N75 -> 7.53 | S75: =+IFERROR(VLOOKUP(D75,LP!C77:S154,15,0),0) -> 7.53 | T75: =+IFERROR(VLOOKUP(D75,LP!A77:S154,16,0),0) -> 0 | U75: 0 | V75: =$L75 -> 20 | W75: =+ROUND($U75*V75,2) -> 0 | X75: =+U75/($H75+$I75) -> 0 | Y75: 0 | Z75: =$L75 -> 20 | AA75: =+ROUND($Y75*Z75,2) -> 0 | AB75: =+Y75/($H75+$I75) -> 0 | AC75: 23 | AD75: =$L75 -> 20 | AE75: =+ROUND($AC75*AD75,2) -> 460 | AF75: =+AC75/($H75+$I75) -> 1.0240427
B76: 10.1 | C76: =+C75+1 -> #REF! | D76: Arandela Cuadrada Plana de A° G°, 57 x 57 x 5 mm, Agujero de 18 mm Ø | G76: u | H76: 1.67 | J76: 107 | K76: =+ROUND($H76*J76,2) -> 178.69 | L76: =+'[193]Metrado'!E71 -> 149 | M76: =+ROUND($H76*L76,2) -> 248.83 | N76: 1.28 | O76: =L76 -> 149 | P76: =+ROUND($N76*O76,2) -> 190.72 | Q76: =+N76/($H76+$I76) -> 0.76646707 | R76: =+(H76+I76)-N76 -> 0.39 | S76: =+IFERROR(VLOOKUP(D76,LP!C78:S154,15,0),0) -> 0.39 | T76: =+IFERROR(VLOOKUP(D76,LP!A78:S154,16,0),0) -> 0 | U76: 0 | V76: =$L76 -> 149 | W76: =+ROUND($U76*V76,2) -> 0 | X76: =+U76/($H76+$I76) -> 0 | Y76: 0 | Z76: =$L76 -> 149 | AA76: =+ROUND($Y76*Z76,2) -> 0 | AB76: =+Y76/($H76+$I76) -> 0 | AC76: 1.5 | AD76: =$L76 -> 149 | AE76: =+ROUND($AC76*AD76,2) -> 223.5 | AF76: =+AC76/($H76+$I76) -> 0.89820359
B77: 10.11 | C77: =+C76+1 -> #REF! | D77: Arandela Cuadrada Curva de A° G°, 57 x 57 x 5 mm, Agujero de 18 mm Ø | G77: u | H77: 1.67 | J77: 211 | K77: =+ROUND($H77*J77,2) -> 352.37 | L77: =+'[193]Metrado'!E72 -> 212 | M77: =+ROUND($H77*L77,2) -> 354.04 | N77: 1.22 | O77: =L77 -> 212 | P77: =+ROUND($N77*O77,2) -> 258.64 | Q77: =+N77/($H77+$I77) -> 0.73053892 | R77: =+(H77+I77)-N77 -> 0.45 | S77: =+IFERROR(VLOOKUP(D77,LP!C79:S154,15,0),0) -> 0.45 | T77: =+IFERROR(VLOOKUP(D77,LP!A79:S154,16,0),0) -> 0 | U77: 0 | V77: =$L77 -> 212 | W77: =+ROUND($U77*V77,2) -> 0 | X77: =+U77/($H77+$I77) -> 0 | Y77: 0 | Z77: =$L77 -> 212 | AA77: =+ROUND($Y77*Z77,2) -> 0 | AB77: =+Y77/($H77+$I77) -> 0 | AC77: 1.5 | AD77: =$L77 -> 212 | AE77: =+ROUND($AC77*AD77,2) -> 318 | AF77: =+AC77/($H77+$I77) -> 0.89820359
B78: 10.12 | C78: =+C75+1 -> #REF! | D78: Plantillas para Identificación y/o codificación de Postes (Peligro, Identificación y/o codificación y Fases) | G78: Jgo. | H78: 23.08 | J78: 34 | K78: =+ROUND($H78*J78,2) -> 784.72 | L78: =+'[193]Metrado'!E73 -> 17 | M78: =+ROUND($H78*L78,2) -> 392.36 | N78: 0 | O78: =L78 -> 17 | P78: =+ROUND($N78*O78,2) -> 0 | Q78: =+N78/($H78+$I78) -> 0 | R78: =+(H78+I78)-N78 -> 23.08 | U78: 0 | V78: =$L78 -> 17 | W78: =+ROUND($U78*V78,2) -> 0 | X78: =+U78/($H78+$I78) -> 0 | Y78: 0 | Z78: =$L78 -> 17 | AA78: =+ROUND($Y78*Z78,2) -> 0 | AB78: =+Y78/($H78+$I78) -> 0 | AC78: 0 | AD78: =$L78 -> 17 | AE78: =+ROUND($AC78*AD78,2) -> 0 | AF78: =+AC78/($H78+$I78) -> 0
B79: 10.13 | C79: =+C78+1 -> #REF! | D79: Placa de Señal de Peligro y accesorios de fijación | G79: u | H79: 18.24 | J79: 2 | K79: =+ROUND($H79*J79,2) -> 36.48 | L79: =+'[193]Metrado'!E74 -> 0 | M79: =+ROUND($H79*L79,2) -> 0 | N79: 0 | O79: =L79 -> 0 | P79: =+ROUND($N79*O79,2) -> 0 | Q79: =+N79/($H79+$I79) -> 0 | R79: =+(H79+I79)-N79 -> 18.24 | U79: 0 | V79: =$L79 -> 0 | W79: =+ROUND($U79*V79,2) -> 0 | X79: =+U79/($H79+$I79) -> 0 | Y79: 0 | Z79: =$L79 -> 0 | AA79: =+ROUND($Y79*Z79,2) -> 0 | AB79: =+Y79/($H79+$I79) -> 0 | AC79: 0 | AD79: =$L79 -> 0 | AE79: =+ROUND($AC79*AD79,2) -> 0 | AF79: =+AC79/($H79+$I79) -> 0
B80: 10.14 | C80: =+C77+1 -> #REF! | D80: Placa de Identificación y/o codificación de Estructura y accesorios de fijación | G80: u | H80: 16.84 | J80: 2 | K80: =+ROUND($H80*J80,2) -> 33.68 | L80: =+'[193]Metrado'!E75 -> 0 | M80: =+ROUND($H80*L80,2) -> 0 | N80: 0 | O80: =L80 -> 0 | P80: =+ROUND($N80*O80,2) -> 0 | Q80: =+N80/($H80+$I80) -> 0 | R80: =+(H80+I80)-N80 -> 16.84 | U80: 0 | V80: =$L80 -> 0 | W80: =+ROUND($U80*V80,2) -> 0 | X80: =+U80/($H80+$I80) -> 0 | Y80: 0 | Z80: =$L80 -> 0 | AA80: =+ROUND($Y80*Z80,2) -> 0 | AB80: =+Y80/($H80+$I80) -> 0 | AC80: 0 | AD80: =$L80 -> 0 | AE80: =+ROUND($AC80*AD80,2) -> 0 | AF80: =+AC80/($H80+$I80) -> 0
B81: 10.15 | C81: =+C80+1 -> #REF! | D81: Placa de Secuencia de Fases y accesorios de fijación | G81: u | H81: 18.78 | J81: 2 | K81: =+ROUND($H81*J81,2) -> 37.56 | L81: =+'[193]Metrado'!E76 -> 0 | M81: =+ROUND($H81*L81,2) -> 0 | N81: 0 | O81: =L81 -> 0 | P81: =+ROUND($N81*O81,2) -> 0 | Q81: =+N81/($H81+$I81) -> 0 | R81: =+(H81+I81)-N81 -> 18.78 | U81: 0 | V81: =$L81 -> 0 | W81: =+ROUND($U81*V81,2) -> 0 | X81: =+U81/($H81+$I81) -> 0 | Y81: 0 | Z81: =$L81 -> 0 | AA81: =+ROUND($Y81*Z81,2) -> 0 | AB81: =+Y81/($H81+$I81) -> 0 | AC81: 0 | AD81: =$L81 -> 0 | AE81: =+ROUND($AC81*AD81,2) -> 0 | AF81: =+AC81/($H81+$I81) -> 0
B82: 10.16 | C82: =+#REF!+1 -> #REF! | D82: Perno de A°G° de 16 mm Ø x 457 mm, provisto de tuerca y contratuerca | G82: u | I82: =+H71*1.5 -> 14.73 | K82: =+ROUND($H82*J82,2) -> 0 | L82: =+'[193]Metrado'!E77 -> 6 | M82: =+ROUND($I82*L82,2) -> 88.38 | N82: 11.7 | O82: =L82 -> 6 | P82: =+ROUND($N82*O82,2) -> 70.2 | Q82: =+N82/($H82+$I82) -> 0.79429735 | R82: =+(H82+I82)-N82 -> 3.03 | S82: =+IFERROR(VLOOKUP(D82,LP!C84:S154,15,0),0) -> 0 | T82: =+IFERROR(VLOOKUP(D82,LP!A84:S154,16,0),0) -> 0 | U82: 0 | V82: =$L82 -> 6 | W82: =+ROUND($U82*V82,2) -> 0 | X82: =+U82/($H82+$I82) -> 0 | Y82: 0 | Z82: =$L82 -> 6 | AA82: =+ROUND($Y82*Z82,2) -> 0 | AB82: =+Y82/($H82+$I82) -> 0 | AC82: 0 | AD82: =$L82 -> 6 | AE82: =+ROUND($AC82*AD82,2) -> 0 | AF82: =+AC82/($H82+$I82) -> 0
B83: 10.17 | C83: =+#REF!+1 -> #REF! | D83: Soporte separador de vértice de poste de A°G° fabricado con platina de 76 x 6,4 mm | G83: u | I83: 31.42 | K83: =+ROUND($H83*J83,2) -> 0 | L83: =+'[193]Metrado'!E78 -> 6 | M83: =+ROUND($I83*L83,2) -> 188.52 | N83: 20.19 | O83: =L83 -> 6 | P83: =+ROUND($N83*O83,2) -> 121.14 | Q83: =+N83/($H83+$I83) -> 0.64258434 | R83: =+(H83+I83)-N83 -> 11.23 | S83: =+IFERROR(VLOOKUP(D83,LP!C85:S154,15,0),0) -> 0 | T83: =+IFERROR(VLOOKUP(D83,LP!A85:S154,16,0),0) -> 0 | U83: 0 | V83: =$L83 -> 6 | W83: =+ROUND($U83*V83,2) -> 0 | X83: =+U83/($H83+$I83) -> 0 | Y83: 0 | Z83: =$L83 -> 6 | AA83: =+ROUND($Y83*Z83,2) -> 0 | AB83: =+Y83/($H83+$I83) -> 0 | AC83: 0 | AD83: =$L83 -> 6 | AE83: =+ROUND($AC83*AD83,2) -> 0 | AF83: =+AC83/($H83+$I83) -> 0
B84: 10.18 | C84: =+#REF!+1 -> #REF! | D84: Tubo espaciador de A°G° de 19 mm x 38 mm Ø | G84: u | I84: 3.98 | K84: =+ROUND($H84*J84,2) -> 0 | L84: =+'[193]Metrado'!E79 -> 6 | M84: =+ROUND($I84*L84,2) -> 23.88 | N84: 3.19 | O84: =L84 -> 6 | P84: =+ROUND($N84*O84,2) -> 19.14 | Q84: =+N84/($H84+$I84) -> 0.80150754 | R84: =+(H84+I84)-N84 -> 0.79 | S84: =+IFERROR(VLOOKUP(D84,LP!C86:S154,15,0),0) -> 0 | T84: =+IFERROR(VLOOKUP(D84,LP!A86:S154,16,0),0) -> 0 | U84: 0 | V84: =$L84 -> 6 | W84: =+ROUND($U84*V84,2) -> 0 | X84: =+U84/($H84+$I84) -> 0 | Y84: 0 | Z84: =$L84 -> 6 | AA84: =+ROUND($Y84*Z84,2) -> 0 | AB84: =+Y84/($H84+$I84) -> 0 | AC84: 1.6 | AD84: =$L84 -> 6 | AE84: =+ROUND($AC84*AD84,2) -> 9.6 | AF84: =+AC84/($H84+$I84) -> 0.40201005
C85: =+C84+1 -> #REF! | F85: =+"SUB-TOTAL "&B66&": " -> SUB-TOTAL 10: | K85: =+SUM(K67:K84) -> 3611.97 | M85: =+SUM(M67:M84) -> 3735.48 | N85: 0 | O85: =L85 -> 0 | P85: =+SUM(P67:P84) -> 2427.01 | R85: =+(H85+I85)-N85 -> 0 | U85: 0 | V85: =$L85 -> 0 | W85: =+SUM(W67:W84) -> 0 | Y85: 0 | Z85: =$L85 -> 0 | AA85: =+SUM(AA67:AA84) -> 0 | AC85: 0 | AD85: =$L85 -> 0 | AE85: =+SUM(AE67:AE84) -> 1921.7
B86: =1+B66 -> 11 | C86: =+C18+1 -> 5 | D86: RETENIDAS Y ANCLAJES | N86: 0 | O86: =L86 -> 0 | R86: =+(H86+I86)-N86 -> 0 | U86: 0 | V86: =$L86 -> 0 | Y86: 0 | Z86: =$L86 -> 0 | AC86: 0 | AD86: =$L86 -> 0
B87: 11.01 | C87: =+C86+1 -> 6 | D87: Cable de Acero Grado Siemens Martin, de 10 mm Ø, 7 hilos | G87: u | H87: 4.31 | J87: 154 | K87: =+ROUND($H87*J87,2) -> 663.74 | L87: =+'[193]Metrado'!E82 -> 0 | M87: =+ROUND($H87*L87,2) -> 0 | N87: 0 | O87: =L87 -> 0 | P87: =+ROUND($N87*O87,2) -> 0 | Q87: =+N87/($H87+$I87) -> 0 | R87: =+(H87+I87)-N87 -> 4.31 | U87: 0 | V87: =$L87 -> 0 | W87: =+ROUND($U87*V87,2) -> 0 | X87: =+U87/($H87+$I87) -> 0 | Y87: 0 | Z87: =$L87 -> 0 | AA87: =+ROUND($Y87*Z87,2) -> 0 | AB87: =+Y87/($H87+$I87) -> 0 | AC87: 3.1 | AD87: =$L87 -> 0 | AE87: =+ROUND($AC87*AD87,2) -> 0 | AF87: =+AC87/($H87+$I87) -> 0.71925754
B88: 11.02 | C88: =+C87+1 -> 7 | D88: Varilla de Anclaje de A°G° de 16 mm Ø x 2,40 m, provisto de Ojal Guardacabo en un extremo; Tuerca y Contratuerca en el otro | G88: u | H88: 46.85 | J88: 9 | K88: =+ROUND($H88*J88,2) -> 421.65 | L88: =+'[193]Metrado'!E83 -> 14 | M88: =+ROUND($H88*L88,2) -> 655.9 | N88: 34.96 | O88: =L88 -> 14 | P88: =+ROUND($N88*O88,2) -> 489.44 | Q88: =+N88/($H88+$I88) -> 0.74621131 | R88: =+(H88+I88)-N88 -> 11.89 | S88: =+IFERROR(VLOOKUP(D88,LP!C90:S154,15,0),0) -> 11.89 | T88: =+IFERROR(VLOOKUP(D88,LP!A90:S154,16,0),0) -> 0 | U88: 0 | V88: =$L88 -> 14 | W88: =+ROUND($U88*V88,2) -> 0 | X88: =+U88/($H88+$I88) -> 0 | Y88: 0 | Z88: =$L88 -> 14 | AA88: =+ROUND($Y88*Z88,2) -> 0 | AB88: =+Y88/($H88+$I88) -> 0 | AC88: 27.5 | AD88: =$L88 -> 14 | AE88: =+ROUND($AC88*AD88,2) -> 385 | AF88: =+AC88/($H88+$I88) -> 0.58697972
B89: 11.03 | C89: =+C88+1 -> 8 | D89: Mordaza Preformada de A°G° para Cable de 10 mm Ø | G89: u | H89: 11.69 | J89: 38 | K89: =+ROUND($H89*J89,2) -> 444.22 | L89: =+'[193]Metrado'!E84 -> 72 | M89: =+ROUND($H89*L89,2) -> 841.68 | N89: 8.5 | O89: =L89 -> 72 | P89: =+ROUND($N89*O89,2) -> 612 | Q89: =+N89/($H89+$I89) -> 0.72711719 | R89: =+(H89+I89)-N89 -> 3.19 | S89: =+IFERROR(VLOOKUP(D89,LP!C91:S154,15,0),0) -> 3.19 | T89: =+IFERROR(VLOOKUP(D89,LP!A91:S154,16,0),0) -> 0 | U89: 0 | V89: =$L89 -> 72 | W89: =+ROUND($U89*V89,2) -> 0 | X89: =+U89/($H89+$I89) -> 0 | Y89: 0 | Z89: =$L89 -> 72 | AA89: =+ROUND($Y89*Z89,2) -> 0 | AB89: =+Y89/($H89+$I89) -> 0 | AC89: 7.5 | AD89: =$L89 -> 72 | AE89: =+ROUND($AC89*AD89,2) -> 540 | AF89: =+AC89/($H89+$I89) -> 0.64157399
B90: 11.04 | C90: =+C89+1 -> 9 | D90: Alambre de Acero N° 14 para Entorchado | G90: u | H90: 0.71 | J90: 36 | K90: =+ROUND($H90*J90,2) -> 25.56 | L90: =+'[193]Metrado'!E85 -> 21 | M90: =+ROUND($H90*L90,2) -> 14.91 | N90: 0.4 | O90: =L90 -> 21 | P90: =+ROUND($N90*O90,2) -> 8.4 | Q90: =+N90/($H90+$I90) -> 0.56338028 | R90: =+(H90+I90)-N90 -> 0.31 | S90: =+IFERROR(VLOOKUP(D90,LP!C92:S154,15,0),0) -> 0.31 | T90: =+IFERROR(VLOOKUP(D90,LP!A92:S154,16,0),0) -> 0 | U90: 0 | V90: =$L90 -> 21 | W90: =+ROUND($U90*V90,2) -> 0 | X90: =+U90/($H90+$I90) -> 0 | Y90: 0 | Z90: =$L90 -> 21 | AA90: =+ROUND($Y90*Z90,2) -> 0 | AB90: =+Y90/($H90+$I90) -> 0 | AC90: 0.6 | AD90: =$L90 -> 21 | AE90: =+ROUND($AC90*AD90,2) -> 12.6 | AF90: =+AC90/($H90+$I90) -> 0.84507042
B91: 11.05 | C91: =+C90+1 -> 10 | D91: Arandela de Anclaje de A°G°, 102 x 102 x 6,35 mm, Agujero de 18 mmø | G91: u | H91: 5.46 | J91: 9 | K91: =+ROUND($H91*J91,2) -> 49.14 | L91: =+'[193]Metrado'!E86 -> 14 | M91: =+ROUND($H91*L91,2) -> 76.44 | N91: 4.56 | O91: =L91 -> 14 | P91: =+ROUND($N91*O91,2) -> 63.84 | Q91: =+N91/($H91+$I91) -> 0.83516484 | R91: =+(H91+I91)-N91 -> 0.9 | S91: =+IFERROR(VLOOKUP(D91,LP!C93:S154,15,0),0) -> 0.9 | T91: =+IFERROR(VLOOKUP(D91,LP!A93:S154,16,0),0) -> 0 | U91: 0 | V91: =$L91 -> 14 | W91: =+ROUND($U91*V91,2) -> 0 | X91: =+U91/($H91+$I91) -> 0 | Y91: 0 | Z91: =$L91 -> 14 | AA91: =+ROUND($Y91*Z91,2) -> 0 | AB91: =+Y91/($H91+$I91) -> 0 | AC91: 5 | AD91: =$L91 -> 14 | AE91: =+ROUND($AC91*AD91,2) -> 70 | AF91: =+AC91/($H91+$I91) -> 0.91575092
B92: 11.06 | C92: =+C91+1 -> 11 | D92: Grillete de Acero de 70 kN | G92: u | H92: 15.01 | J92: 16 | K92: =+ROUND($H92*J92,2) -> 240.16 | L92: =+'[193]Metrado'!E87 -> 14 | M92: =+ROUND($H92*L92,2) -> 210.14 | N92: 10.64 | O92: =L92 -> 14 | P92: =+ROUND($N92*O92,2) -> 148.96 | Q92: =+N92/($H92+$I92) -> 0.70886076 | R92: =+(H92+I92)-N92 -> 4.37 | S92: =+IFERROR(VLOOKUP(D92,LP!C94:S154,15,0),0) -> 4.37 | T92: =+IFERROR(VLOOKUP(D92,LP!A94:S154,16,0),0) -> 0 | U92: 0 | V92: =$L92 -> 14 | W92: =+ROUND($U92*V92,2) -> 0 | X92: =+U92/($H92+$I92) -> 0 | Y92: 0 | Z92: =$L92 -> 14 | AA92: =+ROUND($Y92*Z92,2) -> 0 | AB92: =+Y92/($H92+$I92) -> 0 | AC92: 8.2 | AD92: =$L92 -> 14 | AE92: =+ROUND($AC92*AD92,2) -> 114.8 | AF92: =+AC92/($H92+$I92) -> 0.54630247
B93: 11.07 | C93: =+C92+1 -> 12 | D93: Enlace metálico, de 254 mm x 75 mm x 38 mm, de 70 kN de resistencia | G93: m | H93: 28.99 | J93: 9 | K93: =+ROUND($H93*J93,2) -> 260.91 | L93: =+'[193]Metrado'!E88 -> 14 | M93: =+ROUND($H93*L93,2) -> 405.86 | N93: 17.63 | O93: =L93 -> 14 | P93: =+ROUND($N93*O93,2) -> 246.82 | Q93: =+N93/($H93+$I93) -> 0.60814074 | R93: =+(H93+I93)-N93 -> 11.36 | S93: =+IFERROR(VLOOKUP(D93,LP!C95:S154,15,0),0) -> 11.36 | T93: =+IFERROR(VLOOKUP(D93,LP!A95:S154,16,0),0) -> 0 | U93: 0 | V93: =$L93 -> 14 | W93: =+ROUND($U93*V93,2) -> 0 | X93: =+U93/($H93+$I93) -> 0 | Y93: 0 | Z93: =$L93 -> 14 | AA93: =+ROUND($Y93*Z93,2) -> 0 | AB93: =+Y93/($H93+$I93) -> 0 | AC93: 23 | AD93: =$L93 -> 14 | AE93: =+ROUND($AC93*AD93,2) -> 322 | AF93: =+AC93/($H93+$I93) -> 0.79337703
B94: 11.08 | C94: =+C93+1 -> 13 | D94: Aislador Polimerico con Conexión Horquilla (Estructura) y Lengüeta (Linea) de 36 kV, según Especificacion Técnica, para Retenida Aislada. | G94: u | H94: 76.66 | J94: 9 | K94: =+ROUND($H94*J94,2) -> 689.94 | L94: =+'[193]Metrado'!E89 -> 14 | M94: =+ROUND($H94*L94,2) -> 1073.24 | N94: 0 | O94: =L94 -> 14 | P94: =+ROUND($N94*O94,2) -> 0 | Q94: =+N94/($H94+$I94) -> 0 | R94: =+(H94+I94)-N94 -> 76.66 | U94: 0 | V94: =$L94 -> 14 | W94: =+ROUND($U94*V94,2) -> 0 | X94: =+U94/($H94+$I94) -> 0 | Y94: 0 | Z94: =$L94 -> 14 | AA94: =+ROUND($Y94*Z94,2) -> 0 | AB94: =+Y94/($H94+$I94) -> 0 | AC94: 0 | AD94: =$L94 -> 14 | AE94: =+ROUND($AC94*AD94,2) -> 0 | AF94: =+AC94/($H94+$I94) -> 0
B95: 11.09 | C95: =+C94+1 -> 14 | D95: Bloque de Concreto de 0,40 x 0,40 x 0,15 m | G95: u | H95: 40.94 | J95: 9 | K95: =+ROUND($H95*J95,2) -> 368.46 | L95: =+'[193]Metrado'!E90 -> 14 | M95: =+ROUND($H95*L95,2) -> 573.16 | N95: 0 | O95: =L95 -> 14 | P95: =+ROUND($N95*O95,2) -> 0 | Q95: =+N95/($H95+$I95) -> 0 | R95: =+(H95+I95)-N95 -> 40.94 | U95: 0 | V95: =$L95 -> 14 | W95: =+ROUND($U95*V95,2) -> 0 | X95: =+U95/($H95+$I95) -> 0 | Y95: 0 | Z95: =$L95 -> 14 | AA95: =+ROUND($Y95*Z95,2) -> 0 | AB95: =+Y95/($H95+$I95) -> 0 | AC95: 0 | AD95: =$L95 -> 14 | AE95: =+ROUND($AC95*AD95,2) -> 0 | AF95: =+AC95/($H95+$I95) -> 0
B96: 11.1 | C96: =+C95+1 -> 15 | D96: Tuerca-Ojo para Perno de 16 mm Ø | G96: u | H96: 11.17 | J96: 5 | K96: =+ROUND($H96*J96,2) -> 55.85 | L96: =+'[193]Metrado'!E91 -> 8 | M96: =+ROUND($H96*L96,2) -> 89.36 | N96: 8.69 | O96: =L96 -> 8 | P96: =+ROUND($N96*O96,2) -> 69.52 | Q96: =+N96/($H96+$I96) -> 0.77797672 | R96: =+(H96+I96)-N96 -> 2.48 | S96: =+IFERROR(VLOOKUP(D96,LP!C98:S154,15,0),0) -> 2.48 | T96: =+IFERROR(VLOOKUP(D96,LP!A98:S154,16,0),0) -> 0 | U96: 0 | V96: =$L96 -> 8 | W96: =+ROUND($U96*V96,2) -> 0 | X96: =+U96/($H96+$I96) -> 0 | Y96: 0 | Z96: =$L96 -> 8 | AA96: =+ROUND($Y96*Z96,2) -> 0 | AB96: =+Y96/($H96+$I96) -> 0 | AC96: 5.4 | AD96: =$L96 -> 8 | AE96: =+ROUND($AC96*AD96,2) -> 43.2 | AF96: =+AC96/($H96+$I96) -> 0.48343778
B97: 11.11 | C97: =+C96+1 -> 16 | D97: Abrazadera de 4 sectores para Retenida, de 75 mm de altura, 6,35 mm de espesor y 70 kN de resistencia. Diámetro según dimensiones del poste, incluye 4 pernos de 12,7 mm Ø x 63,5 mm y 4 arandelas | G97: u | H97: 81.85 | J97: 9 | K97: =+ROUND($H97*J97,2) -> 736.65 | L97: =+'[193]Metrado'!E92 -> 14 | M97: =+ROUND($H97*L97,2) -> 1145.9 | N97: 55 | O97: =L97 -> 14 | P97: =+ROUND($N97*O97,2) -> 770 | Q97: =+N97/($H97+$I97) -> 0.6719609 | R97: =+(H97+I97)-N97 -> 26.85 | S97: =+IFERROR(VLOOKUP(D97,LP!C99:S154,15,0),0) -> 33.85 | T97: =+IFERROR(VLOOKUP(D97,LP!A99:S154,16,0),0) -> 0 | U97: 0 | V97: =$L97 -> 14 | W97: =+ROUND($U97*V97,2) -> 0 | X97: =+U97/($H97+$I97) -> 0 | Y97: 0 | Z97: =$L97 -> 14 | AA97: =+ROUND($Y97*Z97,2) -> 0 | AB97: =+Y97/($H97+$I97) -> 0 | AC97: 56 | AD97: =$L97 -> 14 | AE97: =+ROUND($AC97*AD97,2) -> 784 | AF97: =+AC97/($H97+$I97) -> 0.68417838
B98: 11.12 | C98: =+C97+1 -> 17 | D98: Cable de acero grado Alta Resistencia (HS), de 10 mm ø, 7 hilos | G98: u | I98: =+H87 -> 4.31 | K98: =+ROUND($H98*J98,2) -> 0 | L98: =+'[193]Metrado'!E93 -> 212 | M98: =+ROUND($I98*L98,2) -> 913.72 | N98: 2.8 | O98: =L98 -> 212 | P98: =+ROUND($N98*O98,2) -> 593.6 | Q98: =+N98/($H98+$I98) -> 0.64965197 | R98: =+(H98+I98)-N98 -> 1.51 | S98: =+IFERROR(VLOOKUP(D98,LP!C100:S154,15,0),0) -> 1.51 | T98: =+IFERROR(VLOOKUP(D98,LP!A100:S154,16,0),0) -> 0 | U98: 0 | V98: =$L98 -> 212 | W98: =+ROUND($U98*V98,2) -> 0 | X98: =+U98/($H98+$I98) -> 0 | Y98: 0 | Z98: =$L98 -> 212 | AA98: =+ROUND($Y98*Z98,2) -> 0 | AB98: =+Y98/($H98+$I98) -> 0 | AC98: 0 | AD98: =$L98 -> 212 | AE98: =+ROUND($AC98*AD98,2) -> 0 | AF98: =+AC98/($H98+$I98) -> 0
C99: =+#REF!+1 -> #REF! | F99: =+"SUB-TOTAL "&B86&": " -> SUB-TOTAL 11: | K99: =+SUM(K87:K98) -> 3956.28 | M99: =+SUM(M87:M98) -> 6000.31 | N99: 0 | O99: =L99 -> 0 | P99: =+SUM(P87:P98) -> 3002.58 | R99: =+(H99+I99)-N99 -> 0 | U99: 0 | V99: =$L99 -> 0 | W99: =+SUM(W87:W98) -> 0 | Y99: 0 | Z99: =$L99 -> 0 | AA99: =+SUM(AA87:AA98) -> 0 | AC99: 0 | AD99: =$L99 -> 0 | AE99: =+SUM(AE87:AE98) -> 2271.6
B100: =1+B86 -> 12 | C100: =+#REF!+1 -> #REF! | D100: MATERIAL PARA PUESTA A TIERRA | N100: 0 | O100: =L100 -> 0 | R100: =+(H100+I100)-N100 -> 0 | U100: 0 | V100: =$L100 -> 0 | Y100: 0 | Z100: =$L100 -> 0 | AC100: 0 | AD100: =$L100 -> 0
B101: 12.01 | C101: =+C100+1 -> #REF! | D101: Electrodo de Acero Recubierto de Cobre de 16 mm Ø x 2,40 m | G101: u | H101: 66.7 | J101: 49 | K101: =+ROUND($H101*J101,2) -> 3268.3 | L101: =+'[193]Metrado'!E96 -> 45 | M101: =+ROUND($H101*L101,2) -> 3001.5 | N101: 49 | O101: =L101 -> 45 | P101: =+ROUND($N101*O101,2) -> 2205 | Q101: =+N101/($H101+$I101) -> 0.73463268 | R101: =+(H101+I101)-N101 -> 17.7 | S101: =+IFERROR(VLOOKUP(D101,LP!C103:S154,15,0),0) -> 17.7 | T101: =+IFERROR(VLOOKUP(D101,LP!A103:S154,16,0),0) -> 0 | U101: 0 | V101: =$L101 -> 45 | W101: =+ROUND($U101*V101,2) -> 0 | X101: =+U101/($H101+$I101) -> 0 | Y101: 0 | Z101: =$L101 -> 45 | AA101: =+ROUND($Y101*Z101,2) -> 0 | AB101: =+Y101/($H101+$I101) -> 0 | AC101: 48 | AD101: =$L101 -> 45 | AE101: =+ROUND($AC101*AD101,2) -> 2160 | AF101: =+AC101/($H101+$I101) -> 0.71964018
B102: 12.02 | C102: =+C101+1 -> #REF! | D102: Caja Registro de Concreto para Puesta a Tierra 0,50 x 0,50 x 0,45 m | G102: u | H102: 53.58 | J102: 49 | K102: =+ROUND($H102*J102,2) -> 2625.42 | L102: =+'[193]Metrado'!E97 -> 45 | M102: =+ROUND($H102*L102,2) -> 2411.1 | N102: 0 | O102: =L102 -> 45 | P102: =+ROUND($N102*O102,2) -> 0 | Q102: =+N102/($H102+$I102) -> 0 | R102: =+(H102+I102)-N102 -> 53.58 | U102: 0 | V102: =$L102 -> 45 | W102: =+ROUND($U102*V102,2) -> 0 | X102: =+U102/($H102+$I102) -> 0 | Y102: 0 | Z102: =$L102 -> 45 | AA102: =+ROUND($Y102*Z102,2) -> 0 | AB102: =+Y102/($H102+$I102) -> 0 | AC102: 0 | AD102: =$L102 -> 45 | AE102: =+ROUND($AC102*AD102,2) -> 0 | AF102: =+AC102/($H102+$I102) -> 0
B103: 12.03 | C103: =+C102+1 -> #REF! | D103: Plancha Doblada de Cobre para toma a Tierra de Espigas y/o Pernos | G103: u | H103: 10.54 | J103: 72 | K103: =+ROUND($H103*J103,2) -> 758.88 | L103: =+'[193]Metrado'!E98 -> 117 | M103: =+ROUND($H103*L103,2) -> 1233.18 | N103: 9.27 | O103: =L103 -> 117 | P103: =+ROUND($N103*O103,2) -> 1084.59 | Q103: =+N103/($H103+$I103) -> 0.87950664 | R103: =+(H103+I103)-N103 -> 1.27 | S103: =+IFERROR(VLOOKUP(D103,LP!C105:S154,15,0),0) -> 1.27 | T103: =+IFERROR(VLOOKUP(D103,LP!A105:S154,16,0),0) -> 0 | U103: 8.2 | V103: =$L103 -> 117 | W103: =+ROUND($U103*V103,2) -> 959.4 | X103: =+U103/($H103+$I103) -> 0.77798861 | Y103: 8.2 | Z103: =$L103 -> 117 | AA103: =+ROUND($Y103*Z103,2) -> 959.4 | AB103: =+Y103/($H103+$I103) -> 0.77798861 | AC103: 7.5 | AD103: =$L103 -> 117 | AE103: =+ROUND($AC103*AD103,2) -> 877.5 | AF103: =+AC103/($H103+$I103) -> 0.71157495
B104: 12.04 | C104: =+C103+1 -> #REF! | D104: Conector de Bronce para Electrodo de 16 mm ø y Cable de Acero con Recubrimiento Metalúrgico de Cobre de 4 AWG (21,15 mm2) | G104: u | H104: 6.94 | J104: 49 | K104: =+ROUND($H104*J104,2) -> 340.06 | L104: =+'[193]Metrado'!E99 -> 45 | M104: =+ROUND($H104*L104,2) -> 312.3 | N104: 4.56 | O104: =L104 -> 45 | P104: =+ROUND($N104*O104,2) -> 205.2 | Q104: =+N104/($H104+$I104) -> 0.65706052 | R104: =+(H104+I104)-N104 -> 2.38 | S104: =+IFERROR(VLOOKUP(D104,LP!C106:S154,15,0),0) -> 2.38 | T104: =+IFERROR(VLOOKUP(D104,LP!A106:S154,16,0),0) -> 0 | U104: 0 | V104: =$L104 -> 45 | W104: =+ROUND($U104*V104,2) -> 0 | X104: =+U104/($H104+$I104) -> 0 | Y104: 0 | Z104: =$L104 -> 45 | AA104: =+ROUND($Y104*Z104,2) -> 0 | AB104: =+Y104/($H104+$I104) -> 0 | AC104: 4.3 | AD104: =$L104 -> 45 | AE104: =+ROUND($AC104*AD104,2) -> 193.5 | AF104: =+AC104/($H104+$I104) -> 0.61959654
B105: 12.05 | C105: =+C104+1 -> #REF! | D105: Conector de Cobre tipo Perno Partido para Cable de Acero con Recubrimiento Metalúrgico de Cobre de 4 AWG (21,15 mm2) | G105: u | H105: 7.4 | J105: 150 | K105: =+ROUND($H105*J105,2) -> 1110 | L105: =+[193]Metrado!E100 -> 101 | M105: =+ROUND($H105*L105,2) -> 747.4 | N105: 5.2 | O105: =L105 -> 101 | P105: =+ROUND($N105*O105,2) -> 525.2 | Q105: =+N105/($H105+$I105) -> 0.7027027 | R105: =+(H105+I105)-N105 -> 2.2 | S105: =+IFERROR(VLOOKUP(D105,LP!C107:S154,15,0),0) -> 2.2 | T105: =+IFERROR(VLOOKUP(D105,LP!A107:S154,16,0),0) -> 0 | U105: 0 | V105: =$L105 -> 101 | W105: =+ROUND($U105*V105,2) -> 0 | X105: =+U105/($H105+$I105) -> 0 | Y105: 0 | Z105: =$L105 -> 101 | AA105: =+ROUND($Y105*Z105,2) -> 0 | AB105: =+Y105/($H105+$I105) -> 0 | AC105: 5 | AD105: =$L105 -> 101 | AE105: =+ROUND($AC105*AD105,2) -> 505 | AF105: =+AC105/($H105+$I105) -> 0.67567568
B106: 12.06 | C106: =+C105+1 -> #REF! | D106: Grapa en "U" para fijar conductor de PAT a Madera | G106: u | H106: 0.47 | J106: 140 | K106: =+ROUND($H106*J106,2) -> 65.8 | L106: =+'[193]Metrado'!E101 -> 40 | M106: =+ROUND($H106*L106,2) -> 18.8 | N106: 0.12 | O106: =L106 -> 40 | P106: =+ROUND($N106*O106,2) -> 4.8 | Q106: =+N106/($H106+$I106) -> 0.25531915 | R106: =+(H106+I106)-N106 -> 0.35 | S106: =+IFERROR(VLOOKUP(D106,LP!C108:S154,15,0),0) -> 0.35 | T106: =+IFERROR(VLOOKUP(D106,LP!A108:S154,16,0),0) -> 0 | U106: 0 | V106: =$L106 -> 40 | W106: =+ROUND($U106*V106,2) -> 0 | X106: =+U106/($H106+$I106) -> 0 | Y106: 0 | Z106: =$L106 -> 40 | AA106: =+ROUND($Y106*Z106,2) -> 0 | AB106: =+Y106/($H106+$I106) -> 0 | AC106: 0 | AD106: =$L106 -> 40 | AE106: =+ROUND($AC106*AD106,2) -> 0 | AF106: =+AC106/($H106+$I106) -> 0
B107: 12.07 | C107: =+C106+1 -> #REF! | D107: Tubo Plastico de PVC SAP de 19 mm ø x 0,5 m ( incluye curva de plastico de 19 mm ø x 90º) | G107: u | H107: 2.39 | J107: 34 | K107: =+ROUND($H107*J107,2) -> 81.26 | L107: =+'[193]Metrado'!E102 -> 59 | M107: =+ROUND($H107*L107,2) -> 141.01 | N107: 0 | O107: =L107 -> 59 | P107: =+ROUND($N107*O107,2) -> 0 | Q107: =+N107/($H107+$I107) -> 0 | R107: =+(H107+I107)-N107 -> 2.39 | U107: 0 | V107: =$L107 -> 59 | W107: =+ROUND($U107*V107,2) -> 0 | X107: =+U107/($H107+$I107) -> 0 | Y107: 0 | Z107: =$L107 -> 59 | AA107: =+ROUND($Y107*Z107,2) -> 0 | AB107: =+Y107/($H107+$I107) -> 0 | AC107: 2.5 | AD107: =$L107 -> 59 | AE107: =+ROUND($AC107*AD107,2) -> 147.5 | AF107: =+AC107/($H107+$I107) -> 1.0460251
B108: 12.08 | C108: =+C107+1 -> #REF! | D108: Placa de Señalización de Poste (Puesta a Tierra) | G108: u | H108: 17.43 | J108: 2 | K108: =+ROUND($H108*J108,2) -> 34.86 | L108: =+'[193]Metrado'!E103 -> 0 | M108: =+ROUND($H108*L108,2) -> 0 | N108: 0 | O108: =L108 -> 0 | P108: =+ROUND($N108*O108,2) -> 0 | Q108: =+N108/($H108+$I108) -> 0 | R108: =+(H108+I108)-N108 -> 17.43 | U108: 0 | V108: =$L108 -> 0 | W108: =+ROUND($U108*V108,2) -> 0 | X108: =+U108/($H108+$I108) -> 0 | Y108: 0 | Z108: =$L108 -> 0 | AA108: =+ROUND($Y108*Z108,2) -> 0 | AB108: =+Y108/($H108+$I108) -> 0 | AC108: 0 | AD108: =$L108 -> 0 | AE108: =+ROUND($AC108*AD108,2) -> 0 | AF108: =+AC108/($H108+$I108) -> 0
...

Sheet FP RP
B3: FORMULA POLINÓMICA
C6: PROYECTO :
C7: AMPLIACIÓN DEL SERVICIO DE ENERGÍA ELÉCTRICA EN LA PROVINCIA DEL SANTA Y EN EL DISTRITO DE PAMPAROMAS – DEPARTAMENTO DE ANCASH”
C9: REDES PRIMARIAS
C10: PRESUPUESTO BASE S/ | D10: =+'RES-RP'!H18 -> #REF! | L10: =D10=SUM(G13:G28) -> #REF!
B12: Nº | C12: ELEMENTO REPRESENTATIVO | D12: INDICE | E12: SIMBOLO | F12: SIMBOLO MONOMIO | G12: MONTO | H12: INCIDENCIA | I12: % PARCIAL | J12: COEFICIENTE
B13: 1 | C13: POSTES DE MADERA IMPORTADA | D13: 042 | E13: PM | F13: PC | G13: =+RP!M31 -> 0 | H13: =ROUND(G13/$D$10,3) -> #REF! | I13: =ROUND(G13/SUM($G$13:$G$20),4) -> 0 | J13: =ROUND(SUM(H13:H20),3) -> #REF!
C14: CRUCETAS DE MADERA | D14: 043 | E14: CM | G14: =+RP!M22 -> 2021 | H14: =ROUND(G14/$D$10,3) -> #REF! | I14: =ROUND(G14/SUM($G$13:$G$20),4) -> 0.022
C15: POSTES DE CONCRETO | D15: 062 | E15: PC | G15: =+RP!M28+RP!M35 -> 53371.71 | H15: =ROUND(G15/$D$10,3) -> #REF! | I15: =ROUND(G15/SUM($G$13:$G$20),4)+0.0001 -> 0.5812
C16: OTROS MATERIALES DE CONCRETO ARMADO | D16: 062 | E16: CC | G16: =+RP!M40 -> 9029.5 | H16: =ROUND(G16/$D$10,3) -> #REF! | I16: =ROUND(G16/SUM($G$13:$G$20),4) -> 0.0983
C17: FERRETERIA PARA POSTES Y CRUCETAS | D17: 002 | E17: FP | G17: =+RP!M85 -> 3735.48 | H17: =ROUND(G17/$D$10,3) -> #REF! | I17: =ROUND(G17/SUM($G$13:$G$20),4) -> 0.0407
C18: RETENIDAS Y ANCLAJES | D18: 002 | E18: FE | G18: =+RP!M99 -> 6000.31 | H18: =ROUND(G18/$D$10,3) -> #REF! | I18: =ROUND(G18/SUM($G$13:$G$20),4) -> 0.0653
C19: CONDUCTOR DE COBRE Y ACCESORIOS | D19: 006 | E19: CU | G19: =+RP!M65 -> 5523.2 | H19: =ROUND(G19/$D$10,3) -> #REF! | I19: =ROUND(G19/SUM($G$13:$G$20),4) -> 0.0601
C20: MATERIAL PARA PUESTA A TIERRA | D20: 006 | E20: PT | G20: =+RP!M111 -> 12159.04 | H20: =ROUND(G20/$D$10,3+0.1) -> #REF! | I20: =ROUND(G20/SUM($G$13:$G$20),4) -> 0.1324
B21: 2 | C21: EQUIPOS DE PROTECCIÓN | D21: 011 | E21: AE1 | F21: AE1 | G21: =+RP!M117 -> 14296.26 | H21: =ROUND(G21/$D$10,3) -> #REF! | I21: =ROUND(G21/SUM($G$21:$G$24),4) -> 0.3262 | J21: =ROUND(SUM(H21:H24),3) -> #REF!
C22: AISLADORES Y ACCESORIOS | D22: 011 | E22: AE2 | G22: =+RP!M47+RP!M51 -> 15572.01 | H22: =ROUND(G22/$D$10,3) -> #REF! | I22: =ROUND(G22/SUM($G$21:$G$24),4)+0.0001 -> 0.3554
C23: CABLES DE ENERGÍA | D23: 019 | E23: NY | G23: =+RP!M135 -> 3267.22 | H23: =ROUND(G23/$D$10,3) -> #REF! | I23: =ROUND(G23/SUM($G$21:$G$24),4) -> 0.0745
C24: CONDUCTORES DE AAAC Y ACCESORIOS | D24: 030 | E24: DI | G24: =+RP!M54+RP!M62 -> 10691.09 | H24: =ROUND(G24/$D$10,3) -> #REF! | I24: =ROUND(G24/SUM($G$21:$G$24),4) -> 0.2439
B25: 3 | C25: TRANSFORMADORES DE DISTRIBUCIÓN Y TABLEROS | D25: 048 | E25: EN | F25: EN | G25: =+RP!M124+RP!M130 -> 87538.77 | H25: =ROUND(G25/$D$10,3) -> #REF! | I25: =ROUND(G25/SUM($G$25:$G$25),4) -> 1 | J25: =ROUND(SUM(H25),3) -> #REF!
B26: 4 | C26: MONTAJE ELECTROMECANICO | D26: 047 | E26: J | F26: J | G26: =+RP!#REF! -> #REF! | H26: =ROUND(G26/$D$10,3) -> #REF! | I26: =ROUND(G26/($G$26+$G$27),4) -> #REF! | J26: =ROUND(SUM(H26:H27),3) -> #REF!
C27: TRANSPORTE | D27: 032 | E27: FT | G27: =+RP!#REF! -> #REF! | H27: =ROUND(G27/$D$10,3) -> #REF! | I27: =ROUND(G27/($G$26+$G$27),4) -> #REF!
B28: 5 | C28: GASTOS GENERALES Y UTILIDADES | D28: 039 | E28: GG | F28: GG | G28: =+'RES-RP'!H16+'RES-RP'!H17 -> #REF! | H28: =ROUND(G28/$D$10,3) -> #REF! | I28: =+G28/G28 -> #REF! | J28: =ROUND(SUM(H28),3) -> #REF!
B30: K= | C30: =J13&" PCr/PCo + "&J21&" AE1r/AE1o + "&J25&" ENr/ENo+ "&J26&" Jr/Jo + "&J28&" GGr/GGo" -> #REF!
B33: NOTAS:
B35: 1.- | C35: En la fórmula los sub-indices "o" de cada símbolo corresponden al indice de precios según (CREPCO) a la
C36: fecha de Elaboración del Presupuesto (Presupuesto Base) y los sub-indices "r" al indice de precios al
C37: momento de reajuste o fecha de valorización
B38: 2.- | C38: En el caso de los monomios compuestos por varios indices se ha considerado para efecto de denominación
C39: el símbolo que tiene mayor porcentaje de incidencia
B40: 3.- | C40: En caso de cambios en el suministro se deberá actualizar la formula polinómica.
H42: =+IF(SUM(H13:H28)=1,"OK","X") -> #REF! | I42: =+IF(SUM(I13:I28)=5,"OK","X") -> #REF! | J42: =+IF(SUM(J13:J28)=1,"OK","X") -> #REF!

Sheet RES-RS
B2: RESUMEN PRESUPUESTO DE OBRA
B4: AMPLIACIÓN DEL SERVICIO DE ENERGÍA ELÉCTRICA EN LA PROVINCIA DEL SANTA Y EN EL DISTRITO DE PAMPAROMAS – DEPARTAMENTO DE ANCASH
B6: UBICACIÓN | C6: : | D6: ANCASH
B7: SECCIÓN III | C7: : | D7: REDES SECUNDARIAS | H7: Fecha: 30-May-2022
H8: T.C. (S/ /US$): 3,683
B9: ITEM | C9: DESCRIPCION | G9: PRESUPUESTO CONTRATO | H9: PRESUPUESTO ESTUDIO DEFINIVO | I9: ADICIONALES | K9: DEDUCTIVOS
I10: MAYORES METRADOS | J10: PARTIDAS NUEVAS | K10: MENOR METRADO | L10: DEDUCTIVO VINCULANTE
B12: A | D12: SUMINISTRO DE MATERIALES | G12: =+RS!K127 -> 301377.1 | H12: =+RS!M127 -> 420410.61 | I12: =+RS!#REF! -> #REF! | J12: =+RS!#REF! -> #REF! | K12: =+RS!#REF! -> #REF! | L12: =+RS!#REF! -> #REF!
B13: B | D13: MONTAJE ELECTROMECANICO | G13: =+RS!#REF! -> #REF! | H13: =+RS!#REF! -> #REF! | I13: =+RS!#REF! -> #REF! | J13: =+RS!#REF! -> #REF! | K13: =+RS!#REF! -> #REF! | L13: =+RS!#REF! -> #REF!
B14: C | D14: TRANSPORTE DE MATERIALES | G14: =+RS!#REF! -> #REF! | H14: =+RS!#REF! -> #REF! | I14: =+RS!#REF! -> #REF! | J14: =+RS!#REF! -> #REF! | K14: =+RS!#REF! -> #REF! | L14: =+RS!#REF! -> #REF!
B15: D | D15: TOTAL COSTO DIRECTO | G15: =+SUM(G12:G14) -> #REF! | H15: =+SUM(H12:H14) -> #REF! | I15: =+SUM(I12:I14) -> #REF! | J15: =+SUM(J12:J14) -> #REF! | K15: =+SUM(K12:K14) -> #REF! | L15: =+SUM(L12:L14) -> #REF!
B16: E | D16: GASTOS GENERALES (10.12%) | G16: =ROUND(G15*10.12%,2) -> #REF! | H16: =ROUND(H15*10.12%,2) -> #REF! | I16: =ROUND(I15*10.12%,2) -> #REF! | J16: =ROUND(J15*10.12%,2) -> #REF! | K16: =ROUND(K15*10.12%,2) -> #REF! | L16: =ROUND(L15*10.12%,2) -> #REF!
B17: F | D17: UTILIDADES (3%) | G17: =ROUND(G15*3%,2) -> #REF! | H17: =ROUND(H15*3%,2) -> #REF! | I17: =ROUND(I15*3%,2) -> #REF! | J17: =ROUND(J15*3%,2) -> #REF! | K17: =ROUND(K15*3%,2) -> #REF! | L17: =ROUND(L15*3%,2) -> #REF!
B18: G | D18: COSTO TOTAL S/. (No incluye I.G.V.) | G18: =G17+G16+G15 -> #REF! | H18: =H17+H16+H15 -> #REF! | I18: =I17+I16+I15 -> #REF! | J18: =J17+J16+J15 -> #REF! | K18: =K17+K16+K15 -> #REF! | L18: =L17+L16+L15 -> #REF! | M18: =+H18-G18 -> #REF!
D20: INCIDENCIA % | G20: =+G18/G18 -> #REF! | H20: =+H18/$G$18 -> #REF! | I20: =+I18/$G$18 -> #REF! | J20: =+J18/$G$18 -> #REF! | K20: =+K18/$G$18 -> #REF! | L20: =+L18/$G$18 -> #REF!
H22: =+H18-I18+K18-J18 -> #REF! | K22: =+G12-H12+I12+J12-K12 -> #REF!
H23: =+G18-H22 -> #REF! | K23: =+G13-H13+I13+J13-K13 -> #REF!
K24: =+G14-H14+I14+J14-K14 -> #REF!
K25: =+G15-H15+I15+J15-K15 -> #REF!

Sheet RS
B6: COMPARATIVO DE PRECIOS
B8: OBRA | E8: : | F8: =+'RES-GRAL OBRA'!F4:L4 -> AMPLIACIÓN DEL SERVICIO DE ENERGÍA ELÉCTRICA EN LA PROVINCIA DEL SANTA Y EN EL DISTRITO DE PAMPAROMAS – DEPARTAMENTO DE ANCASH
B9: DEPARTAMENTO | E9: : | F9: =+'RES-GRAL OBRA'!F5 -> ANCASH
B10: SECCIÓN III | E10: : | F10: REDES SECUNDARIAS
B12: ITEM | C12: DESCRIPCIÓN DE PARTIDAS | G12: UNID. | H12: Precio de Contrato | I12: Precio Pactado | J12: CONTRACTUAL | L12: ESTUDIO DEFINITIVO | N12: PRECIO DE VENTA | O12: MENDOZA | R12: DIFERENCIA DE PRECIOS | U12: PRECIO DE VENTA | V12: GELCO/Group Electric JYM Sac PU | Y12: PRECIO DE VENTA | Z12: EL DETALLE | AC12: PRECIO DE VENTA | AD12: CIE
J13: Metrado | K13: TOTAL | L13: Metrado | M13: TOTAL | O13: Metrado | P13: TOTAL | Q13: % | V13: Metrado | W13: TOTAL | X13: % | Z13: Metrado | AA13: TOTAL | AB13: % | AD13: Metrado | AE13: TOTAL | AF13: %
H15: Unitario | I15: Unitario | J15: Cantidad | K15: S/. | L15: Cantidad | M15: S/. | N15: S/. | O15: Cantidad | P15: S/. | R15: S/. | U15: S/. | V15: Cantidad | W15: S/. | Y15: S/. | Z15: Cantidad | AA15: S/. | AC15: S/. | AD15: Cantidad | AE15: S/.
B16: A | D16: SUMINISTRO DE MATERIALES
B17: 1 | C17: 3 | D17: POSTES DE CONCRETO ARMADO Y MADERA IMPORTADA
B18: =+B17+0.01 -> 1.01 | C18: =+C17+1 -> 4 | D18: Poste de C.A.C. de 8 m/200 daN (Incluye perilla) | G18: u | H18: 372.21 | J18: 153 | K18: =+ROUND($H18*J18,2) -> 56948.13 | L18: =+[194]Metrado!F12 -> 141 | M18: =+ROUND($H18*L18,2) -> 52481.61 | N18: 0 | O18: =+L18 -> 141 | P18: =+ROUND($N18*O18,2) -> 0 | Q18: =+N18/($H18+$I18) -> 0 | R18: =+(H18+I18)-N18 -> 372.21 | U18: 0 | V18: =+L18 -> 141 | W18: =+ROUND($U18*V18,2) -> 0 | X18: =+U18/($H18+$I18) -> 0 | Y18: 0 | Z18: =+V18 -> 141 | AA18: =+ROUND($Y18*Z18,2) -> 0 | AB18: =+Y18/($H18+$I18) -> 0 | AC18: 0 | AD18: =+Z18 -> 141 | AE18: =+ROUND($AC18*AD18,2) -> 0 | AF18: =+AC18/($H18+$I18) -> 0
B19: =+B18+0.01 -> 1.02 | C19: =+C18+1 -> 5 | D19: Poste de C.A.C. de 8 m/300 daN (Incluye perilla) | G19: u | H19: 402.99 | J19: 79 | K19: =+ROUND($H19*J19,2) -> 31836.21 | L19: =+'[194]Metrado'!F13 -> 100 | M19: =+ROUND($H19*L19,2) -> 40299 | N19: 0 | O19: =+L19 -> 100 | P19: =+ROUND($N19*O19,2) -> 0 | Q19: =+N19/($H19+$I19) -> 0 | R19: =+(H19+I19)-N19 -> 402.99 | U19: 0 | V19: =+L19 -> 100 | W19: =+ROUND($U19*V19,2) -> 0 | X19: =+U19/($H19+$I19) -> 0 | Y19: 0 | Z19: =+V19 -> 100 | AA19: =+ROUND($Y19*Z19,2) -> 0 | AB19: =+Y19/($H19+$I19) -> 0 | AC19: 0 | AD19: =+Z19 -> 100 | AE19: =+ROUND($AC19*AD19,2) -> 0 | AF19: =+AC19/($H19+$I19) -> 0
C20: =+C19+1 -> 6 | F20: =+"SUB-TOTAL "&B17&": " -> SUB-TOTAL 1: | K20: =+SUM(K18:K19) -> 88784.34 | M20: =+SUM(M18:M19) -> 92780.61 | N20: 0 | O20: =+L20 -> 0 | P20: =+SUM(P18:P19) -> 0 | R20: =+(H20+I20)-N20 -> 0 | U20: 0 | V20: =+L20 -> 0 | W20: =+SUM(W18:W19) -> 0 | Y20: 0 | Z20: =+V20 -> 0 | AA20: =+SUM(AA18:AA19) -> 0 | AC20: 0 | AD20: =+Z20 -> 0 | AE20: =+SUM(AE18:AE19) -> 0
B21: =1+B17 -> 2 | C21: =+C20+1 -> 7 | D21: POSTES DE MADERA IMPORTADA | N21: 0 | O21: =+L21 -> 0 | R21: =+(H21+I21)-N21 -> 0 | U21: 0 | V21: =+L21 -> 0 | Y21: 0 | Z21: =+V21 -> 0 | AC21: 0 | AD21: =+Z21 -> 0
B22: =+B21+0.01 -> 2.01 | C22: =+C21+1 -> 8 | D22: Poste de madera importada (Pino Amarillo del Sur) de 8 m, Clase 7 | G22: u | H22: 805.66 | J22: 9 | K22: =+ROUND($H22*J22,2) -> 7250.94 | L22: =+'[194]Metrado'!F16 -> 0 | M22: =+ROUND($H22*L22,2) -> 0 | N22: 0 | O22: =+L22 -> 0 | P22: =+ROUND($N22*O22,2) -> 0 | Q22: =+N22/($H22+$I22) -> 0 | R22: =+(H22+I22)-N22 -> 805.66 | U22: 0 | V22: =+L22 -> 0 | W22: =+ROUND($U22*V22,2) -> 0 | X22: =+U22/($H22+$I22) -> 0 | Y22: 0 | Z22: =+V22 -> 0 | AA22: =+ROUND($Y22*Z22,2) -> 0 | AB22: =+Y22/($H22+$I22) -> 0 | AC22: 0 | AD22: =+Z22 -> 0 | AE22: =+ROUND($AC22*AD22,2) -> 0 | AF22: =+AC22/($H22+$I22) -> 0
C23: =+C22+1 -> 9 | F23: =+"SUB-TOTAL "&B21&": " -> SUB-TOTAL 2: | K23: =+SUM(K22) -> 7250.94 | M23: =+SUM(M22) -> 0 | N23: 0 | O23: =+L23 -> 0 | P23: =+SUM(P22) -> 0 | R23: =+(H23+I23)-N23 -> 0 | U23: 0 | V23: =+L23 -> 0 | W23: =+SUM(W22) -> 0 | Y23: 0 | Z23: =+V23 -> 0 | AA23: =+SUM(AA22) -> 0 | AC23: 0 | AD23: =+Z23 -> 0 | AE23: =+SUM(AE22) -> 0
B24: 2.00A | C24: =+C23+1 -> 10 | D24: POSTES DE FIBRA DE VIDRIO | N24: 0 | O24: =+L24 -> 0 | R24: =+(H24+I24)-N24 -> 0 | U24: 0 | V24: =+L24 -> 0 | Y24: 0 | Z24: =+V24 -> 0 | AC24: 0 | AD24: =+Z24 -> 0
B25: 2.01A | C25: =+C24+1 -> 11 | D25: Postes en Poliéster Reforzado con Fibra de Vidrio (P.R.F.V) de 8m/200 (Incluye tapa) | G25: u | I25: 830.68 | K25: =+ROUND($H25*J25,2) -> 0 | L25: =+'[194]Metrado'!F19 -> 14 | M25: =+ROUND($I25*L25,2) -> 11629.52 | N25: 0 | O25: =+L25 -> 14 | P25: =+ROUND($N25*O25,2) -> 0 | Q25: =+N25/($H25+$I25) -> 0 | R25: =+(H25+I25)-N25 -> 830.68 | U25: 804.76 | V25: =+L25 -> 14 | W25: =+ROUND($U25*V25,2) -> 11266.64 | X25: =+U25/($H25+$I25) -> 0.96879665 | Y25: 804.76 | Z25: =+V25 -> 14 | AA25: =+ROUND($Y25*Z25,2) -> 11266.64 | AB25: =+Y25/($H25+$I25) -> 0.96879665 | AC25: 0 | AD25: =+Z25 -> 14 | AE25: =+ROUND($AC25*AD25,2) -> 0 | AF25: =+AC25/($H25+$I25) -> 0
B26: 2.02A | C26: =+C25+1 -> 12 | D26: Postes en Poliéster Reforzado con Fibra de Vidrio (P.R.F.V) de 8m/300 (Incluye tapa) | G26: u | I26: 921.22133 | K26: =+ROUND($H26*J26,2) -> 0 | L26: =+'[194]Metrado'!F20 -> 16 | M26: =+ROUND($I26*L26,2) -> 14739.54 | N26: 0 | O26: =+L26 -> 16 | P26: =+ROUND($N26*O26,2) -> 0 | Q26: =+N26/($H26+$I26) -> 0 | R26: =+(H26+I26)-N26 -> 921.22133 | U26: 929.49 | V26: =+L26 -> 16 | W26: =+ROUND($U26*V26,2) -> 14871.84 | X26: =+U26/($H26+$I26) -> 1.0089758 | Y26: 929.49 | Z26: =+V26 -> 16 | AA26: =+ROUND($Y26*Z26,2) -> 14871.84 | AB26: =+Y26/($H26+$I26) -> 1.0089758 | AC26: 0 | AD26: =+Z26 -> 16 | AE26: =+ROUND($AC26*AD26,2) -> 0 | AF26: =+AC26/($H26+$I26) -> 0
C27: =+C26+1 -> 13 | F27: =+"SUB-TOTAL "&B24&": " -> SUB-TOTAL 2.00A: | K27: =+SUM(K25:K26) -> 0 | M27: =+SUM(M25:M26) -> 26369.06 | N27: 0 | O27: =+L27 -> 0 | P27: =+SUM(P25:P26) -> 0 | R27: =+(H27+I27)-N27 -> 0 | U27: 0 | V27: =+L27 -> 0 | W27: =+SUM(W25:W26) -> 26138.48 | Y27: 0 | Z27: =+V27 -> 0 | AA27: =+SUM(AA25:AA26) -> 26138.48 | AC27: 0 | AD27: =+Z27 -> 0 | AE27: =+SUM(AE25:AE26) -> 0
B28: =+B21+1 -> 3 | C28: =+C27+1 -> 14 | D28: CABLES Y CONDUCTORES DE ALUMINIO | N28: 0 | O28: =+L28 -> 0 | R28: =+(H28+I28)-N28 -> 0 | U28: 0 | V28: =+L28 -> 0 | Y28: 0 | Z28: =+V28 -> 0 | AC28: 0 | AD28: =+Z28 -> 0
B29: =+B28+0.01 -> 3.01 | C29: =+C28+1 -> 15 | D29: Conductor Autoportante de Aluminio 2X25+16/25 mm² | G29: km | H29: 7749.03 | J29: 1.46 | K29: =+ROUND($H29*J29,2) -> 11313.58 | L29: =+'[194]Metrado'!F23 -> 0.53 | M29: =+ROUND($H29*L29,2) -> 4106.99 | N29: 4674.19 | O29: =+L29 -> 0.53 | P29: =+ROUND($N29*O29,2) -> 2477.32 | Q29: =+N29/($H29+$I29) -> 0.60319679 | R29: =+(H29+I29)-N29 -> 3074.84 | U29: 4400 | V29: =+L29 -> 0.53 | W29: =+ROUND($U29*V29,2) -> 2332 | X29: =+U29/($H29+$I29) -> 0.567813 | Y29: 4.40 | Z29: =+V29 -> 0.53 | AA29: =+ROUND($Y29*Z29,2) -> 2.33 | AB29: =+Y29/($H29+$I29) -> 0.000567813 | AC29: 0 | AD29: =+Z29 -> 0.53 | AE29: =+ROUND($AC29*AD29,2) -> 0 | AF29: =+AC29/($H29+$I29) -> 0
B30: =+B29+0.01 -> 3.02 | C30: =+C29+1 -> 16 | D30: Conductor Autoportante de Aluminio 2X16+16/25 mm² | G30: km | H30: 6431.99 | J30: 0.05 | K30: =+ROUND($H30*J30,2) -> 321.6 | L30: =+'[194]Metrado'!F24 -> 0 | M30: =+ROUND($H30*L30,2) -> 0 | N30: 4886.5 | O30: =+L30 -> 0 | P30: =+ROUND($N30*O30,2) -> 0 | Q30: =+N30/($H30+$I30) -> 0.75971822 | R30: =+(H30+I30)-N30 -> 1545.49 | U30: 0 | V30: =+L30 -> 0 | W30: =+ROUND($U30*V30,2) -> 0 | X30: =+U30/($H30+$I30) -> 0 | Y30: 0 | Z30: =+V30 -> 0 | AA30: =+ROUND($Y30*Z30,2) -> 0 | AB30: =+Y30/($H30+$I30) -> 0 | AC30: 0 | AD30: =+Z30 -> 0 | AE30: =+ROUND($AC30*AD30,2) -> 0 | AF30: =+AC30/($H30+$I30) -> 0
B31: =+B30+0.01 -> 3.03 | C31: =+C30+1 -> 17 | D31: Conductor Autoportante de Aluminio 2X25/25 mm² | G31: km | H31: 6248.95 | J31: 7.08 | K31: =+ROUND($H31*J31,2) -> 44242.57 | L31: =+'[194]Metrado'!F25 -> 3.61 | M31: =+ROUND($H31*L31,2) -> 22558.71 | N31: 3936.16 | O31: =+L31 -> 3.61 | P31: =+ROUND($N31*O31,2) -> 14209.54 | Q31: =+N31/($H31+$I31) -> 0.62989142 | R31: =+(H31+I31)-N31 -> 2312.79 | U31: 3590 | V31: =+L31 -> 3.61 | W31: =+ROUND($U31*V31,2) -> 12959.9 | X31: =+U31/($H31+$I31) -> 0.57449652 | Y31: 3.59 | Z31: =+V31 -> 3.61 | AA31: =+ROUND($Y31*Z31,2) -> 12.96 | AB31: =+Y31/($H31+$I31) -> 0.00057449652 | AC31: 0 | AD31: =+Z31 -> 3.61 | AE31: =+ROUND($AC31*AD31,2) -> 0 | AF31: =+AC31/($H31+$I31) -> 0
B32: =+B31+0.01 -> 3.04 | C32: =+C31+1 -> 18 | D32: Conductor Autoportante de Aluminio 1X16+16/25 mm² | G32: km | H32: 4940.38 | J32: 0.18 | K32: =+ROUND($H32*J32,2) -> 889.27 | L32: =+'[194]Metrado'!F26 -> 0 | M32: =+ROUND($H32*L32,2) -> 0 | N32: 2958.86 | O32: =+L32 -> 0 | P32: =+ROUND($N32*O32,2) -> 0 | Q32: =+N32/($H32+$I32) -> 0.59891344 | R32: =+(H32+I32)-N32 -> 1981.52 | U32: 0 | V32: =+L32 -> 0 | W32: =+ROUND($U32*V32,2) -> 0 | X32: =+U32/($H32+$I32) -> 0 | Y32: 0 | Z32: =+V32 -> 0 | AA32: =+ROUND($Y32*Z32,2) -> 0 | AB32: =+Y32/($H32+$I32) -> 0 | AC32: 0 | AD32: =+Z32 -> 0 | AE32: =+ROUND($AC32*AD32,2) -> 0 | AF32: =+AC32/($H32+$I32) -> 0
B33: =+B32+0.01 -> 3.05 | C33: =+C32+1 -> 19 | D33: Conductor Autoportante de Aluminio 1X16/25 mm² | G33: km | H33: 3440.29 | J33: 4.06 | K33: =+ROUND($H33*J33,2) -> 13967.58 | L33: =+'[194]Metrado'!F27 -> 0.06 | M33: =+ROUND($H33*L33,2) -> 206.42 | N33: 2352.26 | O33: =+L33 -> 0.06 | P33: =+ROUND($N33*O33,2) -> 141.14 | Q33: =+N33/($H33+$I33) -> 0.68373887 | R33: =+(H33+I33)-N33 -> 1088.03 | U33: 2270 | V33: =+L33 -> 0.06 | W33: =+ROUND($U33*V33,2) -> 136.2 | X33: =+U33/($H33+$I33) -> 0.6598281 | Y33: 2.27 | Z33: =+V33 -> 0.06 | AA33: =+ROUND($Y33*Z33,2) -> 0.14 | AB33: =+Y33/($H33+$I33) -> 0.0006598281 | AC33: 0 | AD33: =+Z33 -> 0.06 | AE33: =+ROUND($AC33*AD33,2) -> 0 | AF33: =+AC33/($H33+$I33) -> 0
B34: =+B33+0.01 -> 3.06 | C34: =+#REF!+1 -> #REF! | D34: Conductor Autoportante de Aluminio 2x35+16/NA25 mm² | G34: km | I34: 8623.15 | K34: =+ROUND($H34*J34,2) -> 0 | L34: =+'[194]Metrado'!F28 -> 0.44 | M34: =+ROUND($I34*L34,2) -> 3794.19 | O34: =+L34 -> 0.44 | P34: =+ROUND($N34*O34,2) -> 0 | Q34: =+N34/($H34+$I34) -> 0 | R34: =+(H34+I34)-N34 -> 8623.15 | U34: 5780 | V34: =+L34 -> 0.44 | W34: =+ROUND($U34*V34,2) -> 2543.2 | X34: =+U34/($H34+$I34) -> 0.6702887 | Y34: 5.78 | Z34: =+V34 -> 0.44 | AA34: =+ROUND($Y34*Z34,2) -> 2.54 | AB34: =+Y34/($H34+$I34) -> 0.0006702887 | AC34: 0 | AD34: =+Z34 -> 0.44 | AE34: =+ROUND($AC34*AD34,2) -> 0 | AF34: =+AC34/($H34+$I34) -> 0
B35: =+B34+0.01 -> 3.07 | C35: =+#REF!+1 -> #REF! | D35: Conductor Autoportante de Aluminio 2x25+16/NA25 mm² | G35: km | I35: 7908.7 | K35: =+ROUND($H35*J35,2) -> 0 | L35: =+'[194]Metrado'!F29 -> 4.31 | M35: =+ROUND($I35*L35,2) -> 34086.5 | O35: =+L35 -> 4.31 | P35: =+ROUND($N35*O35,2) -> 0 | Q35: =+N35/($H35+$I35) -> 0 | R35: =+(H35+I35)-N35 -> 7908.7 | U35: 0 | V35: =+L35 -> 4.31 | W35: =+ROUND($U35*V35,2) -> 0 | X35: =+U35/($H35+$I35) -> 0 | Y35: 0 | Z35: =+V35 -> 4.31 | AA35: =+ROUND($Y35*Z35,2) -> 0 | AB35: =+Y35/($H35+$I35) -> 0 | AC35: 0 | AD35: =+Z35 -> 4.31 | AE35: =+ROUND($AC35*AD35,2) -> 0 | AF35: =+AC35/($H35+$I35) -> 0
B36: =+B35+0.01 -> 3.08 | C36: =+C35+1 -> #REF! | D36: Conductor Autoportante de Aluminio 2x25/NA25 mm² | G36: km | I36: 6504.86 | K36: =+ROUND($H36*J36,2) -> 0 | L36: =+'[194]Metrado'!F30 -> 5.25 | M36: =+ROUND($I36*L36,2) -> 34150.52 | O36: =+L36 -> 5.25 | P36: =+ROUND($N36*O36,2) -> 0 | Q36: =+N36/($H36+$I36) -> 0 | R36: =+(H36+I36)-N36 -> 6504.86 | U36: 0 | V36: =+L36 -> 5.25 | W36: =+ROUND($U36*V36,2) -> 0 | X36: =+U36/($H36+$I36) -> 0 | Y36: 0 | Z36: =+V36 -> 5.25 | AA36: =+ROUND($Y36*Z36,2) -> 0 | AB36: =+Y36/($H36+$I36) -> 0 | AC36: 0 | AD36: =+Z36 -> 5.25 | AE36: =+ROUND($AC36*AD36,2) -> 0 | AF36: =+AC36/($H36+$I36) -> 0
C37: =+C36+1 -> #REF! | F37: =+"SUB-TOTAL "&B28&": " -> SUB-TOTAL 3: | K37: =+SUM(K29:K36) -> 70734.6 | M37: =+SUM(M29:M36) -> 98903.33 | N37: 0 | O37: =+L37 -> 0 | P37: =+SUM(P29:P36) -> 16828 | R37: =+(H37+I37)-N37 -> 0 | U37: 0 | V37: =+L37 -> 0 | W37: =+SUM(W29:W36) -> 17971.3 | Y37: 0 | Z37: =+V37 -> 0 | AA37: =+SUM(AA29:AA36) -> 17.97 | AC37: 0 | AD37: =+Z37 -> 0 | AE37: =+SUM(AE29:AE36) -> 0 | AG37: =+M37-W37 -> 80932.03
B38: =+B28+1 -> 4 | C38: =+C37+1 -> #REF! | D38: ACCESORIOS DE CABLES AUTOPORTANTES | N38: 0 | O38: =+L38 -> 0 | R38: =+(H38+I38)-N38 -> 0 | U38: 0 | V38: =+L38 -> 0 | Y38: 0 | Z38: =+V38 -> 0 | AC38: 0 | AD38: =+Z38 -> 0
B39: =+B38+0.01 -> 4.01 | C39: =+C38+1 -> #REF! | D39: Grapa de Suspensión Angular para Conductor de Aleacion de Aluminio de 25 mm2 | G39: u | H39: 12 | J39: 163 | K39: =+ROUND($H39*J39,2) -> 1956 | L39: =+'[194]Metrado'!F33 -> 182 | M39: =+ROUND($H39*L39,2) -> 2184 | N39: 6.38 | O39: =+L39 -> 182 | P39: =+ROUND($N39*O39,2) -> 1161.16 | Q39: =+N39/($H39+$I39) -> 0.53166667 | R39: =+(H39+I39)-N39 -> 5.62 | S39: SI | T39: NO | U39: 0 | V39: =+L39 -> 182 | W39: =+ROUND($U39*V39,2) -> 0 | X39: =+U39/($H39+$I39) -> 0 | Y39: 1.54 | Z39: =+V39 -> 182 | AA39: =+ROUND($Y39*Z39,2) -> 280.28 | AB39: =+Y39/($H39+$I39) -> 0.12833333 | AC39: 0 | AD39: =+Z39 -> 182 | AE39: =+ROUND($AC39*AD39,2) -> 0 | AF39: =+AC39/($H39+$I39) -> 0
B40: =+B39+0.01 -> 4.02 | C40: =+C39+1 -> #REF! | D40: Grapa de Anclaje Cónica para Conductor de Aleación de Aluminio de 25 mm2 | G40: u | H40: 16.87 | J40: 218 | K40: =+ROUND($H40*J40,2) -> 3677.66 | L40: =+'[194]Metrado'!F34 -> 287 | M40: =+ROUND($H40*L40,2) -> 4841.69 | N40: 12.92 | O40: =+L40 -> 287 | P40: =+ROUND($N40*O40,2) -> 3708.04 | Q40: =+N40/($H40+$I40) -> 0.76585655 | R40: =+(H40+I40)-N40 -> 3.95 | S40: SI | T40: NO | U40: 0 | V40: =+L40 -> 287 | W40: =+ROUND($U40*V40,2) -> 0 | X40: =+U40/($H40+$I40) -> 0 | Y40: 3.10 | Z40: =+V40 -> 287 | AA40: =+ROUND($Y40*Z40,2) -> 889.7 | AB40: =+Y40/($H40+$I40) -> 0.18375815 | AC40: 0 | AD40: =+Z40 -> 287 | AE40: =+ROUND($AC40*AD40,2) -> 0 | AF40: =+AC40/($H40+$I40) -> 0
B41: =+B40+0.01 -> 4.03 | C41: =+C40+1 -> #REF! | D41: Conector Bimetálico para Al 25 mm2 / Cu 4-10 mm2, para Neutro Desnudo, tipo Cuña | G41: u | H41: 5.21 | J41: 2 | K41: =+ROUND($H41*J41,2) -> 10.42 | L41: =+'[194]Metrado'!F35 -> 0 | M41: =+ROUND($H41*L41,2) -> 0 | N41: 0 | O41: =+L41 -> 0 | P41: =+ROUND($N41*O41,2) -> 0 | Q41: =+N41/($H41+$I41) -> 0 | R41: =+(H41+I41)-N41 -> 5.21 | U41: 0 | V41: =+L41 -> 0 | W41: =+ROUND($U41*V41,2) -> 0 | X41: =+U41/($H41+$I41) -> 0 | Y41: 0.70 | Z41: =+V41 -> 0 | AA41: =+ROUND($Y41*Z41,2) -> 0 | AB41: =+Y41/($H41+$I41) -> 0.13435701 | AC41: 7.2 | AD41: =+Z41 -> 0 | AE41: =+ROUND($AC41*AD41,2) -> 0 | AF41: =+AC41/($H41+$I41) -> 1.3819578
B42: =+B41+0.01 -> 4.04 | C42: =+C41+1 -> #REF! | D42: Conector Bimetalico Aislado, para Al 16-35 mm2 / Cu 4-10 mm2, para Fase Aislada, tipo Perforación | G42: u | H42: 7.04 | J42: 4 | K42: =+ROUND($H42*J42,2) -> 28.16 | L42: =+'[194]Metrado'!F36 -> 27 | M42: =+ROUND($H42*L42,2) -> 190.08 | N42: 5.2 | O42: =+L42 -> 27 | P42: =+ROUND($N42*O42,2) -> 140.4 | Q42: =+N42/($H42+$I42) -> 0.73863636 | R42: =+(H42+I42)-N42 -> 1.84 | S42: SI | T42: SI | U42: 0 | V42: =+L42 -> 27 | W42: =+ROUND($U42*V42,2) -> 0 | X42: =+U42/($H42+$I42) -> 0 | Y42: 1.54 | Z42: =+V42 -> 27 | AA42: =+ROUND($Y42*Z42,2) -> 41.58 | AB42: =+Y42/($H42+$I42) -> 0.21875 | AC42: 4.5 | AD42: =+Z42 -> 27 | AE42: =+ROUND($AC42*AD42,2) -> 121.5 | AF42: =+AC42/($H42+$I42) -> 0.63920455
B43: =+B42+0.01 -> 4.05 | C43: =+C42+1 -> #REF! | D43: Conector para Al 25 mm², para Neutro Desnudo, tipo Cuña | G43: u | H43: 9.06 | J43: 26 | K43: =+ROUND($H43*J43,2) -> 235.56 | L43: =+'[194]Metrado'!F37 -> 12 | M43: =+ROUND($H43*L43,2) -> 108.72 | N43: 7.6 | O43: =+L43 -> 12 | P43: =+ROUND($N43*O43,2) -> 91.2 | Q43: =+N43/($H43+$I43) -> 0.8388521 | R43: =+(H43+I43)-N43 -> 1.46 | S43: SI | T43: NO | U43: 0 | V43: =+L43 -> 12 | W43: =+ROUND($U43*V43,2) -> 0 | X43: =+U43/($H43+$I43) -> 0 | Y43: 1.19 | Z43: =+V43 -> 12 | AA43: =+ROUND($Y43*Z43,2) -> 14.28 | AB43: =+Y43/($H43+$I43) -> 0.13134658 | AC43: 6.7 | AD43: =+Z43 -> 12 | AE43: =+ROUND($AC43*AD43,2) -> 80.4 | AF43: =+AC43/($H43+$I43) -> 0.73951435
B44: =+B43+0.01 -> 4.06 | C44: =+C43+1 -> #REF! | D44: Conector Aislado para Al 16-35 mm2, para Fase Aislada, tipo Perforación | G44: u | H44: 10.95 | J44: 52 | K44: =+ROUND($H44*J44,2) -> 569.4 | L44: =+'[194]Metrado'!F38 -> 232 | M44: =+ROUND($H44*L44,2) -> 2540.4 | N44: 7.24 | O44: =+L44 -> 232 | P44: =+ROUND($N44*O44,2) -> 1679.68 | Q44: =+N44/($H44+$I44) -> 0.66118721 | R44: =+(H44+I44)-N44 -> 3.71 | S44: SI | T44: SI | U44: 0 | V44: =+L44 -> 232 | W44: =+ROUND($U44*V44,2) -> 0 | X44: =+U44/($H44+$I44) -> 0 | Y44: 1.07 | Z44: =+V44 -> 232 | AA44: =+ROUND($Y44*Z44,2) -> 248.24 | AB44: =+Y44/($H44+$I44) -> 0.097716895 | AC44: 0 | AD44: =+Z44 -> 232 | AE44: =+ROUND($AC44*AD44,2) -> 0 | AF44: =+AC44/($H44+$I44) -> 0
B45: =+B44+0.01 -> 4.07 | C45: =+C44+1 -> #REF! | D45: Correa Plástica de Amarre, color negro | G45: u | H45: 0.4 | J45: 1838 | K45: =+ROUND($H45*J45,2) -> 735.2 | L45: =+'[194]Metrado'!F39 -> 2278 | M45: =+ROUND($H45*L45,2) -> 911.2 | N45: 0.3 | O45: =+L45 -> 2278 | P45: =+ROUND($N45*O45,2) -> 683.4 | Q45: =+N45/($H45+$I45) -> 0.75 | R45: =+(H45+I45)-N45 -> 0.1 | U45: 0 | V45: =+L45 -> 2278 | W45: =+ROUND($U45*V45,2) -> 0 | X45: =+U45/($H45+$I45) -> 0 | Y45: 0.07 | Z45: =+V45 -> 2278 | AA45: =+ROUND($Y45*Z45,2) -> 159.46 | AB45: =+Y45/($H45+$I45) -> 0.175 | AC45: 0.12 | AD45: =+Z45 -> 2278 | AE45: =+ROUND($AC45*AD45,2) -> 273.36 | AF45: =+AC45/($H45+$I45) -> 0.3
B46: =+B45+0.01 -> 4.08 | C46: =+C45+1 -> #REF! | D46: Cinta Autofundente para extremo de cable | G46: m | H46: 4.46 | J46: 51.3 | K46: =+ROUND($H46*J46,2) -> 228.8 | L46: =+'[194]Metrado'!F40 -> 61 | M46: =+ROUND($H46*L46,2) -> 272.06 | N46: 0 | O46: =+L46 -> 61 | P46: =+ROUND($N46*O46,2) -> 0 | Q46: =+N46/($H46+$I46) -> 0 | R46: =+(H46+I46)-N46 -> 4.46 | U46: 0 | V46: =+L46 -> 61 | W46: =+ROUND($U46*V46,2) -> 0 | X46: =+U46/($H46+$I46) -> 0 | Y46: 6.31 | Z46: =+V46 -> 61 | AA46: =+ROUND($Y46*Z46,2) -> 384.91 | AB46: =+Y46/($H46+$I46) -> 1.4147982 | AC46: 3.1 | AD46: =+Z46 -> 61 | AE46: =+ROUND($AC46*AD46,2) -> 189.1 | AF46: =+AC46/($H46+$I46) -> 0.69506726
B47: =+B46+0.01 -> 4.09 | C47: =+C46+1 -> #REF! | D47: Cinta aislante | G47: m | H47: 1.53 | J47: 19 | K47: =+ROUND($H47*J47,2) -> 29.07 | L47: =+'[194]Metrado'!F41 -> 183 | M47: =+ROUND($H47*L47,2) -> 279.99 | N47: 0 | O47: =+L47 -> 183 | P47: =+ROUND($N47*O47,2) -> 0 | Q47: =+N47/($H47+$I47) -> 0 | R47: =+(H47+I47)-N47 -> 1.53 | U47: 0 | V47: =+L47 -> 183 | W47: =+ROUND($U47*V47,2) -> 0 | X47: =+U47/($H47+$I47) -> 0 | Y47: 1.45 | Z47: =+V47 -> 183 | AA47: =+ROUND($Y47*Z47,2) -> 265.35 | AB47: =+Y47/($H47+$I47) -> 0.94771242 | AC47: 0.27 | AD47: =+Z47 -> 183 | AE47: =+ROUND($AC47*AD47,2) -> 49.41 | AF47: =+AC47/($H47+$I47) -> 0.17647059
B48: =+B47+0.01 -> 4.1 | C48: =+C47+1 -> #REF! | D48: Grapa de Anclaje para Conductor de 25 mm² | G48: u | I48: 25.34 | K48: =+ROUND($H48*J48,2) -> 0 | L48: =+'[194]Metrado'!F42 -> 9 | M48: =+ROUND($I48*L48,2) -> 228.06 | N48: 17.33 | O48: =+L48 -> 9 | P48: =+ROUND($N48*O48,2) -> 155.97 | Q48: =+N48/($H48+$I48) -> 0.68389897 | R48: =+(H48+I48)-N48 -> 8.01 | S48: SI | T48: NO | U48: 0 | V48: =+L48 -> 9 | W48: =+ROUND($U48*V48,2) -> 0 | X48: =+U48/($H48+$I48) -> 0 | Y48: 4.56 | Z48: =+V48 -> 9 | AA48: =+ROUND($Y48*Z48,2) -> 41.04 | AB48: =+Y48/($H48+$I48) -> 0.17995264 | AC48: 0 | AD48: =+Z48 -> 9 | AE48: =+ROUND($AC48*AD48,2) -> 0 | AF48: =+AC48/($H48+$I48) -> 0
B49: =+B48+0.01 -> 4.11 | C49: =+C48+1 -> #REF! | D49: Cinta plana de armar 1.3 mm x 7.6 mm | G49: m | I49: 1 | K49: =+ROUND($H49*J49,2) -> 0 | L49: =+'[194]Metrado'!F43 -> 9 | M49: =+ROUND($I49*L49,2) -> 9 | N49: 1.06 | O49: =+L49 -> 9 | P49: =+ROUND($N49*O49,2) -> 9.54 | Q49: =+N49/($H49+$I49) -> 1.06 | R49: =+(H49+I49)-N49 -> -0.06 | S49: SI | T49: NO | U49: 0 | V49: =+L49 -> 9 | W49: =+ROUND($U49*V49,2) -> 0 | X49: =+U49/($H49+$I49) -> 0 | Y49: 0.24 | Z49: =+V49 -> 9 | AA49: =+ROUND($Y49*Z49,2) -> 2.16 | AB49: =+Y49/($H49+$I49) -> 0.24 | AC49: 0.98 | AD49: =+Z49 -> 9 | AE49: =+ROUND($AC49*AD49,2) -> 8.82 | AF49: =+AC49/($H49+$I49) -> 0.98
B50: =+B49+0.01 -> 4.12 | C50: =+C49+1 -> #REF! | D50: Grillete A°G° tipo Lira | G50: u | I50: 17.76 | K50: =+ROUND($H50*J50,2) -> 0 | L50: =+'[194]Metrado'!F44 -> 9 | M50: =+ROUND($I50*L50,2) -> 159.84 | N50: 10.64 | O50: =+L50 -> 9 | P50: =+ROUND($N50*O50,2) -> 95.76 | Q50: =+N50/($H50+$I50) -> 0.5990991 | R50: =+(H50+I50)-N50 -> 7.12 | S50: SI | T50: NO | U50: 0 | V50: =+L50 -> 9 | W50: =+ROUND($U50*V50,2) -> 0 | X50: =+U50/($H50+$I50) -> 0 | Y50: 2.33 | Z50: =+V50 -> 9 | AA50: =+ROUND($Y50*Z50,2) -> 20.97 | AB50: =+Y50/($H50+$I50) -> 0.13119369 | AC50: 8.2 | AD50: =+Z50 -> 9 | AE50: =+ROUND($AC50*AD50,2) -> 73.8 | AF50: =+AC50/($H50+$I50) -> 0.46171171
C51: =+C50+1 -> #REF! | F51: =+"SUB-TOTAL "&B38&": " -> SUB-TOTAL 4: | K51: =+SUM(K39:K50) -> 7470.27 | M51: =+SUM(M39:M50) -> 11725.04 | N51: 0 | O51: =+L51 -> 0 | P51: =+SUM(P39:P50) -> 7725.15 | R51: =+(H51+I51)-N51 -> 0 | U51: 0 | V51: =+L51 -> 0 | W51: =+SUM(W39:W50) -> 0 | Y51: 0 | Z51: =+V51 -> 0 | AA51: =+SUM(AA39:AA50) -> 2347.97 | AC51: 0 | AD51: =+Z51 -> 0 | AE51: =+SUM(AE39:AE50) -> 796.39
B52: =+B38+1 -> 5 | C52: =+C51+1 -> #REF! | D52: CABLES Y CONDUCTORES DE COBRE | N52: 0 | O52: =+L52 -> 0 | R52: =+(H52+I52)-N52 -> 0 | U52: 0 | V52: =+L52 -> 0 | Y52: 0 | Z52: =+V52 -> 0 | AC52: 0 | AD52: =+Z52 -> 0
B53: =+B52+0.01 -> 5.01 | C53: =+C52+1 -> #REF! | D53: Conductor de Cobre Recocido, tipo N2XY, Tripolar, 3 x 10 mm2, cubierta negra | G53: m | H53: 19.26 | J53: 1.2 | K53: =+ROUND($H53*J53,2) -> 23.11 | L53: =+'[194]Metrado'!F47 -> 18 | M53: =+ROUND($H53*L53,2) -> 346.68 | N53: 19.2 | O53: =+L53 -> 18 | P53: =+ROUND($N53*O53,2) -> 345.6 | Q53: =+N53/($H53+$I53) -> 0.99688474 | R53: =+(H53+I53)-N53 -> 0.06 | U53: 0 | V53: =+L53 -> 18 | W53: =+ROUND($U53*V53,2) -> 0 | X53: =+U53/($H53+$I53) -> 0 | Y53: 0 | Z53: =+V53 -> 18 | AA53: =+ROUND($Y53*Z53,2) -> 0 | AB53: =+Y53/($H53+$I53) -> 0 | AC53: 0 | AD53: =+Z53 -> 18 | AE53: =+ROUND($AC53*AD53,2) -> 0 | AF53: =+AC53/($H53+$I53) -> 0
B54: =+B53+0.01 -> 5.02 | C54: =+C53+1 -> #REF! | D54: Conductor de Cobre Recocido, tipo N2XY, Bipolar, 2 x 2,5 mm2 | G54: m | H54: 4.82 | J54: 111.5 | K54: =+ROUND($H54*J54,2) -> 537.43 | L54: =+'[194]Metrado'!F48 -> 160 | M54: =+ROUND($H54*L54,2) -> 771.2 | N54: 5.0213 | O54: =+L54 -> 160 | P54: =+ROUND($N54*O54,2) -> 803.41 | Q54: =+N54/($H54+$I54) -> 1.0417635 | R54: =+(H54+I54)-N54 -> -0.2013 | U54: 0 | V54: =+L54 -> 160 | W54: =+ROUND($U54*V54,2) -> 0 | X54: =+U54/($H54+$I54) -> 0 | Y54: 0 | Z54: =+V54 -> 160 | AA54: =+ROUND($Y54*Z54,2) -> 0 | AB54: =+Y54/($H54+$I54) -> 0 | AC54: 0 | AD54: =+Z54 -> 160 | AE54: =+ROUND($AC54*AD54,2) -> 0 | AF54: =+AC54/($H54+$I54) -> 0
B55: =+B54+0.01 -> 5.03 | C55: =+C54+1 -> #REF! | D55: Conductor de Cobre Concéntrico, 2 x 4 mm2, con aislamiento y cubierta de PVC | G55: m | H55: 4.8 | J55: 3985 | K55: =+ROUND($H55*J55,2) -> 19128 | L55: =+'[194]Metrado'!F49 -> 7465 | M55: =+ROUND($H55*L55,2) -> 35832 | N55: 4.1788 | O55: =+L55 -> 7465 | P55: =+ROUND($N55*O55,2) -> 31194.74 | Q55: =+N55/($H55+$I55) -> 0.87058333 | R55: =+(H55+I55)-N55 -> 0.6212 | U55: 0 | V55: =+L55 -> 7465 | W55: =+ROUND($U55*V55,2) -> 0 | X55: =+U55/($H55+$I55) -> 0 | Y55: 0 | Z55: =+V55 -> 7465 | AA55: =+ROUND($Y55*Z55,2) -> 0 | AB55: =+Y55/($H55+$I55) -> 0 | AC55: 0 | AD55: =+Z55 -> 7465 | AE55: =+ROUND($AC55*AD55,2) -> 0 | AF55: =+AC55/($H55+$I55) -> 0
B56: =+B55+0.01 -> 5.04 | C56: =+C55+1 -> #REF! | D56: Cable de Acero con Recubrimiento Metalúrgico de Cu de 4 AWG (21,15 mm²), para Puesta a Tierra | G56: m | H56: 12.8 | J56: 925.5 | K56: =+ROUND($H56*J56,2) -> 11846.4 | L56: =+'[194]Metrado'!F50 -> 912 | M56: =+ROUND($H56*L56,2) -> 11673.6 | N56: 6.2 | O56: =+L56 -> 912 | P56: =+ROUND($N56*O56,2) -> 5654.4 | Q56: =+N56/($H56+$I56) -> 0.484375 | R56: =+(H56+I56)-N56 -> 6.6 | S56: SI | T56: SI | U56: 0 | V56: =+L56 -> 912 | W56: =+ROUND($U56*V56,2) -> 0 | X56: =+U56/($H56+$I56) -> 0 | Y56: 0 | Z56: =+V56 -> 912 | AA56: =+ROUND($Y56*Z56,2) -> 0 | AB56: =+Y56/($H56+$I56) -> 0 | AC56: 0 | AD56: =+Z56 -> 912 | AE56: =+ROUND($AC56*AD56,2) -> 0 | AF56: =+AC56/($H56+$I56) -> 0
C57: =+C56+1 -> #REF! | F57: =+"SUB-TOTAL "&B52&": " -> SUB-TOTAL 5: | K57: =+SUM(K53:K56) -> 31534.94 | M57: =+SUM(M53:M56) -> 48623.48 | N57: 0 | O57: =+L57 -> 0 | P57: =+SUM(P53:P56) -> 37998.15 | R57: =+(H57+I57)-N57 -> 0 | U57: 0 | V57: =+L57 -> 0 | W57: =+SUM(W53:W56) -> 0 | Y57: 0 | Z57: =+V57 -> 0 | AA57: =+SUM(AA53:AA56) -> 0 | AC57: 0 | AD57: =+Z57 -> 0 | AE57: =+SUM(AE53:AE56) -> 0
B58: =+B52+1 -> 6 | C58: =+C57+1 -> #REF! | D58: LUMINARIAS, LAMPARAS Y ACCESORIOS | N58: 0 | O58: =+L58 -> 0 | R58: =+(H58+I58)-N58 -> 0 | U58: 0 | V58: =+L58 -> 0 | Y58: 0 | Z58: =+V58 -> 0 | AC58: 0 | AD58: =+Z58 -> 0
B59: =+B58+0.01 -> 6.01 | C59: =+C58+1 -> #REF! | D59: Pastoral tubo A°G° 38 mm Ø interior, 500 mm avance horizontal, 720 mm altura y 20° inclinación, provisto de 2 abrazaderas simples y 4 tirafondos para poste de madera | G59: u | H59: 55.07 | J59: 2 | K59: =+ROUND($H59*J59,2) -> 110.14 | L59: =+'[194]Metrado'!F53 -> 0 | M59: =+ROUND($H59*L59,2) -> 0 | N59: 0 | O59: =+L59 -> 0 | P59: =+ROUND($N59*O59,2) -> 0 | Q59: =+N59/($H59+$I59) -> 0 | R59: =+(H59+I59)-N59 -> 55.07 | U59: 0 | V59: =+L59 -> 0 | W59: =+ROUND($U59*V59,2) -> 0 | X59: =+U59/($H59+$I59) -> 0 | Y59: 0 | Z59: =+V59 -> 0 | AA59: =+ROUND($Y59*Z59,2) -> 0 | AB59: =+Y59/($H59+$I59) -> 0 | AC59: 0 | AD59: =+Z59 -> 0 | AE59: =+ROUND($AC59*AD59,2) -> 0 | AF59: =+AC59/($H59+$I59) -> 0
B60: =+B59+0.01 -> 6.02 | C60: =+C59+1 -> #REF! | D60: Pastoral tubo A°G° 38 mm Ø interior, 500 mm avance horizontal, 720 mm altura y 20° inclinación, provisto de 2 abrazaderas dobles para poste de concreto | G60: u | H60: 66.86 | J60: 43 | K60: =+ROUND($H60*J60,2) -> 2874.98 | L60: =+'[194]Metrado'!F54 -> 80 | M60: =+ROUND($H60*L60,2) -> 5348.8 | N60: 0 | O60: =+L60 -> 80 | P60: =+ROUND($N60*O60,2) -> 0 | Q60: =+N60/($H60+$I60) -> 0 | R60: =+(H60+I60)-N60 -> 66.86 | U60: 0 | V60: =+L60 -> 80 | W60: =+ROUND($U60*V60,2) -> 0 | X60: =+U60/($H60+$I60) -> 0 | Y60: 6.64 | Z60: =+V60 -> 80 | AA60: =+ROUND($Y60*Z60,2) -> 531.2 | AB60: =+Y60/($H60+$I60) -> 0.099311995 | AC60: 37 | AD60: =+Z60 -> 80 | AE60: =+ROUND($AC60*AD60,2) -> 2960 | AF60: =+AC60/($H60+$I60) -> 0.55339515
B61: =+B60+0.01 -> 6.03 | C61: =+C60+1 -> #REF! | D61: Luminaria completa con equipo para Lámpara de Vapor de Sodio de 50 W | G61: u | H61: 251.32 | J61: 45 | K61: =+ROUND($H61*J61,2) -> 11309.4 | L61: =+'[194]Metrado'!F55 -> 0 | M61: =+ROUND($H61*L61,2) -> 0 | N61: 0 | O61: =+L61 -> 0 | P61: =+ROUND($N61*O61,2) -> 0 | Q61: =+N61/($H61+$I61) -> 0 | R61: =+(H61+I61)-N61 -> 251.32 | U61: 0 | V61: =+L61 -> 0 | W61: =+ROUND($U61*V61,2) -> 0 | X61: =+U61/($H61+$I61) -> 0 | Y61: 0 | Z61: =+V61 -> 0 | AA61: =+ROUND($Y61*Z61,2) -> 0 | AB61: =+Y61/($H61+$I61) -> 0 | AC61: 0 | AD61: =+Z61 -> 0 | AE61: =+ROUND($AC61*AD61,2) -> 0 | AF61: =+AC61/($H61+$I61) -> 0
B62: =+B61+0.01 -> 6.04 | C62: =+C61+1 -> #REF! | D62: Lámpara de Vapor de Sodio de Alta Presión de 50 W | G62: u | H62: 38.94 | J62: 45 | K62: =+ROUND($H62*J62,2) -> 1752.3 | L62: =+'[194]Metrado'!F56 -> 0 | M62: =+ROUND($H62*L62,2) -> 0 | N62: 0 | O62: =+L62 -> 0 | P62: =+ROUND($N62*O62,2) -> 0 | Q62: =+N62/($H62+$I62) -> 0 | R62: =+(H62+I62)-N62 -> 38.94 | U62: 0 | V62: =+L62 -> 0 | W62: =+ROUND($U62*V62,2) -> 0 | X62: =+U62/($H62+$I62) -> 0 | Y62: 0 | Z62: =+V62 -> 0 | AA62: =+ROUND($Y62*Z62,2) -> 0 | AB62: =+Y62/($H62+$I62) -> 0 | AC62: 0 | AD62: =+Z62 -> 0 | AE62: =+ROUND($AC62*AD62,2) -> 0 | AF62: =+AC62/($H62+$I62) -> 0
B63: =+B62+0.01 -> 6.05 | C63: =+C62+1 -> #REF! | D63: Portafusible Unipolar 220 V, de 5 A, provisto con fusible de 1 A | G63: u | H63: 3.31 | J63: 45 | K63: =+ROUND($H63*J63,2) -> 148.95 | L63: =+'[194]Metrado'!F57 -> 80 | M63: =+ROUND($H63*L63,2) -> 264.8 | N63: 3.89 | O63: =+L63 -> 80 | P63: =+ROUND($N63*O63,2) -> 311.2 | Q63: =+N63/($H63+$I63) -> 1.1752266 | R63: =+(H63+I63)-N63 -> -0.58 | S63: SI | T63: NO | U63: 0 | V63: =+L63 -> 80 | W63: =+ROUND($U63*V63,2) -> 0 | X63: =+U63/($H63+$I63) -> 0 | Y63: 0 | Z63: =+V63 -> 80 | AA63: =+ROUND($Y63*Z63,2) -> 0 | AB63: =+Y63/($H63+$I63) -> 0 | AC63: 4.4 | AD63: =+Z63 -> 80 | AE63: =+ROUND($AC63*AD63,2) -> 352 | AF63: =+AC63/($H63+$I63) -> 1.3293051
B64: =+B63+0.01 -> 6.06 | C64: =+C63+1 -> #REF! | D64: Conector Bimetalico Aislado, para Al 16-35 mm2 / Cu 4-10 mm2, para Fase Aislada, tipo Perforación | G64: u | H64: 7.04 | J64: 45 | K64: =+ROUND($H64*J64,2) -> 316.8 | L64: =+'[194]Metrado'!F58 -> 143 | M64: =+ROUND($H64*L64,2) -> 1006.72 | N64: 5.2 | O64: =+L64 -> 143 | P64: =+ROUND($N64*O64,2) -> 743.6 | Q64: =+N64/($H64+$I64) -> 0.73863636 | R64: =+(H64+I64)-N64 -> 1.84 | S64: SI | T64: SI | U64: 0 | V64: =+L64 -> 143 | W64: =+ROUND($U64*V64,2) -> 0 | X64: =+U64/($H64+$I64) -> 0 | Y64: 1.54 | Z64: =+V64 -> 143 | AA64: =+ROUND($Y64*Z64,2) -> 220.22 | AB64: =+Y64/($H64+$I64) -> 0.21875 | AC64: 4.5 | AD64: =+Z64 -> 143 | AE64: =+ROUND($AC64*AD64,2) -> 643.5 | AF64: =+AC64/($H64+$I64) -> 0.63920455
B65: =+B64+0.01 -> 6.07 | C65: =+C64+1 -> #REF! | D65: Conector Bimetálico para Al 25 mm2 / Cu 4-10 mm2, para Neutro Desnudo, tipo Cuña | G65: u | H65: 5.21 | J65: 45 | K65: =+ROUND($H65*J65,2) -> 234.45 | L65: =+'[194]Metrado'!F59 -> 17 | M65: =+ROUND($H65*L65,2) -> 88.57 | N65: 0 | O65: =+L65 -> 17 | P65: =+ROUND($N65*O65,2) -> 0 | Q65: =+N65/($H65+$I65) -> 0 | R65: =+(H65+I65)-N65 -> 5.21 | U65: 0 | V65: =+L65 -> 17 | W65: =+ROUND($U65*V65,2) -> 0 | X65: =+U65/($H65+$I65) -> 0 | Y65: 0.70 | Z65: =+V65 -> 17 | AA65: =+ROUND($Y65*Z65,2) -> 11.9 | AB65: =+Y65/($H65+$I65) -> 0.13435701 | AC65: 7.2 | AD65: =+Z65 -> 17 | AE65: =+ROUND($AC65*AD65,2) -> 122.4 | AF65: =+AC65/($H65+$I65) -> 1.3819578
B66: =+B65+0.01 -> 6.08 | C66: =+C65+1 -> #REF! | D66: Luminaria para alumbrado público con tecnología LED de 50W a 55W (incluye accesorios de encendido y protección) | G66: u | I66: 386.46 | K66: =+ROUND($H66*J66,2) -> 0 | L66: =+'[194]Metrado'!F60 -> 80 | M66: =+ROUND($I66*L66,2) -> 30916.8 | N66: 0 | O66: =+L66 -> 80 | P66: =+ROUND($N66*O66,2) -> 0 | Q66: =+N66/($H66+$I66) -> 0 | R66: =+(H66+I66)-N66 -> 386.46 | U66: 0 | V66: =+L66 -> 80 | W66: =+ROUND($U66*V66,2) -> 0 | X66: =+U66/($H66+$I66) -> 0 | Y66: 0 | Z66: =+V66 -> 80 | AA66: =+ROUND($Y66*Z66,2) -> 0 | AB66: =+Y66/($H66+$I66) -> 0 | AC66: 238 | AD66: =+Z66 -> 80 | AE66: =+ROUND($AC66*AD66,2) -> 19040 | AF66: =+AC66/($H66+$I66) -> 0.6158464
C67: =+C66+1 -> #REF! | F67: =+"SUB-TOTAL "&B58&": " -> SUB-TOTAL 6: | K67: =+SUM(K59:K66) -> 16747.02 | M67: =+SUM(M59:M66) -> 37625.69 | N67: 0 | O67: =+L67 -> 0 | P67: =+SUM(P59:P66) -> 1054.8 | R67: =+(H67+I67)-N67 -> 0 | U67: 0 | V67: =+L67 -> 0 | W67: =+SUM(W59:W66) -> 0 | Y67: 0 | Z67: =+V67 -> 0 | AA67: =+SUM(AA59:AA66) -> 763.32 | AC67: 0 | AD67: =+Z67 -> 0 | AE67: =+SUM(AE59:AE66) -> 23117.9
B68: =+B58+1 -> 7 | C68: =+C67+1 -> #REF! | D68: RETENIDAS Y ANCLAJES | N68: 0 | O68: =+L68 -> 0 | R68: =+(H68+I68)-N68 -> 0 | U68: 0 | V68: =+L68 -> 0 | Y68: 0 | Z68: =+V68 -> 0 | AC68: 0 | AD68: =+Z68 -> 0
B69: =+B68+0.01 -> 7.01 | C69: =+C68+1 -> #REF! | D69: Cable de acero grado Siemens Martin, de 10 mm ø, 7 hilos | G69: m | H69: 4.31 | J69: 1076 | K69: =+ROUND($H69*J69,2) -> 4637.56 | L69: =+'[194]Metrado'!F63 -> 0 | M69: =+ROUND($H69*L69,2) -> 0 | N69: 0 | O69: =+L69 -> 0 | P69: =+ROUND($N69*O69,2) -> 0 | Q69: =+N69/($H69+$I69) -> 0 | R69: =+(H69+I69)-N69 -> 4.31 | U69: 0 | V69: =+L69 -> 0 | W69: =+ROUND($U69*V69,2) -> 0 | X69: =+U69/($H69+$I69) -> 0 | Y69: 0 | Z69: =+V69 -> 0 | AA69: =+ROUND($Y69*Z69,2) -> 0 | AB69: =+Y69/($H69+$I69) -> 0 | AC69: 3.1 | AD69: =+Z69 -> 0 | AE69: =+ROUND($AC69*AD69,2) -> 0 | AF69: =+AC69/($H69+$I69) -> 0.71925754
B70: =+B69+0.01 -> 7.02 | C70: =+C69+1 -> #REF! | D70: Perno Angular con Ojal Guardacabo de A°G°, 16 mm Ø x 254 mm, provisto de Tuerca y Contratuerca | G70: u | H70: 13.17 | J70: 106 | K70: =+ROUND($H70*J70,2) -> 1396.02 | L70: =+'[194]Metrado'!F64 -> 117 | M70: =+ROUND($H70*L70,2) -> 1540.89 | N70: 7.81 | O70: =+L70 -> 117 | P70: =+ROUND($N70*O70,2) -> 913.77 | Q70: =+N70/($H70+$I70) -> 0.59301443 | R70: =+(H70+I70)-N70 -> 5.36 | S70: SI | T70: SI | U70: 0 | V70: =+L70 -> 117 | W70: =+ROUND($U70*V70,2) -> 0 | X70: =+U70/($H70+$I70) -> 0 | Y70: 2.37 | Z70: =+V70 -> 117 | AA70: =+ROUND($Y70*Z70,2) -> 277.29 | AB70: =+Y70/($H70+$I70) -> 0.17995444 | AC70: 6.1 | AD70: =+Z70 -> 117 | AE70: =+ROUND($AC70*AD70,2) -> 713.7 | AF70: =+AC70/($H70+$I70) -> 0.46317388
B71: =+B70+0.01 -> 7.03 | C71: =+C70+1 -> #REF! | D71: Perno Angular con Ojal Guardacabo de A°G°, 16 mm Ø x 305 mm, provisto de Tuerca y Contratuerca | G71: u | H71: 14.23 | J71: 3 | K71: =+ROUND($H71*J71,2) -> 42.69 | L71: =+'[194]Metrado'!F65 -> 3 | M71: =+ROUND($H71*L71,2) -> 42.69 | N71: 7.9 | O71: =+L71 -> 3 | P71: =+ROUND($N71*O71,2) -> 23.7 | Q71: =+N71/($H71+$I71) -> 0.55516514 | R71: =+(H71+I71)-N71 -> 6.33 | S71: SI | T71: SI | U71: 0 | V71: =+L71 -> 3 | W71: =+ROUND($U71*V71,2) -> 0 | X71: =+U71/($H71+$I71) -> 0 | Y71: 2.52 | Z71: =+V71 -> 3 | AA71: =+ROUND($Y71*Z71,2) -> 7.56 | AB71: =+Y71/($H71+$I71) -> 0.17709065 | AC71: 7.6 | AD71: =+Z71 -> 3 | AE71: =+ROUND($AC71*AD71,2) -> 22.8 | AF71: =+AC71/($H71+$I71) -> 0.53408292
B72: =+B71+0.01 -> 7.04 | C72: =+C71+1 -> #REF! | D72: Varilla de Anclaje de A°G° de 16 mm Ø x 2,40 m, provisto de Ojal Guardacabo en un extremo; Tuerca y Contratuerca en el otro | G72: u | H72: 46.85 | J72: 109 | K72: =+ROUND($H72*J72,2) -> 5106.65 | L72: =+'[194]Metrado'!F66 -> 120 | M72: =+ROUND($H72*L72,2) -> 5622 | N72: 34.96 | O72: =+L72 -> 120 | P72: =+ROUND($N72*O72,2) -> 4195.2 | Q72: =+N72/($H72+$I72) -> 0.74621131 | R72: =+(H72+I72)-N72 -> 11.89 | S72: SI | T72: SI | U72: 0 | V72: =+L72 -> 120 | W72: =+ROUND($U72*V72,2) -> 0 | X72: =+U72/($H72+$I72) -> 0 | Y72: 9.51 | Z72: =+V72 -> 120 | AA72: =+ROUND($Y72*Z72,2) -> 1141.2 | AB72: =+Y72/($H72+$I72) -> 0.20298826 | AC72: 27.5 | AD72: =+Z72 -> 120 | AE72: =+ROUND($AC72*AD72,2) -> 3300 | AF72: =+AC72/($H72+$I72) -> 0.58697972
B73: =+B72+0.01 -> 7.05 | C73: =+C72+1 -> #REF! | D73: Arandela de Anclaje de A°G°, 102 x 102 x 6,35 mm, Agujero de 18 mmø | G73: u | H73: 5.46 | J73: 109 | K73: =+ROUND($H73*J73,2) -> 595.14 | L73: =+'[194]Metrado'!F67 -> 120 | M73: =+ROUND($H73*L73,2) -> 655.2 | N73: 4.56 | O73: =+L73 -> 120 | P73: =+ROUND($N73*O73,2) -> 547.2 | Q73: =+N73/($H73+$I73) -> 0.83516484 | R73: =+(H73+I73)-N73 -> 0.9 | S73: SI | T73: SI | U73: 0 | V73: =+L73 -> 120 | W73: =+ROUND($U73*V73,2) -> 0 | X73: =+U73/($H73+$I73) -> 0 | Y73: 1.31 | Z73: =+V73 -> 120 | AA73: =+ROUND($Y73*Z73,2) -> 157.2 | AB73: =+Y73/($H73+$I73) -> 0.23992674 | AC73: 5.5 | AD73: =+Z73 -> 120 | AE73: =+ROUND($AC73*AD73,2) -> 660 | AF73: =+AC73/($H73+$I73) -> 1.007326
B74: =+B73+0.01 -> 7.06 | C74: =+C73+1 -> #REF! | D74: Mordaza Preformada de A°G° para Cable de 10 mm Ø | G74: u | H74: 11.69 | J74: 218 | K74: =+ROUND($H74*J74,2) -> 2548.42 | L74: =+'[194]Metrado'!F68 -> 240 | M74: =+ROUND($H74*L74,2) -> 2805.6 | N74: 8.5 | O74: =+L74 -> 240 | P74: =+ROUND($N74*O74,2) -> 2040 | Q74: =+N74/($H74+$I74) -> 0.72711719 | R74: =+(H74+I74)-N74 -> 3.19 | S74: SI | T74: NO | U74: 0 | V74: =+L74 -> 240 | W74: =+ROUND($U74*V74,2) -> 0 | X74: =+U74/($H74+$I74) -> 0 | Y74: 2.13 | Z74: =+V74 -> 240 | AA74: =+ROUND($Y74*Z74,2) -> 511.2 | AB74: =+Y74/($H74+$I74) -> 0.18220701 | AC74: 7.5 | AD74: =+Z74 -> 240 | AE74: =+ROUND($AC74*AD74,2) -> 1800 | AF74: =+AC74/($H74+$I74) -> 0.64157399
B75: =+B74+0.01 -> 7.07 | C75: =+C74+1 -> #REF! | D75: Arandela Cuadrada Curva de A° G°, 57 x 57 x 5 mm, Agujero de 18 mm Ø | G75: u | H75: 1.67 | J75: 218 | K75: =+ROUND($H75*J75,2) -> 364.06 | L75: =+'[194]Metrado'!F69 -> 240 | M75: =+ROUND($H75*L75,2) -> 400.8 | N75: 1.22 | O75: =+L75 -> 240 | P75: =+ROUND($N75*O75,2) -> 292.8 | Q75: =+N75/($H75+$I75) -> 0.73053892 | R75: =+(H75+I75)-N75 -> 0.45 | S75: SI | T75: SI | U75: 0 | V75: =+L75 -> 240 | W75: =+ROUND($U75*V75,2) -> 0 | X75: =+U75/($H75+$I75) -> 0 | Y75: 0.31 | Z75: =+V75 -> 240 | AA75: =+ROUND($Y75*Z75,2) -> 74.4 | AB75: =+Y75/($H75+$I75) -> 0.18562874 | AC75: 1.5 | AD75: =+Z75 -> 240 | AE75: =+ROUND($AC75*AD75,2) -> 360 | AF75: =+AC75/($H75+$I75) -> 0.89820359
B76: =+B75+0.01 -> 7.08 | C76: =+C75+1 -> #REF! | D76: Soporte de Contrapunta de 51 mm ø x 1000 mm de longitud, con Abrazadera partida en un extremo y Grapa de Ajuste para Cable en el otro | G76: u | H76: 105.33 | J76: 14 | K76: =+ROUND($H76*J76,2) -> 1474.62 | L76: =+'[194]Metrado'!F70 -> 27 | M76: =+ROUND($H76*L76,2) -> 2843.91 | N76: 79 | O76: =+L76 -> 27 | P76: =+ROUND($N76*O76,2) -> 2133 | Q76: =+N76/($H76+$I76) -> 0.75002373 | R76: =+(H76+I76)-N76 -> 26.33 | S76: SI | T76: NO | U76: 0 | V76: =+L76 -> 27 | W76: =+ROUND($U76*V76,2) -> 0 | X76: =+U76/($H76+$I76) -> 0 | Y76: 20.18 | Z76: =+V76 -> 27 | AA76: =+ROUND($Y76*Z76,2) -> 544.86 | AB76: =+Y76/($H76+$I76) -> 0.19158834 | AC76: 73 | AD76: =+Z76 -> 27 | AE76: =+ROUND($AC76*AD76,2) -> 1971 | AF76: =+AC76/($H76+$I76) -> 0.69305991
B77: =+B76+0.01 -> 7.09 | C77: =+C76+1 -> #REF! | D77: Alambre de Acero N° 12 para Entorchado | G77: m | H77: 0.69 | J77: 327 | K77: =+ROUND($H77*J77,2) -> 225.63 | L77: =+'[194]Metrado'!F71 -> 360 | M77: =+ROUND($H77*L77,2) -> 248.4 | N77: 0.43 | O77: =+L77 -> 360 | P77: =+ROUND($N77*O77,2) -> 154.8 | Q77: =+N77/($H77+$I77) -> 0.62318841 | R77: =+(H77+I77)-N77 -> 0.26 | S77: SI | T77: NO | U77: 0 | V77: =+L77 -> 360 | W77: =+ROUND($U77*V77,2) -> 0 | X77: =+U77/($H77+$I77) -> 0 | Y77: 0.10 | Z77: =+V77 -> 360 | AA77: =+ROUND($Y77*Z77,2) -> 36 | AB77: =+Y77/($H77+$I77) -> 0.14492754 | AC77: 0.6 | AD77: =+Z77 -> 360 | AE77: =+ROUND($AC77*AD77,2) -> 216 | AF77: =+AC77/($H77+$I77) -> 0.86956522
B78: =+B77+0.01 -> 7.1 | C78: =+C77+1 -> #REF! | D78: Bloque de concreto de 0,40 x 0,40 x 0,15 m | G78: u | H78: 40.94 | J78: 109 | K78: =+ROUND($H78*J78,2) -> 4462.46 | L78: =+'[194]Metrado'!F72 -> 120 | M78: =+ROUND($H78*L78,2) -> 4912.8 | N78: 0 | O78: =+L78 -> 120 | P78: =+ROUND($N78*O78,2) -> 0 | Q78: =+N78/($H78+$I78) -> 0 | R78: =+(H78+I78)-N78 -> 40.94 | U78: 0 | V78: =+L78 -> 120 | W78: =+ROUND($U78*V78,2) -> 0 | X78: =+U78/($H78+$I78) -> 0 | Y78: 0 | Z78: =+V78 -> 120 | AA78: =+ROUND($Y78*Z78,2) -> 0 | AB78: =+Y78/($H78+$I78) -> 0 | AC78: 0 | AD78: =+Z78 -> 120 | AE78: =+ROUND($AC78*AD78,2) -> 0 | AF78: =+AC78/($H78+$I78) -> 0
B79: =+B78+0.01 -> 7.11 | C79: =+C78+1 -> #REF! | D79: Conector Bimetálico para Al 25 mm2 / Cu 4-10 mm2, para Neutro Desnudo, tipo Cuña | G79: u | H79: 5.21 | J79: 109 | K79: =+ROUND($H79*J79,2) -> 567.89 | L79: =+'[194]Metrado'!F73 -> 120 | M79: =+ROUND($H79*L79,2) -> 625.2 | N79: 0 | O79: =+L79 -> 120 | P79: =+ROUND($N79*O79,2) -> 0 | Q79: =+N79/($H79+$I79) -> 0 | R79: =+(H79+I79)-N79 -> 5.21 | U79: 0 | V79: =+L79 -> 120 | W79: =+ROUND($U79*V79,2) -> 0 | X79: =+U79/($H79+$I79) -> 0 | Y79: 0.70 | Z79: =+V79 -> 120 | AA79: =+ROUND($Y79*Z79,2) -> 84 | AB79: =+Y79/($H79+$I79) -> 0.13435701 | AC79: 7.2 | AD79: =+Z79 -> 120 | AE79: =+ROUND($AC79*AD79,2) -> 864 | AF79: =+AC79/($H79+$I79) -> 1.3819578
B80: =+B79+0.01 -> 7.12 | C80: =+C79+1 -> #REF! | D80: Conector Doble Via Bimetálico para Cable de Acero de 10 mm ø y para Cable de Acero con Recubrimiento Metalúrgico de Cobre de 4 AWG (21,15 mm2) | G80: u | H80: 8.52 | J80: 109 | K80: =+ROUND($H80*J80,2) -> 928.68 | L80: =+'[194]Metrado'!F74 -> 120 | M80: =+ROUND($H80*L80,2) -> 1022.4 | N80: 5.02 | O80: =+L80 -> 120 | P80: =+ROUND($N80*O80,2) -> 602.4 | Q80: =+N80/($H80+$I80) -> 0.58920188 | R80: =+(H80+I80)-N80 -> 3.5 | S80: NO | T80: SI | U80: 0 | V80: =+L80 -> 120 | W80: =+ROUND($U80*V80,2) -> 0 | X80: =+U80/($H80+$I80) -> 0 | Y80: 1.36 | Z80: =+V80 -> 120 | AA80: =+ROUND($Y80*Z80,2) -> 163.2 | AB80: =+Y80/($H80+$I80) -> 0.15962441 | AC80: 5.5 | AD80: =+Z80 -> 120 | AE80: =+ROUND($AC80*AD80,2) -> 660 | AF80: =+AC80/($H80+$I80) -> 0.64553991
B81: =+B80+0.01 -> 7.13 | C81: =+C80+1 -> #REF! | D81: Cable de acero grado Alta Resistencia (HS), de 10 mm ø, 7 hilos | G81: m | I81: =+H69 -> 4.31 | K81: =+ROUND($H81*J81,2) -> 0 | L81: =+'[194]Metrado'!F75 -> 1173 | M81: =+ROUND($I81*L81,2) -> 5055.63 | N81: 2.8 | O81: =+L81 -> 1173 | P81: =+ROUND($N81*O81,2) -> 3284.4 | Q81: =+N81/($H81+$I81) -> 0.64965197 | R81: =+(H81+I81)-N81 -> 1.51 | S81: SI | T81: SI | U81: 0 | V81: =+L81 -> 1173 | W81: =+ROUND($U81*V81,2) -> 0 | X81: =+U81/($H81+$I81) -> 0 | Y81: 0.79 | Z81: =+V81 -> 1173 | AA81: =+ROUND($Y81*Z81,2) -> 926.67 | AB81: =+Y81/($H81+$I81) -> 0.18329466 | AC81: 0 | AD81: =+Z81 -> 1173 | AE81: =+ROUND($AC81*AD81,2) -> 0 | AF81: =+AC81/($H81+$I81) -> 0
B82: =+B81+0.01 -> 7.14 | C82: =+C81+1 -> #REF! | D82: Guardacabo de AºGº para cable de 10mm ø | G82: u | K82: =+ROUND($H82*J82,2) -> 0 | L82: 0 | M82: =+ROUND($I82*L82,2) -> 0 | N82: 0 | O82: =+L82 -> 0 | P82: =+ROUND($N82*O82,2) -> 0 | R82: =+(H82+I82)-N82 -> 0 | U82: 0 | V82: =+L82 -> 0 | W82: =+ROUND($U82*V82,2) -> 0 | Y82: 0 | Z82: =+V82 -> 0 | AA82: =+ROUND($Y82*Z82,2) -> 0 | AC82: 0 | AD82: =+Z82 -> 0 | AE82: =+ROUND($AC82*AD82,2) -> 0
C83: =+C82+1 -> #REF! | F83: =+"SUB-TOTAL "&B68&": " -> SUB-TOTAL 7: | K83: =+SUM(K69:K82) -> 22349.82 | M83: =+SUM(M69:M82) -> 25775.52 | N83: 0 | O83: =+L83 -> 0 | P83: =+SUM(P69:P82) -> 14187.27 | R83: =+(H83+I83)-N83 -> 0 | U83: 0 | V83: =+L83 -> 0 | W83: =+SUM(W69:W82) -> 0 | Y83: 0 | Z83: =+V83 -> 0 | AA83: =+SUM(AA69:AA82) -> 3923.58 | AC83: 0 | AD83: =+Z83 -> 0 | AE83: =+SUM(AE69:AE82) -> 10567.5
B84: =+B68+1 -> 8 | C84: =+C83+1 -> #REF! | D84: ACCESORIOS DE FERRETERIA PARA ESTRUCTURAS | N84: 0 | O84: =+L84 -> 0 | R84: =+(H84+I84)-N84 -> 0 | U84: 0 | V84: =+L84 -> 0 | Y84: 0 | Z84: =+V84 -> 0 | AC84: 0 | AD84: =+Z84 -> 0
B85: =+B84+0.01 -> 8.01 | C85: =+C84+1 -> #REF! | D85: Perno con Gancho de 16 mm Ø, provisto de Arandela, Tuerca y Contratuerca, longitud de 254 mm | G85: u | H85: 12.36 | J85: 141 | K85: =+ROUND($H85*J85,2) -> 1742.76 | L85: =+'[194]Metrado'!F79 -> 160 | M85: =+ROUND($H85*L85,2) -> 1977.6 | N85: 10.03 | O85: =+L85 -> 160 | P85: =+ROUND($N85*O85,2) -> 1604.8 | Q85: =+N85/($H85+$I85) -> 0.81148867 | R85: =+(H85+I85)-N85 -> 2.33 | S85: SI | T85: SI | U85: 0 | V85: =+L85 -> 160 | W85: =+ROUND($U85*V85,2) -> 0 | X85: =+U85/($H85+$I85) -> 0 | Y85: 2.85 | Z85: =+V85 -> 160 | AA85: =+ROUND($Y85*Z85,2) -> 456 | AB85: =+Y85/($H85+$I85) -> 0.23058252 | AC85: 7.7 | AD85: =+Z85 -> 160 | AE85: =+ROUND($AC85*AD85,2) -> 1232 | AF85: =+AC85/($H85+$I85) -> 0.62297735
B86: =+B85+0.01 -> 8.02 | C86: =+C85+1 -> #REF! | D86: Perno con Gancho de 16 mm Ø, provisto de Arandela, Tuerca y Contratuerca, longitud de 305 mm | G86: u | H86: 14.34 | J86: 22 | K86: =+ROUND($H86*J86,2) -> 315.48 | L86: =+'[194]Metrado'!F80 -> 22 | M86: =+ROUND($H86*L86,2) -> 315.48 | N86: 10.64 | O86: =+L86 -> 22 | P86: =+ROUND($N86*O86,2) -> 234.08 | Q86: =+N86/($H86+$I86) -> 0.74198047 | R86: =+(H86+I86)-N86 -> 3.7 | S86: SI | T86: SI | U86: 0 | V86: =+L86 -> 22 | W86: =+ROUND($U86*V86,2) -> 0 | X86: =+U86/($H86+$I86) -> 0 | Y86: 3.06 | Z86: =+V86 -> 22 | AA86: =+ROUND($Y86*Z86,2) -> 67.32 | AB86: =+Y86/($H86+$I86) -> 0.21338912 | AC86: 8.2 | AD86: =+Z86 -> 22 | AE86: =+ROUND($AC86*AD86,2) -> 180.4 | AF86: =+AC86/($H86+$I86) -> 0.57182706
B87: =+B86+0.01 -> 8.03 | C87: =+C86+1 -> #REF! | D87: Perno de A°G° de 13 mm Ø x 254 mm, provisto de Tuerca y Contratuerca | G87: u | H87: 5.57 | J87: 248 | K87: =+ROUND($H87*J87,2) -> 1381.36 | L87: =+'[194]Metrado'!F81 -> 126 | M87: =+ROUND($H87*L87,2) -> 701.82 | N87: 4.56 | O87: =+L87 -> 126 | P87: =+ROUND($N87*O87,2) -> 574.56 | Q87: =+N87/($H87+$I87) -> 0.81867145 | R87: =+(H87+I87)-N87 -> 1.01 | S87: SI | T87: SI | U87: 0 | V87: =+L87 -> 126 | W87: =+ROUND($U87*V87,2) -> 0 | X87: =+U87/($H87+$I87) -> 0 | Y87: 1.19 | Z87: =+V87 -> 126 | AA87: =+ROUND($Y87*Z87,2) -> 149.94 | AB87: =+Y87/($H87+$I87) -> 0.21364452 | AC87: 2.5 | AD87: =+Z87 -> 126 | AE87: =+ROUND($AC87*AD87,2) -> 315 | AF87: =+AC87/($H87+$I87) -> 0.44883303
B88: =+B87+0.01 -> 8.04 | C88: =+C87+1 -> #REF! | D88: Perno de A°G° de 13 mm Ø x 305 mm, provisto de Tuerca y Contratuerca | G88: u | H88: 6.25 | J88: 50 | K88: =+ROUND($H88*J88,2) -> 312.5 | L88: =+'[194]Metrado'!F82 -> 16 | M88: =+ROUND($H88*L88,2) -> 100 | N88: 6.38 | O88: =+L88 -> 16 | P88: =+ROUND($N88*O88,2) -> 102.08 | Q88: =+N88/($H88+$I88) -> 1.0208 | R88: =+(H88+I88)-N88 -> -0.13 | S88: SI | T88: SI | U88: 0 | V88: =+L88 -> 16 | W88: =+ROUND($U88*V88,2) -> 0 | X88: =+U88/($H88+$I88) -> 0 | Y88: 1.31 | Z88: =+V88 -> 16 | AA88: =+ROUND($Y88*Z88,2) -> 20.96 | AB88: =+Y88/($H88+$I88) -> 0.2096 | AC88: 2.74 | AD88: =+Z88 -> 16 | AE88: =+ROUND($AC88*AD88,2) -> 43.84 | AF88: =+AC88/($H88+$I88) -> 0.4384
B89: =+B88+0.01 -> 8.05 | C89: =+C88+1 -> #REF! | D89: Perno Ojo de A°G° de 16 mm Ø x 254 mm, provisto de Tuerca y Contratuerca | G89: u | H89: 13.11 | J89: 127 | K89: =+ROUND($H89*J89,2) -> 1664.97 | L89: =+'[194]Metrado'!F83 -> 158 | M89: =+ROUND($H89*L89,2) -> 2071.38 | N89: 8.36 | O89: =+L89 -> 158 | P89: =+ROUND($N89*O89,2) -> 1320.88 | Q89: =+N89/($H89+$I89) -> 0.63768116 | R89: =+(H89+I89)-N89 -> 4.75 | S89: SI | T89: SI | U89: 0 | V89: =+L89 -> 158 | W89: =+ROUND($U89*V89,2) -> 0 | X89: =+U89/($H89+$I89) -> 0 | Y89: 2.54 | Z89: =+V89 -> 158 | AA89: =+ROUND($Y89*Z89,2) -> 401.32 | AB89: =+Y89/($H89+$I89) -> 0.19374523 | AC89: 7 | AD89: =+Z89 -> 158 | AE89: =+ROUND($AC89*AD89,2) -> 1106 | AF89: =+AC89/($H89+$I89) -> 0.53394355
B90: =+B89+0.01 -> 8.06 | C90: =+C89+1 -> #REF! | D90: Perno Ojo de A°G° de 16 mm Ø x 305 mm, provisto de Tuerca y Contratuerca | G90: u | H90: 14.35 | J90: 33 | K90: =+ROUND($H90*J90,2) -> 473.55 | L90: =+'[194]Metrado'!F84 -> 38 | M90: =+ROUND($H90*L90,2) -> 545.3 | N90: 9.12 | O90: =+L90 -> 38 | P90: =+ROUND($N90*O90,2) -> 346.56 | Q90: =+N90/($H90+$I90) -> 0.63554007 | R90: =+(H90+I90)-N90 -> 5.23 | S90: SI | T90: SI | U90: 0 | V90: =+L90 -> 38 | W90: =+ROUND($U90*V90,2) -> 0 | X90: =+U90/($H90+$I90) -> 0 | Y90: 2.76 | Z90: =+V90 -> 38 | AA90: =+ROUND($Y90*Z90,2) -> 104.88 | AB90: =+Y90/($H90+$I90) -> 0.19233449 | AC90: 7.5 | AD90: =+Z90 -> 38 | AE90: =+ROUND($AC90*AD90,2) -> 285 | AF90: =+AC90/($H90+$I90) -> 0.52264808
B91: =+B90+0.01 -> 8.07 | C91: =+C90+1 -> #REF! | D91: Tuerca-Ojo para Perno de 16 mm Ø | G91: u | H91: 11.17 | J91: 58 | K91: =+ROUND($H91*J91,2) -> 647.86 | L91: =+'[194]Metrado'!F85 -> 100 | M91: =+ROUND($H91*L91,2) -> 1117 | N91: 8.69 | O91: =+L91 -> 100 | P91: =+ROUND($N91*O91,2) -> 869 | Q91: =+N91/($H91+$I91) -> 0.77797672 | R91: =+(H91+I91)-N91 -> 2.48 | S91: SI | T91: SI | U91: 0 | V91: =+L91 -> 100 | W91: =+ROUND($U91*V91,2) -> 0 | X91: =+U91/($H91+$I91) -> 0 | Y91: 1.84 | Z91: =+V91 -> 100 | AA91: =+ROUND($Y91*Z91,2) -> 184 | AB91: =+Y91/($H91+$I91) -> 0.16472695 | AC91: 5.4 | AD91: =+Z91 -> 100 | AE91: =+ROUND($AC91*AD91,2) -> 540 | AF91: =+AC91/($H91+$I91) -> 0.48343778
B92: =+B91+0.01 -> 8.08 | C92: =+C91+1 -> #REF! | D92: Fleje de acero inoxidable de 19 mm provisto de hebilla | G92: m | H92: 6.02 | J92: 2 | K92: =+ROUND($H92*J92,2) -> 12.04 | L92: =+'[194]Metrado'!F86 -> 9 | M92: =+ROUND($H92*L92,2) -> 54.18 | N92: 0 | O92: =+L92 -> 9 | P92: =+ROUND($N92*O92,2) -> 0 | Q92: =+N92/($H92+$I92) -> 0 | R92: =+(H92+I92)-N92 -> 6.02 | U92: 0 | V92: =+L92 -> 9 | W92: =+ROUND($U92*V92,2) -> 0 | X92: =+U92/($H92+$I92) -> 0 | Y92: 0.66 | Z92: =+V92 -> 9 | AA92: =+ROUND($Y92*Z92,2) -> 5.94 | AB92: =+Y92/($H92+$I92) -> 0.10963455 | AC92: 3.7 | AD92: =+Z92 -> 9 | AE92: =+ROUND($AC92*AD92,2) -> 33.3 | AF92: =+AC92/($H92+$I92) -> 0.61461794
B93: =+B92+0.01 -> 8.09 | C93: =+C92+1 -> #REF! | D93: Arandela Cuadrada Curva de A° G°, 57 x 57 x 5 mm, Agujero de 14 mm Ø | G93: u | H93: 1.63 | J93: 296 | K93: =+ROUND($H93*J93,2) -> 482.48 | L93: =+'[194]Metrado'!F87 -> 80 | M93: =+ROUND($H93*L93,2) -> 130.4 | N93: 1.58 | O93: =+L93 -> 80 | P93: =+ROUND($N93*O93,2) -> 126.4 | Q93: =+N93/($H93+$I93) -> 0.96932515 | R93: =+(H93+I93)-N93 -> 0.05 | S93: NO | T93: NO | U93: 0 | V93: =+L93 -> 80 | W93: =+ROUND($U93*V93,2) -> 0 | X93: =+U93/($H93+$I93) -> 0 | Y93: 0.31 | Z93: =+V93 -> 80 | AA93: =+ROUND($Y93*Z93,2) -> 24.8 | AB93: =+Y93/($H93+$I93) -> 0.19018405 | AC93: 0 | AD93: =+Z93 -> 80 | AE93: =+ROUND($AC93*AD93,2) -> 0 | AF93: =+AC93/($H93+$I93) -> 0
B94: =+B93+0.01 -> 8.1 | C94: =+C93+1 -> #REF! | D94: Arandela Cuadrada Curva de A° G°, 57 x 57 x 5 mm, Agujero de 18 mm Ø | G94: u | H94: 1.67 | J94: 483 | K94: =+ROUND($H94*J94,2) -> 806.61 | L94: =+'[194]Metrado'!F88 -> 580 | M94: =+ROUND($H94*L94,2) -> 968.6 | N94: 1.22 | O94: =+L94 -> 580 | P94: =+ROUND($N94*O94,2) -> 707.6 | Q94: =+N94/($H94+$I94) -> 0.73053892 | R94: =+(H94+I94)-N94 -> 0.45 | S94: SI | T94: SI | U94: 0 | V94: =+L94 -> 580 | W94: =+ROUND($U94*V94,2) -> 0 | X94: =+U94/($H94+$I94) -> 0 | Y94: 0.31 | Z94: =+V94 -> 580 | AA94: =+ROUND($Y94*Z94,2) -> 179.8 | AB94: =+Y94/($H94+$I94) -> 0.18562874 | AC94: 1.5 | AD94: =+Z94 -> 580 | AE94: =+ROUND($AC94*AD94,2) -> 870 | AF94: =+AC94/($H94+$I94) -> 0.89820359
B95: =+B94+0.01 -> 8.11 | C95: =+C94+1 -> #REF! | D95: Caja de derivacion para acometidas, sistema 440-22O V (10 borneras en cada barra de cobre) | G95: u | H95: 133.02 | J95: 2 | K95: =+ROUND($H95*J95,2) -> 266.04 | L95: =+'[194]Metrado'!F89 -> 9 | M95: =+ROUND($H95*L95,2) -> 1197.18 | N95: 117.04 | O95: =+L95 -> 9 | P95: =+ROUND($N95*O95,2) -> 1053.36 | Q95: =+N95/($H95+$I95) -> 0.87986769 | R95: =+(H95+I95)-N95 -> 15.98 | S95: SI | T95: NO | U95: 0 | V95: =+L95 -> 9 | W95: =+ROUND($U95*V95,2) -> 0 | X95: =+U95/($H95+$I95) -> 0 | Y95: 56.74 | Z95: =+V95 -> 9 | AA95: =+ROUND($Y95*Z95,2) -> 510.66 | AB95: =+Y95/($H95+$I95) -> 0.4265524 | AC95: 105 | AD95: =+Z95 -> 9 | AE95: =+ROUND($AC95*AD95,2) -> 945 | AF95: =+AC95/($H95+$I95) -> 0.78935498
B96: =+B95+0.01 -> 8.12 | C96: =+C95+1 -> #REF! | D96: Portalinea unipolar de AºGº, provisto de PIN de 10 mm Ø | G96: u | H96: 6.63 | J96: 300 | K96: =+ROUND($H96*J96,2) -> 1989 | L96: =+'[194]Metrado'!F90 -> 204 | M96: =+ROUND($H96*L96,2) -> 1352.52 | N96: 4.5 | O96: =+L96 -> 204 | P96: =+ROUND($N96*O96,2) -> 918 | Q96: =+N96/($H96+$I96) -> 0.67873303 | R96: =+(H96+I96)-N96 -> 2.13 | S96: SI | T96: SI | U96: 0 | V96: =+L96 -> 204 | W96: =+ROUND($U96*V96,2) -> 0 | X96: =+U96/($H96+$I96) -> 0 | Y96: 1.26 | Z96: =+V96 -> 204 | AA96: =+ROUND($Y96*Z96,2) -> 257.04 | AB96: =+Y96/($H96+$I96) -> 0.19004525 | AC96: 0 | AD96: =+Z96 -> 204 | AE96: =+ROUND($AC96*AD96,2) -> 0 | AF96: =+AC96/($H96+$I96) -> 0
